Workbook

Sheet Inputs
A1: Current Home Value | B1: 515000 | D1: Compare here
A2: Current Mortgage Balance | B2: 338000 | D2: Current payment | E2: =B5 -> 2313.8086
A3: Current Rate | B3: 0.0695 | D3: Refi payment | E3: =B14 -> 2038.2459
A4: Years Remaining | B4: 27 | D4: Monthly payment difference | E4: =B15 -> 275.56268
A5: Current Payment | B5: =PMT(B3/12,B4*12,-B2) -> 2313.8086 | D5: 10-year refi break-even | E5: ='Break-Even & Summary'!B13 -> >10 years
A6: Refi Rate | B6: 0.0585
A7: Refi Term (years) | B7: 30
A8: Refi Closing Costs | B8: 7500
A9: Extra Principal / Month | B9: 300
A10: Investment Return Assumption | B10: 0.07
A11: Home Appreciation | B11: 0.03
A12: Comparison Horizon (years) | B12: 10
A13: Refi Loan Amount | B13: =B2+B8 -> 345500
A14: Refi Payment | B14: =PMT(B6/12,B7*12,-B13) -> 2038.2459
A15: Monthly Payment Difference | B15: =B5-B14 -> 275.56268

Sheet Refi Case
A1: Year | B1: Remaining Balance | C1: Home Value | D1: Equity | E1: Annual Payment | F1: Cumulative Payments | G1: Approx interest | H1: Net worth est.
A2: 0 | B2: =MAX(0,Inputs!$B$13*(1+Inputs!$B$6/12)^(A2*12)-Inputs!$B$14*(((1+Inputs!$B$6/12)^(A2*12)-1)/(Inputs!$B$6/12))) -> 345500 | C2: =Inputs!$B$1*(1+Inputs!$B$11)^A2 -> 515000 | D2: =C2-B2 -> 169500 | E2: =Inputs!$B$14*12 -> 24458.951 | F2: =E2*A2 -> 0 | G2: =F2-((Inputs!$B$13-B2)) -> 0 | H2: =D2-Inputs!$B$8 -> 162000
A3: 1 | B3: =MAX(0,Inputs!$B$13*(1+Inputs!$B$6/12)^(A3*12)-Inputs!$B$14*(((1+Inputs!$B$6/12)^(A3*12)-1)/(Inputs!$B$6/12))) -> 341137.05 | C3: =Inputs!$B$1*(1+Inputs!$B$11)^A3 -> 530450 | D3: =C3-B3 -> 189312.95 | E3: =Inputs!$B$14*12 -> 24458.951 | F3: =E3*A3 -> 24458.951 | G3: =F3-((Inputs!$B$13-B3)) -> 20096.001 | H3: =D3-Inputs!$B$8 -> 181812.95
A4: 2 | B4: =MAX(0,Inputs!$B$13*(1+Inputs!$B$6/12)^(A4*12)-Inputs!$B$14*(((1+Inputs!$B$6/12)^(A4*12)-1)/(Inputs!$B$6/12))) -> 336511.91 | C4: =Inputs!$B$1*(1+Inputs!$B$11)^A4 -> 546363.5 | D4: =C4-B4 -> 209851.59 | E4: =Inputs!$B$14*12 -> 24458.951 | F4: =E4*A4 -> 48917.902 | G4: =F4-((Inputs!$B$13-B4)) -> 39929.813 | H4: =D4-Inputs!$B$8 -> 202351.59
A5: 3 | B5: =MAX(0,Inputs!$B$13*(1+Inputs!$B$6/12)^(A5*12)-Inputs!$B$14*(((1+Inputs!$B$6/12)^(A5*12)-1)/(Inputs!$B$6/12))) -> 331608.83 | C5: =Inputs!$B$1*(1+Inputs!$B$11)^A5 -> 562754.41 | D5: =C5-B5 -> 231145.58 | E5: =Inputs!$B$14*12 -> 24458.951 | F5: =E5*A5 -> 73376.853 | G5: =F5-((Inputs!$B$13-B5)) -> 59485.681 | H5: =D5-Inputs!$B$8 -> 223645.58
A6: 4 | B6: =MAX(0,Inputs!$B$13*(1+Inputs!$B$6/12)^(A6*12)-Inputs!$B$14*(((1+Inputs!$B$6/12)^(A6*12)-1)/(Inputs!$B$6/12))) -> 326411.1 | C6: =Inputs!$B$1*(1+Inputs!$B$11)^A6 -> 579637.04 | D6: =C6-B6 -> 253225.94 | E6: =Inputs!$B$14*12 -> 24458.951 | F6: =E6*A6 -> 97835.805 | G6: =F6-((Inputs!$B$13-B6)) -> 78746.902 | H6: =D6-Inputs!$B$8 -> 245725.94
A7: 5 | B7: =MAX(0,Inputs!$B$13*(1+Inputs!$B$6/12)^(A7*12)-Inputs!$B$14*(((1+Inputs!$B$6/12)^(A7*12)-1)/(Inputs!$B$6/12))) -> 320901.01 | C7: =Inputs!$B$1*(1+Inputs!$B$11)^A7 -> 597026.15 | D7: =C7-B7 -> 276125.14 | E7: =Inputs!$B$14*12 -> 24458.951 | F7: =E7*A7 -> 122294.76 | G7: =F7-((Inputs!$B$13-B7)) -> 97695.769 | H7: =D7-Inputs!$B$8 -> 268625.14
A8: 6 | B8: =MAX(0,Inputs!$B$13*(1+Inputs!$B$6/12)^(A8*12)-Inputs!$B$14*(((1+Inputs!$B$6/12)^(A8*12)-1)/(Inputs!$B$6/12))) -> 315059.8 | C8: =Inputs!$B$1*(1+Inputs!$B$11)^A8 -> 614936.93 | D8: =C8-B8 -> 299877.13 | E8: =Inputs!$B$14*12 -> 24458.951 | F8: =E8*A8 -> 146753.71 | G8: =F8-((Inputs!$B$13-B8)) -> 116313.51 | H8: =D8-Inputs!$B$8 -> 292377.13
A9: 7 | B9: =MAX(0,Inputs!$B$13*(1+Inputs!$B$6/12)^(A9*12)-Inputs!$B$14*(((1+Inputs!$B$6/12)^(A9*12)-1)/(Inputs!$B$6/12))) -> 308867.57 | C9: =Inputs!$B$1*(1+Inputs!$B$11)^A9 -> 633385.04 | D9: =C9-B9 -> 324517.47 | E9: =Inputs!$B$14*12 -> 24458.951 | F9: =E9*A9 -> 171212.66 | G9: =F9-((Inputs!$B$13-B9)) -> 134580.23 | H9: =D9-Inputs!$B$8 -> 317017.47
A10: 8 | B10: =MAX(0,Inputs!$B$13*(1+Inputs!$B$6/12)^(A10*12)-Inputs!$B$14*(((1+Inputs!$B$6/12)^(A10*12)-1)/(Inputs!$B$6/12))) -> 302303.22 | C10: =Inputs!$B$1*(1+Inputs!$B$11)^A10 -> 652386.59 | D10: =C10-B10 -> 350083.37 | E10: =Inputs!$B$14*12 -> 24458.951 | F10: =E10*A10 -> 195671.61 | G10: =F10-((Inputs!$B$13-B10)) -> 152474.83 | H10: =D10-Inputs!$B$8 -> 342583.37
A11: 9 | B11: =MAX(0,Inputs!$B$13*(1+Inputs!$B$6/12)^(A11*12)-Inputs!$B$14*(((1+Inputs!$B$6/12)^(A11*12)-1)/(Inputs!$B$6/12))) -> 295344.39 | C11: =Inputs!$B$1*(1+Inputs!$B$11)^A11 -> 671958.19 | D11: =C11-B11 -> 376613.8 | E11: =Inputs!$B$14*12 -> 24458.951 | F11: =E11*A11 -> 220130.56 | G11: =F11-((Inputs!$B$13-B11)) -> 169974.95 | H11: =D11-Inputs!$B$8 -> 369113.8
A12: 10 | B12: =MAX(0,Inputs!$B$13*(1+Inputs!$B$6/12)^(A12*12)-Inputs!$B$14*(((1+Inputs!$B$6/12)^(A12*12)-1)/(Inputs!$B$6/12))) -> 287967.37 | C12: =Inputs!$B$1*(1+Inputs!$B$11)^A12 -> 692116.94 | D12: =C12-B12 -> 404149.56 | E12: =Inputs!$B$14*12 -> 24458.951 | F12: =E12*A12 -> 244589.51 | G12: =F12-((Inputs!$B$13-B12)) -> 187056.89 | H12: =D12-Inputs!$B$8 -> 396649.56

Sheet Extra Paydown Case
A1: Year | B1: Remaining Balance | C1: Home Value | D1: Equity | E1: Annual Payment | F1: Cumulative Payments | G1: Approx interest | H1: Net worth est. | J1: Payoff Check
A2: 0 | B2: =MAX(0,Inputs!$B$2*(1+Inputs!$B$3/12)^(A2*12)-(Inputs!$B$5+Inputs!$B$9)*(((1+Inputs!$B$3/12)^(A2*12)-1)/(Inputs!$B$3/12))) -> 338000 | C2: =Inputs!$B$1*(1+Inputs!$B$11)^A2 -> 515000 | D2: =C2-B2 -> 177000 | E2: =(Inputs!$B$5+Inputs!$B$9)*12 -> 31365.703 | F2: =E2*A2 -> 0 | G2: =F2-((Inputs!$B$2-B2)) -> 0 | H2: =D2 -> 177000 | J2: Mortgage payoff year | K2: =IFERROR(_xludf.MINIFS(A2:A12,B2:B12,"<=0"),">10 years") -> >10 years
A3: 1 | B3: =MAX(0,Inputs!$B$2*(1+Inputs!$B$3/12)^(A3*12)-(Inputs!$B$5+Inputs!$B$9)*(((1+Inputs!$B$3/12)^(A3*12)-1)/(Inputs!$B$3/12))) -> 329869.55 | C3: =Inputs!$B$1*(1+Inputs!$B$11)^A3 -> 530450 | D3: =C3-B3 -> 200580.45 | E3: =(Inputs!$B$5+Inputs!$B$9)*12 -> 31365.703 | F3: =E3*A3 -> 31365.703 | G3: =F3-((Inputs!$B$2-B3)) -> 23235.252 | H3: =D3 -> 200580.45
A4: 2 | B4: =MAX(0,Inputs!$B$2*(1+Inputs!$B$3/12)^(A4*12)-(Inputs!$B$5+Inputs!$B$9)*(((1+Inputs!$B$3/12)^(A4*12)-1)/(Inputs!$B$3/12))) -> 321155.68 | C4: =Inputs!$B$1*(1+Inputs!$B$11)^A4 -> 546363.5 | D4: =C4-B4 -> 225207.82 | E4: =(Inputs!$B$5+Inputs!$B$9)*12 -> 31365.703 | F4: =E4*A4 -> 62731.407 | G4: =F4-((Inputs!$B$2-B4)) -> 45887.085 | H4: =D4 -> 225207.82
A5: 3 | B5: =MAX(0,Inputs!$B$2*(1+Inputs!$B$3/12)^(A5*12)-(Inputs!$B$5+Inputs!$B$9)*(((1+Inputs!$B$3/12)^(A5*12)-1)/(Inputs!$B$3/12))) -> 311816.53 | C5: =Inputs!$B$1*(1+Inputs!$B$11)^A5 -> 562754.41 | D5: =C5-B5 -> 250937.88 | E5: =(Inputs!$B$5+Inputs!$B$9)*12 -> 31365.703 | F5: =E5*A5 -> 94097.11 | G5: =F5-((Inputs!$B$2-B5)) -> 67913.636 | H5: =D5 -> 250937.88
A6: 4 | B6: =MAX(0,Inputs!$B$2*(1+Inputs!$B$3/12)^(A6*12)-(Inputs!$B$5+Inputs!$B$9)*(((1+Inputs!$B$3/12)^(A6*12)-1)/(Inputs!$B$3/12))) -> 301807.22 | C6: =Inputs!$B$1*(1+Inputs!$B$11)^A6 -> 579637.04 | D6: =C6-B6 -> 277829.82 | E6: =(Inputs!$B$5+Inputs!$B$9)*12 -> 31365.703 | F6: =E6*A6 -> 125462.81 | G6: =F6-((Inputs!$B$2-B6)) -> 89270.035 | H6: =D6 -> 277829.82
A7: 5 | B7: =MAX(0,Inputs!$B$2*(1+Inputs!$B$3/12)^(A7*12)-(Inputs!$B$5+Inputs!$B$9)*(((1+Inputs!$B$3/12)^(A7*12)-1)/(Inputs!$B$3/12))) -> 291079.68 | C7: =Inputs!$B$1*(1+Inputs!$B$11)^A7 -> 597026.15 | D7: =C7-B7 -> 305946.47 | E7: =(Inputs!$B$5+Inputs!$B$9)*12 -> 31365.703 | F7: =E7*A7 -> 156828.52 | G7: =F7-((Inputs!$B$2-B7)) -> 109908.2 | H7: =D7 -> 305946.47
A8: 6 | B8: =MAX(0,Inputs!$B$2*(1+Inputs!$B$3/12)^(A8*12)-(Inputs!$B$5+Inputs!$B$9)*(((1+Inputs!$B$3/12)^(A8*12)-1)/(Inputs!$B$3/12))) -> 279582.36 | C8: =Inputs!$B$1*(1+Inputs!$B$11)^A8 -> 614936.93 | D8: =C8-B8 -> 335354.57 | E8: =(Inputs!$B$5+Inputs!$B$9)*12 -> 31365.703 | F8: =E8*A8 -> 188194.22 | G8: =F8-((Inputs!$B$2-B8)) -> 129776.58 | H8: =D8 -> 335354.57
A9: 7 | B9: =MAX(0,Inputs!$B$2*(1+Inputs!$B$3/12)^(A9*12)-(Inputs!$B$5+Inputs!$B$9)*(((1+Inputs!$B$3/12)^(A9*12)-1)/(Inputs!$B$3/12))) -> 267260.02 | C9: =Inputs!$B$1*(1+Inputs!$B$11)^A9 -> 633385.04 | D9: =C9-B9 -> 366125.02 | E9: =(Inputs!$B$5+Inputs!$B$9)*12 -> 31365.703 | F9: =E9*A9 -> 219559.92 | G9: =F9-((Inputs!$B$2-B9)) -> 148819.94 | H9: =D9 -> 366125.02
A10: 8 | B10: =MAX(0,Inputs!$B$2*(1+Inputs!$B$3/12)^(A10*12)-(Inputs!$B$5+Inputs!$B$9)*(((1+Inputs!$B$3/12)^(A10*12)-1)/(Inputs!$B$3/12))) -> 254053.47 | C10: =Inputs!$B$1*(1+Inputs!$B$11)^A10 -> 652386.59 | D10: =C10-B10 -> 398333.12 | E10: =(Inputs!$B$5+Inputs!$B$9)*12 -> 31365.703 | F10: =E10*A10 -> 250925.63 | G10: =F10-((Inputs!$B$2-B10)) -> 166979.1 | H10: =D10 -> 398333.12
A11: 9 | B11: =MAX(0,Inputs!$B$2*(1+Inputs!$B$3/12)^(A11*12)-(Inputs!$B$5+Inputs!$B$9)*(((1+Inputs!$B$3/12)^(A11*12)-1)/(Inputs!$B$3/12))) -> 239899.25 | C11: =Inputs!$B$1*(1+Inputs!$B$11)^A11 -> 671958.19 | D11: =C11-B11 -> 432058.94 | E11: =(Inputs!$B$5+Inputs!$B$9)*12 -> 31365.703 | F11: =E11*A11 -> 282291.33 | G11: =F11-((Inputs!$B$2-B11)) -> 184190.58 | H11: =D11 -> 432058.94
A12: 10 | B12: =MAX(0,Inputs!$B$2*(1+Inputs!$B$3/12)^(A12*12)-(Inputs!$B$5+Inputs!$B$9)*(((1+Inputs!$B$3/12)^(A12*12)-1)/(Inputs!$B$3/12))) -> 224729.37 | C12: =Inputs!$B$1*(1+Inputs!$B$11)^A12 -> 692116.94 | D12: =C12-B12 -> 467387.57 | E12: =(Inputs!$B$5+Inputs!$B$9)*12 -> 31365.703 | F12: =E12*A12 -> 313657.03 | G12: =F12-((Inputs!$B$2-B12)) -> 200386.4 | H12: =D12 -> 467387.57

Sheet Invest Case
A1: Year | B1: Remaining Balance | C1: Home Value | D1: Equity | E1: Investment Balance | F1: Annual Mortgage Payment | G1: Approx interest | H1: Net worth est.
A2: 0 | B2: =MAX(0,Inputs!$B$2*(1+Inputs!$B$3/12)^(A2*12)-Inputs!$B$5*(((1+Inputs!$B$3/12)^(A2*12)-1)/(Inputs!$B$3/12))) -> 338000 | C2: =Inputs!$B$1*(1+Inputs!$B$11)^A2 -> 515000 | D2: =C2-B2 -> 177000 | E2: =IF(A2=0,0,Inputs!$B$9*((1+Inputs!$B$10/12)^(A2*12)-1)/(Inputs!$B$10/12)) -> 0 | F2: =Inputs!$B$5*12 -> 27765.703 | G2: =F2*A2-((Inputs!$B$2-B2)) -> 0 | H2: =D2+E2 -> 177000
A3: 1 | B3: =MAX(0,Inputs!$B$2*(1+Inputs!$B$3/12)^(A3*12)-Inputs!$B$5*(((1+Inputs!$B$3/12)^(A3*12)-1)/(Inputs!$B$3/12))) -> 333586.47 | C3: =Inputs!$B$1*(1+Inputs!$B$11)^A3 -> 530450 | D3: =C3-B3 -> 196863.53 | E3: =IF(A3=0,0,Inputs!$B$9*((1+Inputs!$B$10/12)^(A3*12)-1)/(Inputs!$B$10/12)) -> 3717.7756 | F3: =Inputs!$B$5*12 -> 27765.703 | G3: =F3*A3-((Inputs!$B$2-B3)) -> 23352.17 | H3: =D3+E3 -> 200581.31
A4: 2 | B4: =MAX(0,Inputs!$B$2*(1+Inputs!$B$3/12)^(A4*12)-Inputs!$B$5*(((1+Inputs!$B$3/12)^(A4*12)-1)/(Inputs!$B$3/12))) -> 328856.23 | C4: =Inputs!$B$1*(1+Inputs!$B$11)^A4 -> 546363.5 | D4: =C4-B4 -> 217507.27 | E4: =IF(A4=0,0,Inputs!$B$9*((1+Inputs!$B$10/12)^(A4*12)-1)/(Inputs!$B$10/12)) -> 7704.3095 | F4: =Inputs!$B$5*12 -> 27765.703 | G4: =F4*A4-((Inputs!$B$2-B4)) -> 46387.636 | H4: =D4+E4 -> 225211.58
A5: 3 | B5: =MAX(0,Inputs!$B$2*(1+Inputs!$B$3/12)^(A5*12)-Inputs!$B$5*(((1+Inputs!$B$3/12)^(A5*12)-1)/(Inputs!$B$3/12))) -> 323786.56 | C5: =Inputs!$B$1*(1+Inputs!$B$11)^A5 -> 562754.41 | D5: =C5-B5 -> 238967.84 | E5: =IF(A5=0,0,Inputs!$B$9*((1+Inputs!$B$10/12)^(A5*12)-1)/(Inputs!$B$10/12)) -> 11979.03 | F5: =Inputs!$B$5*12 -> 27765.703 | G5: =F5*A5-((Inputs!$B$2-B5)) -> 69083.675 | H5: =D5+E5 -> 250946.87
A6: 4 | B6: =MAX(0,Inputs!$B$2*(1+Inputs!$B$3/12)^(A6*12)-Inputs!$B$5*(((1+Inputs!$B$3/12)^(A6*12)-1)/(Inputs!$B$3/12))) -> 318353.12 | C6: =Inputs!$B$1*(1+Inputs!$B$11)^A6 -> 579637.04 | D6: =C6-B6 -> 261283.92 | E6: =IF(A6=0,0,Inputs!$B$9*((1+Inputs!$B$10/12)^(A6*12)-1)/(Inputs!$B$10/12)) -> 16562.771 | F6: =Inputs!$B$5*12 -> 27765.703 | G6: =F6*A6-((Inputs!$B$2-B6)) -> 91415.929 | H6: =D6+E6 -> 277846.69
A7: 5 | B7: =MAX(0,Inputs!$B$2*(1+Inputs!$B$3/12)^(A7*12)-Inputs!$B$5*(((1+Inputs!$B$3/12)^(A7*12)-1)/(Inputs!$B$3/12))) -> 312529.78 | C7: =Inputs!$B$1*(1+Inputs!$B$11)^A7 -> 597026.15 | D7: =C7-B7 -> 284496.37 | E7: =IF(A7=0,0,Inputs!$B$9*((1+Inputs!$B$10/12)^(A7*12)-1)/(Inputs!$B$10/12)) -> 21477.87 | F7: =Inputs!$B$5*12 -> 27765.703 | G7: =F7*A7-((Inputs!$B$2-B7)) -> 113358.29 | H7: =D7+E7 -> 305974.24
A8: 6 | B8: =MAX(0,Inputs!$B$2*(1+Inputs!$B$3/12)^(A8*12)-Inputs!$B$5*(((1+Inputs!$B$3/12)^(A8*12)-1)/(Inputs!$B$3/12))) -> 306288.57 | C8: =Inputs!$B$1*(1+Inputs!$B$11)^A8 -> 614936.93 | D8: =C8-B8 -> 308648.36 | E8: =IF(A8=0,0,Inputs!$B$9*((1+Inputs!$B$10/12)^(A8*12)-1)/(Inputs!$B$10/12)) -> 26748.283 | F8: =Inputs!$B$5*12 -> 27765.703 | G8: =F8*A8-((Inputs!$B$2-B8)) -> 134882.79 | H8: =D8+E8 -> 335396.64
A9: 7 | B9: =MAX(0,Inputs!$B$2*(1+Inputs!$B$3/12)^(A9*12)-Inputs!$B$5*(((1+Inputs!$B$3/12)^(A9*12)-1)/(Inputs!$B$3/12))) -> 299599.52 | C9: =Inputs!$B$1*(1+Inputs!$B$11)^A9 -> 633385.04 | D9: =C9-B9 -> 333785.53 | E9: =IF(A9=0,0,Inputs!$B$9*((1+Inputs!$B$10/12)^(A9*12)-1)/(Inputs!$B$10/12)) -> 32399.694 | F9: =Inputs!$B$5*12 -> 27765.703 | G9: =F9*A9-((Inputs!$B$2-B9)) -> 155959.44 | H9: =D9+E9 -> 366185.22
A10: 8 | B10: =MAX(0,Inputs!$B$2*(1+Inputs!$B$3/12)^(A10*12)-Inputs!$B$5*(((1+Inputs!$B$3/12)^(A10*12)-1)/(Inputs!$B$3/12))) -> 292430.47 | C10: =Inputs!$B$1*(1+Inputs!$B$11)^A10 -> 652386.59 | D10: =C10-B10 -> 359956.12 | E10: =IF(A10=0,0,Inputs!$B$9*((1+Inputs!$B$10/12)^(A10*12)-1)/(Inputs!$B$10/12)) -> 38459.646 | F10: =Inputs!$B$5*12 -> 27765.703 | G10: =F10*A10-((Inputs!$B$2-B10)) -> 176556.1 | H10: =D10+E10 -> 398415.77
A11: 9 | B11: =MAX(0,Inputs!$B$2*(1+Inputs!$B$3/12)^(A11*12)-Inputs!$B$5*(((1+Inputs!$B$3/12)^(A11*12)-1)/(Inputs!$B$3/12))) -> 284747 | C11: =Inputs!$B$1*(1+Inputs!$B$11)^A11 -> 671958.19 | D11: =C11-B11 -> 387211.19 | E11: =IF(A11=0,0,Inputs!$B$9*((1+Inputs!$B$10/12)^(A11*12)-1)/(Inputs!$B$10/12)) -> 44957.673 | F11: =Inputs!$B$5*12 -> 27765.703 | G11: =F11*A11-((Inputs!$B$2-B11)) -> 196638.33 | H11: =D11+E11 -> 432168.86
A12: 10 | B12: =MAX(0,Inputs!$B$2*(1+Inputs!$B$3/12)^(A12*12)-Inputs!$B$5*(((1+Inputs!$B$3/12)^(A12*12)-1)/(Inputs!$B$3/12))) -> 276512.18 | C12: =Inputs!$B$1*(1+Inputs!$B$11)^A12 -> 692116.94 | D12: =C12-B12 -> 415604.76 | E12: =IF(A12=0,0,Inputs!$B$9*((1+Inputs!$B$10/12)^(A12*12)-1)/(Inputs!$B$10/12)) -> 51925.442 | F12: =Inputs!$B$5*12 -> 27765.703 | G12: =F12*A12-((Inputs!$B$2-B12)) -> 216169.21 | H12: =D12+E12 -> 467530.2

Sheet Break-Even & Summary
A1: Current payment | B1: =Inputs!B5 -> 2313.8086
A2: Refi payment | B2: =Inputs!B14 -> 2038.2459
A3: Extra-paydown outflow | B3: =Inputs!B5+Inputs!B9 -> 2613.8086
A4: Invest contribution | B4: =Inputs!B9 -> 300
A6: Year 1 refi net worth | B6: ='Refi Case'!H3 -> 181812.95
A7: Year 1 paydown net worth | B7: ='Extra Paydown Case'!H3 -> 200580.45
A8: Year 1 invest net worth | B8: ='Invest Case'!H3 -> 200581.31
A9: Year 10 refi net worth | B9: ='Refi Case'!H12 -> 396649.56
A10: Year 10 paydown net worth | B10: ='Extra Paydown Case'!H12 -> 467387.57
A11: Year 10 invest net worth | B11: ='Invest Case'!H12 -> 467530.2
A13: Refi break-even year | B13: =IFERROR(_xludf.MINIFS(A19:A28,B19:B28,">=0"),">10 years") -> >10 years
A18: Hold Year | B18: Refi Savings vs Current | C18: Paydown Interest Saved | D18: Opportunity Cost | F18: Year | G18: Refi | H18: Paydown | I18: Invest
A19: 1 | B19: =(Inputs!$B$15*12*A19)-Inputs!$B$8 -> -4193.2478 | C19: ='Invest Case'!G2-'Extra Paydown Case'!G2 -> 0 | D19: ='Invest Case'!E2 -> 0 | F19: 0 | G19: ='Refi Case'!H2 -> 162000 | H19: ='Extra Paydown Case'!H2 -> 177000 | I19: ='Invest Case'!H2 -> 177000
A20: 2 | B20: =(Inputs!$B$15*12*A20)-Inputs!$B$8 -> -886.49557 | C20: ='Invest Case'!G3-'Extra Paydown Case'!G3 -> 116.91798 | D20: ='Invest Case'!E3 -> 3717.7756 | F20: 1 | G20: ='Refi Case'!H3 -> 181812.95 | H20: ='Extra Paydown Case'!H3 -> 200580.45 | I20: ='Invest Case'!H3 -> 200581.31
A21: 3 | B21: =(Inputs!$B$15*12*A21)-Inputs!$B$8 -> 2420.2566 | C21: ='Invest Case'!G4-'Extra Paydown Case'!G4 -> 500.55147 | D21: ='Invest Case'!E4 -> 7704.3095 | F21: 2 | G21: ='Refi Case'!H4 -> 202351.59 | H21: ='Extra Paydown Case'!H4 -> 225207.82 | I21: ='Invest Case'!H4 -> 225211.58
A22: 4 | B22: =(Inputs!$B$15*12*A22)-Inputs!$B$8 -> 5727.0089 | C22: ='Invest Case'!G5-'Extra Paydown Case'!G5 -> 1170.0392 | D22: ='Invest Case'!E5 -> 11979.03 | F22: 3 | G22: ='Refi Case'!H5 -> 223645.58 | H22: ='Extra Paydown Case'!H5 -> 250937.88 | I22: ='Invest Case'!H5 -> 250946.87
A23: 5 | B23: =(Inputs!$B$15*12*A23)-Inputs!$B$8 -> 9033.7611 | C23: ='Invest Case'!G6-'Extra Paydown Case'!G6 -> 2145.8933 | D23: ='Invest Case'!E6 -> 16562.771 | F23: 4 | G23: ='Refi Case'!H6 -> 245725.94 | H23: ='Extra Paydown Case'!H6 -> 277829.82 | I23: ='Invest Case'!H6 -> 277846.69
A24: 6 | B24: =(Inputs!$B$15*12*A24)-Inputs!$B$8 -> 12340.513 | C24: ='Invest Case'!G7-'Extra Paydown Case'!G7 -> 3450.0977 | D24: ='Invest Case'!E7 -> 21477.87 | F24: 5 | G24: ='Refi Case'!H7 -> 268625.14 | H24: ='Extra Paydown Case'!H7 -> 305946.47 | I24: ='Invest Case'!H7 -> 305974.24
A25: 7 | B25: =(Inputs!$B$15*12*A25)-Inputs!$B$8 -> 15647.265 | C25: ='Invest Case'!G8-'Extra Paydown Case'!G8 -> 5106.2139 | D25: ='Invest Case'!E8 -> 26748.283 | F25: 6 | G25: ='Refi Case'!H8 -> 292377.13 | H25: ='Extra Paydown Case'!H8 -> 335354.57 | I25: ='Invest Case'!H8 -> 335396.64
A26: 8 | B26: =(Inputs!$B$15*12*A26)-Inputs!$B$8 -> 18954.018 | C26: ='Invest Case'!G9-'Extra Paydown Case'!G9 -> 7139.4941 | D26: ='Invest Case'!E9 -> 32399.694 | F26: 7 | G26: ='Refi Case'!H9 -> 317017.47 | H26: ='Extra Paydown Case'!H9 -> 366125.02 | I26: ='Invest Case'!H9 -> 366185.22
A27: 9 | B27: =(Inputs!$B$15*12*A27)-Inputs!$B$8 -> 22260.77 | C27: ='Invest Case'!G10-'Extra Paydown Case'!G10 -> 9577.0026 | D27: ='Invest Case'!E10 -> 38459.646 | F27: 8 | G27: ='Refi Case'!H10 -> 342583.37 | H27: ='Extra Paydown Case'!H10 -> 398333.12 | I27: ='Invest Case'!H10 -> 398415.77
A28: 10 | B28: =(Inputs!$B$15*12*A28)-Inputs!$B$8 -> 25567.522 | C28: ='Invest Case'!G11-'Extra Paydown Case'!G11 -> 12447.746 | D28: ='Invest Case'!E11 -> 44957.673 | F28: 9 | G28: ='Refi Case'!H11 -> 369113.8 | H28: ='Extra Paydown Case'!H11 -> 432058.94 | I28: ='Invest Case'!H11 -> 432168.86
F29: 10 | G29: ='Refi Case'!H12 -> 396649.56 | H29: ='Extra Paydown Case'!H12 -> 467387.57 | I29: ='Invest Case'!H12 -> 467530.2
