Workbook

Sheet Ladder Setup
A1: Bond ID | B1: Type | C1: Purchase Date | D1: Maturity Date | E1: Years to Maturity | F1: Par Value | G1: Coupon Rate | H1: Purchase Price (% of par) | I1: Cost Basis | J1: Coupon / Year | K1: Coupon Frequency | L1: Yield Approx. | M1: Reinvest At Maturity | O1: Ladder totals
A2: 2Y Tsy | B2: Treasury | C2: 46115 | D2: 46553 | E2: =(D2-C2)/365 -> 1.2 | F2: 25000 | G2: 0.039 | H2: 99.2 | I2: =F2*H2/100 -> 24800 | J2: =F2*G2 -> 975 | K2: 2 | L2: =IF(I2=0,0,J2/I2) -> 0.039314516 | M2: Yes | O2: Total ladder cost | P2: =SUM(I2:I8) -> 154022
A3: 4Y Tsy | B3: Treasury | C3: 46129 | D3: 47011 | E3: =(D3-C3)/365 -> 2.4164384 | F3: 30000 | G3: 0.041 | H3: 99.7 | I3: =F3*H3/100 -> 29910 | J3: =F3*G3 -> 1230 | K3: 2 | L3: =IF(I3=0,0,J3/I3) -> 0.04112337 | M3: Yes | O3: Total par value | P3: =SUM(F2:F8) -> 156000
A4: Bank CD | B4: CD | C4: 46109 | D4: 47209 | E4: =(D4-C4)/365 -> 3.0136986 | F4: 20000 | G4: 0.044 | H4: 100 | I4: =F4*H4/100 -> 20000 | J4: =F4*G4 -> 880 | K4: 2 | L4: =IF(I4=0,0,J4/I4) -> 0.044 | M4: No | O4: Weighted avg maturity | P4: =SUMPRODUCT(E2:E8,I2:I8)/SUM(I2:I8) -> 4.7586712
A5: City muni | B5: Municipal | C5: 46120 | D5: 47696 | E5: =(D5-C5)/365 -> 4.3178082 | F5: 18000 | G5: 0.0375 | H5: 97.8 | I5: =F5*H5/100 -> 17604 | J5: =F5*G5 -> 675 | K5: 2 | L5: =IF(I5=0,0,J5/I5) -> 0.038343558 | M5: Yes | O5: Weighted avg yield | P5: =SUMPRODUCT(L2:L8,I2:I8)/SUM(I2:I8) -> 0.044350807
A6: Corp 32 | B6: Corporate | C6: 46124 | D6: 48335 | E6: =(D6-C6)/365 -> 6.0575342 | F6: 22000 | G6: 0.0525 | H6: 98.5 | I6: =F6*H6/100 -> 21670 | J6: =F6*G6 -> 1155 | K6: 2 | L6: =IF(I6=0,0,J6/I6) -> 0.053299492 | M6: Yes | O6: Year 1 coupon income | P6: ='Cash Flow Schedule'!B2 -> 6831
A7: 10Y Tsy | B7: Treasury | C7: 46136 | D7: 49263 | E7: =(D7-C7)/365 -> 8.5671233 | F7: 26000 | G7: 0.046 | H7: 96.3 | I7: =F7*H7/100 -> 25038 | J7: =F7*G7 -> 1196 | K7: 2 | L7: =IF(I7=0,0,J7/I7) -> 0.047767394 | M7: No
A8: Long CD | B8: CD | C8: 46144 | D8: 49766 | E8: =(D8-C8)/365 -> 9.9232877 | F8: 15000 | G8: 0.048 | H8: 100 | I8: =F8*H8/100 -> 15000 | J8: =F8*G8 -> 720 | K8: 1 | L8: =IF(I8=0,0,J8/I8) -> 0.048 | M8: Yes

Sheet Cash Flow Schedule
A1: Calendar Year | B1: Coupon Income | C1: Maturity Principal | D1: Total Cash Flow | E1: Reinvested Amount | F1: Net Cash Available
A2: 2027 | B2: =SUMPRODUCT((YEAR('Ladder Setup'!$D$2:$D$8)>=A2)*('Ladder Setup'!$J$2:$J$8)) -> 6831 | C2: =SUMPRODUCT((YEAR('Ladder Setup'!$D$2:$D$8)=A2)*('Ladder Setup'!$F$2:$F$8)) -> 25000 | D2: =B2+C2 -> 31831 | E2: =SUMPRODUCT((YEAR('Ladder Setup'!$D$2:$D$8)=A2)*('Ladder Setup'!$M$2:$M$8="Yes")*('Ladder Setup'!$F$2:$F$8)) -> 25000 | F2: =D2-E2 -> 6831
A3: 2028 | B3: =SUMPRODUCT((YEAR('Ladder Setup'!$D$2:$D$8)>=A3)*('Ladder Setup'!$J$2:$J$8)) -> 5856 | C3: =SUMPRODUCT((YEAR('Ladder Setup'!$D$2:$D$8)=A3)*('Ladder Setup'!$F$2:$F$8)) -> 30000 | D3: =B3+C3 -> 35856 | E3: =SUMPRODUCT((YEAR('Ladder Setup'!$D$2:$D$8)=A3)*('Ladder Setup'!$M$2:$M$8="Yes")*('Ladder Setup'!$F$2:$F$8)) -> 30000 | F3: =D3-E3 -> 5856
A4: 2029 | B4: =SUMPRODUCT((YEAR('Ladder Setup'!$D$2:$D$8)>=A4)*('Ladder Setup'!$J$2:$J$8)) -> 4626 | C4: =SUMPRODUCT((YEAR('Ladder Setup'!$D$2:$D$8)=A4)*('Ladder Setup'!$F$2:$F$8)) -> 20000 | D4: =B4+C4 -> 24626 | E4: =SUMPRODUCT((YEAR('Ladder Setup'!$D$2:$D$8)=A4)*('Ladder Setup'!$M$2:$M$8="Yes")*('Ladder Setup'!$F$2:$F$8)) -> 0 | F4: =D4-E4 -> 24626
A5: 2030 | B5: =SUMPRODUCT((YEAR('Ladder Setup'!$D$2:$D$8)>=A5)*('Ladder Setup'!$J$2:$J$8)) -> 3746 | C5: =SUMPRODUCT((YEAR('Ladder Setup'!$D$2:$D$8)=A5)*('Ladder Setup'!$F$2:$F$8)) -> 18000 | D5: =B5+C5 -> 21746 | E5: =SUMPRODUCT((YEAR('Ladder Setup'!$D$2:$D$8)=A5)*('Ladder Setup'!$M$2:$M$8="Yes")*('Ladder Setup'!$F$2:$F$8)) -> 18000 | F5: =D5-E5 -> 3746
A6: 2031 | B6: =SUMPRODUCT((YEAR('Ladder Setup'!$D$2:$D$8)>=A6)*('Ladder Setup'!$J$2:$J$8)) -> 3071 | C6: =SUMPRODUCT((YEAR('Ladder Setup'!$D$2:$D$8)=A6)*('Ladder Setup'!$F$2:$F$8)) -> 0 | D6: =B6+C6 -> 3071 | E6: =SUMPRODUCT((YEAR('Ladder Setup'!$D$2:$D$8)=A6)*('Ladder Setup'!$M$2:$M$8="Yes")*('Ladder Setup'!$F$2:$F$8)) -> 0 | F6: =D6-E6 -> 3071
A7: 2032 | B7: =SUMPRODUCT((YEAR('Ladder Setup'!$D$2:$D$8)>=A7)*('Ladder Setup'!$J$2:$J$8)) -> 3071 | C7: =SUMPRODUCT((YEAR('Ladder Setup'!$D$2:$D$8)=A7)*('Ladder Setup'!$F$2:$F$8)) -> 22000 | D7: =B7+C7 -> 25071 | E7: =SUMPRODUCT((YEAR('Ladder Setup'!$D$2:$D$8)=A7)*('Ladder Setup'!$M$2:$M$8="Yes")*('Ladder Setup'!$F$2:$F$8)) -> 22000 | F7: =D7-E7 -> 3071
A8: 2033 | B8: =SUMPRODUCT((YEAR('Ladder Setup'!$D$2:$D$8)>=A8)*('Ladder Setup'!$J$2:$J$8)) -> 1916 | C8: =SUMPRODUCT((YEAR('Ladder Setup'!$D$2:$D$8)=A8)*('Ladder Setup'!$F$2:$F$8)) -> 0 | D8: =B8+C8 -> 1916 | E8: =SUMPRODUCT((YEAR('Ladder Setup'!$D$2:$D$8)=A8)*('Ladder Setup'!$M$2:$M$8="Yes")*('Ladder Setup'!$F$2:$F$8)) -> 0 | F8: =D8-E8 -> 1916
A9: 2034 | B9: =SUMPRODUCT((YEAR('Ladder Setup'!$D$2:$D$8)>=A9)*('Ladder Setup'!$J$2:$J$8)) -> 1916 | C9: =SUMPRODUCT((YEAR('Ladder Setup'!$D$2:$D$8)=A9)*('Ladder Setup'!$F$2:$F$8)) -> 26000 | D9: =B9+C9 -> 27916 | E9: =SUMPRODUCT((YEAR('Ladder Setup'!$D$2:$D$8)=A9)*('Ladder Setup'!$M$2:$M$8="Yes")*('Ladder Setup'!$F$2:$F$8)) -> 0 | F9: =D9-E9 -> 27916
A10: 2035 | B10: =SUMPRODUCT((YEAR('Ladder Setup'!$D$2:$D$8)>=A10)*('Ladder Setup'!$J$2:$J$8)) -> 720 | C10: =SUMPRODUCT((YEAR('Ladder Setup'!$D$2:$D$8)=A10)*('Ladder Setup'!$F$2:$F$8)) -> 0 | D10: =B10+C10 -> 720 | E10: =SUMPRODUCT((YEAR('Ladder Setup'!$D$2:$D$8)=A10)*('Ladder Setup'!$M$2:$M$8="Yes")*('Ladder Setup'!$F$2:$F$8)) -> 0 | F10: =D10-E10 -> 720
A11: 2036 | B11: =SUMPRODUCT((YEAR('Ladder Setup'!$D$2:$D$8)>=A11)*('Ladder Setup'!$J$2:$J$8)) -> 720 | C11: =SUMPRODUCT((YEAR('Ladder Setup'!$D$2:$D$8)=A11)*('Ladder Setup'!$F$2:$F$8)) -> 15000 | D11: =B11+C11 -> 15720 | E11: =SUMPRODUCT((YEAR('Ladder Setup'!$D$2:$D$8)=A11)*('Ladder Setup'!$M$2:$M$8="Yes")*('Ladder Setup'!$F$2:$F$8)) -> 15000 | F11: =D11-E11 -> 720

Sheet Reinvestment View
A1: Maturity Year | B1: Principal Maturing | C1: Reinvest Rate | D1: New Term (years) | E1: New Coupon Income | F1: New Maturity Year
A2: ='Cash Flow Schedule'!A2 -> 2027 | B2: ='Cash Flow Schedule'!C2 -> 25000 | C2: =IF($I$4="Yes",$I$2,0) -> 0.0475 | D2: =$I$3 -> 5 | E2: =B2*C2 -> 1187.5 | F2: =A2+D2 -> 2032 | H2: Reinvestment Rate | I2: 0.0475
A3: ='Cash Flow Schedule'!A3 -> 2028 | B3: ='Cash Flow Schedule'!C3 -> 30000 | C3: =IF($I$4="Yes",$I$2,0) -> 0.0475 | D3: =$I$3 -> 5 | E3: =B3*C3 -> 1425 | F3: =A3+D3 -> 2033 | H3: New Bond Term | I3: 5
A4: ='Cash Flow Schedule'!A4 -> 2029 | B4: ='Cash Flow Schedule'!C4 -> 20000 | C4: =IF($I$4="Yes",$I$2,0) -> 0.0475 | D4: =$I$3 -> 5 | E4: =B4*C4 -> 950 | F4: =A4+D4 -> 2034 | H4: Reinvest All Maturities? | I4: Yes
A5: ='Cash Flow Schedule'!A5 -> 2030 | B5: ='Cash Flow Schedule'!C5 -> 18000 | C5: =IF($I$4="Yes",$I$2,0) -> 0.0475 | D5: =$I$3 -> 5 | E5: =B5*C5 -> 855 | F5: =A5+D5 -> 2035
A6: ='Cash Flow Schedule'!A6 -> 2031 | B6: ='Cash Flow Schedule'!C6 -> 0 | C6: =IF($I$4="Yes",$I$2,0) -> 0.0475 | D6: =$I$3 -> 5 | E6: =B6*C6 -> 0 | F6: =A6+D6 -> 2036
A7: ='Cash Flow Schedule'!A7 -> 2032 | B7: ='Cash Flow Schedule'!C7 -> 22000 | C7: =IF($I$4="Yes",$I$2,0) -> 0.0475 | D7: =$I$3 -> 5 | E7: =B7*C7 -> 1045 | F7: =A7+D7 -> 2037 | H7: Roll Summary
A8: ='Cash Flow Schedule'!A8 -> 2033 | B8: ='Cash Flow Schedule'!C8 -> 0 | C8: =IF($I$4="Yes",$I$2,0) -> 0.0475 | D8: =$I$3 -> 5 | E8: =B8*C8 -> 0 | F8: =A8+D8 -> 2038 | H8: Total rolled principal | I8: =SUM(B2:B11) -> 156000
A9: ='Cash Flow Schedule'!A9 -> 2034 | B9: ='Cash Flow Schedule'!C9 -> 26000 | C9: =IF($I$4="Yes",$I$2,0) -> 0.0475 | D9: =$I$3 -> 5 | E9: =B9*C9 -> 1235 | F9: =A9+D9 -> 2039 | H9: Incremental coupon | I9: =SUM(E2:E11) -> 7410
A10: ='Cash Flow Schedule'!A10 -> 2035 | B10: ='Cash Flow Schedule'!C10 -> 0 | C10: =IF($I$4="Yes",$I$2,0) -> 0.0475 | D10: =$I$3 -> 5 | E10: =B10*C10 -> 0 | F10: =A10+D10 -> 2040 | H10: Average reinvest rate | I10: =AVERAGE(C2:C11) -> 0.0475
A11: ='Cash Flow Schedule'!A11 -> 2036 | B11: ='Cash Flow Schedule'!C11 -> 15000 | C11: =IF($I$4="Yes",$I$2,0) -> 0.0475 | D11: =$I$3 -> 5 | E11: =B11*C11 -> 712.5 | F11: =A11+D11 -> 2041

Sheet Summary & Sensitivity
A1: Total cost | B1: ='Ladder Setup'!P2 -> 154022
A2: Total par | B2: ='Ladder Setup'!P3 -> 156000
A3: Weighted avg maturity | B3: ='Ladder Setup'!P4 -> 4.7586712
A4: Weighted avg yield | B4: ='Ladder Setup'!P5 -> 0.044350807
A5: Year 1 coupon income | B5: ='Ladder Setup'!P6 -> 6831
A6: Year 10 ending par | B6: ='Cash Flow Schedule'!C11 -> 15000
A9: Reinvest grid
B10: 95 | C10: 97.5 | D10: 100 | E10: 102.5 | F10: 105
A11: 0.03 | B11: =('Ladder Setup'!$P$5*0.65)+($A11*0.35)-((B$10-100)/100*0.015) -> 0.040078025 | C11: =('Ladder Setup'!$P$5*0.65)+($A11*0.35)-((C$10-100)/100*0.015) -> 0.039703025 | D11: =('Ladder Setup'!$P$5*0.65)+($A11*0.35)-((D$10-100)/100*0.015) -> 0.039328025 | E11: =('Ladder Setup'!$P$5*0.65)+($A11*0.35)-((E$10-100)/100*0.015) -> 0.038953025 | F11: =('Ladder Setup'!$P$5*0.65)+($A11*0.35)-((F$10-100)/100*0.015) -> 0.038578025
A12: 0.04 | B12: =('Ladder Setup'!$P$5*0.65)+($A12*0.35)-((B$10-100)/100*0.015) -> 0.043578025 | C12: =('Ladder Setup'!$P$5*0.65)+($A12*0.35)-((C$10-100)/100*0.015) -> 0.043203025 | D12: =('Ladder Setup'!$P$5*0.65)+($A12*0.35)-((D$10-100)/100*0.015) -> 0.042828025 | E12: =('Ladder Setup'!$P$5*0.65)+($A12*0.35)-((E$10-100)/100*0.015) -> 0.042453025 | F12: =('Ladder Setup'!$P$5*0.65)+($A12*0.35)-((F$10-100)/100*0.015) -> 0.042078025
A13: 0.05 | B13: =('Ladder Setup'!$P$5*0.65)+($A13*0.35)-((B$10-100)/100*0.015) -> 0.047078025 | C13: =('Ladder Setup'!$P$5*0.65)+($A13*0.35)-((C$10-100)/100*0.015) -> 0.046703025 | D13: =('Ladder Setup'!$P$5*0.65)+($A13*0.35)-((D$10-100)/100*0.015) -> 0.046328025 | E13: =('Ladder Setup'!$P$5*0.65)+($A13*0.35)-((E$10-100)/100*0.015) -> 0.045953025 | F13: =('Ladder Setup'!$P$5*0.65)+($A13*0.35)-((F$10-100)/100*0.015) -> 0.045578025
A14: 0.06 | B14: =('Ladder Setup'!$P$5*0.65)+($A14*0.35)-((B$10-100)/100*0.015) -> 0.050578025 | C14: =('Ladder Setup'!$P$5*0.65)+($A14*0.35)-((C$10-100)/100*0.015) -> 0.050203025 | D14: =('Ladder Setup'!$P$5*0.65)+($A14*0.35)-((D$10-100)/100*0.015) -> 0.049828025 | E14: =('Ladder Setup'!$P$5*0.65)+($A14*0.35)-((E$10-100)/100*0.015) -> 0.049453025 | F14: =('Ladder Setup'!$P$5*0.65)+($A14*0.35)-((F$10-100)/100*0.015) -> 0.049078025
A15: 0.07 | B15: =('Ladder Setup'!$P$5*0.65)+($A15*0.35)-((B$10-100)/100*0.015) -> 0.054078025 | C15: =('Ladder Setup'!$P$5*0.65)+($A15*0.35)-((C$10-100)/100*0.015) -> 0.053703025 | D15: =('Ladder Setup'!$P$5*0.65)+($A15*0.35)-((D$10-100)/100*0.015) -> 0.053328025 | E15: =('Ladder Setup'!$P$5*0.65)+($A15*0.35)-((E$10-100)/100*0.015) -> 0.052953025 | F15: =('Ladder Setup'!$P$5*0.65)+($A15*0.35)-((F$10-100)/100*0.015) -> 0.052578025
