Workbook

Sheet Balance Sheet
B2: Personal Balance Sheet (Current Quarter)
B3: Line Item | C3: Amount
B4: CURRENT ASSETS
B5: Cash and Checking | C5: 4820
B6: Savings Accounts | C6: 13204
B7: Money Market | C7: 3414
B8: Subtotal Current Assets | C8: =SUM(C5:C7)
B9: INVESTMENT ASSETS
B10: Taxable Brokerage | C10: 35625
B11: 401k / 403b | C11: 72764
B12: IRA / Roth IRA | C12: 29834
B13: HSA | C13: 5865
B14: 529 Plan | C14: 7395
B15: Other Investments | C15: 2927
B16: Subtotal Investment Assets | C16: =SUM(C10:C15)
B17: FIXED ASSETS
B18: Primary Residence | C18: 289539
B19: Vehicles | C19: 12989
B20: Personal Property | C20: 7506
B21: Subtotal Fixed Assets | C21: =SUM(C18:C20)
B22: TOTAL ASSETS | C22: =C8+C16+C21
B23: CURRENT LIABILITIES
B24: Credit Cards | C24: 2703
B25: Short-Term Loans | C25: 0
B26: Medical Debt | C26: 870
B27: Subtotal Current Liabilities | C27: =SUM(C24:C26)
B28: LONG-TERM LIABILITIES
B29: Mortgage | C29: 142700
B30: Student Loans | C30: 15718
B31: Auto Loans | C31: 6369
B32: HELOC | C32: 0
B33: Subtotal Long-Term Liabilities | C33: =SUM(C29:C32)
B34: TOTAL LIABILITIES | C34: =C27+C33
B35: NET WORTH | C35: =C22-C34

Sheet Quarterly History
B2: Quarterly Balance History
B3: Line Item | C3: Q1 2024 | D3: Q2 2024 | E3: Q3 2024 | F3: Q4 2024 | G3: Q1 2025 | H3: Q2 2025 | I3: Q3 2025 | J3: Q4 2025
B4: CURRENT ASSETS
B5: Cash and Checking | C5: 4475 | D5: 4505 | E5: 4577 | F5: 4605 | G5: 4659 | H5: 4772 | I5: 4782 | J5: 4820
B6: Savings Accounts | C6: 12101 | D6: 12127 | E6: 12173 | F6: 12424 | G6: 12728 | H6: 12830 | I6: 12891 | J6: 13204
B7: Money Market | C7: 2999 | D7: 3044 | E7: 3090 | F7: 3139 | G7: 3211 | H7: 3288 | I7: 3345 | J7: 3414
B8: Subtotal Current Assets | C8: =SUM(C5:C7) | D8: =SUM(D5:D7) | E8: =SUM(E5:E7) | F8: =SUM(F5:F7) | G8: =SUM(G5:G7) | H8: =SUM(H5:H7) | I8: =SUM(I5:I7) | J8: =SUM(J5:J7)
B9: INVESTMENT ASSETS
B10: Taxable Brokerage | C10: 30638 | D10: 31437 | E10: 32090 | F10: 32593 | G10: 33136 | H10: 34238 | I10: 35180 | J10: 35625
B11: 401k / 403b | C11: 63206 | D11: 64266 | E11: 66021 | F11: 67440 | G11: 68569 | H11: 69613 | I11: 71317 | J11: 72764
B12: IRA / Roth IRA | C12: 24410 | D12: 25079 | E12: 25844 | F12: 26654 | G12: 27337 | H12: 28271 | I12: 28904 | J12: 29834
B13: HSA | C13: 5080 | D13: 5235 | E13: 5304 | F13: 5433 | G13: 5557 | H13: 5626 | I13: 5734 | J13: 5865
B14: 529 Plan | C14: 6182 | D14: 6245 | E14: 6399 | F14: 6529 | G14: 6754 | H14: 6965 | I14: 7179 | J14: 7395
B15: Other Investments | C15: 2590 | D15: 2663 | E15: 2696 | F15: 2732 | G15: 2785 | H15: 2830 | I15: 2861 | J15: 2927
B16: Subtotal Investment Assets | C16: =SUM(C10:C15) | D16: =SUM(D10:D15) | E16: =SUM(E10:E15) | F16: =SUM(F10:F15) | G16: =SUM(G10:G15) | H16: =SUM(H10:H15) | I16: =SUM(I10:I15) | J16: =SUM(J10:J15)
B17: FIXED ASSETS
B18: Primary Residence | C18: 269335 | D18: 269327 | E18: 270385 | F18: 276106 | G18: 279201 | H18: 281889 | I18: 284273 | J18: 289539
B19: Vehicles | C19: 15021 | D19: 14722 | E19: 14414 | F19: 14261 | G19: 13840 | H19: 13578 | I19: 13388 | J19: 12989
B20: Personal Property | C20: 6854 | D20: 6913 | E20: 7024 | F20: 7115 | G20: 7204 | H20: 7258 | I20: 7336 | J20: 7506
B21: Subtotal Fixed Assets | C21: =SUM(C18:C20) | D21: =SUM(D18:D20) | E21: =SUM(E18:E20) | F21: =SUM(F18:F20) | G21: =SUM(G18:G20) | H21: =SUM(H18:H20) | I21: =SUM(I18:I20) | J21: =SUM(J18:J20)
B22: TOTAL ASSETS | C22: =C8+C16+C21 | D22: =D8+D16+D21 | E22: =E8+E16+E21 | F22: =F8+F16+F21 | G22: =G8+G16+G21 | H22: =H8+H16+H21 | I22: =I8+I16+I21 | J22: =J8+J16+J21
B23: CURRENT LIABILITIES
B24: Credit Cards | C24: 3142 | D24: 3055 | E24: 2976 | F24: 2890 | G24: 2814 | H24: 2751 | I24: 2719 | J24: 2703
B25: Short-Term Loans | C25: 0 | D25: 0 | E25: 0 | F25: 0 | G25: 0 | H25: 0 | I25: 0 | J25: 0
B26: Medical Debt | C26: 1000 | D26: 983 | E26: 959 | F26: 931 | G26: 917 | H26: 908 | I26: 888 | J26: 870
B27: Subtotal Current Liabilities | C27: =SUM(C24:C26) | D27: =SUM(D24:D26) | E27: =SUM(E24:E26) | F27: =SUM(F24:F26) | G27: =SUM(G24:G26) | H27: =SUM(H24:H26) | I27: =SUM(I24:I26) | J27: =SUM(J24:J26)
B28: LONG-TERM LIABILITIES
B29: Mortgage | C29: 160962 | D29: 158279 | E29: 156759 | F29: 153939 | G29: 149806 | H29: 145739 | I29: 144464 | J29: 142700
B30: Student Loans | C30: 18258 | D30: 17945 | E30: 17462 | F30: 17182 | G30: 16679 | H30: 16304 | I30: 16012 | J30: 15718
B31: Auto Loans | C31: 7061 | D31: 6966 | E31: 6800 | F31: 6729 | G31: 6667 | H31: 6563 | I31: 6524 | J31: 6369
B32: HELOC | C32: 0 | D32: 0 | E32: 0 | F32: 0 | G32: 0 | H32: 0 | I32: 0 | J32: 0
B33: Subtotal Long-Term Liabilities | C33: =SUM(C29:C32) | D33: =SUM(D29:D32) | E33: =SUM(E29:E32) | F33: =SUM(F29:F32) | G33: =SUM(G29:G32) | H33: =SUM(H29:H32) | I33: =SUM(I29:I32) | J33: =SUM(J29:J32)
B34: TOTAL LIABILITIES | C34: =C27+C33 | D34: =D27+D33 | E34: =E27+E33 | F34: =F27+F33 | G34: =G27+G33 | H34: =H27+H33 | I34: =I27+I33 | J34: =J27+J33
B35: NET WORTH | C35: =C22-C34 | D35: =D22-D34 | E35: =E22-E34 | F35: =F22-F34 | G35: =G22-G34 | H35: =H22-H34 | I35: =I22-I34 | J35: =J22-J34
B37: QoQ Change ($) | C37: 0 | D37: =D35-C35 | E37: =E35-D35 | F37: =F35-E35 | G37: =G35-F35 | H37: =H35-G35 | I37: =I35-H35 | J37: =J35-I35
B38: QoQ Change (%) | C38: 0 | D38: =IFERROR(D37/C35,0) | E38: =IFERROR(E37/D35,0) | F38: =IFERROR(F37/E35,0) | G38: =IFERROR(G37/F35,0) | H38: =IFERROR(H37/G35,0) | I38: =IFERROR(I37/H35,0) | J38: =IFERROR(J37/I35,0)

Sheet Ratios
B2: Financial Health Ratios
B3: Inputs
B4: Monthly Gross Income | C4: 7200
B5: Monthly Essential Expenses | C5: 3800
B6: Monthly Property Tax + Insurance | C6: 350
B7: Monthly Savings Amount | C7: 1200
B9: Ratio | C9: Current Value | D9: Prior Quarter | E9: Change | F9: Benchmark | G9: Status
B10: Liquidity Ratio | C10: ='Balance Sheet'!C8/C5 | D10: =IFERROR('Quarterly History'!I8/C5,0) | E10: =C10-D10 | F10: > 3.0 | G10: =IF(C10>3.0,"Healthy",IF(C10>1.7999999999999998,"Watch","Concern"))
B11: Debt-to-Asset Ratio | C11: ='Balance Sheet'!C34/'Balance Sheet'!C22 | D11: =IFERROR('Quarterly History'!I34/'Quarterly History'!I22,0) | E11: =C11-D11 | F11: < 0.50 | G11: =IF(C11<0.5,"Healthy",IF(C11<0.65,"Watch","Concern"))
B12: Solvency Ratio | C12: ='Balance Sheet'!C35/'Balance Sheet'!C22 | D12: =IFERROR('Quarterly History'!I35/'Quarterly History'!I22,0) | E12: =C12-D12 | F12: > 0.50 | G12: =IF(C12>0.5,"Healthy",IF(C12>0.3,"Watch","Concern"))
B13: Savings Rate | C13: =C7/C4 | D13: =C7/C4 | E13: =C13-D13 | F13: > 15% | G13: =IF(C13>0.15,"Healthy",IF(C13>0.09,"Watch","Concern"))
B14: Investment Ratio | C14: ='Balance Sheet'!C16/'Balance Sheet'!C22 | D14: =IFERROR('Quarterly History'!I16/'Quarterly History'!I22,0) | E14: =C14-D14 | F14: > 0.30 | G14: =IF(C14>0.3,"Healthy",IF(C14>0.18,"Watch","Concern"))
B15: Housing Ratio | C15: =('Balance Sheet'!C29/12+C6)/C4 | D15: =IFERROR(('Quarterly History'!I29/12+C6)/C4,0) | E15: =C15-D15 | F15: < 0.28 | G15: =IF(C15<0.28,"Healthy",IF(C15<0.36400000000000005,"Watch","Concern"))

Sheet Changes
B2: Quarter-over-Quarter Changes
B3: Account | C3: Prior Quarter | D3: Current Quarter | E3: Change ($) | F3: Change (%) | G3: Share of NW Change
B4: Cash and Checking | C4: ='Quarterly History'!I5 | D4: ='Quarterly History'!J5 | E4: =D4-C4 | F4: =IFERROR(E4/ABS(C4),0) | G4: =IFERROR(E4/$E$24,0)
B5: Savings Accounts | C5: ='Quarterly History'!I6 | D5: ='Quarterly History'!J6 | E5: =D5-C5 | F5: =IFERROR(E5/ABS(C5),0) | G5: =IFERROR(E5/$E$24,0)
B6: Money Market | C6: ='Quarterly History'!I7 | D6: ='Quarterly History'!J7 | E6: =D6-C6 | F6: =IFERROR(E6/ABS(C6),0) | G6: =IFERROR(E6/$E$24,0)
B7: Taxable Brokerage | C7: ='Quarterly History'!I10 | D7: ='Quarterly History'!J10 | E7: =D7-C7 | F7: =IFERROR(E7/ABS(C7),0) | G7: =IFERROR(E7/$E$24,0)
B8: 401k / 403b | C8: ='Quarterly History'!I11 | D8: ='Quarterly History'!J11 | E8: =D8-C8 | F8: =IFERROR(E8/ABS(C8),0) | G8: =IFERROR(E8/$E$24,0)
B9: IRA / Roth IRA | C9: ='Quarterly History'!I12 | D9: ='Quarterly History'!J12 | E9: =D9-C9 | F9: =IFERROR(E9/ABS(C9),0) | G9: =IFERROR(E9/$E$24,0)
B10: HSA | C10: ='Quarterly History'!I13 | D10: ='Quarterly History'!J13 | E10: =D10-C10 | F10: =IFERROR(E10/ABS(C10),0) | G10: =IFERROR(E10/$E$24,0)
B11: 529 Plan | C11: ='Quarterly History'!I14 | D11: ='Quarterly History'!J14 | E11: =D11-C11 | F11: =IFERROR(E11/ABS(C11),0) | G11: =IFERROR(E11/$E$24,0)
B12: Other Investments | C12: ='Quarterly History'!I15 | D12: ='Quarterly History'!J15 | E12: =D12-C12 | F12: =IFERROR(E12/ABS(C12),0) | G12: =IFERROR(E12/$E$24,0)
B13: Primary Residence | C13: ='Quarterly History'!I18 | D13: ='Quarterly History'!J18 | E13: =D13-C13 | F13: =IFERROR(E13/ABS(C13),0) | G13: =IFERROR(E13/$E$24,0)
B14: Vehicles | C14: ='Quarterly History'!I19 | D14: ='Quarterly History'!J19 | E14: =D14-C14 | F14: =IFERROR(E14/ABS(C14),0) | G14: =IFERROR(E14/$E$24,0)
B15: Personal Property | C15: ='Quarterly History'!I20 | D15: ='Quarterly History'!J20 | E15: =D15-C15 | F15: =IFERROR(E15/ABS(C15),0) | G15: =IFERROR(E15/$E$24,0)
B16: Credit Cards | C16: ='Quarterly History'!I24 | D16: ='Quarterly History'!J24 | E16: =D16-C16 | F16: =IFERROR(E16/ABS(C16),0) | G16: =IFERROR(E16/$E$24,0)
B17: Short-Term Loans | C17: ='Quarterly History'!I25 | D17: ='Quarterly History'!J25 | E17: =D17-C17 | F17: =IFERROR(E17/ABS(C17),0) | G17: =IFERROR(E17/$E$24,0)
B18: Medical Debt | C18: ='Quarterly History'!I26 | D18: ='Quarterly History'!J26 | E18: =D18-C18 | F18: =IFERROR(E18/ABS(C18),0) | G18: =IFERROR(E18/$E$24,0)
B19: Mortgage | C19: ='Quarterly History'!I29 | D19: ='Quarterly History'!J29 | E19: =D19-C19 | F19: =IFERROR(E19/ABS(C19),0) | G19: =IFERROR(E19/$E$24,0)
B20: Student Loans | C20: ='Quarterly History'!I30 | D20: ='Quarterly History'!J30 | E20: =D20-C20 | F20: =IFERROR(E20/ABS(C20),0) | G20: =IFERROR(E20/$E$24,0)
B21: Auto Loans | C21: ='Quarterly History'!I31 | D21: ='Quarterly History'!J31 | E21: =D21-C21 | F21: =IFERROR(E21/ABS(C21),0) | G21: =IFERROR(E21/$E$24,0)
B22: HELOC | C22: ='Quarterly History'!I32 | D22: ='Quarterly History'!J32 | E22: =D22-C22 | F22: =IFERROR(E22/ABS(C22),0) | G22: =IFERROR(E22/$E$24,0)
B24: Total Net Worth Change | E24: =SUM(E4:E22)

Sheet Dashboard
B2: Financial Dashboard
B4: Quarter | C4: Net Worth
B5: Q1 2024 | C5: ='Quarterly History'!C35
B6: Q2 2024 | C6: ='Quarterly History'!D35
B7: Q3 2024 | C7: ='Quarterly History'!E35
B8: Q4 2024 | C8: ='Quarterly History'!F35
B9: Q1 2025 | C9: ='Quarterly History'!G35
B10: Q2 2025 | C10: ='Quarterly History'!H35
B11: Q3 2025 | C11: ='Quarterly History'!I35
B12: Q4 2025 | C12: ='Quarterly History'!J35
B15: Quarter | C15: Current Assets | D15: Investment Assets | E15: Fixed Assets
B16: Q1 2024 | C16: ='Quarterly History'!C8 | D16: ='Quarterly History'!C16 | E16: ='Quarterly History'!C21
B17: Q2 2024 | C17: ='Quarterly History'!D8 | D17: ='Quarterly History'!D16 | E17: ='Quarterly History'!D21
B18: Q3 2024 | C18: ='Quarterly History'!E8 | D18: ='Quarterly History'!E16 | E18: ='Quarterly History'!E21
B19: Q4 2024 | C19: ='Quarterly History'!F8 | D19: ='Quarterly History'!F16 | E19: ='Quarterly History'!F21
B20: Q1 2025 | C20: ='Quarterly History'!G8 | D20: ='Quarterly History'!G16 | E20: ='Quarterly History'!G21
B21: Q2 2025 | C21: ='Quarterly History'!H8 | D21: ='Quarterly History'!H16 | E21: ='Quarterly History'!H21
B22: Q3 2025 | C22: ='Quarterly History'!I8 | D22: ='Quarterly History'!I16 | E22: ='Quarterly History'!I21
B23: Q4 2025 | C23: ='Quarterly History'!J8 | D23: ='Quarterly History'!J16 | E23: ='Quarterly History'!J21
B41: Ratio | C41: Current Value
B42: Liquidity Ratio | C42: =Ratios!C10
B43: Debt-to-Asset Ratio | C43: =Ratios!C11
B44: Solvency Ratio | C44: =Ratios!C12
B45: Savings Rate | C45: =Ratios!C13
B46: Investment Ratio | C46: =Ratios!C14
B47: Housing Ratio | C47: =Ratios!C15
B65: Section | C65: QoQ Change
B66: Current Assets | C66: ='Quarterly History'!J8-'Quarterly History'!I8
B67: Investment Assets | C67: ='Quarterly History'!J16-'Quarterly History'!I16
B68: Fixed Assets | C68: ='Quarterly History'!J21-'Quarterly History'!I21
B69: Current Liabilities | C69: ='Quarterly History'!J27-'Quarterly History'!I27
B70: Long-Term Liabilities | C70: ='Quarterly History'!J33-'Quarterly History'!I33

Sheet Readme
C3: Personal Balance Sheet with Financial Ratios
C5: Sample data covers Q1 2024 through Q4 2025.
C6: All account names and balances are fictional.
C7: Update the Balance Sheet tab each quarter with current figures.
C8: Copy the new quarter into the next column on Quarterly History.
C9: Ratios update automatically from the Balance Sheet and your inputs.
C10: Adjust the monthly income and expense inputs on the Ratios sheet.
C11: Do not insert or delete rows inside the balance sheet structure.
C12: This is not financial advice. Talk to a professional about your situation.
