Workbook

Sheet Property Overview
A1: Property Overview
A2: Section A - Property Details
A3: Property Name | B3: Elm Street Retail Center
A4: Address | B4: 2240 Elm Street, Suite A-D
A5: Property Type | B5: Retail Strip
A6: Total Square Feet (leasable) | B6: 8400
A7: Number of Units / Suites | B7: 4
A8: Year Built | B8: 2004
A9: Parking Spaces | B9: 32
A11: Section B - Acquisition
A12: Purchase Price | B12: 1650000
A13: Price per SqFt | B13: =IF(B6=0,0,B12/B6) -> 196.42857
A14: Closing Costs | B14: 28000
A15: Immediate CapEx (deferred maint.) | B15: 15000
A16: Total Basis | B16: =B12+B14+B15 -> 1693000
A18: Section C - Financing
A19: Down Payment (%) | B19: 0.3
A20: Down Payment ($) | B20: =B12*B19 -> 495000
A21: Loan Amount | B21: =B12-B20 -> 1155000
A22: Interest Rate | B22: 0.0675
A23: Loan Term (years) | B23: 25
A24: Balloon (years) | B24: 10
A25: Monthly Debt Service | B25: =IF(B21=0,0,PMT(B22/12,B23*12,-B21)) -> 7980.0281
A26: Annual Debt Service | B26: =B25*12 -> 95760.337
A27: DSCR (Year 1 NOI / Annual DS) | B27: =IF('10-Year Cash Flow'!N2=0,0,IF(B26=0,0,'10-Year Cash Flow'!N2/B26)) -> 1.0334686
A29: Section D - Hold & Exit
A30: Hold Period (years) | B30: 10
A31: Exit Cap Rate | B31: 0.0725
A32: Selling Costs (%) | B32: 0.04
A33: Annual Expense Growth | B33: 0.025
A34: General Vacancy / Credit Loss | B34: 0.05
A35: Reserves (% of EGI) | B35: 0.04

Sheet Rent Roll
A1: Suite / Unit | B1: Tenant Name | C1: Square Feet | D1: % of Total SqFt | E1: Lease Start | F1: Lease End | G1: Remaining (mo) | H1: Base Rent ($/SF/yr) | I1: Base Rent (mo) | J1: Base Rent (annual) | K1: Annual Escalator (%) | L1: NNN (mo) | M1: Total Mo Rent+NNN | N1: Lease Type | O1: Status | P1: Notes
A2: Suite A | B2: Main Street Deli | C2: 2200 | D2: =IF(C2=0,0,C2/'Property Overview'!$B$6) -> 0.26190476 | E2: 2020-01-01 | F2: 2029-12-31 | G2: =IF(F2="","",IFERROR(MAX(0,DATEDIF(TODAY(),F2,"M")),"")) -> 44 | H2: 19 | I2: =IF(C2=0,0,C2*H2/12) -> 3483.3333 | J2: =IF(C2=0,0,C2*H2) -> 41800 | K2: 0.025 | L2: =IF(A2="",0,IFERROR(INDEX('NNN Breakdown'!$H$21:$H$26,MATCH(A2,'NNN Breakdown'!$A$21:$A$26,0)),0)) -> 912.30159 | M2: =IF(C2=0,0,I2+L2) -> 4395.6349 | N2: NNN | O2: Occupied | P2: Strong tenant
A3: Suite B | B3: State Farm Insurance | C3: 1800 | D3: =IF(C3=0,0,C3/'Property Overview'!$B$6) -> 0.21428571 | E3: 2019-06-01 | F3: 2028-05-31 | G3: =IF(F3="","",IFERROR(MAX(0,DATEDIF(TODAY(),F3,"M")),"")) -> 25 | H3: 18 | I3: =IF(C3=0,0,C3*H3/12) -> 2700 | J3: =IF(C3=0,0,C3*H3) -> 32400 | K3: 0.02 | L3: =IF(A3="",0,IFERROR(INDEX('NNN Breakdown'!$H$21:$H$26,MATCH(A3,'NNN Breakdown'!$A$21:$A$26,0)),0)) -> 746.42857 | M3: =IF(C3=0,0,I3+L3) -> 3446.4286 | N3: NNN | O3: Occupied
A4: Suite C | B4: Anytime Fitness | C4: 3200 | D4: =IF(C4=0,0,C4/'Property Overview'!$B$6) -> 0.38095238 | E4: 2021-03-01 | F4: 2031-02-28 | G4: =IF(F4="","",IFERROR(MAX(0,DATEDIF(TODAY(),F4,"M")),"")) -> 58 | H4: 16.5 | I4: =IF(C4=0,0,C4*H4/12) -> 4400 | J4: =IF(C4=0,0,C4*H4) -> 52800 | K4: 0.03 | L4: =IF(A4="",0,IFERROR(INDEX('NNN Breakdown'!$H$21:$H$26,MATCH(A4,'NNN Breakdown'!$A$21:$A$26,0)),0)) -> 1326.9841 | M4: =IF(C4=0,0,I4+L4) -> 5726.9841 | N4: NNN | O4: Occupied
A5: Suite D | B5: (Vacant) | C5: 1200 | D5: =IF(C5=0,0,C5/'Property Overview'!$B$6) -> 0.14285714 | G5: =IF(F5="","",IFERROR(MAX(0,DATEDIF(TODAY(),F5,"M")),"")) | H5: 20 | I5: =IF(C5=0,0,C5*H5/12) -> 2000 | J5: =IF(C5=0,0,C5*H5) -> 24000 | K5: 0 | L5: =IF(A5="",0,IFERROR(INDEX('NNN Breakdown'!$H$21:$H$26,MATCH(A5,'NNN Breakdown'!$A$21:$A$26,0)),0)) -> 0 | M5: =IF(C5=0,0,I5+L5) -> 2000 | N5: NNN | O5: Vacant | P5: Asking rate
D6: =IF(C6=0,0,C6/'Property Overview'!$B$6) -> 0 | G6: =IF(F6="","",IFERROR(MAX(0,DATEDIF(TODAY(),F6,"M")),"")) | I6: =IF(C6=0,0,C6*H6/12) -> 0 | J6: =IF(C6=0,0,C6*H6) -> 0 | L6: =IF(A6="",0,IFERROR(INDEX('NNN Breakdown'!$H$21:$H$26,MATCH(A6,'NNN Breakdown'!$A$21:$A$26,0)),0)) -> 0 | M6: =IF(C6=0,0,I6+L6) -> 0 | N6: NNN | O6: Vacant
D7: =IF(C7=0,0,C7/'Property Overview'!$B$6) -> 0 | G7: =IF(F7="","",IFERROR(MAX(0,DATEDIF(TODAY(),F7,"M")),"")) | I7: =IF(C7=0,0,C7*H7/12) -> 0 | J7: =IF(C7=0,0,C7*H7) -> 0 | L7: =IF(A7="",0,IFERROR(INDEX('NNN Breakdown'!$H$21:$H$26,MATCH(A7,'NNN Breakdown'!$A$21:$A$26,0)),0)) -> 0 | M7: =IF(C7=0,0,I7+L7) -> 0 | N7: NNN | O7: Vacant
A9: Total Occupied SqFt | B9: =SUMIFS(C2:C7,O2:O7,"Occupied") -> 7200
A10: Occupancy Rate | B10: =IF('Property Overview'!$B$6=0,0,B9/'Property Overview'!$B$6) -> 0.85714286
A11: Total Base Rent (annual, occupied) | B11: =SUMIFS(J2:J7,O2:O7,"Occupied") -> 127000
A12: Avg Rent / SqFt (occupied) | B12: =IF(B9=0,0,B11/B9) -> 17.638889
A13: Blended escalator (wt. by occupied base rent) | B13: =IF(B11=0,0,SUMPRODUCT((O2:O7="Occupied")*J2:J7,K2:K7)/B11) -> 0.02580315

Sheet NNN Breakdown
A1: NNN Breakdown
A2: Total property operating expenses (recoverable)
A3: Property Taxes (annual) | B3: 22400
A4: Property Insurance (annual) | B4: 6800
A5: CAM (annual) | B5: 12600
A6: Total Recoverable Expenses | B6: =B3+B4+B5 -> 41800
A7: Management Fee (% of EGI) | B7: 0.05
A9: CAM detail
A10: Landscaping / Lawn | B10: 3600
A11: Snow Removal | B11: 1800
A12: Parking Lot Maintenance | B12: 1500
A13: Common Area Cleaning | B13: 2400
A14: Exterior Lighting | B14: 600
A15: Trash / Waste Removal | B15: 1800
A16: Miscellaneous | B16: 900
A17: CAM lines sum (check) | B17: =SUM(B10:B16) -> 12600
A19: Tenant NNN allocation
A20: Suite | B20: SqFt | C20: Pro-rata share | D20: Taxes share | E20: Insurance share | F20: CAM share | G20: Total NNN (annual) | H20: Total NNN (monthly)
A21: ='Rent Roll'!A2 -> Suite A | B21: ='Rent Roll'!C2 -> 2200 | C21: =IF('Rent Roll'!C2=0,0,'Rent Roll'!C2/'Property Overview'!$B$6) -> 0.26190476 | D21: =IF(OR('Rent Roll'!$O2<>"Occupied",'Rent Roll'!$C2=0),0,$B$3*('Rent Roll'!$C2/'Property Overview'!$B$6)) -> 5866.6667 | E21: =IF(OR('Rent Roll'!$O2<>"Occupied",'Rent Roll'!$C2=0),0,$B$4*('Rent Roll'!$C2/'Property Overview'!$B$6)) -> 1780.9524 | F21: =IF(OR('Rent Roll'!$O2<>"Occupied",'Rent Roll'!$C2=0),0,$B$5*('Rent Roll'!$C2/'Property Overview'!$B$6)) -> 3300 | G21: =SUM(D21:F21) -> 10947.619 | H21: =IF(G21=0,0,G21/12) -> 912.30159
A22: ='Rent Roll'!A3 -> Suite B | B22: ='Rent Roll'!C3 -> 1800 | C22: =IF('Rent Roll'!C3=0,0,'Rent Roll'!C3/'Property Overview'!$B$6) -> 0.21428571 | D22: =IF(OR('Rent Roll'!$O3<>"Occupied",'Rent Roll'!$C3=0),0,$B$3*('Rent Roll'!$C3/'Property Overview'!$B$6)) -> 4800 | E22: =IF(OR('Rent Roll'!$O3<>"Occupied",'Rent Roll'!$C3=0),0,$B$4*('Rent Roll'!$C3/'Property Overview'!$B$6)) -> 1457.1429 | F22: =IF(OR('Rent Roll'!$O3<>"Occupied",'Rent Roll'!$C3=0),0,$B$5*('Rent Roll'!$C3/'Property Overview'!$B$6)) -> 2700 | G22: =SUM(D22:F22) -> 8957.1429 | H22: =IF(G22=0,0,G22/12) -> 746.42857
A23: ='Rent Roll'!A4 -> Suite C | B23: ='Rent Roll'!C4 -> 3200 | C23: =IF('Rent Roll'!C4=0,0,'Rent Roll'!C4/'Property Overview'!$B$6) -> 0.38095238 | D23: =IF(OR('Rent Roll'!$O4<>"Occupied",'Rent Roll'!$C4=0),0,$B$3*('Rent Roll'!$C4/'Property Overview'!$B$6)) -> 8533.3333 | E23: =IF(OR('Rent Roll'!$O4<>"Occupied",'Rent Roll'!$C4=0),0,$B$4*('Rent Roll'!$C4/'Property Overview'!$B$6)) -> 2590.4762 | F23: =IF(OR('Rent Roll'!$O4<>"Occupied",'Rent Roll'!$C4=0),0,$B$5*('Rent Roll'!$C4/'Property Overview'!$B$6)) -> 4800 | G23: =SUM(D23:F23) -> 15923.81 | H23: =IF(G23=0,0,G23/12) -> 1326.9841
A24: ='Rent Roll'!A5 -> Suite D | B24: ='Rent Roll'!C5 -> 1200 | C24: =IF('Rent Roll'!C5=0,0,'Rent Roll'!C5/'Property Overview'!$B$6) -> 0.14285714 | D24: =IF(OR('Rent Roll'!$O5<>"Occupied",'Rent Roll'!$C5=0),0,$B$3*('Rent Roll'!$C5/'Property Overview'!$B$6)) -> 0 | E24: =IF(OR('Rent Roll'!$O5<>"Occupied",'Rent Roll'!$C5=0),0,$B$4*('Rent Roll'!$C5/'Property Overview'!$B$6)) -> 0 | F24: =IF(OR('Rent Roll'!$O5<>"Occupied",'Rent Roll'!$C5=0),0,$B$5*('Rent Roll'!$C5/'Property Overview'!$B$6)) -> 0 | G24: =SUM(D24:F24) -> 0 | H24: =IF(G24=0,0,G24/12) -> 0
A25: ='Rent Roll'!A6 -> 0 | B25: ='Rent Roll'!C6 -> 0 | C25: =IF('Rent Roll'!C6=0,0,'Rent Roll'!C6/'Property Overview'!$B$6) -> 0 | D25: =IF(OR('Rent Roll'!$O6<>"Occupied",'Rent Roll'!$C6=0),0,$B$3*('Rent Roll'!$C6/'Property Overview'!$B$6)) -> 0 | E25: =IF(OR('Rent Roll'!$O6<>"Occupied",'Rent Roll'!$C6=0),0,$B$4*('Rent Roll'!$C6/'Property Overview'!$B$6)) -> 0 | F25: =IF(OR('Rent Roll'!$O6<>"Occupied",'Rent Roll'!$C6=0),0,$B$5*('Rent Roll'!$C6/'Property Overview'!$B$6)) -> 0 | G25: =SUM(D25:F25) -> 0 | H25: =IF(G25=0,0,G25/12) -> 0
A26: ='Rent Roll'!A7 -> 0 | B26: ='Rent Roll'!C7 -> 0 | C26: =IF('Rent Roll'!C7=0,0,'Rent Roll'!C7/'Property Overview'!$B$6) -> 0 | D26: =IF(OR('Rent Roll'!$O7<>"Occupied",'Rent Roll'!$C7=0),0,$B$3*('Rent Roll'!$C7/'Property Overview'!$B$6)) -> 0 | E26: =IF(OR('Rent Roll'!$O7<>"Occupied",'Rent Roll'!$C7=0),0,$B$4*('Rent Roll'!$C7/'Property Overview'!$B$6)) -> 0 | F26: =IF(OR('Rent Roll'!$O7<>"Occupied",'Rent Roll'!$C7=0),0,$B$5*('Rent Roll'!$C7/'Property Overview'!$B$6)) -> 0 | G26: =SUM(D26:F26) -> 0 | H26: =IF(G26=0,0,G26/12) -> 0
A28: Total NNN recovered (annual) | B28: =SUM(G21:G26) -> 35828.571
A29: Unrecovered NNN (landlord) | B29: =B6-B28 -> 5971.4286
A30: Recovery rate | B30: =IF(B6=0,0,B28/B6) -> 0.85714286

Sheet 10-Year Cash Flow
A1: Year | B1: Calendar Yr | C1: Base Rent (gross) | D1: NNN Recovery | E1: Gross Potential Rent | F1: Vacancy / Credit Loss | G1: EGI | H1: Property Taxes | I1: Insurance | J1: CAM | K1: Management Fee | L1: Reserves | M1: Total Operating Expenses | N1: NOI | O1: Debt Service | P1: CF Before Tax | Q1: DSCR | R1: Cash-on-Cash | S1: Cap Rate (on purchase)
A2: 1 | B2: 2025 | C2: =IF(A2=1,'Rent Roll'!$B$11,'Rent Roll'!$B$11*POWER(1+'Rent Roll'!$B$13,A2-1)) -> 127000 | D2: =IF(A2=1,'NNN Breakdown'!$B$28,'NNN Breakdown'!$B$28*POWER(1+'Property Overview'!$B$33,A2-1)) -> 35828.571 | E2: =C2+D2 -> 162828.57 | F2: =-E2*'Property Overview'!$B$34 -> -8141.4286 | G2: =E2+F2 -> 154687.14 | H2: =IF(A2=1,'NNN Breakdown'!$B$3,'NNN Breakdown'!$B$3*POWER(1+'Property Overview'!$B$33,A2-1)) -> 22400 | I2: =IF(A2=1,'NNN Breakdown'!$B$4,'NNN Breakdown'!$B$4*POWER(1+'Property Overview'!$B$33,A2-1)) -> 6800 | J2: =IF(A2=1,'NNN Breakdown'!$B$5,'NNN Breakdown'!$B$5*POWER(1+'Property Overview'!$B$33,A2-1)) -> 12600 | K2: =G2*'NNN Breakdown'!$B$7 -> 7734.3571 | L2: =G2*'Property Overview'!$B$35 -> 6187.4857 | M2: =SUM(H2:L2) -> 55721.843 | N2: =G2-M2 -> 98965.3 | O2: ='Property Overview'!$B$26 -> 95760.337 | P2: =N2-O2 -> 3204.9626 | Q2: =IF(O2=0,0,N2/O2) -> 1.0334686 | R2: =IF('Property Overview'!$B$20+'Property Overview'!$B$14+'Property Overview'!$B$15=0,0,P2/('Property Overview'!$B$20+'Property Overview'!$B$14+'Property Overview'!$B$15)) -> 0.0059571796 | S2: =IF('Property Overview'!$B$12=0,0,N2/'Property Overview'!$B$12) -> 0.05997897
A3: 2 | B3: 2026 | C3: =IF(A3=1,'Rent Roll'!$B$11,'Rent Roll'!$B$11*POWER(1+'Rent Roll'!$B$13,A3-1)) -> 130277 | D3: =IF(A3=1,'NNN Breakdown'!$B$28,'NNN Breakdown'!$B$28*POWER(1+'Property Overview'!$B$33,A3-1)) -> 36724.286 | E3: =C3+D3 -> 167001.29 | F3: =-E3*'Property Overview'!$B$34 -> -8350.0643 | G3: =E3+F3 -> 158651.22 | H3: =IF(A3=1,'NNN Breakdown'!$B$3,'NNN Breakdown'!$B$3*POWER(1+'Property Overview'!$B$33,A3-1)) -> 22960 | I3: =IF(A3=1,'NNN Breakdown'!$B$4,'NNN Breakdown'!$B$4*POWER(1+'Property Overview'!$B$33,A3-1)) -> 6970 | J3: =IF(A3=1,'NNN Breakdown'!$B$5,'NNN Breakdown'!$B$5*POWER(1+'Property Overview'!$B$33,A3-1)) -> 12915 | K3: =G3*'NNN Breakdown'!$B$7 -> 7932.5611 | L3: =G3*'Property Overview'!$B$35 -> 6346.0489 | M3: =SUM(H3:L3) -> 57123.61 | N3: =G3-M3 -> 101527.61 | O3: ='Property Overview'!$B$26 -> 95760.337 | P3: =N3-O3 -> 5767.2741 | Q3: =IF(O3=0,0,N3/O3) -> 1.0602261 | R3: =IF('Property Overview'!$B$20+'Property Overview'!$B$14+'Property Overview'!$B$15=0,0,P3/('Property Overview'!$B$20+'Property Overview'!$B$14+'Property Overview'!$B$15)) -> 0.01071984 | S3: =IF('Property Overview'!$B$12=0,0,N3/'Property Overview'!$B$12) -> 0.061531886
A4: 3 | B4: 2027 | C4: =IF(A4=1,'Rent Roll'!$B$11,'Rent Roll'!$B$11*POWER(1+'Rent Roll'!$B$13,A4-1)) -> 133638.56 | D4: =IF(A4=1,'NNN Breakdown'!$B$28,'NNN Breakdown'!$B$28*POWER(1+'Property Overview'!$B$33,A4-1)) -> 37642.393 | E4: =C4+D4 -> 171280.95 | F4: =-E4*'Property Overview'!$B$34 -> -8564.0475 | G4: =E4+F4 -> 162716.9 | H4: =IF(A4=1,'NNN Breakdown'!$B$3,'NNN Breakdown'!$B$3*POWER(1+'Property Overview'!$B$33,A4-1)) -> 23534 | I4: =IF(A4=1,'NNN Breakdown'!$B$4,'NNN Breakdown'!$B$4*POWER(1+'Property Overview'!$B$33,A4-1)) -> 7144.25 | J4: =IF(A4=1,'NNN Breakdown'!$B$5,'NNN Breakdown'!$B$5*POWER(1+'Property Overview'!$B$33,A4-1)) -> 13237.875 | K4: =G4*'NNN Breakdown'!$B$7 -> 8135.8451 | L4: =G4*'Property Overview'!$B$35 -> 6508.6761 | M4: =SUM(H4:L4) -> 58560.646 | N4: =G4-M4 -> 104156.26 | O4: ='Property Overview'!$B$26 -> 95760.337 | P4: =N4-O4 -> 8395.9187 | Q4: =IF(O4=0,0,N4/O4) -> 1.0876764 | R4: =IF('Property Overview'!$B$20+'Property Overview'!$B$14+'Property Overview'!$B$15=0,0,P4/('Property Overview'!$B$20+'Property Overview'!$B$14+'Property Overview'!$B$15)) -> 0.015605797 | S4: =IF('Property Overview'!$B$12=0,0,N4/'Property Overview'!$B$12) -> 0.063125004
A5: 4 | B5: 2028 | C5: =IF(A5=1,'Rent Roll'!$B$11,'Rent Roll'!$B$11*POWER(1+'Rent Roll'!$B$13,A5-1)) -> 137086.85 | D5: =IF(A5=1,'NNN Breakdown'!$B$28,'NNN Breakdown'!$B$28*POWER(1+'Property Overview'!$B$33,A5-1)) -> 38583.453 | E5: =C5+D5 -> 175670.31 | F5: =-E5*'Property Overview'!$B$34 -> -8783.5153 | G5: =E5+F5 -> 166886.79 | H5: =IF(A5=1,'NNN Breakdown'!$B$3,'NNN Breakdown'!$B$3*POWER(1+'Property Overview'!$B$33,A5-1)) -> 24122.35 | I5: =IF(A5=1,'NNN Breakdown'!$B$4,'NNN Breakdown'!$B$4*POWER(1+'Property Overview'!$B$33,A5-1)) -> 7322.8562 | J5: =IF(A5=1,'NNN Breakdown'!$B$5,'NNN Breakdown'!$B$5*POWER(1+'Property Overview'!$B$33,A5-1)) -> 13568.822 | K5: =G5*'NNN Breakdown'!$B$7 -> 8344.3395 | L5: =G5*'Property Overview'!$B$35 -> 6675.4716 | M5: =SUM(H5:L5) -> 60033.839 | N5: =G5-M5 -> 106852.95 | O5: ='Property Overview'!$B$26 -> 95760.337 | P5: =N5-O5 -> 11092.613 | Q5: =IF(O5=0,0,N5/O5) -> 1.1158372 | R5: =IF('Property Overview'!$B$20+'Property Overview'!$B$14+'Property Overview'!$B$15=0,0,P5/('Property Overview'!$B$20+'Property Overview'!$B$14+'Property Overview'!$B$15)) -> 0.020618241 | S5: =IF('Property Overview'!$B$12=0,0,N5/'Property Overview'!$B$12) -> 0.064759364
A6: 5 | B6: 2029 | C6: =IF(A6=1,'Rent Roll'!$B$11,'Rent Roll'!$B$11*POWER(1+'Rent Roll'!$B$13,A6-1)) -> 140624.13 | D6: =IF(A6=1,'NNN Breakdown'!$B$28,'NNN Breakdown'!$B$28*POWER(1+'Property Overview'!$B$33,A6-1)) -> 39548.039 | E6: =C6+D6 -> 180172.16 | F6: =-E6*'Property Overview'!$B$34 -> -9008.6082 | G6: =E6+F6 -> 171163.56 | H6: =IF(A6=1,'NNN Breakdown'!$B$3,'NNN Breakdown'!$B$3*POWER(1+'Property Overview'!$B$33,A6-1)) -> 24725.409 | I6: =IF(A6=1,'NNN Breakdown'!$B$4,'NNN Breakdown'!$B$4*POWER(1+'Property Overview'!$B$33,A6-1)) -> 7505.9277 | J6: =IF(A6=1,'NNN Breakdown'!$B$5,'NNN Breakdown'!$B$5*POWER(1+'Property Overview'!$B$33,A6-1)) -> 13908.042 | K6: =G6*'NNN Breakdown'!$B$7 -> 8558.1778 | L6: =G6*'Property Overview'!$B$35 -> 6846.5422 | M6: =SUM(H6:L6) -> 61544.099 | N6: =G6-M6 -> 109619.46 | O6: ='Property Overview'!$B$26 -> 95760.337 | P6: =N6-O6 -> 13859.12 | Q6: =IF(O6=0,0,N6/O6) -> 1.1447271 | R6: =IF('Property Overview'!$B$20+'Property Overview'!$B$14+'Property Overview'!$B$15=0,0,P6/('Property Overview'!$B$20+'Property Overview'!$B$14+'Property Overview'!$B$15)) -> 0.025760446 | S6: =IF('Property Overview'!$B$12=0,0,N6/'Property Overview'!$B$12) -> 0.066436035
A7: 6 | B7: 2030 | C7: =IF(A7=1,'Rent Roll'!$B$11,'Rent Roll'!$B$11*POWER(1+'Rent Roll'!$B$13,A7-1)) -> 144252.67 | D7: =IF(A7=1,'NNN Breakdown'!$B$28,'NNN Breakdown'!$B$28*POWER(1+'Property Overview'!$B$33,A7-1)) -> 40536.74 | E7: =C7+D7 -> 184789.41 | F7: =-E7*'Property Overview'!$B$34 -> -9239.4705 | G7: =E7+F7 -> 175549.94 | H7: =IF(A7=1,'NNN Breakdown'!$B$3,'NNN Breakdown'!$B$3*POWER(1+'Property Overview'!$B$33,A7-1)) -> 25343.544 | I7: =IF(A7=1,'NNN Breakdown'!$B$4,'NNN Breakdown'!$B$4*POWER(1+'Property Overview'!$B$33,A7-1)) -> 7693.5758 | J7: =IF(A7=1,'NNN Breakdown'!$B$5,'NNN Breakdown'!$B$5*POWER(1+'Property Overview'!$B$33,A7-1)) -> 14255.743 | K7: =G7*'NNN Breakdown'!$B$7 -> 8777.497 | L7: =G7*'Property Overview'!$B$35 -> 7021.9976 | M7: =SUM(H7:L7) -> 63092.358 | N7: =G7-M7 -> 112457.58 | O7: ='Property Overview'!$B$26 -> 95760.337 | P7: =N7-O7 -> 16697.245 | Q7: =IF(O7=0,0,N7/O7) -> 1.1743649 | R7: =IF('Property Overview'!$B$20+'Property Overview'!$B$14+'Property Overview'!$B$15=0,0,P7/('Property Overview'!$B$20+'Property Overview'!$B$14+'Property Overview'!$B$15)) -> 0.031035771 | S7: =IF('Property Overview'!$B$12=0,0,N7/'Property Overview'!$B$12) -> 0.06815611
A8: 7 | B8: 2031 | C8: =IF(A8=1,'Rent Roll'!$B$11,'Rent Roll'!$B$11*POWER(1+'Rent Roll'!$B$13,A8-1)) -> 147974.84 | D8: =IF(A8=1,'NNN Breakdown'!$B$28,'NNN Breakdown'!$B$28*POWER(1+'Property Overview'!$B$33,A8-1)) -> 41550.158 | E8: =C8+D8 -> 189525 | F8: =-E8*'Property Overview'!$B$34 -> -9476.2501 | G8: =E8+F8 -> 180048.75 | H8: =IF(A8=1,'NNN Breakdown'!$B$3,'NNN Breakdown'!$B$3*POWER(1+'Property Overview'!$B$33,A8-1)) -> 25977.133 | I8: =IF(A8=1,'NNN Breakdown'!$B$4,'NNN Breakdown'!$B$4*POWER(1+'Property Overview'!$B$33,A8-1)) -> 7885.9152 | J8: =IF(A8=1,'NNN Breakdown'!$B$5,'NNN Breakdown'!$B$5*POWER(1+'Property Overview'!$B$33,A8-1)) -> 14612.137 | K8: =G8*'NNN Breakdown'!$B$7 -> 9002.4376 | L8: =G8*'Property Overview'!$B$35 -> 7201.9501 | M8: =SUM(H8:L8) -> 64679.573 | N8: =G8-M8 -> 115369.18 | O8: ='Property Overview'!$B$26 -> 95760.337 | P8: =N8-O8 -> 19608.842 | Q8: =IF(O8=0,0,N8/O8) -> 1.20477 | R8: =IF('Property Overview'!$B$20+'Property Overview'!$B$14+'Property Overview'!$B$15=0,0,P8/('Property Overview'!$B$20+'Property Overview'!$B$14+'Property Overview'!$B$15)) -> 0.036447662 | S8: =IF('Property Overview'!$B$12=0,0,N8/'Property Overview'!$B$12) -> 0.069920715
A9: 8 | B9: 2032 | C9: =IF(A9=1,'Rent Roll'!$B$11,'Rent Roll'!$B$11*POWER(1+'Rent Roll'!$B$13,A9-1)) -> 151793.06 | D9: =IF(A9=1,'NNN Breakdown'!$B$28,'NNN Breakdown'!$B$28*POWER(1+'Property Overview'!$B$33,A9-1)) -> 42588.912 | E9: =C9+D9 -> 194381.97 | F9: =-E9*'Property Overview'!$B$34 -> -9719.0987 | G9: =E9+F9 -> 184662.87 | H9: =IF(A9=1,'NNN Breakdown'!$B$3,'NNN Breakdown'!$B$3*POWER(1+'Property Overview'!$B$33,A9-1)) -> 26626.561 | I9: =IF(A9=1,'NNN Breakdown'!$B$4,'NNN Breakdown'!$B$4*POWER(1+'Property Overview'!$B$33,A9-1)) -> 8083.0631 | J9: =IF(A9=1,'NNN Breakdown'!$B$5,'NNN Breakdown'!$B$5*POWER(1+'Property Overview'!$B$33,A9-1)) -> 14977.44 | K9: =G9*'NNN Breakdown'!$B$7 -> 9233.1437 | L9: =G9*'Property Overview'!$B$35 -> 7386.515 | M9: =SUM(H9:L9) -> 66306.723 | N9: =G9-M9 -> 118356.15 | O9: ='Property Overview'!$B$26 -> 95760.337 | P9: =N9-O9 -> 22595.814 | Q9: =IF(O9=0,0,N9/O9) -> 1.2359621 | R9: =IF('Property Overview'!$B$20+'Property Overview'!$B$14+'Property Overview'!$B$15=0,0,P9/('Property Overview'!$B$20+'Property Overview'!$B$14+'Property Overview'!$B$15)) -> 0.041999654 | S9: =IF('Property Overview'!$B$12=0,0,N9/'Property Overview'!$B$12) -> 0.071731001
A10: 9 | B10: 2033 | C10: =IF(A10=1,'Rent Roll'!$B$11,'Rent Roll'!$B$11*POWER(1+'Rent Roll'!$B$13,A10-1)) -> 155709.8 | D10: =IF(A10=1,'NNN Breakdown'!$B$28,'NNN Breakdown'!$B$28*POWER(1+'Property Overview'!$B$33,A10-1)) -> 43653.635 | E10: =C10+D10 -> 199363.44 | F10: =-E10*'Property Overview'!$B$34 -> -9968.1718 | G10: =E10+F10 -> 189395.26 | H10: =IF(A10=1,'NNN Breakdown'!$B$3,'NNN Breakdown'!$B$3*POWER(1+'Property Overview'!$B$33,A10-1)) -> 27292.225 | I10: =IF(A10=1,'NNN Breakdown'!$B$4,'NNN Breakdown'!$B$4*POWER(1+'Property Overview'!$B$33,A10-1)) -> 8285.1397 | J10: =IF(A10=1,'NNN Breakdown'!$B$5,'NNN Breakdown'!$B$5*POWER(1+'Property Overview'!$B$33,A10-1)) -> 15351.877 | K10: =G10*'NNN Breakdown'!$B$7 -> 9469.7632 | L10: =G10*'Property Overview'!$B$35 -> 7575.8105 | M10: =SUM(H10:L10) -> 67974.815 | N10: =G10-M10 -> 121420.45 | O10: ='Property Overview'!$B$26 -> 95760.337 | P10: =N10-O10 -> 25660.111 | Q10: =IF(O10=0,0,N10/O10) -> 1.2679618 | R10: =IF('Property Overview'!$B$20+'Property Overview'!$B$14+'Property Overview'!$B$15=0,0,P10/('Property Overview'!$B$20+'Property Overview'!$B$14+'Property Overview'!$B$15)) -> 0.047695374 | S10: =IF('Property Overview'!$B$12=0,0,N10/'Property Overview'!$B$12) -> 0.073588151
A11: 10 | B11: 2034 | C11: =IF(A11=1,'Rent Roll'!$B$11,'Rent Roll'!$B$11*POWER(1+'Rent Roll'!$B$13,A11-1)) -> 159727.6 | D11: =IF(A11=1,'NNN Breakdown'!$B$28,'NNN Breakdown'!$B$28*POWER(1+'Property Overview'!$B$33,A11-1)) -> 44744.976 | E11: =C11+D11 -> 204472.58 | F11: =-E11*'Property Overview'!$B$34 -> -10223.629 | G11: =E11+F11 -> 194248.95 | H11: =IF(A11=1,'NNN Breakdown'!$B$3,'NNN Breakdown'!$B$3*POWER(1+'Property Overview'!$B$33,A11-1)) -> 27974.531 | I11: =IF(A11=1,'NNN Breakdown'!$B$4,'NNN Breakdown'!$B$4*POWER(1+'Property Overview'!$B$33,A11-1)) -> 8492.2682 | J11: =IF(A11=1,'NNN Breakdown'!$B$5,'NNN Breakdown'!$B$5*POWER(1+'Property Overview'!$B$33,A11-1)) -> 15735.673 | K11: =G11*'NNN Breakdown'!$B$7 -> 9712.4475 | L11: =G11*'Property Overview'!$B$35 -> 7769.958 | M11: =SUM(H11:L11) -> 69684.878 | N11: =G11-M11 -> 124564.07 | O11: ='Property Overview'!$B$26 -> 95760.337 | P11: =N11-O11 -> 28803.735 | Q11: =IF(O11=0,0,N11/O11) -> 1.3007898 | R11: =IF('Property Overview'!$B$20+'Property Overview'!$B$14+'Property Overview'!$B$15=0,0,P11/('Property Overview'!$B$20+'Property Overview'!$B$14+'Property Overview'!$B$15)) -> 0.053538541 | S11: =IF('Property Overview'!$B$12=0,0,N11/'Property Overview'!$B$12) -> 0.075493377
A13: Total NOI (10 yr) | B13: =SUM(N2:N11) -> 1113289
A14: Total CF (10 yr) | B14: =SUM(P2:P11) -> 155685.64
A15: Avg Cash-on-Cash | B15: =AVERAGE(R2:R11) -> 0.02893785
A16: Avg DSCR | B16: =AVERAGE(Q2:Q11) -> 1.1625784
A17: NOI growth Y10 vs Y1 | B17: =IF(N2=0,0,N11/N2-1) -> 0.25866412

Sheet Exit & Returns
A1: Exit & Returns
A3: Section A - Exit valuation
A4: Year 10 NOI | B4: ='10-Year Cash Flow'!N11 -> 124564.07
A5: Year 11 projected NOI | B5: ='10-Year Cash Flow'!N11*(1+'Rent Roll'!$B$13) -> 127778.22
A6: Exit cap rate | B6: ='Property Overview'!$B$31 -> 0.0725
A7: Estimated sale price | B7: =B5/B6 -> 1762458.2
A8: Sale price / SqFt | B8: =IF('Property Overview'!$B$6=0,0,B7/'Property Overview'!$B$6) -> 209.81645
A9: Selling costs | B9: =B7*'Property Overview'!$B$32 -> 70498.327
A10: Net sale proceeds (before loan payoff) | B10: =B7-B9 -> 1691959.9
A12: Section B - Loan payoff
A13: Original loan amount | B13: ='Property Overview'!$B$21 -> 1155000
A14: Remaining balance @ Year 10 | B14: =IF(B13=0,0,FV('Property Overview'!$B$22/12,'Property Overview'!$B$30*12,'Property Overview'!$B$25,-B13)) -> 901790.35
A15: Net proceeds after loan payoff | B15: =B10-B14 -> 790169.5
A17: Section C - Total return
A18: Total cash invested (equity) | B18: =('Property Overview'!$B$20+'Property Overview'!$B$14+'Property Overview'!$B$15) -> 538000
A19: Total CF received (10 yr) | B19: ='10-Year Cash Flow'!$B$14 -> 155685.64
A20: Net sale proceeds (after loan) | B20: =B15 -> 790169.5
A21: Total return ($) | B21: =B19+B20-B18 -> 407855.14
A22: Equity multiple | B22: =IF(B18=0,0,(B19+B20)/B18) -> 1.7580951
A23: Avg annual return (simple) | B23: =IF(OR(B18=0,'Property Overview'!$B$30=0),0,B21/B18/'Property Overview'!$B$30) -> 0.075809506
A24: IRR (cash-flow stream) | B24: =IF(Z2=0,0,IRR(Z2:Z12)) -> 0
A26: Section D - Exit cap sensitivity
A27: Exit Cap | B27: Sale Price | C27: Net Proceeds | D27: Equity Multiple | E27: IRR (cash flows)
A28: 0.06 | B28: =$B$5/A28 -> 2129637 | C28: =IF('Property Overview'!$B$20+'Property Overview'!$B$14+'Property Overview'!$B$15=0,0,B28*(1-'Property Overview'!$B$32)-FV('Property Overview'!$B$22/12,'Property Overview'!$B$30*12,'Property Overview'!$B$25,-'Property Overview'!$B$21)) -> 1142661.1 | D28: =IF(('Property Overview'!$B$20+'Property Overview'!$B$14+'Property Overview'!$B$15)=0,0,('10-Year Cash Flow'!$B$14+C28)/('Property Overview'!$B$20+'Property Overview'!$B$14+'Property Overview'!$B$15)) -> 2.413284 | E28: =IF(OR('Property Overview'!$B$20+'Property Overview'!$B$14+'Property Overview'!$B$15=0,ISERROR(IRR(B36:L36))),0,IRR(B36:L36)) -> 0.096648936
A29: 0.065 | B29: =$B$5/A29 -> 1965818.7 | C29: =IF('Property Overview'!$B$20+'Property Overview'!$B$14+'Property Overview'!$B$15=0,0,B29*(1-'Property Overview'!$B$32)-FV('Property Overview'!$B$22/12,'Property Overview'!$B$30*12,'Property Overview'!$B$25,-'Property Overview'!$B$21)) -> 985395.64 | D29: =IF(('Property Overview'!$B$20+'Property Overview'!$B$14+'Property Overview'!$B$15)=0,0,('10-Year Cash Flow'!$B$14+C29)/('Property Overview'!$B$20+'Property Overview'!$B$14+'Property Overview'!$B$15)) -> 2.1209689 | E29: =IF(OR('Property Overview'!$B$20+'Property Overview'!$B$14+'Property Overview'!$B$15=0,ISERROR(IRR(B37:L37))),0,IRR(B37:L37)) -> 0.082313344
A30: 0.07 | B30: =$B$5/A30 -> 1825403.1 | C30: =IF('Property Overview'!$B$20+'Property Overview'!$B$14+'Property Overview'!$B$15=0,0,B30*(1-'Property Overview'!$B$32)-FV('Property Overview'!$B$22/12,'Property Overview'!$B$30*12,'Property Overview'!$B$25,-'Property Overview'!$B$21)) -> 850596.64 | D30: =IF(('Property Overview'!$B$20+'Property Overview'!$B$14+'Property Overview'!$B$15)=0,0,('10-Year Cash Flow'!$B$14+C30)/('Property Overview'!$B$20+'Property Overview'!$B$14+'Property Overview'!$B$15)) -> 1.8704132 | E30: =IF(OR('Property Overview'!$B$20+'Property Overview'!$B$14+'Property Overview'!$B$15=0,ISERROR(IRR(B38:L38))),0,IRR(B38:L38)) -> 0.06844462
A31: 0.0725 | B31: =$B$5/A31 -> 1762458.2 | C31: =IF('Property Overview'!$B$20+'Property Overview'!$B$14+'Property Overview'!$B$15=0,0,B31*(1-'Property Overview'!$B$32)-FV('Property Overview'!$B$22/12,'Property Overview'!$B$30*12,'Property Overview'!$B$25,-'Property Overview'!$B$21)) -> 790169.5 | D31: =IF(('Property Overview'!$B$20+'Property Overview'!$B$14+'Property Overview'!$B$15)=0,0,('10-Year Cash Flow'!$B$14+C31)/('Property Overview'!$B$20+'Property Overview'!$B$14+'Property Overview'!$B$15)) -> 1.7580951 | E31: =IF(OR('Property Overview'!$B$20+'Property Overview'!$B$14+'Property Overview'!$B$15=0,ISERROR(IRR(B39:L39))),0,IRR(B39:L39)) -> 0.061640024
A32: 0.075 | B32: =$B$5/A32 -> 1703709.6 | C32: =IF('Property Overview'!$B$20+'Property Overview'!$B$14+'Property Overview'!$B$15=0,0,B32*(1-'Property Overview'!$B$32)-FV('Property Overview'!$B$22/12,'Property Overview'!$B$30*12,'Property Overview'!$B$25,-'Property Overview'!$B$21)) -> 733770.84 | D32: =IF(('Property Overview'!$B$20+'Property Overview'!$B$14+'Property Overview'!$B$15)=0,0,('10-Year Cash Flow'!$B$14+C32)/('Property Overview'!$B$20+'Property Overview'!$B$14+'Property Overview'!$B$15)) -> 1.6532648 | E32: =IF(OR('Property Overview'!$B$20+'Property Overview'!$B$14+'Property Overview'!$B$15=0,ISERROR(IRR(B40:L40))),0,IRR(B40:L40)) -> 0.054899836
A33: 0.08 | B33: =$B$5/A33 -> 1597227.7 | C33: =IF('Property Overview'!$B$20+'Property Overview'!$B$14+'Property Overview'!$B$15=0,0,B33*(1-'Property Overview'!$B$32)-FV('Property Overview'!$B$22/12,'Property Overview'!$B$30*12,'Property Overview'!$B$25,-'Property Overview'!$B$21)) -> 631548.27 | D33: =IF(('Property Overview'!$B$20+'Property Overview'!$B$14+'Property Overview'!$B$15)=0,0,('10-Year Cash Flow'!$B$14+C33)/('Property Overview'!$B$20+'Property Overview'!$B$14+'Property Overview'!$B$15)) -> 1.46326 | E33: =IF(OR('Property Overview'!$B$20+'Property Overview'!$B$14+'Property Overview'!$B$15=0,ISERROR(IRR(B41:L41))),0,IRR(B41:L41)) -> 0.041550148
A34: 0.085 | B34: =$B$5/A34 -> 1503273.2 | C34: =IF('Property Overview'!$B$20+'Property Overview'!$B$14+'Property Overview'!$B$15=0,0,B34*(1-'Property Overview'!$B$32)-FV('Property Overview'!$B$22/12,'Property Overview'!$B$30*12,'Property Overview'!$B$25,-'Property Overview'!$B$21)) -> 541351.88 | D34: =IF(('Property Overview'!$B$20+'Property Overview'!$B$14+'Property Overview'!$B$15)=0,0,('10-Year Cash Flow'!$B$14+C34)/('Property Overview'!$B$20+'Property Overview'!$B$14+'Property Overview'!$B$15)) -> 1.2956088 | E34: =IF(OR('Property Overview'!$B$20+'Property Overview'!$B$14+'Property Overview'!$B$15=0,ISERROR(IRR(B42:L42))),0,IRR(B42:L42)) -> 0.028273301
B36: =-('Property Overview'!$B$20+'Property Overview'!$B$14+'Property Overview'!$B$15) -> -538000 | C36: ='10-Year Cash Flow'!P2 -> 3204.9626 | D36: ='10-Year Cash Flow'!P3 -> 5767.2741 | E36: ='10-Year Cash Flow'!P4 -> 8395.9187 | F36: ='10-Year Cash Flow'!P5 -> 11092.613 | G36: ='10-Year Cash Flow'!P6 -> 13859.12 | H36: ='10-Year Cash Flow'!P7 -> 16697.245 | I36: ='10-Year Cash Flow'!P8 -> 19608.842 | J36: ='10-Year Cash Flow'!P9 -> 22595.814 | K36: ='10-Year Cash Flow'!P10 -> 25660.111 | L36: ='10-Year Cash Flow'!P11+C28 -> 1171464.9
B37: =-('Property Overview'!$B$20+'Property Overview'!$B$14+'Property Overview'!$B$15) -> -538000 | C37: ='10-Year Cash Flow'!P2 -> 3204.9626 | D37: ='10-Year Cash Flow'!P3 -> 5767.2741 | E37: ='10-Year Cash Flow'!P4 -> 8395.9187 | F37: ='10-Year Cash Flow'!P5 -> 11092.613 | G37: ='10-Year Cash Flow'!P6 -> 13859.12 | H37: ='10-Year Cash Flow'!P7 -> 16697.245 | I37: ='10-Year Cash Flow'!P8 -> 19608.842 | J37: ='10-Year Cash Flow'!P9 -> 22595.814 | K37: ='10-Year Cash Flow'!P10 -> 25660.111 | L37: ='10-Year Cash Flow'!P11+C29 -> 1014199.4
B38: =-('Property Overview'!$B$20+'Property Overview'!$B$14+'Property Overview'!$B$15) -> -538000 | C38: ='10-Year Cash Flow'!P2 -> 3204.9626 | D38: ='10-Year Cash Flow'!P3 -> 5767.2741 | E38: ='10-Year Cash Flow'!P4 -> 8395.9187 | F38: ='10-Year Cash Flow'!P5 -> 11092.613 | G38: ='10-Year Cash Flow'!P6 -> 13859.12 | H38: ='10-Year Cash Flow'!P7 -> 16697.245 | I38: ='10-Year Cash Flow'!P8 -> 19608.842 | J38: ='10-Year Cash Flow'!P9 -> 22595.814 | K38: ='10-Year Cash Flow'!P10 -> 25660.111 | L38: ='10-Year Cash Flow'!P11+C30 -> 879400.38
B39: =-('Property Overview'!$B$20+'Property Overview'!$B$14+'Property Overview'!$B$15) -> -538000 | C39: ='10-Year Cash Flow'!P2 -> 3204.9626 | D39: ='10-Year Cash Flow'!P3 -> 5767.2741 | E39: ='10-Year Cash Flow'!P4 -> 8395.9187 | F39: ='10-Year Cash Flow'!P5 -> 11092.613 | G39: ='10-Year Cash Flow'!P6 -> 13859.12 | H39: ='10-Year Cash Flow'!P7 -> 16697.245 | I39: ='10-Year Cash Flow'!P8 -> 19608.842 | J39: ='10-Year Cash Flow'!P9 -> 22595.814 | K39: ='10-Year Cash Flow'!P10 -> 25660.111 | L39: ='10-Year Cash Flow'!P11+C31 -> 818973.24
B40: =-('Property Overview'!$B$20+'Property Overview'!$B$14+'Property Overview'!$B$15) -> -538000 | C40: ='10-Year Cash Flow'!P2 -> 3204.9626 | D40: ='10-Year Cash Flow'!P3 -> 5767.2741 | E40: ='10-Year Cash Flow'!P4 -> 8395.9187 | F40: ='10-Year Cash Flow'!P5 -> 11092.613 | G40: ='10-Year Cash Flow'!P6 -> 13859.12 | H40: ='10-Year Cash Flow'!P7 -> 16697.245 | I40: ='10-Year Cash Flow'!P8 -> 19608.842 | J40: ='10-Year Cash Flow'!P9 -> 22595.814 | K40: ='10-Year Cash Flow'!P10 -> 25660.111 | L40: ='10-Year Cash Flow'!P11+C32 -> 762574.58
B41: =-('Property Overview'!$B$20+'Property Overview'!$B$14+'Property Overview'!$B$15) -> -538000 | C41: ='10-Year Cash Flow'!P2 -> 3204.9626 | D41: ='10-Year Cash Flow'!P3 -> 5767.2741 | E41: ='10-Year Cash Flow'!P4 -> 8395.9187 | F41: ='10-Year Cash Flow'!P5 -> 11092.613 | G41: ='10-Year Cash Flow'!P6 -> 13859.12 | H41: ='10-Year Cash Flow'!P7 -> 16697.245 | I41: ='10-Year Cash Flow'!P8 -> 19608.842 | J41: ='10-Year Cash Flow'!P9 -> 22595.814 | K41: ='10-Year Cash Flow'!P10 -> 25660.111 | L41: ='10-Year Cash Flow'!P11+C33 -> 660352
B42: =-('Property Overview'!$B$20+'Property Overview'!$B$14+'Property Overview'!$B$15) -> -538000 | C42: ='10-Year Cash Flow'!P2 -> 3204.9626 | D42: ='10-Year Cash Flow'!P3 -> 5767.2741 | E42: ='10-Year Cash Flow'!P4 -> 8395.9187 | F42: ='10-Year Cash Flow'!P5 -> 11092.613 | G42: ='10-Year Cash Flow'!P6 -> 13859.12 | H42: ='10-Year Cash Flow'!P7 -> 16697.245 | I42: ='10-Year Cash Flow'!P8 -> 19608.842 | J42: ='10-Year Cash Flow'!P9 -> 22595.814 | K42: ='10-Year Cash Flow'!P10 -> 25660.111 | L42: ='10-Year Cash Flow'!P11+C34 -> 570155.61
