Workbook

Sheet Holdings & Settings
A1: Ticker | B1: Starting Shares | C1: Avg Cost / Share | D1: Current Price | E1: Annual Dividend / Share | F1: DRIP? | G1: Current Value | H1: Cost Basis | I1: Annual Income | J1: Yield on Cost
A2: JNJ | B2: 120 | C2: 148.5 | D2: 161.2 | E2: 4.96 | F2: Yes | G2: =B2*D2 -> 19344 | H2: =B2*C2 -> 17820 | I2: =B2*E2 -> 595.2 | J2: =IF(H2=0,0,I2/H2) -> 0.033400673
A3: KO | B3: 200 | C3: 58.1 | D3: 62.3 | E3: 1.94 | F3: Yes | G3: =B3*D3 -> 12460 | H3: =B3*C3 -> 11620 | I3: =B3*E3 -> 388 | J3: =IF(H3=0,0,I3/H3) -> 0.033390706
A4: PG | B4: 95 | C4: 143.4 | D4: 158.1 | E4: 4.03 | F4: No | G4: =B4*D4 -> 15019.5 | H4: =B4*C4 -> 13623 | I4: =B4*E4 -> 382.85 | J4: =IF(H4=0,0,I4/H4) -> 0.028103208
A7: Overview
A8: Total portfolio value | B8: =SUM(G2:G4) -> 46823.5
A9: Total annual income | B9: =SUM(I2:I4) -> 1366.05
A10: Weighted yield on cost | B10: =SUMPRODUCT(J2:J4,H2:H4)/SUM(H2:H4) -> 0.031722128
A11: Monthly run rate | B11: =SUM(I2:I4)/12 -> 113.8375

Sheet Dividend Log
A1: Pay Date | B1: Ticker | C1: Shares at Pay Date | D1: Dividend / Share | E1: Cash Dividend | F1: DRIP Price | G1: Shares Added | H1: Cash Taken | I1: Ending Shares | J1: Notes
A2: 46031 | B2: KO | C2: ='Holdings & Settings'!B3 -> 200 | D2: 0.485 | E2: =C2*D2 -> 97 | F2: 60.2 | G2: =IF('Holdings & Settings'!F3="Yes",E2/F2,0) -> 1.6112957 | H2: =IF('Holdings & Settings'!F3="No",E2,0) -> 0 | I2: =C2+G2 -> 201.6113 | J2: jan
A3: 46080 | B3: PG | C3: ='Holdings & Settings'!B4 -> 95 | D3: 1.007 | E3: =C3*D3 -> 95.665 | F3: 154.1 | G3: =IF('Holdings & Settings'!F4="Yes",E3/F3,0) -> 0 | H3: =IF('Holdings & Settings'!F4="No",E3,0) -> 95.665 | I3: =C3+G3 -> 95
A4: 46093 | B4: JNJ | C4: ='Holdings & Settings'!B2 -> 120 | D4: 1.24 | E4: =C4*D4 -> 148.8 | F4: 159.4 | G4: =IF('Holdings & Settings'!F2="Yes",E4/F4,0) -> 0.93350063 | H4: =IF('Holdings & Settings'!F2="No",E4,0) -> 0 | I4: =C4+G4 -> 120.9335 | J4: cash
A5: 46122 | B5: KO | C5: =I2 -> 201.6113 | D5: 0.485 | E5: =C5*D5 -> 97.781478 | F5: 61 | G5: =IF('Holdings & Settings'!F3="Yes",E5/F5,0) -> 1.6029751 | H5: =IF('Holdings & Settings'!F3="No",E5,0) -> 0 | I5: =C5+G5 -> 203.21427
A6: 46170 | B6: PG | C6: =I3 -> 95 | D6: 1.007 | E6: =C6*D6 -> 95.665 | F6: 156.3 | G6: =IF('Holdings & Settings'!F4="Yes",E6/F6,0) -> 0 | H6: =IF('Holdings & Settings'!F4="No",E6,0) -> 95.665 | I6: =C6+G6 -> 95 | J6: drip
A7: 46184 | B7: JNJ | C7: =I4 -> 120.9335 | D7: 1.24 | E7: =C7*D7 -> 149.95754 | F7: 160.8 | G7: =IF('Holdings & Settings'!F2="Yes",E7/F7,0) -> 0.93257177 | H7: =IF('Holdings & Settings'!F2="No",E7,0) -> 0 | I7: =C7+G7 -> 121.86607
A8: 46214 | B8: KO | C8: =I5 -> 203.21427 | D8: 0.486 | E8: =C8*D8 -> 98.762136 | F8: 61.8 | G8: =IF('Holdings & Settings'!F3="Yes",E8/F8,0) -> 1.5980928 | H8: =IF('Holdings & Settings'!F3="No",E8,0) -> 0 | I8: =C8+G8 -> 204.81236 | J8: tiny raise
A9: 46261 | B9: PG | C9: =I6 -> 95 | D9: 1.007 | E9: =C9*D9 -> 95.665 | F9: 157.2 | G9: =IF('Holdings & Settings'!F4="Yes",E9/F9,0) -> 0 | H9: =IF('Holdings & Settings'!F4="No",E9,0) -> 95.665 | I9: =C9+G9 -> 95
A10: 46275 | B10: JNJ | C10: =I7 -> 121.86607 | D10: 1.24 | E10: =C10*D10 -> 151.11393 | F10: 162.1 | G10: =IF('Holdings & Settings'!F2="Yes",E10/F10,0) -> 0.93222659 | H10: =IF('Holdings & Settings'!F2="No",E10,0) -> 0 | I10: =C10+G10 -> 122.7983
A11: 46305 | B11: KO | C11: =I8 -> 204.81236 | D11: 0.486 | E11: =C11*D11 -> 99.538809 | F11: 62.4 | G11: =IF('Holdings & Settings'!F3="Yes",E11/F11,0) -> 1.5951732 | H11: =IF('Holdings & Settings'!F3="No",E11,0) -> 0 | I11: =C11+G11 -> 206.40754
A12: 46352 | B12: PG | C12: =I9 -> 95 | D12: 1.007 | E12: =C12*D12 -> 95.665 | F12: 158.4 | G12: =IF('Holdings & Settings'!F4="Yes",E12/F12,0) -> 0 | H12: =IF('Holdings & Settings'!F4="No",E12,0) -> 95.665 | I12: =C12+G12 -> 95 | J12: holiday wk
A13: 46366 | B13: JNJ | C13: =I10 -> 122.7983 | D13: 1.24 | E13: =C13*D13 -> 152.26989 | F13: 163 | G13: =IF('Holdings & Settings'!F2="Yes",E13/F13,0) -> 0.93417111 | H13: =IF('Holdings & Settings'!F2="No",E13,0) -> 0 | I13: =C13+G13 -> 123.73247

Sheet Reinvestment History
A1: Month | B1: Dividend Cash Generated | C1: Shares Added | D1: Cumulative Shares Added | E1: Cash Taken | F1: Total Shares Outstanding | H1: Roll-Up
A2: Jan | B2: =SUMPRODUCT((MONTH('Dividend Log'!$A$2:$A$13)=1)*('Dividend Log'!$E$2:$E$13)) -> 97 | C2: =SUMPRODUCT((MONTH('Dividend Log'!$A$2:$A$13)=1)*('Dividend Log'!$G$2:$G$13)) -> 1.6112957 | D2: =C2 -> 1.6112957 | E2: =SUMPRODUCT((MONTH('Dividend Log'!$A$2:$A$13)=1)*('Dividend Log'!$H$2:$H$13)) -> 0 | F2: =SUM('Holdings & Settings'!B2:B4)+D2 -> 416.6113 | H2: Total dividends | I2: =SUM(B2:B13) -> 1377.8838
A3: Feb | B3: =SUMPRODUCT((MONTH('Dividend Log'!$A$2:$A$13)=2)*('Dividend Log'!$E$2:$E$13)) -> 95.665 | C3: =SUMPRODUCT((MONTH('Dividend Log'!$A$2:$A$13)=2)*('Dividend Log'!$G$2:$G$13)) -> 0 | D3: =D2+C3 -> 1.6112957 | E3: =SUMPRODUCT((MONTH('Dividend Log'!$A$2:$A$13)=2)*('Dividend Log'!$H$2:$H$13)) -> 95.665 | F3: =SUM('Holdings & Settings'!B2:B4)+D3 -> 416.6113 | H3: Total shares added | I3: =SUM(C2:C13) -> 10.140007
A4: Mar | B4: =SUMPRODUCT((MONTH('Dividend Log'!$A$2:$A$13)=3)*('Dividend Log'!$E$2:$E$13)) -> 148.8 | C4: =SUMPRODUCT((MONTH('Dividend Log'!$A$2:$A$13)=3)*('Dividend Log'!$G$2:$G$13)) -> 0.93350063 | D4: =D3+C4 -> 2.5447963 | E4: =SUMPRODUCT((MONTH('Dividend Log'!$A$2:$A$13)=3)*('Dividend Log'!$H$2:$H$13)) -> 0 | F4: =SUM('Holdings & Settings'!B2:B4)+D4 -> 417.5448 | H4: Total cash taken | I4: =SUM(E2:E13) -> 382.66
A5: Apr | B5: =SUMPRODUCT((MONTH('Dividend Log'!$A$2:$A$13)=4)*('Dividend Log'!$E$2:$E$13)) -> 97.781478 | C5: =SUMPRODUCT((MONTH('Dividend Log'!$A$2:$A$13)=4)*('Dividend Log'!$G$2:$G$13)) -> 1.6029751 | D5: =D4+C5 -> 4.1477714 | E5: =SUMPRODUCT((MONTH('Dividend Log'!$A$2:$A$13)=4)*('Dividend Log'!$H$2:$H$13)) -> 0 | F5: =SUM('Holdings & Settings'!B2:B4)+D5 -> 419.14777
A6: May | B6: =SUMPRODUCT((MONTH('Dividend Log'!$A$2:$A$13)=5)*('Dividend Log'!$E$2:$E$13)) -> 95.665 | C6: =SUMPRODUCT((MONTH('Dividend Log'!$A$2:$A$13)=5)*('Dividend Log'!$G$2:$G$13)) -> 0 | D6: =D5+C6 -> 4.1477714 | E6: =SUMPRODUCT((MONTH('Dividend Log'!$A$2:$A$13)=5)*('Dividend Log'!$H$2:$H$13)) -> 95.665 | F6: =SUM('Holdings & Settings'!B2:B4)+D6 -> 419.14777
A7: Jun | B7: =SUMPRODUCT((MONTH('Dividend Log'!$A$2:$A$13)=6)*('Dividend Log'!$E$2:$E$13)) -> 149.95754 | C7: =SUMPRODUCT((MONTH('Dividend Log'!$A$2:$A$13)=6)*('Dividend Log'!$G$2:$G$13)) -> 0.93257177 | D7: =D6+C7 -> 5.0803431 | E7: =SUMPRODUCT((MONTH('Dividend Log'!$A$2:$A$13)=6)*('Dividend Log'!$H$2:$H$13)) -> 0 | F7: =SUM('Holdings & Settings'!B2:B4)+D7 -> 420.08034
A8: Jul | B8: =SUMPRODUCT((MONTH('Dividend Log'!$A$2:$A$13)=7)*('Dividend Log'!$E$2:$E$13)) -> 98.762136 | C8: =SUMPRODUCT((MONTH('Dividend Log'!$A$2:$A$13)=7)*('Dividend Log'!$G$2:$G$13)) -> 1.5980928 | D8: =D7+C8 -> 6.6784359 | E8: =SUMPRODUCT((MONTH('Dividend Log'!$A$2:$A$13)=7)*('Dividend Log'!$H$2:$H$13)) -> 0 | F8: =SUM('Holdings & Settings'!B2:B4)+D8 -> 421.67844
A9: Aug | B9: =SUMPRODUCT((MONTH('Dividend Log'!$A$2:$A$13)=8)*('Dividend Log'!$E$2:$E$13)) -> 95.665 | C9: =SUMPRODUCT((MONTH('Dividend Log'!$A$2:$A$13)=8)*('Dividend Log'!$G$2:$G$13)) -> 0 | D9: =D8+C9 -> 6.6784359 | E9: =SUMPRODUCT((MONTH('Dividend Log'!$A$2:$A$13)=8)*('Dividend Log'!$H$2:$H$13)) -> 95.665 | F9: =SUM('Holdings & Settings'!B2:B4)+D9 -> 421.67844
A10: Sep | B10: =SUMPRODUCT((MONTH('Dividend Log'!$A$2:$A$13)=9)*('Dividend Log'!$E$2:$E$13)) -> 151.11393 | C10: =SUMPRODUCT((MONTH('Dividend Log'!$A$2:$A$13)=9)*('Dividend Log'!$G$2:$G$13)) -> 0.93222659 | D10: =D9+C10 -> 7.6106625 | E10: =SUMPRODUCT((MONTH('Dividend Log'!$A$2:$A$13)=9)*('Dividend Log'!$H$2:$H$13)) -> 0 | F10: =SUM('Holdings & Settings'!B2:B4)+D10 -> 422.61066
A11: Oct | B11: =SUMPRODUCT((MONTH('Dividend Log'!$A$2:$A$13)=10)*('Dividend Log'!$E$2:$E$13)) -> 99.538809 | C11: =SUMPRODUCT((MONTH('Dividend Log'!$A$2:$A$13)=10)*('Dividend Log'!$G$2:$G$13)) -> 1.5951732 | D11: =D10+C11 -> 9.2058357 | E11: =SUMPRODUCT((MONTH('Dividend Log'!$A$2:$A$13)=10)*('Dividend Log'!$H$2:$H$13)) -> 0 | F11: =SUM('Holdings & Settings'!B2:B4)+D11 -> 424.20584
A12: Nov | B12: =SUMPRODUCT((MONTH('Dividend Log'!$A$2:$A$13)=11)*('Dividend Log'!$E$2:$E$13)) -> 95.665 | C12: =SUMPRODUCT((MONTH('Dividend Log'!$A$2:$A$13)=11)*('Dividend Log'!$G$2:$G$13)) -> 0 | D12: =D11+C12 -> 9.2058357 | E12: =SUMPRODUCT((MONTH('Dividend Log'!$A$2:$A$13)=11)*('Dividend Log'!$H$2:$H$13)) -> 95.665 | F12: =SUM('Holdings & Settings'!B2:B4)+D12 -> 424.20584
A13: Dec | B13: =SUMPRODUCT((MONTH('Dividend Log'!$A$2:$A$13)=12)*('Dividend Log'!$E$2:$E$13)) -> 152.26989 | C13: =SUMPRODUCT((MONTH('Dividend Log'!$A$2:$A$13)=12)*('Dividend Log'!$G$2:$G$13)) -> 0.93417111 | D13: =D12+C13 -> 10.140007 | E13: =SUMPRODUCT((MONTH('Dividend Log'!$A$2:$A$13)=12)*('Dividend Log'!$H$2:$H$13)) -> 0 | F13: =SUM('Holdings & Settings'!B2:B4)+D13 -> 425.14001

Sheet Income & Yield Summary
A1: Starting shares | B1: =SUM('Holdings & Settings'!B2:B4) -> 415
A2: Ending shares | B2: ='Reinvestment History'!F13 -> 425.14001
A3: Total shares added | B3: ='Reinvestment History'!I3 -> 10.140007
A4: Annual income now | B4: =SUM(C10:C12) -> 1396.9937
A5: Weighted yield on cost | B5: =SUMPRODUCT(D10:D12,B10:B12)/SUM(B10:B12) -> 0.033033817
A6: DRIP vs cash annual income | B6: =SUM(C10:C12)-SUM(E10:E12) -> 30.943673
A9: Ticker | B9: Current Shares | C9: Current Annual Income | D9: Yield on Cost | E9: Cash-Take Annual Income
A10: JNJ | B10: ='Dividend Log'!I13 -> 123.73247 | C10: =B10*'Holdings & Settings'!E2 -> 613.71305 | D10: =IF('Holdings & Settings'!H2=0,0,C10/'Holdings & Settings'!H2) -> 0.034439565 | E10: ='Holdings & Settings'!B2*'Holdings & Settings'!E2 -> 595.2
A11: KO | B11: ='Dividend Log'!I11 -> 206.40754 | C11: =B11*'Holdings & Settings'!E3 -> 400.43062 | D11: =IF('Holdings & Settings'!H3=0,0,C11/'Holdings & Settings'!H3) -> 0.034460467 | E11: ='Holdings & Settings'!B3*'Holdings & Settings'!E3 -> 388
A12: PG | B12: ='Dividend Log'!I12 -> 95 | C12: =B12*'Holdings & Settings'!E4 -> 382.85 | D12: =IF('Holdings & Settings'!H4=0,0,C12/'Holdings & Settings'!H4) -> 0.028103208 | E12: ='Holdings & Settings'!B4*'Holdings & Settings'!E4 -> 382.85
