Workbook

Sheet Monthly Expenses
A1: Essential Monthly Expenses
A2: Category | B2: Jan | C2: Feb | D2: Mar | E2: Apr | F2: May | G2: Jun | H2: Jul | I2: Aug | J2: Sep | K2: Oct | L2: Nov | M2: Dec | N2: Annual Total
A3: Rent/Mortgage | B3: 1305 | C3: 1461 | D3: 1325 | E3: 1613 | F3: 1505 | G3: 1297 | H3: 1295 | I3: 1606 | J3: 1344 | K3: 1605 | L3: 1559 | M3: 1502 | N3: =SUM(B3:M3) -> 17417
A4: Utilities | B4: 177 | C4: 165 | D4: 164 | E4: 155 | F4: 148 | G4: 143 | H4: 156 | I4: 154 | J4: 173 | K4: 149 | L4: 155 | M4: 181 | N4: =SUM(B4:M4) -> 1920
A5: Groceries | B5: 414 | C5: 419 | D5: 423 | E5: 449 | F5: 365 | G5: 432 | H5: 348 | I5: 371 | J5: 411 | K5: 378 | L5: 399 | M5: 367 | N5: =SUM(B5:M5) -> 4776
A6: Insurance (Health/Auto/Renters) | B6: 389 | C6: 412 | D6: 434 | E6: 444 | F6: 420 | G6: 405 | H6: 479 | I6: 455 | J6: 426 | K6: 425 | L6: 376 | M6: 382 | N6: =SUM(B6:M6) -> 5047
A7: Transport | B7: 158 | C7: 204 | D7: 198 | E7: 156 | F7: 190 | G7: 173 | H7: 189 | I7: 177 | J7: 171 | K7: 157 | L7: 163 | M7: 176 | N7: =SUM(B7:M7) -> 2112
A8: Medical | B8: 48 | C8: 40 | D8: 44 | E8: 51 | F8: 40 | G8: 44 | H8: 50 | I8: 47 | J8: 51 | K8: 46 | L8: 47 | M8: 41 | N8: =SUM(B8:M8) -> 549
A9: Min Debt Payments | B9: 340 | C9: 353 | D9: 389 | E9: 368 | F9: 337 | G9: 390 | H9: 362 | I9: 373 | J9: 316 | K9: 325 | L9: 360 | M9: 343 | N9: =SUM(B9:M9) -> 4256
A10: Phone | B10: 70 | C10: 84 | D10: 85 | E10: 79 | F10: 86 | G10: 80 | H10: 74 | I10: 66 | J10: 76 | K10: 84 | L10: 77 | M10: 80 | N10: =SUM(B10:M10) -> 941
A11: Internet | B11: 63 | C11: 56 | D11: 65 | E11: 62 | F11: 66 | G11: 74 | H11: 74 | I11: 73 | J11: 68 | K11: 66 | L11: 66 | M11: 73 | N11: =SUM(B11:M11) -> 806
A12: Childcare | B12: 0 | C12: 0 | D12: 0 | E12: 0 | F12: 0 | G12: 0 | H12: 0 | I12: 0 | J12: 0 | K12: 0 | L12: 0 | M12: 0 | N12: =SUM(B12:M12) -> 0
A13: Pet Care | B13: 30 | C13: 30 | D13: 31 | E13: 34 | F13: 40 | G13: 39 | H13: 36 | I13: 40 | J13: 37 | K13: 38 | L13: 32 | M13: 31 | N13: =SUM(B13:M13) -> 418
A14: Essential Subscriptions | B14: 27 | C14: 33 | D14: 33 | E14: 31 | F14: 27 | G14: 29 | H14: 28 | I14: 31 | J14: 32 | K14: 33 | L14: 31 | M14: 28 | N14: =SUM(B14:M14) -> 363
... A17: Other Essentials | B17: 56 | C17: 44 | D17: 57 | E17: 54 | F17: 46 | G17: 43 | H17: 53 | I17: 48 | J17: 47 | K17: 57 | L17: 44 | M17: 48 | N17: =SUM(B17:M17) -> 597
A18: Monthly Total | B18: =SUM(B3:B17) -> 3148 | C18: =SUM(C3:C17) -> 3366 | D18: =SUM(D3:D17) -> 3318 | E18: =SUM(E3:E17) -> 3556 | F18: =SUM(F3:F17) -> 3339 | G18: =SUM(G3:G17) -> 3219 | H18: =SUM(H3:H17) -> 3210 | I18: =SUM(I3:I17) -> 3519 | ... M18: =SUM(M3:M17) -> 3325 | N18: =SUM(B18:M18) -> 40024
A19: Annual Total | B19: =N18 -> 40024
A20: Average Monthly Essentials | B20: =B19/12 -> 3335.3333

Sheet Emergency Fund
A1: Emergency Fund Planner
A2: Target Calculation
A3: Coverage Months | B3: 6
A4: Avg Monthly Essentials | B4: ='Monthly Expenses'!B20 -> 3335.3333
A5: Target Amount | B5: =B3*B4 -> 20012
A6: Current Status
A7: Current Balance | B7: 9200
A8: Monthly Contribution | B8: 450
A9: Shortfall | B9: =MAX(0,B5-B7) -> 10812
A10: Months to Fully Funded | B10: =IFERROR(IF(B9=0,0,B9/B8),0) -> 24.026667
A11: Projected Funded Date | B11: =IF(B10=0,TODAY(),TODAY()+B10*30.44) -> 46853.372
A12: Status | B12: =IF(B7>=B5,"Fully Funded","Building") -> Building
A13: What-If Boost
A14: Extra Monthly Amount | B14: 200
A15: Boosted Contribution | B15: =B8+B14 -> 650
A16: Boosted Months to Fund | B16: =IFERROR(IF(B9=0,0,B9/B15),0) -> 16.633846
A17: Boosted Funded Date | B17: =IF(B16=0,TODAY(),TODAY()+B16*30.44) -> 46628.334
A18: Time Saved (months) | B18: =MAX(0,B10-B16) -> 7.3928205

Sheet Goals
A1: Savings Goals
A2: Goal Name | B2: Target | C2: Current Balance | D2: Monthly Contrib. | E2: Priority | F2: Proj. Months | G2: Proj. Date | H2: EF Redirect Months | I2: EF Redirect Date | J2: Status
A3: Vacation | B3: 4500 | C3: 1800 | D3: 200 | E3: 2 | F3: =IFERROR(IF(C3>=B3,0,(B3-C3)/D3),0) -> 13.5 | G3: =IF(F3=0,TODAY(),TODAY()+F3*30.44) -> 46532.94 | H3: =IFERROR(IF(C3>=B3,0,(B3-C3)/(D3+'Emergency Fund'!$B$8)),0) -> 4.1538462 | I3: =IF(H3=0,TODAY(),TODAY()+H3*30.44) -> 46248.443 | J3: =IF(C3>=B3,"Reached",IF(F3<120,"On Track","Behind")) -> On Track
A4: House Down Payment | B4: 50000 | C4: 8500 | D4: 600 | E4: 1 | F4: =IFERROR(IF(C4>=B4,0,(B4-C4)/D4),0) -> 69.166667 | G4: =IF(F4=0,TODAY(),TODAY()+F4*30.44) -> 48227.433 | H4: =IFERROR(IF(C4>=B4,0,(B4-C4)/(D4+'Emergency Fund'!$B$8)),0) -> 39.52381 | I4: =IF(H4=0,TODAY(),TODAY()+H4*30.44) -> 47325.105 | J4: =IF(C4>=B4,"Reached",IF(F4<120,"On Track","Behind")) -> On Track
A5: New Car | B5: 12000 | C5: 3200 | D5: 250 | E5: 3 | F5: =IFERROR(IF(C5>=B5,0,(B5-C5)/D5),0) -> 35.2 | G5: =IF(F5=0,TODAY(),TODAY()+F5*30.44) -> 47193.488 | H5: =IFERROR(IF(C5>=B5,0,(B5-C5)/(D5+'Emergency Fund'!$B$8)),0) -> 12.571429 | I5: =IF(H5=0,TODAY(),TODAY()+H5*30.44) -> 46504.674 | J5: =IF(C5>=B5,"Reached",IF(F5<120,"On Track","Behind")) -> On Track
A6: Wedding | B6: 18000 | C6: 2000 | D6: 350 | E6: 4 | F6: =IFERROR(IF(C6>=B6,0,(B6-C6)/D6),0) -> 45.714286 | G6: =IF(F6=0,TODAY(),TODAY()+F6*30.44) -> 47513.543 | H6: =IFERROR(IF(C6>=B6,0,(B6-C6)/(D6+'Emergency Fund'!$B$8)),0) -> 20 | I6: =IF(H6=0,TODAY(),TODAY()+H6*30.44) -> 46730.8 | J6: =IF(C6>=B6,"Reached",IF(F6<120,"On Track","Behind")) -> On Track
A7: Home Renovation | B7: 8000 | C7: 1200 | D7: 150 | E7: 5 | F7: =IFERROR(IF(C7>=B7,0,(B7-C7)/D7),0) -> 45.333333 | G7: =IF(F7=0,TODAY(),TODAY()+F7*30.44) -> 47501.947 | H7: =IFERROR(IF(C7>=B7,0,(B7-C7)/(D7+'Emergency Fund'!$B$8)),0) -> 11.333333 | I7: =IF(H7=0,TODAY(),TODAY()+H7*30.44) -> 46466.987 | J7: =IF(C7>=B7,"Reached",IF(F7<120,"On Track","Behind")) -> On Track
A8: Sabbatical Fund | B8: 25000 | C8: 4000 | D8: 300 | E8: 3 | F8: =IFERROR(IF(C8>=B8,0,(B8-C8)/D8),0) -> 70 | G8: =IF(F8=0,TODAY(),TODAY()+F8*30.44) -> 48252.8 | H8: =IFERROR(IF(C8>=B8,0,(B8-C8)/(D8+'Emergency Fund'!$B$8)),0) -> 28 | I8: =IF(H8=0,TODAY(),TODAY()+H8*30.44) -> 46974.32 | J8: =IF(C8>=B8,"Reached",IF(F8<120,"On Track","Behind")) -> On Track

Sheet Contributions
A1: Monthly Contribution Log
A2: Month | B2: Emergency Fund | C2: Vacation | D2: House Down Payment | E2: New Car | F2: Wedding | G2: Home Renovation | H2: Sabbatical Fund | I2: Total Actual | J2: Total Planned | K2: Variance
A3: Jan | B3: 491 | C3: 186 | D3: 594 | E3: 234 | F3: 336 | G3: 134 | H3: 310 | I3: =SUM(B3:H3) -> 2285 | J3: 2300 | K3: =I3-J3 -> -15
A4: Feb | B4: 430 | C4: 225 | D4: 595 | E4: 245 | F4: 351 | G4: 161 | H4: 309 | I4: =SUM(B4:H4) -> 2316 | J4: 2300 | K4: =I4-J4 -> 16
A5: Mar | B5: 460 | C5: 202 | D5: 625 | E5: 242 | F5: 349 | G5: 165 | H5: 283 | I5: =SUM(B5:H5) -> 2326 | J5: 2300 | K5: =I5-J5 -> 26
A6: Apr | B6: 442 | C6: 211 | D6: 598 | E6: 258 | F6: 335 | G6: 180 | H6: 284 | I6: =SUM(B6:H6) -> 2308 | J6: 2300 | K6: =I6-J6 -> 8
A7: May | B7: 478 | C7: 195 | D7: 606 | E7: 271 | F7: 375 | G7: 177 | H7: 327 | I7: =SUM(B7:H7) -> 2429 | J7: 2300 | K7: =I7-J7 -> 129
A8: Jun | B8: 437 | C8: 181 | D8: 625 | E8: 270 | F8: 332 | G8: 179 | H8: 312 | I8: =SUM(B8:H8) -> 2336 | J8: 2300 | K8: =I8-J8 -> 36
A9: Jul | B9: 421 | C9: 227 | D9: 598 | E9: 275 | F9: 340 | G9: 154 | H9: 287 | I9: =SUM(B9:H9) -> 2302 | J9: 2300 | K9: =I9-J9 -> 2
A10: Aug | B10: 494 | C10: 191 | D10: 591 | E10: 251 | F10: 343 | G10: 130 | H10: 303 | I10: =SUM(B10:H10) -> 2303 | J10: 2300 | K10: =I10-J10 -> 3
A11: Sep | B11: 462 | C11: 211 | D11: 582 | E11: 280 | F11: 347 | G11: 144 | H11: 319 | I11: =SUM(B11:H11) -> 2345 | J11: 2300 | K11: =I11-J11 -> 45
A12: Oct | B12: 470 | C12: 199 | D12: 582 | E12: 242 | F12: 369 | G12: 160 | H12: 318 | I12: =SUM(B12:H12) -> 2340 | J12: 2300 | K12: =I12-J12 -> 40
A13: Nov | B13: 422 | C13: 210 | D13: 590 | E13: 249 | F13: 361 | G13: 158 | H13: 286 | I13: =SUM(B13:H13) -> 2276 | J13: 2300 | K13: =I13-J13 -> -24
A14: Dec | B14: 480 | C14: 215 | D14: 583 | E14: 242 | F14: 354 | G14: 156 | H14: 287 | I14: =SUM(B14:H14) -> 2317 | J14: 2300 | K14: =I14-J14 -> 17
A17: Running Balance | B17: =SUM(B3:B14) -> 5487 | C17: =SUM(C3:C14) -> 2453 | D17: =SUM(D3:D14) -> 7169 | E17: =SUM(E3:E14) -> 3059 | F17: =SUM(F3:F14) -> 4192 | G17: =SUM(G3:G14) -> 1898 | H17: =SUM(H3:H14) -> 3625

Sheet Projections
A1: 24-Month Forward Projections
A2: Month # | B2: Date | C2: EF Balance | D2: Vacation | E2: House Down Payment | F2: New Car | G2: Wedding | H2: Home Renovation | I2: Sabbatical Fund | J2: EF Boosted | K2: Vacation Boosted | L2: House Down Payment Boosted | M2: New Car Boosted | N2: Wedding Boosted | O2: Home Renovation Boosted | P2: Sabbatical Fund Boosted
A3: 1 | B3: =TODAY()+0*30.44 -> 46122 | C3: =MIN('Emergency Fund'!$B$5,'Emergency Fund'!$B$7+'Emergency Fund'!$B$8*1) -> 9650 | D3: =MIN(Goals!$B$3,Goals!$C$3+Goals!$D$3*1) -> 2000 | E3: =MIN(Goals!$B$4,Goals!$C$4+Goals!$D$4*1) -> 9100 | F3: =MIN(Goals!$B$5,Goals!$C$5+Goals!$D$5*1) -> 3450 | G3: =MIN(Goals!$B$6,Goals!$C$6+Goals!$D$6*1) -> 2350 | H3: =MIN(Goals!$B$7,Goals!$C$7+Goals!$D$7*1) -> 1350 | I3: =MIN(Goals!$B$8,Goals!$C$8+Goals!$D$8*1) -> 4300 | J3: =MIN('Emergency Fund'!$B$5,'Emergency Fund'!$B$7+'Emergency Fund'!$B$15*1) -> 9850 | K3: =MIN(Goals!$B$3,Goals!$C$3+(Goals!$D$3+'Emergency Fund'!$B$14/6)*1) -> 2033.3333 | L3: =MIN(Goals!$B$4,Goals!$C$4+(Goals!$D$4+'Emergency Fund'!$B$14/6)*1) -> 9133.3333 | M3: =MIN(Goals!$B$5,Goals!$C$5+(Goals!$D$5+'Emergency Fund'!$B$14/6)*1) -> 3483.3333 | N3: =MIN(Goals!$B$6,Goals!$C$6+(Goals!$D$6+'Emergency Fund'!$B$14/6)*1) -> 2383.3333 | O3: =MIN(Goals!$B$7,Goals!$C$7+(Goals!$D$7+'Emergency Fund'!$B$14/6)*1) -> 1383.3333 | P3: =MIN(Goals!$B$8,Goals!$C$8+(Goals!$D$8+'Emergency Fund'!$B$14/6)*1) -> 4333.3333
A4: 2 | B4: =TODAY()+1*30.44 -> 46152.44 | C4: =MIN('Emergency Fund'!$B$5,'Emergency Fund'!$B$7+'Emergency Fund'!$B$8*2) -> 10100 | D4: =MIN(Goals!$B$3,Goals!$C$3+Goals!$D$3*2) -> 2200 | E4: =MIN(Goals!$B$4,Goals!$C$4+Goals!$D$4*2) -> 9700 | F4: =MIN(Goals!$B$5,Goals!$C$5+Goals!$D$5*2) -> 3700 | G4: =MIN(Goals!$B$6,Goals!$C$6+Goals!$D$6*2) -> 2700 | H4: =MIN(Goals!$B$7,Goals!$C$7+Goals!$D$7*2) -> 1500 | I4: =MIN(Goals!$B$8,Goals!$C$8+Goals!$D$8*2) -> 4600 | J4: =MIN('Emergency Fund'!$B$5,'Emergency Fund'!$B$7+'Emergency Fund'!$B$15*2) -> 10500 | K4: =MIN(Goals!$B$3,Goals!$C$3+(Goals!$D$3+'Emergency Fund'!$B$14/6)*2) -> 2266.6667 | L4: =MIN(Goals!$B$4,Goals!$C$4+(Goals!$D$4+'Emergency Fund'!$B$14/6)*2) -> 9766.6667 | M4: =MIN(Goals!$B$5,Goals!$C$5+(Goals!$D$5+'Emergency Fund'!$B$14/6)*2) -> 3766.6667 | N4: =MIN(Goals!$B$6,Goals!$C$6+(Goals!$D$6+'Emergency Fund'!$B$14/6)*2) -> 2766.6667 | O4: =MIN(Goals!$B$7,Goals!$C$7+(Goals!$D$7+'Emergency Fund'!$B$14/6)*2) -> 1566.6667 | P4: =MIN(Goals!$B$8,Goals!$C$8+(Goals!$D$8+'Emergency Fund'!$B$14/6)*2) -> 4666.6667
A5: 3 | B5: =TODAY()+2*30.44 -> 46182.88 | C5: =MIN('Emergency Fund'!$B$5,'Emergency Fund'!$B$7+'Emergency Fund'!$B$8*3) -> 10550 | D5: =MIN(Goals!$B$3,Goals!$C$3+Goals!$D$3*3) -> 2400 | E5: =MIN(Goals!$B$4,Goals!$C$4+Goals!$D$4*3) -> 10300 | F5: =MIN(Goals!$B$5,Goals!$C$5+Goals!$D$5*3) -> 3950 | G5: =MIN(Goals!$B$6,Goals!$C$6+Goals!$D$6*3) -> 3050 | H5: =MIN(Goals!$B$7,Goals!$C$7+Goals!$D$7*3) -> 1650 | I5: =MIN(Goals!$B$8,Goals!$C$8+Goals!$D$8*3) -> 4900 | J5: =MIN('Emergency Fund'!$B$5,'Emergency Fund'!$B$7+'Emergency Fund'!$B$15*3) -> 11150 | K5: =MIN(Goals!$B$3,Goals!$C$3+(Goals!$D$3+'Emergency Fund'!$B$14/6)*3) -> 2500 | L5: =MIN(Goals!$B$4,Goals!$C$4+(Goals!$D$4+'Emergency Fund'!$B$14/6)*3) -> 10400 | M5: =MIN(Goals!$B$5,Goals!$C$5+(Goals!$D$5+'Emergency Fund'!$B$14/6)*3) -> 4050 | N5: =MIN(Goals!$B$6,Goals!$C$6+(Goals!$D$6+'Emergency Fund'!$B$14/6)*3) -> 3150 | O5: =MIN(Goals!$B$7,Goals!$C$7+(Goals!$D$7+'Emergency Fund'!$B$14/6)*3) -> 1750 | P5: =MIN(Goals!$B$8,Goals!$C$8+(Goals!$D$8+'Emergency Fund'!$B$14/6)*3) -> 5000
A6: 4 | B6: =TODAY()+3*30.44 -> 46213.32 | C6: =MIN('Emergency Fund'!$B$5,'Emergency Fund'!$B$7+'Emergency Fund'!$B$8*4) -> 11000 | D6: =MIN(Goals!$B$3,Goals!$C$3+Goals!$D$3*4) -> 2600 | E6: =MIN(Goals!$B$4,Goals!$C$4+Goals!$D$4*4) -> 10900 | F6: =MIN(Goals!$B$5,Goals!$C$5+Goals!$D$5*4) -> 4200 | G6: =MIN(Goals!$B$6,Goals!$C$6+Goals!$D$6*4) -> 3400 | H6: =MIN(Goals!$B$7,Goals!$C$7+Goals!$D$7*4) -> 1800 | I6: =MIN(Goals!$B$8,Goals!$C$8+Goals!$D$8*4) -> 5200 | J6: =MIN('Emergency Fund'!$B$5,'Emergency Fund'!$B$7+'Emergency Fund'!$B$15*4) -> 11800 | K6: =MIN(Goals!$B$3,Goals!$C$3+(Goals!$D$3+'Emergency Fund'!$B$14/6)*4) -> 2733.3333 | L6: =MIN(Goals!$B$4,Goals!$C$4+(Goals!$D$4+'Emergency Fund'!$B$14/6)*4) -> 11033.333 | M6: =MIN(Goals!$B$5,Goals!$C$5+(Goals!$D$5+'Emergency Fund'!$B$14/6)*4) -> 4333.3333 | N6: =MIN(Goals!$B$6,Goals!$C$6+(Goals!$D$6+'Emergency Fund'!$B$14/6)*4) -> 3533.3333 | O6: =MIN(Goals!$B$7,Goals!$C$7+(Goals!$D$7+'Emergency Fund'!$B$14/6)*4) -> 1933.3333 | P6: =MIN(Goals!$B$8,Goals!$C$8+(Goals!$D$8+'Emergency Fund'!$B$14/6)*4) -> 5333.3333
A7: 5 | B7: =TODAY()+4*30.44 -> 46243.76 | C7: =MIN('Emergency Fund'!$B$5,'Emergency Fund'!$B$7+'Emergency Fund'!$B$8*5) -> 11450 | D7: =MIN(Goals!$B$3,Goals!$C$3+Goals!$D$3*5) -> 2800 | E7: =MIN(Goals!$B$4,Goals!$C$4+Goals!$D$4*5) -> 11500 | F7: =MIN(Goals!$B$5,Goals!$C$5+Goals!$D$5*5) -> 4450 | G7: =MIN(Goals!$B$6,Goals!$C$6+Goals!$D$6*5) -> 3750 | H7: =MIN(Goals!$B$7,Goals!$C$7+Goals!$D$7*5) -> 1950 | I7: =MIN(Goals!$B$8,Goals!$C$8+Goals!$D$8*5) -> 5500 | J7: =MIN('Emergency Fund'!$B$5,'Emergency Fund'!$B$7+'Emergency Fund'!$B$15*5) -> 12450 | K7: =MIN(Goals!$B$3,Goals!$C$3+(Goals!$D$3+'Emergency Fund'!$B$14/6)*5) -> 2966.6667 | L7: =MIN(Goals!$B$4,Goals!$C$4+(Goals!$D$4+'Emergency Fund'!$B$14/6)*5) -> 11666.667 | M7: =MIN(Goals!$B$5,Goals!$C$5+(Goals!$D$5+'Emergency Fund'!$B$14/6)*5) -> 4616.6667 | N7: =MIN(Goals!$B$6,Goals!$C$6+(Goals!$D$6+'Emergency Fund'!$B$14/6)*5) -> 3916.6667 | O7: =MIN(Goals!$B$7,Goals!$C$7+(Goals!$D$7+'Emergency Fund'!$B$14/6)*5) -> 2116.6667 | P7: =MIN(Goals!$B$8,Goals!$C$8+(Goals!$D$8+'Emergency Fund'!$B$14/6)*5) -> 5666.6667
A8: 6 | B8: =TODAY()+5*30.44 -> 46274.2 | C8: =MIN('Emergency Fund'!$B$5,'Emergency Fund'!$B$7+'Emergency Fund'!$B$8*6) -> 11900 | D8: =MIN(Goals!$B$3,Goals!$C$3+Goals!$D$3*6) -> 3000 | E8: =MIN(Goals!$B$4,Goals!$C$4+Goals!$D$4*6) -> 12100 | F8: =MIN(Goals!$B$5,Goals!$C$5+Goals!$D$5*6) -> 4700 | G8: =MIN(Goals!$B$6,Goals!$C$6+Goals!$D$6*6) -> 4100 | H8: =MIN(Goals!$B$7,Goals!$C$7+Goals!$D$7*6) -> 2100 | I8: =MIN(Goals!$B$8,Goals!$C$8+Goals!$D$8*6) -> 5800 | J8: =MIN('Emergency Fund'!$B$5,'Emergency Fund'!$B$7+'Emergency Fund'!$B$15*6) -> 13100 | K8: =MIN(Goals!$B$3,Goals!$C$3+(Goals!$D$3+'Emergency Fund'!$B$14/6)*6) -> 3200 | L8: =MIN(Goals!$B$4,Goals!$C$4+(Goals!$D$4+'Emergency Fund'!$B$14/6)*6) -> 12300 | M8: =MIN(Goals!$B$5,Goals!$C$5+(Goals!$D$5+'Emergency Fund'!$B$14/6)*6) -> 4900 | N8: =MIN(Goals!$B$6,Goals!$C$6+(Goals!$D$6+'Emergency Fund'!$B$14/6)*6) -> 4300 | O8: =MIN(Goals!$B$7,Goals!$C$7+(Goals!$D$7+'Emergency Fund'!$B$14/6)*6) -> 2300 | P8: =MIN(Goals!$B$8,Goals!$C$8+(Goals!$D$8+'Emergency Fund'!$B$14/6)*6) -> 6000
A9: 7 | B9: =TODAY()+6*30.44 -> 46304.64 | C9: =MIN('Emergency Fund'!$B$5,'Emergency Fund'!$B$7+'Emergency Fund'!$B$8*7) -> 12350 | D9: =MIN(Goals!$B$3,Goals!$C$3+Goals!$D$3*7) -> 3200 | E9: =MIN(Goals!$B$4,Goals!$C$4+Goals!$D$4*7) -> 12700 | F9: =MIN(Goals!$B$5,Goals!$C$5+Goals!$D$5*7) -> 4950 | G9: =MIN(Goals!$B$6,Goals!$C$6+Goals!$D$6*7) -> 4450 | H9: =MIN(Goals!$B$7,Goals!$C$7+Goals!$D$7*7) -> 2250 | I9: =MIN(Goals!$B$8,Goals!$C$8+Goals!$D$8*7) -> 6100 | J9: =MIN('Emergency Fund'!$B$5,'Emergency Fund'!$B$7+'Emergency Fund'!$B$15*7) -> 13750 | K9: =MIN(Goals!$B$3,Goals!$C$3+(Goals!$D$3+'Emergency Fund'!$B$14/6)*7) -> 3433.3333 | L9: =MIN(Goals!$B$4,Goals!$C$4+(Goals!$D$4+'Emergency Fund'!$B$14/6)*7) -> 12933.333 | M9: =MIN(Goals!$B$5,Goals!$C$5+(Goals!$D$5+'Emergency Fund'!$B$14/6)*7) -> 5183.3333 | N9: =MIN(Goals!$B$6,Goals!$C$6+(Goals!$D$6+'Emergency Fund'!$B$14/6)*7) -> 4683.3333 | O9: =MIN(Goals!$B$7,Goals!$C$7+(Goals!$D$7+'Emergency Fund'!$B$14/6)*7) -> 2483.3333 | P9: =MIN(Goals!$B$8,Goals!$C$8+(Goals!$D$8+'Emergency Fund'!$B$14/6)*7) -> 6333.3333
A10: 8 | B10: =TODAY()+7*30.44 -> 46335.08 | C10: =MIN('Emergency Fund'!$B$5,'Emergency Fund'!$B$7+'Emergency Fund'!$B$8*8) -> 12800 | D10: =MIN(Goals!$B$3,Goals!$C$3+Goals!$D$3*8) -> 3400 | E10: =MIN(Goals!$B$4,Goals!$C$4+Goals!$D$4*8) -> 13300 | F10: =MIN(Goals!$B$5,Goals!$C$5+Goals!$D$5*8) -> 5200 | G10: =MIN(Goals!$B$6,Goals!$C$6+Goals!$D$6*8) -> 4800 | H10: =MIN(Goals!$B$7,Goals!$C$7+Goals!$D$7*8) -> 2400 | I10: =MIN(Goals!$B$8,Goals!$C$8+Goals!$D$8*8) -> 6400 | J10: =MIN('Emergency Fund'!$B$5,'Emergency Fund'!$B$7+'Emergency Fund'!$B$15*8) -> 14400 | K10: =MIN(Goals!$B$3,Goals!$C$3+(Goals!$D$3+'Emergency Fund'!$B$14/6)*8) -> 3666.6667 | L10: =MIN(Goals!$B$4,Goals!$C$4+(Goals!$D$4+'Emergency Fund'!$B$14/6)*8) -> 13566.667 | M10: =MIN(Goals!$B$5,Goals!$C$5+(Goals!$D$5+'Emergency Fund'!$B$14/6)*8) -> 5466.6667 | N10: =MIN(Goals!$B$6,Goals!$C$6+(Goals!$D$6+'Emergency Fund'!$B$14/6)*8) -> 5066.6667 | O10: =MIN(Goals!$B$7,Goals!$C$7+(Goals!$D$7+'Emergency Fund'!$B$14/6)*8) -> 2666.6667 | P10: =MIN(Goals!$B$8,Goals!$C$8+(Goals!$D$8+'Emergency Fund'!$B$14/6)*8) -> 6666.6667
A11: 9 | B11: =TODAY()+8*30.44 -> 46365.52 | C11: =MIN('Emergency Fund'!$B$5,'Emergency Fund'!$B$7+'Emergency Fund'!$B$8*9) -> 13250 | D11: =MIN(Goals!$B$3,Goals!$C$3+Goals!$D$3*9) -> 3600 | E11: =MIN(Goals!$B$4,Goals!$C$4+Goals!$D$4*9) -> 13900 | F11: =MIN(Goals!$B$5,Goals!$C$5+Goals!$D$5*9) -> 5450 | G11: =MIN(Goals!$B$6,Goals!$C$6+Goals!$D$6*9) -> 5150 | H11: =MIN(Goals!$B$7,Goals!$C$7+Goals!$D$7*9) -> 2550 | I11: =MIN(Goals!$B$8,Goals!$C$8+Goals!$D$8*9) -> 6700 | J11: =MIN('Emergency Fund'!$B$5,'Emergency Fund'!$B$7+'Emergency Fund'!$B$15*9) -> 15050 | K11: =MIN(Goals!$B$3,Goals!$C$3+(Goals!$D$3+'Emergency Fund'!$B$14/6)*9) -> 3900 | L11: =MIN(Goals!$B$4,Goals!$C$4+(Goals!$D$4+'Emergency Fund'!$B$14/6)*9) -> 14200 | M11: =MIN(Goals!$B$5,Goals!$C$5+(Goals!$D$5+'Emergency Fund'!$B$14/6)*9) -> 5750 | N11: =MIN(Goals!$B$6,Goals!$C$6+(Goals!$D$6+'Emergency Fund'!$B$14/6)*9) -> 5450 | O11: =MIN(Goals!$B$7,Goals!$C$7+(Goals!$D$7+'Emergency Fund'!$B$14/6)*9) -> 2850 | P11: =MIN(Goals!$B$8,Goals!$C$8+(Goals!$D$8+'Emergency Fund'!$B$14/6)*9) -> 7000
A12: 10 | B12: =TODAY()+9*30.44 -> 46395.96 | C12: =MIN('Emergency Fund'!$B$5,'Emergency Fund'!$B$7+'Emergency Fund'!$B$8*10) -> 13700 | D12: =MIN(Goals!$B$3,Goals!$C$3+Goals!$D$3*10) -> 3800 | E12: =MIN(Goals!$B$4,Goals!$C$4+Goals!$D$4*10) -> 14500 | F12: =MIN(Goals!$B$5,Goals!$C$5+Goals!$D$5*10) -> 5700 | G12: =MIN(Goals!$B$6,Goals!$C$6+Goals!$D$6*10) -> 5500 | H12: =MIN(Goals!$B$7,Goals!$C$7+Goals!$D$7*10) -> 2700 | I12: =MIN(Goals!$B$8,Goals!$C$8+Goals!$D$8*10) -> 7000 | J12: =MIN('Emergency Fund'!$B$5,'Emergency Fund'!$B$7+'Emergency Fund'!$B$15*10) -> 15700 | K12: =MIN(Goals!$B$3,Goals!$C$3+(Goals!$D$3+'Emergency Fund'!$B$14/6)*10) -> 4133.3333 | L12: =MIN(Goals!$B$4,Goals!$C$4+(Goals!$D$4+'Emergency Fund'!$B$14/6)*10) -> 14833.333 | M12: =MIN(Goals!$B$5,Goals!$C$5+(Goals!$D$5+'Emergency Fund'!$B$14/6)*10) -> 6033.3333 | N12: =MIN(Goals!$B$6,Goals!$C$6+(Goals!$D$6+'Emergency Fund'!$B$14/6)*10) -> 5833.3333 | O12: =MIN(Goals!$B$7,Goals!$C$7+(Goals!$D$7+'Emergency Fund'!$B$14/6)*10) -> 3033.3333 | P12: =MIN(Goals!$B$8,Goals!$C$8+(Goals!$D$8+'Emergency Fund'!$B$14/6)*10) -> 7333.3333
A13: 11 | B13: =TODAY()+10*30.44 -> 46426.4 | C13: =MIN('Emergency Fund'!$B$5,'Emergency Fund'!$B$7+'Emergency Fund'!$B$8*11) -> 14150 | D13: =MIN(Goals!$B$3,Goals!$C$3+Goals!$D$3*11) -> 4000 | E13: =MIN(Goals!$B$4,Goals!$C$4+Goals!$D$4*11) -> 15100 | F13: =MIN(Goals!$B$5,Goals!$C$5+Goals!$D$5*11) -> 5950 | G13: =MIN(Goals!$B$6,Goals!$C$6+Goals!$D$6*11) -> 5850 | H13: =MIN(Goals!$B$7,Goals!$C$7+Goals!$D$7*11) -> 2850 | I13: =MIN(Goals!$B$8,Goals!$C$8+Goals!$D$8*11) -> 7300 | J13: =MIN('Emergency Fund'!$B$5,'Emergency Fund'!$B$7+'Emergency Fund'!$B$15*11) -> 16350 | K13: =MIN(Goals!$B$3,Goals!$C$3+(Goals!$D$3+'Emergency Fund'!$B$14/6)*11) -> 4366.6667 | L13: =MIN(Goals!$B$4,Goals!$C$4+(Goals!$D$4+'Emergency Fund'!$B$14/6)*11) -> 15466.667 | M13: =MIN(Goals!$B$5,Goals!$C$5+(Goals!$D$5+'Emergency Fund'!$B$14/6)*11) -> 6316.6667 | N13: =MIN(Goals!$B$6,Goals!$C$6+(Goals!$D$6+'Emergency Fund'!$B$14/6)*11) -> 6216.6667 | O13: =MIN(Goals!$B$7,Goals!$C$7+(Goals!$D$7+'Emergency Fund'!$B$14/6)*11) -> 3216.6667 | P13: =MIN(Goals!$B$8,Goals!$C$8+(Goals!$D$8+'Emergency Fund'!$B$14/6)*11) -> 7666.6667
A14: 12 | B14: =TODAY()+11*30.44 -> 46456.84 | C14: =MIN('Emergency Fund'!$B$5,'Emergency Fund'!$B$7+'Emergency Fund'!$B$8*12) -> 14600 | D14: =MIN(Goals!$B$3,Goals!$C$3+Goals!$D$3*12) -> 4200 | E14: =MIN(Goals!$B$4,Goals!$C$4+Goals!$D$4*12) -> 15700 | F14: =MIN(Goals!$B$5,Goals!$C$5+Goals!$D$5*12) -> 6200 | G14: =MIN(Goals!$B$6,Goals!$C$6+Goals!$D$6*12) -> 6200 | H14: =MIN(Goals!$B$7,Goals!$C$7+Goals!$D$7*12) -> 3000 | I14: =MIN(Goals!$B$8,Goals!$C$8+Goals!$D$8*12) -> 7600 | J14: =MIN('Emergency Fund'!$B$5,'Emergency Fund'!$B$7+'Emergency Fund'!$B$15*12) -> 17000 | K14: =MIN(Goals!$B$3,Goals!$C$3+(Goals!$D$3+'Emergency Fund'!$B$14/6)*12) -> 4500 | L14: =MIN(Goals!$B$4,Goals!$C$4+(Goals!$D$4+'Emergency Fund'!$B$14/6)*12) -> 16100 | M14: =MIN(Goals!$B$5,Goals!$C$5+(Goals!$D$5+'Emergency Fund'!$B$14/6)*12) -> 6600 | N14: =MIN(Goals!$B$6,Goals!$C$6+(Goals!$D$6+'Emergency Fund'!$B$14/6)*12) -> 6600 | O14: =MIN(Goals!$B$7,Goals!$C$7+(Goals!$D$7+'Emergency Fund'!$B$14/6)*12) -> 3400 | P14: =MIN(Goals!$B$8,Goals!$C$8+(Goals!$D$8+'Emergency Fund'!$B$14/6)*12) -> 8000
A15: 13 | B15: =TODAY()+12*30.44 -> 46487.28 | C15: =MIN('Emergency Fund'!$B$5,'Emergency Fund'!$B$7+'Emergency Fund'!$B$8*13) -> 15050 | D15: =MIN(Goals!$B$3,Goals!$C$3+Goals!$D$3*13) -> 4400 | E15: =MIN(Goals!$B$4,Goals!$C$4+Goals!$D$4*13) -> 16300 | F15: =MIN(Goals!$B$5,Goals!$C$5+Goals!$D$5*13) -> 6450 | G15: =MIN(Goals!$B$6,Goals!$C$6+Goals!$D$6*13) -> 6550 | H15: =MIN(Goals!$B$7,Goals!$C$7+Goals!$D$7*13) -> 3150 | I15: =MIN(Goals!$B$8,Goals!$C$8+Goals!$D$8*13) -> 7900 | J15: =MIN('Emergency Fund'!$B$5,'Emergency Fund'!$B$7+'Emergency Fund'!$B$15*13) -> 17650 | K15: =MIN(Goals!$B$3,Goals!$C$3+(Goals!$D$3+'Emergency Fund'!$B$14/6)*13) -> 4500 | L15: =MIN(Goals!$B$4,Goals!$C$4+(Goals!$D$4+'Emergency Fund'!$B$14/6)*13) -> 16733.333 | M15: =MIN(Goals!$B$5,Goals!$C$5+(Goals!$D$5+'Emergency Fund'!$B$14/6)*13) -> 6883.3333 | N15: =MIN(Goals!$B$6,Goals!$C$6+(Goals!$D$6+'Emergency Fund'!$B$14/6)*13) -> 6983.3333 | O15: =MIN(Goals!$B$7,Goals!$C$7+(Goals!$D$7+'Emergency Fund'!$B$14/6)*13) -> 3583.3333 | P15: =MIN(Goals!$B$8,Goals!$C$8+(Goals!$D$8+'Emergency Fund'!$B$14/6)*13) -> 8333.3333
A16: 14 | B16: =TODAY()+13*30.44 -> 46517.72 | C16: =MIN('Emergency Fund'!$B$5,'Emergency Fund'!$B$7+'Emergency Fund'!$B$8*14) -> 15500 | D16: =MIN(Goals!$B$3,Goals!$C$3+Goals!$D$3*14) -> 4500 | E16: =MIN(Goals!$B$4,Goals!$C$4+Goals!$D$4*14) -> 16900 | F16: =MIN(Goals!$B$5,Goals!$C$5+Goals!$D$5*14) -> 6700 | G16: =MIN(Goals!$B$6,Goals!$C$6+Goals!$D$6*14) -> 6900 | H16: =MIN(Goals!$B$7,Goals!$C$7+Goals!$D$7*14) -> 3300 | I16: =MIN(Goals!$B$8,Goals!$C$8+Goals!$D$8*14) -> 8200 | J16: =MIN('Emergency Fund'!$B$5,'Emergency Fund'!$B$7+'Emergency Fund'!$B$15*14) -> 18300 | K16: =MIN(Goals!$B$3,Goals!$C$3+(Goals!$D$3+'Emergency Fund'!$B$14/6)*14) -> 4500 | L16: =MIN(Goals!$B$4,Goals!$C$4+(Goals!$D$4+'Emergency Fund'!$B$14/6)*14) -> 17366.667 | M16: =MIN(Goals!$B$5,Goals!$C$5+(Goals!$D$5+'Emergency Fund'!$B$14/6)*14) -> 7166.6667 | N16: =MIN(Goals!$B$6,Goals!$C$6+(Goals!$D$6+'Emergency Fund'!$B$14/6)*14) -> 7366.6667 | O16: =MIN(Goals!$B$7,Goals!$C$7+(Goals!$D$7+'Emergency Fund'!$B$14/6)*14) -> 3766.6667 | P16: =MIN(Goals!$B$8,Goals!$C$8+(Goals!$D$8+'Emergency Fund'!$B$14/6)*14) -> 8666.6667
A17: 15 | B17: =TODAY()+14*30.44 -> 46548.16 | C17: =MIN('Emergency Fund'!$B$5,'Emergency Fund'!$B$7+'Emergency Fund'!$B$8*15) -> 15950 | D17: =MIN(Goals!$B$3,Goals!$C$3+Goals!$D$3*15) -> 4500 | E17: =MIN(Goals!$B$4,Goals!$C$4+Goals!$D$4*15) -> 17500 | F17: =MIN(Goals!$B$5,Goals!$C$5+Goals!$D$5*15) -> 6950 | G17: =MIN(Goals!$B$6,Goals!$C$6+Goals!$D$6*15) -> 7250 | H17: =MIN(Goals!$B$7,Goals!$C$7+Goals!$D$7*15) -> 3450 | I17: =MIN(Goals!$B$8,Goals!$C$8+Goals!$D$8*15) -> 8500 | J17: =MIN('Emergency Fund'!$B$5,'Emergency Fund'!$B$7+'Emergency Fund'!$B$15*15) -> 18950 | K17: =MIN(Goals!$B$3,Goals!$C$3+(Goals!$D$3+'Emergency Fund'!$B$14/6)*15) -> 4500 | L17: =MIN(Goals!$B$4,Goals!$C$4+(Goals!$D$4+'Emergency Fund'!$B$14/6)*15) -> 18000 | M17: =MIN(Goals!$B$5,Goals!$C$5+(Goals!$D$5+'Emergency Fund'!$B$14/6)*15) -> 7450 | N17: =MIN(Goals!$B$6,Goals!$C$6+(Goals!$D$6+'Emergency Fund'!$B$14/6)*15) -> 7750 | O17: =MIN(Goals!$B$7,Goals!$C$7+(Goals!$D$7+'Emergency Fund'!$B$14/6)*15) -> 3950 | P17: =MIN(Goals!$B$8,Goals!$C$8+(Goals!$D$8+'Emergency Fund'!$B$14/6)*15) -> 9000
A18: 16 | B18: =TODAY()+15*30.44 -> 46578.6 | C18: =MIN('Emergency Fund'!$B$5,'Emergency Fund'!$B$7+'Emergency Fund'!$B$8*16) -> 16400 | D18: =MIN(Goals!$B$3,Goals!$C$3+Goals!$D$3*16) -> 4500 | E18: =MIN(Goals!$B$4,Goals!$C$4+Goals!$D$4*16) -> 18100 | F18: =MIN(Goals!$B$5,Goals!$C$5+Goals!$D$5*16) -> 7200 | G18: =MIN(Goals!$B$6,Goals!$C$6+Goals!$D$6*16) -> 7600 | H18: =MIN(Goals!$B$7,Goals!$C$7+Goals!$D$7*16) -> 3600 | I18: =MIN(Goals!$B$8,Goals!$C$8+Goals!$D$8*16) -> 8800 | J18: =MIN('Emergency Fund'!$B$5,'Emergency Fund'!$B$7+'Emergency Fund'!$B$15*16) -> 19600 | K18: =MIN(Goals!$B$3,Goals!$C$3+(Goals!$D$3+'Emergency Fund'!$B$14/6)*16) -> 4500 | L18: =MIN(Goals!$B$4,Goals!$C$4+(Goals!$D$4+'Emergency Fund'!$B$14/6)*16) -> 18633.333 | M18: =MIN(Goals!$B$5,Goals!$C$5+(Goals!$D$5+'Emergency Fund'!$B$14/6)*16) -> 7733.3333 | N18: =MIN(Goals!$B$6,Goals!$C$6+(Goals!$D$6+'Emergency Fund'!$B$14/6)*16) -> 8133.3333 | O18: =MIN(Goals!$B$7,Goals!$C$7+(Goals!$D$7+'Emergency Fund'!$B$14/6)*16) -> 4133.3333 | P18: =MIN(Goals!$B$8,Goals!$C$8+(Goals!$D$8+'Emergency Fund'!$B$14/6)*16) -> 9333.3333
A19: 17 | B19: =TODAY()+16*30.44 -> 46609.04 | C19: =MIN('Emergency Fund'!$B$5,'Emergency Fund'!$B$7+'Emergency Fund'!$B$8*17) -> 16850 | D19: =MIN(Goals!$B$3,Goals!$C$3+Goals!$D$3*17) -> 4500 | E19: =MIN(Goals!$B$4,Goals!$C$4+Goals!$D$4*17) -> 18700 | F19: =MIN(Goals!$B$5,Goals!$C$5+Goals!$D$5*17) -> 7450 | G19: =MIN(Goals!$B$6,Goals!$C$6+Goals!$D$6*17) -> 7950 | H19: =MIN(Goals!$B$7,Goals!$C$7+Goals!$D$7*17) -> 3750 | I19: =MIN(Goals!$B$8,Goals!$C$8+Goals!$D$8*17) -> 9100 | J19: =MIN('Emergency Fund'!$B$5,'Emergency Fund'!$B$7+'Emergency Fund'!$B$15*17) -> 20012 | K19: =MIN(Goals!$B$3,Goals!$C$3+(Goals!$D$3+'Emergency Fund'!$B$14/6)*17) -> 4500 | L19: =MIN(Goals!$B$4,Goals!$C$4+(Goals!$D$4+'Emergency Fund'!$B$14/6)*17) -> 19266.667 | M19: =MIN(Goals!$B$5,Goals!$C$5+(Goals!$D$5+'Emergency Fund'!$B$14/6)*17) -> 8016.6667 | N19: =MIN(Goals!$B$6,Goals!$C$6+(Goals!$D$6+'Emergency Fund'!$B$14/6)*17) -> 8516.6667 | O19: =MIN(Goals!$B$7,Goals!$C$7+(Goals!$D$7+'Emergency Fund'!$B$14/6)*17) -> 4316.6667 | P19: =MIN(Goals!$B$8,Goals!$C$8+(Goals!$D$8+'Emergency Fund'!$B$14/6)*17) -> 9666.6667
A20: 18 | B20: =TODAY()+17*30.44 -> 46639.48 | C20: =MIN('Emergency Fund'!$B$5,'Emergency Fund'!$B$7+'Emergency Fund'!$B$8*18) -> 17300 | D20: =MIN(Goals!$B$3,Goals!$C$3+Goals!$D$3*18) -> 4500 | E20: =MIN(Goals!$B$4,Goals!$C$4+Goals!$D$4*18) -> 19300 | F20: =MIN(Goals!$B$5,Goals!$C$5+Goals!$D$5*18) -> 7700 | G20: =MIN(Goals!$B$6,Goals!$C$6+Goals!$D$6*18) -> 8300 | H20: =MIN(Goals!$B$7,Goals!$C$7+Goals!$D$7*18) -> 3900 | I20: =MIN(Goals!$B$8,Goals!$C$8+Goals!$D$8*18) -> 9400 | J20: =MIN('Emergency Fund'!$B$5,'Emergency Fund'!$B$7+'Emergency Fund'!$B$15*18) -> 20012 | K20: =MIN(Goals!$B$3,Goals!$C$3+(Goals!$D$3+'Emergency Fund'!$B$14/6)*18) -> 4500 | L20: =MIN(Goals!$B$4,Goals!$C$4+(Goals!$D$4+'Emergency Fund'!$B$14/6)*18) -> 19900 | M20: =MIN(Goals!$B$5,Goals!$C$5+(Goals!$D$5+'Emergency Fund'!$B$14/6)*18) -> 8300 | N20: =MIN(Goals!$B$6,Goals!$C$6+(Goals!$D$6+'Emergency Fund'!$B$14/6)*18) -> 8900 | O20: =MIN(Goals!$B$7,Goals!$C$7+(Goals!$D$7+'Emergency Fund'!$B$14/6)*18) -> 4500 | P20: =MIN(Goals!$B$8,Goals!$C$8+(Goals!$D$8+'Emergency Fund'!$B$14/6)*18) -> 10000
A21: 19 | B21: =TODAY()+18*30.44 -> 46669.92 | C21: =MIN('Emergency Fund'!$B$5,'Emergency Fund'!$B$7+'Emergency Fund'!$B$8*19) -> 17750 | D21: =MIN(Goals!$B$3,Goals!$C$3+Goals!$D$3*19) -> 4500 | E21: =MIN(Goals!$B$4,Goals!$C$4+Goals!$D$4*19) -> 19900 | F21: =MIN(Goals!$B$5,Goals!$C$5+Goals!$D$5*19) -> 7950 | G21: =MIN(Goals!$B$6,Goals!$C$6+Goals!$D$6*19) -> 8650 | H21: =MIN(Goals!$B$7,Goals!$C$7+Goals!$D$7*19) -> 4050 | I21: =MIN(Goals!$B$8,Goals!$C$8+Goals!$D$8*19) -> 9700 | J21: =MIN('Emergency Fund'!$B$5,'Emergency Fund'!$B$7+'Emergency Fund'!$B$15*19) -> 20012 | K21: =MIN(Goals!$B$3,Goals!$C$3+(Goals!$D$3+'Emergency Fund'!$B$14/6)*19) -> 4500 | L21: =MIN(Goals!$B$4,Goals!$C$4+(Goals!$D$4+'Emergency Fund'!$B$14/6)*19) -> 20533.333 | M21: =MIN(Goals!$B$5,Goals!$C$5+(Goals!$D$5+'Emergency Fund'!$B$14/6)*19) -> 8583.3333 | N21: =MIN(Goals!$B$6,Goals!$C$6+(Goals!$D$6+'Emergency Fund'!$B$14/6)*19) -> 9283.3333 | O21: =MIN(Goals!$B$7,Goals!$C$7+(Goals!$D$7+'Emergency Fund'!$B$14/6)*19) -> 4683.3333 | P21: =MIN(Goals!$B$8,Goals!$C$8+(Goals!$D$8+'Emergency Fund'!$B$14/6)*19) -> 10333.333
A22: 20 | B22: =TODAY()+19*30.44 -> 46700.36 | C22: =MIN('Emergency Fund'!$B$5,'Emergency Fund'!$B$7+'Emergency Fund'!$B$8*20) -> 18200 | D22: =MIN(Goals!$B$3,Goals!$C$3+Goals!$D$3*20) -> 4500 | E22: =MIN(Goals!$B$4,Goals!$C$4+Goals!$D$4*20) -> 20500 | F22: =MIN(Goals!$B$5,Goals!$C$5+Goals!$D$5*20) -> 8200 | G22: =MIN(Goals!$B$6,Goals!$C$6+Goals!$D$6*20) -> 9000 | H22: =MIN(Goals!$B$7,Goals!$C$7+Goals!$D$7*20) -> 4200 | I22: =MIN(Goals!$B$8,Goals!$C$8+Goals!$D$8*20) -> 10000 | J22: =MIN('Emergency Fund'!$B$5,'Emergency Fund'!$B$7+'Emergency Fund'!$B$15*20) -> 20012 | K22: =MIN(Goals!$B$3,Goals!$C$3+(Goals!$D$3+'Emergency Fund'!$B$14/6)*20) -> 4500 | L22: =MIN(Goals!$B$4,Goals!$C$4+(Goals!$D$4+'Emergency Fund'!$B$14/6)*20) -> 21166.667 | M22: =MIN(Goals!$B$5,Goals!$C$5+(Goals!$D$5+'Emergency Fund'!$B$14/6)*20) -> 8866.6667 | N22: =MIN(Goals!$B$6,Goals!$C$6+(Goals!$D$6+'Emergency Fund'!$B$14/6)*20) -> 9666.6667 | O22: =MIN(Goals!$B$7,Goals!$C$7+(Goals!$D$7+'Emergency Fund'!$B$14/6)*20) -> 4866.6667 | P22: =MIN(Goals!$B$8,Goals!$C$8+(Goals!$D$8+'Emergency Fund'!$B$14/6)*20) -> 10666.667
A23: 21 | B23: =TODAY()+20*30.44 -> 46730.8 | C23: =MIN('Emergency Fund'!$B$5,'Emergency Fund'!$B$7+'Emergency Fund'!$B$8*21) -> 18650 | D23: =MIN(Goals!$B$3,Goals!$C$3+Goals!$D$3*21) -> 4500 | E23: =MIN(Goals!$B$4,Goals!$C$4+Goals!$D$4*21) -> 21100 | F23: =MIN(Goals!$B$5,Goals!$C$5+Goals!$D$5*21) -> 8450 | G23: =MIN(Goals!$B$6,Goals!$C$6+Goals!$D$6*21) -> 9350 | H23: =MIN(Goals!$B$7,Goals!$C$7+Goals!$D$7*21) -> 4350 | I23: =MIN(Goals!$B$8,Goals!$C$8+Goals!$D$8*21) -> 10300 | J23: =MIN('Emergency Fund'!$B$5,'Emergency Fund'!$B$7+'Emergency Fund'!$B$15*21) -> 20012 | K23: =MIN(Goals!$B$3,Goals!$C$3+(Goals!$D$3+'Emergency Fund'!$B$14/6)*21) -> 4500 | L23: =MIN(Goals!$B$4,Goals!$C$4+(Goals!$D$4+'Emergency Fund'!$B$14/6)*21) -> 21800 | M23: =MIN(Goals!$B$5,Goals!$C$5+(Goals!$D$5+'Emergency Fund'!$B$14/6)*21) -> 9150 | N23: =MIN(Goals!$B$6,Goals!$C$6+(Goals!$D$6+'Emergency Fund'!$B$14/6)*21) -> 10050 | O23: =MIN(Goals!$B$7,Goals!$C$7+(Goals!$D$7+'Emergency Fund'!$B$14/6)*21) -> 5050 | P23: =MIN(Goals!$B$8,Goals!$C$8+(Goals!$D$8+'Emergency Fund'!$B$14/6)*21) -> 11000
A24: 22 | B24: =TODAY()+21*30.44 -> 46761.24 | C24: =MIN('Emergency Fund'!$B$5,'Emergency Fund'!$B$7+'Emergency Fund'!$B$8*22) -> 19100 | D24: =MIN(Goals!$B$3,Goals!$C$3+Goals!$D$3*22) -> 4500 | E24: =MIN(Goals!$B$4,Goals!$C$4+Goals!$D$4*22) -> 21700 | F24: =MIN(Goals!$B$5,Goals!$C$5+Goals!$D$5*22) -> 8700 | G24: =MIN(Goals!$B$6,Goals!$C$6+Goals!$D$6*22) -> 9700 | H24: =MIN(Goals!$B$7,Goals!$C$7+Goals!$D$7*22) -> 4500 | I24: =MIN(Goals!$B$8,Goals!$C$8+Goals!$D$8*22) -> 10600 | J24: =MIN('Emergency Fund'!$B$5,'Emergency Fund'!$B$7+'Emergency Fund'!$B$15*22) -> 20012 | K24: =MIN(Goals!$B$3,Goals!$C$3+(Goals!$D$3+'Emergency Fund'!$B$14/6)*22) -> 4500 | L24: =MIN(Goals!$B$4,Goals!$C$4+(Goals!$D$4+'Emergency Fund'!$B$14/6)*22) -> 22433.333 | M24: =MIN(Goals!$B$5,Goals!$C$5+(Goals!$D$5+'Emergency Fund'!$B$14/6)*22) -> 9433.3333 | N24: =MIN(Goals!$B$6,Goals!$C$6+(Goals!$D$6+'Emergency Fund'!$B$14/6)*22) -> 10433.333 | O24: =MIN(Goals!$B$7,Goals!$C$7+(Goals!$D$7+'Emergency Fund'!$B$14/6)*22) -> 5233.3333 | P24: =MIN(Goals!$B$8,Goals!$C$8+(Goals!$D$8+'Emergency Fund'!$B$14/6)*22) -> 11333.333
A25: 23 | B25: =TODAY()+22*30.44 -> 46791.68 | C25: =MIN('Emergency Fund'!$B$5,'Emergency Fund'!$B$7+'Emergency Fund'!$B$8*23) -> 19550 | D25: =MIN(Goals!$B$3,Goals!$C$3+Goals!$D$3*23) -> 4500 | E25: =MIN(Goals!$B$4,Goals!$C$4+Goals!$D$4*23) -> 22300 | F25: =MIN(Goals!$B$5,Goals!$C$5+Goals!$D$5*23) -> 8950 | G25: =MIN(Goals!$B$6,Goals!$C$6+Goals!$D$6*23) -> 10050 | H25: =MIN(Goals!$B$7,Goals!$C$7+Goals!$D$7*23) -> 4650 | I25: =MIN(Goals!$B$8,Goals!$C$8+Goals!$D$8*23) -> 10900 | J25: =MIN('Emergency Fund'!$B$5,'Emergency Fund'!$B$7+'Emergency Fund'!$B$15*23) -> 20012 | K25: =MIN(Goals!$B$3,Goals!$C$3+(Goals!$D$3+'Emergency Fund'!$B$14/6)*23) -> 4500 | L25: =MIN(Goals!$B$4,Goals!$C$4+(Goals!$D$4+'Emergency Fund'!$B$14/6)*23) -> 23066.667 | M25: =MIN(Goals!$B$5,Goals!$C$5+(Goals!$D$5+'Emergency Fund'!$B$14/6)*23) -> 9716.6667 | N25: =MIN(Goals!$B$6,Goals!$C$6+(Goals!$D$6+'Emergency Fund'!$B$14/6)*23) -> 10816.667 | O25: =MIN(Goals!$B$7,Goals!$C$7+(Goals!$D$7+'Emergency Fund'!$B$14/6)*23) -> 5416.6667 | P25: =MIN(Goals!$B$8,Goals!$C$8+(Goals!$D$8+'Emergency Fund'!$B$14/6)*23) -> 11666.667
A26: 24 | B26: =TODAY()+23*30.44 -> 46822.12 | C26: =MIN('Emergency Fund'!$B$5,'Emergency Fund'!$B$7+'Emergency Fund'!$B$8*24) -> 20000 | D26: =MIN(Goals!$B$3,Goals!$C$3+Goals!$D$3*24) -> 4500 | E26: =MIN(Goals!$B$4,Goals!$C$4+Goals!$D$4*24) -> 22900 | F26: =MIN(Goals!$B$5,Goals!$C$5+Goals!$D$5*24) -> 9200 | G26: =MIN(Goals!$B$6,Goals!$C$6+Goals!$D$6*24) -> 10400 | H26: =MIN(Goals!$B$7,Goals!$C$7+Goals!$D$7*24) -> 4800 | I26: =MIN(Goals!$B$8,Goals!$C$8+Goals!$D$8*24) -> 11200 | J26: =MIN('Emergency Fund'!$B$5,'Emergency Fund'!$B$7+'Emergency Fund'!$B$15*24) -> 20012 | K26: =MIN(Goals!$B$3,Goals!$C$3+(Goals!$D$3+'Emergency Fund'!$B$14/6)*24) -> 4500 | L26: =MIN(Goals!$B$4,Goals!$C$4+(Goals!$D$4+'Emergency Fund'!$B$14/6)*24) -> 23700 | M26: =MIN(Goals!$B$5,Goals!$C$5+(Goals!$D$5+'Emergency Fund'!$B$14/6)*24) -> 10000 | N26: =MIN(Goals!$B$6,Goals!$C$6+(Goals!$D$6+'Emergency Fund'!$B$14/6)*24) -> 11200 | O26: =MIN(Goals!$B$7,Goals!$C$7+(Goals!$D$7+'Emergency Fund'!$B$14/6)*24) -> 5600 | P26: =MIN(Goals!$B$8,Goals!$C$8+(Goals!$D$8+'Emergency Fund'!$B$14/6)*24) -> 12000

Sheet Dashboard
A1: Savings Dashboard
A2: Emergency fund and goal snapshot
A3: Emergency Fund Progress
A4: Category | B4: Current | C4: Target
A5: Emergency Fund | B5: ='Emergency Fund'!B7 -> 9200 | C5: ='Emergency Fund'!B5 -> 20012
A8: Goal | B8: Current | C8: Target
A9: =Goals!A3 -> Vacation | B9: =Goals!C3 -> 1800 | C9: =Goals!B3 -> 4500
A10: =Goals!A4 -> House Down Payment | B10: =Goals!C4 -> 8500 | C10: =Goals!B4 -> 50000
A11: =Goals!A5 -> New Car | B11: =Goals!C5 -> 3200 | C11: =Goals!B5 -> 12000
A12: =Goals!A6 -> Wedding | B12: =Goals!C6 -> 2000 | C12: =Goals!B6 -> 18000
A13: =Goals!A7 -> Home Renovation | B13: =Goals!C7 -> 1200 | C13: =Goals!B7 -> 8000
A14: =Goals!A8 -> Sabbatical Fund | B14: =Goals!C8 -> 4000 | C14: =Goals!B8 -> 25000
A16: Summary
A17: Total Saved (all goals + EF) | B17: ='Emergency Fund'!B7+SUM(Goals!C3:C8) -> 29900
A18: Total Monthly Contributions | B18: ='Emergency Fund'!B8+SUM(Goals!D3:D8) -> 2300
A19: Avg Months to Completion | B19: =AVERAGE(Goals!F3:F8) -> 46.485714

Sheet Readme
A1: Emergency Fund and Savings Goal Planner
A2: Sample data covers a hypothetical 2025 scenario.
A3: All expenses and balances are fictional.
A4: Start by filling in your actual essential expenses on the Monthly Expenses sheet.
A5: The Emergency Fund target is derived from your average monthly expenses.
A6: Set your coverage months (3 or 6 or 9 or 12) on the Emergency Fund sheet.
A7: Log contributions monthly on the Contributions sheet.
A8: Do not insert or delete rows inside the data ranges.
A9: This is not financial advice. Talk to a professional about your situation.
