Workbook

Sheet Envelopes
B2: Envelope Setup
B3: Envelope | C3: Group | D3: Monthly Target | E3: Rollover | F3: Priority | G3: Annual Target
B4: Rent | C4: Essentials | D4: 1500 | E4: Yes | F4: 1 | G4: =D4*12
B5: Utilities | C5: Essentials | D5: 170 | E5: Yes | F5: 2 | G5: =D5*12
B6: Groceries | C6: Essentials | D6: 400 | E6: Yes | F6: 3 | G6: =D6*12
B7: Gas | C7: Essentials | D7: 130 | E7: Yes | F7: 4 | G7: =D7*12
B8: Auto Insurance | C8: Essentials | D8: 110 | E8: Yes | F8: 5 | G8: =D8*12
B9: Phone | C9: Essentials | D9: 75 | E9: Yes | F9: 6 | G9: =D9*12
B10: Medical | C10: Essentials | D10: 60 | E10: Yes | F10: 7 | G10: =D10*12
B11: Dining Out | C11: Lifestyle | D11: 160 | E11: No | F11: 8 | G11: =D11*12
B12: Coffee | C12: Lifestyle | D12: 40 | E12: No | F12: 9 | G12: =D12*12
B13: Entertainment | C13: Lifestyle | D13: 80 | E13: No | F13: 10 | G13: =D13*12
B14: Clothing | C14: Lifestyle | D14: 70 | E14: No | F14: 11 | G14: =D14*12
B15: Personal Care | C15: Lifestyle | D15: 35 | E15: No | F15: 12 | G15: =D15*12
... B19: Car Repair Fund | C19: Goals | D19: 80 | E19: Yes | F19: 16 | G19: =D19*12

Sheet Funding
B2: Paycheck Funding
B3: Pay Date | C3: Gross Pay | D3: Net Pay | E3: Rent | F3: Utilities | G3: Groceries | H3: Gas | I3: Auto Insurance | J3: Phone | K3: Medical | L3: Dining Out | M3: Coffee | N3: Entertainment | O3: Clothing | P3: Personal Care | Q3: Subscriptions | R3: Emergency Fund | S3: Vacation | T3: Car Repair Fund | U3: Remainder
B4: 45660 | C4: 3200 | D4: 2400 | E4: 690 | F4: 72 | G4: 188 | H4: 61 | I4: 44 | J4: 39 | K4: 37 | L4: 79 | M4: 27 | N4: 27 | O4: 38 | P4: 19 | Q4: 31 | R4: 115 | S4: 55 | T4: 37 | U4: =D4-SUM(E4:T4)
B5: 45674 | C5: 3200 | D5: 2400 | E5: 700 | F5: 85 | G5: 187 | H5: 62 | I5: 46 | J5: 26 | K5: 21 | L5: 67 | M5: 20 | N5: 31 | O5: 25 | P5: 11 | Q5: 29 | R5: 115 | S5: 55 | T5: 37 | U5: =D5-SUM(E5:T5)
B6: 45688 | C6: 3400 | D6: 2550 | E6: 685 | F6: 80 | G6: 193 | H6: 66 | I6: 49 | J6: 43 | K6: 23 | L6: 76 | M6: 10 | N6: 28 | O6: 40 | P6: 7 | Q6: 18 | R6: 115 | S6: 55 | T6: 37 | U6: =D6-SUM(E6:T6)
B7: 45702 | C7: 3200 | D7: 2400 | E7: 686 | F7: 77 | G7: 182 | H7: 52 | I7: 57 | J7: 44 | K7: 21 | L7: 82 | M7: 28 | N7: 47 | O7: 23 | P7: 9 | Q7: 32 | R7: 115 | S7: 55 | T7: 37 | U7: =D7-SUM(E7:T7)
B8: 45716 | C8: 3400 | D8: 2550 | E8: 701 | F8: 78 | G8: 184 | H8: 66 | I8: 55 | J8: 30 | K8: 22 | L8: 66 | M8: 18 | N8: 28 | O8: 40 | P8: 14 | Q8: 24 | R8: 115 | S8: 55 | T8: 37 | U8: =D8-SUM(E8:T8)
B9: 45730 | C9: 3200 | D9: 2400 | E9: 700 | F9: 70 | G9: 191 | H9: 53 | I9: 50 | J9: 40 | K9: 29 | L9: 77 | M9: 9 | N9: 42 | O9: 35 | P9: 25 | Q9: 15 | R9: 115 | S9: 55 | T9: 37 | U9: =D9-SUM(E9:T9)
B10: 45744 | C10: 3200 | D10: 2400 | E10: 685 | F10: 88 | G10: 176 | H10: 54 | I10: 59 | J10: 34 | K10: 21 | L10: 81 | M10: 21 | N10: 41 | O10: 40 | P10: 7 | Q10: 17 | R10: 115 | S10: 55 | T10: 37 | U10: =D10-SUM(E10:T10)
B11: 45758 | C11: 3200 | D11: 2400 | E11: 684 | F11: 71 | G11: 178 | H11: 50 | I11: 51 | J11: 28 | K11: 35 | L11: 79 | M11: 16 | N11: 41 | O11: 32 | P11: 18 | Q11: 15 | R11: 115 | S11: 55 | T11: 37 | U11: =D11-SUM(E11:T11)
B12: 45772 | C12: 3200 | D12: 2400 | E12: 683 | F12: 74 | G12: 186 | H12: 56 | I12: 59 | J12: 37 | K12: 26 | L12: 83 | M12: 26 | N12: 40 | O12: 32 | P12: 18 | Q12: 24 | R12: 115 | S12: 55 | T12: 37 | U12: =D12-SUM(E12:T12)
B13: 45786 | C13: 3200 | D13: 2400 | E13: 686 | F13: 85 | G13: 179 | H13: 56 | I13: 42 | J13: 32 | K13: 27 | L13: 71 | M13: 19 | N13: 33 | O13: 28 | P13: 18 | Q13: 25 | R13: 115 | S13: 55 | T13: 37 | U13: =D13-SUM(E13:T13)
B14: 45800 | C14: 3200 | D14: 2400 | E14: 682 | F14: 82 | G14: 190 | H14: 51 | I14: 44 | J14: 25 | K14: 18 | L14: 81 | M14: 27 | N14: 43 | O14: 38 | P14: 22 | Q14: 16 | R14: 115 | S14: 55 | T14: 37 | U14: =D14-SUM(E14:T14)
B15: 45814 | C15: 3200 | D15: 2400 | E15: 689 | F15: 75 | G15: 178 | H15: 64 | I15: 53 | J15: 29 | K15: 25 | L15: 64 | M15: 11 | N15: 34 | O15: 25 | P15: 24 | Q15: 32 | R15: 115 | S15: 55 | T15: 37 | U15: =D15-SUM(E15:T15)
... B29: 46010 | C29: 3200 | D29: 2400 | E29: 682 | F29: 80 | G29: 175 | H29: 53 | I29: 44 | J29: 34 | K29: 18 | L29: 66 | M29: 27 | N29: 43 | O29: 29 | P29: 14 | Q29: 21 | R29: 115 | S29: 55 | T29: 37 | U29: =D29-SUM(E29:T29)

Sheet Spending
B2: Spending Log
B3: Date | C3: Payee | D3: Amount | E3: Envelope | F3: Notes
B4: 45671 | C4: Landlord | D4: 1500 | E4: Rent
B5: 45667 | C5: Power Co | D5: 153.62 | E5: Utilities
B6: 45663 | C6: Trader Joes | D6: 154 | E6: Groceries
B7: 45680 | C7: Costco | D7: 141.06 | E7: Groceries
B8: 45669 | C8: Shell | D8: 78.84 | E8: Gas
B9: 45668 | C9: BP | D9: 73.84 | E9: Gas
B10: 45677 | C10: Geico | D10: 110 | E10: Auto Insurance
B11: 45661 | C11: T-Mobile | D11: 75 | E11: Phone
B12: 45668 | C12: CVS | D12: 48.96 | E12: Medical
B13: 45673 | C13: Thai Kitchen | D13: 47.72 | E13: Dining Out
B14: 45664 | C14: Thai Kitchen | D14: 34.95 | E14: Dining Out
B15: 45666 | C15: Thai Kitchen | D15: 36.27 | E15: Dining Out
... B278: 46016 | C278: Netflix | D278: 52.06 | E278: Subscriptions

Sheet Monthly Balances
B2: Monthly Envelope Balances
B3: Envelope | C3: Jan Starting | D3: Jan Funded | E3: Jan Spent | F3: Jan Ending | G3: Feb Starting | H3: Feb Funded | I3: Feb Spent | J3: Feb Ending | K3: Mar Starting | L3: Mar Funded | M3: Mar Spent | N3: Mar Ending | O3: Apr Starting | P3: Apr Funded | Q3: Apr Spent | R3: Apr Ending | S3: May Starting | T3: May Funded | U3: May Spent | V3: May Ending | W3: Jun Starting | X3: Jun Funded | Y3: Jun Spent | Z3: Jun Ending | AA3: Jul Starting | AB3: Jul Funded | AC3: Jul Spent | AD3: Jul Ending | AE3: Aug Starting | AF3: Aug Funded | AG3: Aug Spent | AH3: Aug Ending | AI3: Sep Starting | AJ3: Sep Funded | AK3: Sep Spent | AL3: Sep Ending | AM3: Oct Starting | AN3: Oct Funded | AO3: Oct Spent | AP3: Oct Ending | AQ3: Nov Starting | AR3: Nov Funded | AS3: Nov Spent | AT3: Nov Ending | AU3: Dec Starting | AV3: Dec Funded | AW3: Dec Spent | AX3: Dec Ending
B4: Rent | C4: 0 | D4: =SUMPRODUCT((MONTH(Funding!$B$4:$B$29)=1)*Funding!E$4:E$29) | E4: =SUMPRODUCT((MONTH(Spending!$B$4:$B$278)=1)*(Spending!$E$4:$E$278="Rent")*Spending!$D$4:$D$278) | F4: =C4+D4-E4 | G4: =IF(Envelopes!$E$4="Yes",F4,0) | H4: =SUMPRODUCT((MONTH(Funding!$B$4:$B$29)=2)*Funding!E$4:E$29) | I4: =SUMPRODUCT((MONTH(Spending!$B$4:$B$278)=2)*(Spending!$E$4:$E$278="Rent")*Spending!$D$4:$D$278) | J4: =G4+H4-I4 | K4: =IF(Envelopes!$E$4="Yes",J4,0) | L4: =SUMPRODUCT((MONTH(Funding!$B$4:$B$29)=3)*Funding!E$4:E$29) | M4: =SUMPRODUCT((MONTH(Spending!$B$4:$B$278)=3)*(Spending!$E$4:$E$278="Rent")*Spending!$D$4:$D$278) | N4: =K4+L4-M4 | O4: =IF(Envelopes!$E$4="Yes",N4,0) | P4: =SUMPRODUCT((MONTH(Funding!$B$4:$B$29)=4)*Funding!E$4:E$29) | Q4: =SUMPRODUCT((MONTH(Spending!$B$4:$B$278)=4)*(Spending!$E$4:$E$278="Rent")*Spending!$D$4:$D$278) | R4: =O4+P4-Q4 | S4: =IF(Envelopes!$E$4="Yes",R4,0) | T4: =SUMPRODUCT((MONTH(Funding!$B$4:$B$29)=5)*Funding!E$4:E$29) | U4: =SUMPRODUCT((MONTH(Spending!$B$4:$B$278)=5)*(Spending!$E$4:$E$278="Rent")*Spending!$D$4:$D$278) | V4: =S4+T4-U4 | W4: =IF(Envelopes!$E$4="Yes",V4,0) | X4: =SUMPRODUCT((MONTH(Funding!$B$4:$B$29)=6)*Funding!E$4:E$29) | Y4: =SUMPRODUCT((MONTH(Spending!$B$4:$B$278)=6)*(Spending!$E$4:$E$278="Rent")*Spending!$D$4:$D$278) | Z4: =W4+X4-Y4 | AA4: =IF(Envelopes!$E$4="Yes",Z4,0) | AB4: =SUMPRODUCT((MONTH(Funding!$B$4:$B$29)=7)*Funding!E$4:E$29) | AC4: =SUMPRODUCT((MONTH(Spending!$B$4:$B$278)=7)*(Spending!$E$4:$E$278="Rent")*Spending!$D$4:$D$278) | AD4: =AA4+AB4-AC4 | AE4: =IF(Envelopes!$E$4="Yes",AD4,0) | AF4: =SUMPRODUCT((MONTH(Funding!$B$4:$B$29)=8)*Funding!E$4:E$29) | AG4: =SUMPRODUCT((MONTH(Spending!$B$4:$B$278)=8)*(Spending!$E$4:$E$278="Rent")*Spending!$D$4:$D$278) | AH4: =AE4+AF4-AG4 | AI4: =IF(Envelopes!$E$4="Yes",AH4,0) | AJ4: =SUMPRODUCT((MONTH(Funding!$B$4:$B$29)=9)*Funding!E$4:E$29) | AK4: =SUMPRODUCT((MONTH(Spending!$B$4:$B$278)=9)*(Spending!$E$4:$E$278="Rent")*Spending!$D$4:$D$278) | AL4: =AI4+AJ4-AK4 | AM4: =IF(Envelopes!$E$4="Yes",AL4,0) | AN4: =SUMPRODUCT((MONTH(Funding!$B$4:$B$29)=10)*Funding!E$4:E$29) | AO4: =SUMPRODUCT((MONTH(Spending!$B$4:$B$278)=10)*(Spending!$E$4:$E$278="Rent")*Spending!$D$4:$D$278) | AP4: =AM4+AN4-AO4 | AQ4: =IF(Envelopes!$E$4="Yes",AP4,0) | AR4: =SUMPRODUCT((MONTH(Funding!$B$4:$B$29)=11)*Funding!E$4:E$29) | AS4: =SUMPRODUCT((MONTH(Spending!$B$4:$B$278)=11)*(Spending!$E$4:$E$278="Rent")*Spending!$D$4:$D$278) | AT4: =AQ4+AR4-AS4 | AU4: =IF(Envelopes!$E$4="Yes",AT4,0) | AV4: =SUMPRODUCT((MONTH(Funding!$B$4:$B$29)=12)*Funding!E$4:E$29) | AW4: =SUMPRODUCT((MONTH(Spending!$B$4:$B$278)=12)*(Spending!$E$4:$E$278="Rent")*Spending!$D$4:$D$278) | AX4: =AU4+AV4-AW4
B5: Utilities | C5: 0 | D5: =SUMPRODUCT((MONTH(Funding!$B$4:$B$29)=1)*Funding!F$4:F$29) | E5: =SUMPRODUCT((MONTH(Spending!$B$4:$B$278)=1)*(Spending!$E$4:$E$278="Utilities")*Spending!$D$4:$D$278) | F5: =C5+D5-E5 | G5: =IF(Envelopes!$E$5="Yes",F5,0) | H5: =SUMPRODUCT((MONTH(Funding!$B$4:$B$29)=2)*Funding!F$4:F$29) | I5: =SUMPRODUCT((MONTH(Spending!$B$4:$B$278)=2)*(Spending!$E$4:$E$278="Utilities")*Spending!$D$4:$D$278) | J5: =G5+H5-I5 | K5: =IF(Envelopes!$E$5="Yes",J5,0) | L5: =SUMPRODUCT((MONTH(Funding!$B$4:$B$29)=3)*Funding!F$4:F$29) | M5: =SUMPRODUCT((MONTH(Spending!$B$4:$B$278)=3)*(Spending!$E$4:$E$278="Utilities")*Spending!$D$4:$D$278) | N5: =K5+L5-M5 | O5: =IF(Envelopes!$E$5="Yes",N5,0) | P5: =SUMPRODUCT((MONTH(Funding!$B$4:$B$29)=4)*Funding!F$4:F$29) | Q5: =SUMPRODUCT((MONTH(Spending!$B$4:$B$278)=4)*(Spending!$E$4:$E$278="Utilities")*Spending!$D$4:$D$278) | R5: =O5+P5-Q5 | S5: =IF(Envelopes!$E$5="Yes",R5,0) | T5: =SUMPRODUCT((MONTH(Funding!$B$4:$B$29)=5)*Funding!F$4:F$29) | U5: =SUMPRODUCT((MONTH(Spending!$B$4:$B$278)=5)*(Spending!$E$4:$E$278="Utilities")*Spending!$D$4:$D$278) | V5: =S5+T5-U5 | W5: =IF(Envelopes!$E$5="Yes",V5,0) | X5: =SUMPRODUCT((MONTH(Funding!$B$4:$B$29)=6)*Funding!F$4:F$29) | Y5: =SUMPRODUCT((MONTH(Spending!$B$4:$B$278)=6)*(Spending!$E$4:$E$278="Utilities")*Spending!$D$4:$D$278) | Z5: =W5+X5-Y5 | AA5: =IF(Envelopes!$E$5="Yes",Z5,0) | AB5: =SUMPRODUCT((MONTH(Funding!$B$4:$B$29)=7)*Funding!F$4:F$29) | AC5: =SUMPRODUCT((MONTH(Spending!$B$4:$B$278)=7)*(Spending!$E$4:$E$278="Utilities")*Spending!$D$4:$D$278) | AD5: =AA5+AB5-AC5 | AE5: =IF(Envelopes!$E$5="Yes",AD5,0) | AF5: =SUMPRODUCT((MONTH(Funding!$B$4:$B$29)=8)*Funding!F$4:F$29) | AG5: =SUMPRODUCT((MONTH(Spending!$B$4:$B$278)=8)*(Spending!$E$4:$E$278="Utilities")*Spending!$D$4:$D$278) | AH5: =AE5+AF5-AG5 | AI5: =IF(Envelopes!$E$5="Yes",AH5,0) | AJ5: =SUMPRODUCT((MONTH(Funding!$B$4:$B$29)=9)*Funding!F$4:F$29) | AK5: =SUMPRODUCT((MONTH(Spending!$B$4:$B$278)=9)*(Spending!$E$4:$E$278="Utilities")*Spending!$D$4:$D$278) | AL5: =AI5+AJ5-AK5 | AM5: =IF(Envelopes!$E$5="Yes",AL5,0) | AN5: =SUMPRODUCT((MONTH(Funding!$B$4:$B$29)=10)*Funding!F$4:F$29) | AO5: =SUMPRODUCT((MONTH(Spending!$B$4:$B$278)=10)*(Spending!$E$4:$E$278="Utilities")*Spending!$D$4:$D$278) | AP5: =AM5+AN5-AO5 | AQ5: =IF(Envelopes!$E$5="Yes",AP5,0) | AR5: =SUMPRODUCT((MONTH(Funding!$B$4:$B$29)=11)*Funding!F$4:F$29) | AS5: =SUMPRODUCT((MONTH(Spending!$B$4:$B$278)=11)*(Spending!$E$4:$E$278="Utilities")*Spending!$D$4:$D$278) | AT5: =AQ5+AR5-AS5 | AU5: =IF(Envelopes!$E$5="Yes",AT5,0) | AV5: =SUMPRODUCT((MONTH(Funding!$B$4:$B$29)=12)*Funding!F$4:F$29) | AW5: =SUMPRODUCT((MONTH(Spending!$B$4:$B$278)=12)*(Spending!$E$4:$E$278="Utilities")*Spending!$D$4:$D$278) | AX5: =AU5+AV5-AW5
B6: Groceries | C6: 0 | D6: =SUMPRODUCT((MONTH(Funding!$B$4:$B$29)=1)*Funding!G$4:G$29) | E6: =SUMPRODUCT((MONTH(Spending!$B$4:$B$278)=1)*(Spending!$E$4:$E$278="Groceries")*Spending!$D$4:$D$278) | F6: =C6+D6-E6 | G6: =IF(Envelopes!$E$6="Yes",F6,0) | H6: =SUMPRODUCT((MONTH(Funding!$B$4:$B$29)=2)*Funding!G$4:G$29) | I6: =SUMPRODUCT((MONTH(Spending!$B$4:$B$278)=2)*(Spending!$E$4:$E$278="Groceries")*Spending!$D$4:$D$278) | J6: =G6+H6-I6 | K6: =IF(Envelopes!$E$6="Yes",J6,0) | L6: =SUMPRODUCT((MONTH(Funding!$B$4:$B$29)=3)*Funding!G$4:G$29) | M6: =SUMPRODUCT((MONTH(Spending!$B$4:$B$278)=3)*(Spending!$E$4:$E$278="Groceries")*Spending!$D$4:$D$278) | N6: =K6+L6-M6 | O6: =IF(Envelopes!$E$6="Yes",N6,0) | P6: =SUMPRODUCT((MONTH(Funding!$B$4:$B$29)=4)*Funding!G$4:G$29) | Q6: =SUMPRODUCT((MONTH(Spending!$B$4:$B$278)=4)*(Spending!$E$4:$E$278="Groceries")*Spending!$D$4:$D$278) | R6: =O6+P6-Q6 | S6: =IF(Envelopes!$E$6="Yes",R6,0) | T6: =SUMPRODUCT((MONTH(Funding!$B$4:$B$29)=5)*Funding!G$4:G$29) | U6: =SUMPRODUCT((MONTH(Spending!$B$4:$B$278)=5)*(Spending!$E$4:$E$278="Groceries")*Spending!$D$4:$D$278) | V6: =S6+T6-U6 | W6: =IF(Envelopes!$E$6="Yes",V6,0) | X6: =SUMPRODUCT((MONTH(Funding!$B$4:$B$29)=6)*Funding!G$4:G$29) | Y6: =SUMPRODUCT((MONTH(Spending!$B$4:$B$278)=6)*(Spending!$E$4:$E$278="Groceries")*Spending!$D$4:$D$278) | Z6: =W6+X6-Y6 | AA6: =IF(Envelopes!$E$6="Yes",Z6,0) | AB6: =SUMPRODUCT((MONTH(Funding!$B$4:$B$29)=7)*Funding!G$4:G$29) | AC6: =SUMPRODUCT((MONTH(Spending!$B$4:$B$278)=7)*(Spending!$E$4:$E$278="Groceries")*Spending!$D$4:$D$278) | AD6: =AA6+AB6-AC6 | AE6: =IF(Envelopes!$E$6="Yes",AD6,0) | AF6: =SUMPRODUCT((MONTH(Funding!$B$4:$B$29)=8)*Funding!G$4:G$29) | AG6: =SUMPRODUCT((MONTH(Spending!$B$4:$B$278)=8)*(Spending!$E$4:$E$278="Groceries")*Spending!$D$4:$D$278) | AH6: =AE6+AF6-AG6 | AI6: =IF(Envelopes!$E$6="Yes",AH6,0) | AJ6: =SUMPRODUCT((MONTH(Funding!$B$4:$B$29)=9)*Funding!G$4:G$29) | AK6: =SUMPRODUCT((MONTH(Spending!$B$4:$B$278)=9)*(Spending!$E$4:$E$278="Groceries")*Spending!$D$4:$D$278) | AL6: =AI6+AJ6-AK6 | AM6: =IF(Envelopes!$E$6="Yes",AL6,0) | AN6: =SUMPRODUCT((MONTH(Funding!$B$4:$B$29)=10)*Funding!G$4:G$29) | AO6: =SUMPRODUCT((MONTH(Spending!$B$4:$B$278)=10)*(Spending!$E$4:$E$278="Groceries")*Spending!$D$4:$D$278) | AP6: =AM6+AN6-AO6 | AQ6: =IF(Envelopes!$E$6="Yes",AP6,0) | AR6: =SUMPRODUCT((MONTH(Funding!$B$4:$B$29)=11)*Funding!G$4:G$29) | AS6: =SUMPRODUCT((MONTH(Spending!$B$4:$B$278)=11)*(Spending!$E$4:$E$278="Groceries")*Spending!$D$4:$D$278) | AT6: =AQ6+AR6-AS6 | AU6: =IF(Envelopes!$E$6="Yes",AT6,0) | AV6: =SUMPRODUCT((MONTH(Funding!$B$4:$B$29)=12)*Funding!G$4:G$29) | AW6: =SUMPRODUCT((MONTH(Spending!$B$4:$B$278)=12)*(Spending!$E$4:$E$278="Groceries")*Spending!$D$4:$D$278) | AX6: =AU6+AV6-AW6
B7: Gas | C7: 0 | D7: =SUMPRODUCT((MONTH(Funding!$B$4:$B$29)=1)*Funding!H$4:H$29) | E7: =SUMPRODUCT((MONTH(Spending!$B$4:$B$278)=1)*(Spending!$E$4:$E$278="Gas")*Spending!$D$4:$D$278) | F7: =C7+D7-E7 | G7: =IF(Envelopes!$E$7="Yes",F7,0) | H7: =SUMPRODUCT((MONTH(Funding!$B$4:$B$29)=2)*Funding!H$4:H$29) | I7: =SUMPRODUCT((MONTH(Spending!$B$4:$B$278)=2)*(Spending!$E$4:$E$278="Gas")*Spending!$D$4:$D$278) | J7: =G7+H7-I7 | K7: =IF(Envelopes!$E$7="Yes",J7,0) | L7: =SUMPRODUCT((MONTH(Funding!$B$4:$B$29)=3)*Funding!H$4:H$29) | M7: =SUMPRODUCT((MONTH(Spending!$B$4:$B$278)=3)*(Spending!$E$4:$E$278="Gas")*Spending!$D$4:$D$278) | N7: =K7+L7-M7 | O7: =IF(Envelopes!$E$7="Yes",N7,0) | P7: =SUMPRODUCT((MONTH(Funding!$B$4:$B$29)=4)*Funding!H$4:H$29) | Q7: =SUMPRODUCT((MONTH(Spending!$B$4:$B$278)=4)*(Spending!$E$4:$E$278="Gas")*Spending!$D$4:$D$278) | R7: =O7+P7-Q7 | S7: =IF(Envelopes!$E$7="Yes",R7,0) | T7: =SUMPRODUCT((MONTH(Funding!$B$4:$B$29)=5)*Funding!H$4:H$29) | U7: =SUMPRODUCT((MONTH(Spending!$B$4:$B$278)=5)*(Spending!$E$4:$E$278="Gas")*Spending!$D$4:$D$278) | V7: =S7+T7-U7 | W7: =IF(Envelopes!$E$7="Yes",V7,0) | X7: =SUMPRODUCT((MONTH(Funding!$B$4:$B$29)=6)*Funding!H$4:H$29) | Y7: =SUMPRODUCT((MONTH(Spending!$B$4:$B$278)=6)*(Spending!$E$4:$E$278="Gas")*Spending!$D$4:$D$278) | Z7: =W7+X7-Y7 | AA7: =IF(Envelopes!$E$7="Yes",Z7,0) | AB7: =SUMPRODUCT((MONTH(Funding!$B$4:$B$29)=7)*Funding!H$4:H$29) | AC7: =SUMPRODUCT((MONTH(Spending!$B$4:$B$278)=7)*(Spending!$E$4:$E$278="Gas")*Spending!$D$4:$D$278) | AD7: =AA7+AB7-AC7 | AE7: =IF(Envelopes!$E$7="Yes",AD7,0) | AF7: =SUMPRODUCT((MONTH(Funding!$B$4:$B$29)=8)*Funding!H$4:H$29) | AG7: =SUMPRODUCT((MONTH(Spending!$B$4:$B$278)=8)*(Spending!$E$4:$E$278="Gas")*Spending!$D$4:$D$278) | AH7: =AE7+AF7-AG7 | AI7: =IF(Envelopes!$E$7="Yes",AH7,0) | AJ7: =SUMPRODUCT((MONTH(Funding!$B$4:$B$29)=9)*Funding!H$4:H$29) | AK7: =SUMPRODUCT((MONTH(Spending!$B$4:$B$278)=9)*(Spending!$E$4:$E$278="Gas")*Spending!$D$4:$D$278) | AL7: =AI7+AJ7-AK7 | AM7: =IF(Envelopes!$E$7="Yes",AL7,0) | AN7: =SUMPRODUCT((MONTH(Funding!$B$4:$B$29)=10)*Funding!H$4:H$29) | AO7: =SUMPRODUCT((MONTH(Spending!$B$4:$B$278)=10)*(Spending!$E$4:$E$278="Gas")*Spending!$D$4:$D$278) | AP7: =AM7+AN7-AO7 | AQ7: =IF(Envelopes!$E$7="Yes",AP7,0) | AR7: =SUMPRODUCT((MONTH(Funding!$B$4:$B$29)=11)*Funding!H$4:H$29) | AS7: =SUMPRODUCT((MONTH(Spending!$B$4:$B$278)=11)*(Spending!$E$4:$E$278="Gas")*Spending!$D$4:$D$278) | AT7: =AQ7+AR7-AS7 | AU7: =IF(Envelopes!$E$7="Yes",AT7,0) | AV7: =SUMPRODUCT((MONTH(Funding!$B$4:$B$29)=12)*Funding!H$4:H$29) | AW7: =SUMPRODUCT((MONTH(Spending!$B$4:$B$278)=12)*(Spending!$E$4:$E$278="Gas")*Spending!$D$4:$D$278) | AX7: =AU7+AV7-AW7
B8: Auto Insurance | C8: 0 | D8: =SUMPRODUCT((MONTH(Funding!$B$4:$B$29)=1)*Funding!I$4:I$29) | E8: =SUMPRODUCT((MONTH(Spending!$B$4:$B$278)=1)*(Spending!$E$4:$E$278="Auto Insurance")*Spending!$D$4:$D$278) | F8: =C8+D8-E8 | G8: =IF(Envelopes!$E$8="Yes",F8,0) | H8: =SUMPRODUCT((MONTH(Funding!$B$4:$B$29)=2)*Funding!I$4:I$29) | I8: =SUMPRODUCT((MONTH(Spending!$B$4:$B$278)=2)*(Spending!$E$4:$E$278="Auto Insurance")*Spending!$D$4:$D$278) | J8: =G8+H8-I8 | K8: =IF(Envelopes!$E$8="Yes",J8,0) | L8: =SUMPRODUCT((MONTH(Funding!$B$4:$B$29)=3)*Funding!I$4:I$29) | M8: =SUMPRODUCT((MONTH(Spending!$B$4:$B$278)=3)*(Spending!$E$4:$E$278="Auto Insurance")*Spending!$D$4:$D$278) | N8: =K8+L8-M8 | O8: =IF(Envelopes!$E$8="Yes",N8,0) | P8: =SUMPRODUCT((MONTH(Funding!$B$4:$B$29)=4)*Funding!I$4:I$29) | Q8: =SUMPRODUCT((MONTH(Spending!$B$4:$B$278)=4)*(Spending!$E$4:$E$278="Auto Insurance")*Spending!$D$4:$D$278) | R8: =O8+P8-Q8 | S8: =IF(Envelopes!$E$8="Yes",R8,0) | T8: =SUMPRODUCT((MONTH(Funding!$B$4:$B$29)=5)*Funding!I$4:I$29) | U8: =SUMPRODUCT((MONTH(Spending!$B$4:$B$278)=5)*(Spending!$E$4:$E$278="Auto Insurance")*Spending!$D$4:$D$278) | V8: =S8+T8-U8 | W8: =IF(Envelopes!$E$8="Yes",V8,0) | X8: =SUMPRODUCT((MONTH(Funding!$B$4:$B$29)=6)*Funding!I$4:I$29) | Y8: =SUMPRODUCT((MONTH(Spending!$B$4:$B$278)=6)*(Spending!$E$4:$E$278="Auto Insurance")*Spending!$D$4:$D$278) | Z8: =W8+X8-Y8 | AA8: =IF(Envelopes!$E$8="Yes",Z8,0) | AB8: =SUMPRODUCT((MONTH(Funding!$B$4:$B$29)=7)*Funding!I$4:I$29) | AC8: =SUMPRODUCT((MONTH(Spending!$B$4:$B$278)=7)*(Spending!$E$4:$E$278="Auto Insurance")*Spending!$D$4:$D$278) | AD8: =AA8+AB8-AC8 | AE8: =IF(Envelopes!$E$8="Yes",AD8,0) | AF8: =SUMPRODUCT((MONTH(Funding!$B$4:$B$29)=8)*Funding!I$4:I$29) | AG8: =SUMPRODUCT((MONTH(Spending!$B$4:$B$278)=8)*(Spending!$E$4:$E$278="Auto Insurance")*Spending!$D$4:$D$278) | AH8: =AE8+AF8-AG8 | AI8: =IF(Envelopes!$E$8="Yes",AH8,0) | AJ8: =SUMPRODUCT((MONTH(Funding!$B$4:$B$29)=9)*Funding!I$4:I$29) | AK8: =SUMPRODUCT((MONTH(Spending!$B$4:$B$278)=9)*(Spending!$E$4:$E$278="Auto Insurance")*Spending!$D$4:$D$278) | AL8: =AI8+AJ8-AK8 | AM8: =IF(Envelopes!$E$8="Yes",AL8,0) | AN8: =SUMPRODUCT((MONTH(Funding!$B$4:$B$29)=10)*Funding!I$4:I$29) | AO8: =SUMPRODUCT((MONTH(Spending!$B$4:$B$278)=10)*(Spending!$E$4:$E$278="Auto Insurance")*Spending!$D$4:$D$278) | AP8: =AM8+AN8-AO8 | AQ8: =IF(Envelopes!$E$8="Yes",AP8,0) | AR8: =SUMPRODUCT((MONTH(Funding!$B$4:$B$29)=11)*Funding!I$4:I$29) | AS8: =SUMPRODUCT((MONTH(Spending!$B$4:$B$278)=11)*(Spending!$E$4:$E$278="Auto Insurance")*Spending!$D$4:$D$278) | AT8: =AQ8+AR8-AS8 | AU8: =IF(Envelopes!$E$8="Yes",AT8,0) | AV8: =SUMPRODUCT((MONTH(Funding!$B$4:$B$29)=12)*Funding!I$4:I$29) | AW8: =SUMPRODUCT((MONTH(Spending!$B$4:$B$278)=12)*(Spending!$E$4:$E$278="Auto Insurance")*Spending!$D$4:$D$278) | AX8: =AU8+AV8-AW8
B9: Phone | C9: 0 | D9: =SUMPRODUCT((MONTH(Funding!$B$4:$B$29)=1)*Funding!J$4:J$29) | E9: =SUMPRODUCT((MONTH(Spending!$B$4:$B$278)=1)*(Spending!$E$4:$E$278="Phone")*Spending!$D$4:$D$278) | F9: =C9+D9-E9 | G9: =IF(Envelopes!$E$9="Yes",F9,0) | H9: =SUMPRODUCT((MONTH(Funding!$B$4:$B$29)=2)*Funding!J$4:J$29) | I9: =SUMPRODUCT((MONTH(Spending!$B$4:$B$278)=2)*(Spending!$E$4:$E$278="Phone")*Spending!$D$4:$D$278) | J9: =G9+H9-I9 | K9: =IF(Envelopes!$E$9="Yes",J9,0) | L9: =SUMPRODUCT((MONTH(Funding!$B$4:$B$29)=3)*Funding!J$4:J$29) | M9: =SUMPRODUCT((MONTH(Spending!$B$4:$B$278)=3)*(Spending!$E$4:$E$278="Phone")*Spending!$D$4:$D$278) | N9: =K9+L9-M9 | O9: =IF(Envelopes!$E$9="Yes",N9,0) | P9: =SUMPRODUCT((MONTH(Funding!$B$4:$B$29)=4)*Funding!J$4:J$29) | Q9: =SUMPRODUCT((MONTH(Spending!$B$4:$B$278)=4)*(Spending!$E$4:$E$278="Phone")*Spending!$D$4:$D$278) | R9: =O9+P9-Q9 | S9: =IF(Envelopes!$E$9="Yes",R9,0) | T9: =SUMPRODUCT((MONTH(Funding!$B$4:$B$29)=5)*Funding!J$4:J$29) | U9: =SUMPRODUCT((MONTH(Spending!$B$4:$B$278)=5)*(Spending!$E$4:$E$278="Phone")*Spending!$D$4:$D$278) | V9: =S9+T9-U9 | W9: =IF(Envelopes!$E$9="Yes",V9,0) | X9: =SUMPRODUCT((MONTH(Funding!$B$4:$B$29)=6)*Funding!J$4:J$29) | Y9: =SUMPRODUCT((MONTH(Spending!$B$4:$B$278)=6)*(Spending!$E$4:$E$278="Phone")*Spending!$D$4:$D$278) | Z9: =W9+X9-Y9 | AA9: =IF(Envelopes!$E$9="Yes",Z9,0) | AB9: =SUMPRODUCT((MONTH(Funding!$B$4:$B$29)=7)*Funding!J$4:J$29) | AC9: =SUMPRODUCT((MONTH(Spending!$B$4:$B$278)=7)*(Spending!$E$4:$E$278="Phone")*Spending!$D$4:$D$278) | AD9: =AA9+AB9-AC9 | AE9: =IF(Envelopes!$E$9="Yes",AD9,0) | AF9: =SUMPRODUCT((MONTH(Funding!$B$4:$B$29)=8)*Funding!J$4:J$29) | AG9: =SUMPRODUCT((MONTH(Spending!$B$4:$B$278)=8)*(Spending!$E$4:$E$278="Phone")*Spending!$D$4:$D$278) | AH9: =AE9+AF9-AG9 | AI9: =IF(Envelopes!$E$9="Yes",AH9,0) | AJ9: =SUMPRODUCT((MONTH(Funding!$B$4:$B$29)=9)*Funding!J$4:J$29) | AK9: =SUMPRODUCT((MONTH(Spending!$B$4:$B$278)=9)*(Spending!$E$4:$E$278="Phone")*Spending!$D$4:$D$278) | AL9: =AI9+AJ9-AK9 | AM9: =IF(Envelopes!$E$9="Yes",AL9,0) | AN9: =SUMPRODUCT((MONTH(Funding!$B$4:$B$29)=10)*Funding!J$4:J$29) | AO9: =SUMPRODUCT((MONTH(Spending!$B$4:$B$278)=10)*(Spending!$E$4:$E$278="Phone")*Spending!$D$4:$D$278) | AP9: =AM9+AN9-AO9 | AQ9: =IF(Envelopes!$E$9="Yes",AP9,0) | AR9: =SUMPRODUCT((MONTH(Funding!$B$4:$B$29)=11)*Funding!J$4:J$29) | AS9: =SUMPRODUCT((MONTH(Spending!$B$4:$B$278)=11)*(Spending!$E$4:$E$278="Phone")*Spending!$D$4:$D$278) | AT9: =AQ9+AR9-AS9 | AU9: =IF(Envelopes!$E$9="Yes",AT9,0) | AV9: =SUMPRODUCT((MONTH(Funding!$B$4:$B$29)=12)*Funding!J$4:J$29) | AW9: =SUMPRODUCT((MONTH(Spending!$B$4:$B$278)=12)*(Spending!$E$4:$E$278="Phone")*Spending!$D$4:$D$278) | AX9: =AU9+AV9-AW9
B10: Medical | C10: 0 | D10: =SUMPRODUCT((MONTH(Funding!$B$4:$B$29)=1)*Funding!K$4:K$29) | E10: =SUMPRODUCT((MONTH(Spending!$B$4:$B$278)=1)*(Spending!$E$4:$E$278="Medical")*Spending!$D$4:$D$278) | F10: =C10+D10-E10 | G10: =IF(Envelopes!$E$10="Yes",F10,0) | H10: =SUMPRODUCT((MONTH(Funding!$B$4:$B$29)=2)*Funding!K$4:K$29) | I10: =SUMPRODUCT((MONTH(Spending!$B$4:$B$278)=2)*(Spending!$E$4:$E$278="Medical")*Spending!$D$4:$D$278) | J10: =G10+H10-I10 | K10: =IF(Envelopes!$E$10="Yes",J10,0) | L10: =SUMPRODUCT((MONTH(Funding!$B$4:$B$29)=3)*Funding!K$4:K$29) | M10: =SUMPRODUCT((MONTH(Spending!$B$4:$B$278)=3)*(Spending!$E$4:$E$278="Medical")*Spending!$D$4:$D$278) | N10: =K10+L10-M10 | O10: =IF(Envelopes!$E$10="Yes",N10,0) | P10: =SUMPRODUCT((MONTH(Funding!$B$4:$B$29)=4)*Funding!K$4:K$29) | Q10: =SUMPRODUCT((MONTH(Spending!$B$4:$B$278)=4)*(Spending!$E$4:$E$278="Medical")*Spending!$D$4:$D$278) | R10: =O10+P10-Q10 | S10: =IF(Envelopes!$E$10="Yes",R10,0) | T10: =SUMPRODUCT((MONTH(Funding!$B$4:$B$29)=5)*Funding!K$4:K$29) | U10: =SUMPRODUCT((MONTH(Spending!$B$4:$B$278)=5)*(Spending!$E$4:$E$278="Medical")*Spending!$D$4:$D$278) | V10: =S10+T10-U10 | W10: =IF(Envelopes!$E$10="Yes",V10,0) | X10: =SUMPRODUCT((MONTH(Funding!$B$4:$B$29)=6)*Funding!K$4:K$29) | Y10: =SUMPRODUCT((MONTH(Spending!$B$4:$B$278)=6)*(Spending!$E$4:$E$278="Medical")*Spending!$D$4:$D$278) | Z10: =W10+X10-Y10 | AA10: =IF(Envelopes!$E$10="Yes",Z10,0) | AB10: =SUMPRODUCT((MONTH(Funding!$B$4:$B$29)=7)*Funding!K$4:K$29) | AC10: =SUMPRODUCT((MONTH(Spending!$B$4:$B$278)=7)*(Spending!$E$4:$E$278="Medical")*Spending!$D$4:$D$278) | AD10: =AA10+AB10-AC10 | AE10: =IF(Envelopes!$E$10="Yes",AD10,0) | AF10: =SUMPRODUCT((MONTH(Funding!$B$4:$B$29)=8)*Funding!K$4:K$29) | AG10: =SUMPRODUCT((MONTH(Spending!$B$4:$B$278)=8)*(Spending!$E$4:$E$278="Medical")*Spending!$D$4:$D$278) | AH10: =AE10+AF10-AG10 | AI10: =IF(Envelopes!$E$10="Yes",AH10,0) | AJ10: =SUMPRODUCT((MONTH(Funding!$B$4:$B$29)=9)*Funding!K$4:K$29) | AK10: =SUMPRODUCT((MONTH(Spending!$B$4:$B$278)=9)*(Spending!$E$4:$E$278="Medical")*Spending!$D$4:$D$278) | AL10: =AI10+AJ10-AK10 | AM10: =IF(Envelopes!$E$10="Yes",AL10,0) | AN10: =SUMPRODUCT((MONTH(Funding!$B$4:$B$29)=10)*Funding!K$4:K$29) | AO10: =SUMPRODUCT((MONTH(Spending!$B$4:$B$278)=10)*(Spending!$E$4:$E$278="Medical")*Spending!$D$4:$D$278) | AP10: =AM10+AN10-AO10 | AQ10: =IF(Envelopes!$E$10="Yes",AP10,0) | AR10: =SUMPRODUCT((MONTH(Funding!$B$4:$B$29)=11)*Funding!K$4:K$29) | AS10: =SUMPRODUCT((MONTH(Spending!$B$4:$B$278)=11)*(Spending!$E$4:$E$278="Medical")*Spending!$D$4:$D$278) | AT10: =AQ10+AR10-AS10 | AU10: =IF(Envelopes!$E$10="Yes",AT10,0) | AV10: =SUMPRODUCT((MONTH(Funding!$B$4:$B$29)=12)*Funding!K$4:K$29) | AW10: =SUMPRODUCT((MONTH(Spending!$B$4:$B$278)=12)*(Spending!$E$4:$E$278="Medical")*Spending!$D$4:$D$278) | AX10: =AU10+AV10-AW10
B11: Dining Out | C11: 0 | D11: =SUMPRODUCT((MONTH(Funding!$B$4:$B$29)=1)*Funding!L$4:L$29) | E11: =SUMPRODUCT((MONTH(Spending!$B$4:$B$278)=1)*(Spending!$E$4:$E$278="Dining Out")*Spending!$D$4:$D$278) | F11: =C11+D11-E11 | G11: =IF(Envelopes!$E$11="Yes",F11,0) | H11: =SUMPRODUCT((MONTH(Funding!$B$4:$B$29)=2)*Funding!L$4:L$29) | I11: =SUMPRODUCT((MONTH(Spending!$B$4:$B$278)=2)*(Spending!$E$4:$E$278="Dining Out")*Spending!$D$4:$D$278) | J11: =G11+H11-I11 | K11: =IF(Envelopes!$E$11="Yes",J11,0) | L11: =SUMPRODUCT((MONTH(Funding!$B$4:$B$29)=3)*Funding!L$4:L$29) | M11: =SUMPRODUCT((MONTH(Spending!$B$4:$B$278)=3)*(Spending!$E$4:$E$278="Dining Out")*Spending!$D$4:$D$278) | N11: =K11+L11-M11 | O11: =IF(Envelopes!$E$11="Yes",N11,0) | P11: =SUMPRODUCT((MONTH(Funding!$B$4:$B$29)=4)*Funding!L$4:L$29) | Q11: =SUMPRODUCT((MONTH(Spending!$B$4:$B$278)=4)*(Spending!$E$4:$E$278="Dining Out")*Spending!$D$4:$D$278) | R11: =O11+P11-Q11 | S11: =IF(Envelopes!$E$11="Yes",R11,0) | T11: =SUMPRODUCT((MONTH(Funding!$B$4:$B$29)=5)*Funding!L$4:L$29) | U11: =SUMPRODUCT((MONTH(Spending!$B$4:$B$278)=5)*(Spending!$E$4:$E$278="Dining Out")*Spending!$D$4:$D$278) | V11: =S11+T11-U11 | W11: =IF(Envelopes!$E$11="Yes",V11,0) | X11: =SUMPRODUCT((MONTH(Funding!$B$4:$B$29)=6)*Funding!L$4:L$29) | Y11: =SUMPRODUCT((MONTH(Spending!$B$4:$B$278)=6)*(Spending!$E$4:$E$278="Dining Out")*Spending!$D$4:$D$278) | Z11: =W11+X11-Y11 | AA11: =IF(Envelopes!$E$11="Yes",Z11,0) | AB11: =SUMPRODUCT((MONTH(Funding!$B$4:$B$29)=7)*Funding!L$4:L$29) | AC11: =SUMPRODUCT((MONTH(Spending!$B$4:$B$278)=7)*(Spending!$E$4:$E$278="Dining Out")*Spending!$D$4:$D$278) | AD11: =AA11+AB11-AC11 | AE11: =IF(Envelopes!$E$11="Yes",AD11,0) | AF11: =SUMPRODUCT((MONTH(Funding!$B$4:$B$29)=8)*Funding!L$4:L$29) | AG11: =SUMPRODUCT((MONTH(Spending!$B$4:$B$278)=8)*(Spending!$E$4:$E$278="Dining Out")*Spending!$D$4:$D$278) | AH11: =AE11+AF11-AG11 | AI11: =IF(Envelopes!$E$11="Yes",AH11,0) | AJ11: =SUMPRODUCT((MONTH(Funding!$B$4:$B$29)=9)*Funding!L$4:L$29) | AK11: =SUMPRODUCT((MONTH(Spending!$B$4:$B$278)=9)*(Spending!$E$4:$E$278="Dining Out")*Spending!$D$4:$D$278) | AL11: =AI11+AJ11-AK11 | AM11: =IF(Envelopes!$E$11="Yes",AL11,0) | AN11: =SUMPRODUCT((MONTH(Funding!$B$4:$B$29)=10)*Funding!L$4:L$29) | AO11: =SUMPRODUCT((MONTH(Spending!$B$4:$B$278)=10)*(Spending!$E$4:$E$278="Dining Out")*Spending!$D$4:$D$278) | AP11: =AM11+AN11-AO11 | AQ11: =IF(Envelopes!$E$11="Yes",AP11,0) | AR11: =SUMPRODUCT((MONTH(Funding!$B$4:$B$29)=11)*Funding!L$4:L$29) | AS11: =SUMPRODUCT((MONTH(Spending!$B$4:$B$278)=11)*(Spending!$E$4:$E$278="Dining Out")*Spending!$D$4:$D$278) | AT11: =AQ11+AR11-AS11 | AU11: =IF(Envelopes!$E$11="Yes",AT11,0) | AV11: =SUMPRODUCT((MONTH(Funding!$B$4:$B$29)=12)*Funding!L$4:L$29) | AW11: =SUMPRODUCT((MONTH(Spending!$B$4:$B$278)=12)*(Spending!$E$4:$E$278="Dining Out")*Spending!$D$4:$D$278) | AX11: =AU11+AV11-AW11
B12: Coffee | C12: 0 | D12: =SUMPRODUCT((MONTH(Funding!$B$4:$B$29)=1)*Funding!M$4:M$29) | E12: =SUMPRODUCT((MONTH(Spending!$B$4:$B$278)=1)*(Spending!$E$4:$E$278="Coffee")*Spending!$D$4:$D$278) | F12: =C12+D12-E12 | G12: =IF(Envelopes!$E$12="Yes",F12,0) | H12: =SUMPRODUCT((MONTH(Funding!$B$4:$B$29)=2)*Funding!M$4:M$29) | I12: =SUMPRODUCT((MONTH(Spending!$B$4:$B$278)=2)*(Spending!$E$4:$E$278="Coffee")*Spending!$D$4:$D$278) | J12: =G12+H12-I12 | K12: =IF(Envelopes!$E$12="Yes",J12,0) | L12: =SUMPRODUCT((MONTH(Funding!$B$4:$B$29)=3)*Funding!M$4:M$29) | M12: =SUMPRODUCT((MONTH(Spending!$B$4:$B$278)=3)*(Spending!$E$4:$E$278="Coffee")*Spending!$D$4:$D$278) | N12: =K12+L12-M12 | O12: =IF(Envelopes!$E$12="Yes",N12,0) | P12: =SUMPRODUCT((MONTH(Funding!$B$4:$B$29)=4)*Funding!M$4:M$29) | Q12: =SUMPRODUCT((MONTH(Spending!$B$4:$B$278)=4)*(Spending!$E$4:$E$278="Coffee")*Spending!$D$4:$D$278) | R12: =O12+P12-Q12 | S12: =IF(Envelopes!$E$12="Yes",R12,0) | T12: =SUMPRODUCT((MONTH(Funding!$B$4:$B$29)=5)*Funding!M$4:M$29) | U12: =SUMPRODUCT((MONTH(Spending!$B$4:$B$278)=5)*(Spending!$E$4:$E$278="Coffee")*Spending!$D$4:$D$278) | V12: =S12+T12-U12 | W12: =IF(Envelopes!$E$12="Yes",V12,0) | X12: =SUMPRODUCT((MONTH(Funding!$B$4:$B$29)=6)*Funding!M$4:M$29) | Y12: =SUMPRODUCT((MONTH(Spending!$B$4:$B$278)=6)*(Spending!$E$4:$E$278="Coffee")*Spending!$D$4:$D$278) | Z12: =W12+X12-Y12 | AA12: =IF(Envelopes!$E$12="Yes",Z12,0) | AB12: =SUMPRODUCT((MONTH(Funding!$B$4:$B$29)=7)*Funding!M$4:M$29) | AC12: =SUMPRODUCT((MONTH(Spending!$B$4:$B$278)=7)*(Spending!$E$4:$E$278="Coffee")*Spending!$D$4:$D$278) | AD12: =AA12+AB12-AC12 | AE12: =IF(Envelopes!$E$12="Yes",AD12,0) | AF12: =SUMPRODUCT((MONTH(Funding!$B$4:$B$29)=8)*Funding!M$4:M$29) | AG12: =SUMPRODUCT((MONTH(Spending!$B$4:$B$278)=8)*(Spending!$E$4:$E$278="Coffee")*Spending!$D$4:$D$278) | AH12: =AE12+AF12-AG12 | AI12: =IF(Envelopes!$E$12="Yes",AH12,0) | AJ12: =SUMPRODUCT((MONTH(Funding!$B$4:$B$29)=9)*Funding!M$4:M$29) | AK12: =SUMPRODUCT((MONTH(Spending!$B$4:$B$278)=9)*(Spending!$E$4:$E$278="Coffee")*Spending!$D$4:$D$278) | AL12: =AI12+AJ12-AK12 | AM12: =IF(Envelopes!$E$12="Yes",AL12,0) | AN12: =SUMPRODUCT((MONTH(Funding!$B$4:$B$29)=10)*Funding!M$4:M$29) | AO12: =SUMPRODUCT((MONTH(Spending!$B$4:$B$278)=10)*(Spending!$E$4:$E$278="Coffee")*Spending!$D$4:$D$278) | AP12: =AM12+AN12-AO12 | AQ12: =IF(Envelopes!$E$12="Yes",AP12,0) | AR12: =SUMPRODUCT((MONTH(Funding!$B$4:$B$29)=11)*Funding!M$4:M$29) | AS12: =SUMPRODUCT((MONTH(Spending!$B$4:$B$278)=11)*(Spending!$E$4:$E$278="Coffee")*Spending!$D$4:$D$278) | AT12: =AQ12+AR12-AS12 | AU12: =IF(Envelopes!$E$12="Yes",AT12,0) | AV12: =SUMPRODUCT((MONTH(Funding!$B$4:$B$29)=12)*Funding!M$4:M$29) | AW12: =SUMPRODUCT((MONTH(Spending!$B$4:$B$278)=12)*(Spending!$E$4:$E$278="Coffee")*Spending!$D$4:$D$278) | AX12: =AU12+AV12-AW12
B13: Entertainment | C13: 0 | D13: =SUMPRODUCT((MONTH(Funding!$B$4:$B$29)=1)*Funding!N$4:N$29) | E13: =SUMPRODUCT((MONTH(Spending!$B$4:$B$278)=1)*(Spending!$E$4:$E$278="Entertainment")*Spending!$D$4:$D$278) | F13: =C13+D13-E13 | G13: =IF(Envelopes!$E$13="Yes",F13,0) | H13: =SUMPRODUCT((MONTH(Funding!$B$4:$B$29)=2)*Funding!N$4:N$29) | I13: =SUMPRODUCT((MONTH(Spending!$B$4:$B$278)=2)*(Spending!$E$4:$E$278="Entertainment")*Spending!$D$4:$D$278) | J13: =G13+H13-I13 | K13: =IF(Envelopes!$E$13="Yes",J13,0) | L13: =SUMPRODUCT((MONTH(Funding!$B$4:$B$29)=3)*Funding!N$4:N$29) | M13: =SUMPRODUCT((MONTH(Spending!$B$4:$B$278)=3)*(Spending!$E$4:$E$278="Entertainment")*Spending!$D$4:$D$278) | N13: =K13+L13-M13 | O13: =IF(Envelopes!$E$13="Yes",N13,0) | P13: =SUMPRODUCT((MONTH(Funding!$B$4:$B$29)=4)*Funding!N$4:N$29) | Q13: =SUMPRODUCT((MONTH(Spending!$B$4:$B$278)=4)*(Spending!$E$4:$E$278="Entertainment")*Spending!$D$4:$D$278) | R13: =O13+P13-Q13 | S13: =IF(Envelopes!$E$13="Yes",R13,0) | T13: =SUMPRODUCT((MONTH(Funding!$B$4:$B$29)=5)*Funding!N$4:N$29) | U13: =SUMPRODUCT((MONTH(Spending!$B$4:$B$278)=5)*(Spending!$E$4:$E$278="Entertainment")*Spending!$D$4:$D$278) | V13: =S13+T13-U13 | W13: =IF(Envelopes!$E$13="Yes",V13,0) | X13: =SUMPRODUCT((MONTH(Funding!$B$4:$B$29)=6)*Funding!N$4:N$29) | Y13: =SUMPRODUCT((MONTH(Spending!$B$4:$B$278)=6)*(Spending!$E$4:$E$278="Entertainment")*Spending!$D$4:$D$278) | Z13: =W13+X13-Y13 | AA13: =IF(Envelopes!$E$13="Yes",Z13,0) | AB13: =SUMPRODUCT((MONTH(Funding!$B$4:$B$29)=7)*Funding!N$4:N$29) | AC13: =SUMPRODUCT((MONTH(Spending!$B$4:$B$278)=7)*(Spending!$E$4:$E$278="Entertainment")*Spending!$D$4:$D$278) | AD13: =AA13+AB13-AC13 | AE13: =IF(Envelopes!$E$13="Yes",AD13,0) | AF13: =SUMPRODUCT((MONTH(Funding!$B$4:$B$29)=8)*Funding!N$4:N$29) | AG13: =SUMPRODUCT((MONTH(Spending!$B$4:$B$278)=8)*(Spending!$E$4:$E$278="Entertainment")*Spending!$D$4:$D$278) | AH13: =AE13+AF13-AG13 | AI13: =IF(Envelopes!$E$13="Yes",AH13,0) | AJ13: =SUMPRODUCT((MONTH(Funding!$B$4:$B$29)=9)*Funding!N$4:N$29) | AK13: =SUMPRODUCT((MONTH(Spending!$B$4:$B$278)=9)*(Spending!$E$4:$E$278="Entertainment")*Spending!$D$4:$D$278) | AL13: =AI13+AJ13-AK13 | AM13: =IF(Envelopes!$E$13="Yes",AL13,0) | AN13: =SUMPRODUCT((MONTH(Funding!$B$4:$B$29)=10)*Funding!N$4:N$29) | AO13: =SUMPRODUCT((MONTH(Spending!$B$4:$B$278)=10)*(Spending!$E$4:$E$278="Entertainment")*Spending!$D$4:$D$278) | AP13: =AM13+AN13-AO13 | AQ13: =IF(Envelopes!$E$13="Yes",AP13,0) | AR13: =SUMPRODUCT((MONTH(Funding!$B$4:$B$29)=11)*Funding!N$4:N$29) | AS13: =SUMPRODUCT((MONTH(Spending!$B$4:$B$278)=11)*(Spending!$E$4:$E$278="Entertainment")*Spending!$D$4:$D$278) | AT13: =AQ13+AR13-AS13 | AU13: =IF(Envelopes!$E$13="Yes",AT13,0) | AV13: =SUMPRODUCT((MONTH(Funding!$B$4:$B$29)=12)*Funding!N$4:N$29) | AW13: =SUMPRODUCT((MONTH(Spending!$B$4:$B$278)=12)*(Spending!$E$4:$E$278="Entertainment")*Spending!$D$4:$D$278) | AX13: =AU13+AV13-AW13
B14: Clothing | C14: 0 | D14: =SUMPRODUCT((MONTH(Funding!$B$4:$B$29)=1)*Funding!O$4:O$29) | E14: =SUMPRODUCT((MONTH(Spending!$B$4:$B$278)=1)*(Spending!$E$4:$E$278="Clothing")*Spending!$D$4:$D$278) | F14: =C14+D14-E14 | G14: =IF(Envelopes!$E$14="Yes",F14,0) | H14: =SUMPRODUCT((MONTH(Funding!$B$4:$B$29)=2)*Funding!O$4:O$29) | I14: =SUMPRODUCT((MONTH(Spending!$B$4:$B$278)=2)*(Spending!$E$4:$E$278="Clothing")*Spending!$D$4:$D$278) | J14: =G14+H14-I14 | K14: =IF(Envelopes!$E$14="Yes",J14,0) | L14: =SUMPRODUCT((MONTH(Funding!$B$4:$B$29)=3)*Funding!O$4:O$29) | M14: =SUMPRODUCT((MONTH(Spending!$B$4:$B$278)=3)*(Spending!$E$4:$E$278="Clothing")*Spending!$D$4:$D$278) | N14: =K14+L14-M14 | O14: =IF(Envelopes!$E$14="Yes",N14,0) | P14: =SUMPRODUCT((MONTH(Funding!$B$4:$B$29)=4)*Funding!O$4:O$29) | Q14: =SUMPRODUCT((MONTH(Spending!$B$4:$B$278)=4)*(Spending!$E$4:$E$278="Clothing")*Spending!$D$4:$D$278) | R14: =O14+P14-Q14 | S14: =IF(Envelopes!$E$14="Yes",R14,0) | T14: =SUMPRODUCT((MONTH(Funding!$B$4:$B$29)=5)*Funding!O$4:O$29) | U14: =SUMPRODUCT((MONTH(Spending!$B$4:$B$278)=5)*(Spending!$E$4:$E$278="Clothing")*Spending!$D$4:$D$278) | V14: =S14+T14-U14 | W14: =IF(Envelopes!$E$14="Yes",V14,0) | X14: =SUMPRODUCT((MONTH(Funding!$B$4:$B$29)=6)*Funding!O$4:O$29) | Y14: =SUMPRODUCT((MONTH(Spending!$B$4:$B$278)=6)*(Spending!$E$4:$E$278="Clothing")*Spending!$D$4:$D$278) | Z14: =W14+X14-Y14 | AA14: =IF(Envelopes!$E$14="Yes",Z14,0) | AB14: =SUMPRODUCT((MONTH(Funding!$B$4:$B$29)=7)*Funding!O$4:O$29) | AC14: =SUMPRODUCT((MONTH(Spending!$B$4:$B$278)=7)*(Spending!$E$4:$E$278="Clothing")*Spending!$D$4:$D$278) | AD14: =AA14+AB14-AC14 | AE14: =IF(Envelopes!$E$14="Yes",AD14,0) | AF14: =SUMPRODUCT((MONTH(Funding!$B$4:$B$29)=8)*Funding!O$4:O$29) | AG14: =SUMPRODUCT((MONTH(Spending!$B$4:$B$278)=8)*(Spending!$E$4:$E$278="Clothing")*Spending!$D$4:$D$278) | AH14: =AE14+AF14-AG14 | AI14: =IF(Envelopes!$E$14="Yes",AH14,0) | AJ14: =SUMPRODUCT((MONTH(Funding!$B$4:$B$29)=9)*Funding!O$4:O$29) | AK14: =SUMPRODUCT((MONTH(Spending!$B$4:$B$278)=9)*(Spending!$E$4:$E$278="Clothing")*Spending!$D$4:$D$278) | AL14: =AI14+AJ14-AK14 | AM14: =IF(Envelopes!$E$14="Yes",AL14,0) | AN14: =SUMPRODUCT((MONTH(Funding!$B$4:$B$29)=10)*Funding!O$4:O$29) | AO14: =SUMPRODUCT((MONTH(Spending!$B$4:$B$278)=10)*(Spending!$E$4:$E$278="Clothing")*Spending!$D$4:$D$278) | AP14: =AM14+AN14-AO14 | AQ14: =IF(Envelopes!$E$14="Yes",AP14,0) | AR14: =SUMPRODUCT((MONTH(Funding!$B$4:$B$29)=11)*Funding!O$4:O$29) | AS14: =SUMPRODUCT((MONTH(Spending!$B$4:$B$278)=11)*(Spending!$E$4:$E$278="Clothing")*Spending!$D$4:$D$278) | AT14: =AQ14+AR14-AS14 | AU14: =IF(Envelopes!$E$14="Yes",AT14,0) | AV14: =SUMPRODUCT((MONTH(Funding!$B$4:$B$29)=12)*Funding!O$4:O$29) | AW14: =SUMPRODUCT((MONTH(Spending!$B$4:$B$278)=12)*(Spending!$E$4:$E$278="Clothing")*Spending!$D$4:$D$278) | AX14: =AU14+AV14-AW14
B15: Personal Care | C15: 0 | D15: =SUMPRODUCT((MONTH(Funding!$B$4:$B$29)=1)*Funding!P$4:P$29) | E15: =SUMPRODUCT((MONTH(Spending!$B$4:$B$278)=1)*(Spending!$E$4:$E$278="Personal Care")*Spending!$D$4:$D$278) | F15: =C15+D15-E15 | G15: =IF(Envelopes!$E$15="Yes",F15,0) | H15: =SUMPRODUCT((MONTH(Funding!$B$4:$B$29)=2)*Funding!P$4:P$29) | I15: =SUMPRODUCT((MONTH(Spending!$B$4:$B$278)=2)*(Spending!$E$4:$E$278="Personal Care")*Spending!$D$4:$D$278) | J15: =G15+H15-I15 | K15: =IF(Envelopes!$E$15="Yes",J15,0) | L15: =SUMPRODUCT((MONTH(Funding!$B$4:$B$29)=3)*Funding!P$4:P$29) | M15: =SUMPRODUCT((MONTH(Spending!$B$4:$B$278)=3)*(Spending!$E$4:$E$278="Personal Care")*Spending!$D$4:$D$278) | N15: =K15+L15-M15 | O15: =IF(Envelopes!$E$15="Yes",N15,0) | P15: =SUMPRODUCT((MONTH(Funding!$B$4:$B$29)=4)*Funding!P$4:P$29) | Q15: =SUMPRODUCT((MONTH(Spending!$B$4:$B$278)=4)*(Spending!$E$4:$E$278="Personal Care")*Spending!$D$4:$D$278) | R15: =O15+P15-Q15 | S15: =IF(Envelopes!$E$15="Yes",R15,0) | T15: =SUMPRODUCT((MONTH(Funding!$B$4:$B$29)=5)*Funding!P$4:P$29) | U15: =SUMPRODUCT((MONTH(Spending!$B$4:$B$278)=5)*(Spending!$E$4:$E$278="Personal Care")*Spending!$D$4:$D$278) | V15: =S15+T15-U15 | W15: =IF(Envelopes!$E$15="Yes",V15,0) | X15: =SUMPRODUCT((MONTH(Funding!$B$4:$B$29)=6)*Funding!P$4:P$29) | Y15: =SUMPRODUCT((MONTH(Spending!$B$4:$B$278)=6)*(Spending!$E$4:$E$278="Personal Care")*Spending!$D$4:$D$278) | Z15: =W15+X15-Y15 | AA15: =IF(Envelopes!$E$15="Yes",Z15,0) | AB15: =SUMPRODUCT((MONTH(Funding!$B$4:$B$29)=7)*Funding!P$4:P$29) | AC15: =SUMPRODUCT((MONTH(Spending!$B$4:$B$278)=7)*(Spending!$E$4:$E$278="Personal Care")*Spending!$D$4:$D$278) | AD15: =AA15+AB15-AC15 | AE15: =IF(Envelopes!$E$15="Yes",AD15,0) | AF15: =SUMPRODUCT((MONTH(Funding!$B$4:$B$29)=8)*Funding!P$4:P$29) | AG15: =SUMPRODUCT((MONTH(Spending!$B$4:$B$278)=8)*(Spending!$E$4:$E$278="Personal Care")*Spending!$D$4:$D$278) | AH15: =AE15+AF15-AG15 | AI15: =IF(Envelopes!$E$15="Yes",AH15,0) | AJ15: =SUMPRODUCT((MONTH(Funding!$B$4:$B$29)=9)*Funding!P$4:P$29) | AK15: =SUMPRODUCT((MONTH(Spending!$B$4:$B$278)=9)*(Spending!$E$4:$E$278="Personal Care")*Spending!$D$4:$D$278) | AL15: =AI15+AJ15-AK15 | AM15: =IF(Envelopes!$E$15="Yes",AL15,0) | AN15: =SUMPRODUCT((MONTH(Funding!$B$4:$B$29)=10)*Funding!P$4:P$29) | AO15: =SUMPRODUCT((MONTH(Spending!$B$4:$B$278)=10)*(Spending!$E$4:$E$278="Personal Care")*Spending!$D$4:$D$278) | AP15: =AM15+AN15-AO15 | AQ15: =IF(Envelopes!$E$15="Yes",AP15,0) | AR15: =SUMPRODUCT((MONTH(Funding!$B$4:$B$29)=11)*Funding!P$4:P$29) | AS15: =SUMPRODUCT((MONTH(Spending!$B$4:$B$278)=11)*(Spending!$E$4:$E$278="Personal Care")*Spending!$D$4:$D$278) | AT15: =AQ15+AR15-AS15 | AU15: =IF(Envelopes!$E$15="Yes",AT15,0) | AV15: =SUMPRODUCT((MONTH(Funding!$B$4:$B$29)=12)*Funding!P$4:P$29) | AW15: =SUMPRODUCT((MONTH(Spending!$B$4:$B$278)=12)*(Spending!$E$4:$E$278="Personal Care")*Spending!$D$4:$D$278) | AX15: =AU15+AV15-AW15
B16: Subscriptions | C16: 0 | D16: =SUMPRODUCT((MONTH(Funding!$B$4:$B$29)=1)*Funding!Q$4:Q$29) | E16: =SUMPRODUCT((MONTH(Spending!$B$4:$B$278)=1)*(Spending!$E$4:$E$278="Subscriptions")*Spending!$D$4:$D$278) | F16: =C16+D16-E16 | G16: =IF(Envelopes!$E$16="Yes",F16,0) | H16: =SUMPRODUCT((MONTH(Funding!$B$4:$B$29)=2)*Funding!Q$4:Q$29) | I16: =SUMPRODUCT((MONTH(Spending!$B$4:$B$278)=2)*(Spending!$E$4:$E$278="Subscriptions")*Spending!$D$4:$D$278) | J16: =G16+H16-I16 | K16: =IF(Envelopes!$E$16="Yes",J16,0) | L16: =SUMPRODUCT((MONTH(Funding!$B$4:$B$29)=3)*Funding!Q$4:Q$29) | M16: =SUMPRODUCT((MONTH(Spending!$B$4:$B$278)=3)*(Spending!$E$4:$E$278="Subscriptions")*Spending!$D$4:$D$278) | N16: =K16+L16-M16 | O16: =IF(Envelopes!$E$16="Yes",N16,0) | P16: =SUMPRODUCT((MONTH(Funding!$B$4:$B$29)=4)*Funding!Q$4:Q$29) | Q16: =SUMPRODUCT((MONTH(Spending!$B$4:$B$278)=4)*(Spending!$E$4:$E$278="Subscriptions")*Spending!$D$4:$D$278) | R16: =O16+P16-Q16 | S16: =IF(Envelopes!$E$16="Yes",R16,0) | T16: =SUMPRODUCT((MONTH(Funding!$B$4:$B$29)=5)*Funding!Q$4:Q$29) | U16: =SUMPRODUCT((MONTH(Spending!$B$4:$B$278)=5)*(Spending!$E$4:$E$278="Subscriptions")*Spending!$D$4:$D$278) | V16: =S16+T16-U16 | W16: =IF(Envelopes!$E$16="Yes",V16,0) | X16: =SUMPRODUCT((MONTH(Funding!$B$4:$B$29)=6)*Funding!Q$4:Q$29) | Y16: =SUMPRODUCT((MONTH(Spending!$B$4:$B$278)=6)*(Spending!$E$4:$E$278="Subscriptions")*Spending!$D$4:$D$278) | Z16: =W16+X16-Y16 | AA16: =IF(Envelopes!$E$16="Yes",Z16,0) | AB16: =SUMPRODUCT((MONTH(Funding!$B$4:$B$29)=7)*Funding!Q$4:Q$29) | AC16: =SUMPRODUCT((MONTH(Spending!$B$4:$B$278)=7)*(Spending!$E$4:$E$278="Subscriptions")*Spending!$D$4:$D$278) | AD16: =AA16+AB16-AC16 | AE16: =IF(Envelopes!$E$16="Yes",AD16,0) | AF16: =SUMPRODUCT((MONTH(Funding!$B$4:$B$29)=8)*Funding!Q$4:Q$29) | AG16: =SUMPRODUCT((MONTH(Spending!$B$4:$B$278)=8)*(Spending!$E$4:$E$278="Subscriptions")*Spending!$D$4:$D$278) | AH16: =AE16+AF16-AG16 | AI16: =IF(Envelopes!$E$16="Yes",AH16,0) | AJ16: =SUMPRODUCT((MONTH(Funding!$B$4:$B$29)=9)*Funding!Q$4:Q$29) | AK16: =SUMPRODUCT((MONTH(Spending!$B$4:$B$278)=9)*(Spending!$E$4:$E$278="Subscriptions")*Spending!$D$4:$D$278) | AL16: =AI16+AJ16-AK16 | AM16: =IF(Envelopes!$E$16="Yes",AL16,0) | AN16: =SUMPRODUCT((MONTH(Funding!$B$4:$B$29)=10)*Funding!Q$4:Q$29) | AO16: =SUMPRODUCT((MONTH(Spending!$B$4:$B$278)=10)*(Spending!$E$4:$E$278="Subscriptions")*Spending!$D$4:$D$278) | AP16: =AM16+AN16-AO16 | AQ16: =IF(Envelopes!$E$16="Yes",AP16,0) | AR16: =SUMPRODUCT((MONTH(Funding!$B$4:$B$29)=11)*Funding!Q$4:Q$29) | AS16: =SUMPRODUCT((MONTH(Spending!$B$4:$B$278)=11)*(Spending!$E$4:$E$278="Subscriptions")*Spending!$D$4:$D$278) | AT16: =AQ16+AR16-AS16 | AU16: =IF(Envelopes!$E$16="Yes",AT16,0) | AV16: =SUMPRODUCT((MONTH(Funding!$B$4:$B$29)=12)*Funding!Q$4:Q$29) | AW16: =SUMPRODUCT((MONTH(Spending!$B$4:$B$278)=12)*(Spending!$E$4:$E$278="Subscriptions")*Spending!$D$4:$D$278) | AX16: =AU16+AV16-AW16
B17: Emergency Fund | C17: 0 | D17: =SUMPRODUCT((MONTH(Funding!$B$4:$B$29)=1)*Funding!R$4:R$29) | E17: =SUMPRODUCT((MONTH(Spending!$B$4:$B$278)=1)*(Spending!$E$4:$E$278="Emergency Fund")*Spending!$D$4:$D$278) | F17: =C17+D17-E17 | G17: =IF(Envelopes!$E$17="Yes",F17,0) | H17: =SUMPRODUCT((MONTH(Funding!$B$4:$B$29)=2)*Funding!R$4:R$29) | I17: =SUMPRODUCT((MONTH(Spending!$B$4:$B$278)=2)*(Spending!$E$4:$E$278="Emergency Fund")*Spending!$D$4:$D$278) | J17: =G17+H17-I17 | K17: =IF(Envelopes!$E$17="Yes",J17,0) | L17: =SUMPRODUCT((MONTH(Funding!$B$4:$B$29)=3)*Funding!R$4:R$29) | M17: =SUMPRODUCT((MONTH(Spending!$B$4:$B$278)=3)*(Spending!$E$4:$E$278="Emergency Fund")*Spending!$D$4:$D$278) | N17: =K17+L17-M17 | O17: =IF(Envelopes!$E$17="Yes",N17,0) | P17: =SUMPRODUCT((MONTH(Funding!$B$4:$B$29)=4)*Funding!R$4:R$29) | Q17: =SUMPRODUCT((MONTH(Spending!$B$4:$B$278)=4)*(Spending!$E$4:$E$278="Emergency Fund")*Spending!$D$4:$D$278) | R17: =O17+P17-Q17 | S17: =IF(Envelopes!$E$17="Yes",R17,0) | T17: =SUMPRODUCT((MONTH(Funding!$B$4:$B$29)=5)*Funding!R$4:R$29) | U17: =SUMPRODUCT((MONTH(Spending!$B$4:$B$278)=5)*(Spending!$E$4:$E$278="Emergency Fund")*Spending!$D$4:$D$278) | V17: =S17+T17-U17 | W17: =IF(Envelopes!$E$17="Yes",V17,0) | X17: =SUMPRODUCT((MONTH(Funding!$B$4:$B$29)=6)*Funding!R$4:R$29) | Y17: =SUMPRODUCT((MONTH(Spending!$B$4:$B$278)=6)*(Spending!$E$4:$E$278="Emergency Fund")*Spending!$D$4:$D$278) | Z17: =W17+X17-Y17 | AA17: =IF(Envelopes!$E$17="Yes",Z17,0) | AB17: =SUMPRODUCT((MONTH(Funding!$B$4:$B$29)=7)*Funding!R$4:R$29) | AC17: =SUMPRODUCT((MONTH(Spending!$B$4:$B$278)=7)*(Spending!$E$4:$E$278="Emergency Fund")*Spending!$D$4:$D$278) | AD17: =AA17+AB17-AC17 | AE17: =IF(Envelopes!$E$17="Yes",AD17,0) | AF17: =SUMPRODUCT((MONTH(Funding!$B$4:$B$29)=8)*Funding!R$4:R$29) | AG17: =SUMPRODUCT((MONTH(Spending!$B$4:$B$278)=8)*(Spending!$E$4:$E$278="Emergency Fund")*Spending!$D$4:$D$278) | AH17: =AE17+AF17-AG17 | AI17: =IF(Envelopes!$E$17="Yes",AH17,0) | AJ17: =SUMPRODUCT((MONTH(Funding!$B$4:$B$29)=9)*Funding!R$4:R$29) | AK17: =SUMPRODUCT((MONTH(Spending!$B$4:$B$278)=9)*(Spending!$E$4:$E$278="Emergency Fund")*Spending!$D$4:$D$278) | AL17: =AI17+AJ17-AK17 | AM17: =IF(Envelopes!$E$17="Yes",AL17,0) | AN17: =SUMPRODUCT((MONTH(Funding!$B$4:$B$29)=10)*Funding!R$4:R$29) | AO17: =SUMPRODUCT((MONTH(Spending!$B$4:$B$278)=10)*(Spending!$E$4:$E$278="Emergency Fund")*Spending!$D$4:$D$278) | AP17: =AM17+AN17-AO17 | AQ17: =IF(Envelopes!$E$17="Yes",AP17,0) | AR17: =SUMPRODUCT((MONTH(Funding!$B$4:$B$29)=11)*Funding!R$4:R$29) | AS17: =SUMPRODUCT((MONTH(Spending!$B$4:$B$278)=11)*(Spending!$E$4:$E$278="Emergency Fund")*Spending!$D$4:$D$278) | AT17: =AQ17+AR17-AS17 | AU17: =IF(Envelopes!$E$17="Yes",AT17,0) | AV17: =SUMPRODUCT((MONTH(Funding!$B$4:$B$29)=12)*Funding!R$4:R$29) | AW17: =SUMPRODUCT((MONTH(Spending!$B$4:$B$278)=12)*(Spending!$E$4:$E$278="Emergency Fund")*Spending!$D$4:$D$278) | AX17: =AU17+AV17-AW17
B18: Vacation | C18: 0 | D18: =SUMPRODUCT((MONTH(Funding!$B$4:$B$29)=1)*Funding!S$4:S$29) | E18: =SUMPRODUCT((MONTH(Spending!$B$4:$B$278)=1)*(Spending!$E$4:$E$278="Vacation")*Spending!$D$4:$D$278) | F18: =C18+D18-E18 | G18: =IF(Envelopes!$E$18="Yes",F18,0) | H18: =SUMPRODUCT((MONTH(Funding!$B$4:$B$29)=2)*Funding!S$4:S$29) | I18: =SUMPRODUCT((MONTH(Spending!$B$4:$B$278)=2)*(Spending!$E$4:$E$278="Vacation")*Spending!$D$4:$D$278) | J18: =G18+H18-I18 | K18: =IF(Envelopes!$E$18="Yes",J18,0) | L18: =SUMPRODUCT((MONTH(Funding!$B$4:$B$29)=3)*Funding!S$4:S$29) | M18: =SUMPRODUCT((MONTH(Spending!$B$4:$B$278)=3)*(Spending!$E$4:$E$278="Vacation")*Spending!$D$4:$D$278) | N18: =K18+L18-M18 | O18: =IF(Envelopes!$E$18="Yes",N18,0) | P18: =SUMPRODUCT((MONTH(Funding!$B$4:$B$29)=4)*Funding!S$4:S$29) | Q18: =SUMPRODUCT((MONTH(Spending!$B$4:$B$278)=4)*(Spending!$E$4:$E$278="Vacation")*Spending!$D$4:$D$278) | R18: =O18+P18-Q18 | S18: =IF(Envelopes!$E$18="Yes",R18,0) | T18: =SUMPRODUCT((MONTH(Funding!$B$4:$B$29)=5)*Funding!S$4:S$29) | U18: =SUMPRODUCT((MONTH(Spending!$B$4:$B$278)=5)*(Spending!$E$4:$E$278="Vacation")*Spending!$D$4:$D$278) | V18: =S18+T18-U18 | W18: =IF(Envelopes!$E$18="Yes",V18,0) | X18: =SUMPRODUCT((MONTH(Funding!$B$4:$B$29)=6)*Funding!S$4:S$29) | Y18: =SUMPRODUCT((MONTH(Spending!$B$4:$B$278)=6)*(Spending!$E$4:$E$278="Vacation")*Spending!$D$4:$D$278) | Z18: =W18+X18-Y18 | AA18: =IF(Envelopes!$E$18="Yes",Z18,0) | AB18: =SUMPRODUCT((MONTH(Funding!$B$4:$B$29)=7)*Funding!S$4:S$29) | AC18: =SUMPRODUCT((MONTH(Spending!$B$4:$B$278)=7)*(Spending!$E$4:$E$278="Vacation")*Spending!$D$4:$D$278) | AD18: =AA18+AB18-AC18 | AE18: =IF(Envelopes!$E$18="Yes",AD18,0) | AF18: =SUMPRODUCT((MONTH(Funding!$B$4:$B$29)=8)*Funding!S$4:S$29) | AG18: =SUMPRODUCT((MONTH(Spending!$B$4:$B$278)=8)*(Spending!$E$4:$E$278="Vacation")*Spending!$D$4:$D$278) | AH18: =AE18+AF18-AG18 | AI18: =IF(Envelopes!$E$18="Yes",AH18,0) | AJ18: =SUMPRODUCT((MONTH(Funding!$B$4:$B$29)=9)*Funding!S$4:S$29) | AK18: =SUMPRODUCT((MONTH(Spending!$B$4:$B$278)=9)*(Spending!$E$4:$E$278="Vacation")*Spending!$D$4:$D$278) | AL18: =AI18+AJ18-AK18 | AM18: =IF(Envelopes!$E$18="Yes",AL18,0) | AN18: =SUMPRODUCT((MONTH(Funding!$B$4:$B$29)=10)*Funding!S$4:S$29) | AO18: =SUMPRODUCT((MONTH(Spending!$B$4:$B$278)=10)*(Spending!$E$4:$E$278="Vacation")*Spending!$D$4:$D$278) | AP18: =AM18+AN18-AO18 | AQ18: =IF(Envelopes!$E$18="Yes",AP18,0) | AR18: =SUMPRODUCT((MONTH(Funding!$B$4:$B$29)=11)*Funding!S$4:S$29) | AS18: =SUMPRODUCT((MONTH(Spending!$B$4:$B$278)=11)*(Spending!$E$4:$E$278="Vacation")*Spending!$D$4:$D$278) | AT18: =AQ18+AR18-AS18 | AU18: =IF(Envelopes!$E$18="Yes",AT18,0) | AV18: =SUMPRODUCT((MONTH(Funding!$B$4:$B$29)=12)*Funding!S$4:S$29) | AW18: =SUMPRODUCT((MONTH(Spending!$B$4:$B$278)=12)*(Spending!$E$4:$E$278="Vacation")*Spending!$D$4:$D$278) | AX18: =AU18+AV18-AW18
B19: Car Repair Fund | C19: 0 | D19: =SUMPRODUCT((MONTH(Funding!$B$4:$B$29)=1)*Funding!T$4:T$29) | E19: =SUMPRODUCT((MONTH(Spending!$B$4:$B$278)=1)*(Spending!$E$4:$E$278="Car Repair Fund")*Spending!$D$4:$D$278) | F19: =C19+D19-E19 | G19: =IF(Envelopes!$E$19="Yes",F19,0) | H19: =SUMPRODUCT((MONTH(Funding!$B$4:$B$29)=2)*Funding!T$4:T$29) | I19: =SUMPRODUCT((MONTH(Spending!$B$4:$B$278)=2)*(Spending!$E$4:$E$278="Car Repair Fund")*Spending!$D$4:$D$278) | J19: =G19+H19-I19 | K19: =IF(Envelopes!$E$19="Yes",J19,0) | L19: =SUMPRODUCT((MONTH(Funding!$B$4:$B$29)=3)*Funding!T$4:T$29) | M19: =SUMPRODUCT((MONTH(Spending!$B$4:$B$278)=3)*(Spending!$E$4:$E$278="Car Repair Fund")*Spending!$D$4:$D$278) | N19: =K19+L19-M19 | O19: =IF(Envelopes!$E$19="Yes",N19,0) | P19: =SUMPRODUCT((MONTH(Funding!$B$4:$B$29)=4)*Funding!T$4:T$29) | Q19: =SUMPRODUCT((MONTH(Spending!$B$4:$B$278)=4)*(Spending!$E$4:$E$278="Car Repair Fund")*Spending!$D$4:$D$278) | R19: =O19+P19-Q19 | S19: =IF(Envelopes!$E$19="Yes",R19,0) | T19: =SUMPRODUCT((MONTH(Funding!$B$4:$B$29)=5)*Funding!T$4:T$29) | U19: =SUMPRODUCT((MONTH(Spending!$B$4:$B$278)=5)*(Spending!$E$4:$E$278="Car Repair Fund")*Spending!$D$4:$D$278) | V19: =S19+T19-U19 | W19: =IF(Envelopes!$E$19="Yes",V19,0) | X19: =SUMPRODUCT((MONTH(Funding!$B$4:$B$29)=6)*Funding!T$4:T$29) | Y19: =SUMPRODUCT((MONTH(Spending!$B$4:$B$278)=6)*(Spending!$E$4:$E$278="Car Repair Fund")*Spending!$D$4:$D$278) | Z19: =W19+X19-Y19 | AA19: =IF(Envelopes!$E$19="Yes",Z19,0) | AB19: =SUMPRODUCT((MONTH(Funding!$B$4:$B$29)=7)*Funding!T$4:T$29) | AC19: =SUMPRODUCT((MONTH(Spending!$B$4:$B$278)=7)*(Spending!$E$4:$E$278="Car Repair Fund")*Spending!$D$4:$D$278) | AD19: =AA19+AB19-AC19 | AE19: =IF(Envelopes!$E$19="Yes",AD19,0) | AF19: =SUMPRODUCT((MONTH(Funding!$B$4:$B$29)=8)*Funding!T$4:T$29) | AG19: =SUMPRODUCT((MONTH(Spending!$B$4:$B$278)=8)*(Spending!$E$4:$E$278="Car Repair Fund")*Spending!$D$4:$D$278) | AH19: =AE19+AF19-AG19 | AI19: =IF(Envelopes!$E$19="Yes",AH19,0) | AJ19: =SUMPRODUCT((MONTH(Funding!$B$4:$B$29)=9)*Funding!T$4:T$29) | AK19: =SUMPRODUCT((MONTH(Spending!$B$4:$B$278)=9)*(Spending!$E$4:$E$278="Car Repair Fund")*Spending!$D$4:$D$278) | AL19: =AI19+AJ19-AK19 | AM19: =IF(Envelopes!$E$19="Yes",AL19,0) | AN19: =SUMPRODUCT((MONTH(Funding!$B$4:$B$29)=10)*Funding!T$4:T$29) | AO19: =SUMPRODUCT((MONTH(Spending!$B$4:$B$278)=10)*(Spending!$E$4:$E$278="Car Repair Fund")*Spending!$D$4:$D$278) | AP19: =AM19+AN19-AO19 | AQ19: =IF(Envelopes!$E$19="Yes",AP19,0) | AR19: =SUMPRODUCT((MONTH(Funding!$B$4:$B$29)=11)*Funding!T$4:T$29) | AS19: =SUMPRODUCT((MONTH(Spending!$B$4:$B$278)=11)*(Spending!$E$4:$E$278="Car Repair Fund")*Spending!$D$4:$D$278) | AT19: =AQ19+AR19-AS19 | AU19: =IF(Envelopes!$E$19="Yes",AT19,0) | AV19: =SUMPRODUCT((MONTH(Funding!$B$4:$B$29)=12)*Funding!T$4:T$29) | AW19: =SUMPRODUCT((MONTH(Spending!$B$4:$B$278)=12)*(Spending!$E$4:$E$278="Car Repair Fund")*Spending!$D$4:$D$278) | AX19: =AU19+AV19-AW19

Sheet Dashboard
B2: Envelope Dashboard
B4: Total Funded YTD | C4: Total Spent YTD | D4: Envelopes Overspent (Dec) | E4: Net YTD
B5: =SUM(Funding!D4:D29) | C5: =SUM(E4:E19)+SUM(I4:I19)+SUM(M4:M19)+SUM(Q4:Q19)+SUM(U4:U19)+SUM(Y4:Y19)+SUM(AC4:AC19)+SUM(AG4:AG19)+SUM(AK4:AK19)+SUM(AO4:AO19)+SUM(AS4:AS19)+SUM(AW4:AW19) | D5: =COUNTIF('Monthly Balances'!AX4:AX19,"<0") | E5: =B5-C5
B8: Envelope | C8: Dec Ending Balance
B9: Rent | C9: ='Monthly Balances'!AX4
B10: Utilities | C10: ='Monthly Balances'!AX5
B11: Groceries | C11: ='Monthly Balances'!AX6
B12: Gas | C12: ='Monthly Balances'!AX7
B13: Auto Insurance | C13: ='Monthly Balances'!AX8
B14: Phone | C14: ='Monthly Balances'!AX9
B15: Medical | C15: ='Monthly Balances'!AX10
B16: Dining Out | C16: ='Monthly Balances'!AX11
B17: Coffee | C17: ='Monthly Balances'!AX12
B18: Entertainment | C18: ='Monthly Balances'!AX13
B19: Clothing | C19: ='Monthly Balances'!AX14
B20: Personal Care | C20: ='Monthly Balances'!AX15
... B24: Car Repair Fund | C24: ='Monthly Balances'!AX19
B27: Month | C27: Total Funded | D27: Total Spent
B28: Jan | C28: =SUM('Monthly Balances'!D4:D19) | D28: =SUM('Monthly Balances'!E4:E19)
B29: Feb | C29: =SUM('Monthly Balances'!H4:H19) | D29: =SUM('Monthly Balances'!I4:I19)
B30: Mar | C30: =SUM('Monthly Balances'!L4:L19) | D30: =SUM('Monthly Balances'!M4:M19)
B31: Apr | C31: =SUM('Monthly Balances'!P4:P19) | D31: =SUM('Monthly Balances'!Q4:Q19)
B32: May | C32: =SUM('Monthly Balances'!T4:T19) | D32: =SUM('Monthly Balances'!U4:U19)
B33: Jun | C33: =SUM('Monthly Balances'!X4:X19) | D33: =SUM('Monthly Balances'!Y4:Y19)
B34: Jul | C34: =SUM('Monthly Balances'!AB4:AB19) | D34: =SUM('Monthly Balances'!AC4:AC19)
B35: Aug | C35: =SUM('Monthly Balances'!AF4:AF19) | D35: =SUM('Monthly Balances'!AG4:AG19)
B36: Sep | C36: =SUM('Monthly Balances'!AJ4:AJ19) | D36: =SUM('Monthly Balances'!AK4:AK19)
B37: Oct | C37: =SUM('Monthly Balances'!AN4:AN19) | D37: =SUM('Monthly Balances'!AO4:AO19)
B38: Nov | C38: =SUM('Monthly Balances'!AR4:AR19) | D38: =SUM('Monthly Balances'!AS4:AS19)
B39: Dec | C39: =SUM('Monthly Balances'!AV4:AV19) | D39: =SUM('Monthly Balances'!AW4:AW19)

Sheet Readme
C3: Envelope Budget System
C5: Sample data covers 26 bi-weekly paychecks in 2025.
C6: All transactions and amounts are fictional.
C7: Start on the Envelopes sheet to set targets and rollover rules.
C8: Split each paycheck across envelopes on the Funding sheet.
C9: Log spending on the Spending sheet using the envelope dropdown.
C10: Monthly Balances runs the rollover math automatically.
C11: Do not insert or delete rows inside the data ranges.
C12: This is not financial advice. Talk to a professional about your situation.
