Workbook

Sheet Accounts
B2: Account Registry
B3: Account Name | C3: Institution | D3: Type | E3: Asset Class | F3: Current Balance | G3: Monthly Contribution | H3: Expected Annual Return | I3: Last Updated
B4: Chase Checking | C4: Chase | D4: Checking | E4: Cash | F4: 5800 | G4: 0 | H4: 0.005 | I4: 45748
B5: Ally HYSA | C5: Ally | D5: Savings | E5: Cash | F5: 18000 | G5: 500 | H5: 0.045 | I5: 45748
B6: Vanguard Total Market | C6: Vanguard | D6: Brokerage | E6: US Equity | F6: 42000 | G6: 400 | H6: 0.08 | I6: 45748
B7: Fidelity Intl Fund | C7: Fidelity | D7: Brokerage | E7: Intl Equity | F7: 15000 | G7: 200 | H7: 0.07 | I7: 45748
B8: Company 401k | C8: Fidelity | D8: 401k | E8: US Equity | F8: 78000 | G8: 750 | H8: 0.08 | I8: 45748
B9: Roth IRA | C9: Vanguard | D9: Roth IRA | E9: US Equity | F9: 32000 | G9: 500 | H9: 0.08 | I9: 45748
B10: Traditional IRA | C10: Schwab | D10: IRA | E10: US Bonds | F10: 12000 | G10: 0 | H10: 0.04 | I10: 45748
B11: HSA | C11: Optum | D11: HSA | E11: US Equity | F11: 6200 | G11: 150 | H11: 0.07 | I11: 45748
B12: 529 Plan | C12: Vanguard | D12: 529 | E12: US Equity | F12: 8500 | G12: 200 | H12: 0.07 | I12: 45748
B13: Coinbase | C13: Coinbase | D13: Crypto | E13: Alternatives | F13: 4200 | G13: 0 | H13: 0.1 | I13: 45748
B14: Home Equity | C14: Zillow Est. | D14: Real Estate | E14: Real Estate | F14: 95000 | G14: 0 | H14: 0.03 | I14: 45748
B15: Car Value | C15: KBB Est. | D15: Vehicle | E15: N-A | F15: 16000 | G15: 0 | H15: -0.1 | I15: 45748
... B19: Auto Loan | C19: Capital One | D19: Auto Loan | E19: N-A | F19: 9800 | G19: 0 | H19: 0 | I19: 45748

Sheet Cash Flow
B2: Monthly Cash Flow
B3: Month | C3: Total Income | D3: Fixed Expenses | E3: Variable Expenses | F3: Total Expenses | G3: Net Surplus | H3: Savings Rate | I3: YTD Surplus
B4: Jan | C4: 7561 | D4: 3790 | E4: 1435 | F4: =D4+E4 | G4: =C4-F4 | H4: =IFERROR(G4/C4,0) | I4: =SUM(G$4:G4)
B5: Feb | C5: 7570 | D5: 3841 | E5: 1847 | F5: =D5+E5 | G5: =C5-F5 | H5: =IFERROR(G5/C5,0) | I5: =SUM(G$4:G5)
B6: Mar | C6: 7309 | D6: 3814 | E6: 1497 | F6: =D6+E6 | G6: =C6-F6 | H6: =IFERROR(G6/C6,0) | I6: =SUM(G$4:G6)
B7: Apr | C7: 7446 | D7: 3771 | E7: 1458 | F7: =D7+E7 | G7: =C7-F7 | H7: =IFERROR(G7/C7,0) | I7: =SUM(G$4:G7)
B8: May | C8: 7110 | D8: 3813 | E8: 1964 | F8: =D8+E8 | G8: =C8-F8 | H8: =IFERROR(G8/C8,0) | I8: =SUM(G$4:G8)
B9: Jun | C9: 7225 | D9: 3777 | E9: 2080 | F9: =D9+E9 | G9: =C9-F9 | H9: =IFERROR(G9/C9,0) | I9: =SUM(G$4:G9)
B10: Jul | C10: 7523 | D10: 3821 | E10: 1820 | F10: =D10+E10 | G10: =C10-F10 | H10: =IFERROR(G10/C10,0) | I10: =SUM(G$4:G10)
B11: Aug | C11: 7158 | D11: 3810 | E11: 1522 | F11: =D11+E11 | G11: =C11-F11 | H11: =IFERROR(G11/C11,0) | I11: =SUM(G$4:G11)
B12: Sep | C12: 7028 | D12: 3759 | E12: 1733 | F12: =D12+E12 | G12: =C12-F12 | H12: =IFERROR(G12/C12,0) | I12: =SUM(G$4:G12)
B13: Oct | C13: 7065 | D13: 3766 | E13: 1810 | F13: =D13+E13 | G13: =C13-F13 | H13: =IFERROR(G13/C13,0) | I13: =SUM(G$4:G13)
B14: Nov | C14: 7166 | D14: 3766 | E14: 1357 | F14: =D14+E14 | G14: =C14-F14 | H14: =IFERROR(G14/C14,0) | I14: =SUM(G$4:G14)
B15: Dec | C15: 7561 | D15: 3787 | E15: 1647 | F15: =D15+E15 | G15: =C15-F15 | H15: =IFERROR(G15/C15,0) | I15: =SUM(G$4:G15)
B17: Annual Total | C17: =SUM(C4:C15) | D17: =SUM(D4:D15) | E17: =SUM(E4:E15) | F17: =SUM(F4:F15) | G17: =SUM(G4:G15) | H17: =IFERROR(G17/C17,0)

Sheet Goals
B2: Financial Goals
B3: Goal Name | C3: Target | D3: Current Saved | E3: Monthly Contrib. | F3: Expected Return | G3: Start Date | H3: Proj. Months | I3: Proj. Date | J3: Progress % | K3: Status
B4: Emergency Fund | C4: 15000 | D4: 8200 | E4: 400 | F4: 0.045 | G4: 45292 | H4: =IFERROR(NPER(F4/12,-E4,-D4,C4),0) | I4: =IF(H4<=0,TODAY(),TODAY()+H4*30.44) | J4: =MIN(1,D4/C4) | K4: =IF(D4>=C4,"Reached",IF(H4<120,"On Track","Behind"))
B5: House Down Payment | C5: 60000 | D5: 12000 | E5: 800 | F5: 0.05 | G5: 45444 | H5: =IFERROR(NPER(F5/12,-E5,-D5,C5),0) | I5: =IF(H5<=0,TODAY(),TODAY()+H5*30.44) | J5: =MIN(1,D5/C5) | K5: =IF(D5>=C5,"Reached",IF(H5<120,"On Track","Behind"))
B6: Vacation Fund | C6: 5000 | D6: 2100 | E6: 250 | F6: 0.02 | G6: 45658 | H6: =IFERROR(NPER(F6/12,-E6,-D6,C6),0) | I6: =IF(H6<=0,TODAY(),TODAY()+H6*30.44) | J6: =MIN(1,D6/C6) | K6: =IF(D6>=C6,"Reached",IF(H6<120,"On Track","Behind"))
B7: New Car Fund | C7: 8000 | D7: 1500 | E7: 200 | F7: 0.03 | G7: 45717 | H7: =IFERROR(NPER(F7/12,-E7,-D7,C7),0) | I7: =IF(H7<=0,TODAY(),TODAY()+H7*30.44) | J7: =MIN(1,D7/C7) | K7: =IF(D7>=C7,"Reached",IF(H7<120,"On Track","Behind"))
B8: Kids College (529) | C8: 40000 | D8: 8500 | E8: 200 | F8: 0.07 | G8: 45170 | H8: =IFERROR(NPER(F8/12,-E8,-D8,C8),0) | I8: =IF(H8<=0,TODAY(),TODAY()+H8*30.44) | J8: =MIN(1,D8/C8) | K8: =IF(D8>=C8,"Reached",IF(H8<120,"On Track","Behind"))
B9: Early Retirement Buffer | C9: 200000 | D9: 32000 | E9: 500 | F9: 0.08 | G9: 44562 | H9: =IFERROR(NPER(F9/12,-E9,-D9,C9),0) | I9: =IF(H9<=0,TODAY(),TODAY()+H9*30.44) | J9: =MIN(1,D9/C9) | K9: =IF(D9>=C9,"Reached",IF(H9<120,"On Track","Behind"))

Sheet Allocation
B2: Asset Allocation Analysis
B3: Total Investable Assets | C3: =SUMPRODUCT((Accounts!$D$4:$D$19="Brokerage")*Accounts!$F$4:$F$19)+SUMPRODUCT((Accounts!$D$4:$D$19="401k")*Accounts!$F$4:$F$19)+SUMPRODUCT((Accounts!$D$4:$D$19="IRA")*Accounts!$F$4:$F$19)+SUMPRODUCT((Accounts!$D$4:$D$19="Roth IRA")*Accounts!$F$4:$F$19)+SUMPRODUCT((Accounts!$D$4:$D$19="HSA")*Accounts!$F$4:$F$19)+SUMPRODUCT((Accounts!$D$4:$D$19="529")*Accounts!$F$4:$F$19)+SUMPRODUCT((Accounts!$D$4:$D$19="Crypto")*Accounts!$F$4:$F$19)
B5: Asset Class | C5: Current $ | D5: Current % | E5: Target % | F5: Difference % | G5: Rebalance $
B6: Cash | C6: =SUMPRODUCT((Accounts!$E$4:$E$19="Cash")*Accounts!$F$4:$F$19) | D6: =IFERROR(C6/$C$3,0) | E6: 0.05 | F6: =D6-E6 | G6: =(E6*$C$3)-C6
B7: US Bonds | C7: =SUMPRODUCT((Accounts!$E$4:$E$19="US Bonds")*Accounts!$F$4:$F$19) | D7: =IFERROR(C7/$C$3,0) | E7: 0.1 | F7: =D7-E7 | G7: =(E7*$C$3)-C7
B8: US Equity | C8: =SUMPRODUCT((Accounts!$E$4:$E$19="US Equity")*Accounts!$F$4:$F$19) | D8: =IFERROR(C8/$C$3,0) | E8: 0.5 | F8: =D8-E8 | G8: =(E8*$C$3)-C8
B9: Intl Equity | C9: =SUMPRODUCT((Accounts!$E$4:$E$19="Intl Equity")*Accounts!$F$4:$F$19) | D9: =IFERROR(C9/$C$3,0) | E9: 0.15 | F9: =D9-E9 | G9: =(E9*$C$3)-C9
B10: Real Estate | C10: =SUMPRODUCT((Accounts!$E$4:$E$19="Real Estate")*Accounts!$F$4:$F$19) | D10: =IFERROR(C10/$C$3,0) | E10: 0.1 | F10: =D10-E10 | G10: =(E10*$C$3)-C10
B11: Alternatives | C11: =SUMPRODUCT((Accounts!$E$4:$E$19="Alternatives")*Accounts!$F$4:$F$19) | D11: =IFERROR(C11/$C$3,0) | E11: 0.1 | F11: =D11-E11 | G11: =(E11*$C$3)-C11

Sheet Dashboard
B2: Financial Command Center
B4: Total Net Worth | C4: =(SUMPRODUCT((Accounts!$D$4:$D$19="Checking")*Accounts!$F$4:$F$19)+SUMPRODUCT((Accounts!$D$4:$D$19="Savings")*Accounts!$F$4:$F$19)+SUMPRODUCT((Accounts!$D$4:$D$19="Brokerage")*Accounts!$F$4:$F$19)+SUMPRODUCT((Accounts!$D$4:$D$19="401k")*Accounts!$F$4:$F$19)+SUMPRODUCT((Accounts!$D$4:$D$19="IRA")*Accounts!$F$4:$F$19)+SUMPRODUCT((Accounts!$D$4:$D$19="Roth IRA")*Accounts!$F$4:$F$19)+SUMPRODUCT((Accounts!$D$4:$D$19="HSA")*Accounts!$F$4:$F$19)+SUMPRODUCT((Accounts!$D$4:$D$19="529")*Accounts!$F$4:$F$19)+SUMPRODUCT((Accounts!$D$4:$D$19="Crypto")*Accounts!$F$4:$F$19)+SUMPRODUCT((Accounts!$D$4:$D$19="Real Estate")*Accounts!$F$4:$F$19)+SUMPRODUCT((Accounts!$D$4:$D$19="Vehicle")*Accounts!$F$4:$F$19))-(SUMPRODUCT((Accounts!$D$4:$D$19="Credit Card")*Accounts!$F$4:$F$19)+SUMPRODUCT((Accounts!$D$4:$D$19="Student Loan")*Accounts!$F$4:$F$19)+SUMPRODUCT((Accounts!$D$4:$D$19="Mortgage")*Accounts!$F$4:$F$19)+SUMPRODUCT((Accounts!$D$4:$D$19="Auto Loan")*Accounts!$F$4:$F$19))
B5: Savings Rate (3-Mo Avg) | C5: =AVERAGE('Cash Flow'!H13:'Cash Flow'!H15)
B6: Months to Next Goal | C6: =MIN(Goals!H4:H9)
B7: Largest Allocation Gap | C7: =MAX(ABS(Allocation!F6:F11))
B10: Asset Class | C10: Current % | E10: Asset Class | F10: Target %
B11: Cash | C11: =Allocation!D6 | E11: Cash | F11: =Allocation!E6
B12: US Bonds | C12: =Allocation!D7 | E12: US Bonds | F12: =Allocation!E7
B13: US Equity | C13: =Allocation!D8 | E13: US Equity | F13: =Allocation!E8
B14: Intl Equity | C14: =Allocation!D9 | E14: Intl Equity | F14: =Allocation!E9
B15: Real Estate | C15: =Allocation!D10 | E15: Real Estate | F15: =Allocation!E10
B16: Alternatives | C16: =Allocation!D11 | E16: Alternatives | F16: =Allocation!E11
B19: Goal | C19: Progress %
B20: =Goals!B4 | C20: =Goals!J4
B21: =Goals!B5 | C21: =Goals!J5
B22: =Goals!B6 | C22: =Goals!J6
B23: =Goals!B7 | C23: =Goals!J7
B24: =Goals!B8 | C24: =Goals!J8
B25: =Goals!B9 | C25: =Goals!J9
B43: Month | C43: Net Surplus
B44: Jan | C44: ='Cash Flow'!G4
B45: Feb | C45: ='Cash Flow'!G5
B46: Mar | C46: ='Cash Flow'!G6
B47: Apr | C47: ='Cash Flow'!G7
B48: May | C48: ='Cash Flow'!G8
B49: Jun | C49: ='Cash Flow'!G9
B50: Jul | C50: ='Cash Flow'!G10
B51: Aug | C51: ='Cash Flow'!G11
B52: Sep | C52: ='Cash Flow'!G12
B53: Oct | C53: ='Cash Flow'!G13
B54: Nov | C54: ='Cash Flow'!G14
B55: Dec | C55: ='Cash Flow'!G15

Sheet Readme
C3: Financial Command Center
C5: Sample data as of April 2025.
C6: All account names and balances are fictional.
C7: Update the Accounts sheet with current balances periodically.
C8: Log monthly income and expenses in the Cash Flow sheet.
C9: Goal projections use NPER which accounts for expected returns.
C10: Adjust target allocation percentages on the Allocation sheet.
C11: Do not insert or delete rows inside the account or goal ranges.
C12: This is not financial advice. Talk to a professional about your situation.
