Workbook

Sheet Income
A1: Employment Income
A2: Annual Gross Salary | B2: 78000
A3: Pay Frequency | B3: Semi-monthly
A4: Paychecks per Year | B4: =IF(B3="Weekly",52,IF(B3="Biweekly",26,IF(B3="Semi-monthly",24,12))) -> 24
A5: Gross per Paycheck | B5: =B2/B4 -> 3250
A6: Deductions per Paycheck
A7: Federal Tax (est.) | B7: =IF(B2<=11925,B2*0.1,IF(B2<=48475,11925*0.1+(B2-11925)*0.12,IF(B2<=103350,11925*0.1+36550*0.12+(B2-48475)*0.22,IF(B2<=197300,11925*0.1+36550*0.12+54875*0.22+(B2-103350)*0.24,B2*0.22))))/B4 -> 503.08333
A8: State Tax Rate | B8: 0.05
A9: State Tax | B9: =B5*B8 -> 162.5
A10: FICA (7.65%) | B10: =B5*0.0765 -> 248.625
A11: Payroll Health Insurance | B11: 180
A12: Payroll 401k Contribution | B12: 250
A13: Other Deductions | B13: 0
A14: Total Deductions | B14: =SUM(B7,B9:B13) -> 1344.2083
A15: Net per Paycheck | B15: =B5-B14 -> 1905.7917
A16: Monthly Net Income
A17: Monthly Net from Job | B17: =B15*(B4/12) -> 3811.5833
A18: Other Monthly Income | B18: 400
A19: Total Monthly Net | B19: =B17+B18 -> 4211.5833
A20: 50/30/20 Targets
A21: Needs Target (50%) | B21: =B19*0.5 -> 2105.7917
A22: Wants Target (30%) | B22: =B19*0.3 -> 1263.475
A23: Savings Target (20%) | B23: =B19*0.2 -> 842.31667

Sheet Category Map
A1: Category | B1: Bucket
A2: Rent/Mortgage | B2: Needs
A3: Utilities | B3: Needs
A4: Groceries | B4: Needs
A5: Auto Insurance | B5: Needs
A6: Gas | B6: Needs
A7: Health Insurance (manual) | B7: Needs
A8: Phone | B8: Needs
A9: Min Debt Payment | B9: Needs
A10: Medical/Prescriptions | B10: Needs
A11: Renters Insurance | B11: Needs
A12: Internet | B12: Needs
... A29: 529 College | B29: Savings

Sheet Expense Log
A1: Date | B1: Payee | C1: Amount | D1: Category | E1: Bucket | F1: Recurring | G1: Notes
A2: 45666 | B2: Landlord LLC | C2: 1450 | D2: Rent/Mortgage | E2: =IFERROR(VLOOKUP(D2,'Category Map'!$A$2:$B$29,2,FALSE),"") -> Needs | F2: Yes
A3: 45658 | B3: Power Co | C3: 64.47 | D3: Utilities | E3: =IFERROR(VLOOKUP(D3,'Category Map'!$A$2:$B$29,2,FALSE),"") -> Needs | F3: No
A4: 45673 | B4: Power Co | C4: 67.65 | D4: Utilities | E4: =IFERROR(VLOOKUP(D4,'Category Map'!$A$2:$B$29,2,FALSE),"") -> Needs | F4: No
A5: 45667 | B5: Kroger | C5: 179.74 | D5: Groceries | E5: =IFERROR(VLOOKUP(D5,'Category Map'!$A$2:$B$29,2,FALSE),"") -> Needs | F5: No
A6: 45686 | B6: Kroger | C6: 156.48 | D6: Groceries | E6: =IFERROR(VLOOKUP(D6,'Category Map'!$A$2:$B$29,2,FALSE),"") -> Needs | F6: No
A7: 45662 | B7: State Farm | C7: 105 | D7: Auto Insurance | E7: =IFERROR(VLOOKUP(D7,'Category Map'!$A$2:$B$29,2,FALSE),"") -> Needs | F7: Yes
A8: 45677 | B8: Costco Gas | C8: 24.24 | D8: Gas | E8: =IFERROR(VLOOKUP(D8,'Category Map'!$A$2:$B$29,2,FALSE),"") -> Needs | F8: No
A9: 45662 | B9: BP | C9: 41.84 | D9: Gas | E9: =IFERROR(VLOOKUP(D9,'Category Map'!$A$2:$B$29,2,FALSE),"") -> Needs | F9: No
A10: 45659 | B10: Shell | C10: 36.98 | D10: Gas | E10: =IFERROR(VLOOKUP(D10,'Category Map'!$A$2:$B$29,2,FALSE),"") -> Needs | F10: No
A11: 45663 | B11: Costco Gas | C11: 30 | D11: Gas | E11: =IFERROR(VLOOKUP(D11,'Category Map'!$A$2:$B$29,2,FALSE),"") -> Needs | F11: No
A12: 45666 | B12: Verizon | C12: 70 | D12: Phone | E12: =IFERROR(VLOOKUP(D12,'Category Map'!$A$2:$B$29,2,FALSE),"") -> Needs | F12: Yes
A13: 45682 | B13: Chase Visa | C13: 300 | D13: Min Debt Payment | E13: =IFERROR(VLOOKUP(D13,'Category Map'!$A$2:$B$29,2,FALSE),"") -> Needs | F13: Yes
... A453: 46001 | B453: Fidelity Transfer | C453: 150 | D453: Investments | E453: =IFERROR(VLOOKUP(D453,'Category Map'!$A$2:$B$29,2,FALSE),"") -> Savings | F453: Yes

Sheet Monthly Tracker
A1: Bucket | B1: Jan Actual | C1: Jan Target | D1: Jan Delta | E1: Feb Actual | F1: Feb Target | G1: Feb Delta | H1: Mar Actual | I1: Mar Target | J1: Mar Delta | K1: Apr Actual | L1: Apr Target | M1: Apr Delta | N1: May Actual | O1: May Target | P1: May Delta | Q1: Jun Actual | R1: Jun Target | S1: Jun Delta | T1: Jul Actual | U1: Jul Target | V1: Jul Delta | W1: Aug Actual | X1: Aug Target | Y1: Aug Delta | Z1: Sep Actual | AA1: Sep Target | AB1: Sep Delta | AC1: Oct Actual | AD1: Oct Target | AE1: Oct Delta | AF1: Nov Actual | AG1: Nov Target | AH1: Nov Delta | AI1: Dec Actual | AJ1: Dec Target | AK1: Dec Delta | AL1: Annual Act. | AM1: Annual Tgt. | AN1: Annual Delta
A2: Needs | B2: =SUMIFS('Expense Log'!$C$2:$C$453,'Expense Log'!$E$2:$E$453,"Needs",'Expense Log'!$A$2:$A$453,">="&DATE(2025,1,1),'Expense Log'!$A$2:$A$453,"<"&DATE(2025,2,1)) -> 2647.21 | C2: =Income!$B$21 -> 2105.7917 | D2: =C2-B2 -> -541.41833 | E2: =SUMIFS('Expense Log'!$C$2:$C$453,'Expense Log'!$E$2:$E$453,"Needs",'Expense Log'!$A$2:$A$453,">="&DATE(2025,2,1),'Expense Log'!$A$2:$A$453,"<"&DATE(2025,3,1)) -> 2868.26 | F2: =Income!$B$21 -> 2105.7917 | G2: =F2-E2 -> -762.46833 | H2: =SUMIFS('Expense Log'!$C$2:$C$453,'Expense Log'!$E$2:$E$453,"Needs",'Expense Log'!$A$2:$A$453,">="&DATE(2025,3,1),'Expense Log'!$A$2:$A$453,"<"&DATE(2025,4,1)) -> 2793.19 | I2: =Income!$B$21 -> 2105.7917 | J2: =I2-H2 -> -687.39833 | K2: =SUMIFS('Expense Log'!$C$2:$C$453,'Expense Log'!$E$2:$E$453,"Needs",'Expense Log'!$A$2:$A$453,">="&DATE(2025,4,1),'Expense Log'!$A$2:$A$453,"<"&DATE(2025,5,1)) -> 2823.94 | L2: =Income!$B$21 -> 2105.7917 | M2: =L2-K2 -> -718.14833 | N2: =SUMIFS('Expense Log'!$C$2:$C$453,'Expense Log'!$E$2:$E$453,"Needs",'Expense Log'!$A$2:$A$453,">="&DATE(2025,5,1),'Expense Log'!$A$2:$A$453,"<"&DATE(2025,6,1)) -> 2748.59 | O2: =Income!$B$21 -> 2105.7917 | P2: =O2-N2 -> -642.79833 | Q2: =SUMIFS('Expense Log'!$C$2:$C$453,'Expense Log'!$E$2:$E$453,"Needs",'Expense Log'!$A$2:$A$453,">="&DATE(2025,6,1),'Expense Log'!$A$2:$A$453,"<"&DATE(2025,7,1)) -> 2826.94 | R2: =Income!$B$21 -> 2105.7917 | S2: =R2-Q2 -> -721.14833 | T2: =SUMIFS('Expense Log'!$C$2:$C$453,'Expense Log'!$E$2:$E$453,"Needs",'Expense Log'!$A$2:$A$453,">="&DATE(2025,7,1),'Expense Log'!$A$2:$A$453,"<"&DATE(2025,8,1)) -> 2638.8 | U2: =Income!$B$21 -> 2105.7917 | V2: =U2-T2 -> -533.00833 | W2: =SUMIFS('Expense Log'!$C$2:$C$453,'Expense Log'!$E$2:$E$453,"Needs",'Expense Log'!$A$2:$A$453,">="&DATE(2025,8,1),'Expense Log'!$A$2:$A$453,"<"&DATE(2025,9,1)) -> 2787.86 | X2: =Income!$B$21 -> 2105.7917 | Y2: =X2-W2 -> -682.06833 | Z2: =SUMIFS('Expense Log'!$C$2:$C$453,'Expense Log'!$E$2:$E$453,"Needs",'Expense Log'!$A$2:$A$453,">="&DATE(2025,9,1),'Expense Log'!$A$2:$A$453,"<"&DATE(2025,10,1)) -> 2707.89 | AA2: =Income!$B$21 -> 2105.7917 | AB2: =AA2-Z2 -> -602.09833 | AC2: =SUMIFS('Expense Log'!$C$2:$C$453,'Expense Log'!$E$2:$E$453,"Needs",'Expense Log'!$A$2:$A$453,">="&DATE(2025,10,1),'Expense Log'!$A$2:$A$453,"<"&DATE(2025,11,1)) -> 2840.65 | AD2: =Income!$B$21 -> 2105.7917 | AE2: =AD2-AC2 -> -734.85833 | AF2: =SUMIFS('Expense Log'!$C$2:$C$453,'Expense Log'!$E$2:$E$453,"Needs",'Expense Log'!$A$2:$A$453,">="&DATE(2025,11,1),'Expense Log'!$A$2:$A$453,"<"&DATE(2025,12,1)) -> 2730.16 | AG2: =Income!$B$21 -> 2105.7917 | AH2: =AG2-AF2 -> -624.36833 | AI2: =SUMIFS('Expense Log'!$C$2:$C$453,'Expense Log'!$E$2:$E$453,"Needs",'Expense Log'!$A$2:$A$453,">="&DATE(2025,12,1),'Expense Log'!$A$2:$A$453,"<"&DATE(2026,1,1)) -> 2752.63 | AJ2: =Income!$B$21 -> 2105.7917 | AK2: =AJ2-AI2 -> -646.83833 | AL2: =B2+E2+H2+K2+N2+Q2+T2+W2+Z2+AC2+AF2+AI2 -> 33166.12 | AM2: =C2+F2+I2+L2+O2+R2+U2+X2+AA2+AD2+AG2+AJ2 -> 25269.5 | AN2: =AM2-AL2 -> -7896.62
A3: Wants | B3: =SUMIFS('Expense Log'!$C$2:$C$453,'Expense Log'!$E$2:$E$453,"Wants",'Expense Log'!$A$2:$A$453,">="&DATE(2025,1,1),'Expense Log'!$A$2:$A$453,"<"&DATE(2025,2,1)) -> 538.19 | C3: =Income!$B$22 -> 1263.475 | D3: =C3-B3 -> 725.285 | E3: =SUMIFS('Expense Log'!$C$2:$C$453,'Expense Log'!$E$2:$E$453,"Wants",'Expense Log'!$A$2:$A$453,">="&DATE(2025,2,1),'Expense Log'!$A$2:$A$453,"<"&DATE(2025,3,1)) -> 603.2 | F3: =Income!$B$22 -> 1263.475 | G3: =F3-E3 -> 660.275 | H3: =SUMIFS('Expense Log'!$C$2:$C$453,'Expense Log'!$E$2:$E$453,"Wants",'Expense Log'!$A$2:$A$453,">="&DATE(2025,3,1),'Expense Log'!$A$2:$A$453,"<"&DATE(2025,4,1)) -> 579.04 | I3: =Income!$B$22 -> 1263.475 | J3: =I3-H3 -> 684.435 | K3: =SUMIFS('Expense Log'!$C$2:$C$453,'Expense Log'!$E$2:$E$453,"Wants",'Expense Log'!$A$2:$A$453,">="&DATE(2025,4,1),'Expense Log'!$A$2:$A$453,"<"&DATE(2025,5,1)) -> 595.97 | L3: =Income!$B$22 -> 1263.475 | M3: =L3-K3 -> 667.505 | N3: =SUMIFS('Expense Log'!$C$2:$C$453,'Expense Log'!$E$2:$E$453,"Wants",'Expense Log'!$A$2:$A$453,">="&DATE(2025,5,1),'Expense Log'!$A$2:$A$453,"<"&DATE(2025,6,1)) -> 649.71 | O3: =Income!$B$22 -> 1263.475 | P3: =O3-N3 -> 613.765 | Q3: =SUMIFS('Expense Log'!$C$2:$C$453,'Expense Log'!$E$2:$E$453,"Wants",'Expense Log'!$A$2:$A$453,">="&DATE(2025,6,1),'Expense Log'!$A$2:$A$453,"<"&DATE(2025,7,1)) -> 1094.27 | R3: =Income!$B$22 -> 1263.475 | S3: =R3-Q3 -> 169.205 | T3: =SUMIFS('Expense Log'!$C$2:$C$453,'Expense Log'!$E$2:$E$453,"Wants",'Expense Log'!$A$2:$A$453,">="&DATE(2025,7,1),'Expense Log'!$A$2:$A$453,"<"&DATE(2025,8,1)) -> 513.72 | U3: =Income!$B$22 -> 1263.475 | V3: =U3-T3 -> 749.755 | W3: =SUMIFS('Expense Log'!$C$2:$C$453,'Expense Log'!$E$2:$E$453,"Wants",'Expense Log'!$A$2:$A$453,">="&DATE(2025,8,1),'Expense Log'!$A$2:$A$453,"<"&DATE(2025,9,1)) -> 555.4 | X3: =Income!$B$22 -> 1263.475 | Y3: =X3-W3 -> 708.075 | Z3: =SUMIFS('Expense Log'!$C$2:$C$453,'Expense Log'!$E$2:$E$453,"Wants",'Expense Log'!$A$2:$A$453,">="&DATE(2025,9,1),'Expense Log'!$A$2:$A$453,"<"&DATE(2025,10,1)) -> 600.62 | AA3: =Income!$B$22 -> 1263.475 | AB3: =AA3-Z3 -> 662.855 | AC3: =SUMIFS('Expense Log'!$C$2:$C$453,'Expense Log'!$E$2:$E$453,"Wants",'Expense Log'!$A$2:$A$453,">="&DATE(2025,10,1),'Expense Log'!$A$2:$A$453,"<"&DATE(2025,11,1)) -> 562.11 | AD3: =Income!$B$22 -> 1263.475 | AE3: =AD3-AC3 -> 701.365 | AF3: =SUMIFS('Expense Log'!$C$2:$C$453,'Expense Log'!$E$2:$E$453,"Wants",'Expense Log'!$A$2:$A$453,">="&DATE(2025,11,1),'Expense Log'!$A$2:$A$453,"<"&DATE(2025,12,1)) -> 547.2 | AG3: =Income!$B$22 -> 1263.475 | AH3: =AG3-AF3 -> 716.275 | AI3: =SUMIFS('Expense Log'!$C$2:$C$453,'Expense Log'!$E$2:$E$453,"Wants",'Expense Log'!$A$2:$A$453,">="&DATE(2025,12,1),'Expense Log'!$A$2:$A$453,"<"&DATE(2026,1,1)) -> 938.6 | AJ3: =Income!$B$22 -> 1263.475 | AK3: =AJ3-AI3 -> 324.875 | AL3: =B3+E3+H3+K3+N3+Q3+T3+W3+Z3+AC3+AF3+AI3 -> 7778.03 | AM3: =C3+F3+I3+L3+O3+R3+U3+X3+AA3+AD3+AG3+AJ3 -> 15161.7 | AN3: =AM3-AL3 -> 7383.67
A4: Savings | B4: =SUMIFS('Expense Log'!$C$2:$C$453,'Expense Log'!$E$2:$E$453,"Savings",'Expense Log'!$A$2:$A$453,">="&DATE(2025,1,1),'Expense Log'!$A$2:$A$453,"<"&DATE(2025,2,1)) -> 975 | C4: =Income!$B$23 -> 842.31667 | D4: =C4-B4 -> -132.68333 | E4: =SUMIFS('Expense Log'!$C$2:$C$453,'Expense Log'!$E$2:$E$453,"Savings",'Expense Log'!$A$2:$A$453,">="&DATE(2025,2,1),'Expense Log'!$A$2:$A$453,"<"&DATE(2025,3,1)) -> 725 | F4: =Income!$B$23 -> 842.31667 | G4: =F4-E4 -> 117.31667 | H4: =SUMIFS('Expense Log'!$C$2:$C$453,'Expense Log'!$E$2:$E$453,"Savings",'Expense Log'!$A$2:$A$453,">="&DATE(2025,3,1),'Expense Log'!$A$2:$A$453,"<"&DATE(2025,4,1)) -> 725 | I4: =Income!$B$23 -> 842.31667 | J4: =I4-H4 -> 117.31667 | K4: =SUMIFS('Expense Log'!$C$2:$C$453,'Expense Log'!$E$2:$E$453,"Savings",'Expense Log'!$A$2:$A$453,">="&DATE(2025,4,1),'Expense Log'!$A$2:$A$453,"<"&DATE(2025,5,1)) -> 725 | L4: =Income!$B$23 -> 842.31667 | M4: =L4-K4 -> 117.31667 | N4: =SUMIFS('Expense Log'!$C$2:$C$453,'Expense Log'!$E$2:$E$453,"Savings",'Expense Log'!$A$2:$A$453,">="&DATE(2025,5,1),'Expense Log'!$A$2:$A$453,"<"&DATE(2025,6,1)) -> 725 | O4: =Income!$B$23 -> 842.31667 | P4: =O4-N4 -> 117.31667 | Q4: =SUMIFS('Expense Log'!$C$2:$C$453,'Expense Log'!$E$2:$E$453,"Savings",'Expense Log'!$A$2:$A$453,">="&DATE(2025,6,1),'Expense Log'!$A$2:$A$453,"<"&DATE(2025,7,1)) -> 725 | R4: =Income!$B$23 -> 842.31667 | S4: =R4-Q4 -> 117.31667 | T4: =SUMIFS('Expense Log'!$C$2:$C$453,'Expense Log'!$E$2:$E$453,"Savings",'Expense Log'!$A$2:$A$453,">="&DATE(2025,7,1),'Expense Log'!$A$2:$A$453,"<"&DATE(2025,8,1)) -> 975 | U4: =Income!$B$23 -> 842.31667 | V4: =U4-T4 -> -132.68333 | W4: =SUMIFS('Expense Log'!$C$2:$C$453,'Expense Log'!$E$2:$E$453,"Savings",'Expense Log'!$A$2:$A$453,">="&DATE(2025,8,1),'Expense Log'!$A$2:$A$453,"<"&DATE(2025,9,1)) -> 725 | X4: =Income!$B$23 -> 842.31667 | Y4: =X4-W4 -> 117.31667 | Z4: =SUMIFS('Expense Log'!$C$2:$C$453,'Expense Log'!$E$2:$E$453,"Savings",'Expense Log'!$A$2:$A$453,">="&DATE(2025,9,1),'Expense Log'!$A$2:$A$453,"<"&DATE(2025,10,1)) -> 725 | AA4: =Income!$B$23 -> 842.31667 | AB4: =AA4-Z4 -> 117.31667 | AC4: =SUMIFS('Expense Log'!$C$2:$C$453,'Expense Log'!$E$2:$E$453,"Savings",'Expense Log'!$A$2:$A$453,">="&DATE(2025,10,1),'Expense Log'!$A$2:$A$453,"<"&DATE(2025,11,1)) -> 725 | AD4: =Income!$B$23 -> 842.31667 | AE4: =AD4-AC4 -> 117.31667 | AF4: =SUMIFS('Expense Log'!$C$2:$C$453,'Expense Log'!$E$2:$E$453,"Savings",'Expense Log'!$A$2:$A$453,">="&DATE(2025,11,1),'Expense Log'!$A$2:$A$453,"<"&DATE(2025,12,1)) -> 725 | AG4: =Income!$B$23 -> 842.31667 | AH4: =AG4-AF4 -> 117.31667 | AI4: =SUMIFS('Expense Log'!$C$2:$C$453,'Expense Log'!$E$2:$E$453,"Savings",'Expense Log'!$A$2:$A$453,">="&DATE(2025,12,1),'Expense Log'!$A$2:$A$453,"<"&DATE(2026,1,1)) -> 725 | AJ4: =Income!$B$23 -> 842.31667 | AK4: =AJ4-AI4 -> 117.31667 | AL4: =B4+E4+H4+K4+N4+Q4+T4+W4+Z4+AC4+AF4+AI4 -> 9200 | AM4: =C4+F4+I4+L4+O4+R4+U4+X4+AA4+AD4+AG4+AJ4 -> 10107.8 | AN4: =AM4-AL4 -> 907.8
A6: Actual % of Net Income
A7: Needs | B7: =IFERROR(B2/Income!$B$19,0) -> 0.62855458 | E7: =IFERROR(E2/Income!$B$19,0) -> 0.68104078 | H7: =IFERROR(H2/Income!$B$19,0) -> 0.66321613 | K7: =IFERROR(K2/Income!$B$19,0) -> 0.67051742 | N7: =IFERROR(N2/Income!$B$19,0) -> 0.65262629 | Q7: =IFERROR(Q2/Income!$B$19,0) -> 0.67122974 | T7: =IFERROR(T2/Income!$B$19,0) -> 0.62655771 | W7: =IFERROR(W2/Income!$B$19,0) -> 0.66195057 | Z7: =IFERROR(Z2/Income!$B$19,0) -> 0.64296246 | AC7: =IFERROR(AC2/Income!$B$19,0) -> 0.67448505 | AF7: =IFERROR(AF2/Income!$B$19,0) -> 0.64825026 | AI7: =IFERROR(AI2/Income!$B$19,0) -> 0.65358555
A8: Wants | B8: =IFERROR(B3/Income!$B$19,0) -> 0.12778804 | E8: =IFERROR(E3/Income!$B$19,0) -> 0.14322404 | H8: =IFERROR(H3/Income!$B$19,0) -> 0.13748748 | K8: =IFERROR(K3/Income!$B$19,0) -> 0.14150735 | N8: =IFERROR(N3/Income!$B$19,0) -> 0.1542674 | Q8: =IFERROR(Q3/Income!$B$19,0) -> 0.2598239 | T8: =IFERROR(T3/Income!$B$19,0) -> 0.12197788 | W8: =IFERROR(W3/Income!$B$19,0) -> 0.13187439 | Z8: =IFERROR(Z3/Income!$B$19,0) -> 0.14261145 | AC8: =IFERROR(AC3/Income!$B$19,0) -> 0.13346762 | AF8: =IFERROR(AF3/Income!$B$19,0) -> 0.12992738 | AI8: =IFERROR(AI3/Income!$B$19,0) -> 0.22286155
A9: Savings | B9: =IFERROR(B4/Income!$B$19,0) -> 0.23150438 | E9: =IFERROR(E4/Income!$B$19,0) -> 0.17214428 | H9: =IFERROR(H4/Income!$B$19,0) -> 0.17214428 | K9: =IFERROR(K4/Income!$B$19,0) -> 0.17214428 | N9: =IFERROR(N4/Income!$B$19,0) -> 0.17214428 | Q9: =IFERROR(Q4/Income!$B$19,0) -> 0.17214428 | T9: =IFERROR(T4/Income!$B$19,0) -> 0.23150438 | W9: =IFERROR(W4/Income!$B$19,0) -> 0.17214428 | Z9: =IFERROR(Z4/Income!$B$19,0) -> 0.17214428 | AC9: =IFERROR(AC4/Income!$B$19,0) -> 0.17214428 | AF9: =IFERROR(AF4/Income!$B$19,0) -> 0.17214428 | AI9: =IFERROR(AI4/Income!$B$19,0) -> 0.17214428

Sheet Paycheck Planner
A1: Bill / Expense | B1: Monthly Amount | C1: Due Around | D1: Paycheck 1 (1st) | E1: Paycheck 2 (15th) | F1: Auto-pay?
A2: Rent/Mortgage | B2: 1450 | C2: 1st | D2: 1450 | E2: 0 | F2: Yes
A3: Utilities | B3: 155 | C3: 10th | D3: 155 | E3: 0 | F3: Yes
A4: Internet | B4: 60 | C4: 8th | D4: 60 | E4: 0 | F4: Yes
A5: Phone | B5: 70 | C5: 12th | D5: 70 | E5: 0 | F5: Yes
A6: Auto Insurance | B6: 105 | C6: 5th | D6: 105 | E6: 0 | F6: Yes
A7: Renters Insurance | B7: 22 | C7: 1st | D7: 22 | E7: 0 | F7: Yes
A8: Gym | B8: 40 | C8: 1st | D8: 40 | E8: 0 | F8: Yes
A9: Min Debt Payment | B9: 300 | C9: 15th | D9: 0 | E9: 300 | F9: Yes
A10: Emergency Fund | B10: 200 | C10: 15th | D10: 0 | E10: 200 | F10: Yes
A11: Retirement Extra | B11: 200 | C11: 15th | D11: 0 | E11: 200 | F11: Yes
A12: Vacation Fund | B12: 100 | C12: 15th | D12: 0 | E12: 100 | F12: No
A13: Sinking Funds | B13: 75 | C13: 15th | D13: 0 | E13: 75 | F13: No
... A15: Subscriptions | B15: 50 | C15: Various | D15: 50 | E15: 0 | F15: Yes
A17: Total Committed | D17: =SUM(D2:D15) -> 1952 | E17: =SUM(E2:E15) -> 1025
A18: Discretionary Remaining | D18: =Income!$B$15-D17 -> -46.208333 | E18: =Income!$B$15-E17 -> 880.79167

Sheet Analysis
A1: Annual Split
A2: Needs | B2: ='Monthly Tracker'!AL2 -> 33166.12
A3: Wants | B3: ='Monthly Tracker'!AL3 -> 7778.03
A4: Savings | B4: ='Monthly Tracker'!AL4 -> 9200
A7: Monthly % of Net Income
A8: Month | B8: Needs % | C8: Wants % | D8: Savings %
A9: Jan | B9: ='Monthly Tracker'!B7 -> 0.62855458 | C9: ='Monthly Tracker'!B8 -> 0.12778804 | D9: ='Monthly Tracker'!B9 -> 0.23150438
A10: Feb | B10: ='Monthly Tracker'!E7 -> 0.68104078 | C10: ='Monthly Tracker'!E8 -> 0.14322404 | D10: ='Monthly Tracker'!E9 -> 0.17214428
A11: Mar | B11: ='Monthly Tracker'!H7 -> 0.66321613 | C11: ='Monthly Tracker'!H8 -> 0.13748748 | D11: ='Monthly Tracker'!H9 -> 0.17214428
A12: Apr | B12: ='Monthly Tracker'!K7 -> 0.67051742 | C12: ='Monthly Tracker'!K8 -> 0.14150735 | D12: ='Monthly Tracker'!K9 -> 0.17214428
A13: May | B13: ='Monthly Tracker'!N7 -> 0.65262629 | C13: ='Monthly Tracker'!N8 -> 0.1542674 | D13: ='Monthly Tracker'!N9 -> 0.17214428
A14: Jun | B14: ='Monthly Tracker'!Q7 -> 0.67122974 | C14: ='Monthly Tracker'!Q8 -> 0.2598239 | D14: ='Monthly Tracker'!Q9 -> 0.17214428
A15: Jul | B15: ='Monthly Tracker'!T7 -> 0.62655771 | C15: ='Monthly Tracker'!T8 -> 0.12197788 | D15: ='Monthly Tracker'!T9 -> 0.23150438
A16: Aug | B16: ='Monthly Tracker'!W7 -> 0.66195057 | C16: ='Monthly Tracker'!W8 -> 0.13187439 | D16: ='Monthly Tracker'!W9 -> 0.17214428
A17: Sep | B17: ='Monthly Tracker'!Z7 -> 0.64296246 | C17: ='Monthly Tracker'!Z8 -> 0.14261145 | D17: ='Monthly Tracker'!Z9 -> 0.17214428
A18: Oct | B18: ='Monthly Tracker'!AC7 -> 0.67448505 | C18: ='Monthly Tracker'!AC8 -> 0.13346762 | D18: ='Monthly Tracker'!AC9 -> 0.17214428
A19: Nov | B19: ='Monthly Tracker'!AF7 -> 0.64825026 | C19: ='Monthly Tracker'!AF8 -> 0.12992738 | D19: ='Monthly Tracker'!AF9 -> 0.17214428
A20: Dec | B20: ='Monthly Tracker'!AI7 -> 0.65358555 | C20: ='Monthly Tracker'!AI8 -> 0.22286155 | D20: ='Monthly Tracker'!AI9 -> 0.17214428
A23: Monthly Dollar Split
A24: Month | B24: Needs | C24: Wants | D24: Savings
A25: Jan | B25: ='Monthly Tracker'!B2 -> 2647.21 | C25: ='Monthly Tracker'!B3 -> 538.19 | D25: ='Monthly Tracker'!B4 -> 975
A26: Feb | B26: ='Monthly Tracker'!E2 -> 2868.26 | C26: ='Monthly Tracker'!E3 -> 603.2 | D26: ='Monthly Tracker'!E4 -> 725
A27: Mar | B27: ='Monthly Tracker'!H2 -> 2793.19 | C27: ='Monthly Tracker'!H3 -> 579.04 | D27: ='Monthly Tracker'!H4 -> 725
A28: Apr | B28: ='Monthly Tracker'!K2 -> 2823.94 | C28: ='Monthly Tracker'!K3 -> 595.97 | D28: ='Monthly Tracker'!K4 -> 725
A29: May | B29: ='Monthly Tracker'!N2 -> 2748.59 | C29: ='Monthly Tracker'!N3 -> 649.71 | D29: ='Monthly Tracker'!N4 -> 725
A30: Jun | B30: ='Monthly Tracker'!Q2 -> 2826.94 | C30: ='Monthly Tracker'!Q3 -> 1094.27 | D30: ='Monthly Tracker'!Q4 -> 725
A31: Jul | B31: ='Monthly Tracker'!T2 -> 2638.8 | C31: ='Monthly Tracker'!T3 -> 513.72 | D31: ='Monthly Tracker'!T4 -> 975
A32: Aug | B32: ='Monthly Tracker'!W2 -> 2787.86 | C32: ='Monthly Tracker'!W3 -> 555.4 | D32: ='Monthly Tracker'!W4 -> 725
A33: Sep | B33: ='Monthly Tracker'!Z2 -> 2707.89 | C33: ='Monthly Tracker'!Z3 -> 600.62 | D33: ='Monthly Tracker'!Z4 -> 725
A34: Oct | B34: ='Monthly Tracker'!AC2 -> 2840.65 | C34: ='Monthly Tracker'!AC3 -> 562.11 | D34: ='Monthly Tracker'!AC4 -> 725
A35: Nov | B35: ='Monthly Tracker'!AF2 -> 2730.16 | C35: ='Monthly Tracker'!AF3 -> 547.2 | D35: ='Monthly Tracker'!AF4 -> 725
A36: Dec | B36: ='Monthly Tracker'!AI2 -> 2752.63 | C36: ='Monthly Tracker'!AI3 -> 938.6 | D36: ='Monthly Tracker'!AI4 -> 725

Sheet Readme
A1: 50/30/20 Budget Analyzer
A3: Sample data covers January through December 2025.
A4: All transactions and income figures are fictional.
A5: Start on the Income sheet to set salary and deductions.
A6: Payroll health insurance and payroll 401k already reduce net pay.
A7: Do not log those again unless you pay them outside payroll.
A8: Adjust category buckets on the Category Map sheet if needed.
A9: Log expenses in the Expense Log as they happen.
A10: The Monthly Tracker auto-classifies spending by bucket.
A11: Do not insert or delete rows inside data ranges.
A12: This is not financial advice. Talk to a professional about your situation.
