Workbook

Sheet Property & Assumptions
A1: Property Name / Address | B1: Lake House on Cedar Rd
A2: Property Type | B2: Entire Home
A3: Bedrooms | B3: 3
A4: Max Guests | B4: 8
A5: Purchase Price | B5: 340000
A6: Down Payment (%) | B6: 0.2
A7: Mortgage Rate | B7: 0.07
A8: Loan Term (years) | B8: 30
A9: Monthly Mortgage (P&I) | B9: =IF(B5=0,0,PMT(B7/12,B8*12,-(B5*(1-B6)))) -> 1809.6228
A11: Month | B11: Nightly Rate | C11: Occupancy
A12: January | B12: 135 | C12: 0.35
A13: February | B13: 135 | C13: 0.38
A14: March | B14: 155 | C14: 0.52
A15: April | B15: 165 | C15: 0.55
A16: May | B16: 195 | C16: 0.72
A17: June | B17: 245 | C17: 0.88
A18: July | B18: 265 | C18: 0.92
A19: August | B19: 255 | C19: 0.9
A20: September | B20: 195 | C20: 0.68
A21: October | B21: 175 | C21: 0.58
A22: November | B22: 145 | C22: 0.4
A23: December | B23: 165 | C23: 0.55
A26: Platform Fee (% of booking) | B26: 0.03
A27: Cleaning Fee Charged to Guest | B27: 150
A28: Cleaning Cost (your cost) | B28: 120
A29: Average Stay Length (nights) | B29: 3.5
A30: Property Management (%) | B30: 0.2
A31: Supplies per Turnover | B31: 25
A34: Property Tax (monthly) | B34: 350
A35: Insurance (STR) | B35: 210
A36: HOA | B36: 0
A37: Utilities | B37: 320
A38: Internet / Streaming | B38: 95
A39: Lawn / Pool / Maintenance | B39: 150
... A51: Est. LTR hours / year (for $/hr) | B51: 12

Sheet Monthly Revenue
A1: Month | B1: Days | C1: Nightly | D1: Occ % | E1: Occ Nights | F1: Gross Book | G1: Turnovers | H1: Clean Rev | I1: Tot Gross | J1: Platform | K1: Net Rev
A2: ='Property & Assumptions'!A12 -> January | B2: 31 | C2: ='Property & Assumptions'!B12 -> 135 | D2: ='Property & Assumptions'!C12 -> 0.35 | E2: =B2*D2 -> 10.85 | F2: =C2*E2 -> 1464.75 | G2: =ROUND(E2/'Property & Assumptions'!$B$29,0) -> 3 | H2: =G2*'Property & Assumptions'!$B$27 -> 450 | I2: =F2+H2 -> 1914.75 | J2: =-F2*'Property & Assumptions'!$B$26 -> -43.9425 | K2: =I2+J2 -> 1870.8075
A3: ='Property & Assumptions'!A13 -> February | B3: 28 | C3: ='Property & Assumptions'!B13 -> 135 | D3: ='Property & Assumptions'!C13 -> 0.38 | E3: =B3*D3 -> 10.64 | F3: =C3*E3 -> 1436.4 | G3: =ROUND(E3/'Property & Assumptions'!$B$29,0) -> 3 | H3: =G3*'Property & Assumptions'!$B$27 -> 450 | I3: =F3+H3 -> 1886.4 | J3: =-F3*'Property & Assumptions'!$B$26 -> -43.092 | K3: =I3+J3 -> 1843.308
A4: ='Property & Assumptions'!A14 -> March | B4: 31 | C4: ='Property & Assumptions'!B14 -> 155 | D4: ='Property & Assumptions'!C14 -> 0.52 | E4: =B4*D4 -> 16.12 | F4: =C4*E4 -> 2498.6 | G4: =ROUND(E4/'Property & Assumptions'!$B$29,0) -> 5 | H4: =G4*'Property & Assumptions'!$B$27 -> 750 | I4: =F4+H4 -> 3248.6 | J4: =-F4*'Property & Assumptions'!$B$26 -> -74.958 | K4: =I4+J4 -> 3173.642
A5: ='Property & Assumptions'!A15 -> April | B5: 30 | C5: ='Property & Assumptions'!B15 -> 165 | D5: ='Property & Assumptions'!C15 -> 0.55 | E5: =B5*D5 -> 16.5 | F5: =C5*E5 -> 2722.5 | G5: =ROUND(E5/'Property & Assumptions'!$B$29,0) -> 5 | H5: =G5*'Property & Assumptions'!$B$27 -> 750 | I5: =F5+H5 -> 3472.5 | J5: =-F5*'Property & Assumptions'!$B$26 -> -81.675 | K5: =I5+J5 -> 3390.825
A6: ='Property & Assumptions'!A16 -> May | B6: 31 | C6: ='Property & Assumptions'!B16 -> 195 | D6: ='Property & Assumptions'!C16 -> 0.72 | E6: =B6*D6 -> 22.32 | F6: =C6*E6 -> 4352.4 | G6: =ROUND(E6/'Property & Assumptions'!$B$29,0) -> 6 | H6: =G6*'Property & Assumptions'!$B$27 -> 900 | I6: =F6+H6 -> 5252.4 | J6: =-F6*'Property & Assumptions'!$B$26 -> -130.572 | K6: =I6+J6 -> 5121.828
A7: ='Property & Assumptions'!A17 -> June | B7: 30 | C7: ='Property & Assumptions'!B17 -> 245 | D7: ='Property & Assumptions'!C17 -> 0.88 | E7: =B7*D7 -> 26.4 | F7: =C7*E7 -> 6468 | G7: =ROUND(E7/'Property & Assumptions'!$B$29,0) -> 8 | H7: =G7*'Property & Assumptions'!$B$27 -> 1200 | I7: =F7+H7 -> 7668 | J7: =-F7*'Property & Assumptions'!$B$26 -> -194.04 | K7: =I7+J7 -> 7473.96
A8: ='Property & Assumptions'!A18 -> July | B8: 31 | C8: ='Property & Assumptions'!B18 -> 265 | D8: ='Property & Assumptions'!C18 -> 0.92 | E8: =B8*D8 -> 28.52 | F8: =C8*E8 -> 7557.8 | G8: =ROUND(E8/'Property & Assumptions'!$B$29,0) -> 8 | H8: =G8*'Property & Assumptions'!$B$27 -> 1200 | I8: =F8+H8 -> 8757.8 | J8: =-F8*'Property & Assumptions'!$B$26 -> -226.734 | K8: =I8+J8 -> 8531.066
A9: ='Property & Assumptions'!A19 -> August | B9: 31 | C9: ='Property & Assumptions'!B19 -> 255 | D9: ='Property & Assumptions'!C19 -> 0.9 | E9: =B9*D9 -> 27.9 | F9: =C9*E9 -> 7114.5 | G9: =ROUND(E9/'Property & Assumptions'!$B$29,0) -> 8 | H9: =G9*'Property & Assumptions'!$B$27 -> 1200 | I9: =F9+H9 -> 8314.5 | J9: =-F9*'Property & Assumptions'!$B$26 -> -213.435 | K9: =I9+J9 -> 8101.065
A10: ='Property & Assumptions'!A20 -> September | B10: 30 | C10: ='Property & Assumptions'!B20 -> 195 | D10: ='Property & Assumptions'!C20 -> 0.68 | E10: =B10*D10 -> 20.4 | F10: =C10*E10 -> 3978 | G10: =ROUND(E10/'Property & Assumptions'!$B$29,0) -> 6 | H10: =G10*'Property & Assumptions'!$B$27 -> 900 | I10: =F10+H10 -> 4878 | J10: =-F10*'Property & Assumptions'!$B$26 -> -119.34 | K10: =I10+J10 -> 4758.66
A11: ='Property & Assumptions'!A21 -> October | B11: 31 | C11: ='Property & Assumptions'!B21 -> 175 | D11: ='Property & Assumptions'!C21 -> 0.58 | E11: =B11*D11 -> 17.98 | F11: =C11*E11 -> 3146.5 | G11: =ROUND(E11/'Property & Assumptions'!$B$29,0) -> 5 | H11: =G11*'Property & Assumptions'!$B$27 -> 750 | I11: =F11+H11 -> 3896.5 | J11: =-F11*'Property & Assumptions'!$B$26 -> -94.395 | K11: =I11+J11 -> 3802.105
A12: ='Property & Assumptions'!A22 -> November | B12: 30 | C12: ='Property & Assumptions'!B22 -> 145 | D12: ='Property & Assumptions'!C22 -> 0.4 | E12: =B12*D12 -> 12 | F12: =C12*E12 -> 1740 | G12: =ROUND(E12/'Property & Assumptions'!$B$29,0) -> 3 | H12: =G12*'Property & Assumptions'!$B$27 -> 450 | I12: =F12+H12 -> 2190 | J12: =-F12*'Property & Assumptions'!$B$26 -> -52.2 | K12: =I12+J12 -> 2137.8
A13: ='Property & Assumptions'!A23 -> December | B13: 31 | C13: ='Property & Assumptions'!B23 -> 165 | D13: ='Property & Assumptions'!C23 -> 0.55 | E13: =B13*D13 -> 17.05 | F13: =C13*E13 -> 2813.25 | G13: =ROUND(E13/'Property & Assumptions'!$B$29,0) -> 5 | H13: =G13*'Property & Assumptions'!$B$27 -> 750 | I13: =F13+H13 -> 3563.25 | J13: =-F13*'Property & Assumptions'!$B$26 -> -84.3975 | K13: =I13+J13 -> 3478.8525
A14: Annual | E14: =SUM(E2:E13) -> 226.68 | F14: =SUM(F2:F13) -> 45292.7 | I14: =SUM(I2:I13) -> 55042.7 | J14: =SUM(J2:J13) -> -1358.781 | K14: =SUM(K2:K13) -> 53683.919
A15: Avg occ nights / mo | E15: =AVERAGE(E2:E13) -> 18.89
A16: Annual occupancy | E16: =SUM(E2:E13)/365 -> 0.6210411
A17: Blended nightly (gross book / occ nights) | E17: =IF(E14=0,0,F14/E14) -> 199.80898

Sheet Monthly Expenses
A1: Month | B1: Cleaning | C1: Supplies | D1: Mgmt | E1: Tax | F1: Ins | G1: HOA | H1: Util | I1: Internet | J1: Lawn | K1: Pest | L1: MaintR | M1: CapR | N1: Other | O1: Mortg | P1: Tot | Q1: NetCF
A2: ='Monthly Revenue'!A2 -> January | B2: ='Monthly Revenue'!G2*'Property & Assumptions'!$B$28 -> 360 | C2: ='Monthly Revenue'!G2*'Property & Assumptions'!$B$31 -> 75 | D2: ='Monthly Revenue'!K2*'Property & Assumptions'!$B$30 -> 374.1615 | E2: ='Property & Assumptions'!$B$34 -> 350 | F2: ='Property & Assumptions'!$B$35 -> 210 | G2: ='Property & Assumptions'!$B$36 -> 0 | H2: ='Property & Assumptions'!$B$37 -> 320 | I2: ='Property & Assumptions'!$B$38 -> 95 | J2: ='Property & Assumptions'!$B$39 -> 150 | K2: ='Property & Assumptions'!$B$40 -> 35 | L2: ='Monthly Revenue'!K2*'Property & Assumptions'!$B$41 -> 93.540375 | M2: ='Monthly Revenue'!K2*'Property & Assumptions'!$B$42 -> 56.124225 | N2: ='Property & Assumptions'!$B$43 -> 0 | O2: ='Property & Assumptions'!$B$9 -> 1809.6228 | P2: =SUM(B2:O2) -> 3928.4489 | Q2: ='Monthly Revenue'!K2-P2 -> -2057.6414
A3: ='Monthly Revenue'!A3 -> February | B3: ='Monthly Revenue'!G3*'Property & Assumptions'!$B$28 -> 360 | C3: ='Monthly Revenue'!G3*'Property & Assumptions'!$B$31 -> 75 | D3: ='Monthly Revenue'!K3*'Property & Assumptions'!$B$30 -> 368.6616 | E3: ='Property & Assumptions'!$B$34 -> 350 | F3: ='Property & Assumptions'!$B$35 -> 210 | G3: ='Property & Assumptions'!$B$36 -> 0 | H3: ='Property & Assumptions'!$B$37 -> 320 | I3: ='Property & Assumptions'!$B$38 -> 95 | J3: ='Property & Assumptions'!$B$39 -> 150 | K3: ='Property & Assumptions'!$B$40 -> 35 | L3: ='Monthly Revenue'!K3*'Property & Assumptions'!$B$41 -> 92.1654 | M3: ='Monthly Revenue'!K3*'Property & Assumptions'!$B$42 -> 55.29924 | N3: ='Property & Assumptions'!$B$43 -> 0 | O3: ='Property & Assumptions'!$B$9 -> 1809.6228 | P3: =SUM(B3:O3) -> 3920.749 | Q3: ='Monthly Revenue'!K3-P3 -> -2077.441
A4: ='Monthly Revenue'!A4 -> March | B4: ='Monthly Revenue'!G4*'Property & Assumptions'!$B$28 -> 600 | C4: ='Monthly Revenue'!G4*'Property & Assumptions'!$B$31 -> 125 | D4: ='Monthly Revenue'!K4*'Property & Assumptions'!$B$30 -> 634.7284 | E4: ='Property & Assumptions'!$B$34 -> 350 | F4: ='Property & Assumptions'!$B$35 -> 210 | G4: ='Property & Assumptions'!$B$36 -> 0 | H4: ='Property & Assumptions'!$B$37 -> 320 | I4: ='Property & Assumptions'!$B$38 -> 95 | J4: ='Property & Assumptions'!$B$39 -> 150 | K4: ='Property & Assumptions'!$B$40 -> 35 | L4: ='Monthly Revenue'!K4*'Property & Assumptions'!$B$41 -> 158.6821 | M4: ='Monthly Revenue'!K4*'Property & Assumptions'!$B$42 -> 95.20926 | N4: ='Property & Assumptions'!$B$43 -> 0 | O4: ='Property & Assumptions'!$B$9 -> 1809.6228 | P4: =SUM(B4:O4) -> 4583.2425 | Q4: ='Monthly Revenue'!K4-P4 -> -1409.6005
A5: ='Monthly Revenue'!A5 -> April | B5: ='Monthly Revenue'!G5*'Property & Assumptions'!$B$28 -> 600 | C5: ='Monthly Revenue'!G5*'Property & Assumptions'!$B$31 -> 125 | D5: ='Monthly Revenue'!K5*'Property & Assumptions'!$B$30 -> 678.165 | E5: ='Property & Assumptions'!$B$34 -> 350 | F5: ='Property & Assumptions'!$B$35 -> 210 | G5: ='Property & Assumptions'!$B$36 -> 0 | H5: ='Property & Assumptions'!$B$37 -> 320 | I5: ='Property & Assumptions'!$B$38 -> 95 | J5: ='Property & Assumptions'!$B$39 -> 150 | K5: ='Property & Assumptions'!$B$40 -> 35 | L5: ='Monthly Revenue'!K5*'Property & Assumptions'!$B$41 -> 169.54125 | M5: ='Monthly Revenue'!K5*'Property & Assumptions'!$B$42 -> 101.72475 | N5: ='Property & Assumptions'!$B$43 -> 0 | O5: ='Property & Assumptions'!$B$9 -> 1809.6228 | P5: =SUM(B5:O5) -> 4644.0538 | Q5: ='Monthly Revenue'!K5-P5 -> -1253.2288
A6: ='Monthly Revenue'!A6 -> May | B6: ='Monthly Revenue'!G6*'Property & Assumptions'!$B$28 -> 720 | C6: ='Monthly Revenue'!G6*'Property & Assumptions'!$B$31 -> 150 | D6: ='Monthly Revenue'!K6*'Property & Assumptions'!$B$30 -> 1024.3656 | E6: ='Property & Assumptions'!$B$34 -> 350 | F6: ='Property & Assumptions'!$B$35 -> 210 | G6: ='Property & Assumptions'!$B$36 -> 0 | H6: ='Property & Assumptions'!$B$37 -> 320 | I6: ='Property & Assumptions'!$B$38 -> 95 | J6: ='Property & Assumptions'!$B$39 -> 150 | K6: ='Property & Assumptions'!$B$40 -> 35 | L6: ='Monthly Revenue'!K6*'Property & Assumptions'!$B$41 -> 256.0914 | M6: ='Monthly Revenue'!K6*'Property & Assumptions'!$B$42 -> 153.65484 | N6: ='Property & Assumptions'!$B$43 -> 0 | O6: ='Property & Assumptions'!$B$9 -> 1809.6228 | P6: =SUM(B6:O6) -> 5273.7346 | Q6: ='Monthly Revenue'!K6-P6 -> -151.90663
A7: ='Monthly Revenue'!A7 -> June | B7: ='Monthly Revenue'!G7*'Property & Assumptions'!$B$28 -> 960 | C7: ='Monthly Revenue'!G7*'Property & Assumptions'!$B$31 -> 200 | D7: ='Monthly Revenue'!K7*'Property & Assumptions'!$B$30 -> 1494.792 | E7: ='Property & Assumptions'!$B$34 -> 350 | F7: ='Property & Assumptions'!$B$35 -> 210 | G7: ='Property & Assumptions'!$B$36 -> 0 | H7: ='Property & Assumptions'!$B$37 -> 320 | I7: ='Property & Assumptions'!$B$38 -> 95 | J7: ='Property & Assumptions'!$B$39 -> 150 | K7: ='Property & Assumptions'!$B$40 -> 35 | L7: ='Monthly Revenue'!K7*'Property & Assumptions'!$B$41 -> 373.698 | M7: ='Monthly Revenue'!K7*'Property & Assumptions'!$B$42 -> 224.2188 | N7: ='Property & Assumptions'!$B$43 -> 0 | O7: ='Property & Assumptions'!$B$9 -> 1809.6228 | P7: =SUM(B7:O7) -> 6222.3316 | Q7: ='Monthly Revenue'!K7-P7 -> 1251.6284
A8: ='Monthly Revenue'!A8 -> July | B8: ='Monthly Revenue'!G8*'Property & Assumptions'!$B$28 -> 960 | C8: ='Monthly Revenue'!G8*'Property & Assumptions'!$B$31 -> 200 | D8: ='Monthly Revenue'!K8*'Property & Assumptions'!$B$30 -> 1706.2132 | E8: ='Property & Assumptions'!$B$34 -> 350 | F8: ='Property & Assumptions'!$B$35 -> 210 | G8: ='Property & Assumptions'!$B$36 -> 0 | H8: ='Property & Assumptions'!$B$37 -> 320 | I8: ='Property & Assumptions'!$B$38 -> 95 | J8: ='Property & Assumptions'!$B$39 -> 150 | K8: ='Property & Assumptions'!$B$40 -> 35 | L8: ='Monthly Revenue'!K8*'Property & Assumptions'!$B$41 -> 426.5533 | M8: ='Monthly Revenue'!K8*'Property & Assumptions'!$B$42 -> 255.93198 | N8: ='Property & Assumptions'!$B$43 -> 0 | O8: ='Property & Assumptions'!$B$9 -> 1809.6228 | P8: =SUM(B8:O8) -> 6518.3213 | Q8: ='Monthly Revenue'!K8-P8 -> 2012.7447
A9: ='Monthly Revenue'!A9 -> August | B9: ='Monthly Revenue'!G9*'Property & Assumptions'!$B$28 -> 960 | C9: ='Monthly Revenue'!G9*'Property & Assumptions'!$B$31 -> 200 | D9: ='Monthly Revenue'!K9*'Property & Assumptions'!$B$30 -> 1620.213 | E9: ='Property & Assumptions'!$B$34 -> 350 | F9: ='Property & Assumptions'!$B$35 -> 210 | G9: ='Property & Assumptions'!$B$36 -> 0 | H9: ='Property & Assumptions'!$B$37 -> 320 | I9: ='Property & Assumptions'!$B$38 -> 95 | J9: ='Property & Assumptions'!$B$39 -> 150 | K9: ='Property & Assumptions'!$B$40 -> 35 | L9: ='Monthly Revenue'!K9*'Property & Assumptions'!$B$41 -> 405.05325 | M9: ='Monthly Revenue'!K9*'Property & Assumptions'!$B$42 -> 243.03195 | N9: ='Property & Assumptions'!$B$43 -> 0 | O9: ='Property & Assumptions'!$B$9 -> 1809.6228 | P9: =SUM(B9:O9) -> 6397.921 | Q9: ='Monthly Revenue'!K9-P9 -> 1703.144
A10: ='Monthly Revenue'!A10 -> September | B10: ='Monthly Revenue'!G10*'Property & Assumptions'!$B$28 -> 720 | C10: ='Monthly Revenue'!G10*'Property & Assumptions'!$B$31 -> 150 | D10: ='Monthly Revenue'!K10*'Property & Assumptions'!$B$30 -> 951.732 | E10: ='Property & Assumptions'!$B$34 -> 350 | F10: ='Property & Assumptions'!$B$35 -> 210 | G10: ='Property & Assumptions'!$B$36 -> 0 | H10: ='Property & Assumptions'!$B$37 -> 320 | I10: ='Property & Assumptions'!$B$38 -> 95 | J10: ='Property & Assumptions'!$B$39 -> 150 | K10: ='Property & Assumptions'!$B$40 -> 35 | L10: ='Monthly Revenue'!K10*'Property & Assumptions'!$B$41 -> 237.933 | M10: ='Monthly Revenue'!K10*'Property & Assumptions'!$B$42 -> 142.7598 | N10: ='Property & Assumptions'!$B$43 -> 0 | O10: ='Property & Assumptions'!$B$9 -> 1809.6228 | P10: =SUM(B10:O10) -> 5172.0476 | Q10: ='Monthly Revenue'!K10-P10 -> -413.38759
A11: ='Monthly Revenue'!A11 -> October | B11: ='Monthly Revenue'!G11*'Property & Assumptions'!$B$28 -> 600 | C11: ='Monthly Revenue'!G11*'Property & Assumptions'!$B$31 -> 125 | D11: ='Monthly Revenue'!K11*'Property & Assumptions'!$B$30 -> 760.421 | E11: ='Property & Assumptions'!$B$34 -> 350 | F11: ='Property & Assumptions'!$B$35 -> 210 | G11: ='Property & Assumptions'!$B$36 -> 0 | H11: ='Property & Assumptions'!$B$37 -> 320 | I11: ='Property & Assumptions'!$B$38 -> 95 | J11: ='Property & Assumptions'!$B$39 -> 150 | K11: ='Property & Assumptions'!$B$40 -> 35 | L11: ='Monthly Revenue'!K11*'Property & Assumptions'!$B$41 -> 190.10525 | M11: ='Monthly Revenue'!K11*'Property & Assumptions'!$B$42 -> 114.06315 | N11: ='Property & Assumptions'!$B$43 -> 0 | O11: ='Property & Assumptions'!$B$9 -> 1809.6228 | P11: =SUM(B11:O11) -> 4759.2122 | Q11: ='Monthly Revenue'!K11-P11 -> -957.10719
A12: ='Monthly Revenue'!A12 -> November | B12: ='Monthly Revenue'!G12*'Property & Assumptions'!$B$28 -> 360 | C12: ='Monthly Revenue'!G12*'Property & Assumptions'!$B$31 -> 75 | D12: ='Monthly Revenue'!K12*'Property & Assumptions'!$B$30 -> 427.56 | E12: ='Property & Assumptions'!$B$34 -> 350 | F12: ='Property & Assumptions'!$B$35 -> 210 | G12: ='Property & Assumptions'!$B$36 -> 0 | H12: ='Property & Assumptions'!$B$37 -> 320 | I12: ='Property & Assumptions'!$B$38 -> 95 | J12: ='Property & Assumptions'!$B$39 -> 150 | K12: ='Property & Assumptions'!$B$40 -> 35 | L12: ='Monthly Revenue'!K12*'Property & Assumptions'!$B$41 -> 106.89 | M12: ='Monthly Revenue'!K12*'Property & Assumptions'!$B$42 -> 64.134 | N12: ='Property & Assumptions'!$B$43 -> 0 | O12: ='Property & Assumptions'!$B$9 -> 1809.6228 | P12: =SUM(B12:O12) -> 4003.2068 | Q12: ='Monthly Revenue'!K12-P12 -> -1865.4068
A13: ='Monthly Revenue'!A13 -> December | B13: ='Monthly Revenue'!G13*'Property & Assumptions'!$B$28 -> 600 | C13: ='Monthly Revenue'!G13*'Property & Assumptions'!$B$31 -> 125 | D13: ='Monthly Revenue'!K13*'Property & Assumptions'!$B$30 -> 695.7705 | E13: ='Property & Assumptions'!$B$34 -> 350 | F13: ='Property & Assumptions'!$B$35 -> 210 | G13: ='Property & Assumptions'!$B$36 -> 0 | H13: ='Property & Assumptions'!$B$37 -> 320 | I13: ='Property & Assumptions'!$B$38 -> 95 | J13: ='Property & Assumptions'!$B$39 -> 150 | K13: ='Property & Assumptions'!$B$40 -> 35 | L13: ='Monthly Revenue'!K13*'Property & Assumptions'!$B$41 -> 173.94263 | M13: ='Monthly Revenue'!K13*'Property & Assumptions'!$B$42 -> 104.36557 | N13: ='Property & Assumptions'!$B$43 -> 0 | O13: ='Property & Assumptions'!$B$9 -> 1809.6228 | P13: =SUM(B13:O13) -> 4668.7015 | Q13: ='Monthly Revenue'!K13-P13 -> -1189.849
A14: Annual | B14: =SUM(B2:B13) -> 7800 | C14: =SUM(C2:C13) -> 1625 | D14: =SUM(D2:D13) -> 10736.784 | E14: =SUM(E2:E13) -> 4200 | F14: =SUM(F2:F13) -> 2520 | G14: =SUM(G2:G13) -> 0 | H14: =SUM(H2:H13) -> 3840 | I14: =SUM(I2:I13) -> 1140 | ... Q14: =SUM(Q2:Q13) -> -6408.0518

Sheet Annual Summary & Comparison
A1: STR (annual)
A3: Gross revenue (total gross) | B3: ='Monthly Revenue'!$I$14 -> 55042.7
A4: Platform fees (abs) | B4: =-'Monthly Revenue'!$J$14 -> 1358.781
A5: Net revenue | B5: ='Monthly Revenue'!$K$14 -> 53683.919
A6: Operating expenses (ex-mortgage) | B6: ='Monthly Expenses'!$P$14-'Property & Assumptions'!$B$9*12 -> 38376.497
A7: NOI (net rev - opex ex loan) | B7: =B5-B6 -> 15307.422
A8: Mortgage (annual P&I) | B8: ='Property & Assumptions'!$B$9*12 -> 21715.473
A9: Cash flow after debt | B9: =B7-B8 -> -6408.0518
A10: Cash-on-cash return | B10: =IF('Property & Assumptions'!$B$5*'Property & Assumptions'!$B$6=0,0,B9/('Property & Assumptions'!$B$5*'Property & Assumptions'!$B$6)) -> -0.094236055
A11: Cap rate (NOI / price) | B11: =IF('Property & Assumptions'!$B$5=0,0,B7/'Property & Assumptions'!$B$5) -> 0.045021828
A12: RevPAN (gross / 365) | B12: =IF(B3=0,0,B3/365) -> 150.80192
A13: Revenue per occupied night (gross book) | B13: =IF('Monthly Revenue'!$E$14=0,0,'Monthly Revenue'!$F$14/'Monthly Revenue'!$E$14) -> 199.80898
A14: Avg monthly cash flow | B14: =B9/12 -> -534.00431
A15: Expense ratio (total exp / gross) | B15: =IF(B3=0,0,'Monthly Expenses'!$P$14/B3) -> 1.0917337
A17: LTR (annual)
A18: Gross rent | B18: ='Property & Assumptions'!$B$46*12 -> 22200
A19: Vacancy loss | B19: =B18*'Property & Assumptions'!$B$47 -> 1110
A20: Effective gross income | B20: =B18-B19 -> 21090
A21: Management fee | B21: =B20*'Property & Assumptions'!$B$48 -> 1687.2
A22: Property tax | B22: ='Property & Assumptions'!$B$34*12 -> 4200
A23: Insurance (LTR est.) | B23: ='Property & Assumptions'!$B$35*12*0.7 -> 1764
A24: Maintenance (5% of gross rent) | B24: =B18*0.05 -> 1110
A25: NOI | B25: =B20-B21-B22-B23-B24 -> 12328.8
A26: Mortgage (annual P&I) | B26: ='Property & Assumptions'!$B$9*12 -> 21715.473
A27: Cash flow after debt | B27: =B25-B26 -> -9386.6734
A28: Cash-on-cash return | B28: =IF('Property & Assumptions'!$B$5*'Property & Assumptions'!$B$6=0,0,B27/('Property & Assumptions'!$B$5*'Property & Assumptions'!$B$6)) -> -0.13803932
A29: Compare (STR vs LTR)
A30: Annual cash flow after debt | B30: =B9 -> -6408.0518 | C30: =B27 -> -9386.6734 | D30: =B9-B27 -> 2978.6217
A31: NOI | B31: =B7 -> 15307.422 | C31: =B25 -> 12328.8 | D31: =B7-B25 -> 2978.6217
A32: Cash-on-cash | B32: =B10 -> -0.094236055 | C32: =B28 -> -0.13803932 | D32: =B10-B28 -> 0.04380326
A33: Avg monthly cash flow | B33: =B14 -> -534.00431 | C33: =B27/12 -> -782.22279 | D33: =B14-C33 -> 248.21847
A35: Break-even vs LTR cash flow
A36: LTR annual cash flow (target) | B36: =B27 -> -9386.6734
A37: STR fixed costs (annual) | B37: ='Monthly Expenses'!$E$14+'Monthly Expenses'!$F$14+'Monthly Expenses'!$G$14+'Monthly Expenses'!$H$14+'Monthly Expenses'!$I$14+'Monthly Expenses'!$J$14+'Monthly Expenses'!$K$14+'Monthly Expenses'!$N$14+'Monthly Expenses'!$O$14 -> 35635.473
A38: STR variable costs (annual) | B38: ='Monthly Expenses'!$B$14+'Monthly Expenses'!$C$14+'Monthly Expenses'!$D$14+'Monthly Expenses'!$L$14+'Monthly Expenses'!$M$14 -> 24456.497
A39: Variable cost per occupied night | B39: =IF('Monthly Revenue'!$E$14=0,0,B38/'Monthly Revenue'!$E$14) -> 107.88997
A40: Blended nightly (gross book / occ nights) | B40: ='Monthly Revenue'!$E$17 -> 199.80898
A41: Break-even occupied nights (approx.) | B41: =IF(B40-B39<=0,"n/a",(B36+B37)/(B40-B39)) -> 285.56441
A42: Break-even occupancy (approx.) | B42: =IF(B41="n/a","n/a",B41/365) -> 0.78236825
A43: Current annual occupancy | B43: ='Monthly Revenue'!$E$16 -> 0.6210411

Sheet Scenario Planner
A1: Scenario Planner
B2: Conservative (-15% rate, -10 pts occ) | N2: Base (actuals) | O2: Optimistic (+10% rate, +5 pts occ)
B4: Days | C4: Rate | D4: Occ | E4: OccN | F4: GrossBk | G4: Turns | H4: Clean$ | I4: TotG | J4: Plat | K4: NetRev | L4: Expense | M4: NetCF | O4: Days | P4: Rate | Q4: Occ | R4: OccN | S4: GrossBk | T4: Turns | U4: Clean$ | V4: TotG | W4: Plat | X4: NetRev | Y4: Expense | Z4: NetCF
B5: 31 | C5: ='Property & Assumptions'!$B$12*0.85 -> 114.75 | D5: =MAX(0,'Property & Assumptions'!$C$12-0.1) -> 0.25 | E5: =B5*D5 -> 7.75 | F5: =C5*E5 -> 889.3125 | G5: =ROUND(E5/'Property & Assumptions'!$B$29,0) -> 2 | H5: =G5*'Property & Assumptions'!$B$27 -> 300 | I5: =F5+H5 -> 1189.3125 | J5: =-F5*'Property & Assumptions'!$B$26 -> -26.679375 | K5: =I5+J5 -> 1162.6331 | L5: =G5*'Property & Assumptions'!$B$28+G5*'Property & Assumptions'!$B$31+K5*'Property & Assumptions'!$B$30+K5*'Property & Assumptions'!$B$41+K5*'Property & Assumptions'!$B$42+SUM('Monthly Expenses'!E2:K2)+'Monthly Expenses'!N2+'Monthly Expenses'!O2 -> 3585.1601 | M5: =K5-L5 -> -2422.5269 | O5: 31 | P5: ='Property & Assumptions'!$B$12*1.1 -> 148.5 | Q5: =MIN(1,'Property & Assumptions'!$C$12+0.05) -> 0.4 | R5: =O5*Q5 -> 12.4 | S5: =P5*R5 -> 1841.4 | T5: =ROUND(R5/'Property & Assumptions'!$B$29,0) -> 4 | U5: =T5*'Property & Assumptions'!$B$27 -> 600 | V5: =S5+U5 -> 2441.4 | W5: =-S5*'Property & Assumptions'!$B$26 -> -55.242 | X5: =V5+W5 -> 2386.158 | Y5: =T5*'Property & Assumptions'!$B$28+T5*'Property & Assumptions'!$B$31+X5*'Property & Assumptions'!$B$30+X5*'Property & Assumptions'!$B$41+X5*'Property & Assumptions'!$B$42+SUM('Monthly Expenses'!E2:K2)+'Monthly Expenses'!N2+'Monthly Expenses'!O2 -> 4217.747 | Z5: =X5-Y5 -> -1831.589
B6: 28 | C6: ='Property & Assumptions'!$B$13*0.85 -> 114.75 | D6: =MAX(0,'Property & Assumptions'!$C$13-0.1) -> 0.28 | E6: =B6*D6 -> 7.84 | F6: =C6*E6 -> 899.64 | G6: =ROUND(E6/'Property & Assumptions'!$B$29,0) -> 2 | H6: =G6*'Property & Assumptions'!$B$27 -> 300 | I6: =F6+H6 -> 1199.64 | J6: =-F6*'Property & Assumptions'!$B$26 -> -26.9892 | K6: =I6+J6 -> 1172.6508 | L6: =G6*'Property & Assumptions'!$B$28+G6*'Property & Assumptions'!$B$31+K6*'Property & Assumptions'!$B$30+K6*'Property & Assumptions'!$B$41+K6*'Property & Assumptions'!$B$42+SUM('Monthly Expenses'!E3:K3)+'Monthly Expenses'!N3+'Monthly Expenses'!O3 -> 3587.965 | M6: =K6-L6 -> -2415.3142 | O6: 28 | P6: ='Property & Assumptions'!$B$13*1.1 -> 148.5 | Q6: =MIN(1,'Property & Assumptions'!$C$13+0.05) -> 0.43 | R6: =O6*Q6 -> 12.04 | S6: =P6*R6 -> 1787.94 | T6: =ROUND(R6/'Property & Assumptions'!$B$29,0) -> 3 | U6: =T6*'Property & Assumptions'!$B$27 -> 450 | V6: =S6+U6 -> 2237.94 | W6: =-S6*'Property & Assumptions'!$B$26 -> -53.6382 | X6: =V6+W6 -> 2184.3018 | Y6: =T6*'Property & Assumptions'!$B$28+T6*'Property & Assumptions'!$B$31+X6*'Property & Assumptions'!$B$30+X6*'Property & Assumptions'!$B$41+X6*'Property & Assumptions'!$B$42+SUM('Monthly Expenses'!E3:K3)+'Monthly Expenses'!N3+'Monthly Expenses'!O3 -> 4016.2273 | Z6: =X6-Y6 -> -1831.9255
B7: 31 | C7: ='Property & Assumptions'!$B$14*0.85 -> 131.75 | D7: =MAX(0,'Property & Assumptions'!$C$14-0.1) -> 0.42 | E7: =B7*D7 -> 13.02 | F7: =C7*E7 -> 1715.385 | G7: =ROUND(E7/'Property & Assumptions'!$B$29,0) -> 4 | H7: =G7*'Property & Assumptions'!$B$27 -> 600 | I7: =F7+H7 -> 2315.385 | J7: =-F7*'Property & Assumptions'!$B$26 -> -51.46155 | K7: =I7+J7 -> 2263.9235 | L7: =G7*'Property & Assumptions'!$B$28+G7*'Property & Assumptions'!$B$31+K7*'Property & Assumptions'!$B$30+K7*'Property & Assumptions'!$B$41+K7*'Property & Assumptions'!$B$42+SUM('Monthly Expenses'!E4:K4)+'Monthly Expenses'!N4+'Monthly Expenses'!O4 -> 4183.5214 | M7: =K7-L7 -> -1919.5979 | O7: 31 | P7: ='Property & Assumptions'!$B$14*1.1 -> 170.5 | Q7: =MIN(1,'Property & Assumptions'!$C$14+0.05) -> 0.57 | R7: =O7*Q7 -> 17.67 | S7: =P7*R7 -> 3012.735 | T7: =ROUND(R7/'Property & Assumptions'!$B$29,0) -> 5 | U7: =T7*'Property & Assumptions'!$B$27 -> 750 | V7: =S7+U7 -> 3762.735 | W7: =-S7*'Property & Assumptions'!$B$26 -> -90.38205 | X7: =V7+W7 -> 3672.3529 | Y7: =T7*'Property & Assumptions'!$B$28+T7*'Property & Assumptions'!$B$31+X7*'Property & Assumptions'!$B$30+X7*'Property & Assumptions'!$B$41+X7*'Property & Assumptions'!$B$42+SUM('Monthly Expenses'!E4:K4)+'Monthly Expenses'!N4+'Monthly Expenses'!O4 -> 4722.8816 | Z7: =X7-Y7 -> -1050.5287
B8: 30 | C8: ='Property & Assumptions'!$B$15*0.85 -> 140.25 | D8: =MAX(0,'Property & Assumptions'!$C$15-0.1) -> 0.45 | E8: =B8*D8 -> 13.5 | F8: =C8*E8 -> 1893.375 | G8: =ROUND(E8/'Property & Assumptions'!$B$29,0) -> 4 | H8: =G8*'Property & Assumptions'!$B$27 -> 600 | I8: =F8+H8 -> 2493.375 | J8: =-F8*'Property & Assumptions'!$B$26 -> -56.80125 | K8: =I8+J8 -> 2436.5738 | L8: =G8*'Property & Assumptions'!$B$28+G8*'Property & Assumptions'!$B$31+K8*'Property & Assumptions'!$B$30+K8*'Property & Assumptions'!$B$41+K8*'Property & Assumptions'!$B$42+SUM('Monthly Expenses'!E5:K5)+'Monthly Expenses'!N5+'Monthly Expenses'!O5 -> 4231.8634 | M8: =K8-L8 -> -1795.2897 | O8: 30 | P8: ='Property & Assumptions'!$B$15*1.1 -> 181.5 | Q8: =MIN(1,'Property & Assumptions'!$C$15+0.05) -> 0.6 | R8: =O8*Q8 -> 18 | S8: =P8*R8 -> 3267 | T8: =ROUND(R8/'Property & Assumptions'!$B$29,0) -> 5 | U8: =T8*'Property & Assumptions'!$B$27 -> 750 | V8: =S8+U8 -> 4017 | W8: =-S8*'Property & Assumptions'!$B$26 -> -98.01 | X8: =V8+W8 -> 3918.99 | Y8: =T8*'Property & Assumptions'!$B$28+T8*'Property & Assumptions'!$B$31+X8*'Property & Assumptions'!$B$30+X8*'Property & Assumptions'!$B$41+X8*'Property & Assumptions'!$B$42+SUM('Monthly Expenses'!E5:K5)+'Monthly Expenses'!N5+'Monthly Expenses'!O5 -> 4791.94 | Z8: =X8-Y8 -> -872.94999
B9: 31 | C9: ='Property & Assumptions'!$B$16*0.85 -> 165.75 | D9: =MAX(0,'Property & Assumptions'!$C$16-0.1) -> 0.62 | E9: =B9*D9 -> 19.22 | F9: =C9*E9 -> 3185.715 | G9: =ROUND(E9/'Property & Assumptions'!$B$29,0) -> 5 | H9: =G9*'Property & Assumptions'!$B$27 -> 750 | I9: =F9+H9 -> 3935.715 | J9: =-F9*'Property & Assumptions'!$B$26 -> -95.57145 | K9: =I9+J9 -> 3840.1435 | L9: =G9*'Property & Assumptions'!$B$28+G9*'Property & Assumptions'!$B$31+K9*'Property & Assumptions'!$B$30+K9*'Property & Assumptions'!$B$41+K9*'Property & Assumptions'!$B$42+SUM('Monthly Expenses'!E6:K6)+'Monthly Expenses'!N6+'Monthly Expenses'!O6 -> 4769.863 | M9: =K9-L9 -> -929.71943 | O9: 31 | P9: ='Property & Assumptions'!$B$16*1.1 -> 214.5 | Q9: =MIN(1,'Property & Assumptions'!$C$16+0.05) -> 0.77 | R9: =O9*Q9 -> 23.87 | S9: =P9*R9 -> 5120.115 | T9: =ROUND(R9/'Property & Assumptions'!$B$29,0) -> 7 | U9: =T9*'Property & Assumptions'!$B$27 -> 1050 | V9: =S9+U9 -> 6170.115 | W9: =-S9*'Property & Assumptions'!$B$26 -> -153.60345 | X9: =V9+W9 -> 6016.5116 | Y9: =T9*'Property & Assumptions'!$B$28+T9*'Property & Assumptions'!$B$31+X9*'Property & Assumptions'!$B$30+X9*'Property & Assumptions'!$B$41+X9*'Property & Assumptions'!$B$42+SUM('Monthly Expenses'!E6:K6)+'Monthly Expenses'!N6+'Monthly Expenses'!O6 -> 5669.246 | Z9: =X9-Y9 -> 347.26553
B10: 30 | C10: ='Property & Assumptions'!$B$17*0.85 -> 208.25 | D10: =MAX(0,'Property & Assumptions'!$C$17-0.1) -> 0.78 | E10: =B10*D10 -> 23.4 | F10: =C10*E10 -> 4873.05 | G10: =ROUND(E10/'Property & Assumptions'!$B$29,0) -> 7 | H10: =G10*'Property & Assumptions'!$B$27 -> 1050 | I10: =F10+H10 -> 5923.05 | J10: =-F10*'Property & Assumptions'!$B$26 -> -146.1915 | K10: =I10+J10 -> 5776.8585 | L10: =G10*'Property & Assumptions'!$B$28+G10*'Property & Assumptions'!$B$31+K10*'Property & Assumptions'!$B$30+K10*'Property & Assumptions'!$B$41+K10*'Property & Assumptions'!$B$42+SUM('Monthly Expenses'!E7:K7)+'Monthly Expenses'!N7+'Monthly Expenses'!O7 -> 5602.1432 | M10: =K10-L10 -> 174.71533 | O10: 30 | P10: ='Property & Assumptions'!$B$17*1.1 -> 269.5 | Q10: =MIN(1,'Property & Assumptions'!$C$17+0.05) -> 0.93 | R10: =O10*Q10 -> 27.9 | S10: =P10*R10 -> 7519.05 | T10: =ROUND(R10/'Property & Assumptions'!$B$29,0) -> 8 | U10: =T10*'Property & Assumptions'!$B$27 -> 1200 | V10: =S10+U10 -> 8719.05 | W10: =-S10*'Property & Assumptions'!$B$26 -> -225.5715 | X10: =V10+W10 -> 8493.4785 | Y10: =T10*'Property & Assumptions'!$B$28+T10*'Property & Assumptions'!$B$31+X10*'Property & Assumptions'!$B$30+X10*'Property & Assumptions'!$B$41+X10*'Property & Assumptions'!$B$42+SUM('Monthly Expenses'!E7:K7)+'Monthly Expenses'!N7+'Monthly Expenses'!O7 -> 6507.7968 | Z10: =X10-Y10 -> 1985.6817
B11: 31 | C11: ='Property & Assumptions'!$B$18*0.85 -> 225.25 | D11: =MAX(0,'Property & Assumptions'!$C$18-0.1) -> 0.82 | E11: =B11*D11 -> 25.42 | F11: =C11*E11 -> 5725.855 | G11: =ROUND(E11/'Property & Assumptions'!$B$29,0) -> 7 | H11: =G11*'Property & Assumptions'!$B$27 -> 1050 | I11: =F11+H11 -> 6775.855 | J11: =-F11*'Property & Assumptions'!$B$26 -> -171.77565 | K11: =I11+J11 -> 6604.0794 | L11: =G11*'Property & Assumptions'!$B$28+G11*'Property & Assumptions'!$B$31+K11*'Property & Assumptions'!$B$30+K11*'Property & Assumptions'!$B$41+K11*'Property & Assumptions'!$B$42+SUM('Monthly Expenses'!E8:K8)+'Monthly Expenses'!N8+'Monthly Expenses'!O8 -> 5833.765 | M11: =K11-L11 -> 770.31435 | O11: 31 | P11: ='Property & Assumptions'!$B$18*1.1 -> 291.5 | Q11: =MIN(1,'Property & Assumptions'!$C$18+0.05) -> 0.97 | R11: =O11*Q11 -> 30.07 | S11: =P11*R11 -> 8765.405 | T11: =ROUND(R11/'Property & Assumptions'!$B$29,0) -> 9 | U11: =T11*'Property & Assumptions'!$B$27 -> 1350 | V11: =S11+U11 -> 10115.405 | W11: =-S11*'Property & Assumptions'!$B$26 -> -262.96215 | X11: =V11+W11 -> 9852.4429 | Y11: =T11*'Property & Assumptions'!$B$28+T11*'Property & Assumptions'!$B$31+X11*'Property & Assumptions'!$B$30+X11*'Property & Assumptions'!$B$41+X11*'Property & Assumptions'!$B$42+SUM('Monthly Expenses'!E8:K8)+'Monthly Expenses'!N8+'Monthly Expenses'!O8 -> 7033.3068 | Z11: =X11-Y11 -> 2819.1361
B12: 31 | C12: ='Property & Assumptions'!$B$19*0.85 -> 216.75 | D12: =MAX(0,'Property & Assumptions'!$C$19-0.1) -> 0.8 | E12: =B12*D12 -> 24.8 | F12: =C12*E12 -> 5375.4 | G12: =ROUND(E12/'Property & Assumptions'!$B$29,0) -> 7 | H12: =G12*'Property & Assumptions'!$B$27 -> 1050 | I12: =F12+H12 -> 6425.4 | J12: =-F12*'Property & Assumptions'!$B$26 -> -161.262 | K12: =I12+J12 -> 6264.138 | L12: =G12*'Property & Assumptions'!$B$28+G12*'Property & Assumptions'!$B$31+K12*'Property & Assumptions'!$B$30+K12*'Property & Assumptions'!$B$41+K12*'Property & Assumptions'!$B$42+SUM('Monthly Expenses'!E9:K9)+'Monthly Expenses'!N9+'Monthly Expenses'!O9 -> 5738.5814 | M12: =K12-L12 -> 525.55657 | O12: 31 | P12: ='Property & Assumptions'!$B$19*1.1 -> 280.5 | Q12: =MIN(1,'Property & Assumptions'!$C$19+0.05) -> 0.95 | R12: =O12*Q12 -> 29.45 | S12: =P12*R12 -> 8260.725 | T12: =ROUND(R12/'Property & Assumptions'!$B$29,0) -> 8 | U12: =T12*'Property & Assumptions'!$B$27 -> 1200 | V12: =S12+U12 -> 9460.725 | W12: =-S12*'Property & Assumptions'!$B$26 -> -247.82175 | X12: =V12+W12 -> 9212.9033 | Y12: =T12*'Property & Assumptions'!$B$28+T12*'Property & Assumptions'!$B$31+X12*'Property & Assumptions'!$B$30+X12*'Property & Assumptions'!$B$41+X12*'Property & Assumptions'!$B$42+SUM('Monthly Expenses'!E9:K9)+'Monthly Expenses'!N9+'Monthly Expenses'!O9 -> 6709.2357 | Z12: =X12-Y12 -> 2503.6676
B13: 30 | C13: ='Property & Assumptions'!$B$20*0.85 -> 165.75 | D13: =MAX(0,'Property & Assumptions'!$C$20-0.1) -> 0.58 | E13: =B13*D13 -> 17.4 | F13: =C13*E13 -> 2884.05 | G13: =ROUND(E13/'Property & Assumptions'!$B$29,0) -> 5 | H13: =G13*'Property & Assumptions'!$B$27 -> 750 | I13: =F13+H13 -> 3634.05 | J13: =-F13*'Property & Assumptions'!$B$26 -> -86.5215 | K13: =I13+J13 -> 3547.5285 | L13: =G13*'Property & Assumptions'!$B$28+G13*'Property & Assumptions'!$B$31+K13*'Property & Assumptions'!$B$30+K13*'Property & Assumptions'!$B$41+K13*'Property & Assumptions'!$B$42+SUM('Monthly Expenses'!E10:K10)+'Monthly Expenses'!N10+'Monthly Expenses'!O10 -> 4687.9308 | M13: =K13-L13 -> -1140.4023 | O13: 30 | P13: ='Property & Assumptions'!$B$20*1.1 -> 214.5 | Q13: =MIN(1,'Property & Assumptions'!$C$20+0.05) -> 0.73 | R13: =O13*Q13 -> 21.9 | S13: =P13*R13 -> 4697.55 | T13: =ROUND(R13/'Property & Assumptions'!$B$29,0) -> 6 | U13: =T13*'Property & Assumptions'!$B$27 -> 900 | V13: =S13+U13 -> 5597.55 | W13: =-S13*'Property & Assumptions'!$B$26 -> -140.9265 | X13: =V13+W13 -> 5456.6235 | Y13: =T13*'Property & Assumptions'!$B$28+T13*'Property & Assumptions'!$B$31+X13*'Property & Assumptions'!$B$30+X13*'Property & Assumptions'!$B$41+X13*'Property & Assumptions'!$B$42+SUM('Monthly Expenses'!E10:K10)+'Monthly Expenses'!N10+'Monthly Expenses'!O10 -> 5367.4774 | Z13: =X13-Y13 -> 89.146133
B14: 31 | C14: ='Property & Assumptions'!$B$21*0.85 -> 148.75 | D14: =MAX(0,'Property & Assumptions'!$C$21-0.1) -> 0.48 | E14: =B14*D14 -> 14.88 | F14: =C14*E14 -> 2213.4 | G14: =ROUND(E14/'Property & Assumptions'!$B$29,0) -> 4 | H14: =G14*'Property & Assumptions'!$B$27 -> 600 | I14: =F14+H14 -> 2813.4 | J14: =-F14*'Property & Assumptions'!$B$26 -> -66.402 | K14: =I14+J14 -> 2746.998 | L14: =G14*'Property & Assumptions'!$B$28+G14*'Property & Assumptions'!$B$31+K14*'Property & Assumptions'!$B$30+K14*'Property & Assumptions'!$B$41+K14*'Property & Assumptions'!$B$42+SUM('Monthly Expenses'!E11:K11)+'Monthly Expenses'!N11+'Monthly Expenses'!O11 -> 4318.7822 | M14: =K14-L14 -> -1571.7842 | O14: 31 | P14: ='Property & Assumptions'!$B$21*1.1 -> 192.5 | Q14: =MIN(1,'Property & Assumptions'!$C$21+0.05) -> 0.63 | R14: =O14*Q14 -> 19.53 | S14: =P14*R14 -> 3759.525 | T14: =ROUND(R14/'Property & Assumptions'!$B$29,0) -> 6 | U14: =T14*'Property & Assumptions'!$B$27 -> 900 | V14: =S14+U14 -> 4659.525 | W14: =-S14*'Property & Assumptions'!$B$26 -> -112.78575 | X14: =V14+W14 -> 4546.7393 | Y14: =T14*'Property & Assumptions'!$B$28+T14*'Property & Assumptions'!$B$31+X14*'Property & Assumptions'!$B$30+X14*'Property & Assumptions'!$B$41+X14*'Property & Assumptions'!$B$42+SUM('Monthly Expenses'!E11:K11)+'Monthly Expenses'!N11+'Monthly Expenses'!O11 -> 5112.7098 | Z14: =X14-Y14 -> -565.97053
B15: 30 | C15: ='Property & Assumptions'!$B$22*0.85 -> 123.25 | D15: =MAX(0,'Property & Assumptions'!$C$22-0.1) -> 0.3 | E15: =B15*D15 -> 9 | F15: =C15*E15 -> 1109.25 | G15: =ROUND(E15/'Property & Assumptions'!$B$29,0) -> 3 | H15: =G15*'Property & Assumptions'!$B$27 -> 450 | I15: =F15+H15 -> 1559.25 | J15: =-F15*'Property & Assumptions'!$B$26 -> -33.2775 | K15: =I15+J15 -> 1525.9725 | L15: =G15*'Property & Assumptions'!$B$28+G15*'Property & Assumptions'!$B$31+K15*'Property & Assumptions'!$B$30+K15*'Property & Assumptions'!$B$41+K15*'Property & Assumptions'!$B$42+SUM('Monthly Expenses'!E12:K12)+'Monthly Expenses'!N12+'Monthly Expenses'!O12 -> 3831.8951 | M15: =K15-L15 -> -2305.9226 | O15: 30 | P15: ='Property & Assumptions'!$B$22*1.1 -> 159.5 | Q15: =MIN(1,'Property & Assumptions'!$C$22+0.05) -> 0.45 | R15: =O15*Q15 -> 13.5 | S15: =P15*R15 -> 2153.25 | T15: =ROUND(R15/'Property & Assumptions'!$B$29,0) -> 4 | U15: =T15*'Property & Assumptions'!$B$27 -> 600 | V15: =S15+U15 -> 2753.25 | W15: =-S15*'Property & Assumptions'!$B$26 -> -64.5975 | X15: =V15+W15 -> 2688.6525 | Y15: =T15*'Property & Assumptions'!$B$28+T15*'Property & Assumptions'!$B$31+X15*'Property & Assumptions'!$B$30+X15*'Property & Assumptions'!$B$41+X15*'Property & Assumptions'!$B$42+SUM('Monthly Expenses'!E12:K12)+'Monthly Expenses'!N12+'Monthly Expenses'!O12 -> 4302.4455 | Z15: =X15-Y15 -> -1613.793
B16: 31 | C16: ='Property & Assumptions'!$B$23*0.85 -> 140.25 | D16: =MAX(0,'Property & Assumptions'!$C$23-0.1) -> 0.45 | E16: =B16*D16 -> 13.95 | F16: =C16*E16 -> 1956.4875 | G16: =ROUND(E16/'Property & Assumptions'!$B$29,0) -> 4 | H16: =G16*'Property & Assumptions'!$B$27 -> 600 | I16: =F16+H16 -> 2556.4875 | J16: =-F16*'Property & Assumptions'!$B$26 -> -58.694625 | K16: =I16+J16 -> 2497.7929 | L16: =G16*'Property & Assumptions'!$B$28+G16*'Property & Assumptions'!$B$31+K16*'Property & Assumptions'!$B$30+K16*'Property & Assumptions'!$B$41+K16*'Property & Assumptions'!$B$42+SUM('Monthly Expenses'!E13:K13)+'Monthly Expenses'!N13+'Monthly Expenses'!O13 -> 4249.0048 | M16: =K16-L16 -> -1751.2119 | O16: 31 | P16: ='Property & Assumptions'!$B$23*1.1 -> 181.5 | Q16: =MIN(1,'Property & Assumptions'!$C$23+0.05) -> 0.6 | R16: =O16*Q16 -> 18.6 | S16: =P16*R16 -> 3375.9 | T16: =ROUND(R16/'Property & Assumptions'!$B$29,0) -> 5 | U16: =T16*'Property & Assumptions'!$B$27 -> 750 | V16: =S16+U16 -> 4125.9 | W16: =-S16*'Property & Assumptions'!$B$26 -> -101.277 | X16: =V16+W16 -> 4024.623 | Y16: =T16*'Property & Assumptions'!$B$28+T16*'Property & Assumptions'!$B$31+X16*'Property & Assumptions'!$B$30+X16*'Property & Assumptions'!$B$41+X16*'Property & Assumptions'!$B$42+SUM('Monthly Expenses'!E13:K13)+'Monthly Expenses'!N13+'Monthly Expenses'!O13 -> 4821.5172 | Z16: =X16-Y16 -> -796.89423
A19: Avg nightly (gross book / occ nights) | B19: =IF(SUM(E5:E16)=0,0,SUM(F5:F16)/SUM(E5:E16)) -> 172.05237 | N19: ='Monthly Revenue'!$E$17 -> 199.80898 | AA19: =IF(SUM(R5:R16)=0,0,SUM(S5:S16)/SUM(R5:R16)) -> 218.67715
A20: Avg occupancy (simple average of months) | B20: =AVERAGE(D5:D16) -> 0.51916667 | N20: =AVERAGE('Property & Assumptions'!$C$12:$C$23) -> 0.61916667 | AA20: =AVERAGE(Q5:Q16) -> 0.66916667
A21: Gross booking revenue (annual) | B21: =SUM(F5:F16) -> 32720.92 | N21: =SUM('Monthly Revenue'!$F$2:$F$13) -> 45292.7 | AA21: =SUM(S5:S16) -> 53560.595
A22: Net revenue (annual) | B22: =SUM(K5:K16) -> 39839.292 | N22: ='Monthly Revenue'!$K$14 -> 53683.919 | AA22: =SUM(X5:X16) -> 62453.777
A23: Total expenses (annual) | B23: =SUM(L5:L16) -> 54620.475 | N23: ='Monthly Expenses'!$P$14 -> 60091.971 | AA23: =SUM(Y5:Y16) -> 63272.531
A24: Cash flow (annual) | B24: =SUM(M5:M16) -> -14781.183 | N24: ='Monthly Expenses'!$Q$14 -> -6408.0518 | AA24: =SUM(Z5:Z16) -> -818.75389
A25: Cash-on-cash | B25: =IF('Property & Assumptions'!$B$5*'Property & Assumptions'!$B$6=0,0,B24/('Property & Assumptions'!$B$5*'Property & Assumptions'!$B$6)) -> -0.21737034 | N25: ='Annual Summary & Comparison'!$B$10 -> -0.094236055 | AA25: =IF('Property & Assumptions'!$B$5*'Property & Assumptions'!$B$6=0,0,Z24/('Property & Assumptions'!$B$5*'Property & Assumptions'!$B$6)) -> 0
A27: You need Base case or better to beat long-term rent at your current LTR inputs.
