Workbook

Sheet Deal Inputs
A1: Property Address | B1: 1847 Maple Drive
A2: Purchase Price | B2: 195000
A3: Closing Costs (buy side) | B3: 3500
A4: Earnest Money | B4: 5000
A7: Financing Type | B7: Hard Money
A8: Loan-to-Cost (%) | B8: 0.85
A9: Loan Amount | B9: =IF(B7="Cash",0,MIN((B2+'Rehab Budget'!$C$16)*B8,B2+'Rehab Budget'!$C$16)) -> 223380
A10: Cash Out of Pocket | B10: =IF(B7="Cash",B2+B3+'Rehab Budget'!$C$16,B2+B3+'Rehab Budget'!$C$16-B9) -> 42920
A11: Interest Rate (annual) | B11: 0.12
A12: Points (origination) | B12: 2
A13: Point Cost ($) | B13: =B9*B12/100 -> 4467.6
A14: Estimated Hold Period (months) | B14: 5
A15: Monthly Interest Cost | B15: =B9*B11/12 -> 2233.8
A18: Estimated ARV | B18: 315000
A19: Comp 1 (notes) | B19: -
A20: Comp 2 | B20: -
A21: Comp 3 | B21: -
A22: Avg Comp Price / SqFt | B22: 185
A23: Subject Property SqFt | B23: 1700
A24: ARV per SqFt | B24: =B18/B23 -> 185.29412
A27: Agent Commission (%) | B27: 0.05
A28: Agent Commission ($) | B28: =B18*B27 -> 15750
A29: Seller Closing Costs | B29: 3000
A30: Staging / Marketing | B30: 1500
A31: Total Selling Costs | B31: =B28+B29+B30 -> 20250

Sheet Rehab Budget
A1: Category | B1: Description | C1: Est. Cost | D1: Actual Cost | E1: Variance | F1: % of Budget | G1: Status | H1: Notes
A2: Kitchen (cabinets, counters, appliances) | B2: Full kitchen refresh | C2: 18000 | E2: =D2-C2 -> -18000 | F2: =IF($C$16=0,0,C2/$C$16) -> 0.26548673
A3: Bathrooms (2 full, 1 half) | B3: Fixtures + tile | C3: 12000 | E3: =D3-C3 -> -12000 | F3: =IF($C$16=0,0,C3/$C$16) -> 0.17699115
A4: Flooring (LVP throughout) | B4: Main level | C4: 6500 | E4: =D4-C4 -> -6500 | F4: =IF($C$16=0,0,C4/$C$16) -> 0.095870206
A5: Interior Paint | B5: Whole house | C5: 4200 | E5: =D5-C5 -> -4200 | F5: =IF($C$16=0,0,C5/$C$16) -> 0.061946903
A6: Exterior Paint / Siding | B6: Touch-ups | C6: 3800 | E6: =D6-C6 -> -3800 | F6: =IF($C$16=0,0,C6/$C$16) -> 0.056047198
A7: Roof | B7: Not needed | C7: 0 | E7: =D7-C7 -> 0 | F7: =IF($C$16=0,0,C7/$C$16) -> 0
A8: HVAC | B8: No change | C8: 0 | E8: =D8-C8 -> 0 | F8: =IF($C$16=0,0,C8/$C$16) -> 0
A9: Electrical (panel upgrade, fixtures) | B9: Panel + LED | C9: 3200 | E9: =D9-C9 -> -3200 | F9: =IF($C$16=0,0,C9/$C$16) -> 0.04719764
A10: Plumbing (2 fixtures + water heater) | B10: HW heater | C10: 4500 | E10: =D10-C10 -> -4500 | F10: =IF($C$16=0,0,C10/$C$16) -> 0.066371681
A11: Windows (6 replaced) | B11: Efficiency | C11: 4800 | E11: =D11-C11 -> -4800 | F11: =IF($C$16=0,0,C11/$C$16) -> 0.07079646
A12: Landscaping / Curb Appeal | B12: Mulch + beds | C12: 2500 | E12: =D12-C12 -> -2500 | F12: =IF($C$16=0,0,C12/$C$16) -> 0.036873156
A13: Permits & Inspections | B13: Permit fees | C13: 1200 | E13: =D13-C13 -> -1200 | F13: =IF($C$16=0,0,C13/$C$16) -> 0.017699115
... A15: Contingency (10-15%) | B15: Buffer | C15: 6200 | E15: =D15-C15 -> -6200 | F15: =IF($C$16=0,0,C15/$C$16) -> 0.091445428
B16: Total Estimated | C16: =SUM(C2:C15) -> 67800 | D16: =SUM(D2:D15) -> 0 | E16: =SUM(E2:E15) -> -67800
B17: Budget Remaining | C17: =C16-D16 -> 67800
B18: % Complete (by cost) | C18: =IF(C16=0,0,D16/C16) -> 0

Sheet Holding Costs
A1: Cost Category | B1: Monthly Cost | C1: Months | D1: Total
A2: Loan Interest | B2: ='Deal Inputs'!$B$15 -> 2233.8 | C2: ='Deal Inputs'!$B$14 -> 5 | D2: =B2*C2 -> 11169
A3: Property Tax | B3: 320 | C3: ='Deal Inputs'!$B$14 -> 5 | D3: =B3*C3 -> 1600
A4: Insurance (vacant/builder) | B4: 175 | C4: ='Deal Inputs'!$B$14 -> 5 | D4: =B4*C4 -> 875
A5: Utilities | B5: 280 | C5: ='Deal Inputs'!$B$14 -> 5 | D5: =B5*C5 -> 1400
A6: Lawn / Snow / Maintenance | B6: 100 | C6: ='Deal Inputs'!$B$14 -> 5 | D6: =B6*C6 -> 500
A7: HOA | B7: 0 | C7: ='Deal Inputs'!$B$14 -> 5 | D7: =B7*C7 -> 0
A8: Security / Monitoring | B8: 0 | C8: ='Deal Inputs'!$B$14 -> 5 | D8: =B8*C8 -> 0
A9: Other | B9: 0 | C9: ='Deal Inputs'!$B$14 -> 5 | D9: =B9*C9 -> 0
A10: TOTALS | B10: =SUM(B2:B9) -> 3108.8 | D10: =SUM(D2:D9) -> 15544

Sheet Profit Analysis
A1: Line | B1: Label | C1: Amount
A2: 1 | B2: Purchase Price | C2: ='Deal Inputs'!$B$2 -> 195000
A3: 2 | B3: Closing Costs (buy) | C3: ='Deal Inputs'!$B$3 -> 3500
A4: 3 | B4: Rehab Budget (est.) | C4: ='Rehab Budget'!$C$16 -> 67800
A5: 4 | B5: Loan Points / Origination | C5: ='Deal Inputs'!$B$13 -> 4467.6
A6: 5 | B6: Holding Costs | C6: ='Holding Costs'!$D$10 -> 15544
A7: 6 | B7: Selling Costs | C7: ='Deal Inputs'!$B$31 -> 20250
B8: Total Project Cost | C8: =SUM(C2:C7) -> 306561.6
B11: After-Repair Value | C11: ='Deal Inputs'!$B$18 -> 315000
B12: Total Project Cost | C12: =C8 -> 306561.6
B13: Net Profit | C13: =C11-C12 -> 8438.4
B14: ROI (on total project cost) | C14: =IF(C8=0,0,C13/C8) -> 0.027525952
B15: ROI (on cash invested) | C15: =IF('Deal Inputs'!$B$10=0,0,C13/'Deal Inputs'!$B$10) -> 0.19660764
B16: Annualized ROI (cash) | C16: =IF(OR('Deal Inputs'!$B$10=0,'Deal Inputs'!$B$14=0),0,C15*(12/'Deal Inputs'!$B$14)) -> 0.47185834
B17: Profit per Month | C17: =IF('Deal Inputs'!$B$14=0,0,C13/'Deal Inputs'!$B$14) -> 1687.68
B20: 70% Rule Max Offer | C20: ='Deal Inputs'!$B$18*0.7-'Rehab Budget'!$C$16 -> 152700
B21: Passes 70% rule? | C21: =IF('Deal Inputs'!$B$2<=C20,"PASS","FAIL") -> FAIL
B22: Target Profit Margin (input) | C22: 0.15
B23: Target Profit ($) | C23: ='Deal Inputs'!$B$18*C22 -> 47250
B24: MAO (simple) | C24: ='Deal Inputs'!$B$18-'Rehab Budget'!$C$16-C23-'Deal Inputs'!$B$31-'Holding Costs'!$D$10 -> 164156
B25: Actual Profit Margin | C25: =IF('Deal Inputs'!$B$18=0,0,C13/'Deal Inputs'!$B$18) -> 0.026788571
B27: Sensitivity: Net Profit
C28: ARV -10% | D28: ARV -5% | E28: ARV (base) | F28: ARV +5% | G28: ARV +10%
B29: Rehab +20% | C29: ='Deal Inputs'!$B$18*(1+-0.1)-('Deal Inputs'!$B$2+'Deal Inputs'!$B$3+'Rehab Budget'!$C$16*(1+0.2)+'Deal Inputs'!$B$13+'Holding Costs'!$D$10+'Deal Inputs'!$B$31) -> -36621.6 | D29: ='Deal Inputs'!$B$18*(1+-0.05)-('Deal Inputs'!$B$2+'Deal Inputs'!$B$3+'Rehab Budget'!$C$16*(1+0.2)+'Deal Inputs'!$B$13+'Holding Costs'!$D$10+'Deal Inputs'!$B$31) -> -20871.6 | E29: ='Deal Inputs'!$B$18*(1+0)-('Deal Inputs'!$B$2+'Deal Inputs'!$B$3+'Rehab Budget'!$C$16*(1+0.2)+'Deal Inputs'!$B$13+'Holding Costs'!$D$10+'Deal Inputs'!$B$31) -> -5121.6 | F29: ='Deal Inputs'!$B$18*(1+0.05)-('Deal Inputs'!$B$2+'Deal Inputs'!$B$3+'Rehab Budget'!$C$16*(1+0.2)+'Deal Inputs'!$B$13+'Holding Costs'!$D$10+'Deal Inputs'!$B$31) -> 10628.4 | G29: ='Deal Inputs'!$B$18*(1+0.1)-('Deal Inputs'!$B$2+'Deal Inputs'!$B$3+'Rehab Budget'!$C$16*(1+0.2)+'Deal Inputs'!$B$13+'Holding Costs'!$D$10+'Deal Inputs'!$B$31) -> 26378.4
B30: Rehab +10% | C30: ='Deal Inputs'!$B$18*(1+-0.1)-('Deal Inputs'!$B$2+'Deal Inputs'!$B$3+'Rehab Budget'!$C$16*(1+0.1)+'Deal Inputs'!$B$13+'Holding Costs'!$D$10+'Deal Inputs'!$B$31) -> -29841.6 | D30: ='Deal Inputs'!$B$18*(1+-0.05)-('Deal Inputs'!$B$2+'Deal Inputs'!$B$3+'Rehab Budget'!$C$16*(1+0.1)+'Deal Inputs'!$B$13+'Holding Costs'!$D$10+'Deal Inputs'!$B$31) -> -14091.6 | E30: ='Deal Inputs'!$B$18*(1+0)-('Deal Inputs'!$B$2+'Deal Inputs'!$B$3+'Rehab Budget'!$C$16*(1+0.1)+'Deal Inputs'!$B$13+'Holding Costs'!$D$10+'Deal Inputs'!$B$31) -> 1658.4 | F30: ='Deal Inputs'!$B$18*(1+0.05)-('Deal Inputs'!$B$2+'Deal Inputs'!$B$3+'Rehab Budget'!$C$16*(1+0.1)+'Deal Inputs'!$B$13+'Holding Costs'!$D$10+'Deal Inputs'!$B$31) -> 17408.4 | G30: ='Deal Inputs'!$B$18*(1+0.1)-('Deal Inputs'!$B$2+'Deal Inputs'!$B$3+'Rehab Budget'!$C$16*(1+0.1)+'Deal Inputs'!$B$13+'Holding Costs'!$D$10+'Deal Inputs'!$B$31) -> 33158.4
B31: Rehab (base) | C31: ='Deal Inputs'!$B$18*(1+-0.1)-('Deal Inputs'!$B$2+'Deal Inputs'!$B$3+'Rehab Budget'!$C$16*(1+0)+'Deal Inputs'!$B$13+'Holding Costs'!$D$10+'Deal Inputs'!$B$31) -> -23061.6 | D31: ='Deal Inputs'!$B$18*(1+-0.05)-('Deal Inputs'!$B$2+'Deal Inputs'!$B$3+'Rehab Budget'!$C$16*(1+0)+'Deal Inputs'!$B$13+'Holding Costs'!$D$10+'Deal Inputs'!$B$31) -> -7311.6 | E31: ='Deal Inputs'!$B$18*(1+0)-('Deal Inputs'!$B$2+'Deal Inputs'!$B$3+'Rehab Budget'!$C$16*(1+0)+'Deal Inputs'!$B$13+'Holding Costs'!$D$10+'Deal Inputs'!$B$31) -> 8438.4 | F31: ='Deal Inputs'!$B$18*(1+0.05)-('Deal Inputs'!$B$2+'Deal Inputs'!$B$3+'Rehab Budget'!$C$16*(1+0)+'Deal Inputs'!$B$13+'Holding Costs'!$D$10+'Deal Inputs'!$B$31) -> 24188.4 | G31: ='Deal Inputs'!$B$18*(1+0.1)-('Deal Inputs'!$B$2+'Deal Inputs'!$B$3+'Rehab Budget'!$C$16*(1+0)+'Deal Inputs'!$B$13+'Holding Costs'!$D$10+'Deal Inputs'!$B$31) -> 39938.4
B32: Rehab -10% | C32: ='Deal Inputs'!$B$18*(1+-0.1)-('Deal Inputs'!$B$2+'Deal Inputs'!$B$3+'Rehab Budget'!$C$16*(1+-0.1)+'Deal Inputs'!$B$13+'Holding Costs'!$D$10+'Deal Inputs'!$B$31) -> -16281.6 | D32: ='Deal Inputs'!$B$18*(1+-0.05)-('Deal Inputs'!$B$2+'Deal Inputs'!$B$3+'Rehab Budget'!$C$16*(1+-0.1)+'Deal Inputs'!$B$13+'Holding Costs'!$D$10+'Deal Inputs'!$B$31) -> -531.6 | E32: ='Deal Inputs'!$B$18*(1+0)-('Deal Inputs'!$B$2+'Deal Inputs'!$B$3+'Rehab Budget'!$C$16*(1+-0.1)+'Deal Inputs'!$B$13+'Holding Costs'!$D$10+'Deal Inputs'!$B$31) -> 15218.4 | F32: ='Deal Inputs'!$B$18*(1+0.05)-('Deal Inputs'!$B$2+'Deal Inputs'!$B$3+'Rehab Budget'!$C$16*(1+-0.1)+'Deal Inputs'!$B$13+'Holding Costs'!$D$10+'Deal Inputs'!$B$31) -> 30968.4 | G32: ='Deal Inputs'!$B$18*(1+0.1)-('Deal Inputs'!$B$2+'Deal Inputs'!$B$3+'Rehab Budget'!$C$16*(1+-0.1)+'Deal Inputs'!$B$13+'Holding Costs'!$D$10+'Deal Inputs'!$B$31) -> 46718.4
B33: Rehab -20% | C33: ='Deal Inputs'!$B$18*(1+-0.1)-('Deal Inputs'!$B$2+'Deal Inputs'!$B$3+'Rehab Budget'!$C$16*(1+-0.2)+'Deal Inputs'!$B$13+'Holding Costs'!$D$10+'Deal Inputs'!$B$31) -> -9501.6 | D33: ='Deal Inputs'!$B$18*(1+-0.05)-('Deal Inputs'!$B$2+'Deal Inputs'!$B$3+'Rehab Budget'!$C$16*(1+-0.2)+'Deal Inputs'!$B$13+'Holding Costs'!$D$10+'Deal Inputs'!$B$31) -> 6248.4 | E33: ='Deal Inputs'!$B$18*(1+0)-('Deal Inputs'!$B$2+'Deal Inputs'!$B$3+'Rehab Budget'!$C$16*(1+-0.2)+'Deal Inputs'!$B$13+'Holding Costs'!$D$10+'Deal Inputs'!$B$31) -> 21998.4 | F33: ='Deal Inputs'!$B$18*(1+0.05)-('Deal Inputs'!$B$2+'Deal Inputs'!$B$3+'Rehab Budget'!$C$16*(1+-0.2)+'Deal Inputs'!$B$13+'Holding Costs'!$D$10+'Deal Inputs'!$B$31) -> 37748.4 | G33: ='Deal Inputs'!$B$18*(1+0.1)-('Deal Inputs'!$B$2+'Deal Inputs'!$B$3+'Rehab Budget'!$C$16*(1+-0.2)+'Deal Inputs'!$B$13+'Holding Costs'!$D$10+'Deal Inputs'!$B$31) -> 53498.4

Sheet Timeline
A1: Week # | B1: Date Range (fill in) | C1: Phase | D1: Key Tasks | E1: Est. Spend Week | F1: Cumulative Spend | G1: Status
A2: 1 | B2: Close / acquisition | C2: Acquisition | D2: Close on property | E2: 3500 | F2: =E2 -> 3500 | G2: In Progress
A3: 2 | B3: Demo start | C3: Demo | D3: Kitchen + bath demo | E3: 4000 | F3: =F2+E3 -> 7500
A4: 3 | B4: Demo cont. | C4: Demo | D4: Debris out | E4: 1200 | F4: =F3+E4 -> 8700
A5: 4 | B5: Rough-in | C5: Rough-In | D5: Electrical/plumbing rough | E5: 5500 | F5: =F4+E5 -> 14200 | G5: Delayed
A6: 5 | B6: Rough-in | C6: Rough-In | D6: Inspect rough | E6: 800 | F6: =F5+E6 -> 15000
A7: 6 | B7: Drywall | C7: Rough-In | D7: Hang + mud | E7: 6200 | F7: =F6+E7 -> 21200
A8: 7 | B8: Paint | C8: Finishes | D8: Interior paint | E8: 4200 | F8: =F7+E8 -> 25400
A9: 8 | B9: Flooring | C9: Finishes | D9: LVP install | E9: 6500 | F9: =F8+E9 -> 31900
A10: 9 | B10: Kitchen | C10: Finishes | D10: Cabinets + counters | E10: 12000 | F10: =F9+E10 -> 43900
A11: 10 | B11: Baths | C11: Finishes | D11: Fixtures + tile | E11: 9000 | F11: =F10+E11 -> 52900
A12: 11 | B12: Punch list | C12: Punch List | D12: Touch-ups | E12: 1500 | F12: =F11+E12 -> 54400
A13: 12 | B13: Listing prep | C13: Listing | D13: Clean + stage | E13: 1800 | F13: =F12+E13 -> 56200
A14: 13 | B14: Live | C14: Listing | D14: Photos + listing | E14: 600 | F14: =F13+E14 -> 56800
A15: 14 | B15: On market | C15: Under Contract | D15: Showings | E15: 0 | F15: =F14+E15 -> 56800
A16: 15 | B16: On market | C16: Under Contract | D16: Price tweak | E16: 0 | F16: =F15+E16 -> 56800
A17: 16 | B17: UC | C17: Under Contract | D17: Inspection response | E17: 900 | F17: =F16+E17 -> 57700
... A21: 20 | B21: Closed | C21: Closing | D21: Recording | E21: 300 | F21: =F20+E21 -> 58500
