Workbook

Sheet My Loans
A1: As-of date (for payoff estimates) | B1: 45658
A2: Loan name | B2: Lender | C2: Original balance | D2: Current balance | E2: Interest rate (annual) | F2: Minimum payment | G2: Months remaining | H2: Monthly interest | I2: Payoff date (min only) | J2: Sort key (avalanche) | K2: Sort key (snowball)
A3: Stafford Sub #1 | B3: FedLoan | C3: 10000 | D3: 8200 | E3: 0.045 | F3: 95 | G3: 120 | H3: =D3*E3/12 -> 30.75 | I3: =EDATE($B$1,G3) -> 49310 | J3: =IF($D3<=0,-(10^6+ROW()/10^8),$E3+ROW()/10^10) -> 0.045 | K3: =IF($D3<=0,10^12+ROW()/10^8,$D3+ROW()/10^10) -> 8200
A4: Stafford Unsub #1 | B4: FedLoan | C4: 15000 | D4: 12800 | E4: 0.055 | F4: 142 | G4: 118 | H4: =D4*E4/12 -> 58.666667 | I4: =EDATE($B$1,G4) -> 49249 | J4: =IF($D4<=0,-(10^6+ROW()/10^8),$E4+ROW()/10^10) -> 0.055 | K4: =IF($D4<=0,10^12+ROW()/10^8,$D4+ROW()/10^10) -> 12800
A5: Private SoFi | B5: SoFi | C5: 32000 | D5: 28000 | E5: 0.079 | F5: 410 | G5: 108 | H5: =D5*E5/12 -> 184.33333 | I5: =EDATE($B$1,G5) -> 48945 | J5: =IF($D5<=0,-(10^6+ROW()/10^8),$E5+ROW()/10^10) -> 0.079000001 | K5: =IF($D5<=0,10^12+ROW()/10^8,$D5+ROW()/10^10) -> 28000
A6: Parent PLUS | B6: EdFinancial | C6: 18000 | D6: 15200 | E6: 0.062 | F6: 178 | G6: 100 | H6: =D6*E6/12 -> 78.533333 | I6: =EDATE($B$1,G6) -> 48700 | J6: =IF($D6<=0,-(10^6+ROW()/10^8),$E6+ROW()/10^10) -> 0.062000001 | K6: =IF($D6<=0,10^12+ROW()/10^8,$D6+ROW()/10^10) -> 15200
A7: Stafford Sub #2 | B7: FedLoan | C7: 12000 | D7: 9800 | E7: 0.049 | F7: 112 | G7: 115 | H7: =D7*E7/12 -> 40.016667 | I7: =EDATE($B$1,G7) -> 49157 | J7: =IF($D7<=0,-(10^6+ROW()/10^8),$E7+ROW()/10^10) -> 0.049000001 | K7: =IF($D7<=0,10^12+ROW()/10^8,$D7+ROW()/10^10) -> 9800
C8: 0 | D8: 0 | E8: 0 | F8: 0 | G8: 0 | H8: =IF(D8=0,"",D8*E8/12) | I8: =IF(D8=0,"",EDATE($B$1,G8)) | J8: =IF($D8<=0,-(10^6+ROW()/10^8),$E8+ROW()/10^10) -> -1000000 | K8: =IF($D8<=0,10^12+ROW()/10^8,$D8+ROW()/10^10) -> 1000000000000
C9: 0 | D9: 0 | E9: 0 | F9: 0 | G9: 0 | H9: =IF(D9=0,"",D9*E9/12) | I9: =IF(D9=0,"",EDATE($B$1,G9)) | J9: =IF($D9<=0,-(10^6+ROW()/10^8),$E9+ROW()/10^10) -> -1000000 | K9: =IF($D9<=0,10^12+ROW()/10^8,$D9+ROW()/10^10) -> 1000000000000
C10: 0 | D10: 0 | E10: 0 | F10: 0 | G10: 0 | H10: =IF(D10=0,"",D10*E10/12) | I10: =IF(D10=0,"",EDATE($B$1,G10)) | J10: =IF($D10<=0,-(10^6+ROW()/10^8),$E10+ROW()/10^10) -> -1000000 | K10: =IF($D10<=0,10^12+ROW()/10^8,$D10+ROW()/10^10) -> 1000000000000
A13: Total monthly loan budget | B13: 1400 | N13: Avalanche: My Loans row # | O13: Snowball: My Loans row #
A14: Sum of minimums | B14: =SUM(F3:F10) -> 937 | N14: =IFERROR(MATCH(LARGE($J$3:$J$10,1),$J$3:$J$10,0)+2,"") -> 5 | O14: =IFERROR(MATCH(SMALL($K$3:$K$10,1),$K$3:$K$10,0)+2,"") -> 3
A15: Extra payment available | B15: =B13-B14 -> 463 | N15: =IFERROR(MATCH(LARGE($J$3:$J$10,2),$J$3:$J$10,0)+2,"") -> 6 | O15: =IFERROR(MATCH(SMALL($K$3:$K$10,2),$K$3:$K$10,0)+2,"") -> 7
A16: Target payoff date (optional) | N16: =IFERROR(MATCH(LARGE($J$3:$J$10,3),$J$3:$J$10,0)+2,"") -> 4 | O16: =IFERROR(MATCH(SMALL($K$3:$K$10,3),$K$3:$K$10,0)+2,"") -> 4
N17: =IFERROR(MATCH(LARGE($J$3:$J$10,4),$J$3:$J$10,0)+2,"") -> 7 | O17: =IFERROR(MATCH(SMALL($K$3:$K$10,4),$K$3:$K$10,0)+2,"") -> 6
A18: Total current balance | B18: =SUM(D3:D10) -> 74000 | N18: =IFERROR(MATCH(LARGE($J$3:$J$10,5),$J$3:$J$10,0)+2,"") -> 3 | O18: =IFERROR(MATCH(SMALL($K$3:$K$10,5),$K$3:$K$10,0)+2,"") -> 5
A19: Weighted avg rate | B19: =IF(SUM(D3:D10)=0,0,SUMPRODUCT(D3:D10,E3:E10)/SUM(D3:D10)) -> 0.063616216 | N19: =IFERROR(MATCH(LARGE($J$3:$J$10,6),$J$3:$J$10,0)+2,"") -> 8 | O19: =IFERROR(MATCH(SMALL($K$3:$K$10,6),$K$3:$K$10,0)+2,"") -> 8
A20: Longest term (months) | B20: =MAX(G3:G10) -> 120 | N20: =IFERROR(MATCH(LARGE($J$3:$J$10,7),$J$3:$J$10,0)+2,"") -> 9 | O20: =IFERROR(MATCH(SMALL($K$3:$K$10,7),$K$3:$K$10,0)+2,"") -> 8
A21: Total interest (min pay, from Amortization) | B21: ='Amortization (Full)'!$F$2 -> 22036.792 | N21: =IFERROR(MATCH(LARGE($J$3:$J$10,8),$J$3:$J$10,0)+2,"") -> 10 | O21: =IFERROR(MATCH(SMALL($K$3:$K$10,8),$K$3:$K$10,0)+2,"") -> 8
A22: Highest rate loan | B22: =INDEX(A3:A10,MATCH(MAX(E3:E10),E3:E10,0)) -> Private SoFi
A24: Strategy slot map (auto; do not edit)

Sheet Avalanche
A1: Month | B1: L1 beg | C1: L1 int | D1: L1 min | E1: L2 beg | F1: L2 int | G1: L2 min | H1: L3 beg | I1: L3 int | J1: L3 min | K1: L4 beg | L1: L4 int | M1: L4 min | N1: L5 beg | O1: L5 int | P1: L5 min | Q1: L6 beg | R1: L6 int | S1: L6 min | T1: L7 beg | U1: L7 int | V1: L7 min | W1: L8 beg | X1: L8 int | Y1: L8 min | Z1: Surplus | AA1: Rem0 | AB1: cascade | AC1: cascade | AD1: cascade | AE1: cascade | AF1: cascade | AG1: cascade | AH1: cascade | AI1: cascade | AJ1: cascade | AK1: cascade | AL1: cascade | AM1: cascade | AN1: cascade | AO1: cascade | AP1: cascade | AQ1: cascade | AR1: cascade | AS1: cascade | AT1: cascade | AU1: cascade | AV1: cascade | AW1: cascade | AX1: cascade | AY1: cascade | AZ1: cascade | BA1: cascade | BB1: cascade | BC1: cascade | BD1: cascade | BE1: cascade | BF1: cascade | BG1: cascade | BH1: cascade | BI1: cascade | BJ1: cascade | BK1: cascade | BL1: cascade | BM1: cascade | BN1: cascade | BO1: Total pay | BP1: Total int | BQ1: Sum balance
A2: 1 | B2: =IF(A2=1,IF(OR('My Loans'!$N$14="",'My Loans'!$N$14=0),0,INDIRECT("'My Loans'!$D"&'My Loans'!$N$14)),AE1) -> 28000 | C2: =IF(OR('My Loans'!$N$14="",'My Loans'!$N$14=0),0,B2*INDIRECT("'My Loans'!$E"&'My Loans'!$N$14)/12) -> 184.33333 | D2: =IF(OR('My Loans'!$N$14="",'My Loans'!$N$14=0),0,IF(B2<0.005,0,MIN(INDIRECT("'My Loans'!$F"&'My Loans'!$N$14),B2+C2))) -> 410 | E2: =IF(A2=1,IF(OR('My Loans'!$N$15="",'My Loans'!$N$15=0),0,INDIRECT("'My Loans'!$D"&'My Loans'!$N$15)),AJ1) -> 15200 | F2: =IF(OR('My Loans'!$N$15="",'My Loans'!$N$15=0),0,E2*INDIRECT("'My Loans'!$E"&'My Loans'!$N$15)/12) -> 78.533333 | G2: =IF(OR('My Loans'!$N$15="",'My Loans'!$N$15=0),0,IF(E2<0.005,0,MIN(INDIRECT("'My Loans'!$F"&'My Loans'!$N$15),E2+F2))) -> 178 | H2: =IF(A2=1,IF(OR('My Loans'!$N$16="",'My Loans'!$N$16=0),0,INDIRECT("'My Loans'!$D"&'My Loans'!$N$16)),AO1) -> 12800 | I2: =IF(OR('My Loans'!$N$16="",'My Loans'!$N$16=0),0,H2*INDIRECT("'My Loans'!$E"&'My Loans'!$N$16)/12) -> 58.666667 | J2: =IF(OR('My Loans'!$N$16="",'My Loans'!$N$16=0),0,IF(H2<0.005,0,MIN(INDIRECT("'My Loans'!$F"&'My Loans'!$N$16),H2+I2))) -> 142 | K2: =IF(A2=1,IF(OR('My Loans'!$N$17="",'My Loans'!$N$17=0),0,INDIRECT("'My Loans'!$D"&'My Loans'!$N$17)),AT1) -> 9800 | L2: =IF(OR('My Loans'!$N$17="",'My Loans'!$N$17=0),0,K2*INDIRECT("'My Loans'!$E"&'My Loans'!$N$17)/12) -> 40.016667 | M2: =IF(OR('My Loans'!$N$17="",'My Loans'!$N$17=0),0,IF(K2<0.005,0,MIN(INDIRECT("'My Loans'!$F"&'My Loans'!$N$17),K2+L2))) -> 112 | N2: =IF(A2=1,IF(OR('My Loans'!$N$18="",'My Loans'!$N$18=0),0,INDIRECT("'My Loans'!$D"&'My Loans'!$N$18)),AY1) -> 8200 | O2: =IF(OR('My Loans'!$N$18="",'My Loans'!$N$18=0),0,N2*INDIRECT("'My Loans'!$E"&'My Loans'!$N$18)/12) -> 30.75 | P2: =IF(OR('My Loans'!$N$18="",'My Loans'!$N$18=0),0,IF(N2<0.005,0,MIN(INDIRECT("'My Loans'!$F"&'My Loans'!$N$18),N2+O2))) -> 95 | Q2: =IF(A2=1,IF(OR('My Loans'!$N$19="",'My Loans'!$N$19=0),0,INDIRECT("'My Loans'!$D"&'My Loans'!$N$19)),BD1) -> 0 | R2: =IF(OR('My Loans'!$N$19="",'My Loans'!$N$19=0),0,Q2*INDIRECT("'My Loans'!$E"&'My Loans'!$N$19)/12) -> 0 | S2: =IF(OR('My Loans'!$N$19="",'My Loans'!$N$19=0),0,IF(Q2<0.005,0,MIN(INDIRECT("'My Loans'!$F"&'My Loans'!$N$19),Q2+R2))) -> 0 | T2: =IF(A2=1,IF(OR('My Loans'!$N$20="",'My Loans'!$N$20=0),0,INDIRECT("'My Loans'!$D"&'My Loans'!$N$20)),BI1) -> 0 | U2: =IF(OR('My Loans'!$N$20="",'My Loans'!$N$20=0),0,T2*INDIRECT("'My Loans'!$E"&'My Loans'!$N$20)/12) -> 0 | V2: =IF(OR('My Loans'!$N$20="",'My Loans'!$N$20=0),0,IF(T2<0.005,0,MIN(INDIRECT("'My Loans'!$F"&'My Loans'!$N$20),T2+U2))) -> 0 | W2: =IF(A2=1,IF(OR('My Loans'!$N$21="",'My Loans'!$N$21=0),0,INDIRECT("'My Loans'!$D"&'My Loans'!$N$21)),BN1) -> 0 | X2: =IF(OR('My Loans'!$N$21="",'My Loans'!$N$21=0),0,W2*INDIRECT("'My Loans'!$E"&'My Loans'!$N$21)/12) -> 0 | Y2: =IF(OR('My Loans'!$N$21="",'My Loans'!$N$21=0),0,IF(W2<0.005,0,MIN(INDIRECT("'My Loans'!$F"&'My Loans'!$N$21),W2+X2))) -> 0 | Z2: ='My Loans'!$B$13-(D2+G2+J2+M2+P2+S2+V2+Y2) -> 463 | AA2: =MAX(0,Z2) -> 463 | AB2: =MAX(0,B2+C2-D2) -> 27774.333 | AC2: =MIN(AA2,AB2) -> 463 | AD2: =D2+AC2 -> 873 | AE2: =MAX(0,B2+C2-AD2) -> 27311.333 | AF2: =MAX(0,AA2-AC2) -> 0 | AG2: =MAX(0,E2+F2-G2) -> 15100.533 | AH2: =MIN(AF2,AG2) -> 0 | AI2: =G2+AH2 -> 178 | AJ2: =MAX(0,E2+F2-AI2) -> 15100.533 | AK2: =MAX(0,AF2-AH2) -> 0 | AL2: =MAX(0,H2+I2-J2) -> 12716.667 | AM2: =MIN(AK2,AL2) -> 0 | AN2: =J2+AM2 -> 142 | AO2: =MAX(0,H2+I2-AN2) -> 12716.667 | AP2: =MAX(0,AK2-AM2) -> 0 | AQ2: =MAX(0,K2+L2-M2) -> 9728.0167 | AR2: =MIN(AP2,AQ2) -> 0 | AS2: =M2+AR2 -> 112 | AT2: =MAX(0,K2+L2-AS2) -> 9728.0167 | AU2: =MAX(0,AP2-AR2) -> 0 | AV2: =MAX(0,N2+O2-P2) -> 8135.75 | AW2: =MIN(AU2,AV2) -> 0 | AX2: =P2+AW2 -> 95 | AY2: =MAX(0,N2+O2-AX2) -> 8135.75 | AZ2: =MAX(0,AU2-AW2) -> 0 | BA2: =MAX(0,Q2+R2-S2) -> 0 | BB2: =MIN(AZ2,BA2) -> 0 | BC2: =S2+BB2 -> 0 | BD2: =MAX(0,Q2+R2-BC2) -> 0 | BE2: =MAX(0,AZ2-BB2) -> 0 | BF2: =MAX(0,T2+U2-V2) -> 0 | BG2: =MIN(BE2,BF2) -> 0 | BH2: =V2+BG2 -> 0 | BI2: =MAX(0,T2+U2-BH2) -> 0 | BJ2: =MAX(0,BE2-BG2) -> 0 | BK2: =MAX(0,W2+X2-Y2) -> 0 | BL2: =MIN(BJ2,BK2) -> 0 | BM2: =Y2+BL2 -> 0 | BN2: =MAX(0,W2+X2-BM2) -> 0 | BO2: =AD2+AI2+AN2+AS2+AX2+BC2+BH2+BM2 -> 1400 | BP2: =C2+F2+I2+L2+O2+R2+U2+X2 -> 392.3 | BQ2: =AE2+AJ2+AO2+AT2+AY2+BD2+BI2+BN2 -> 72992.3
A3: 2 | B3: =IF(A3=1,IF(OR('My Loans'!$N$14="",'My Loans'!$N$14=0),0,INDIRECT("'My Loans'!$D"&'My Loans'!$N$14)),AE2) -> 27311.333 | C3: =IF(OR('My Loans'!$N$14="",'My Loans'!$N$14=0),0,B3*INDIRECT("'My Loans'!$E"&'My Loans'!$N$14)/12) -> 179.79961 | D3: =IF(OR('My Loans'!$N$14="",'My Loans'!$N$14=0),0,IF(B3<0.005,0,MIN(INDIRECT("'My Loans'!$F"&'My Loans'!$N$14),B3+C3))) -> 410 | E3: =IF(A3=1,IF(OR('My Loans'!$N$15="",'My Loans'!$N$15=0),0,INDIRECT("'My Loans'!$D"&'My Loans'!$N$15)),AJ2) -> 15100.533 | F3: =IF(OR('My Loans'!$N$15="",'My Loans'!$N$15=0),0,E3*INDIRECT("'My Loans'!$E"&'My Loans'!$N$15)/12) -> 78.019422 | G3: =IF(OR('My Loans'!$N$15="",'My Loans'!$N$15=0),0,IF(E3<0.005,0,MIN(INDIRECT("'My Loans'!$F"&'My Loans'!$N$15),E3+F3))) -> 178 | H3: =IF(A3=1,IF(OR('My Loans'!$N$16="",'My Loans'!$N$16=0),0,INDIRECT("'My Loans'!$D"&'My Loans'!$N$16)),AO2) -> 12716.667 | I3: =IF(OR('My Loans'!$N$16="",'My Loans'!$N$16=0),0,H3*INDIRECT("'My Loans'!$E"&'My Loans'!$N$16)/12) -> 58.284722 | J3: =IF(OR('My Loans'!$N$16="",'My Loans'!$N$16=0),0,IF(H3<0.005,0,MIN(INDIRECT("'My Loans'!$F"&'My Loans'!$N$16),H3+I3))) -> 142 | K3: =IF(A3=1,IF(OR('My Loans'!$N$17="",'My Loans'!$N$17=0),0,INDIRECT("'My Loans'!$D"&'My Loans'!$N$17)),AT2) -> 9728.0167 | L3: =IF(OR('My Loans'!$N$17="",'My Loans'!$N$17=0),0,K3*INDIRECT("'My Loans'!$E"&'My Loans'!$N$17)/12) -> 39.722735 | M3: =IF(OR('My Loans'!$N$17="",'My Loans'!$N$17=0),0,IF(K3<0.005,0,MIN(INDIRECT("'My Loans'!$F"&'My Loans'!$N$17),K3+L3))) -> 112 | N3: =IF(A3=1,IF(OR('My Loans'!$N$18="",'My Loans'!$N$18=0),0,INDIRECT("'My Loans'!$D"&'My Loans'!$N$18)),AY2) -> 8135.75 | O3: =IF(OR('My Loans'!$N$18="",'My Loans'!$N$18=0),0,N3*INDIRECT("'My Loans'!$E"&'My Loans'!$N$18)/12) -> 30.509062 | P3: =IF(OR('My Loans'!$N$18="",'My Loans'!$N$18=0),0,IF(N3<0.005,0,MIN(INDIRECT("'My Loans'!$F"&'My Loans'!$N$18),N3+O3))) -> 95 | Q3: =IF(A3=1,IF(OR('My Loans'!$N$19="",'My Loans'!$N$19=0),0,INDIRECT("'My Loans'!$D"&'My Loans'!$N$19)),BD2) -> 0 | R3: =IF(OR('My Loans'!$N$19="",'My Loans'!$N$19=0),0,Q3*INDIRECT("'My Loans'!$E"&'My Loans'!$N$19)/12) -> 0 | S3: =IF(OR('My Loans'!$N$19="",'My Loans'!$N$19=0),0,IF(Q3<0.005,0,MIN(INDIRECT("'My Loans'!$F"&'My Loans'!$N$19),Q3+R3))) -> 0 | T3: =IF(A3=1,IF(OR('My Loans'!$N$20="",'My Loans'!$N$20=0),0,INDIRECT("'My Loans'!$D"&'My Loans'!$N$20)),BI2) -> 0 | U3: =IF(OR('My Loans'!$N$20="",'My Loans'!$N$20=0),0,T3*INDIRECT("'My Loans'!$E"&'My Loans'!$N$20)/12) -> 0 | V3: =IF(OR('My Loans'!$N$20="",'My Loans'!$N$20=0),0,IF(T3<0.005,0,MIN(INDIRECT("'My Loans'!$F"&'My Loans'!$N$20),T3+U3))) -> 0 | W3: =IF(A3=1,IF(OR('My Loans'!$N$21="",'My Loans'!$N$21=0),0,INDIRECT("'My Loans'!$D"&'My Loans'!$N$21)),BN2) -> 0 | X3: =IF(OR('My Loans'!$N$21="",'My Loans'!$N$21=0),0,W3*INDIRECT("'My Loans'!$E"&'My Loans'!$N$21)/12) -> 0 | Y3: =IF(OR('My Loans'!$N$21="",'My Loans'!$N$21=0),0,IF(W3<0.005,0,MIN(INDIRECT("'My Loans'!$F"&'My Loans'!$N$21),W3+X3))) -> 0 | Z3: ='My Loans'!$B$13-(D3+G3+J3+M3+P3+S3+V3+Y3) -> 463 | AA3: =MAX(0,Z3) -> 463 | AB3: =MAX(0,B3+C3-D3) -> 27081.133 | AC3: =MIN(AA3,AB3) -> 463 | AD3: =D3+AC3 -> 873 | AE3: =MAX(0,B3+C3-AD3) -> 26618.133 | AF3: =MAX(0,AA3-AC3) -> 0 | AG3: =MAX(0,E3+F3-G3) -> 15000.553 | AH3: =MIN(AF3,AG3) -> 0 | AI3: =G3+AH3 -> 178 | AJ3: =MAX(0,E3+F3-AI3) -> 15000.553 | AK3: =MAX(0,AF3-AH3) -> 0 | AL3: =MAX(0,H3+I3-J3) -> 12632.951 | AM3: =MIN(AK3,AL3) -> 0 | AN3: =J3+AM3 -> 142 | AO3: =MAX(0,H3+I3-AN3) -> 12632.951 | AP3: =MAX(0,AK3-AM3) -> 0 | AQ3: =MAX(0,K3+L3-M3) -> 9655.7394 | AR3: =MIN(AP3,AQ3) -> 0 | AS3: =M3+AR3 -> 112 | AT3: =MAX(0,K3+L3-AS3) -> 9655.7394 | AU3: =MAX(0,AP3-AR3) -> 0 | AV3: =MAX(0,N3+O3-P3) -> 8071.2591 | AW3: =MIN(AU3,AV3) -> 0 | AX3: =P3+AW3 -> 95 | AY3: =MAX(0,N3+O3-AX3) -> 8071.2591 | AZ3: =MAX(0,AU3-AW3) -> 0 | BA3: =MAX(0,Q3+R3-S3) -> 0 | BB3: =MIN(AZ3,BA3) -> 0 | BC3: =S3+BB3 -> 0 | BD3: =MAX(0,Q3+R3-BC3) -> 0 | BE3: =MAX(0,AZ3-BB3) -> 0 | BF3: =MAX(0,T3+U3-V3) -> 0 | BG3: =MIN(BE3,BF3) -> 0 | BH3: =V3+BG3 -> 0 | BI3: =MAX(0,T3+U3-BH3) -> 0 | BJ3: =MAX(0,BE3-BG3) -> 0 | BK3: =MAX(0,W3+X3-Y3) -> 0 | BL3: =MIN(BJ3,BK3) -> 0 | BM3: =Y3+BL3 -> 0 | BN3: =MAX(0,W3+X3-BM3) -> 0 | BO3: =AD3+AI3+AN3+AS3+AX3+BC3+BH3+BM3 -> 1400 | BP3: =C3+F3+I3+L3+O3+R3+U3+X3 -> 386.33555 | BQ3: =AE3+AJ3+AO3+AT3+AY3+BD3+BI3+BN3 -> 71978.636
A4: 3 | B4: =IF(A4=1,IF(OR('My Loans'!$N$14="",'My Loans'!$N$14=0),0,INDIRECT("'My Loans'!$D"&'My Loans'!$N$14)),AE3) -> 26618.133 | C4: =IF(OR('My Loans'!$N$14="",'My Loans'!$N$14=0),0,B4*INDIRECT("'My Loans'!$E"&'My Loans'!$N$14)/12) -> 175.23604 | D4: =IF(OR('My Loans'!$N$14="",'My Loans'!$N$14=0),0,IF(B4<0.005,0,MIN(INDIRECT("'My Loans'!$F"&'My Loans'!$N$14),B4+C4))) -> 410 | E4: =IF(A4=1,IF(OR('My Loans'!$N$15="",'My Loans'!$N$15=0),0,INDIRECT("'My Loans'!$D"&'My Loans'!$N$15)),AJ3) -> 15000.553 | F4: =IF(OR('My Loans'!$N$15="",'My Loans'!$N$15=0),0,E4*INDIRECT("'My Loans'!$E"&'My Loans'!$N$15)/12) -> 77.502856 | G4: =IF(OR('My Loans'!$N$15="",'My Loans'!$N$15=0),0,IF(E4<0.005,0,MIN(INDIRECT("'My Loans'!$F"&'My Loans'!$N$15),E4+F4))) -> 178 | H4: =IF(A4=1,IF(OR('My Loans'!$N$16="",'My Loans'!$N$16=0),0,INDIRECT("'My Loans'!$D"&'My Loans'!$N$16)),AO3) -> 12632.951 | I4: =IF(OR('My Loans'!$N$16="",'My Loans'!$N$16=0),0,H4*INDIRECT("'My Loans'!$E"&'My Loans'!$N$16)/12) -> 57.901027 | J4: =IF(OR('My Loans'!$N$16="",'My Loans'!$N$16=0),0,IF(H4<0.005,0,MIN(INDIRECT("'My Loans'!$F"&'My Loans'!$N$16),H4+I4))) -> 142 | K4: =IF(A4=1,IF(OR('My Loans'!$N$17="",'My Loans'!$N$17=0),0,INDIRECT("'My Loans'!$D"&'My Loans'!$N$17)),AT3) -> 9655.7394 | L4: =IF(OR('My Loans'!$N$17="",'My Loans'!$N$17=0),0,K4*INDIRECT("'My Loans'!$E"&'My Loans'!$N$17)/12) -> 39.427603 | M4: =IF(OR('My Loans'!$N$17="",'My Loans'!$N$17=0),0,IF(K4<0.005,0,MIN(INDIRECT("'My Loans'!$F"&'My Loans'!$N$17),K4+L4))) -> 112 | N4: =IF(A4=1,IF(OR('My Loans'!$N$18="",'My Loans'!$N$18=0),0,INDIRECT("'My Loans'!$D"&'My Loans'!$N$18)),AY3) -> 8071.2591 | O4: =IF(OR('My Loans'!$N$18="",'My Loans'!$N$18=0),0,N4*INDIRECT("'My Loans'!$E"&'My Loans'!$N$18)/12) -> 30.267221 | P4: =IF(OR('My Loans'!$N$18="",'My Loans'!$N$18=0),0,IF(N4<0.005,0,MIN(INDIRECT("'My Loans'!$F"&'My Loans'!$N$18),N4+O4))) -> 95 | Q4: =IF(A4=1,IF(OR('My Loans'!$N$19="",'My Loans'!$N$19=0),0,INDIRECT("'My Loans'!$D"&'My Loans'!$N$19)),BD3) -> 0 | R4: =IF(OR('My Loans'!$N$19="",'My Loans'!$N$19=0),0,Q4*INDIRECT("'My Loans'!$E"&'My Loans'!$N$19)/12) -> 0 | S4: =IF(OR('My Loans'!$N$19="",'My Loans'!$N$19=0),0,IF(Q4<0.005,0,MIN(INDIRECT("'My Loans'!$F"&'My Loans'!$N$19),Q4+R4))) -> 0 | T4: =IF(A4=1,IF(OR('My Loans'!$N$20="",'My Loans'!$N$20=0),0,INDIRECT("'My Loans'!$D"&'My Loans'!$N$20)),BI3) -> 0 | U4: =IF(OR('My Loans'!$N$20="",'My Loans'!$N$20=0),0,T4*INDIRECT("'My Loans'!$E"&'My Loans'!$N$20)/12) -> 0 | V4: =IF(OR('My Loans'!$N$20="",'My Loans'!$N$20=0),0,IF(T4<0.005,0,MIN(INDIRECT("'My Loans'!$F"&'My Loans'!$N$20),T4+U4))) -> 0 | W4: =IF(A4=1,IF(OR('My Loans'!$N$21="",'My Loans'!$N$21=0),0,INDIRECT("'My Loans'!$D"&'My Loans'!$N$21)),BN3) -> 0 | X4: =IF(OR('My Loans'!$N$21="",'My Loans'!$N$21=0),0,W4*INDIRECT("'My Loans'!$E"&'My Loans'!$N$21)/12) -> 0 | Y4: =IF(OR('My Loans'!$N$21="",'My Loans'!$N$21=0),0,IF(W4<0.005,0,MIN(INDIRECT("'My Loans'!$F"&'My Loans'!$N$21),W4+X4))) -> 0 | Z4: ='My Loans'!$B$13-(D4+G4+J4+M4+P4+S4+V4+Y4) -> 463 | AA4: =MAX(0,Z4) -> 463 | AB4: =MAX(0,B4+C4-D4) -> 26383.369 | AC4: =MIN(AA4,AB4) -> 463 | AD4: =D4+AC4 -> 873 | AE4: =MAX(0,B4+C4-AD4) -> 25920.369 | AF4: =MAX(0,AA4-AC4) -> 0 | AG4: =MAX(0,E4+F4-G4) -> 14900.056 | AH4: =MIN(AF4,AG4) -> 0 | AI4: =G4+AH4 -> 178 | AJ4: =MAX(0,E4+F4-AI4) -> 14900.056 | AK4: =MAX(0,AF4-AH4) -> 0 | AL4: =MAX(0,H4+I4-J4) -> 12548.852 | AM4: =MIN(AK4,AL4) -> 0 | AN4: =J4+AM4 -> 142 | AO4: =MAX(0,H4+I4-AN4) -> 12548.852 | AP4: =MAX(0,AK4-AM4) -> 0 | AQ4: =MAX(0,K4+L4-M4) -> 9583.167 | AR4: =MIN(AP4,AQ4) -> 0 | AS4: =M4+AR4 -> 112 | AT4: =MAX(0,K4+L4-AS4) -> 9583.167 | AU4: =MAX(0,AP4-AR4) -> 0 | AV4: =MAX(0,N4+O4-P4) -> 8006.5263 | AW4: =MIN(AU4,AV4) -> 0 | AX4: =P4+AW4 -> 95 | AY4: =MAX(0,N4+O4-AX4) -> 8006.5263 | AZ4: =MAX(0,AU4-AW4) -> 0 | BA4: =MAX(0,Q4+R4-S4) -> 0 | BB4: =MIN(AZ4,BA4) -> 0 | BC4: =S4+BB4 -> 0 | BD4: =MAX(0,Q4+R4-BC4) -> 0 | BE4: =MAX(0,AZ4-BB4) -> 0 | BF4: =MAX(0,T4+U4-V4) -> 0 | BG4: =MIN(BE4,BF4) -> 0 | BH4: =V4+BG4 -> 0 | BI4: =MAX(0,T4+U4-BH4) -> 0 | BJ4: =MAX(0,BE4-BG4) -> 0 | BK4: =MAX(0,W4+X4-Y4) -> 0 | BL4: =MIN(BJ4,BK4) -> 0 | BM4: =Y4+BL4 -> 0 | BN4: =MAX(0,W4+X4-BM4) -> 0 | BO4: =AD4+AI4+AN4+AS4+AX4+BC4+BH4+BM4 -> 1400 | BP4: =C4+F4+I4+L4+O4+R4+U4+X4 -> 380.33475 | BQ4: =AE4+AJ4+AO4+AT4+AY4+BD4+BI4+BN4 -> 70958.97
A5: 4 | B5: =IF(A5=1,IF(OR('My Loans'!$N$14="",'My Loans'!$N$14=0),0,INDIRECT("'My Loans'!$D"&'My Loans'!$N$14)),AE4) -> 25920.369 | C5: =IF(OR('My Loans'!$N$14="",'My Loans'!$N$14=0),0,B5*INDIRECT("'My Loans'!$E"&'My Loans'!$N$14)/12) -> 170.64243 | D5: =IF(OR('My Loans'!$N$14="",'My Loans'!$N$14=0),0,IF(B5<0.005,0,MIN(INDIRECT("'My Loans'!$F"&'My Loans'!$N$14),B5+C5))) -> 410 | E5: =IF(A5=1,IF(OR('My Loans'!$N$15="",'My Loans'!$N$15=0),0,INDIRECT("'My Loans'!$D"&'My Loans'!$N$15)),AJ4) -> 14900.056 | F5: =IF(OR('My Loans'!$N$15="",'My Loans'!$N$15=0),0,E5*INDIRECT("'My Loans'!$E"&'My Loans'!$N$15)/12) -> 76.983621 | G5: =IF(OR('My Loans'!$N$15="",'My Loans'!$N$15=0),0,IF(E5<0.005,0,MIN(INDIRECT("'My Loans'!$F"&'My Loans'!$N$15),E5+F5))) -> 178 | H5: =IF(A5=1,IF(OR('My Loans'!$N$16="",'My Loans'!$N$16=0),0,INDIRECT("'My Loans'!$D"&'My Loans'!$N$16)),AO4) -> 12548.852 | I5: =IF(OR('My Loans'!$N$16="",'My Loans'!$N$16=0),0,H5*INDIRECT("'My Loans'!$E"&'My Loans'!$N$16)/12) -> 57.515574 | J5: =IF(OR('My Loans'!$N$16="",'My Loans'!$N$16=0),0,IF(H5<0.005,0,MIN(INDIRECT("'My Loans'!$F"&'My Loans'!$N$16),H5+I5))) -> 142 | K5: =IF(A5=1,IF(OR('My Loans'!$N$17="",'My Loans'!$N$17=0),0,INDIRECT("'My Loans'!$D"&'My Loans'!$N$17)),AT4) -> 9583.167 | L5: =IF(OR('My Loans'!$N$17="",'My Loans'!$N$17=0),0,K5*INDIRECT("'My Loans'!$E"&'My Loans'!$N$17)/12) -> 39.131265 | M5: =IF(OR('My Loans'!$N$17="",'My Loans'!$N$17=0),0,IF(K5<0.005,0,MIN(INDIRECT("'My Loans'!$F"&'My Loans'!$N$17),K5+L5))) -> 112 | N5: =IF(A5=1,IF(OR('My Loans'!$N$18="",'My Loans'!$N$18=0),0,INDIRECT("'My Loans'!$D"&'My Loans'!$N$18)),AY4) -> 8006.5263 | O5: =IF(OR('My Loans'!$N$18="",'My Loans'!$N$18=0),0,N5*INDIRECT("'My Loans'!$E"&'My Loans'!$N$18)/12) -> 30.024474 | P5: =IF(OR('My Loans'!$N$18="",'My Loans'!$N$18=0),0,IF(N5<0.005,0,MIN(INDIRECT("'My Loans'!$F"&'My Loans'!$N$18),N5+O5))) -> 95 | Q5: =IF(A5=1,IF(OR('My Loans'!$N$19="",'My Loans'!$N$19=0),0,INDIRECT("'My Loans'!$D"&'My Loans'!$N$19)),BD4) -> 0 | R5: =IF(OR('My Loans'!$N$19="",'My Loans'!$N$19=0),0,Q5*INDIRECT("'My Loans'!$E"&'My Loans'!$N$19)/12) -> 0 | S5: =IF(OR('My Loans'!$N$19="",'My Loans'!$N$19=0),0,IF(Q5<0.005,0,MIN(INDIRECT("'My Loans'!$F"&'My Loans'!$N$19),Q5+R5))) -> 0 | T5: =IF(A5=1,IF(OR('My Loans'!$N$20="",'My Loans'!$N$20=0),0,INDIRECT("'My Loans'!$D"&'My Loans'!$N$20)),BI4) -> 0 | U5: =IF(OR('My Loans'!$N$20="",'My Loans'!$N$20=0),0,T5*INDIRECT("'My Loans'!$E"&'My Loans'!$N$20)/12) -> 0 | V5: =IF(OR('My Loans'!$N$20="",'My Loans'!$N$20=0),0,IF(T5<0.005,0,MIN(INDIRECT("'My Loans'!$F"&'My Loans'!$N$20),T5+U5))) -> 0 | W5: =IF(A5=1,IF(OR('My Loans'!$N$21="",'My Loans'!$N$21=0),0,INDIRECT("'My Loans'!$D"&'My Loans'!$N$21)),BN4) -> 0 | X5: =IF(OR('My Loans'!$N$21="",'My Loans'!$N$21=0),0,W5*INDIRECT("'My Loans'!$E"&'My Loans'!$N$21)/12) -> 0 | Y5: =IF(OR('My Loans'!$N$21="",'My Loans'!$N$21=0),0,IF(W5<0.005,0,MIN(INDIRECT("'My Loans'!$F"&'My Loans'!$N$21),W5+X5))) -> 0 | Z5: ='My Loans'!$B$13-(D5+G5+J5+M5+P5+S5+V5+Y5) -> 463 | AA5: =MAX(0,Z5) -> 463 | AB5: =MAX(0,B5+C5-D5) -> 25681.011 | AC5: =MIN(AA5,AB5) -> 463 | AD5: =D5+AC5 -> 873 | AE5: =MAX(0,B5+C5-AD5) -> 25218.011 | AF5: =MAX(0,AA5-AC5) -> 0 | AG5: =MAX(0,E5+F5-G5) -> 14799.039 | AH5: =MIN(AF5,AG5) -> 0 | AI5: =G5+AH5 -> 178 | AJ5: =MAX(0,E5+F5-AI5) -> 14799.039 | AK5: =MAX(0,AF5-AH5) -> 0 | AL5: =MAX(0,H5+I5-J5) -> 12464.368 | AM5: =MIN(AK5,AL5) -> 0 | AN5: =J5+AM5 -> 142 | AO5: =MAX(0,H5+I5-AN5) -> 12464.368 | AP5: =MAX(0,AK5-AM5) -> 0 | AQ5: =MAX(0,K5+L5-M5) -> 9510.2983 | AR5: =MIN(AP5,AQ5) -> 0 | AS5: =M5+AR5 -> 112 | AT5: =MAX(0,K5+L5-AS5) -> 9510.2983 | AU5: =MAX(0,AP5-AR5) -> 0 | AV5: =MAX(0,N5+O5-P5) -> 7941.5508 | AW5: =MIN(AU5,AV5) -> 0 | AX5: =P5+AW5 -> 95 | AY5: =MAX(0,N5+O5-AX5) -> 7941.5508 | AZ5: =MAX(0,AU5-AW5) -> 0 | BA5: =MAX(0,Q5+R5-S5) -> 0 | BB5: =MIN(AZ5,BA5) -> 0 | BC5: =S5+BB5 -> 0 | BD5: =MAX(0,Q5+R5-BC5) -> 0 | BE5: =MAX(0,AZ5-BB5) -> 0 | BF5: =MAX(0,T5+U5-V5) -> 0 | BG5: =MIN(BE5,BF5) -> 0 | BH5: =V5+BG5 -> 0 | BI5: =MAX(0,T5+U5-BH5) -> 0 | BJ5: =MAX(0,BE5-BG5) -> 0 | BK5: =MAX(0,W5+X5-Y5) -> 0 | BL5: =MIN(BJ5,BK5) -> 0 | BM5: =Y5+BL5 -> 0 | BN5: =MAX(0,W5+X5-BM5) -> 0 | BO5: =AD5+AI5+AN5+AS5+AX5+BC5+BH5+BM5 -> 1400 | BP5: =C5+F5+I5+L5+O5+R5+U5+X5 -> 374.29736 | BQ5: =AE5+AJ5+AO5+AT5+AY5+BD5+BI5+BN5 -> 69933.268
A6: 5 | B6: =IF(A6=1,IF(OR('My Loans'!$N$14="",'My Loans'!$N$14=0),0,INDIRECT("'My Loans'!$D"&'My Loans'!$N$14)),AE5) -> 25218.011 | C6: =IF(OR('My Loans'!$N$14="",'My Loans'!$N$14=0),0,B6*INDIRECT("'My Loans'!$E"&'My Loans'!$N$14)/12) -> 166.01858 | D6: =IF(OR('My Loans'!$N$14="",'My Loans'!$N$14=0),0,IF(B6<0.005,0,MIN(INDIRECT("'My Loans'!$F"&'My Loans'!$N$14),B6+C6))) -> 410 | E6: =IF(A6=1,IF(OR('My Loans'!$N$15="",'My Loans'!$N$15=0),0,INDIRECT("'My Loans'!$D"&'My Loans'!$N$15)),AJ5) -> 14799.039 | F6: =IF(OR('My Loans'!$N$15="",'My Loans'!$N$15=0),0,E6*INDIRECT("'My Loans'!$E"&'My Loans'!$N$15)/12) -> 76.461703 | G6: =IF(OR('My Loans'!$N$15="",'My Loans'!$N$15=0),0,IF(E6<0.005,0,MIN(INDIRECT("'My Loans'!$F"&'My Loans'!$N$15),E6+F6))) -> 178 | H6: =IF(A6=1,IF(OR('My Loans'!$N$16="",'My Loans'!$N$16=0),0,INDIRECT("'My Loans'!$D"&'My Loans'!$N$16)),AO5) -> 12464.368 | I6: =IF(OR('My Loans'!$N$16="",'My Loans'!$N$16=0),0,H6*INDIRECT("'My Loans'!$E"&'My Loans'!$N$16)/12) -> 57.128353 | J6: =IF(OR('My Loans'!$N$16="",'My Loans'!$N$16=0),0,IF(H6<0.005,0,MIN(INDIRECT("'My Loans'!$F"&'My Loans'!$N$16),H6+I6))) -> 142 | K6: =IF(A6=1,IF(OR('My Loans'!$N$17="",'My Loans'!$N$17=0),0,INDIRECT("'My Loans'!$D"&'My Loans'!$N$17)),AT5) -> 9510.2983 | L6: =IF(OR('My Loans'!$N$17="",'My Loans'!$N$17=0),0,K6*INDIRECT("'My Loans'!$E"&'My Loans'!$N$17)/12) -> 38.833718 | M6: =IF(OR('My Loans'!$N$17="",'My Loans'!$N$17=0),0,IF(K6<0.005,0,MIN(INDIRECT("'My Loans'!$F"&'My Loans'!$N$17),K6+L6))) -> 112 | N6: =IF(A6=1,IF(OR('My Loans'!$N$18="",'My Loans'!$N$18=0),0,INDIRECT("'My Loans'!$D"&'My Loans'!$N$18)),AY5) -> 7941.5508 | O6: =IF(OR('My Loans'!$N$18="",'My Loans'!$N$18=0),0,N6*INDIRECT("'My Loans'!$E"&'My Loans'!$N$18)/12) -> 29.780815 | P6: =IF(OR('My Loans'!$N$18="",'My Loans'!$N$18=0),0,IF(N6<0.005,0,MIN(INDIRECT("'My Loans'!$F"&'My Loans'!$N$18),N6+O6))) -> 95 | Q6: =IF(A6=1,IF(OR('My Loans'!$N$19="",'My Loans'!$N$19=0),0,INDIRECT("'My Loans'!$D"&'My Loans'!$N$19)),BD5) -> 0 | R6: =IF(OR('My Loans'!$N$19="",'My Loans'!$N$19=0),0,Q6*INDIRECT("'My Loans'!$E"&'My Loans'!$N$19)/12) -> 0 | S6: =IF(OR('My Loans'!$N$19="",'My Loans'!$N$19=0),0,IF(Q6<0.005,0,MIN(INDIRECT("'My Loans'!$F"&'My Loans'!$N$19),Q6+R6))) -> 0 | T6: =IF(A6=1,IF(OR('My Loans'!$N$20="",'My Loans'!$N$20=0),0,INDIRECT("'My Loans'!$D"&'My Loans'!$N$20)),BI5) -> 0 | U6: =IF(OR('My Loans'!$N$20="",'My Loans'!$N$20=0),0,T6*INDIRECT("'My Loans'!$E"&'My Loans'!$N$20)/12) -> 0 | V6: =IF(OR('My Loans'!$N$20="",'My Loans'!$N$20=0),0,IF(T6<0.005,0,MIN(INDIRECT("'My Loans'!$F"&'My Loans'!$N$20),T6+U6))) -> 0 | W6: =IF(A6=1,IF(OR('My Loans'!$N$21="",'My Loans'!$N$21=0),0,INDIRECT("'My Loans'!$D"&'My Loans'!$N$21)),BN5) -> 0 | X6: =IF(OR('My Loans'!$N$21="",'My Loans'!$N$21=0),0,W6*INDIRECT("'My Loans'!$E"&'My Loans'!$N$21)/12) -> 0 | Y6: =IF(OR('My Loans'!$N$21="",'My Loans'!$N$21=0),0,IF(W6<0.005,0,MIN(INDIRECT("'My Loans'!$F"&'My Loans'!$N$21),W6+X6))) -> 0 | Z6: ='My Loans'!$B$13-(D6+G6+J6+M6+P6+S6+V6+Y6) -> 463 | AA6: =MAX(0,Z6) -> 463 | AB6: =MAX(0,B6+C6-D6) -> 24974.03 | AC6: =MIN(AA6,AB6) -> 463 | AD6: =D6+AC6 -> 873 | AE6: =MAX(0,B6+C6-AD6) -> 24511.03 | AF6: =MAX(0,AA6-AC6) -> 0 | AG6: =MAX(0,E6+F6-G6) -> 14697.501 | AH6: =MIN(AF6,AG6) -> 0 | AI6: =G6+AH6 -> 178 | AJ6: =MAX(0,E6+F6-AI6) -> 14697.501 | AK6: =MAX(0,AF6-AH6) -> 0 | AL6: =MAX(0,H6+I6-J6) -> 12379.496 | AM6: =MIN(AK6,AL6) -> 0 | AN6: =J6+AM6 -> 142 | AO6: =MAX(0,H6+I6-AN6) -> 12379.496 | AP6: =MAX(0,AK6-AM6) -> 0 | AQ6: =MAX(0,K6+L6-M6) -> 9437.132 | AR6: =MIN(AP6,AQ6) -> 0 | AS6: =M6+AR6 -> 112 | AT6: =MAX(0,K6+L6-AS6) -> 9437.132 | AU6: =MAX(0,AP6-AR6) -> 0 | AV6: =MAX(0,N6+O6-P6) -> 7876.3316 | AW6: =MIN(AU6,AV6) -> 0 | AX6: =P6+AW6 -> 95 | AY6: =MAX(0,N6+O6-AX6) -> 7876.3316 | AZ6: =MAX(0,AU6-AW6) -> 0 | BA6: =MAX(0,Q6+R6-S6) -> 0 | BB6: =MIN(AZ6,BA6) -> 0 | BC6: =S6+BB6 -> 0 | BD6: =MAX(0,Q6+R6-BC6) -> 0 | BE6: =MAX(0,AZ6-BB6) -> 0 | BF6: =MAX(0,T6+U6-V6) -> 0 | BG6: =MIN(BE6,BF6) -> 0 | BH6: =V6+BG6 -> 0 | BI6: =MAX(0,T6+U6-BH6) -> 0 | BJ6: =MAX(0,BE6-BG6) -> 0 | BK6: =MAX(0,W6+X6-Y6) -> 0 | BL6: =MIN(BJ6,BK6) -> 0 | BM6: =Y6+BL6 -> 0 | BN6: =MAX(0,W6+X6-BM6) -> 0 | BO6: =AD6+AI6+AN6+AS6+AX6+BC6+BH6+BM6 -> 1400 | BP6: =C6+F6+I6+L6+O6+R6+U6+X6 -> 368.22316 | BQ6: =AE6+AJ6+AO6+AT6+AY6+BD6+BI6+BN6 -> 68901.491
A7: 6 | B7: =IF(A7=1,IF(OR('My Loans'!$N$14="",'My Loans'!$N$14=0),0,INDIRECT("'My Loans'!$D"&'My Loans'!$N$14)),AE6) -> 24511.03 | C7: =IF(OR('My Loans'!$N$14="",'My Loans'!$N$14=0),0,B7*INDIRECT("'My Loans'!$E"&'My Loans'!$N$14)/12) -> 161.36428 | D7: =IF(OR('My Loans'!$N$14="",'My Loans'!$N$14=0),0,IF(B7<0.005,0,MIN(INDIRECT("'My Loans'!$F"&'My Loans'!$N$14),B7+C7))) -> 410 | E7: =IF(A7=1,IF(OR('My Loans'!$N$15="",'My Loans'!$N$15=0),0,INDIRECT("'My Loans'!$D"&'My Loans'!$N$15)),AJ6) -> 14697.501 | F7: =IF(OR('My Loans'!$N$15="",'My Loans'!$N$15=0),0,E7*INDIRECT("'My Loans'!$E"&'My Loans'!$N$15)/12) -> 75.937088 | G7: =IF(OR('My Loans'!$N$15="",'My Loans'!$N$15=0),0,IF(E7<0.005,0,MIN(INDIRECT("'My Loans'!$F"&'My Loans'!$N$15),E7+F7))) -> 178 | H7: =IF(A7=1,IF(OR('My Loans'!$N$16="",'My Loans'!$N$16=0),0,INDIRECT("'My Loans'!$D"&'My Loans'!$N$16)),AO6) -> 12379.496 | I7: =IF(OR('My Loans'!$N$16="",'My Loans'!$N$16=0),0,H7*INDIRECT("'My Loans'!$E"&'My Loans'!$N$16)/12) -> 56.739358 | J7: =IF(OR('My Loans'!$N$16="",'My Loans'!$N$16=0),0,IF(H7<0.005,0,MIN(INDIRECT("'My Loans'!$F"&'My Loans'!$N$16),H7+I7))) -> 142 | K7: =IF(A7=1,IF(OR('My Loans'!$N$17="",'My Loans'!$N$17=0),0,INDIRECT("'My Loans'!$D"&'My Loans'!$N$17)),AT6) -> 9437.132 | L7: =IF(OR('My Loans'!$N$17="",'My Loans'!$N$17=0),0,K7*INDIRECT("'My Loans'!$E"&'My Loans'!$N$17)/12) -> 38.534956 | M7: =IF(OR('My Loans'!$N$17="",'My Loans'!$N$17=0),0,IF(K7<0.005,0,MIN(INDIRECT("'My Loans'!$F"&'My Loans'!$N$17),K7+L7))) -> 112 | N7: =IF(A7=1,IF(OR('My Loans'!$N$18="",'My Loans'!$N$18=0),0,INDIRECT("'My Loans'!$D"&'My Loans'!$N$18)),AY6) -> 7876.3316 | O7: =IF(OR('My Loans'!$N$18="",'My Loans'!$N$18=0),0,N7*INDIRECT("'My Loans'!$E"&'My Loans'!$N$18)/12) -> 29.536243 | P7: =IF(OR('My Loans'!$N$18="",'My Loans'!$N$18=0),0,IF(N7<0.005,0,MIN(INDIRECT("'My Loans'!$F"&'My Loans'!$N$18),N7+O7))) -> 95 | Q7: =IF(A7=1,IF(OR('My Loans'!$N$19="",'My Loans'!$N$19=0),0,INDIRECT("'My Loans'!$D"&'My Loans'!$N$19)),BD6) -> 0 | R7: =IF(OR('My Loans'!$N$19="",'My Loans'!$N$19=0),0,Q7*INDIRECT("'My Loans'!$E"&'My Loans'!$N$19)/12) -> 0 | S7: =IF(OR('My Loans'!$N$19="",'My Loans'!$N$19=0),0,IF(Q7<0.005,0,MIN(INDIRECT("'My Loans'!$F"&'My Loans'!$N$19),Q7+R7))) -> 0 | T7: =IF(A7=1,IF(OR('My Loans'!$N$20="",'My Loans'!$N$20=0),0,INDIRECT("'My Loans'!$D"&'My Loans'!$N$20)),BI6) -> 0 | U7: =IF(OR('My Loans'!$N$20="",'My Loans'!$N$20=0),0,T7*INDIRECT("'My Loans'!$E"&'My Loans'!$N$20)/12) -> 0 | V7: =IF(OR('My Loans'!$N$20="",'My Loans'!$N$20=0),0,IF(T7<0.005,0,MIN(INDIRECT("'My Loans'!$F"&'My Loans'!$N$20),T7+U7))) -> 0 | W7: =IF(A7=1,IF(OR('My Loans'!$N$21="",'My Loans'!$N$21=0),0,INDIRECT("'My Loans'!$D"&'My Loans'!$N$21)),BN6) -> 0 | X7: =IF(OR('My Loans'!$N$21="",'My Loans'!$N$21=0),0,W7*INDIRECT("'My Loans'!$E"&'My Loans'!$N$21)/12) -> 0 | Y7: =IF(OR('My Loans'!$N$21="",'My Loans'!$N$21=0),0,IF(W7<0.005,0,MIN(INDIRECT("'My Loans'!$F"&'My Loans'!$N$21),W7+X7))) -> 0 | Z7: ='My Loans'!$B$13-(D7+G7+J7+M7+P7+S7+V7+Y7) -> 463 | AA7: =MAX(0,Z7) -> 463 | AB7: =MAX(0,B7+C7-D7) -> 24262.394 | AC7: =MIN(AA7,AB7) -> 463 | AD7: =D7+AC7 -> 873 | AE7: =MAX(0,B7+C7-AD7) -> 23799.394 | AF7: =MAX(0,AA7-AC7) -> 0 | AG7: =MAX(0,E7+F7-G7) -> 14595.438 | AH7: =MIN(AF7,AG7) -> 0 | AI7: =G7+AH7 -> 178 | AJ7: =MAX(0,E7+F7-AI7) -> 14595.438 | AK7: =MAX(0,AF7-AH7) -> 0 | AL7: =MAX(0,H7+I7-J7) -> 12294.236 | AM7: =MIN(AK7,AL7) -> 0 | AN7: =J7+AM7 -> 142 | AO7: =MAX(0,H7+I7-AN7) -> 12294.236 | AP7: =MAX(0,AK7-AM7) -> 0 | AQ7: =MAX(0,K7+L7-M7) -> 9363.6669 | AR7: =MIN(AP7,AQ7) -> 0 | AS7: =M7+AR7 -> 112 | AT7: =MAX(0,K7+L7-AS7) -> 9363.6669 | AU7: =MAX(0,AP7-AR7) -> 0 | AV7: =MAX(0,N7+O7-P7) -> 7810.8678 | AW7: =MIN(AU7,AV7) -> 0 | AX7: =P7+AW7 -> 95 | AY7: =MAX(0,N7+O7-AX7) -> 7810.8678 | AZ7: =MAX(0,AU7-AW7) -> 0 | BA7: =MAX(0,Q7+R7-S7) -> 0 | BB7: =MIN(AZ7,BA7) -> 0 | BC7: =S7+BB7 -> 0 | BD7: =MAX(0,Q7+R7-BC7) -> 0 | BE7: =MAX(0,AZ7-BB7) -> 0 | BF7: =MAX(0,T7+U7-V7) -> 0 | BG7: =MIN(BE7,BF7) -> 0 | BH7: =V7+BG7 -> 0 | BI7: =MAX(0,T7+U7-BH7) -> 0 | BJ7: =MAX(0,BE7-BG7) -> 0 | BK7: =MAX(0,W7+X7-Y7) -> 0 | BL7: =MIN(BJ7,BK7) -> 0 | BM7: =Y7+BL7 -> 0 | BN7: =MAX(0,W7+X7-BM7) -> 0 | BO7: =AD7+AI7+AN7+AS7+AX7+BC7+BH7+BM7 -> 1400 | BP7: =C7+F7+I7+L7+O7+R7+U7+X7 -> 362.11193 | BQ7: =AE7+AJ7+AO7+AT7+AY7+BD7+BI7+BN7 -> 67863.603
A8: 7 | B8: =IF(A8=1,IF(OR('My Loans'!$N$14="",'My Loans'!$N$14=0),0,INDIRECT("'My Loans'!$D"&'My Loans'!$N$14)),AE7) -> 23799.394 | C8: =IF(OR('My Loans'!$N$14="",'My Loans'!$N$14=0),0,B8*INDIRECT("'My Loans'!$E"&'My Loans'!$N$14)/12) -> 156.67935 | D8: =IF(OR('My Loans'!$N$14="",'My Loans'!$N$14=0),0,IF(B8<0.005,0,MIN(INDIRECT("'My Loans'!$F"&'My Loans'!$N$14),B8+C8))) -> 410 | E8: =IF(A8=1,IF(OR('My Loans'!$N$15="",'My Loans'!$N$15=0),0,INDIRECT("'My Loans'!$D"&'My Loans'!$N$15)),AJ7) -> 14595.438 | F8: =IF(OR('My Loans'!$N$15="",'My Loans'!$N$15=0),0,E8*INDIRECT("'My Loans'!$E"&'My Loans'!$N$15)/12) -> 75.409763 | G8: =IF(OR('My Loans'!$N$15="",'My Loans'!$N$15=0),0,IF(E8<0.005,0,MIN(INDIRECT("'My Loans'!$F"&'My Loans'!$N$15),E8+F8))) -> 178 | H8: =IF(A8=1,IF(OR('My Loans'!$N$16="",'My Loans'!$N$16=0),0,INDIRECT("'My Loans'!$D"&'My Loans'!$N$16)),AO7) -> 12294.236 | I8: =IF(OR('My Loans'!$N$16="",'My Loans'!$N$16=0),0,H8*INDIRECT("'My Loans'!$E"&'My Loans'!$N$16)/12) -> 56.34858 | J8: =IF(OR('My Loans'!$N$16="",'My Loans'!$N$16=0),0,IF(H8<0.005,0,MIN(INDIRECT("'My Loans'!$F"&'My Loans'!$N$16),H8+I8))) -> 142 | K8: =IF(A8=1,IF(OR('My Loans'!$N$17="",'My Loans'!$N$17=0),0,INDIRECT("'My Loans'!$D"&'My Loans'!$N$17)),AT7) -> 9363.6669 | L8: =IF(OR('My Loans'!$N$17="",'My Loans'!$N$17=0),0,K8*INDIRECT("'My Loans'!$E"&'My Loans'!$N$17)/12) -> 38.234973 | M8: =IF(OR('My Loans'!$N$17="",'My Loans'!$N$17=0),0,IF(K8<0.005,0,MIN(INDIRECT("'My Loans'!$F"&'My Loans'!$N$17),K8+L8))) -> 112 | N8: =IF(A8=1,IF(OR('My Loans'!$N$18="",'My Loans'!$N$18=0),0,INDIRECT("'My Loans'!$D"&'My Loans'!$N$18)),AY7) -> 7810.8678 | O8: =IF(OR('My Loans'!$N$18="",'My Loans'!$N$18=0),0,N8*INDIRECT("'My Loans'!$E"&'My Loans'!$N$18)/12) -> 29.290754 | P8: =IF(OR('My Loans'!$N$18="",'My Loans'!$N$18=0),0,IF(N8<0.005,0,MIN(INDIRECT("'My Loans'!$F"&'My Loans'!$N$18),N8+O8))) -> 95 | Q8: =IF(A8=1,IF(OR('My Loans'!$N$19="",'My Loans'!$N$19=0),0,INDIRECT("'My Loans'!$D"&'My Loans'!$N$19)),BD7) -> 0 | R8: =IF(OR('My Loans'!$N$19="",'My Loans'!$N$19=0),0,Q8*INDIRECT("'My Loans'!$E"&'My Loans'!$N$19)/12) -> 0 | S8: =IF(OR('My Loans'!$N$19="",'My Loans'!$N$19=0),0,IF(Q8<0.005,0,MIN(INDIRECT("'My Loans'!$F"&'My Loans'!$N$19),Q8+R8))) -> 0 | T8: =IF(A8=1,IF(OR('My Loans'!$N$20="",'My Loans'!$N$20=0),0,INDIRECT("'My Loans'!$D"&'My Loans'!$N$20)),BI7) -> 0 | U8: =IF(OR('My Loans'!$N$20="",'My Loans'!$N$20=0),0,T8*INDIRECT("'My Loans'!$E"&'My Loans'!$N$20)/12) -> 0 | V8: =IF(OR('My Loans'!$N$20="",'My Loans'!$N$20=0),0,IF(T8<0.005,0,MIN(INDIRECT("'My Loans'!$F"&'My Loans'!$N$20),T8+U8))) -> 0 | W8: =IF(A8=1,IF(OR('My Loans'!$N$21="",'My Loans'!$N$21=0),0,INDIRECT("'My Loans'!$D"&'My Loans'!$N$21)),BN7) -> 0 | X8: =IF(OR('My Loans'!$N$21="",'My Loans'!$N$21=0),0,W8*INDIRECT("'My Loans'!$E"&'My Loans'!$N$21)/12) -> 0 | Y8: =IF(OR('My Loans'!$N$21="",'My Loans'!$N$21=0),0,IF(W8<0.005,0,MIN(INDIRECT("'My Loans'!$F"&'My Loans'!$N$21),W8+X8))) -> 0 | Z8: ='My Loans'!$B$13-(D8+G8+J8+M8+P8+S8+V8+Y8) -> 463 | AA8: =MAX(0,Z8) -> 463 | AB8: =MAX(0,B8+C8-D8) -> 23546.074 | AC8: =MIN(AA8,AB8) -> 463 | AD8: =D8+AC8 -> 873 | AE8: =MAX(0,B8+C8-AD8) -> 23083.074 | AF8: =MAX(0,AA8-AC8) -> 0 | AG8: =MAX(0,E8+F8-G8) -> 14492.848 | AH8: =MIN(AF8,AG8) -> 0 | AI8: =G8+AH8 -> 178 | AJ8: =MAX(0,E8+F8-AI8) -> 14492.848 | AK8: =MAX(0,AF8-AH8) -> 0 | AL8: =MAX(0,H8+I8-J8) -> 12208.584 | AM8: =MIN(AK8,AL8) -> 0 | AN8: =J8+AM8 -> 142 | AO8: =MAX(0,H8+I8-AN8) -> 12208.584 | AP8: =MAX(0,AK8-AM8) -> 0 | AQ8: =MAX(0,K8+L8-M8) -> 9289.9019 | AR8: =MIN(AP8,AQ8) -> 0 | AS8: =M8+AR8 -> 112 | AT8: =MAX(0,K8+L8-AS8) -> 9289.9019 | AU8: =MAX(0,AP8-AR8) -> 0 | AV8: =MAX(0,N8+O8-P8) -> 7745.1586 | AW8: =MIN(AU8,AV8) -> 0 | AX8: =P8+AW8 -> 95 | AY8: =MAX(0,N8+O8-AX8) -> 7745.1586 | AZ8: =MAX(0,AU8-AW8) -> 0 | BA8: =MAX(0,Q8+R8-S8) -> 0 | BB8: =MIN(AZ8,BA8) -> 0 | BC8: =S8+BB8 -> 0 | BD8: =MAX(0,Q8+R8-BC8) -> 0 | BE8: =MAX(0,AZ8-BB8) -> 0 | BF8: =MAX(0,T8+U8-V8) -> 0 | BG8: =MIN(BE8,BF8) -> 0 | BH8: =V8+BG8 -> 0 | BI8: =MAX(0,T8+U8-BH8) -> 0 | BJ8: =MAX(0,BE8-BG8) -> 0 | BK8: =MAX(0,W8+X8-Y8) -> 0 | BL8: =MIN(BJ8,BK8) -> 0 | BM8: =Y8+BL8 -> 0 | BN8: =MAX(0,W8+X8-BM8) -> 0 | BO8: =AD8+AI8+AN8+AS8+AX8+BC8+BH8+BM8 -> 1400 | BP8: =C8+F8+I8+L8+O8+R8+U8+X8 -> 355.96342 | BQ8: =AE8+AJ8+AO8+AT8+AY8+BD8+BI8+BN8 -> 66819.566
A9: 8 | B9: =IF(A9=1,IF(OR('My Loans'!$N$14="",'My Loans'!$N$14=0),0,INDIRECT("'My Loans'!$D"&'My Loans'!$N$14)),AE8) -> 23083.074 | C9: =IF(OR('My Loans'!$N$14="",'My Loans'!$N$14=0),0,B9*INDIRECT("'My Loans'!$E"&'My Loans'!$N$14)/12) -> 151.96357 | D9: =IF(OR('My Loans'!$N$14="",'My Loans'!$N$14=0),0,IF(B9<0.005,0,MIN(INDIRECT("'My Loans'!$F"&'My Loans'!$N$14),B9+C9))) -> 410 | E9: =IF(A9=1,IF(OR('My Loans'!$N$15="",'My Loans'!$N$15=0),0,INDIRECT("'My Loans'!$D"&'My Loans'!$N$15)),AJ8) -> 14492.848 | F9: =IF(OR('My Loans'!$N$15="",'My Loans'!$N$15=0),0,E9*INDIRECT("'My Loans'!$E"&'My Loans'!$N$15)/12) -> 74.879714 | G9: =IF(OR('My Loans'!$N$15="",'My Loans'!$N$15=0),0,IF(E9<0.005,0,MIN(INDIRECT("'My Loans'!$F"&'My Loans'!$N$15),E9+F9))) -> 178 | H9: =IF(A9=1,IF(OR('My Loans'!$N$16="",'My Loans'!$N$16=0),0,INDIRECT("'My Loans'!$D"&'My Loans'!$N$16)),AO8) -> 12208.584 | I9: =IF(OR('My Loans'!$N$16="",'My Loans'!$N$16=0),0,H9*INDIRECT("'My Loans'!$E"&'My Loans'!$N$16)/12) -> 55.956011 | J9: =IF(OR('My Loans'!$N$16="",'My Loans'!$N$16=0),0,IF(H9<0.005,0,MIN(INDIRECT("'My Loans'!$F"&'My Loans'!$N$16),H9+I9))) -> 142 | K9: =IF(A9=1,IF(OR('My Loans'!$N$17="",'My Loans'!$N$17=0),0,INDIRECT("'My Loans'!$D"&'My Loans'!$N$17)),AT8) -> 9289.9019 | L9: =IF(OR('My Loans'!$N$17="",'My Loans'!$N$17=0),0,K9*INDIRECT("'My Loans'!$E"&'My Loans'!$N$17)/12) -> 37.933766 | M9: =IF(OR('My Loans'!$N$17="",'My Loans'!$N$17=0),0,IF(K9<0.005,0,MIN(INDIRECT("'My Loans'!$F"&'My Loans'!$N$17),K9+L9))) -> 112 | N9: =IF(A9=1,IF(OR('My Loans'!$N$18="",'My Loans'!$N$18=0),0,INDIRECT("'My Loans'!$D"&'My Loans'!$N$18)),AY8) -> 7745.1586 | O9: =IF(OR('My Loans'!$N$18="",'My Loans'!$N$18=0),0,N9*INDIRECT("'My Loans'!$E"&'My Loans'!$N$18)/12) -> 29.044345 | P9: =IF(OR('My Loans'!$N$18="",'My Loans'!$N$18=0),0,IF(N9<0.005,0,MIN(INDIRECT("'My Loans'!$F"&'My Loans'!$N$18),N9+O9))) -> 95 | Q9: =IF(A9=1,IF(OR('My Loans'!$N$19="",'My Loans'!$N$19=0),0,INDIRECT("'My Loans'!$D"&'My Loans'!$N$19)),BD8) -> 0 | R9: =IF(OR('My Loans'!$N$19="",'My Loans'!$N$19=0),0,Q9*INDIRECT("'My Loans'!$E"&'My Loans'!$N$19)/12) -> 0 | S9: =IF(OR('My Loans'!$N$19="",'My Loans'!$N$19=0),0,IF(Q9<0.005,0,MIN(INDIRECT("'My Loans'!$F"&'My Loans'!$N$19),Q9+R9))) -> 0 | T9: =IF(A9=1,IF(OR('My Loans'!$N$20="",'My Loans'!$N$20=0),0,INDIRECT("'My Loans'!$D"&'My Loans'!$N$20)),BI8) -> 0 | U9: =IF(OR('My Loans'!$N$20="",'My Loans'!$N$20=0),0,T9*INDIRECT("'My Loans'!$E"&'My Loans'!$N$20)/12) -> 0 | V9: =IF(OR('My Loans'!$N$20="",'My Loans'!$N$20=0),0,IF(T9<0.005,0,MIN(INDIRECT("'My Loans'!$F"&'My Loans'!$N$20),T9+U9))) -> 0 | W9: =IF(A9=1,IF(OR('My Loans'!$N$21="",'My Loans'!$N$21=0),0,INDIRECT("'My Loans'!$D"&'My Loans'!$N$21)),BN8) -> 0 | X9: =IF(OR('My Loans'!$N$21="",'My Loans'!$N$21=0),0,W9*INDIRECT("'My Loans'!$E"&'My Loans'!$N$21)/12) -> 0 | Y9: =IF(OR('My Loans'!$N$21="",'My Loans'!$N$21=0),0,IF(W9<0.005,0,MIN(INDIRECT("'My Loans'!$F"&'My Loans'!$N$21),W9+X9))) -> 0 | Z9: ='My Loans'!$B$13-(D9+G9+J9+M9+P9+S9+V9+Y9) -> 463 | AA9: =MAX(0,Z9) -> 463 | AB9: =MAX(0,B9+C9-D9) -> 22825.037 | AC9: =MIN(AA9,AB9) -> 463 | AD9: =D9+AC9 -> 873 | AE9: =MAX(0,B9+C9-AD9) -> 22362.037 | AF9: =MAX(0,AA9-AC9) -> 0 | AG9: =MAX(0,E9+F9-G9) -> 14389.727 | AH9: =MIN(AF9,AG9) -> 0 | AI9: =G9+AH9 -> 178 | AJ9: =MAX(0,E9+F9-AI9) -> 14389.727 | AK9: =MAX(0,AF9-AH9) -> 0 | AL9: =MAX(0,H9+I9-J9) -> 12122.54 | AM9: =MIN(AK9,AL9) -> 0 | AN9: =J9+AM9 -> 142 | AO9: =MAX(0,H9+I9-AN9) -> 12122.54 | AP9: =MAX(0,AK9-AM9) -> 0 | AQ9: =MAX(0,K9+L9-M9) -> 9215.8357 | AR9: =MIN(AP9,AQ9) -> 0 | AS9: =M9+AR9 -> 112 | AT9: =MAX(0,K9+L9-AS9) -> 9215.8357 | AU9: =MAX(0,AP9-AR9) -> 0 | AV9: =MAX(0,N9+O9-P9) -> 7679.2029 | AW9: =MIN(AU9,AV9) -> 0 | AX9: =P9+AW9 -> 95 | AY9: =MAX(0,N9+O9-AX9) -> 7679.2029 | AZ9: =MAX(0,AU9-AW9) -> 0 | BA9: =MAX(0,Q9+R9-S9) -> 0 | BB9: =MIN(AZ9,BA9) -> 0 | BC9: =S9+BB9 -> 0 | BD9: =MAX(0,Q9+R9-BC9) -> 0 | BE9: =MAX(0,AZ9-BB9) -> 0 | BF9: =MAX(0,T9+U9-V9) -> 0 | BG9: =MIN(BE9,BF9) -> 0 | BH9: =V9+BG9 -> 0 | BI9: =MAX(0,T9+U9-BH9) -> 0 | BJ9: =MAX(0,BE9-BG9) -> 0 | BK9: =MAX(0,W9+X9-Y9) -> 0 | BL9: =MIN(BJ9,BK9) -> 0 | BM9: =Y9+BL9 -> 0 | BN9: =MAX(0,W9+X9-BM9) -> 0 | BO9: =AD9+AI9+AN9+AS9+AX9+BC9+BH9+BM9 -> 1400 | BP9: =C9+F9+I9+L9+O9+R9+U9+X9 -> 349.7774 | BQ9: =AE9+AJ9+AO9+AT9+AY9+BD9+BI9+BN9 -> 65769.344
A10: 9 | B10: =IF(A10=1,IF(OR('My Loans'!$N$14="",'My Loans'!$N$14=0),0,INDIRECT("'My Loans'!$D"&'My Loans'!$N$14)),AE9) -> 22362.037 | C10: =IF(OR('My Loans'!$N$14="",'My Loans'!$N$14=0),0,B10*INDIRECT("'My Loans'!$E"&'My Loans'!$N$14)/12) -> 147.21674 | D10: =IF(OR('My Loans'!$N$14="",'My Loans'!$N$14=0),0,IF(B10<0.005,0,MIN(INDIRECT("'My Loans'!$F"&'My Loans'!$N$14),B10+C10))) -> 410 | E10: =IF(A10=1,IF(OR('My Loans'!$N$15="",'My Loans'!$N$15=0),0,INDIRECT("'My Loans'!$D"&'My Loans'!$N$15)),AJ9) -> 14389.727 | F10: =IF(OR('My Loans'!$N$15="",'My Loans'!$N$15=0),0,E10*INDIRECT("'My Loans'!$E"&'My Loans'!$N$15)/12) -> 74.346925 | G10: =IF(OR('My Loans'!$N$15="",'My Loans'!$N$15=0),0,IF(E10<0.005,0,MIN(INDIRECT("'My Loans'!$F"&'My Loans'!$N$15),E10+F10))) -> 178 | H10: =IF(A10=1,IF(OR('My Loans'!$N$16="",'My Loans'!$N$16=0),0,INDIRECT("'My Loans'!$D"&'My Loans'!$N$16)),AO9) -> 12122.54 | I10: =IF(OR('My Loans'!$N$16="",'My Loans'!$N$16=0),0,H10*INDIRECT("'My Loans'!$E"&'My Loans'!$N$16)/12) -> 55.561643 | J10: =IF(OR('My Loans'!$N$16="",'My Loans'!$N$16=0),0,IF(H10<0.005,0,MIN(INDIRECT("'My Loans'!$F"&'My Loans'!$N$16),H10+I10))) -> 142 | K10: =IF(A10=1,IF(OR('My Loans'!$N$17="",'My Loans'!$N$17=0),0,INDIRECT("'My Loans'!$D"&'My Loans'!$N$17)),AT9) -> 9215.8357 | L10: =IF(OR('My Loans'!$N$17="",'My Loans'!$N$17=0),0,K10*INDIRECT("'My Loans'!$E"&'My Loans'!$N$17)/12) -> 37.631329 | M10: =IF(OR('My Loans'!$N$17="",'My Loans'!$N$17=0),0,IF(K10<0.005,0,MIN(INDIRECT("'My Loans'!$F"&'My Loans'!$N$17),K10+L10))) -> 112 | N10: =IF(A10=1,IF(OR('My Loans'!$N$18="",'My Loans'!$N$18=0),0,INDIRECT("'My Loans'!$D"&'My Loans'!$N$18)),AY9) -> 7679.2029 | O10: =IF(OR('My Loans'!$N$18="",'My Loans'!$N$18=0),0,N10*INDIRECT("'My Loans'!$E"&'My Loans'!$N$18)/12) -> 28.797011 | P10: =IF(OR('My Loans'!$N$18="",'My Loans'!$N$18=0),0,IF(N10<0.005,0,MIN(INDIRECT("'My Loans'!$F"&'My Loans'!$N$18),N10+O10))) -> 95 | Q10: =IF(A10=1,IF(OR('My Loans'!$N$19="",'My Loans'!$N$19=0),0,INDIRECT("'My Loans'!$D"&'My Loans'!$N$19)),BD9) -> 0 | R10: =IF(OR('My Loans'!$N$19="",'My Loans'!$N$19=0),0,Q10*INDIRECT("'My Loans'!$E"&'My Loans'!$N$19)/12) -> 0 | S10: =IF(OR('My Loans'!$N$19="",'My Loans'!$N$19=0),0,IF(Q10<0.005,0,MIN(INDIRECT("'My Loans'!$F"&'My Loans'!$N$19),Q10+R10))) -> 0 | T10: =IF(A10=1,IF(OR('My Loans'!$N$20="",'My Loans'!$N$20=0),0,INDIRECT("'My Loans'!$D"&'My Loans'!$N$20)),BI9) -> 0 | U10: =IF(OR('My Loans'!$N$20="",'My Loans'!$N$20=0),0,T10*INDIRECT("'My Loans'!$E"&'My Loans'!$N$20)/12) -> 0 | V10: =IF(OR('My Loans'!$N$20="",'My Loans'!$N$20=0),0,IF(T10<0.005,0,MIN(INDIRECT("'My Loans'!$F"&'My Loans'!$N$20),T10+U10))) -> 0 | W10: =IF(A10=1,IF(OR('My Loans'!$N$21="",'My Loans'!$N$21=0),0,INDIRECT("'My Loans'!$D"&'My Loans'!$N$21)),BN9) -> 0 | X10: =IF(OR('My Loans'!$N$21="",'My Loans'!$N$21=0),0,W10*INDIRECT("'My Loans'!$E"&'My Loans'!$N$21)/12) -> 0 | Y10: =IF(OR('My Loans'!$N$21="",'My Loans'!$N$21=0),0,IF(W10<0.005,0,MIN(INDIRECT("'My Loans'!$F"&'My Loans'!$N$21),W10+X10))) -> 0 | Z10: ='My Loans'!$B$13-(D10+G10+J10+M10+P10+S10+V10+Y10) -> 463 | AA10: =MAX(0,Z10) -> 463 | AB10: =MAX(0,B10+C10-D10) -> 22099.254 | AC10: =MIN(AA10,AB10) -> 463 | AD10: =D10+AC10 -> 873 | AE10: =MAX(0,B10+C10-AD10) -> 21636.254 | AF10: =MAX(0,AA10-AC10) -> 0 | AG10: =MAX(0,E10+F10-G10) -> 14286.074 | AH10: =MIN(AF10,AG10) -> 0 | AI10: =G10+AH10 -> 178 | AJ10: =MAX(0,E10+F10-AI10) -> 14286.074 | AK10: =MAX(0,AF10-AH10) -> 0 | AL10: =MAX(0,H10+I10-J10) -> 12036.102 | AM10: =MIN(AK10,AL10) -> 0 | AN10: =J10+AM10 -> 142 | AO10: =MAX(0,H10+I10-AN10) -> 12036.102 | AP10: =MAX(0,AK10-AM10) -> 0 | AQ10: =MAX(0,K10+L10-M10) -> 9141.467 | AR10: =MIN(AP10,AQ10) -> 0 | AS10: =M10+AR10 -> 112 | AT10: =MAX(0,K10+L10-AS10) -> 9141.467 | AU10: =MAX(0,AP10-AR10) -> 0 | AV10: =MAX(0,N10+O10-P10) -> 7612.9999 | AW10: =MIN(AU10,AV10) -> 0 | AX10: =P10+AW10 -> 95 | AY10: =MAX(0,N10+O10-AX10) -> 7612.9999 | AZ10: =MAX(0,AU10-AW10) -> 0 | BA10: =MAX(0,Q10+R10-S10) -> 0 | BB10: =MIN(AZ10,BA10) -> 0 | BC10: =S10+BB10 -> 0 | BD10: =MAX(0,Q10+R10-BC10) -> 0 | BE10: =MAX(0,AZ10-BB10) -> 0 | BF10: =MAX(0,T10+U10-V10) -> 0 | BG10: =MIN(BE10,BF10) -> 0 | BH10: =V10+BG10 -> 0 | BI10: =MAX(0,T10+U10-BH10) -> 0 | BJ10: =MAX(0,BE10-BG10) -> 0 | BK10: =MAX(0,W10+X10-Y10) -> 0 | BL10: =MIN(BJ10,BK10) -> 0 | BM10: =Y10+BL10 -> 0 | BN10: =MAX(0,W10+X10-BM10) -> 0 | BO10: =AD10+AI10+AN10+AS10+AX10+BC10+BH10+BM10 -> 1400 | BP10: =C10+F10+I10+L10+O10+R10+U10+X10 -> 343.55365 | BQ10: =AE10+AJ10+AO10+AT10+AY10+BD10+BI10+BN10 -> 64712.897
A11: 10 | B11: =IF(A11=1,IF(OR('My Loans'!$N$14="",'My Loans'!$N$14=0),0,INDIRECT("'My Loans'!$D"&'My Loans'!$N$14)),AE10) -> 21636.254 | C11: =IF(OR('My Loans'!$N$14="",'My Loans'!$N$14=0),0,B11*INDIRECT("'My Loans'!$E"&'My Loans'!$N$14)/12) -> 142.43867 | D11: =IF(OR('My Loans'!$N$14="",'My Loans'!$N$14=0),0,IF(B11<0.005,0,MIN(INDIRECT("'My Loans'!$F"&'My Loans'!$N$14),B11+C11))) -> 410 | E11: =IF(A11=1,IF(OR('My Loans'!$N$15="",'My Loans'!$N$15=0),0,INDIRECT("'My Loans'!$D"&'My Loans'!$N$15)),AJ10) -> 14286.074 | F11: =IF(OR('My Loans'!$N$15="",'My Loans'!$N$15=0),0,E11*INDIRECT("'My Loans'!$E"&'My Loans'!$N$15)/12) -> 73.811385 | G11: =IF(OR('My Loans'!$N$15="",'My Loans'!$N$15=0),0,IF(E11<0.005,0,MIN(INDIRECT("'My Loans'!$F"&'My Loans'!$N$15),E11+F11))) -> 178 | H11: =IF(A11=1,IF(OR('My Loans'!$N$16="",'My Loans'!$N$16=0),0,INDIRECT("'My Loans'!$D"&'My Loans'!$N$16)),AO10) -> 12036.102 | I11: =IF(OR('My Loans'!$N$16="",'My Loans'!$N$16=0),0,H11*INDIRECT("'My Loans'!$E"&'My Loans'!$N$16)/12) -> 55.165467 | J11: =IF(OR('My Loans'!$N$16="",'My Loans'!$N$16=0),0,IF(H11<0.005,0,MIN(INDIRECT("'My Loans'!$F"&'My Loans'!$N$16),H11+I11))) -> 142 | K11: =IF(A11=1,IF(OR('My Loans'!$N$17="",'My Loans'!$N$17=0),0,INDIRECT("'My Loans'!$D"&'My Loans'!$N$17)),AT10) -> 9141.467 | L11: =IF(OR('My Loans'!$N$17="",'My Loans'!$N$17=0),0,K11*INDIRECT("'My Loans'!$E"&'My Loans'!$N$17)/12) -> 37.327657 | M11: =IF(OR('My Loans'!$N$17="",'My Loans'!$N$17=0),0,IF(K11<0.005,0,MIN(INDIRECT("'My Loans'!$F"&'My Loans'!$N$17),K11+L11))) -> 112 | N11: =IF(A11=1,IF(OR('My Loans'!$N$18="",'My Loans'!$N$18=0),0,INDIRECT("'My Loans'!$D"&'My Loans'!$N$18)),AY10) -> 7612.9999 | O11: =IF(OR('My Loans'!$N$18="",'My Loans'!$N$18=0),0,N11*INDIRECT("'My Loans'!$E"&'My Loans'!$N$18)/12) -> 28.54875 | P11: =IF(OR('My Loans'!$N$18="",'My Loans'!$N$18=0),0,IF(N11<0.005,0,MIN(INDIRECT("'My Loans'!$F"&'My Loans'!$N$18),N11+O11))) -> 95 | Q11: =IF(A11=1,IF(OR('My Loans'!$N$19="",'My Loans'!$N$19=0),0,INDIRECT("'My Loans'!$D"&'My Loans'!$N$19)),BD10) -> 0 | R11: =IF(OR('My Loans'!$N$19="",'My Loans'!$N$19=0),0,Q11*INDIRECT("'My Loans'!$E"&'My Loans'!$N$19)/12) -> 0 | S11: =IF(OR('My Loans'!$N$19="",'My Loans'!$N$19=0),0,IF(Q11<0.005,0,MIN(INDIRECT("'My Loans'!$F"&'My Loans'!$N$19),Q11+R11))) -> 0 | T11: =IF(A11=1,IF(OR('My Loans'!$N$20="",'My Loans'!$N$20=0),0,INDIRECT("'My Loans'!$D"&'My Loans'!$N$20)),BI10) -> 0 | U11: =IF(OR('My Loans'!$N$20="",'My Loans'!$N$20=0),0,T11*INDIRECT("'My Loans'!$E"&'My Loans'!$N$20)/12) -> 0 | V11: =IF(OR('My Loans'!$N$20="",'My Loans'!$N$20=0),0,IF(T11<0.005,0,MIN(INDIRECT("'My Loans'!$F"&'My Loans'!$N$20),T11+U11))) -> 0 | W11: =IF(A11=1,IF(OR('My Loans'!$N$21="",'My Loans'!$N$21=0),0,INDIRECT("'My Loans'!$D"&'My Loans'!$N$21)),BN10) -> 0 | X11: =IF(OR('My Loans'!$N$21="",'My Loans'!$N$21=0),0,W11*INDIRECT("'My Loans'!$E"&'My Loans'!$N$21)/12) -> 0 | Y11: =IF(OR('My Loans'!$N$21="",'My Loans'!$N$21=0),0,IF(W11<0.005,0,MIN(INDIRECT("'My Loans'!$F"&'My Loans'!$N$21),W11+X11))) -> 0 | Z11: ='My Loans'!$B$13-(D11+G11+J11+M11+P11+S11+V11+Y11) -> 463 | AA11: =MAX(0,Z11) -> 463 | AB11: =MAX(0,B11+C11-D11) -> 21368.693 | AC11: =MIN(AA11,AB11) -> 463 | AD11: =D11+AC11 -> 873 | AE11: =MAX(0,B11+C11-AD11) -> 20905.693 | AF11: =MAX(0,AA11-AC11) -> 0 | AG11: =MAX(0,E11+F11-G11) -> 14181.886 | AH11: =MIN(AF11,AG11) -> 0 | AI11: =G11+AH11 -> 178 | AJ11: =MAX(0,E11+F11-AI11) -> 14181.886 | AK11: =MAX(0,AF11-AH11) -> 0 | AL11: =MAX(0,H11+I11-J11) -> 11949.267 | AM11: =MIN(AK11,AL11) -> 0 | AN11: =J11+AM11 -> 142 | AO11: =MAX(0,H11+I11-AN11) -> 11949.267 | AP11: =MAX(0,AK11-AM11) -> 0 | AQ11: =MAX(0,K11+L11-M11) -> 9066.7947 | AR11: =MIN(AP11,AQ11) -> 0 | AS11: =M11+AR11 -> 112 | AT11: =MAX(0,K11+L11-AS11) -> 9066.7947 | AU11: =MAX(0,AP11-AR11) -> 0 | AV11: =MAX(0,N11+O11-P11) -> 7546.5487 | AW11: =MIN(AU11,AV11) -> 0 | AX11: =P11+AW11 -> 95 | AY11: =MAX(0,N11+O11-AX11) -> 7546.5487 | AZ11: =MAX(0,AU11-AW11) -> 0 | BA11: =MAX(0,Q11+R11-S11) -> 0 | BB11: =MIN(AZ11,BA11) -> 0 | BC11: =S11+BB11 -> 0 | BD11: =MAX(0,Q11+R11-BC11) -> 0 | BE11: =MAX(0,AZ11-BB11) -> 0 | BF11: =MAX(0,T11+U11-V11) -> 0 | BG11: =MIN(BE11,BF11) -> 0 | BH11: =V11+BG11 -> 0 | BI11: =MAX(0,T11+U11-BH11) -> 0 | BJ11: =MAX(0,BE11-BG11) -> 0 | BK11: =MAX(0,W11+X11-Y11) -> 0 | BL11: =MIN(BJ11,BK11) -> 0 | BM11: =Y11+BL11 -> 0 | BN11: =MAX(0,W11+X11-BM11) -> 0 | BO11: =AD11+AI11+AN11+AS11+AX11+BC11+BH11+BM11 -> 1400 | BP11: =C11+F11+I11+L11+O11+R11+U11+X11 -> 337.29193 | BQ11: =AE11+AJ11+AO11+AT11+AY11+BD11+BI11+BN11 -> 63650.189
A12: 11 | B12: =IF(A12=1,IF(OR('My Loans'!$N$14="",'My Loans'!$N$14=0),0,INDIRECT("'My Loans'!$D"&'My Loans'!$N$14)),AE11) -> 20905.693 | C12: =IF(OR('My Loans'!$N$14="",'My Loans'!$N$14=0),0,B12*INDIRECT("'My Loans'!$E"&'My Loans'!$N$14)/12) -> 137.62914 | D12: =IF(OR('My Loans'!$N$14="",'My Loans'!$N$14=0),0,IF(B12<0.005,0,MIN(INDIRECT("'My Loans'!$F"&'My Loans'!$N$14),B12+C12))) -> 410 | E12: =IF(A12=1,IF(OR('My Loans'!$N$15="",'My Loans'!$N$15=0),0,INDIRECT("'My Loans'!$D"&'My Loans'!$N$15)),AJ11) -> 14181.886 | F12: =IF(OR('My Loans'!$N$15="",'My Loans'!$N$15=0),0,E12*INDIRECT("'My Loans'!$E"&'My Loans'!$N$15)/12) -> 73.273077 | G12: =IF(OR('My Loans'!$N$15="",'My Loans'!$N$15=0),0,IF(E12<0.005,0,MIN(INDIRECT("'My Loans'!$F"&'My Loans'!$N$15),E12+F12))) -> 178 | H12: =IF(A12=1,IF(OR('My Loans'!$N$16="",'My Loans'!$N$16=0),0,INDIRECT("'My Loans'!$D"&'My Loans'!$N$16)),AO11) -> 11949.267 | I12: =IF(OR('My Loans'!$N$16="",'My Loans'!$N$16=0),0,H12*INDIRECT("'My Loans'!$E"&'My Loans'!$N$16)/12) -> 54.767476 | J12: =IF(OR('My Loans'!$N$16="",'My Loans'!$N$16=0),0,IF(H12<0.005,0,MIN(INDIRECT("'My Loans'!$F"&'My Loans'!$N$16),H12+I12))) -> 142 | K12: =IF(A12=1,IF(OR('My Loans'!$N$17="",'My Loans'!$N$17=0),0,INDIRECT("'My Loans'!$D"&'My Loans'!$N$17)),AT11) -> 9066.7947 | L12: =IF(OR('My Loans'!$N$17="",'My Loans'!$N$17=0),0,K12*INDIRECT("'My Loans'!$E"&'My Loans'!$N$17)/12) -> 37.022745 | M12: =IF(OR('My Loans'!$N$17="",'My Loans'!$N$17=0),0,IF(K12<0.005,0,MIN(INDIRECT("'My Loans'!$F"&'My Loans'!$N$17),K12+L12))) -> 112 | N12: =IF(A12=1,IF(OR('My Loans'!$N$18="",'My Loans'!$N$18=0),0,INDIRECT("'My Loans'!$D"&'My Loans'!$N$18)),AY11) -> 7546.5487 | O12: =IF(OR('My Loans'!$N$18="",'My Loans'!$N$18=0),0,N12*INDIRECT("'My Loans'!$E"&'My Loans'!$N$18)/12) -> 28.299558 | P12: =IF(OR('My Loans'!$N$18="",'My Loans'!$N$18=0),0,IF(N12<0.005,0,MIN(INDIRECT("'My Loans'!$F"&'My Loans'!$N$18),N12+O12))) -> 95 | Q12: =IF(A12=1,IF(OR('My Loans'!$N$19="",'My Loans'!$N$19=0),0,INDIRECT("'My Loans'!$D"&'My Loans'!$N$19)),BD11) -> 0 | R12: =IF(OR('My Loans'!$N$19="",'My Loans'!$N$19=0),0,Q12*INDIRECT("'My Loans'!$E"&'My Loans'!$N$19)/12) -> 0 | S12: =IF(OR('My Loans'!$N$19="",'My Loans'!$N$19=0),0,IF(Q12<0.005,0,MIN(INDIRECT("'My Loans'!$F"&'My Loans'!$N$19),Q12+R12))) -> 0 | T12: =IF(A12=1,IF(OR('My Loans'!$N$20="",'My Loans'!$N$20=0),0,INDIRECT("'My Loans'!$D"&'My Loans'!$N$20)),BI11) -> 0 | U12: =IF(OR('My Loans'!$N$20="",'My Loans'!$N$20=0),0,T12*INDIRECT("'My Loans'!$E"&'My Loans'!$N$20)/12) -> 0 | V12: =IF(OR('My Loans'!$N$20="",'My Loans'!$N$20=0),0,IF(T12<0.005,0,MIN(INDIRECT("'My Loans'!$F"&'My Loans'!$N$20),T12+U12))) -> 0 | W12: =IF(A12=1,IF(OR('My Loans'!$N$21="",'My Loans'!$N$21=0),0,INDIRECT("'My Loans'!$D"&'My Loans'!$N$21)),BN11) -> 0 | X12: =IF(OR('My Loans'!$N$21="",'My Loans'!$N$21=0),0,W12*INDIRECT("'My Loans'!$E"&'My Loans'!$N$21)/12) -> 0 | Y12: =IF(OR('My Loans'!$N$21="",'My Loans'!$N$21=0),0,IF(W12<0.005,0,MIN(INDIRECT("'My Loans'!$F"&'My Loans'!$N$21),W12+X12))) -> 0 | Z12: ='My Loans'!$B$13-(D12+G12+J12+M12+P12+S12+V12+Y12) -> 463 | AA12: =MAX(0,Z12) -> 463 | AB12: =MAX(0,B12+C12-D12) -> 20633.322 | AC12: =MIN(AA12,AB12) -> 463 | AD12: =D12+AC12 -> 873 | AE12: =MAX(0,B12+C12-AD12) -> 20170.322 | AF12: =MAX(0,AA12-AC12) -> 0 | AG12: =MAX(0,E12+F12-G12) -> 14077.159 | AH12: =MIN(AF12,AG12) -> 0 | AI12: =G12+AH12 -> 178 | AJ12: =MAX(0,E12+F12-AI12) -> 14077.159 | AK12: =MAX(0,AF12-AH12) -> 0 | AL12: =MAX(0,H12+I12-J12) -> 11862.035 | AM12: =MIN(AK12,AL12) -> 0 | AN12: =J12+AM12 -> 142 | AO12: =MAX(0,H12+I12-AN12) -> 11862.035 | AP12: =MAX(0,AK12-AM12) -> 0 | AQ12: =MAX(0,K12+L12-M12) -> 8991.8174 | AR12: =MIN(AP12,AQ12) -> 0 | AS12: =M12+AR12 -> 112 | AT12: =MAX(0,K12+L12-AS12) -> 8991.8174 | AU12: =MAX(0,AP12-AR12) -> 0 | AV12: =MAX(0,N12+O12-P12) -> 7479.8482 | AW12: =MIN(AU12,AV12) -> 0 | AX12: =P12+AW12 -> 95 | AY12: =MAX(0,N12+O12-AX12) -> 7479.8482 | AZ12: =MAX(0,AU12-AW12) -> 0 | BA12: =MAX(0,Q12+R12-S12) -> 0 | BB12: =MIN(AZ12,BA12) -> 0 | BC12: =S12+BB12 -> 0 | BD12: =MAX(0,Q12+R12-BC12) -> 0 | BE12: =MAX(0,AZ12-BB12) -> 0 | BF12: =MAX(0,T12+U12-V12) -> 0 | BG12: =MIN(BE12,BF12) -> 0 | BH12: =V12+BG12 -> 0 | BI12: =MAX(0,T12+U12-BH12) -> 0 | BJ12: =MAX(0,BE12-BG12) -> 0 | BK12: =MAX(0,W12+X12-Y12) -> 0 | BL12: =MIN(BJ12,BK12) -> 0 | BM12: =Y12+BL12 -> 0 | BN12: =MAX(0,W12+X12-BM12) -> 0 | BO12: =AD12+AI12+AN12+AS12+AX12+BC12+BH12+BM12 -> 1400 | BP12: =C12+F12+I12+L12+O12+R12+U12+X12 -> 330.992 | BQ12: =AE12+AJ12+AO12+AT12+AY12+BD12+BI12+BN12 -> 62581.181
A13: 12 | B13: =IF(A13=1,IF(OR('My Loans'!$N$14="",'My Loans'!$N$14=0),0,INDIRECT("'My Loans'!$D"&'My Loans'!$N$14)),AE12) -> 20170.322 | C13: =IF(OR('My Loans'!$N$14="",'My Loans'!$N$14=0),0,B13*INDIRECT("'My Loans'!$E"&'My Loans'!$N$14)/12) -> 132.78795 | D13: =IF(OR('My Loans'!$N$14="",'My Loans'!$N$14=0),0,IF(B13<0.005,0,MIN(INDIRECT("'My Loans'!$F"&'My Loans'!$N$14),B13+C13))) -> 410 | E13: =IF(A13=1,IF(OR('My Loans'!$N$15="",'My Loans'!$N$15=0),0,INDIRECT("'My Loans'!$D"&'My Loans'!$N$15)),AJ12) -> 14077.159 | F13: =IF(OR('My Loans'!$N$15="",'My Loans'!$N$15=0),0,E13*INDIRECT("'My Loans'!$E"&'My Loans'!$N$15)/12) -> 72.731988 | G13: =IF(OR('My Loans'!$N$15="",'My Loans'!$N$15=0),0,IF(E13<0.005,0,MIN(INDIRECT("'My Loans'!$F"&'My Loans'!$N$15),E13+F13))) -> 178 | H13: =IF(A13=1,IF(OR('My Loans'!$N$16="",'My Loans'!$N$16=0),0,INDIRECT("'My Loans'!$D"&'My Loans'!$N$16)),AO12) -> 11862.035 | I13: =IF(OR('My Loans'!$N$16="",'My Loans'!$N$16=0),0,H13*INDIRECT("'My Loans'!$E"&'My Loans'!$N$16)/12) -> 54.36766 | J13: =IF(OR('My Loans'!$N$16="",'My Loans'!$N$16=0),0,IF(H13<0.005,0,MIN(INDIRECT("'My Loans'!$F"&'My Loans'!$N$16),H13+I13))) -> 142 | K13: =IF(A13=1,IF(OR('My Loans'!$N$17="",'My Loans'!$N$17=0),0,INDIRECT("'My Loans'!$D"&'My Loans'!$N$17)),AT12) -> 8991.8174 | L13: =IF(OR('My Loans'!$N$17="",'My Loans'!$N$17=0),0,K13*INDIRECT("'My Loans'!$E"&'My Loans'!$N$17)/12) -> 36.716588 | M13: =IF(OR('My Loans'!$N$17="",'My Loans'!$N$17=0),0,IF(K13<0.005,0,MIN(INDIRECT("'My Loans'!$F"&'My Loans'!$N$17),K13+L13))) -> 112 | N13: =IF(A13=1,IF(OR('My Loans'!$N$18="",'My Loans'!$N$18=0),0,INDIRECT("'My Loans'!$D"&'My Loans'!$N$18)),AY12) -> 7479.8482 | O13: =IF(OR('My Loans'!$N$18="",'My Loans'!$N$18=0),0,N13*INDIRECT("'My Loans'!$E"&'My Loans'!$N$18)/12) -> 28.049431 | P13: =IF(OR('My Loans'!$N$18="",'My Loans'!$N$18=0),0,IF(N13<0.005,0,MIN(INDIRECT("'My Loans'!$F"&'My Loans'!$N$18),N13+O13))) -> 95 | Q13: =IF(A13=1,IF(OR('My Loans'!$N$19="",'My Loans'!$N$19=0),0,INDIRECT("'My Loans'!$D"&'My Loans'!$N$19)),BD12) -> 0 | R13: =IF(OR('My Loans'!$N$19="",'My Loans'!$N$19=0),0,Q13*INDIRECT("'My Loans'!$E"&'My Loans'!$N$19)/12) -> 0 | S13: =IF(OR('My Loans'!$N$19="",'My Loans'!$N$19=0),0,IF(Q13<0.005,0,MIN(INDIRECT("'My Loans'!$F"&'My Loans'!$N$19),Q13+R13))) -> 0 | T13: =IF(A13=1,IF(OR('My Loans'!$N$20="",'My Loans'!$N$20=0),0,INDIRECT("'My Loans'!$D"&'My Loans'!$N$20)),BI12) -> 0 | U13: =IF(OR('My Loans'!$N$20="",'My Loans'!$N$20=0),0,T13*INDIRECT("'My Loans'!$E"&'My Loans'!$N$20)/12) -> 0 | V13: =IF(OR('My Loans'!$N$20="",'My Loans'!$N$20=0),0,IF(T13<0.005,0,MIN(INDIRECT("'My Loans'!$F"&'My Loans'!$N$20),T13+U13))) -> 0 | W13: =IF(A13=1,IF(OR('My Loans'!$N$21="",'My Loans'!$N$21=0),0,INDIRECT("'My Loans'!$D"&'My Loans'!$N$21)),BN12) -> 0 | X13: =IF(OR('My Loans'!$N$21="",'My Loans'!$N$21=0),0,W13*INDIRECT("'My Loans'!$E"&'My Loans'!$N$21)/12) -> 0 | Y13: =IF(OR('My Loans'!$N$21="",'My Loans'!$N$21=0),0,IF(W13<0.005,0,MIN(INDIRECT("'My Loans'!$F"&'My Loans'!$N$21),W13+X13))) -> 0 | Z13: ='My Loans'!$B$13-(D13+G13+J13+M13+P13+S13+V13+Y13) -> 463 | AA13: =MAX(0,Z13) -> 463 | AB13: =MAX(0,B13+C13-D13) -> 19893.11 | AC13: =MIN(AA13,AB13) -> 463 | AD13: =D13+AC13 -> 873 | AE13: =MAX(0,B13+C13-AD13) -> 19430.11 | AF13: =MAX(0,AA13-AC13) -> 0 | AG13: =MAX(0,E13+F13-G13) -> 13971.891 | AH13: =MIN(AF13,AG13) -> 0 | AI13: =G13+AH13 -> 178 | AJ13: =MAX(0,E13+F13-AI13) -> 13971.891 | AK13: =MAX(0,AF13-AH13) -> 0 | AL13: =MAX(0,H13+I13-J13) -> 11774.403 | AM13: =MIN(AK13,AL13) -> 0 | AN13: =J13+AM13 -> 142 | AO13: =MAX(0,H13+I13-AN13) -> 11774.403 | AP13: =MAX(0,AK13-AM13) -> 0 | AQ13: =MAX(0,K13+L13-M13) -> 8916.534 | AR13: =MIN(AP13,AQ13) -> 0 | AS13: =M13+AR13 -> 112 | AT13: =MAX(0,K13+L13-AS13) -> 8916.534 | AU13: =MAX(0,AP13-AR13) -> 0 | AV13: =MAX(0,N13+O13-P13) -> 7412.8977 | AW13: =MIN(AU13,AV13) -> 0 | AX13: =P13+AW13 -> 95 | AY13: =MAX(0,N13+O13-AX13) -> 7412.8977 | AZ13: =MAX(0,AU13-AW13) -> 0 | BA13: =MAX(0,Q13+R13-S13) -> 0 | BB13: =MIN(AZ13,BA13) -> 0 | BC13: =S13+BB13 -> 0 | BD13: =MAX(0,Q13+R13-BC13) -> 0 | BE13: =MAX(0,AZ13-BB13) -> 0 | BF13: =MAX(0,T13+U13-V13) -> 0 | BG13: =MIN(BE13,BF13) -> 0 | BH13: =V13+BG13 -> 0 | BI13: =MAX(0,T13+U13-BH13) -> 0 | BJ13: =MAX(0,BE13-BG13) -> 0 | BK13: =MAX(0,W13+X13-Y13) -> 0 | BL13: =MIN(BJ13,BK13) -> 0 | BM13: =Y13+BL13 -> 0 | BN13: =MAX(0,W13+X13-BM13) -> 0 | BO13: =AD13+AI13+AN13+AS13+AX13+BC13+BH13+BM13 -> 1400 | BP13: =C13+F13+I13+L13+O13+R13+U13+X13 -> 324.65362 | BQ13: =AE13+AJ13+AO13+AT13+AY13+BD13+BI13+BN13 -> 61505.835
... A121: 120 | B121: =IF(A121=1,IF(OR('My Loans'!$N$14="",'My Loans'!$N$14=0),0,INDIRECT("'My Loans'!$D"&'My Loans'!$N$14)),AE120) -> 0 | C121: =IF(OR('My Loans'!$N$14="",'My Loans'!$N$14=0),0,B121*INDIRECT("'My Loans'!$E"&'My Loans'!$N$14)/12) -> 0 | D121: =IF(OR('My Loans'!$N$14="",'My Loans'!$N$14=0),0,IF(B121<0.005,0,MIN(INDIRECT("'My Loans'!$F"&'My Loans'!$N$14),B121+C121))) -> 0 | E121: =IF(A121=1,IF(OR('My Loans'!$N$15="",'My Loans'!$N$15=0),0,INDIRECT("'My Loans'!$D"&'My Loans'!$N$15)),AJ120) -> 0 | F121: =IF(OR('My Loans'!$N$15="",'My Loans'!$N$15=0),0,E121*INDIRECT("'My Loans'!$E"&'My Loans'!$N$15)/12) -> 0 | G121: =IF(OR('My Loans'!$N$15="",'My Loans'!$N$15=0),0,IF(E121<0.005,0,MIN(INDIRECT("'My Loans'!$F"&'My Loans'!$N$15),E121+F121))) -> 0 | H121: =IF(A121=1,IF(OR('My Loans'!$N$16="",'My Loans'!$N$16=0),0,INDIRECT("'My Loans'!$D"&'My Loans'!$N$16)),AO120) -> 0 | I121: =IF(OR('My Loans'!$N$16="",'My Loans'!$N$16=0),0,H121*INDIRECT("'My Loans'!$E"&'My Loans'!$N$16)/12) -> 0 | J121: =IF(OR('My Loans'!$N$16="",'My Loans'!$N$16=0),0,IF(H121<0.005,0,MIN(INDIRECT("'My Loans'!$F"&'My Loans'!$N$16),H121+I121))) -> 0 | K121: =IF(A121=1,IF(OR('My Loans'!$N$17="",'My Loans'!$N$17=0),0,INDIRECT("'My Loans'!$D"&'My Loans'!$N$17)),AT120) -> 0 | L121: =IF(OR('My Loans'!$N$17="",'My Loans'!$N$17=0),0,K121*INDIRECT("'My Loans'!$E"&'My Loans'!$N$17)/12) -> 0 | M121: =IF(OR('My Loans'!$N$17="",'My Loans'!$N$17=0),0,IF(K121<0.005,0,MIN(INDIRECT("'My Loans'!$F"&'My Loans'!$N$17),K121+L121))) -> 0 | N121: =IF(A121=1,IF(OR('My Loans'!$N$18="",'My Loans'!$N$18=0),0,INDIRECT("'My Loans'!$D"&'My Loans'!$N$18)),AY120) -> 0 | O121: =IF(OR('My Loans'!$N$18="",'My Loans'!$N$18=0),0,N121*INDIRECT("'My Loans'!$E"&'My Loans'!$N$18)/12) -> 0 | P121: =IF(OR('My Loans'!$N$18="",'My Loans'!$N$18=0),0,IF(N121<0.005,0,MIN(INDIRECT("'My Loans'!$F"&'My Loans'!$N$18),N121+O121))) -> 0 | Q121: =IF(A121=1,IF(OR('My Loans'!$N$19="",'My Loans'!$N$19=0),0,INDIRECT("'My Loans'!$D"&'My Loans'!$N$19)),BD120) -> 0 | R121: =IF(OR('My Loans'!$N$19="",'My Loans'!$N$19=0),0,Q121*INDIRECT("'My Loans'!$E"&'My Loans'!$N$19)/12) -> 0 | S121: =IF(OR('My Loans'!$N$19="",'My Loans'!$N$19=0),0,IF(Q121<0.005,0,MIN(INDIRECT("'My Loans'!$F"&'My Loans'!$N$19),Q121+R121))) -> 0 | T121: =IF(A121=1,IF(OR('My Loans'!$N$20="",'My Loans'!$N$20=0),0,INDIRECT("'My Loans'!$D"&'My Loans'!$N$20)),BI120) -> 0 | U121: =IF(OR('My Loans'!$N$20="",'My Loans'!$N$20=0),0,T121*INDIRECT("'My Loans'!$E"&'My Loans'!$N$20)/12) -> 0 | V121: =IF(OR('My Loans'!$N$20="",'My Loans'!$N$20=0),0,IF(T121<0.005,0,MIN(INDIRECT("'My Loans'!$F"&'My Loans'!$N$20),T121+U121))) -> 0 | W121: =IF(A121=1,IF(OR('My Loans'!$N$21="",'My Loans'!$N$21=0),0,INDIRECT("'My Loans'!$D"&'My Loans'!$N$21)),BN120) -> 0 | X121: =IF(OR('My Loans'!$N$21="",'My Loans'!$N$21=0),0,W121*INDIRECT("'My Loans'!$E"&'My Loans'!$N$21)/12) -> 0 | Y121: =IF(OR('My Loans'!$N$21="",'My Loans'!$N$21=0),0,IF(W121<0.005,0,MIN(INDIRECT("'My Loans'!$F"&'My Loans'!$N$21),W121+X121))) -> 0 | Z121: ='My Loans'!$B$13-(D121+G121+J121+M121+P121+S121+V121+Y121) -> 1400 | AA121: =MAX(0,Z121) -> 1400 | AB121: =MAX(0,B121+C121-D121) -> 0 | AC121: =MIN(AA121,AB121) -> 0 | AD121: =D121+AC121 -> 0 | AE121: =MAX(0,B121+C121-AD121) -> 0 | AF121: =MAX(0,AA121-AC121) -> 1400 | AG121: =MAX(0,E121+F121-G121) -> 0 | AH121: =MIN(AF121,AG121) -> 0 | AI121: =G121+AH121 -> 0 | AJ121: =MAX(0,E121+F121-AI121) -> 0 | AK121: =MAX(0,AF121-AH121) -> 1400 | AL121: =MAX(0,H121+I121-J121) -> 0 | AM121: =MIN(AK121,AL121) -> 0 | AN121: =J121+AM121 -> 0 | AO121: =MAX(0,H121+I121-AN121) -> 0 | AP121: =MAX(0,AK121-AM121) -> 1400 | AQ121: =MAX(0,K121+L121-M121) -> 0 | AR121: =MIN(AP121,AQ121) -> 0 | AS121: =M121+AR121 -> 0 | AT121: =MAX(0,K121+L121-AS121) -> 0 | AU121: =MAX(0,AP121-AR121) -> 1400 | AV121: =MAX(0,N121+O121-P121) -> 0 | AW121: =MIN(AU121,AV121) -> 0 | AX121: =P121+AW121 -> 0 | AY121: =MAX(0,N121+O121-AX121) -> 0 | AZ121: =MAX(0,AU121-AW121) -> 1400 | BA121: =MAX(0,Q121+R121-S121) -> 0 | BB121: =MIN(AZ121,BA121) -> 0 | BC121: =S121+BB121 -> 0 | BD121: =MAX(0,Q121+R121-BC121) -> 0 | BE121: =MAX(0,AZ121-BB121) -> 1400 | BF121: =MAX(0,T121+U121-V121) -> 0 | BG121: =MIN(BE121,BF121) -> 0 | BH121: =V121+BG121 -> 0 | BI121: =MAX(0,T121+U121-BH121) -> 0 | BJ121: =MAX(0,BE121-BG121) -> 1400 | BK121: =MAX(0,W121+X121-Y121) -> 0 | BL121: =MIN(BJ121,BK121) -> 0 | BM121: =Y121+BL121 -> 0 | BN121: =MAX(0,W121+X121-BM121) -> 0 | BO121: =AD121+AI121+AN121+AS121+AX121+BC121+BH121+BM121 -> 0 | BP121: =C121+F121+I121+L121+O121+R121+U121+X121 -> 0 | BQ121: =AE121+AJ121+AO121+AT121+AY121+BD121+BI121+BN121 -> 0
A123: Totals / metrics
A124: Total interest paid | B124: =SUM(BP2:BP121) -> 12051.681
A125: Total payments | B125: =SUM(BO2:BO121) -> 86051.681
A126: Months to payoff | B126: =IFERROR(MATCH(TRUE,BQ2:BQ121<=0.005,0),120) -> 120
A127: Payoff date | B127: =EDATE('My Loans'!$B$1,B126) -> 49310
A128: Payoff month by loan (for Comparison)
A129: Loan slot 1 | B129: =IFERROR(MATCH(TRUE,AE2:AE121<=0.005,0),"")
A130: Loan slot 2 | B130: =IFERROR(MATCH(TRUE,AJ2:AJ121<=0.005,0),"")
A131: Loan slot 3 | B131: =IFERROR(MATCH(TRUE,AO2:AO121<=0.005,0),"")
A132: Loan slot 4 | B132: =IFERROR(MATCH(TRUE,AT2:AT121<=0.005,0),"")
A133: Loan slot 5 | B133: =IFERROR(MATCH(TRUE,AY2:AY121<=0.005,0),"")
A134: Loan slot 6 | B134: =IFERROR(MATCH(TRUE,BD2:BD121<=0.005,0),"")
A135: Loan slot 7 | B135: =IFERROR(MATCH(TRUE,BI2:BI121<=0.005,0),"")
A136: Loan slot 8 | B136: =IFERROR(MATCH(TRUE,BN2:BN121<=0.005,0),"")

Sheet Snowball
A1: Month | B1: L1 beg | C1: L1 int | D1: L1 min | E1: L2 beg | F1: L2 int | G1: L2 min | H1: L3 beg | I1: L3 int | J1: L3 min | K1: L4 beg | L1: L4 int | M1: L4 min | N1: L5 beg | O1: L5 int | P1: L5 min | Q1: L6 beg | R1: L6 int | S1: L6 min | T1: L7 beg | U1: L7 int | V1: L7 min | W1: L8 beg | X1: L8 int | Y1: L8 min | Z1: Surplus | AA1: Rem0 | AB1: cascade | AC1: cascade | AD1: cascade | AE1: cascade | AF1: cascade | AG1: cascade | AH1: cascade | AI1: cascade | AJ1: cascade | AK1: cascade | AL1: cascade | AM1: cascade | AN1: cascade | AO1: cascade | AP1: cascade | AQ1: cascade | AR1: cascade | AS1: cascade | AT1: cascade | AU1: cascade | AV1: cascade | AW1: cascade | AX1: cascade | AY1: cascade | AZ1: cascade | BA1: cascade | BB1: cascade | BC1: cascade | BD1: cascade | BE1: cascade | BF1: cascade | BG1: cascade | BH1: cascade | BI1: cascade | BJ1: cascade | BK1: cascade | BL1: cascade | BM1: cascade | BN1: cascade | BO1: Total pay | BP1: Total int | BQ1: Sum balance
A2: 1 | B2: =IF(A2=1,IF(OR('My Loans'!$O$14="",'My Loans'!$O$14=0),0,INDIRECT("'My Loans'!$D"&'My Loans'!$O$14)),AE1) -> 8200 | C2: =IF(OR('My Loans'!$O$14="",'My Loans'!$O$14=0),0,B2*INDIRECT("'My Loans'!$E"&'My Loans'!$O$14)/12) -> 30.75 | D2: =IF(OR('My Loans'!$O$14="",'My Loans'!$O$14=0),0,IF(B2<0.005,0,MIN(INDIRECT("'My Loans'!$F"&'My Loans'!$O$14),B2+C2))) -> 95 | E2: =IF(A2=1,IF(OR('My Loans'!$O$15="",'My Loans'!$O$15=0),0,INDIRECT("'My Loans'!$D"&'My Loans'!$O$15)),AJ1) -> 9800 | F2: =IF(OR('My Loans'!$O$15="",'My Loans'!$O$15=0),0,E2*INDIRECT("'My Loans'!$E"&'My Loans'!$O$15)/12) -> 40.016667 | G2: =IF(OR('My Loans'!$O$15="",'My Loans'!$O$15=0),0,IF(E2<0.005,0,MIN(INDIRECT("'My Loans'!$F"&'My Loans'!$O$15),E2+F2))) -> 112 | H2: =IF(A2=1,IF(OR('My Loans'!$O$16="",'My Loans'!$O$16=0),0,INDIRECT("'My Loans'!$D"&'My Loans'!$O$16)),AO1) -> 12800 | I2: =IF(OR('My Loans'!$O$16="",'My Loans'!$O$16=0),0,H2*INDIRECT("'My Loans'!$E"&'My Loans'!$O$16)/12) -> 58.666667 | J2: =IF(OR('My Loans'!$O$16="",'My Loans'!$O$16=0),0,IF(H2<0.005,0,MIN(INDIRECT("'My Loans'!$F"&'My Loans'!$O$16),H2+I2))) -> 142 | K2: =IF(A2=1,IF(OR('My Loans'!$O$17="",'My Loans'!$O$17=0),0,INDIRECT("'My Loans'!$D"&'My Loans'!$O$17)),AT1) -> 15200 | L2: =IF(OR('My Loans'!$O$17="",'My Loans'!$O$17=0),0,K2*INDIRECT("'My Loans'!$E"&'My Loans'!$O$17)/12) -> 78.533333 | M2: =IF(OR('My Loans'!$O$17="",'My Loans'!$O$17=0),0,IF(K2<0.005,0,MIN(INDIRECT("'My Loans'!$F"&'My Loans'!$O$17),K2+L2))) -> 178 | N2: =IF(A2=1,IF(OR('My Loans'!$O$18="",'My Loans'!$O$18=0),0,INDIRECT("'My Loans'!$D"&'My Loans'!$O$18)),AY1) -> 28000 | O2: =IF(OR('My Loans'!$O$18="",'My Loans'!$O$18=0),0,N2*INDIRECT("'My Loans'!$E"&'My Loans'!$O$18)/12) -> 184.33333 | P2: =IF(OR('My Loans'!$O$18="",'My Loans'!$O$18=0),0,IF(N2<0.005,0,MIN(INDIRECT("'My Loans'!$F"&'My Loans'!$O$18),N2+O2))) -> 410 | Q2: =IF(A2=1,IF(OR('My Loans'!$O$19="",'My Loans'!$O$19=0),0,INDIRECT("'My Loans'!$D"&'My Loans'!$O$19)),BD1) -> 0 | R2: =IF(OR('My Loans'!$O$19="",'My Loans'!$O$19=0),0,Q2*INDIRECT("'My Loans'!$E"&'My Loans'!$O$19)/12) -> 0 | S2: =IF(OR('My Loans'!$O$19="",'My Loans'!$O$19=0),0,IF(Q2<0.005,0,MIN(INDIRECT("'My Loans'!$F"&'My Loans'!$O$19),Q2+R2))) -> 0 | T2: =IF(A2=1,IF(OR('My Loans'!$O$20="",'My Loans'!$O$20=0),0,INDIRECT("'My Loans'!$D"&'My Loans'!$O$20)),BI1) -> 0 | U2: =IF(OR('My Loans'!$O$20="",'My Loans'!$O$20=0),0,T2*INDIRECT("'My Loans'!$E"&'My Loans'!$O$20)/12) -> 0 | V2: =IF(OR('My Loans'!$O$20="",'My Loans'!$O$20=0),0,IF(T2<0.005,0,MIN(INDIRECT("'My Loans'!$F"&'My Loans'!$O$20),T2+U2))) -> 0 | W2: =IF(A2=1,IF(OR('My Loans'!$O$21="",'My Loans'!$O$21=0),0,INDIRECT("'My Loans'!$D"&'My Loans'!$O$21)),BN1) -> 0 | X2: =IF(OR('My Loans'!$O$21="",'My Loans'!$O$21=0),0,W2*INDIRECT("'My Loans'!$E"&'My Loans'!$O$21)/12) -> 0 | Y2: =IF(OR('My Loans'!$O$21="",'My Loans'!$O$21=0),0,IF(W2<0.005,0,MIN(INDIRECT("'My Loans'!$F"&'My Loans'!$O$21),W2+X2))) -> 0 | Z2: ='My Loans'!$B$13-(D2+G2+J2+M2+P2+S2+V2+Y2) -> 463 | AA2: =MAX(0,Z2) -> 463 | AB2: =MAX(0,B2+C2-D2) -> 8135.75 | AC2: =MIN(AA2,AB2) -> 463 | AD2: =D2+AC2 -> 558 | AE2: =MAX(0,B2+C2-AD2) -> 7672.75 | AF2: =MAX(0,AA2-AC2) -> 0 | AG2: =MAX(0,E2+F2-G2) -> 9728.0167 | AH2: =MIN(AF2,AG2) -> 0 | AI2: =G2+AH2 -> 112 | AJ2: =MAX(0,E2+F2-AI2) -> 9728.0167 | AK2: =MAX(0,AF2-AH2) -> 0 | AL2: =MAX(0,H2+I2-J2) -> 12716.667 | AM2: =MIN(AK2,AL2) -> 0 | AN2: =J2+AM2 -> 142 | AO2: =MAX(0,H2+I2-AN2) -> 12716.667 | AP2: =MAX(0,AK2-AM2) -> 0 | AQ2: =MAX(0,K2+L2-M2) -> 15100.533 | AR2: =MIN(AP2,AQ2) -> 0 | AS2: =M2+AR2 -> 178 | AT2: =MAX(0,K2+L2-AS2) -> 15100.533 | AU2: =MAX(0,AP2-AR2) -> 0 | AV2: =MAX(0,N2+O2-P2) -> 27774.333 | AW2: =MIN(AU2,AV2) -> 0 | AX2: =P2+AW2 -> 410 | AY2: =MAX(0,N2+O2-AX2) -> 27774.333 | AZ2: =MAX(0,AU2-AW2) -> 0 | BA2: =MAX(0,Q2+R2-S2) -> 0 | BB2: =MIN(AZ2,BA2) -> 0 | BC2: =S2+BB2 -> 0 | BD2: =MAX(0,Q2+R2-BC2) -> 0 | BE2: =MAX(0,AZ2-BB2) -> 0 | BF2: =MAX(0,T2+U2-V2) -> 0 | BG2: =MIN(BE2,BF2) -> 0 | BH2: =V2+BG2 -> 0 | BI2: =MAX(0,T2+U2-BH2) -> 0 | BJ2: =MAX(0,BE2-BG2) -> 0 | BK2: =MAX(0,W2+X2-Y2) -> 0 | BL2: =MIN(BJ2,BK2) -> 0 | BM2: =Y2+BL2 -> 0 | BN2: =MAX(0,W2+X2-BM2) -> 0 | BO2: =AD2+AI2+AN2+AS2+AX2+BC2+BH2+BM2 -> 1400 | BP2: =C2+F2+I2+L2+O2+R2+U2+X2 -> 392.3 | BQ2: =AE2+AJ2+AO2+AT2+AY2+BD2+BI2+BN2 -> 72992.3
A3: 2 | B3: =IF(A3=1,IF(OR('My Loans'!$O$14="",'My Loans'!$O$14=0),0,INDIRECT("'My Loans'!$D"&'My Loans'!$O$14)),AE2) -> 7672.75 | C3: =IF(OR('My Loans'!$O$14="",'My Loans'!$O$14=0),0,B3*INDIRECT("'My Loans'!$E"&'My Loans'!$O$14)/12) -> 28.772813 | D3: =IF(OR('My Loans'!$O$14="",'My Loans'!$O$14=0),0,IF(B3<0.005,0,MIN(INDIRECT("'My Loans'!$F"&'My Loans'!$O$14),B3+C3))) -> 95 | E3: =IF(A3=1,IF(OR('My Loans'!$O$15="",'My Loans'!$O$15=0),0,INDIRECT("'My Loans'!$D"&'My Loans'!$O$15)),AJ2) -> 9728.0167 | F3: =IF(OR('My Loans'!$O$15="",'My Loans'!$O$15=0),0,E3*INDIRECT("'My Loans'!$E"&'My Loans'!$O$15)/12) -> 39.722735 | G3: =IF(OR('My Loans'!$O$15="",'My Loans'!$O$15=0),0,IF(E3<0.005,0,MIN(INDIRECT("'My Loans'!$F"&'My Loans'!$O$15),E3+F3))) -> 112 | H3: =IF(A3=1,IF(OR('My Loans'!$O$16="",'My Loans'!$O$16=0),0,INDIRECT("'My Loans'!$D"&'My Loans'!$O$16)),AO2) -> 12716.667 | I3: =IF(OR('My Loans'!$O$16="",'My Loans'!$O$16=0),0,H3*INDIRECT("'My Loans'!$E"&'My Loans'!$O$16)/12) -> 58.284722 | J3: =IF(OR('My Loans'!$O$16="",'My Loans'!$O$16=0),0,IF(H3<0.005,0,MIN(INDIRECT("'My Loans'!$F"&'My Loans'!$O$16),H3+I3))) -> 142 | K3: =IF(A3=1,IF(OR('My Loans'!$O$17="",'My Loans'!$O$17=0),0,INDIRECT("'My Loans'!$D"&'My Loans'!$O$17)),AT2) -> 15100.533 | L3: =IF(OR('My Loans'!$O$17="",'My Loans'!$O$17=0),0,K3*INDIRECT("'My Loans'!$E"&'My Loans'!$O$17)/12) -> 78.019422 | M3: =IF(OR('My Loans'!$O$17="",'My Loans'!$O$17=0),0,IF(K3<0.005,0,MIN(INDIRECT("'My Loans'!$F"&'My Loans'!$O$17),K3+L3))) -> 178 | N3: =IF(A3=1,IF(OR('My Loans'!$O$18="",'My Loans'!$O$18=0),0,INDIRECT("'My Loans'!$D"&'My Loans'!$O$18)),AY2) -> 27774.333 | O3: =IF(OR('My Loans'!$O$18="",'My Loans'!$O$18=0),0,N3*INDIRECT("'My Loans'!$E"&'My Loans'!$O$18)/12) -> 182.84769 | P3: =IF(OR('My Loans'!$O$18="",'My Loans'!$O$18=0),0,IF(N3<0.005,0,MIN(INDIRECT("'My Loans'!$F"&'My Loans'!$O$18),N3+O3))) -> 410 | Q3: =IF(A3=1,IF(OR('My Loans'!$O$19="",'My Loans'!$O$19=0),0,INDIRECT("'My Loans'!$D"&'My Loans'!$O$19)),BD2) -> 0 | R3: =IF(OR('My Loans'!$O$19="",'My Loans'!$O$19=0),0,Q3*INDIRECT("'My Loans'!$E"&'My Loans'!$O$19)/12) -> 0 | S3: =IF(OR('My Loans'!$O$19="",'My Loans'!$O$19=0),0,IF(Q3<0.005,0,MIN(INDIRECT("'My Loans'!$F"&'My Loans'!$O$19),Q3+R3))) -> 0 | T3: =IF(A3=1,IF(OR('My Loans'!$O$20="",'My Loans'!$O$20=0),0,INDIRECT("'My Loans'!$D"&'My Loans'!$O$20)),BI2) -> 0 | U3: =IF(OR('My Loans'!$O$20="",'My Loans'!$O$20=0),0,T3*INDIRECT("'My Loans'!$E"&'My Loans'!$O$20)/12) -> 0 | V3: =IF(OR('My Loans'!$O$20="",'My Loans'!$O$20=0),0,IF(T3<0.005,0,MIN(INDIRECT("'My Loans'!$F"&'My Loans'!$O$20),T3+U3))) -> 0 | W3: =IF(A3=1,IF(OR('My Loans'!$O$21="",'My Loans'!$O$21=0),0,INDIRECT("'My Loans'!$D"&'My Loans'!$O$21)),BN2) -> 0 | X3: =IF(OR('My Loans'!$O$21="",'My Loans'!$O$21=0),0,W3*INDIRECT("'My Loans'!$E"&'My Loans'!$O$21)/12) -> 0 | Y3: =IF(OR('My Loans'!$O$21="",'My Loans'!$O$21=0),0,IF(W3<0.005,0,MIN(INDIRECT("'My Loans'!$F"&'My Loans'!$O$21),W3+X3))) -> 0 | Z3: ='My Loans'!$B$13-(D3+G3+J3+M3+P3+S3+V3+Y3) -> 463 | AA3: =MAX(0,Z3) -> 463 | AB3: =MAX(0,B3+C3-D3) -> 7606.5228 | AC3: =MIN(AA3,AB3) -> 463 | AD3: =D3+AC3 -> 558 | AE3: =MAX(0,B3+C3-AD3) -> 7143.5228 | AF3: =MAX(0,AA3-AC3) -> 0 | AG3: =MAX(0,E3+F3-G3) -> 9655.7394 | AH3: =MIN(AF3,AG3) -> 0 | AI3: =G3+AH3 -> 112 | AJ3: =MAX(0,E3+F3-AI3) -> 9655.7394 | AK3: =MAX(0,AF3-AH3) -> 0 | AL3: =MAX(0,H3+I3-J3) -> 12632.951 | AM3: =MIN(AK3,AL3) -> 0 | AN3: =J3+AM3 -> 142 | AO3: =MAX(0,H3+I3-AN3) -> 12632.951 | AP3: =MAX(0,AK3-AM3) -> 0 | AQ3: =MAX(0,K3+L3-M3) -> 15000.553 | AR3: =MIN(AP3,AQ3) -> 0 | AS3: =M3+AR3 -> 178 | AT3: =MAX(0,K3+L3-AS3) -> 15000.553 | AU3: =MAX(0,AP3-AR3) -> 0 | AV3: =MAX(0,N3+O3-P3) -> 27547.181 | AW3: =MIN(AU3,AV3) -> 0 | AX3: =P3+AW3 -> 410 | AY3: =MAX(0,N3+O3-AX3) -> 27547.181 | AZ3: =MAX(0,AU3-AW3) -> 0 | BA3: =MAX(0,Q3+R3-S3) -> 0 | BB3: =MIN(AZ3,BA3) -> 0 | BC3: =S3+BB3 -> 0 | BD3: =MAX(0,Q3+R3-BC3) -> 0 | BE3: =MAX(0,AZ3-BB3) -> 0 | BF3: =MAX(0,T3+U3-V3) -> 0 | BG3: =MIN(BE3,BF3) -> 0 | BH3: =V3+BG3 -> 0 | BI3: =MAX(0,T3+U3-BH3) -> 0 | BJ3: =MAX(0,BE3-BG3) -> 0 | BK3: =MAX(0,W3+X3-Y3) -> 0 | BL3: =MIN(BJ3,BK3) -> 0 | BM3: =Y3+BL3 -> 0 | BN3: =MAX(0,W3+X3-BM3) -> 0 | BO3: =AD3+AI3+AN3+AS3+AX3+BC3+BH3+BM3 -> 1400 | BP3: =C3+F3+I3+L3+O3+R3+U3+X3 -> 387.64739 | BQ3: =AE3+AJ3+AO3+AT3+AY3+BD3+BI3+BN3 -> 71979.947
A4: 3 | B4: =IF(A4=1,IF(OR('My Loans'!$O$14="",'My Loans'!$O$14=0),0,INDIRECT("'My Loans'!$D"&'My Loans'!$O$14)),AE3) -> 7143.5228 | C4: =IF(OR('My Loans'!$O$14="",'My Loans'!$O$14=0),0,B4*INDIRECT("'My Loans'!$E"&'My Loans'!$O$14)/12) -> 26.788211 | D4: =IF(OR('My Loans'!$O$14="",'My Loans'!$O$14=0),0,IF(B4<0.005,0,MIN(INDIRECT("'My Loans'!$F"&'My Loans'!$O$14),B4+C4))) -> 95 | E4: =IF(A4=1,IF(OR('My Loans'!$O$15="",'My Loans'!$O$15=0),0,INDIRECT("'My Loans'!$D"&'My Loans'!$O$15)),AJ3) -> 9655.7394 | F4: =IF(OR('My Loans'!$O$15="",'My Loans'!$O$15=0),0,E4*INDIRECT("'My Loans'!$E"&'My Loans'!$O$15)/12) -> 39.427603 | G4: =IF(OR('My Loans'!$O$15="",'My Loans'!$O$15=0),0,IF(E4<0.005,0,MIN(INDIRECT("'My Loans'!$F"&'My Loans'!$O$15),E4+F4))) -> 112 | H4: =IF(A4=1,IF(OR('My Loans'!$O$16="",'My Loans'!$O$16=0),0,INDIRECT("'My Loans'!$D"&'My Loans'!$O$16)),AO3) -> 12632.951 | I4: =IF(OR('My Loans'!$O$16="",'My Loans'!$O$16=0),0,H4*INDIRECT("'My Loans'!$E"&'My Loans'!$O$16)/12) -> 57.901027 | J4: =IF(OR('My Loans'!$O$16="",'My Loans'!$O$16=0),0,IF(H4<0.005,0,MIN(INDIRECT("'My Loans'!$F"&'My Loans'!$O$16),H4+I4))) -> 142 | K4: =IF(A4=1,IF(OR('My Loans'!$O$17="",'My Loans'!$O$17=0),0,INDIRECT("'My Loans'!$D"&'My Loans'!$O$17)),AT3) -> 15000.553 | L4: =IF(OR('My Loans'!$O$17="",'My Loans'!$O$17=0),0,K4*INDIRECT("'My Loans'!$E"&'My Loans'!$O$17)/12) -> 77.502856 | M4: =IF(OR('My Loans'!$O$17="",'My Loans'!$O$17=0),0,IF(K4<0.005,0,MIN(INDIRECT("'My Loans'!$F"&'My Loans'!$O$17),K4+L4))) -> 178 | N4: =IF(A4=1,IF(OR('My Loans'!$O$18="",'My Loans'!$O$18=0),0,INDIRECT("'My Loans'!$D"&'My Loans'!$O$18)),AY3) -> 27547.181 | O4: =IF(OR('My Loans'!$O$18="",'My Loans'!$O$18=0),0,N4*INDIRECT("'My Loans'!$E"&'My Loans'!$O$18)/12) -> 181.35228 | P4: =IF(OR('My Loans'!$O$18="",'My Loans'!$O$18=0),0,IF(N4<0.005,0,MIN(INDIRECT("'My Loans'!$F"&'My Loans'!$O$18),N4+O4))) -> 410 | Q4: =IF(A4=1,IF(OR('My Loans'!$O$19="",'My Loans'!$O$19=0),0,INDIRECT("'My Loans'!$D"&'My Loans'!$O$19)),BD3) -> 0 | R4: =IF(OR('My Loans'!$O$19="",'My Loans'!$O$19=0),0,Q4*INDIRECT("'My Loans'!$E"&'My Loans'!$O$19)/12) -> 0 | S4: =IF(OR('My Loans'!$O$19="",'My Loans'!$O$19=0),0,IF(Q4<0.005,0,MIN(INDIRECT("'My Loans'!$F"&'My Loans'!$O$19),Q4+R4))) -> 0 | T4: =IF(A4=1,IF(OR('My Loans'!$O$20="",'My Loans'!$O$20=0),0,INDIRECT("'My Loans'!$D"&'My Loans'!$O$20)),BI3) -> 0 | U4: =IF(OR('My Loans'!$O$20="",'My Loans'!$O$20=0),0,T4*INDIRECT("'My Loans'!$E"&'My Loans'!$O$20)/12) -> 0 | V4: =IF(OR('My Loans'!$O$20="",'My Loans'!$O$20=0),0,IF(T4<0.005,0,MIN(INDIRECT("'My Loans'!$F"&'My Loans'!$O$20),T4+U4))) -> 0 | W4: =IF(A4=1,IF(OR('My Loans'!$O$21="",'My Loans'!$O$21=0),0,INDIRECT("'My Loans'!$D"&'My Loans'!$O$21)),BN3) -> 0 | X4: =IF(OR('My Loans'!$O$21="",'My Loans'!$O$21=0),0,W4*INDIRECT("'My Loans'!$E"&'My Loans'!$O$21)/12) -> 0 | Y4: =IF(OR('My Loans'!$O$21="",'My Loans'!$O$21=0),0,IF(W4<0.005,0,MIN(INDIRECT("'My Loans'!$F"&'My Loans'!$O$21),W4+X4))) -> 0 | Z4: ='My Loans'!$B$13-(D4+G4+J4+M4+P4+S4+V4+Y4) -> 463 | AA4: =MAX(0,Z4) -> 463 | AB4: =MAX(0,B4+C4-D4) -> 7075.311 | AC4: =MIN(AA4,AB4) -> 463 | AD4: =D4+AC4 -> 558 | AE4: =MAX(0,B4+C4-AD4) -> 6612.311 | AF4: =MAX(0,AA4-AC4) -> 0 | AG4: =MAX(0,E4+F4-G4) -> 9583.167 | AH4: =MIN(AF4,AG4) -> 0 | AI4: =G4+AH4 -> 112 | AJ4: =MAX(0,E4+F4-AI4) -> 9583.167 | AK4: =MAX(0,AF4-AH4) -> 0 | AL4: =MAX(0,H4+I4-J4) -> 12548.852 | AM4: =MIN(AK4,AL4) -> 0 | AN4: =J4+AM4 -> 142 | AO4: =MAX(0,H4+I4-AN4) -> 12548.852 | AP4: =MAX(0,AK4-AM4) -> 0 | AQ4: =MAX(0,K4+L4-M4) -> 14900.056 | AR4: =MIN(AP4,AQ4) -> 0 | AS4: =M4+AR4 -> 178 | AT4: =MAX(0,K4+L4-AS4) -> 14900.056 | AU4: =MAX(0,AP4-AR4) -> 0 | AV4: =MAX(0,N4+O4-P4) -> 27318.533 | AW4: =MIN(AU4,AV4) -> 0 | AX4: =P4+AW4 -> 410 | AY4: =MAX(0,N4+O4-AX4) -> 27318.533 | AZ4: =MAX(0,AU4-AW4) -> 0 | BA4: =MAX(0,Q4+R4-S4) -> 0 | BB4: =MIN(AZ4,BA4) -> 0 | BC4: =S4+BB4 -> 0 | BD4: =MAX(0,Q4+R4-BC4) -> 0 | BE4: =MAX(0,AZ4-BB4) -> 0 | BF4: =MAX(0,T4+U4-V4) -> 0 | BG4: =MIN(BE4,BF4) -> 0 | BH4: =V4+BG4 -> 0 | BI4: =MAX(0,T4+U4-BH4) -> 0 | BJ4: =MAX(0,BE4-BG4) -> 0 | BK4: =MAX(0,W4+X4-Y4) -> 0 | BL4: =MIN(BJ4,BK4) -> 0 | BM4: =Y4+BL4 -> 0 | BN4: =MAX(0,W4+X4-BM4) -> 0 | BO4: =AD4+AI4+AN4+AS4+AX4+BC4+BH4+BM4 -> 1400 | BP4: =C4+F4+I4+L4+O4+R4+U4+X4 -> 382.97197 | BQ4: =AE4+AJ4+AO4+AT4+AY4+BD4+BI4+BN4 -> 70962.919
A5: 4 | B5: =IF(A5=1,IF(OR('My Loans'!$O$14="",'My Loans'!$O$14=0),0,INDIRECT("'My Loans'!$D"&'My Loans'!$O$14)),AE4) -> 6612.311 | C5: =IF(OR('My Loans'!$O$14="",'My Loans'!$O$14=0),0,B5*INDIRECT("'My Loans'!$E"&'My Loans'!$O$14)/12) -> 24.796166 | D5: =IF(OR('My Loans'!$O$14="",'My Loans'!$O$14=0),0,IF(B5<0.005,0,MIN(INDIRECT("'My Loans'!$F"&'My Loans'!$O$14),B5+C5))) -> 95 | E5: =IF(A5=1,IF(OR('My Loans'!$O$15="",'My Loans'!$O$15=0),0,INDIRECT("'My Loans'!$D"&'My Loans'!$O$15)),AJ4) -> 9583.167 | F5: =IF(OR('My Loans'!$O$15="",'My Loans'!$O$15=0),0,E5*INDIRECT("'My Loans'!$E"&'My Loans'!$O$15)/12) -> 39.131265 | G5: =IF(OR('My Loans'!$O$15="",'My Loans'!$O$15=0),0,IF(E5<0.005,0,MIN(INDIRECT("'My Loans'!$F"&'My Loans'!$O$15),E5+F5))) -> 112 | H5: =IF(A5=1,IF(OR('My Loans'!$O$16="",'My Loans'!$O$16=0),0,INDIRECT("'My Loans'!$D"&'My Loans'!$O$16)),AO4) -> 12548.852 | I5: =IF(OR('My Loans'!$O$16="",'My Loans'!$O$16=0),0,H5*INDIRECT("'My Loans'!$E"&'My Loans'!$O$16)/12) -> 57.515574 | J5: =IF(OR('My Loans'!$O$16="",'My Loans'!$O$16=0),0,IF(H5<0.005,0,MIN(INDIRECT("'My Loans'!$F"&'My Loans'!$O$16),H5+I5))) -> 142 | K5: =IF(A5=1,IF(OR('My Loans'!$O$17="",'My Loans'!$O$17=0),0,INDIRECT("'My Loans'!$D"&'My Loans'!$O$17)),AT4) -> 14900.056 | L5: =IF(OR('My Loans'!$O$17="",'My Loans'!$O$17=0),0,K5*INDIRECT("'My Loans'!$E"&'My Loans'!$O$17)/12) -> 76.983621 | M5: =IF(OR('My Loans'!$O$17="",'My Loans'!$O$17=0),0,IF(K5<0.005,0,MIN(INDIRECT("'My Loans'!$F"&'My Loans'!$O$17),K5+L5))) -> 178 | N5: =IF(A5=1,IF(OR('My Loans'!$O$18="",'My Loans'!$O$18=0),0,INDIRECT("'My Loans'!$D"&'My Loans'!$O$18)),AY4) -> 27318.533 | O5: =IF(OR('My Loans'!$O$18="",'My Loans'!$O$18=0),0,N5*INDIRECT("'My Loans'!$E"&'My Loans'!$O$18)/12) -> 179.84701 | P5: =IF(OR('My Loans'!$O$18="",'My Loans'!$O$18=0),0,IF(N5<0.005,0,MIN(INDIRECT("'My Loans'!$F"&'My Loans'!$O$18),N5+O5))) -> 410 | Q5: =IF(A5=1,IF(OR('My Loans'!$O$19="",'My Loans'!$O$19=0),0,INDIRECT("'My Loans'!$D"&'My Loans'!$O$19)),BD4) -> 0 | R5: =IF(OR('My Loans'!$O$19="",'My Loans'!$O$19=0),0,Q5*INDIRECT("'My Loans'!$E"&'My Loans'!$O$19)/12) -> 0 | S5: =IF(OR('My Loans'!$O$19="",'My Loans'!$O$19=0),0,IF(Q5<0.005,0,MIN(INDIRECT("'My Loans'!$F"&'My Loans'!$O$19),Q5+R5))) -> 0 | T5: =IF(A5=1,IF(OR('My Loans'!$O$20="",'My Loans'!$O$20=0),0,INDIRECT("'My Loans'!$D"&'My Loans'!$O$20)),BI4) -> 0 | U5: =IF(OR('My Loans'!$O$20="",'My Loans'!$O$20=0),0,T5*INDIRECT("'My Loans'!$E"&'My Loans'!$O$20)/12) -> 0 | V5: =IF(OR('My Loans'!$O$20="",'My Loans'!$O$20=0),0,IF(T5<0.005,0,MIN(INDIRECT("'My Loans'!$F"&'My Loans'!$O$20),T5+U5))) -> 0 | W5: =IF(A5=1,IF(OR('My Loans'!$O$21="",'My Loans'!$O$21=0),0,INDIRECT("'My Loans'!$D"&'My Loans'!$O$21)),BN4) -> 0 | X5: =IF(OR('My Loans'!$O$21="",'My Loans'!$O$21=0),0,W5*INDIRECT("'My Loans'!$E"&'My Loans'!$O$21)/12) -> 0 | Y5: =IF(OR('My Loans'!$O$21="",'My Loans'!$O$21=0),0,IF(W5<0.005,0,MIN(INDIRECT("'My Loans'!$F"&'My Loans'!$O$21),W5+X5))) -> 0 | Z5: ='My Loans'!$B$13-(D5+G5+J5+M5+P5+S5+V5+Y5) -> 463 | AA5: =MAX(0,Z5) -> 463 | AB5: =MAX(0,B5+C5-D5) -> 6542.1072 | AC5: =MIN(AA5,AB5) -> 463 | AD5: =D5+AC5 -> 558 | AE5: =MAX(0,B5+C5-AD5) -> 6079.1072 | AF5: =MAX(0,AA5-AC5) -> 0 | AG5: =MAX(0,E5+F5-G5) -> 9510.2983 | AH5: =MIN(AF5,AG5) -> 0 | AI5: =G5+AH5 -> 112 | AJ5: =MAX(0,E5+F5-AI5) -> 9510.2983 | AK5: =MAX(0,AF5-AH5) -> 0 | AL5: =MAX(0,H5+I5-J5) -> 12464.368 | AM5: =MIN(AK5,AL5) -> 0 | AN5: =J5+AM5 -> 142 | AO5: =MAX(0,H5+I5-AN5) -> 12464.368 | AP5: =MAX(0,AK5-AM5) -> 0 | AQ5: =MAX(0,K5+L5-M5) -> 14799.039 | AR5: =MIN(AP5,AQ5) -> 0 | AS5: =M5+AR5 -> 178 | AT5: =MAX(0,K5+L5-AS5) -> 14799.039 | AU5: =MAX(0,AP5-AR5) -> 0 | AV5: =MAX(0,N5+O5-P5) -> 27088.38 | AW5: =MIN(AU5,AV5) -> 0 | AX5: =P5+AW5 -> 410 | AY5: =MAX(0,N5+O5-AX5) -> 27088.38 | AZ5: =MAX(0,AU5-AW5) -> 0 | BA5: =MAX(0,Q5+R5-S5) -> 0 | BB5: =MIN(AZ5,BA5) -> 0 | BC5: =S5+BB5 -> 0 | BD5: =MAX(0,Q5+R5-BC5) -> 0 | BE5: =MAX(0,AZ5-BB5) -> 0 | BF5: =MAX(0,T5+U5-V5) -> 0 | BG5: =MIN(BE5,BF5) -> 0 | BH5: =V5+BG5 -> 0 | BI5: =MAX(0,T5+U5-BH5) -> 0 | BJ5: =MAX(0,BE5-BG5) -> 0 | BK5: =MAX(0,W5+X5-Y5) -> 0 | BL5: =MIN(BJ5,BK5) -> 0 | BM5: =Y5+BL5 -> 0 | BN5: =MAX(0,W5+X5-BM5) -> 0 | BO5: =AD5+AI5+AN5+AS5+AX5+BC5+BH5+BM5 -> 1400 | BP5: =C5+F5+I5+L5+O5+R5+U5+X5 -> 378.27364 | BQ5: =AE5+AJ5+AO5+AT5+AY5+BD5+BI5+BN5 -> 69941.193
A6: 5 | B6: =IF(A6=1,IF(OR('My Loans'!$O$14="",'My Loans'!$O$14=0),0,INDIRECT("'My Loans'!$D"&'My Loans'!$O$14)),AE5) -> 6079.1072 | C6: =IF(OR('My Loans'!$O$14="",'My Loans'!$O$14=0),0,B6*INDIRECT("'My Loans'!$E"&'My Loans'!$O$14)/12) -> 22.796652 | D6: =IF(OR('My Loans'!$O$14="",'My Loans'!$O$14=0),0,IF(B6<0.005,0,MIN(INDIRECT("'My Loans'!$F"&'My Loans'!$O$14),B6+C6))) -> 95 | E6: =IF(A6=1,IF(OR('My Loans'!$O$15="",'My Loans'!$O$15=0),0,INDIRECT("'My Loans'!$D"&'My Loans'!$O$15)),AJ5) -> 9510.2983 | F6: =IF(OR('My Loans'!$O$15="",'My Loans'!$O$15=0),0,E6*INDIRECT("'My Loans'!$E"&'My Loans'!$O$15)/12) -> 38.833718 | G6: =IF(OR('My Loans'!$O$15="",'My Loans'!$O$15=0),0,IF(E6<0.005,0,MIN(INDIRECT("'My Loans'!$F"&'My Loans'!$O$15),E6+F6))) -> 112 | H6: =IF(A6=1,IF(OR('My Loans'!$O$16="",'My Loans'!$O$16=0),0,INDIRECT("'My Loans'!$D"&'My Loans'!$O$16)),AO5) -> 12464.368 | I6: =IF(OR('My Loans'!$O$16="",'My Loans'!$O$16=0),0,H6*INDIRECT("'My Loans'!$E"&'My Loans'!$O$16)/12) -> 57.128353 | J6: =IF(OR('My Loans'!$O$16="",'My Loans'!$O$16=0),0,IF(H6<0.005,0,MIN(INDIRECT("'My Loans'!$F"&'My Loans'!$O$16),H6+I6))) -> 142 | K6: =IF(A6=1,IF(OR('My Loans'!$O$17="",'My Loans'!$O$17=0),0,INDIRECT("'My Loans'!$D"&'My Loans'!$O$17)),AT5) -> 14799.039 | L6: =IF(OR('My Loans'!$O$17="",'My Loans'!$O$17=0),0,K6*INDIRECT("'My Loans'!$E"&'My Loans'!$O$17)/12) -> 76.461703 | M6: =IF(OR('My Loans'!$O$17="",'My Loans'!$O$17=0),0,IF(K6<0.005,0,MIN(INDIRECT("'My Loans'!$F"&'My Loans'!$O$17),K6+L6))) -> 178 | N6: =IF(A6=1,IF(OR('My Loans'!$O$18="",'My Loans'!$O$18=0),0,INDIRECT("'My Loans'!$D"&'My Loans'!$O$18)),AY5) -> 27088.38 | O6: =IF(OR('My Loans'!$O$18="",'My Loans'!$O$18=0),0,N6*INDIRECT("'My Loans'!$E"&'My Loans'!$O$18)/12) -> 178.33184 | P6: =IF(OR('My Loans'!$O$18="",'My Loans'!$O$18=0),0,IF(N6<0.005,0,MIN(INDIRECT("'My Loans'!$F"&'My Loans'!$O$18),N6+O6))) -> 410 | Q6: =IF(A6=1,IF(OR('My Loans'!$O$19="",'My Loans'!$O$19=0),0,INDIRECT("'My Loans'!$D"&'My Loans'!$O$19)),BD5) -> 0 | R6: =IF(OR('My Loans'!$O$19="",'My Loans'!$O$19=0),0,Q6*INDIRECT("'My Loans'!$E"&'My Loans'!$O$19)/12) -> 0 | S6: =IF(OR('My Loans'!$O$19="",'My Loans'!$O$19=0),0,IF(Q6<0.005,0,MIN(INDIRECT("'My Loans'!$F"&'My Loans'!$O$19),Q6+R6))) -> 0 | T6: =IF(A6=1,IF(OR('My Loans'!$O$20="",'My Loans'!$O$20=0),0,INDIRECT("'My Loans'!$D"&'My Loans'!$O$20)),BI5) -> 0 | U6: =IF(OR('My Loans'!$O$20="",'My Loans'!$O$20=0),0,T6*INDIRECT("'My Loans'!$E"&'My Loans'!$O$20)/12) -> 0 | V6: =IF(OR('My Loans'!$O$20="",'My Loans'!$O$20=0),0,IF(T6<0.005,0,MIN(INDIRECT("'My Loans'!$F"&'My Loans'!$O$20),T6+U6))) -> 0 | W6: =IF(A6=1,IF(OR('My Loans'!$O$21="",'My Loans'!$O$21=0),0,INDIRECT("'My Loans'!$D"&'My Loans'!$O$21)),BN5) -> 0 | X6: =IF(OR('My Loans'!$O$21="",'My Loans'!$O$21=0),0,W6*INDIRECT("'My Loans'!$E"&'My Loans'!$O$21)/12) -> 0 | Y6: =IF(OR('My Loans'!$O$21="",'My Loans'!$O$21=0),0,IF(W6<0.005,0,MIN(INDIRECT("'My Loans'!$F"&'My Loans'!$O$21),W6+X6))) -> 0 | Z6: ='My Loans'!$B$13-(D6+G6+J6+M6+P6+S6+V6+Y6) -> 463 | AA6: =MAX(0,Z6) -> 463 | AB6: =MAX(0,B6+C6-D6) -> 6006.9038 | AC6: =MIN(AA6,AB6) -> 463 | AD6: =D6+AC6 -> 558 | AE6: =MAX(0,B6+C6-AD6) -> 5543.9038 | AF6: =MAX(0,AA6-AC6) -> 0 | AG6: =MAX(0,E6+F6-G6) -> 9437.132 | AH6: =MIN(AF6,AG6) -> 0 | AI6: =G6+AH6 -> 112 | AJ6: =MAX(0,E6+F6-AI6) -> 9437.132 | AK6: =MAX(0,AF6-AH6) -> 0 | AL6: =MAX(0,H6+I6-J6) -> 12379.496 | AM6: =MIN(AK6,AL6) -> 0 | AN6: =J6+AM6 -> 142 | AO6: =MAX(0,H6+I6-AN6) -> 12379.496 | AP6: =MAX(0,AK6-AM6) -> 0 | AQ6: =MAX(0,K6+L6-M6) -> 14697.501 | AR6: =MIN(AP6,AQ6) -> 0 | AS6: =M6+AR6 -> 178 | AT6: =MAX(0,K6+L6-AS6) -> 14697.501 | AU6: =MAX(0,AP6-AR6) -> 0 | AV6: =MAX(0,N6+O6-P6) -> 26856.712 | AW6: =MIN(AU6,AV6) -> 0 | AX6: =P6+AW6 -> 410 | AY6: =MAX(0,N6+O6-AX6) -> 26856.712 | AZ6: =MAX(0,AU6-AW6) -> 0 | BA6: =MAX(0,Q6+R6-S6) -> 0 | BB6: =MIN(AZ6,BA6) -> 0 | BC6: =S6+BB6 -> 0 | BD6: =MAX(0,Q6+R6-BC6) -> 0 | BE6: =MAX(0,AZ6-BB6) -> 0 | BF6: =MAX(0,T6+U6-V6) -> 0 | BG6: =MIN(BE6,BF6) -> 0 | BH6: =V6+BG6 -> 0 | BI6: =MAX(0,T6+U6-BH6) -> 0 | BJ6: =MAX(0,BE6-BG6) -> 0 | BK6: =MAX(0,W6+X6-Y6) -> 0 | BL6: =MIN(BJ6,BK6) -> 0 | BM6: =Y6+BL6 -> 0 | BN6: =MAX(0,W6+X6-BM6) -> 0 | BO6: =AD6+AI6+AN6+AS6+AX6+BC6+BH6+BM6 -> 1400 | BP6: =C6+F6+I6+L6+O6+R6+U6+X6 -> 373.55226 | BQ6: =AE6+AJ6+AO6+AT6+AY6+BD6+BI6+BN6 -> 68914.745
A7: 6 | B7: =IF(A7=1,IF(OR('My Loans'!$O$14="",'My Loans'!$O$14=0),0,INDIRECT("'My Loans'!$D"&'My Loans'!$O$14)),AE6) -> 5543.9038 | C7: =IF(OR('My Loans'!$O$14="",'My Loans'!$O$14=0),0,B7*INDIRECT("'My Loans'!$E"&'My Loans'!$O$14)/12) -> 20.789639 | D7: =IF(OR('My Loans'!$O$14="",'My Loans'!$O$14=0),0,IF(B7<0.005,0,MIN(INDIRECT("'My Loans'!$F"&'My Loans'!$O$14),B7+C7))) -> 95 | E7: =IF(A7=1,IF(OR('My Loans'!$O$15="",'My Loans'!$O$15=0),0,INDIRECT("'My Loans'!$D"&'My Loans'!$O$15)),AJ6) -> 9437.132 | F7: =IF(OR('My Loans'!$O$15="",'My Loans'!$O$15=0),0,E7*INDIRECT("'My Loans'!$E"&'My Loans'!$O$15)/12) -> 38.534956 | G7: =IF(OR('My Loans'!$O$15="",'My Loans'!$O$15=0),0,IF(E7<0.005,0,MIN(INDIRECT("'My Loans'!$F"&'My Loans'!$O$15),E7+F7))) -> 112 | H7: =IF(A7=1,IF(OR('My Loans'!$O$16="",'My Loans'!$O$16=0),0,INDIRECT("'My Loans'!$D"&'My Loans'!$O$16)),AO6) -> 12379.496 | I7: =IF(OR('My Loans'!$O$16="",'My Loans'!$O$16=0),0,H7*INDIRECT("'My Loans'!$E"&'My Loans'!$O$16)/12) -> 56.739358 | J7: =IF(OR('My Loans'!$O$16="",'My Loans'!$O$16=0),0,IF(H7<0.005,0,MIN(INDIRECT("'My Loans'!$F"&'My Loans'!$O$16),H7+I7))) -> 142 | K7: =IF(A7=1,IF(OR('My Loans'!$O$17="",'My Loans'!$O$17=0),0,INDIRECT("'My Loans'!$D"&'My Loans'!$O$17)),AT6) -> 14697.501 | L7: =IF(OR('My Loans'!$O$17="",'My Loans'!$O$17=0),0,K7*INDIRECT("'My Loans'!$E"&'My Loans'!$O$17)/12) -> 75.937088 | M7: =IF(OR('My Loans'!$O$17="",'My Loans'!$O$17=0),0,IF(K7<0.005,0,MIN(INDIRECT("'My Loans'!$F"&'My Loans'!$O$17),K7+L7))) -> 178 | N7: =IF(A7=1,IF(OR('My Loans'!$O$18="",'My Loans'!$O$18=0),0,INDIRECT("'My Loans'!$D"&'My Loans'!$O$18)),AY6) -> 26856.712 | O7: =IF(OR('My Loans'!$O$18="",'My Loans'!$O$18=0),0,N7*INDIRECT("'My Loans'!$E"&'My Loans'!$O$18)/12) -> 176.80669 | P7: =IF(OR('My Loans'!$O$18="",'My Loans'!$O$18=0),0,IF(N7<0.005,0,MIN(INDIRECT("'My Loans'!$F"&'My Loans'!$O$18),N7+O7))) -> 410 | Q7: =IF(A7=1,IF(OR('My Loans'!$O$19="",'My Loans'!$O$19=0),0,INDIRECT("'My Loans'!$D"&'My Loans'!$O$19)),BD6) -> 0 | R7: =IF(OR('My Loans'!$O$19="",'My Loans'!$O$19=0),0,Q7*INDIRECT("'My Loans'!$E"&'My Loans'!$O$19)/12) -> 0 | S7: =IF(OR('My Loans'!$O$19="",'My Loans'!$O$19=0),0,IF(Q7<0.005,0,MIN(INDIRECT("'My Loans'!$F"&'My Loans'!$O$19),Q7+R7))) -> 0 | T7: =IF(A7=1,IF(OR('My Loans'!$O$20="",'My Loans'!$O$20=0),0,INDIRECT("'My Loans'!$D"&'My Loans'!$O$20)),BI6) -> 0 | U7: =IF(OR('My Loans'!$O$20="",'My Loans'!$O$20=0),0,T7*INDIRECT("'My Loans'!$E"&'My Loans'!$O$20)/12) -> 0 | V7: =IF(OR('My Loans'!$O$20="",'My Loans'!$O$20=0),0,IF(T7<0.005,0,MIN(INDIRECT("'My Loans'!$F"&'My Loans'!$O$20),T7+U7))) -> 0 | W7: =IF(A7=1,IF(OR('My Loans'!$O$21="",'My Loans'!$O$21=0),0,INDIRECT("'My Loans'!$D"&'My Loans'!$O$21)),BN6) -> 0 | X7: =IF(OR('My Loans'!$O$21="",'My Loans'!$O$21=0),0,W7*INDIRECT("'My Loans'!$E"&'My Loans'!$O$21)/12) -> 0 | Y7: =IF(OR('My Loans'!$O$21="",'My Loans'!$O$21=0),0,IF(W7<0.005,0,MIN(INDIRECT("'My Loans'!$F"&'My Loans'!$O$21),W7+X7))) -> 0 | Z7: ='My Loans'!$B$13-(D7+G7+J7+M7+P7+S7+V7+Y7) -> 463 | AA7: =MAX(0,Z7) -> 463 | AB7: =MAX(0,B7+C7-D7) -> 5469.6935 | AC7: =MIN(AA7,AB7) -> 463 | AD7: =D7+AC7 -> 558 | AE7: =MAX(0,B7+C7-AD7) -> 5006.6935 | AF7: =MAX(0,AA7-AC7) -> 0 | AG7: =MAX(0,E7+F7-G7) -> 9363.6669 | AH7: =MIN(AF7,AG7) -> 0 | AI7: =G7+AH7 -> 112 | AJ7: =MAX(0,E7+F7-AI7) -> 9363.6669 | AK7: =MAX(0,AF7-AH7) -> 0 | AL7: =MAX(0,H7+I7-J7) -> 12294.236 | AM7: =MIN(AK7,AL7) -> 0 | AN7: =J7+AM7 -> 142 | AO7: =MAX(0,H7+I7-AN7) -> 12294.236 | AP7: =MAX(0,AK7-AM7) -> 0 | AQ7: =MAX(0,K7+L7-M7) -> 14595.438 | AR7: =MIN(AP7,AQ7) -> 0 | AS7: =M7+AR7 -> 178 | AT7: =MAX(0,K7+L7-AS7) -> 14595.438 | AU7: =MAX(0,AP7-AR7) -> 0 | AV7: =MAX(0,N7+O7-P7) -> 26623.519 | AW7: =MIN(AU7,AV7) -> 0 | AX7: =P7+AW7 -> 410 | AY7: =MAX(0,N7+O7-AX7) -> 26623.519 | AZ7: =MAX(0,AU7-AW7) -> 0 | BA7: =MAX(0,Q7+R7-S7) -> 0 | BB7: =MIN(AZ7,BA7) -> 0 | BC7: =S7+BB7 -> 0 | BD7: =MAX(0,Q7+R7-BC7) -> 0 | BE7: =MAX(0,AZ7-BB7) -> 0 | BF7: =MAX(0,T7+U7-V7) -> 0 | BG7: =MIN(BE7,BF7) -> 0 | BH7: =V7+BG7 -> 0 | BI7: =MAX(0,T7+U7-BH7) -> 0 | BJ7: =MAX(0,BE7-BG7) -> 0 | BK7: =MAX(0,W7+X7-Y7) -> 0 | BL7: =MIN(BJ7,BK7) -> 0 | BM7: =Y7+BL7 -> 0 | BN7: =MAX(0,W7+X7-BM7) -> 0 | BO7: =AD7+AI7+AN7+AS7+AX7+BC7+BH7+BM7 -> 1400 | BP7: =C7+F7+I7+L7+O7+R7+U7+X7 -> 368.80773 | BQ7: =AE7+AJ7+AO7+AT7+AY7+BD7+BI7+BN7 -> 67883.553
A8: 7 | B8: =IF(A8=1,IF(OR('My Loans'!$O$14="",'My Loans'!$O$14=0),0,INDIRECT("'My Loans'!$D"&'My Loans'!$O$14)),AE7) -> 5006.6935 | C8: =IF(OR('My Loans'!$O$14="",'My Loans'!$O$14=0),0,B8*INDIRECT("'My Loans'!$E"&'My Loans'!$O$14)/12) -> 18.775101 | D8: =IF(OR('My Loans'!$O$14="",'My Loans'!$O$14=0),0,IF(B8<0.005,0,MIN(INDIRECT("'My Loans'!$F"&'My Loans'!$O$14),B8+C8))) -> 95 | E8: =IF(A8=1,IF(OR('My Loans'!$O$15="",'My Loans'!$O$15=0),0,INDIRECT("'My Loans'!$D"&'My Loans'!$O$15)),AJ7) -> 9363.6669 | F8: =IF(OR('My Loans'!$O$15="",'My Loans'!$O$15=0),0,E8*INDIRECT("'My Loans'!$E"&'My Loans'!$O$15)/12) -> 38.234973 | G8: =IF(OR('My Loans'!$O$15="",'My Loans'!$O$15=0),0,IF(E8<0.005,0,MIN(INDIRECT("'My Loans'!$F"&'My Loans'!$O$15),E8+F8))) -> 112 | H8: =IF(A8=1,IF(OR('My Loans'!$O$16="",'My Loans'!$O$16=0),0,INDIRECT("'My Loans'!$D"&'My Loans'!$O$16)),AO7) -> 12294.236 | I8: =IF(OR('My Loans'!$O$16="",'My Loans'!$O$16=0),0,H8*INDIRECT("'My Loans'!$E"&'My Loans'!$O$16)/12) -> 56.34858 | J8: =IF(OR('My Loans'!$O$16="",'My Loans'!$O$16=0),0,IF(H8<0.005,0,MIN(INDIRECT("'My Loans'!$F"&'My Loans'!$O$16),H8+I8))) -> 142 | K8: =IF(A8=1,IF(OR('My Loans'!$O$17="",'My Loans'!$O$17=0),0,INDIRECT("'My Loans'!$D"&'My Loans'!$O$17)),AT7) -> 14595.438 | L8: =IF(OR('My Loans'!$O$17="",'My Loans'!$O$17=0),0,K8*INDIRECT("'My Loans'!$E"&'My Loans'!$O$17)/12) -> 75.409763 | M8: =IF(OR('My Loans'!$O$17="",'My Loans'!$O$17=0),0,IF(K8<0.005,0,MIN(INDIRECT("'My Loans'!$F"&'My Loans'!$O$17),K8+L8))) -> 178 | N8: =IF(A8=1,IF(OR('My Loans'!$O$18="",'My Loans'!$O$18=0),0,INDIRECT("'My Loans'!$D"&'My Loans'!$O$18)),AY7) -> 26623.519 | O8: =IF(OR('My Loans'!$O$18="",'My Loans'!$O$18=0),0,N8*INDIRECT("'My Loans'!$E"&'My Loans'!$O$18)/12) -> 175.2715 | P8: =IF(OR('My Loans'!$O$18="",'My Loans'!$O$18=0),0,IF(N8<0.005,0,MIN(INDIRECT("'My Loans'!$F"&'My Loans'!$O$18),N8+O8))) -> 410 | Q8: =IF(A8=1,IF(OR('My Loans'!$O$19="",'My Loans'!$O$19=0),0,INDIRECT("'My Loans'!$D"&'My Loans'!$O$19)),BD7) -> 0 | R8: =IF(OR('My Loans'!$O$19="",'My Loans'!$O$19=0),0,Q8*INDIRECT("'My Loans'!$E"&'My Loans'!$O$19)/12) -> 0 | S8: =IF(OR('My Loans'!$O$19="",'My Loans'!$O$19=0),0,IF(Q8<0.005,0,MIN(INDIRECT("'My Loans'!$F"&'My Loans'!$O$19),Q8+R8))) -> 0 | T8: =IF(A8=1,IF(OR('My Loans'!$O$20="",'My Loans'!$O$20=0),0,INDIRECT("'My Loans'!$D"&'My Loans'!$O$20)),BI7) -> 0 | U8: =IF(OR('My Loans'!$O$20="",'My Loans'!$O$20=0),0,T8*INDIRECT("'My Loans'!$E"&'My Loans'!$O$20)/12) -> 0 | V8: =IF(OR('My Loans'!$O$20="",'My Loans'!$O$20=0),0,IF(T8<0.005,0,MIN(INDIRECT("'My Loans'!$F"&'My Loans'!$O$20),T8+U8))) -> 0 | W8: =IF(A8=1,IF(OR('My Loans'!$O$21="",'My Loans'!$O$21=0),0,INDIRECT("'My Loans'!$D"&'My Loans'!$O$21)),BN7) -> 0 | X8: =IF(OR('My Loans'!$O$21="",'My Loans'!$O$21=0),0,W8*INDIRECT("'My Loans'!$E"&'My Loans'!$O$21)/12) -> 0 | Y8: =IF(OR('My Loans'!$O$21="",'My Loans'!$O$21=0),0,IF(W8<0.005,0,MIN(INDIRECT("'My Loans'!$F"&'My Loans'!$O$21),W8+X8))) -> 0 | Z8: ='My Loans'!$B$13-(D8+G8+J8+M8+P8+S8+V8+Y8) -> 463 | AA8: =MAX(0,Z8) -> 463 | AB8: =MAX(0,B8+C8-D8) -> 4930.4686 | AC8: =MIN(AA8,AB8) -> 463 | AD8: =D8+AC8 -> 558 | AE8: =MAX(0,B8+C8-AD8) -> 4467.4686 | AF8: =MAX(0,AA8-AC8) -> 0 | AG8: =MAX(0,E8+F8-G8) -> 9289.9019 | AH8: =MIN(AF8,AG8) -> 0 | AI8: =G8+AH8 -> 112 | AJ8: =MAX(0,E8+F8-AI8) -> 9289.9019 | AK8: =MAX(0,AF8-AH8) -> 0 | AL8: =MAX(0,H8+I8-J8) -> 12208.584 | AM8: =MIN(AK8,AL8) -> 0 | AN8: =J8+AM8 -> 142 | AO8: =MAX(0,H8+I8-AN8) -> 12208.584 | AP8: =MAX(0,AK8-AM8) -> 0 | AQ8: =MAX(0,K8+L8-M8) -> 14492.848 | AR8: =MIN(AP8,AQ8) -> 0 | AS8: =M8+AR8 -> 178 | AT8: =MAX(0,K8+L8-AS8) -> 14492.848 | AU8: =MAX(0,AP8-AR8) -> 0 | AV8: =MAX(0,N8+O8-P8) -> 26388.79 | AW8: =MIN(AU8,AV8) -> 0 | AX8: =P8+AW8 -> 410 | AY8: =MAX(0,N8+O8-AX8) -> 26388.79 | AZ8: =MAX(0,AU8-AW8) -> 0 | BA8: =MAX(0,Q8+R8-S8) -> 0 | BB8: =MIN(AZ8,BA8) -> 0 | BC8: =S8+BB8 -> 0 | BD8: =MAX(0,Q8+R8-BC8) -> 0 | BE8: =MAX(0,AZ8-BB8) -> 0 | BF8: =MAX(0,T8+U8-V8) -> 0 | BG8: =MIN(BE8,BF8) -> 0 | BH8: =V8+BG8 -> 0 | BI8: =MAX(0,T8+U8-BH8) -> 0 | BJ8: =MAX(0,BE8-BG8) -> 0 | BK8: =MAX(0,W8+X8-Y8) -> 0 | BL8: =MIN(BJ8,BK8) -> 0 | BM8: =Y8+BL8 -> 0 | BN8: =MAX(0,W8+X8-BM8) -> 0 | BO8: =AD8+AI8+AN8+AS8+AX8+BC8+BH8+BM8 -> 1400 | BP8: =C8+F8+I8+L8+O8+R8+U8+X8 -> 364.03992 | BQ8: =AE8+AJ8+AO8+AT8+AY8+BD8+BI8+BN8 -> 66847.593
A9: 8 | B9: =IF(A9=1,IF(OR('My Loans'!$O$14="",'My Loans'!$O$14=0),0,INDIRECT("'My Loans'!$D"&'My Loans'!$O$14)),AE8) -> 4467.4686 | C9: =IF(OR('My Loans'!$O$14="",'My Loans'!$O$14=0),0,B9*INDIRECT("'My Loans'!$E"&'My Loans'!$O$14)/12) -> 16.753007 | D9: =IF(OR('My Loans'!$O$14="",'My Loans'!$O$14=0),0,IF(B9<0.005,0,MIN(INDIRECT("'My Loans'!$F"&'My Loans'!$O$14),B9+C9))) -> 95 | E9: =IF(A9=1,IF(OR('My Loans'!$O$15="",'My Loans'!$O$15=0),0,INDIRECT("'My Loans'!$D"&'My Loans'!$O$15)),AJ8) -> 9289.9019 | F9: =IF(OR('My Loans'!$O$15="",'My Loans'!$O$15=0),0,E9*INDIRECT("'My Loans'!$E"&'My Loans'!$O$15)/12) -> 37.933766 | G9: =IF(OR('My Loans'!$O$15="",'My Loans'!$O$15=0),0,IF(E9<0.005,0,MIN(INDIRECT("'My Loans'!$F"&'My Loans'!$O$15),E9+F9))) -> 112 | H9: =IF(A9=1,IF(OR('My Loans'!$O$16="",'My Loans'!$O$16=0),0,INDIRECT("'My Loans'!$D"&'My Loans'!$O$16)),AO8) -> 12208.584 | I9: =IF(OR('My Loans'!$O$16="",'My Loans'!$O$16=0),0,H9*INDIRECT("'My Loans'!$E"&'My Loans'!$O$16)/12) -> 55.956011 | J9: =IF(OR('My Loans'!$O$16="",'My Loans'!$O$16=0),0,IF(H9<0.005,0,MIN(INDIRECT("'My Loans'!$F"&'My Loans'!$O$16),H9+I9))) -> 142 | K9: =IF(A9=1,IF(OR('My Loans'!$O$17="",'My Loans'!$O$17=0),0,INDIRECT("'My Loans'!$D"&'My Loans'!$O$17)),AT8) -> 14492.848 | L9: =IF(OR('My Loans'!$O$17="",'My Loans'!$O$17=0),0,K9*INDIRECT("'My Loans'!$E"&'My Loans'!$O$17)/12) -> 74.879714 | M9: =IF(OR('My Loans'!$O$17="",'My Loans'!$O$17=0),0,IF(K9<0.005,0,MIN(INDIRECT("'My Loans'!$F"&'My Loans'!$O$17),K9+L9))) -> 178 | N9: =IF(A9=1,IF(OR('My Loans'!$O$18="",'My Loans'!$O$18=0),0,INDIRECT("'My Loans'!$D"&'My Loans'!$O$18)),AY8) -> 26388.79 | O9: =IF(OR('My Loans'!$O$18="",'My Loans'!$O$18=0),0,N9*INDIRECT("'My Loans'!$E"&'My Loans'!$O$18)/12) -> 173.7262 | P9: =IF(OR('My Loans'!$O$18="",'My Loans'!$O$18=0),0,IF(N9<0.005,0,MIN(INDIRECT("'My Loans'!$F"&'My Loans'!$O$18),N9+O9))) -> 410 | Q9: =IF(A9=1,IF(OR('My Loans'!$O$19="",'My Loans'!$O$19=0),0,INDIRECT("'My Loans'!$D"&'My Loans'!$O$19)),BD8) -> 0 | R9: =IF(OR('My Loans'!$O$19="",'My Loans'!$O$19=0),0,Q9*INDIRECT("'My Loans'!$E"&'My Loans'!$O$19)/12) -> 0 | S9: =IF(OR('My Loans'!$O$19="",'My Loans'!$O$19=0),0,IF(Q9<0.005,0,MIN(INDIRECT("'My Loans'!$F"&'My Loans'!$O$19),Q9+R9))) -> 0 | T9: =IF(A9=1,IF(OR('My Loans'!$O$20="",'My Loans'!$O$20=0),0,INDIRECT("'My Loans'!$D"&'My Loans'!$O$20)),BI8) -> 0 | U9: =IF(OR('My Loans'!$O$20="",'My Loans'!$O$20=0),0,T9*INDIRECT("'My Loans'!$E"&'My Loans'!$O$20)/12) -> 0 | V9: =IF(OR('My Loans'!$O$20="",'My Loans'!$O$20=0),0,IF(T9<0.005,0,MIN(INDIRECT("'My Loans'!$F"&'My Loans'!$O$20),T9+U9))) -> 0 | W9: =IF(A9=1,IF(OR('My Loans'!$O$21="",'My Loans'!$O$21=0),0,INDIRECT("'My Loans'!$D"&'My Loans'!$O$21)),BN8) -> 0 | X9: =IF(OR('My Loans'!$O$21="",'My Loans'!$O$21=0),0,W9*INDIRECT("'My Loans'!$E"&'My Loans'!$O$21)/12) -> 0 | Y9: =IF(OR('My Loans'!$O$21="",'My Loans'!$O$21=0),0,IF(W9<0.005,0,MIN(INDIRECT("'My Loans'!$F"&'My Loans'!$O$21),W9+X9))) -> 0 | Z9: ='My Loans'!$B$13-(D9+G9+J9+M9+P9+S9+V9+Y9) -> 463 | AA9: =MAX(0,Z9) -> 463 | AB9: =MAX(0,B9+C9-D9) -> 4389.2216 | AC9: =MIN(AA9,AB9) -> 463 | AD9: =D9+AC9 -> 558 | AE9: =MAX(0,B9+C9-AD9) -> 3926.2216 | AF9: =MAX(0,AA9-AC9) -> 0 | AG9: =MAX(0,E9+F9-G9) -> 9215.8357 | AH9: =MIN(AF9,AG9) -> 0 | AI9: =G9+AH9 -> 112 | AJ9: =MAX(0,E9+F9-AI9) -> 9215.8357 | AK9: =MAX(0,AF9-AH9) -> 0 | AL9: =MAX(0,H9+I9-J9) -> 12122.54 | AM9: =MIN(AK9,AL9) -> 0 | AN9: =J9+AM9 -> 142 | AO9: =MAX(0,H9+I9-AN9) -> 12122.54 | AP9: =MAX(0,AK9-AM9) -> 0 | AQ9: =MAX(0,K9+L9-M9) -> 14389.727 | AR9: =MIN(AP9,AQ9) -> 0 | AS9: =M9+AR9 -> 178 | AT9: =MAX(0,K9+L9-AS9) -> 14389.727 | AU9: =MAX(0,AP9-AR9) -> 0 | AV9: =MAX(0,N9+O9-P9) -> 26152.517 | AW9: =MIN(AU9,AV9) -> 0 | AX9: =P9+AW9 -> 410 | AY9: =MAX(0,N9+O9-AX9) -> 26152.517 | AZ9: =MAX(0,AU9-AW9) -> 0 | BA9: =MAX(0,Q9+R9-S9) -> 0 | BB9: =MIN(AZ9,BA9) -> 0 | BC9: =S9+BB9 -> 0 | BD9: =MAX(0,Q9+R9-BC9) -> 0 | BE9: =MAX(0,AZ9-BB9) -> 0 | BF9: =MAX(0,T9+U9-V9) -> 0 | BG9: =MIN(BE9,BF9) -> 0 | BH9: =V9+BG9 -> 0 | BI9: =MAX(0,T9+U9-BH9) -> 0 | BJ9: =MAX(0,BE9-BG9) -> 0 | BK9: =MAX(0,W9+X9-Y9) -> 0 | BL9: =MIN(BJ9,BK9) -> 0 | BM9: =Y9+BL9 -> 0 | BN9: =MAX(0,W9+X9-BM9) -> 0 | BO9: =AD9+AI9+AN9+AS9+AX9+BC9+BH9+BM9 -> 1400 | BP9: =C9+F9+I9+L9+O9+R9+U9+X9 -> 359.2487 | BQ9: =AE9+AJ9+AO9+AT9+AY9+BD9+BI9+BN9 -> 65806.842
A10: 9 | B10: =IF(A10=1,IF(OR('My Loans'!$O$14="",'My Loans'!$O$14=0),0,INDIRECT("'My Loans'!$D"&'My Loans'!$O$14)),AE9) -> 3926.2216 | C10: =IF(OR('My Loans'!$O$14="",'My Loans'!$O$14=0),0,B10*INDIRECT("'My Loans'!$E"&'My Loans'!$O$14)/12) -> 14.723331 | D10: =IF(OR('My Loans'!$O$14="",'My Loans'!$O$14=0),0,IF(B10<0.005,0,MIN(INDIRECT("'My Loans'!$F"&'My Loans'!$O$14),B10+C10))) -> 95 | E10: =IF(A10=1,IF(OR('My Loans'!$O$15="",'My Loans'!$O$15=0),0,INDIRECT("'My Loans'!$D"&'My Loans'!$O$15)),AJ9) -> 9215.8357 | F10: =IF(OR('My Loans'!$O$15="",'My Loans'!$O$15=0),0,E10*INDIRECT("'My Loans'!$E"&'My Loans'!$O$15)/12) -> 37.631329 | G10: =IF(OR('My Loans'!$O$15="",'My Loans'!$O$15=0),0,IF(E10<0.005,0,MIN(INDIRECT("'My Loans'!$F"&'My Loans'!$O$15),E10+F10))) -> 112 | H10: =IF(A10=1,IF(OR('My Loans'!$O$16="",'My Loans'!$O$16=0),0,INDIRECT("'My Loans'!$D"&'My Loans'!$O$16)),AO9) -> 12122.54 | I10: =IF(OR('My Loans'!$O$16="",'My Loans'!$O$16=0),0,H10*INDIRECT("'My Loans'!$E"&'My Loans'!$O$16)/12) -> 55.561643 | J10: =IF(OR('My Loans'!$O$16="",'My Loans'!$O$16=0),0,IF(H10<0.005,0,MIN(INDIRECT("'My Loans'!$F"&'My Loans'!$O$16),H10+I10))) -> 142 | K10: =IF(A10=1,IF(OR('My Loans'!$O$17="",'My Loans'!$O$17=0),0,INDIRECT("'My Loans'!$D"&'My Loans'!$O$17)),AT9) -> 14389.727 | L10: =IF(OR('My Loans'!$O$17="",'My Loans'!$O$17=0),0,K10*INDIRECT("'My Loans'!$E"&'My Loans'!$O$17)/12) -> 74.346925 | M10: =IF(OR('My Loans'!$O$17="",'My Loans'!$O$17=0),0,IF(K10<0.005,0,MIN(INDIRECT("'My Loans'!$F"&'My Loans'!$O$17),K10+L10))) -> 178 | N10: =IF(A10=1,IF(OR('My Loans'!$O$18="",'My Loans'!$O$18=0),0,INDIRECT("'My Loans'!$D"&'My Loans'!$O$18)),AY9) -> 26152.517 | O10: =IF(OR('My Loans'!$O$18="",'My Loans'!$O$18=0),0,N10*INDIRECT("'My Loans'!$E"&'My Loans'!$O$18)/12) -> 172.17073 | P10: =IF(OR('My Loans'!$O$18="",'My Loans'!$O$18=0),0,IF(N10<0.005,0,MIN(INDIRECT("'My Loans'!$F"&'My Loans'!$O$18),N10+O10))) -> 410 | Q10: =IF(A10=1,IF(OR('My Loans'!$O$19="",'My Loans'!$O$19=0),0,INDIRECT("'My Loans'!$D"&'My Loans'!$O$19)),BD9) -> 0 | R10: =IF(OR('My Loans'!$O$19="",'My Loans'!$O$19=0),0,Q10*INDIRECT("'My Loans'!$E"&'My Loans'!$O$19)/12) -> 0 | S10: =IF(OR('My Loans'!$O$19="",'My Loans'!$O$19=0),0,IF(Q10<0.005,0,MIN(INDIRECT("'My Loans'!$F"&'My Loans'!$O$19),Q10+R10))) -> 0 | T10: =IF(A10=1,IF(OR('My Loans'!$O$20="",'My Loans'!$O$20=0),0,INDIRECT("'My Loans'!$D"&'My Loans'!$O$20)),BI9) -> 0 | U10: =IF(OR('My Loans'!$O$20="",'My Loans'!$O$20=0),0,T10*INDIRECT("'My Loans'!$E"&'My Loans'!$O$20)/12) -> 0 | V10: =IF(OR('My Loans'!$O$20="",'My Loans'!$O$20=0),0,IF(T10<0.005,0,MIN(INDIRECT("'My Loans'!$F"&'My Loans'!$O$20),T10+U10))) -> 0 | W10: =IF(A10=1,IF(OR('My Loans'!$O$21="",'My Loans'!$O$21=0),0,INDIRECT("'My Loans'!$D"&'My Loans'!$O$21)),BN9) -> 0 | X10: =IF(OR('My Loans'!$O$21="",'My Loans'!$O$21=0),0,W10*INDIRECT("'My Loans'!$E"&'My Loans'!$O$21)/12) -> 0 | Y10: =IF(OR('My Loans'!$O$21="",'My Loans'!$O$21=0),0,IF(W10<0.005,0,MIN(INDIRECT("'My Loans'!$F"&'My Loans'!$O$21),W10+X10))) -> 0 | Z10: ='My Loans'!$B$13-(D10+G10+J10+M10+P10+S10+V10+Y10) -> 463 | AA10: =MAX(0,Z10) -> 463 | AB10: =MAX(0,B10+C10-D10) -> 3845.9449 | AC10: =MIN(AA10,AB10) -> 463 | AD10: =D10+AC10 -> 558 | AE10: =MAX(0,B10+C10-AD10) -> 3382.9449 | AF10: =MAX(0,AA10-AC10) -> 0 | AG10: =MAX(0,E10+F10-G10) -> 9141.467 | AH10: =MIN(AF10,AG10) -> 0 | AI10: =G10+AH10 -> 112 | AJ10: =MAX(0,E10+F10-AI10) -> 9141.467 | AK10: =MAX(0,AF10-AH10) -> 0 | AL10: =MAX(0,H10+I10-J10) -> 12036.102 | AM10: =MIN(AK10,AL10) -> 0 | AN10: =J10+AM10 -> 142 | AO10: =MAX(0,H10+I10-AN10) -> 12036.102 | AP10: =MAX(0,AK10-AM10) -> 0 | AQ10: =MAX(0,K10+L10-M10) -> 14286.074 | AR10: =MIN(AP10,AQ10) -> 0 | AS10: =M10+AR10 -> 178 | AT10: =MAX(0,K10+L10-AS10) -> 14286.074 | AU10: =MAX(0,AP10-AR10) -> 0 | AV10: =MAX(0,N10+O10-P10) -> 25914.687 | AW10: =MIN(AU10,AV10) -> 0 | AX10: =P10+AW10 -> 410 | AY10: =MAX(0,N10+O10-AX10) -> 25914.687 | AZ10: =MAX(0,AU10-AW10) -> 0 | BA10: =MAX(0,Q10+R10-S10) -> 0 | BB10: =MIN(AZ10,BA10) -> 0 | BC10: =S10+BB10 -> 0 | BD10: =MAX(0,Q10+R10-BC10) -> 0 | BE10: =MAX(0,AZ10-BB10) -> 0 | BF10: =MAX(0,T10+U10-V10) -> 0 | BG10: =MIN(BE10,BF10) -> 0 | BH10: =V10+BG10 -> 0 | BI10: =MAX(0,T10+U10-BH10) -> 0 | BJ10: =MAX(0,BE10-BG10) -> 0 | BK10: =MAX(0,W10+X10-Y10) -> 0 | BL10: =MIN(BJ10,BK10) -> 0 | BM10: =Y10+BL10 -> 0 | BN10: =MAX(0,W10+X10-BM10) -> 0 | BO10: =AD10+AI10+AN10+AS10+AX10+BC10+BH10+BM10 -> 1400 | BP10: =C10+F10+I10+L10+O10+R10+U10+X10 -> 354.43396 | BQ10: =AE10+AJ10+AO10+AT10+AY10+BD10+BI10+BN10 -> 64761.276
A11: 10 | B11: =IF(A11=1,IF(OR('My Loans'!$O$14="",'My Loans'!$O$14=0),0,INDIRECT("'My Loans'!$D"&'My Loans'!$O$14)),AE10) -> 3382.9449 | C11: =IF(OR('My Loans'!$O$14="",'My Loans'!$O$14=0),0,B11*INDIRECT("'My Loans'!$E"&'My Loans'!$O$14)/12) -> 12.686043 | D11: =IF(OR('My Loans'!$O$14="",'My Loans'!$O$14=0),0,IF(B11<0.005,0,MIN(INDIRECT("'My Loans'!$F"&'My Loans'!$O$14),B11+C11))) -> 95 | E11: =IF(A11=1,IF(OR('My Loans'!$O$15="",'My Loans'!$O$15=0),0,INDIRECT("'My Loans'!$D"&'My Loans'!$O$15)),AJ10) -> 9141.467 | F11: =IF(OR('My Loans'!$O$15="",'My Loans'!$O$15=0),0,E11*INDIRECT("'My Loans'!$E"&'My Loans'!$O$15)/12) -> 37.327657 | G11: =IF(OR('My Loans'!$O$15="",'My Loans'!$O$15=0),0,IF(E11<0.005,0,MIN(INDIRECT("'My Loans'!$F"&'My Loans'!$O$15),E11+F11))) -> 112 | H11: =IF(A11=1,IF(OR('My Loans'!$O$16="",'My Loans'!$O$16=0),0,INDIRECT("'My Loans'!$D"&'My Loans'!$O$16)),AO10) -> 12036.102 | I11: =IF(OR('My Loans'!$O$16="",'My Loans'!$O$16=0),0,H11*INDIRECT("'My Loans'!$E"&'My Loans'!$O$16)/12) -> 55.165467 | J11: =IF(OR('My Loans'!$O$16="",'My Loans'!$O$16=0),0,IF(H11<0.005,0,MIN(INDIRECT("'My Loans'!$F"&'My Loans'!$O$16),H11+I11))) -> 142 | K11: =IF(A11=1,IF(OR('My Loans'!$O$17="",'My Loans'!$O$17=0),0,INDIRECT("'My Loans'!$D"&'My Loans'!$O$17)),AT10) -> 14286.074 | L11: =IF(OR('My Loans'!$O$17="",'My Loans'!$O$17=0),0,K11*INDIRECT("'My Loans'!$E"&'My Loans'!$O$17)/12) -> 73.811385 | M11: =IF(OR('My Loans'!$O$17="",'My Loans'!$O$17=0),0,IF(K11<0.005,0,MIN(INDIRECT("'My Loans'!$F"&'My Loans'!$O$17),K11+L11))) -> 178 | N11: =IF(A11=1,IF(OR('My Loans'!$O$18="",'My Loans'!$O$18=0),0,INDIRECT("'My Loans'!$D"&'My Loans'!$O$18)),AY10) -> 25914.687 | O11: =IF(OR('My Loans'!$O$18="",'My Loans'!$O$18=0),0,N11*INDIRECT("'My Loans'!$E"&'My Loans'!$O$18)/12) -> 170.60502 | P11: =IF(OR('My Loans'!$O$18="",'My Loans'!$O$18=0),0,IF(N11<0.005,0,MIN(INDIRECT("'My Loans'!$F"&'My Loans'!$O$18),N11+O11))) -> 410 | Q11: =IF(A11=1,IF(OR('My Loans'!$O$19="",'My Loans'!$O$19=0),0,INDIRECT("'My Loans'!$D"&'My Loans'!$O$19)),BD10) -> 0 | R11: =IF(OR('My Loans'!$O$19="",'My Loans'!$O$19=0),0,Q11*INDIRECT("'My Loans'!$E"&'My Loans'!$O$19)/12) -> 0 | S11: =IF(OR('My Loans'!$O$19="",'My Loans'!$O$19=0),0,IF(Q11<0.005,0,MIN(INDIRECT("'My Loans'!$F"&'My Loans'!$O$19),Q11+R11))) -> 0 | T11: =IF(A11=1,IF(OR('My Loans'!$O$20="",'My Loans'!$O$20=0),0,INDIRECT("'My Loans'!$D"&'My Loans'!$O$20)),BI10) -> 0 | U11: =IF(OR('My Loans'!$O$20="",'My Loans'!$O$20=0),0,T11*INDIRECT("'My Loans'!$E"&'My Loans'!$O$20)/12) -> 0 | V11: =IF(OR('My Loans'!$O$20="",'My Loans'!$O$20=0),0,IF(T11<0.005,0,MIN(INDIRECT("'My Loans'!$F"&'My Loans'!$O$20),T11+U11))) -> 0 | W11: =IF(A11=1,IF(OR('My Loans'!$O$21="",'My Loans'!$O$21=0),0,INDIRECT("'My Loans'!$D"&'My Loans'!$O$21)),BN10) -> 0 | X11: =IF(OR('My Loans'!$O$21="",'My Loans'!$O$21=0),0,W11*INDIRECT("'My Loans'!$E"&'My Loans'!$O$21)/12) -> 0 | Y11: =IF(OR('My Loans'!$O$21="",'My Loans'!$O$21=0),0,IF(W11<0.005,0,MIN(INDIRECT("'My Loans'!$F"&'My Loans'!$O$21),W11+X11))) -> 0 | Z11: ='My Loans'!$B$13-(D11+G11+J11+M11+P11+S11+V11+Y11) -> 463 | AA11: =MAX(0,Z11) -> 463 | AB11: =MAX(0,B11+C11-D11) -> 3300.631 | AC11: =MIN(AA11,AB11) -> 463 | AD11: =D11+AC11 -> 558 | AE11: =MAX(0,B11+C11-AD11) -> 2837.631 | AF11: =MAX(0,AA11-AC11) -> 0 | AG11: =MAX(0,E11+F11-G11) -> 9066.7947 | AH11: =MIN(AF11,AG11) -> 0 | AI11: =G11+AH11 -> 112 | AJ11: =MAX(0,E11+F11-AI11) -> 9066.7947 | AK11: =MAX(0,AF11-AH11) -> 0 | AL11: =MAX(0,H11+I11-J11) -> 11949.267 | AM11: =MIN(AK11,AL11) -> 0 | AN11: =J11+AM11 -> 142 | AO11: =MAX(0,H11+I11-AN11) -> 11949.267 | AP11: =MAX(0,AK11-AM11) -> 0 | AQ11: =MAX(0,K11+L11-M11) -> 14181.886 | AR11: =MIN(AP11,AQ11) -> 0 | AS11: =M11+AR11 -> 178 | AT11: =MAX(0,K11+L11-AS11) -> 14181.886 | AU11: =MAX(0,AP11-AR11) -> 0 | AV11: =MAX(0,N11+O11-P11) -> 25675.292 | AW11: =MIN(AU11,AV11) -> 0 | AX11: =P11+AW11 -> 410 | AY11: =MAX(0,N11+O11-AX11) -> 25675.292 | AZ11: =MAX(0,AU11-AW11) -> 0 | BA11: =MAX(0,Q11+R11-S11) -> 0 | BB11: =MIN(AZ11,BA11) -> 0 | BC11: =S11+BB11 -> 0 | BD11: =MAX(0,Q11+R11-BC11) -> 0 | BE11: =MAX(0,AZ11-BB11) -> 0 | BF11: =MAX(0,T11+U11-V11) -> 0 | BG11: =MIN(BE11,BF11) -> 0 | BH11: =V11+BG11 -> 0 | BI11: =MAX(0,T11+U11-BH11) -> 0 | BJ11: =MAX(0,BE11-BG11) -> 0 | BK11: =MAX(0,W11+X11-Y11) -> 0 | BL11: =MIN(BJ11,BK11) -> 0 | BM11: =Y11+BL11 -> 0 | BN11: =MAX(0,W11+X11-BM11) -> 0 | BO11: =AD11+AI11+AN11+AS11+AX11+BC11+BH11+BM11 -> 1400 | BP11: =C11+F11+I11+L11+O11+R11+U11+X11 -> 349.59558 | BQ11: =AE11+AJ11+AO11+AT11+AY11+BD11+BI11+BN11 -> 63710.871
A12: 11 | B12: =IF(A12=1,IF(OR('My Loans'!$O$14="",'My Loans'!$O$14=0),0,INDIRECT("'My Loans'!$D"&'My Loans'!$O$14)),AE11) -> 2837.631 | C12: =IF(OR('My Loans'!$O$14="",'My Loans'!$O$14=0),0,B12*INDIRECT("'My Loans'!$E"&'My Loans'!$O$14)/12) -> 10.641116 | D12: =IF(OR('My Loans'!$O$14="",'My Loans'!$O$14=0),0,IF(B12<0.005,0,MIN(INDIRECT("'My Loans'!$F"&'My Loans'!$O$14),B12+C12))) -> 95 | E12: =IF(A12=1,IF(OR('My Loans'!$O$15="",'My Loans'!$O$15=0),0,INDIRECT("'My Loans'!$D"&'My Loans'!$O$15)),AJ11) -> 9066.7947 | F12: =IF(OR('My Loans'!$O$15="",'My Loans'!$O$15=0),0,E12*INDIRECT("'My Loans'!$E"&'My Loans'!$O$15)/12) -> 37.022745 | G12: =IF(OR('My Loans'!$O$15="",'My Loans'!$O$15=0),0,IF(E12<0.005,0,MIN(INDIRECT("'My Loans'!$F"&'My Loans'!$O$15),E12+F12))) -> 112 | H12: =IF(A12=1,IF(OR('My Loans'!$O$16="",'My Loans'!$O$16=0),0,INDIRECT("'My Loans'!$D"&'My Loans'!$O$16)),AO11) -> 11949.267 | I12: =IF(OR('My Loans'!$O$16="",'My Loans'!$O$16=0),0,H12*INDIRECT("'My Loans'!$E"&'My Loans'!$O$16)/12) -> 54.767476 | J12: =IF(OR('My Loans'!$O$16="",'My Loans'!$O$16=0),0,IF(H12<0.005,0,MIN(INDIRECT("'My Loans'!$F"&'My Loans'!$O$16),H12+I12))) -> 142 | K12: =IF(A12=1,IF(OR('My Loans'!$O$17="",'My Loans'!$O$17=0),0,INDIRECT("'My Loans'!$D"&'My Loans'!$O$17)),AT11) -> 14181.886 | L12: =IF(OR('My Loans'!$O$17="",'My Loans'!$O$17=0),0,K12*INDIRECT("'My Loans'!$E"&'My Loans'!$O$17)/12) -> 73.273077 | M12: =IF(OR('My Loans'!$O$17="",'My Loans'!$O$17=0),0,IF(K12<0.005,0,MIN(INDIRECT("'My Loans'!$F"&'My Loans'!$O$17),K12+L12))) -> 178 | N12: =IF(A12=1,IF(OR('My Loans'!$O$18="",'My Loans'!$O$18=0),0,INDIRECT("'My Loans'!$D"&'My Loans'!$O$18)),AY11) -> 25675.292 | O12: =IF(OR('My Loans'!$O$18="",'My Loans'!$O$18=0),0,N12*INDIRECT("'My Loans'!$E"&'My Loans'!$O$18)/12) -> 169.02901 | P12: =IF(OR('My Loans'!$O$18="",'My Loans'!$O$18=0),0,IF(N12<0.005,0,MIN(INDIRECT("'My Loans'!$F"&'My Loans'!$O$18),N12+O12))) -> 410 | Q12: =IF(A12=1,IF(OR('My Loans'!$O$19="",'My Loans'!$O$19=0),0,INDIRECT("'My Loans'!$D"&'My Loans'!$O$19)),BD11) -> 0 | R12: =IF(OR('My Loans'!$O$19="",'My Loans'!$O$19=0),0,Q12*INDIRECT("'My Loans'!$E"&'My Loans'!$O$19)/12) -> 0 | S12: =IF(OR('My Loans'!$O$19="",'My Loans'!$O$19=0),0,IF(Q12<0.005,0,MIN(INDIRECT("'My Loans'!$F"&'My Loans'!$O$19),Q12+R12))) -> 0 | T12: =IF(A12=1,IF(OR('My Loans'!$O$20="",'My Loans'!$O$20=0),0,INDIRECT("'My Loans'!$D"&'My Loans'!$O$20)),BI11) -> 0 | U12: =IF(OR('My Loans'!$O$20="",'My Loans'!$O$20=0),0,T12*INDIRECT("'My Loans'!$E"&'My Loans'!$O$20)/12) -> 0 | V12: =IF(OR('My Loans'!$O$20="",'My Loans'!$O$20=0),0,IF(T12<0.005,0,MIN(INDIRECT("'My Loans'!$F"&'My Loans'!$O$20),T12+U12))) -> 0 | W12: =IF(A12=1,IF(OR('My Loans'!$O$21="",'My Loans'!$O$21=0),0,INDIRECT("'My Loans'!$D"&'My Loans'!$O$21)),BN11) -> 0 | X12: =IF(OR('My Loans'!$O$21="",'My Loans'!$O$21=0),0,W12*INDIRECT("'My Loans'!$E"&'My Loans'!$O$21)/12) -> 0 | Y12: =IF(OR('My Loans'!$O$21="",'My Loans'!$O$21=0),0,IF(W12<0.005,0,MIN(INDIRECT("'My Loans'!$F"&'My Loans'!$O$21),W12+X12))) -> 0 | Z12: ='My Loans'!$B$13-(D12+G12+J12+M12+P12+S12+V12+Y12) -> 463 | AA12: =MAX(0,Z12) -> 463 | AB12: =MAX(0,B12+C12-D12) -> 2753.2721 | AC12: =MIN(AA12,AB12) -> 463 | AD12: =D12+AC12 -> 558 | AE12: =MAX(0,B12+C12-AD12) -> 2290.2721 | AF12: =MAX(0,AA12-AC12) -> 0 | AG12: =MAX(0,E12+F12-G12) -> 8991.8174 | AH12: =MIN(AF12,AG12) -> 0 | AI12: =G12+AH12 -> 112 | AJ12: =MAX(0,E12+F12-AI12) -> 8991.8174 | AK12: =MAX(0,AF12-AH12) -> 0 | AL12: =MAX(0,H12+I12-J12) -> 11862.035 | AM12: =MIN(AK12,AL12) -> 0 | AN12: =J12+AM12 -> 142 | AO12: =MAX(0,H12+I12-AN12) -> 11862.035 | AP12: =MAX(0,AK12-AM12) -> 0 | AQ12: =MAX(0,K12+L12-M12) -> 14077.159 | AR12: =MIN(AP12,AQ12) -> 0 | AS12: =M12+AR12 -> 178 | AT12: =MAX(0,K12+L12-AS12) -> 14077.159 | AU12: =MAX(0,AP12-AR12) -> 0 | AV12: =MAX(0,N12+O12-P12) -> 25434.321 | AW12: =MIN(AU12,AV12) -> 0 | AX12: =P12+AW12 -> 410 | AY12: =MAX(0,N12+O12-AX12) -> 25434.321 | AZ12: =MAX(0,AU12-AW12) -> 0 | BA12: =MAX(0,Q12+R12-S12) -> 0 | BB12: =MIN(AZ12,BA12) -> 0 | BC12: =S12+BB12 -> 0 | BD12: =MAX(0,Q12+R12-BC12) -> 0 | BE12: =MAX(0,AZ12-BB12) -> 0 | BF12: =MAX(0,T12+U12-V12) -> 0 | BG12: =MIN(BE12,BF12) -> 0 | BH12: =V12+BG12 -> 0 | BI12: =MAX(0,T12+U12-BH12) -> 0 | BJ12: =MAX(0,BE12-BG12) -> 0 | BK12: =MAX(0,W12+X12-Y12) -> 0 | BL12: =MIN(BJ12,BK12) -> 0 | BM12: =Y12+BL12 -> 0 | BN12: =MAX(0,W12+X12-BM12) -> 0 | BO12: =AD12+AI12+AN12+AS12+AX12+BC12+BH12+BM12 -> 1400 | BP12: =C12+F12+I12+L12+O12+R12+U12+X12 -> 344.73342 | BQ12: =AE12+AJ12+AO12+AT12+AY12+BD12+BI12+BN12 -> 62655.605
A13: 12 | B13: =IF(A13=1,IF(OR('My Loans'!$O$14="",'My Loans'!$O$14=0),0,INDIRECT("'My Loans'!$D"&'My Loans'!$O$14)),AE12) -> 2290.2721 | C13: =IF(OR('My Loans'!$O$14="",'My Loans'!$O$14=0),0,B13*INDIRECT("'My Loans'!$E"&'My Loans'!$O$14)/12) -> 8.5885203 | D13: =IF(OR('My Loans'!$O$14="",'My Loans'!$O$14=0),0,IF(B13<0.005,0,MIN(INDIRECT("'My Loans'!$F"&'My Loans'!$O$14),B13+C13))) -> 95 | E13: =IF(A13=1,IF(OR('My Loans'!$O$15="",'My Loans'!$O$15=0),0,INDIRECT("'My Loans'!$D"&'My Loans'!$O$15)),AJ12) -> 8991.8174 | F13: =IF(OR('My Loans'!$O$15="",'My Loans'!$O$15=0),0,E13*INDIRECT("'My Loans'!$E"&'My Loans'!$O$15)/12) -> 36.716588 | G13: =IF(OR('My Loans'!$O$15="",'My Loans'!$O$15=0),0,IF(E13<0.005,0,MIN(INDIRECT("'My Loans'!$F"&'My Loans'!$O$15),E13+F13))) -> 112 | H13: =IF(A13=1,IF(OR('My Loans'!$O$16="",'My Loans'!$O$16=0),0,INDIRECT("'My Loans'!$D"&'My Loans'!$O$16)),AO12) -> 11862.035 | I13: =IF(OR('My Loans'!$O$16="",'My Loans'!$O$16=0),0,H13*INDIRECT("'My Loans'!$E"&'My Loans'!$O$16)/12) -> 54.36766 | J13: =IF(OR('My Loans'!$O$16="",'My Loans'!$O$16=0),0,IF(H13<0.005,0,MIN(INDIRECT("'My Loans'!$F"&'My Loans'!$O$16),H13+I13))) -> 142 | K13: =IF(A13=1,IF(OR('My Loans'!$O$17="",'My Loans'!$O$17=0),0,INDIRECT("'My Loans'!$D"&'My Loans'!$O$17)),AT12) -> 14077.159 | L13: =IF(OR('My Loans'!$O$17="",'My Loans'!$O$17=0),0,K13*INDIRECT("'My Loans'!$E"&'My Loans'!$O$17)/12) -> 72.731988 | M13: =IF(OR('My Loans'!$O$17="",'My Loans'!$O$17=0),0,IF(K13<0.005,0,MIN(INDIRECT("'My Loans'!$F"&'My Loans'!$O$17),K13+L13))) -> 178 | N13: =IF(A13=1,IF(OR('My Loans'!$O$18="",'My Loans'!$O$18=0),0,INDIRECT("'My Loans'!$D"&'My Loans'!$O$18)),AY12) -> 25434.321 | O13: =IF(OR('My Loans'!$O$18="",'My Loans'!$O$18=0),0,N13*INDIRECT("'My Loans'!$E"&'My Loans'!$O$18)/12) -> 167.44262 | P13: =IF(OR('My Loans'!$O$18="",'My Loans'!$O$18=0),0,IF(N13<0.005,0,MIN(INDIRECT("'My Loans'!$F"&'My Loans'!$O$18),N13+O13))) -> 410 | Q13: =IF(A13=1,IF(OR('My Loans'!$O$19="",'My Loans'!$O$19=0),0,INDIRECT("'My Loans'!$D"&'My Loans'!$O$19)),BD12) -> 0 | R13: =IF(OR('My Loans'!$O$19="",'My Loans'!$O$19=0),0,Q13*INDIRECT("'My Loans'!$E"&'My Loans'!$O$19)/12) -> 0 | S13: =IF(OR('My Loans'!$O$19="",'My Loans'!$O$19=0),0,IF(Q13<0.005,0,MIN(INDIRECT("'My Loans'!$F"&'My Loans'!$O$19),Q13+R13))) -> 0 | T13: =IF(A13=1,IF(OR('My Loans'!$O$20="",'My Loans'!$O$20=0),0,INDIRECT("'My Loans'!$D"&'My Loans'!$O$20)),BI12) -> 0 | U13: =IF(OR('My Loans'!$O$20="",'My Loans'!$O$20=0),0,T13*INDIRECT("'My Loans'!$E"&'My Loans'!$O$20)/12) -> 0 | V13: =IF(OR('My Loans'!$O$20="",'My Loans'!$O$20=0),0,IF(T13<0.005,0,MIN(INDIRECT("'My Loans'!$F"&'My Loans'!$O$20),T13+U13))) -> 0 | W13: =IF(A13=1,IF(OR('My Loans'!$O$21="",'My Loans'!$O$21=0),0,INDIRECT("'My Loans'!$D"&'My Loans'!$O$21)),BN12) -> 0 | X13: =IF(OR('My Loans'!$O$21="",'My Loans'!$O$21=0),0,W13*INDIRECT("'My Loans'!$E"&'My Loans'!$O$21)/12) -> 0 | Y13: =IF(OR('My Loans'!$O$21="",'My Loans'!$O$21=0),0,IF(W13<0.005,0,MIN(INDIRECT("'My Loans'!$F"&'My Loans'!$O$21),W13+X13))) -> 0 | Z13: ='My Loans'!$B$13-(D13+G13+J13+M13+P13+S13+V13+Y13) -> 463 | AA13: =MAX(0,Z13) -> 463 | AB13: =MAX(0,B13+C13-D13) -> 2203.8606 | AC13: =MIN(AA13,AB13) -> 463 | AD13: =D13+AC13 -> 558 | AE13: =MAX(0,B13+C13-AD13) -> 1740.8606 | AF13: =MAX(0,AA13-AC13) -> 0 | AG13: =MAX(0,E13+F13-G13) -> 8916.534 | AH13: =MIN(AF13,AG13) -> 0 | AI13: =G13+AH13 -> 112 | AJ13: =MAX(0,E13+F13-AI13) -> 8916.534 | AK13: =MAX(0,AF13-AH13) -> 0 | AL13: =MAX(0,H13+I13-J13) -> 11774.403 | AM13: =MIN(AK13,AL13) -> 0 | AN13: =J13+AM13 -> 142 | AO13: =MAX(0,H13+I13-AN13) -> 11774.403 | AP13: =MAX(0,AK13-AM13) -> 0 | AQ13: =MAX(0,K13+L13-M13) -> 13971.891 | AR13: =MIN(AP13,AQ13) -> 0 | AS13: =M13+AR13 -> 178 | AT13: =MAX(0,K13+L13-AS13) -> 13971.891 | AU13: =MAX(0,AP13-AR13) -> 0 | AV13: =MAX(0,N13+O13-P13) -> 25191.764 | AW13: =MIN(AU13,AV13) -> 0 | AX13: =P13+AW13 -> 410 | AY13: =MAX(0,N13+O13-AX13) -> 25191.764 | AZ13: =MAX(0,AU13-AW13) -> 0 | BA13: =MAX(0,Q13+R13-S13) -> 0 | BB13: =MIN(AZ13,BA13) -> 0 | BC13: =S13+BB13 -> 0 | BD13: =MAX(0,Q13+R13-BC13) -> 0 | BE13: =MAX(0,AZ13-BB13) -> 0 | BF13: =MAX(0,T13+U13-V13) -> 0 | BG13: =MIN(BE13,BF13) -> 0 | BH13: =V13+BG13 -> 0 | BI13: =MAX(0,T13+U13-BH13) -> 0 | BJ13: =MAX(0,BE13-BG13) -> 0 | BK13: =MAX(0,W13+X13-Y13) -> 0 | BL13: =MIN(BJ13,BK13) -> 0 | BM13: =Y13+BL13 -> 0 | BN13: =MAX(0,W13+X13-BM13) -> 0 | BO13: =AD13+AI13+AN13+AS13+AX13+BC13+BH13+BM13 -> 1400 | BP13: =C13+F13+I13+L13+O13+R13+U13+X13 -> 339.84737 | BQ13: =AE13+AJ13+AO13+AT13+AY13+BD13+BI13+BN13 -> 61595.452
... A121: 120 | B121: =IF(A121=1,IF(OR('My Loans'!$O$14="",'My Loans'!$O$14=0),0,INDIRECT("'My Loans'!$D"&'My Loans'!$O$14)),AE120) -> 0 | C121: =IF(OR('My Loans'!$O$14="",'My Loans'!$O$14=0),0,B121*INDIRECT("'My Loans'!$E"&'My Loans'!$O$14)/12) -> 0 | D121: =IF(OR('My Loans'!$O$14="",'My Loans'!$O$14=0),0,IF(B121<0.005,0,MIN(INDIRECT("'My Loans'!$F"&'My Loans'!$O$14),B121+C121))) -> 0 | E121: =IF(A121=1,IF(OR('My Loans'!$O$15="",'My Loans'!$O$15=0),0,INDIRECT("'My Loans'!$D"&'My Loans'!$O$15)),AJ120) -> 0 | F121: =IF(OR('My Loans'!$O$15="",'My Loans'!$O$15=0),0,E121*INDIRECT("'My Loans'!$E"&'My Loans'!$O$15)/12) -> 0 | G121: =IF(OR('My Loans'!$O$15="",'My Loans'!$O$15=0),0,IF(E121<0.005,0,MIN(INDIRECT("'My Loans'!$F"&'My Loans'!$O$15),E121+F121))) -> 0 | H121: =IF(A121=1,IF(OR('My Loans'!$O$16="",'My Loans'!$O$16=0),0,INDIRECT("'My Loans'!$D"&'My Loans'!$O$16)),AO120) -> 0 | I121: =IF(OR('My Loans'!$O$16="",'My Loans'!$O$16=0),0,H121*INDIRECT("'My Loans'!$E"&'My Loans'!$O$16)/12) -> 0 | J121: =IF(OR('My Loans'!$O$16="",'My Loans'!$O$16=0),0,IF(H121<0.005,0,MIN(INDIRECT("'My Loans'!$F"&'My Loans'!$O$16),H121+I121))) -> 0 | K121: =IF(A121=1,IF(OR('My Loans'!$O$17="",'My Loans'!$O$17=0),0,INDIRECT("'My Loans'!$D"&'My Loans'!$O$17)),AT120) -> 0 | L121: =IF(OR('My Loans'!$O$17="",'My Loans'!$O$17=0),0,K121*INDIRECT("'My Loans'!$E"&'My Loans'!$O$17)/12) -> 0 | M121: =IF(OR('My Loans'!$O$17="",'My Loans'!$O$17=0),0,IF(K121<0.005,0,MIN(INDIRECT("'My Loans'!$F"&'My Loans'!$O$17),K121+L121))) -> 0 | N121: =IF(A121=1,IF(OR('My Loans'!$O$18="",'My Loans'!$O$18=0),0,INDIRECT("'My Loans'!$D"&'My Loans'!$O$18)),AY120) -> 0 | O121: =IF(OR('My Loans'!$O$18="",'My Loans'!$O$18=0),0,N121*INDIRECT("'My Loans'!$E"&'My Loans'!$O$18)/12) -> 0 | P121: =IF(OR('My Loans'!$O$18="",'My Loans'!$O$18=0),0,IF(N121<0.005,0,MIN(INDIRECT("'My Loans'!$F"&'My Loans'!$O$18),N121+O121))) -> 0 | Q121: =IF(A121=1,IF(OR('My Loans'!$O$19="",'My Loans'!$O$19=0),0,INDIRECT("'My Loans'!$D"&'My Loans'!$O$19)),BD120) -> 0 | R121: =IF(OR('My Loans'!$O$19="",'My Loans'!$O$19=0),0,Q121*INDIRECT("'My Loans'!$E"&'My Loans'!$O$19)/12) -> 0 | S121: =IF(OR('My Loans'!$O$19="",'My Loans'!$O$19=0),0,IF(Q121<0.005,0,MIN(INDIRECT("'My Loans'!$F"&'My Loans'!$O$19),Q121+R121))) -> 0 | T121: =IF(A121=1,IF(OR('My Loans'!$O$20="",'My Loans'!$O$20=0),0,INDIRECT("'My Loans'!$D"&'My Loans'!$O$20)),BI120) -> 0 | U121: =IF(OR('My Loans'!$O$20="",'My Loans'!$O$20=0),0,T121*INDIRECT("'My Loans'!$E"&'My Loans'!$O$20)/12) -> 0 | V121: =IF(OR('My Loans'!$O$20="",'My Loans'!$O$20=0),0,IF(T121<0.005,0,MIN(INDIRECT("'My Loans'!$F"&'My Loans'!$O$20),T121+U121))) -> 0 | W121: =IF(A121=1,IF(OR('My Loans'!$O$21="",'My Loans'!$O$21=0),0,INDIRECT("'My Loans'!$D"&'My Loans'!$O$21)),BN120) -> 0 | X121: =IF(OR('My Loans'!$O$21="",'My Loans'!$O$21=0),0,W121*INDIRECT("'My Loans'!$E"&'My Loans'!$O$21)/12) -> 0 | Y121: =IF(OR('My Loans'!$O$21="",'My Loans'!$O$21=0),0,IF(W121<0.005,0,MIN(INDIRECT("'My Loans'!$F"&'My Loans'!$O$21),W121+X121))) -> 0 | Z121: ='My Loans'!$B$13-(D121+G121+J121+M121+P121+S121+V121+Y121) -> 1400 | AA121: =MAX(0,Z121) -> 1400 | AB121: =MAX(0,B121+C121-D121) -> 0 | AC121: =MIN(AA121,AB121) -> 0 | AD121: =D121+AC121 -> 0 | AE121: =MAX(0,B121+C121-AD121) -> 0 | AF121: =MAX(0,AA121-AC121) -> 1400 | AG121: =MAX(0,E121+F121-G121) -> 0 | AH121: =MIN(AF121,AG121) -> 0 | AI121: =G121+AH121 -> 0 | AJ121: =MAX(0,E121+F121-AI121) -> 0 | AK121: =MAX(0,AF121-AH121) -> 1400 | AL121: =MAX(0,H121+I121-J121) -> 0 | AM121: =MIN(AK121,AL121) -> 0 | AN121: =J121+AM121 -> 0 | AO121: =MAX(0,H121+I121-AN121) -> 0 | AP121: =MAX(0,AK121-AM121) -> 1400 | AQ121: =MAX(0,K121+L121-M121) -> 0 | AR121: =MIN(AP121,AQ121) -> 0 | AS121: =M121+AR121 -> 0 | AT121: =MAX(0,K121+L121-AS121) -> 0 | AU121: =MAX(0,AP121-AR121) -> 1400 | AV121: =MAX(0,N121+O121-P121) -> 0 | AW121: =MIN(AU121,AV121) -> 0 | AX121: =P121+AW121 -> 0 | AY121: =MAX(0,N121+O121-AX121) -> 0 | AZ121: =MAX(0,AU121-AW121) -> 1400 | BA121: =MAX(0,Q121+R121-S121) -> 0 | BB121: =MIN(AZ121,BA121) -> 0 | BC121: =S121+BB121 -> 0 | BD121: =MAX(0,Q121+R121-BC121) -> 0 | BE121: =MAX(0,AZ121-BB121) -> 1400 | BF121: =MAX(0,T121+U121-V121) -> 0 | BG121: =MIN(BE121,BF121) -> 0 | BH121: =V121+BG121 -> 0 | BI121: =MAX(0,T121+U121-BH121) -> 0 | BJ121: =MAX(0,BE121-BG121) -> 1400 | BK121: =MAX(0,W121+X121-Y121) -> 0 | BL121: =MIN(BJ121,BK121) -> 0 | BM121: =Y121+BL121 -> 0 | BN121: =MAX(0,W121+X121-BM121) -> 0 | BO121: =AD121+AI121+AN121+AS121+AX121+BC121+BH121+BM121 -> 0 | BP121: =C121+F121+I121+L121+O121+R121+U121+X121 -> 0 | BQ121: =AE121+AJ121+AO121+AT121+AY121+BD121+BI121+BN121 -> 0
A123: Totals / metrics
A124: Total interest paid | B124: =SUM(BP2:BP121) -> 14016.831
A125: Total payments | B125: =SUM(BO2:BO121) -> 88016.831
A126: Months to payoff | B126: =IFERROR(MATCH(TRUE,BQ2:BQ121<=0.005,0),120) -> 120
A127: Payoff date | B127: =EDATE('My Loans'!$B$1,B126) -> 49310
A128: Payoff month by loan (for Comparison)
A129: Loan slot 1 | B129: =IFERROR(MATCH(TRUE,AE2:AE121<=0.005,0),"")
A130: Loan slot 2 | B130: =IFERROR(MATCH(TRUE,AJ2:AJ121<=0.005,0),"")
A131: Loan slot 3 | B131: =IFERROR(MATCH(TRUE,AO2:AO121<=0.005,0),"")
A132: Loan slot 4 | B132: =IFERROR(MATCH(TRUE,AT2:AT121<=0.005,0),"")
A133: Loan slot 5 | B133: =IFERROR(MATCH(TRUE,AY2:AY121<=0.005,0),"")
A134: Loan slot 6 | B134: =IFERROR(MATCH(TRUE,BD2:BD121<=0.005,0),"")
A135: Loan slot 7 | B135: =IFERROR(MATCH(TRUE,BI2:BI121<=0.005,0),"")
A136: Loan slot 8 | B136: =IFERROR(MATCH(TRUE,BN2:BN121<=0.005,0),"")

Sheet Comparison
A1: Strategy comparison
A3: Total interest paid | B3: =Avalanche!B124 -> 12051.681 | C3: =Snowball!B124 -> 14016.831 | D3: =B3-C3 -> -1965.1502
A4: Total amount paid | B4: =Avalanche!B125 -> 86051.681 | C4: =Snowball!B125 -> 88016.831 | D4: =B4-C4 -> -1965.1502
A5: Months to payoff | B5: =Avalanche!B126 -> 120 | C5: =Snowball!B126 -> 120 | D5: =B5-C5 -> 0
A6: Payoff date | B6: =Avalanche!B127 -> 49310 | C6: =Snowball!B127 -> 49310 | D6: -
A7: Interest saved vs minimum-pay baseline | B7: ='My Loans'!$B$21-Avalanche!$B$124 -> 9985.1112 | C7: ='My Loans'!$B$21-Snowball!$B$124 -> 8019.961
A9: Payoff order (Avalanche, by rate)
A10: Slot | B10: Loan | C10: My Loans row | D10: Payoff month #
A11: 1 | B11: =IF('My Loans'!$N$14="","",INDEX('My Loans'!$A$3:$A$10,'My Loans'!$N$14-2)) -> Private SoFi | C11: ='My Loans'!$N$14 -> 5 | D11: =Avalanche!B129
A12: 2 | B12: =IF('My Loans'!$N$15="","",INDEX('My Loans'!$A$3:$A$10,'My Loans'!$N$15-2)) -> Parent PLUS | C12: ='My Loans'!$N$15 -> 6 | D12: =Avalanche!B130
A13: 3 | B13: =IF('My Loans'!$N$16="","",INDEX('My Loans'!$A$3:$A$10,'My Loans'!$N$16-2)) -> Stafford Unsub #1 | C13: ='My Loans'!$N$16 -> 4 | D13: =Avalanche!B131
A14: 4 | B14: =IF('My Loans'!$N$17="","",INDEX('My Loans'!$A$3:$A$10,'My Loans'!$N$17-2)) -> Stafford Sub #2 | C14: ='My Loans'!$N$17 -> 7 | D14: =Avalanche!B132
A15: 5 | B15: =IF('My Loans'!$N$18="","",INDEX('My Loans'!$A$3:$A$10,'My Loans'!$N$18-2)) -> Stafford Sub #1 | C15: ='My Loans'!$N$18 -> 3 | D15: =Avalanche!B133
A16: 6 | B16: =IF('My Loans'!$N$19="","",INDEX('My Loans'!$A$3:$A$10,'My Loans'!$N$19-2)) -> 0 | C16: ='My Loans'!$N$19 -> 8 | D16: =Avalanche!B134
A17: 7 | B17: =IF('My Loans'!$N$20="","",INDEX('My Loans'!$A$3:$A$10,'My Loans'!$N$20-2)) -> 0 | C17: ='My Loans'!$N$20 -> 9 | D17: =Avalanche!B135
A18: 8 | B18: =IF('My Loans'!$N$21="","",INDEX('My Loans'!$A$3:$A$10,'My Loans'!$N$21-2)) -> 0 | C18: ='My Loans'!$N$21 -> 10 | D18: =Avalanche!B136
A20: Payoff order (Snowball, by balance)
A21: Slot | B21: Loan | C21: My Loans row | D21: Payoff month #
A22: 1 | B22: =IF('My Loans'!$O$14="","",INDEX('My Loans'!$A$3:$A$10,'My Loans'!$O$14-2)) -> Stafford Sub #1 | C22: ='My Loans'!$O$14 -> 3 | D22: =Snowball!B129
A23: 2 | B23: =IF('My Loans'!$O$15="","",INDEX('My Loans'!$A$3:$A$10,'My Loans'!$O$15-2)) -> Stafford Sub #2 | C23: ='My Loans'!$O$15 -> 7 | D23: =Snowball!B130
A24: 3 | B24: =IF('My Loans'!$O$16="","",INDEX('My Loans'!$A$3:$A$10,'My Loans'!$O$16-2)) -> Stafford Unsub #1 | C24: ='My Loans'!$O$16 -> 4 | D24: =Snowball!B131
A25: 4 | B25: =IF('My Loans'!$O$17="","",INDEX('My Loans'!$A$3:$A$10,'My Loans'!$O$17-2)) -> Parent PLUS | C25: ='My Loans'!$O$17 -> 6 | D25: =Snowball!B132
A26: 5 | B26: =IF('My Loans'!$O$18="","",INDEX('My Loans'!$A$3:$A$10,'My Loans'!$O$18-2)) -> Private SoFi | C26: ='My Loans'!$O$18 -> 5 | D26: =Snowball!B133
A27: 6 | B27: =IF('My Loans'!$O$19="","",INDEX('My Loans'!$A$3:$A$10,'My Loans'!$O$19-2)) -> 0 | C27: ='My Loans'!$O$19 -> 8 | D27: =Snowball!B134
A28: 7 | B28: =IF('My Loans'!$O$20="","",INDEX('My Loans'!$A$3:$A$10,'My Loans'!$O$20-2)) -> 0 | C28: ='My Loans'!$O$20 -> 8 | D28: =Snowball!B135
A29: 8 | B29: =IF('My Loans'!$O$21="","",INDEX('My Loans'!$A$3:$A$10,'My Loans'!$O$21-2)) -> 0 | C29: ='My Loans'!$O$21 -> 8 | D29: =Snowball!B136
A31: What-if: change Total monthly loan budget on My Loans (B13) to model extra payment toward loans.

Sheet Amortization (Full)
A1: Baseline: minimum payment only (no extra). Total baseline interest: | F1: =B126+B250+B374+B498+B622+B746+B870+B994 -> 22036.792
A2: Grand total interest (all loans) | F2: =F1 -> 22036.792
A4: Stafford Sub #1 (row 3)
A5: Month | B5: Beg bal | C5: Payment | D5: Interest | E5: Principal | F5: End bal
A6: 1 | B6: ='My Loans'!$D$3 -> 8200 | C6: =MIN('My Loans'!$F$3,B6+D6) -> 95 | D6: =B6*'My Loans'!$E$3/12 -> 30.75 | E6: =C6-D6 -> 64.25 | F6: =MAX(0,B6-E6) -> 8135.75
A7: 2 | B7: =F6 -> 8135.75 | C7: =MIN('My Loans'!$F$3,B7+D7) -> 95 | D7: =B7*'My Loans'!$E$3/12 -> 30.509062 | E7: =C7-D7 -> 64.490938 | F7: =MAX(0,B7-E7) -> 8071.2591
A8: 3 | B8: =F7 -> 8071.2591 | C8: =MIN('My Loans'!$F$3,B8+D8) -> 95 | D8: =B8*'My Loans'!$E$3/12 -> 30.267221 | E8: =C8-D8 -> 64.732779 | F8: =MAX(0,B8-E8) -> 8006.5263
A9: 4 | B9: =F8 -> 8006.5263 | C9: =MIN('My Loans'!$F$3,B9+D9) -> 95 | D9: =B9*'My Loans'!$E$3/12 -> 30.024474 | E9: =C9-D9 -> 64.975526 | F9: =MAX(0,B9-E9) -> 7941.5508
A10: 5 | B10: =F9 -> 7941.5508 | C10: =MIN('My Loans'!$F$3,B10+D10) -> 95 | D10: =B10*'My Loans'!$E$3/12 -> 29.780815 | E10: =C10-D10 -> 65.219185 | F10: =MAX(0,B10-E10) -> 7876.3316
A11: 6 | B11: =F10 -> 7876.3316 | C11: =MIN('My Loans'!$F$3,B11+D11) -> 95 | D11: =B11*'My Loans'!$E$3/12 -> 29.536243 | E11: =C11-D11 -> 65.463757 | F11: =MAX(0,B11-E11) -> 7810.8678
A12: 7 | B12: =F11 -> 7810.8678 | C12: =MIN('My Loans'!$F$3,B12+D12) -> 95 | D12: =B12*'My Loans'!$E$3/12 -> 29.290754 | E12: =C12-D12 -> 65.709246 | F12: =MAX(0,B12-E12) -> 7745.1586
A13: 8 | B13: =F12 -> 7745.1586 | C13: =MIN('My Loans'!$F$3,B13+D13) -> 95 | D13: =B13*'My Loans'!$E$3/12 -> 29.044345 | E13: =C13-D13 -> 65.955655 | F13: =MAX(0,B13-E13) -> 7679.2029
A14: 9 | B14: =F13 -> 7679.2029 | C14: =MIN('My Loans'!$F$3,B14+D14) -> 95 | D14: =B14*'My Loans'!$E$3/12 -> 28.797011 | E14: =C14-D14 -> 66.202989 | F14: =MAX(0,B14-E14) -> 7612.9999
A15: 10 | B15: =F14 -> 7612.9999 | C15: =MIN('My Loans'!$F$3,B15+D15) -> 95 | D15: =B15*'My Loans'!$E$3/12 -> 28.54875 | E15: =C15-D15 -> 66.45125 | F15: =MAX(0,B15-E15) -> 7546.5487
A16: 11 | B16: =F15 -> 7546.5487 | C16: =MIN('My Loans'!$F$3,B16+D16) -> 95 | D16: =B16*'My Loans'!$E$3/12 -> 28.299558 | E16: =C16-D16 -> 66.700442 | F16: =MAX(0,B16-E16) -> 7479.8482
A17: 12 | B17: =F16 -> 7479.8482 | C17: =MIN('My Loans'!$F$3,B17+D17) -> 95 | D17: =B17*'My Loans'!$E$3/12 -> 28.049431 | E17: =C17-D17 -> 66.950569 | F17: =MAX(0,B17-E17) -> 7412.8977
A18: 13 | B18: =F17 -> 7412.8977 | C18: =MIN('My Loans'!$F$3,B18+D18) -> 95 | D18: =B18*'My Loans'!$E$3/12 -> 27.798366 | E18: =C18-D18 -> 67.201634 | F18: =MAX(0,B18-E18) -> 7345.696
... A125: 120 | B125: =F124 -> 0 | C125: =MIN('My Loans'!$F$3,B125+D125) -> 0 | D125: =B125*'My Loans'!$E$3/12 -> 0 | E125: =C125-D125 -> 0 | F125: =MAX(0,B125-E125) -> 0
A126: Loan total interest | B126: =SUM(D6:D125) -> 1726.3541
A128: Stafford Unsub #1 (row 4)
A129: Month | B129: Beg bal | C129: Payment | D129: Interest | E129: Principal | F129: End bal
A130: 1 | B130: ='My Loans'!$D$4 -> 12800 | C130: =MIN('My Loans'!$F$4,B130+D130) -> 142 | D130: =B130*'My Loans'!$E$4/12 -> 58.666667 | E130: =C130-D130 -> 83.333333 | F130: =MAX(0,B130-E130) -> 12716.667
A131: 2 | B131: =F130 -> 12716.667 | C131: =MIN('My Loans'!$F$4,B131+D131) -> 142 | D131: =B131*'My Loans'!$E$4/12 -> 58.284722 | E131: =C131-D131 -> 83.715278 | F131: =MAX(0,B131-E131) -> 12632.951
A132: 3 | B132: =F131 -> 12632.951 | C132: =MIN('My Loans'!$F$4,B132+D132) -> 142 | D132: =B132*'My Loans'!$E$4/12 -> 57.901027 | E132: =C132-D132 -> 84.098973 | F132: =MAX(0,B132-E132) -> 12548.852
A133: 4 | B133: =F132 -> 12548.852 | C133: =MIN('My Loans'!$F$4,B133+D133) -> 142 | D133: =B133*'My Loans'!$E$4/12 -> 57.515574 | E133: =C133-D133 -> 84.484426 | F133: =MAX(0,B133-E133) -> 12464.368
A134: 5 | B134: =F133 -> 12464.368 | C134: =MIN('My Loans'!$F$4,B134+D134) -> 142 | D134: =B134*'My Loans'!$E$4/12 -> 57.128353 | E134: =C134-D134 -> 84.871647 | F134: =MAX(0,B134-E134) -> 12379.496
A135: 6 | B135: =F134 -> 12379.496 | C135: =MIN('My Loans'!$F$4,B135+D135) -> 142 | D135: =B135*'My Loans'!$E$4/12 -> 56.739358 | E135: =C135-D135 -> 85.260642 | F135: =MAX(0,B135-E135) -> 12294.236
A136: 7 | B136: =F135 -> 12294.236 | C136: =MIN('My Loans'!$F$4,B136+D136) -> 142 | D136: =B136*'My Loans'!$E$4/12 -> 56.34858 | E136: =C136-D136 -> 85.65142 | F136: =MAX(0,B136-E136) -> 12208.584
A137: 8 | B137: =F136 -> 12208.584 | C137: =MIN('My Loans'!$F$4,B137+D137) -> 142 | D137: =B137*'My Loans'!$E$4/12 -> 55.956011 | E137: =C137-D137 -> 86.043989 | F137: =MAX(0,B137-E137) -> 12122.54
A138: 9 | B138: =F137 -> 12122.54 | C138: =MIN('My Loans'!$F$4,B138+D138) -> 142 | D138: =B138*'My Loans'!$E$4/12 -> 55.561643 | E138: =C138-D138 -> 86.438357 | F138: =MAX(0,B138-E138) -> 12036.102
A139: 10 | B139: =F138 -> 12036.102 | C139: =MIN('My Loans'!$F$4,B139+D139) -> 142 | D139: =B139*'My Loans'!$E$4/12 -> 55.165467 | E139: =C139-D139 -> 86.834533 | F139: =MAX(0,B139-E139) -> 11949.267
A140: 11 | B140: =F139 -> 11949.267 | C140: =MIN('My Loans'!$F$4,B140+D140) -> 142 | D140: =B140*'My Loans'!$E$4/12 -> 54.767476 | E140: =C140-D140 -> 87.232524 | F140: =MAX(0,B140-E140) -> 11862.035
A141: 12 | B141: =F140 -> 11862.035 | C141: =MIN('My Loans'!$F$4,B141+D141) -> 142 | D141: =B141*'My Loans'!$E$4/12 -> 54.36766 | E141: =C141-D141 -> 87.63234 | F141: =MAX(0,B141-E141) -> 11774.403
A142: 13 | B142: =F141 -> 11774.403 | C142: =MIN('My Loans'!$F$4,B142+D142) -> 142 | D142: =B142*'My Loans'!$E$4/12 -> 53.966012 | E142: =C142-D142 -> 88.033988 | F142: =MAX(0,B142-E142) -> 11686.369
... A249: 120 | B249: =F248 -> 0 | C249: =MIN('My Loans'!$F$4,B249+D249) -> 0 | D249: =B249*'My Loans'!$E$4/12 -> 0 | E249: =C249-D249 -> 0 | F249: =MAX(0,B249-E249) -> 0
A250: Loan total interest | B250: =SUM(D130:D249) -> 3750.5337
A252: Private SoFi (row 5)
A253: Month | B253: Beg bal | C253: Payment | D253: Interest | E253: Principal | F253: End bal
A254: 1 | B254: ='My Loans'!$D$5 -> 28000 | C254: =MIN('My Loans'!$F$5,B254+D254) -> 410 | D254: =B254*'My Loans'!$E$5/12 -> 184.33333 | E254: =C254-D254 -> 225.66667 | F254: =MAX(0,B254-E254) -> 27774.333
A255: 2 | B255: =F254 -> 27774.333 | C255: =MIN('My Loans'!$F$5,B255+D255) -> 410 | D255: =B255*'My Loans'!$E$5/12 -> 182.84769 | E255: =C255-D255 -> 227.15231 | F255: =MAX(0,B255-E255) -> 27547.181
A256: 3 | B256: =F255 -> 27547.181 | C256: =MIN('My Loans'!$F$5,B256+D256) -> 410 | D256: =B256*'My Loans'!$E$5/12 -> 181.35228 | E256: =C256-D256 -> 228.64772 | F256: =MAX(0,B256-E256) -> 27318.533
A257: 4 | B257: =F256 -> 27318.533 | C257: =MIN('My Loans'!$F$5,B257+D257) -> 410 | D257: =B257*'My Loans'!$E$5/12 -> 179.84701 | E257: =C257-D257 -> 230.15299 | F257: =MAX(0,B257-E257) -> 27088.38
A258: 5 | B258: =F257 -> 27088.38 | C258: =MIN('My Loans'!$F$5,B258+D258) -> 410 | D258: =B258*'My Loans'!$E$5/12 -> 178.33184 | E258: =C258-D258 -> 231.66816 | F258: =MAX(0,B258-E258) -> 26856.712
A259: 6 | B259: =F258 -> 26856.712 | C259: =MIN('My Loans'!$F$5,B259+D259) -> 410 | D259: =B259*'My Loans'!$E$5/12 -> 176.80669 | E259: =C259-D259 -> 233.19331 | F259: =MAX(0,B259-E259) -> 26623.519
A260: 7 | B260: =F259 -> 26623.519 | C260: =MIN('My Loans'!$F$5,B260+D260) -> 410 | D260: =B260*'My Loans'!$E$5/12 -> 175.2715 | E260: =C260-D260 -> 234.7285 | F260: =MAX(0,B260-E260) -> 26388.79
A261: 8 | B261: =F260 -> 26388.79 | C261: =MIN('My Loans'!$F$5,B261+D261) -> 410 | D261: =B261*'My Loans'!$E$5/12 -> 173.7262 | E261: =C261-D261 -> 236.2738 | F261: =MAX(0,B261-E261) -> 26152.517
A262: 9 | B262: =F261 -> 26152.517 | C262: =MIN('My Loans'!$F$5,B262+D262) -> 410 | D262: =B262*'My Loans'!$E$5/12 -> 172.17073 | E262: =C262-D262 -> 237.82927 | F262: =MAX(0,B262-E262) -> 25914.687
A263: 10 | B263: =F262 -> 25914.687 | C263: =MIN('My Loans'!$F$5,B263+D263) -> 410 | D263: =B263*'My Loans'!$E$5/12 -> 170.60502 | E263: =C263-D263 -> 239.39498 | F263: =MAX(0,B263-E263) -> 25675.292
A264: 11 | B264: =F263 -> 25675.292 | C264: =MIN('My Loans'!$F$5,B264+D264) -> 410 | D264: =B264*'My Loans'!$E$5/12 -> 169.02901 | E264: =C264-D264 -> 240.97099 | F264: =MAX(0,B264-E264) -> 25434.321
A265: 12 | B265: =F264 -> 25434.321 | C265: =MIN('My Loans'!$F$5,B265+D265) -> 410 | D265: =B265*'My Loans'!$E$5/12 -> 167.44262 | E265: =C265-D265 -> 242.55738 | F265: =MAX(0,B265-E265) -> 25191.764
A266: 13 | B266: =F265 -> 25191.764 | C266: =MIN('My Loans'!$F$5,B266+D266) -> 410 | D266: =B266*'My Loans'!$E$5/12 -> 165.84578 | E266: =C266-D266 -> 244.15422 | F266: =MAX(0,B266-E266) -> 24947.61
... A373: 120 | B373: =F372 -> 0 | C373: =MIN('My Loans'!$F$5,B373+D373) -> 0 | D373: =B373*'My Loans'!$E$5/12 -> 0 | E373: =C373-D373 -> 0 | F373: =MAX(0,B373-E373) -> 0
A374: Loan total interest | B374: =SUM(D254:D373) -> 9308.6431
A376: Parent PLUS (row 6)
A377: Month | B377: Beg bal | C377: Payment | D377: Interest | E377: Principal | F377: End bal
A378: 1 | B378: ='My Loans'!$D$6 -> 15200 | C378: =MIN('My Loans'!$F$6,B378+D378) -> 178 | D378: =B378*'My Loans'!$E$6/12 -> 78.533333 | E378: =C378-D378 -> 99.466667 | F378: =MAX(0,B378-E378) -> 15100.533
A379: 2 | B379: =F378 -> 15100.533 | C379: =MIN('My Loans'!$F$6,B379+D379) -> 178 | D379: =B379*'My Loans'!$E$6/12 -> 78.019422 | E379: =C379-D379 -> 99.980578 | F379: =MAX(0,B379-E379) -> 15000.553
A380: 3 | B380: =F379 -> 15000.553 | C380: =MIN('My Loans'!$F$6,B380+D380) -> 178 | D380: =B380*'My Loans'!$E$6/12 -> 77.502856 | E380: =C380-D380 -> 100.49714 | F380: =MAX(0,B380-E380) -> 14900.056
A381: 4 | B381: =F380 -> 14900.056 | C381: =MIN('My Loans'!$F$6,B381+D381) -> 178 | D381: =B381*'My Loans'!$E$6/12 -> 76.983621 | E381: =C381-D381 -> 101.01638 | F381: =MAX(0,B381-E381) -> 14799.039
A382: 5 | B382: =F381 -> 14799.039 | C382: =MIN('My Loans'!$F$6,B382+D382) -> 178 | D382: =B382*'My Loans'!$E$6/12 -> 76.461703 | E382: =C382-D382 -> 101.5383 | F382: =MAX(0,B382-E382) -> 14697.501
A383: 6 | B383: =F382 -> 14697.501 | C383: =MIN('My Loans'!$F$6,B383+D383) -> 178 | D383: =B383*'My Loans'!$E$6/12 -> 75.937088 | E383: =C383-D383 -> 102.06291 | F383: =MAX(0,B383-E383) -> 14595.438
A384: 7 | B384: =F383 -> 14595.438 | C384: =MIN('My Loans'!$F$6,B384+D384) -> 178 | D384: =B384*'My Loans'!$E$6/12 -> 75.409763 | E384: =C384-D384 -> 102.59024 | F384: =MAX(0,B384-E384) -> 14492.848
A385: 8 | B385: =F384 -> 14492.848 | C385: =MIN('My Loans'!$F$6,B385+D385) -> 178 | D385: =B385*'My Loans'!$E$6/12 -> 74.879714 | E385: =C385-D385 -> 103.12029 | F385: =MAX(0,B385-E385) -> 14389.727
A386: 9 | B386: =F385 -> 14389.727 | C386: =MIN('My Loans'!$F$6,B386+D386) -> 178 | D386: =B386*'My Loans'!$E$6/12 -> 74.346925 | E386: =C386-D386 -> 103.65307 | F386: =MAX(0,B386-E386) -> 14286.074
A387: 10 | B387: =F386 -> 14286.074 | C387: =MIN('My Loans'!$F$6,B387+D387) -> 178 | D387: =B387*'My Loans'!$E$6/12 -> 73.811385 | E387: =C387-D387 -> 104.18862 | F387: =MAX(0,B387-E387) -> 14181.886
A388: 11 | B388: =F387 -> 14181.886 | C388: =MIN('My Loans'!$F$6,B388+D388) -> 178 | D388: =B388*'My Loans'!$E$6/12 -> 73.273077 | E388: =C388-D388 -> 104.72692 | F388: =MAX(0,B388-E388) -> 14077.159
A389: 12 | B389: =F388 -> 14077.159 | C389: =MIN('My Loans'!$F$6,B389+D389) -> 178 | D389: =B389*'My Loans'!$E$6/12 -> 72.731988 | E389: =C389-D389 -> 105.26801 | F389: =MAX(0,B389-E389) -> 13971.891
A390: 13 | B390: =F389 -> 13971.891 | C390: =MIN('My Loans'!$F$6,B390+D390) -> 178 | D390: =B390*'My Loans'!$E$6/12 -> 72.188103 | E390: =C390-D390 -> 105.8119 | F390: =MAX(0,B390-E390) -> 13866.079
... A497: 120 | B497: =F496 -> 0 | C497: =MIN('My Loans'!$F$6,B497+D497) -> 0 | D497: =B497*'My Loans'!$E$6/12 -> 0 | E497: =C497-D497 -> 0 | F497: =MAX(0,B497-E497) -> 0
A498: Loan total interest | B498: =SUM(D378:D497) -> 4901.2746
A500: Stafford Sub #2 (row 7)
A501: Month | B501: Beg bal | C501: Payment | D501: Interest | E501: Principal | F501: End bal
A502: 1 | B502: ='My Loans'!$D$7 -> 9800 | C502: =MIN('My Loans'!$F$7,B502+D502) -> 112 | D502: =B502*'My Loans'!$E$7/12 -> 40.016667 | E502: =C502-D502 -> 71.983333 | F502: =MAX(0,B502-E502) -> 9728.0167
A503: 2 | B503: =F502 -> 9728.0167 | C503: =MIN('My Loans'!$F$7,B503+D503) -> 112 | D503: =B503*'My Loans'!$E$7/12 -> 39.722735 | E503: =C503-D503 -> 72.277265 | F503: =MAX(0,B503-E503) -> 9655.7394
A504: 3 | B504: =F503 -> 9655.7394 | C504: =MIN('My Loans'!$F$7,B504+D504) -> 112 | D504: =B504*'My Loans'!$E$7/12 -> 39.427603 | E504: =C504-D504 -> 72.572397 | F504: =MAX(0,B504-E504) -> 9583.167
A505: 4 | B505: =F504 -> 9583.167 | C505: =MIN('My Loans'!$F$7,B505+D505) -> 112 | D505: =B505*'My Loans'!$E$7/12 -> 39.131265 | E505: =C505-D505 -> 72.868735 | F505: =MAX(0,B505-E505) -> 9510.2983
A506: 5 | B506: =F505 -> 9510.2983 | C506: =MIN('My Loans'!$F$7,B506+D506) -> 112 | D506: =B506*'My Loans'!$E$7/12 -> 38.833718 | E506: =C506-D506 -> 73.166282 | F506: =MAX(0,B506-E506) -> 9437.132
A507: 6 | B507: =F506 -> 9437.132 | C507: =MIN('My Loans'!$F$7,B507+D507) -> 112 | D507: =B507*'My Loans'!$E$7/12 -> 38.534956 | E507: =C507-D507 -> 73.465044 | F507: =MAX(0,B507-E507) -> 9363.6669
A508: 7 | B508: =F507 -> 9363.6669 | C508: =MIN('My Loans'!$F$7,B508+D508) -> 112 | D508: =B508*'My Loans'!$E$7/12 -> 38.234973 | E508: =C508-D508 -> 73.765027 | F508: =MAX(0,B508-E508) -> 9289.9019
A509: 8 | B509: =F508 -> 9289.9019 | C509: =MIN('My Loans'!$F$7,B509+D509) -> 112 | D509: =B509*'My Loans'!$E$7/12 -> 37.933766 | E509: =C509-D509 -> 74.066234 | F509: =MAX(0,B509-E509) -> 9215.8357
A510: 9 | B510: =F509 -> 9215.8357 | C510: =MIN('My Loans'!$F$7,B510+D510) -> 112 | D510: =B510*'My Loans'!$E$7/12 -> 37.631329 | E510: =C510-D510 -> 74.368671 | F510: =MAX(0,B510-E510) -> 9141.467
A511: 10 | B511: =F510 -> 9141.467 | C511: =MIN('My Loans'!$F$7,B511+D511) -> 112 | D511: =B511*'My Loans'!$E$7/12 -> 37.327657 | E511: =C511-D511 -> 74.672343 | F511: =MAX(0,B511-E511) -> 9066.7947
A512: 11 | B512: =F511 -> 9066.7947 | C512: =MIN('My Loans'!$F$7,B512+D512) -> 112 | D512: =B512*'My Loans'!$E$7/12 -> 37.022745 | E512: =C512-D512 -> 74.977255 | F512: =MAX(0,B512-E512) -> 8991.8174
A513: 12 | B513: =F512 -> 8991.8174 | C513: =MIN('My Loans'!$F$7,B513+D513) -> 112 | D513: =B513*'My Loans'!$E$7/12 -> 36.716588 | E513: =C513-D513 -> 75.283412 | F513: =MAX(0,B513-E513) -> 8916.534
A514: 13 | B514: =F513 -> 8916.534 | C514: =MIN('My Loans'!$F$7,B514+D514) -> 112 | D514: =B514*'My Loans'!$E$7/12 -> 36.409181 | E514: =C514-D514 -> 75.590819 | F514: =MAX(0,B514-E514) -> 8840.9432
... A621: 120 | B621: =F620 -> 0 | C621: =MIN('My Loans'!$F$7,B621+D621) -> 0 | D621: =B621*'My Loans'!$E$7/12 -> 0 | E621: =C621-D621 -> 0 | F621: =MAX(0,B621-E621) -> 0
A622: Loan total interest | B622: =SUM(D502:D621) -> 2349.9869
A624: Row 8 (row 8)
A625: Month | B625: Beg bal | C625: Payment | D625: Interest | E625: Principal | F625: End bal
A626: 1 | B626: ='My Loans'!$D$8 -> 0 | C626: =MIN('My Loans'!$F$8,B626+D626) -> 0 | D626: =B626*'My Loans'!$E$8/12 -> 0 | E626: =C626-D626 -> 0 | F626: =MAX(0,B626-E626) -> 0
A627: 2 | B627: =F626 -> 0 | C627: =MIN('My Loans'!$F$8,B627+D627) -> 0 | D627: =B627*'My Loans'!$E$8/12 -> 0 | E627: =C627-D627 -> 0 | F627: =MAX(0,B627-E627) -> 0
A628: 3 | B628: =F627 -> 0 | C628: =MIN('My Loans'!$F$8,B628+D628) -> 0 | D628: =B628*'My Loans'!$E$8/12 -> 0 | E628: =C628-D628 -> 0 | F628: =MAX(0,B628-E628) -> 0
A629: 4 | B629: =F628 -> 0 | C629: =MIN('My Loans'!$F$8,B629+D629) -> 0 | D629: =B629*'My Loans'!$E$8/12 -> 0 | E629: =C629-D629 -> 0 | F629: =MAX(0,B629-E629) -> 0
A630: 5 | B630: =F629 -> 0 | C630: =MIN('My Loans'!$F$8,B630+D630) -> 0 | D630: =B630*'My Loans'!$E$8/12 -> 0 | E630: =C630-D630 -> 0 | F630: =MAX(0,B630-E630) -> 0
A631: 6 | B631: =F630 -> 0 | C631: =MIN('My Loans'!$F$8,B631+D631) -> 0 | D631: =B631*'My Loans'!$E$8/12 -> 0 | E631: =C631-D631 -> 0 | F631: =MAX(0,B631-E631) -> 0
A632: 7 | B632: =F631 -> 0 | C632: =MIN('My Loans'!$F$8,B632+D632) -> 0 | D632: =B632*'My Loans'!$E$8/12 -> 0 | E632: =C632-D632 -> 0 | F632: =MAX(0,B632-E632) -> 0
A633: 8 | B633: =F632 -> 0 | C633: =MIN('My Loans'!$F$8,B633+D633) -> 0 | D633: =B633*'My Loans'!$E$8/12 -> 0 | E633: =C633-D633 -> 0 | F633: =MAX(0,B633-E633) -> 0
A634: 9 | B634: =F633 -> 0 | C634: =MIN('My Loans'!$F$8,B634+D634) -> 0 | D634: =B634*'My Loans'!$E$8/12 -> 0 | E634: =C634-D634 -> 0 | F634: =MAX(0,B634-E634) -> 0
A635: 10 | B635: =F634 -> 0 | C635: =MIN('My Loans'!$F$8,B635+D635) -> 0 | D635: =B635*'My Loans'!$E$8/12 -> 0 | E635: =C635-D635 -> 0 | F635: =MAX(0,B635-E635) -> 0
A636: 11 | B636: =F635 -> 0 | C636: =MIN('My Loans'!$F$8,B636+D636) -> 0 | D636: =B636*'My Loans'!$E$8/12 -> 0 | E636: =C636-D636 -> 0 | F636: =MAX(0,B636-E636) -> 0
...
