Workbook

Sheet Deal Inputs
A1: Deal Inputs
A2: Analysis start date | B2: 45658
A3: Property address | B3: 742 Evergreen Terrace
A4: Purchase price | B4: 285000
A5: Closing costs (% of purchase) | B5: 0.03
A6: Estimated repairs | B6: 12000
A7: Total cash invested | B7: =B4*B5+B11+B6 -> 91800
A9: Financing
A10: Down payment (%) | B10: 0.25
A11: Down payment ($) | B11: =B4*B10 -> 71250
A12: Loan amount | B12: =B4-B11 -> 213750
A13: Interest rate (annual) | B13: 0.07125
A14: Loan term (years) | B14: 30
A15: Monthly P&I | B15: =PMT(B13/12,B14*12,-B12) -> 1440.0733
A17: Income assumptions
A18: Monthly gross rent | B18: 2100
A19: Other income (monthly) | B19: 75
A20: Vacancy rate | B20: 0.06
A21: Annual rent growth | B21: 0.03
A23: Operating expenses (monthly)
A24: Property tax | B24: 240
A25: Insurance | B25: 115
A26: Property management (% of EGI) | B26: 0.1
A27: Maintenance reserve (% of gross rent) | B27: 0.05
A28: CapEx reserve (% of gross rent) | B28: 0.05
A29: HOA / condo fee | B29: 0
A30: Utilities (landlord-paid) | B30: 0
A31: Other expense | B31: 0
A33: Growth and exit
A34: Expense growth (annual) | B34: 0.02
A35: Appreciation (annual) | B35: 0.03
A36: Holding period (years, exit) | B36: 5
A37: Selling costs (% of sale) | B37: 0.06
A39: Figures are pre-tax and for planning only, not tax or legal advice. Monthly and annual projections cover 60 months (5 years). Holding period must stay between 1 and 5 years (validated on the input).

Sheet Monthly Cash Flow
A1: Month # | B1: Date | C1: Gross rent | D1: Other income | E1: Vacancy loss | F1: Effective gross income | G1: Property tax | H1: Insurance | I1: Management fee | J1: Maintenance reserve | K1: CapEx reserve | L1: HOA | M1: Utilities | N1: Other | O1: Total OpEx | P1: NOI | Q1: Debt service (P&I) | R1: Cash flow (pre-tax)
A2: 1 | B2: =EDATE('Deal Inputs'!$B$2,A2-1) -> 45658 | C2: ='Deal Inputs'!$B$18*(1+'Deal Inputs'!$B$21)^INT((A2-1)/12) -> 2100 | D2: ='Deal Inputs'!$B$19 -> 75 | E2: =-C2*'Deal Inputs'!$B$20 -> -126 | F2: =C2+D2+E2 -> 2049 | G2: ='Deal Inputs'!$B$24*(1+'Deal Inputs'!$B$34)^INT((A2-1)/12) -> 240 | H2: ='Deal Inputs'!$B$25*(1+'Deal Inputs'!$B$34)^INT((A2-1)/12) -> 115 | I2: =F2*'Deal Inputs'!$B$26 -> 204.9 | J2: =C2*'Deal Inputs'!$B$27 -> 105 | K2: =C2*'Deal Inputs'!$B$28 -> 105 | L2: ='Deal Inputs'!$B$29 -> 0 | M2: ='Deal Inputs'!$B$30 -> 0 | N2: ='Deal Inputs'!$B$31 -> 0 | O2: =SUM(G2:N2) -> 769.9 | P2: =F2-O2 -> 1279.1 | Q2: ='Deal Inputs'!$B$15 -> 1440.0733 | R2: =P2-Q2 -> -160.97334
A3: 2 | B3: =EDATE('Deal Inputs'!$B$2,A3-1) -> 45689 | C3: ='Deal Inputs'!$B$18*(1+'Deal Inputs'!$B$21)^INT((A3-1)/12) -> 2100 | D3: ='Deal Inputs'!$B$19 -> 75 | E3: =-C3*'Deal Inputs'!$B$20 -> -126 | F3: =C3+D3+E3 -> 2049 | G3: ='Deal Inputs'!$B$24*(1+'Deal Inputs'!$B$34)^INT((A3-1)/12) -> 240 | H3: ='Deal Inputs'!$B$25*(1+'Deal Inputs'!$B$34)^INT((A3-1)/12) -> 115 | I3: =F3*'Deal Inputs'!$B$26 -> 204.9 | J3: =C3*'Deal Inputs'!$B$27 -> 105 | K3: =C3*'Deal Inputs'!$B$28 -> 105 | L3: ='Deal Inputs'!$B$29 -> 0 | M3: ='Deal Inputs'!$B$30 -> 0 | N3: ='Deal Inputs'!$B$31 -> 0 | O3: =SUM(G3:N3) -> 769.9 | P3: =F3-O3 -> 1279.1 | Q3: ='Deal Inputs'!$B$15 -> 1440.0733 | R3: =P3-Q3 -> -160.97334
A4: 3 | B4: =EDATE('Deal Inputs'!$B$2,A4-1) -> 45717 | C4: ='Deal Inputs'!$B$18*(1+'Deal Inputs'!$B$21)^INT((A4-1)/12) -> 2100 | D4: ='Deal Inputs'!$B$19 -> 75 | E4: =-C4*'Deal Inputs'!$B$20 -> -126 | F4: =C4+D4+E4 -> 2049 | G4: ='Deal Inputs'!$B$24*(1+'Deal Inputs'!$B$34)^INT((A4-1)/12) -> 240 | H4: ='Deal Inputs'!$B$25*(1+'Deal Inputs'!$B$34)^INT((A4-1)/12) -> 115 | I4: =F4*'Deal Inputs'!$B$26 -> 204.9 | J4: =C4*'Deal Inputs'!$B$27 -> 105 | K4: =C4*'Deal Inputs'!$B$28 -> 105 | L4: ='Deal Inputs'!$B$29 -> 0 | M4: ='Deal Inputs'!$B$30 -> 0 | N4: ='Deal Inputs'!$B$31 -> 0 | O4: =SUM(G4:N4) -> 769.9 | P4: =F4-O4 -> 1279.1 | Q4: ='Deal Inputs'!$B$15 -> 1440.0733 | R4: =P4-Q4 -> -160.97334
A5: 4 | B5: =EDATE('Deal Inputs'!$B$2,A5-1) -> 45748 | C5: ='Deal Inputs'!$B$18*(1+'Deal Inputs'!$B$21)^INT((A5-1)/12) -> 2100 | D5: ='Deal Inputs'!$B$19 -> 75 | E5: =-C5*'Deal Inputs'!$B$20 -> -126 | F5: =C5+D5+E5 -> 2049 | G5: ='Deal Inputs'!$B$24*(1+'Deal Inputs'!$B$34)^INT((A5-1)/12) -> 240 | H5: ='Deal Inputs'!$B$25*(1+'Deal Inputs'!$B$34)^INT((A5-1)/12) -> 115 | I5: =F5*'Deal Inputs'!$B$26 -> 204.9 | J5: =C5*'Deal Inputs'!$B$27 -> 105 | K5: =C5*'Deal Inputs'!$B$28 -> 105 | L5: ='Deal Inputs'!$B$29 -> 0 | M5: ='Deal Inputs'!$B$30 -> 0 | N5: ='Deal Inputs'!$B$31 -> 0 | O5: =SUM(G5:N5) -> 769.9 | P5: =F5-O5 -> 1279.1 | Q5: ='Deal Inputs'!$B$15 -> 1440.0733 | R5: =P5-Q5 -> -160.97334
A6: 5 | B6: =EDATE('Deal Inputs'!$B$2,A6-1) -> 45778 | C6: ='Deal Inputs'!$B$18*(1+'Deal Inputs'!$B$21)^INT((A6-1)/12) -> 2100 | D6: ='Deal Inputs'!$B$19 -> 75 | E6: =-C6*'Deal Inputs'!$B$20 -> -126 | F6: =C6+D6+E6 -> 2049 | G6: ='Deal Inputs'!$B$24*(1+'Deal Inputs'!$B$34)^INT((A6-1)/12) -> 240 | H6: ='Deal Inputs'!$B$25*(1+'Deal Inputs'!$B$34)^INT((A6-1)/12) -> 115 | I6: =F6*'Deal Inputs'!$B$26 -> 204.9 | J6: =C6*'Deal Inputs'!$B$27 -> 105 | K6: =C6*'Deal Inputs'!$B$28 -> 105 | L6: ='Deal Inputs'!$B$29 -> 0 | M6: ='Deal Inputs'!$B$30 -> 0 | N6: ='Deal Inputs'!$B$31 -> 0 | O6: =SUM(G6:N6) -> 769.9 | P6: =F6-O6 -> 1279.1 | Q6: ='Deal Inputs'!$B$15 -> 1440.0733 | R6: =P6-Q6 -> -160.97334
A7: 6 | B7: =EDATE('Deal Inputs'!$B$2,A7-1) -> 45809 | C7: ='Deal Inputs'!$B$18*(1+'Deal Inputs'!$B$21)^INT((A7-1)/12) -> 2100 | D7: ='Deal Inputs'!$B$19 -> 75 | E7: =-C7*'Deal Inputs'!$B$20 -> -126 | F7: =C7+D7+E7 -> 2049 | G7: ='Deal Inputs'!$B$24*(1+'Deal Inputs'!$B$34)^INT((A7-1)/12) -> 240 | H7: ='Deal Inputs'!$B$25*(1+'Deal Inputs'!$B$34)^INT((A7-1)/12) -> 115 | I7: =F7*'Deal Inputs'!$B$26 -> 204.9 | J7: =C7*'Deal Inputs'!$B$27 -> 105 | K7: =C7*'Deal Inputs'!$B$28 -> 105 | L7: ='Deal Inputs'!$B$29 -> 0 | M7: ='Deal Inputs'!$B$30 -> 0 | N7: ='Deal Inputs'!$B$31 -> 0 | O7: =SUM(G7:N7) -> 769.9 | P7: =F7-O7 -> 1279.1 | Q7: ='Deal Inputs'!$B$15 -> 1440.0733 | R7: =P7-Q7 -> -160.97334
A8: 7 | B8: =EDATE('Deal Inputs'!$B$2,A8-1) -> 45839 | C8: ='Deal Inputs'!$B$18*(1+'Deal Inputs'!$B$21)^INT((A8-1)/12) -> 2100 | D8: ='Deal Inputs'!$B$19 -> 75 | E8: =-C8*'Deal Inputs'!$B$20 -> -126 | F8: =C8+D8+E8 -> 2049 | G8: ='Deal Inputs'!$B$24*(1+'Deal Inputs'!$B$34)^INT((A8-1)/12) -> 240 | H8: ='Deal Inputs'!$B$25*(1+'Deal Inputs'!$B$34)^INT((A8-1)/12) -> 115 | I8: =F8*'Deal Inputs'!$B$26 -> 204.9 | J8: =C8*'Deal Inputs'!$B$27 -> 105 | K8: =C8*'Deal Inputs'!$B$28 -> 105 | L8: ='Deal Inputs'!$B$29 -> 0 | M8: ='Deal Inputs'!$B$30 -> 0 | N8: ='Deal Inputs'!$B$31 -> 0 | O8: =SUM(G8:N8) -> 769.9 | P8: =F8-O8 -> 1279.1 | Q8: ='Deal Inputs'!$B$15 -> 1440.0733 | R8: =P8-Q8 -> -160.97334
A9: 8 | B9: =EDATE('Deal Inputs'!$B$2,A9-1) -> 45870 | C9: ='Deal Inputs'!$B$18*(1+'Deal Inputs'!$B$21)^INT((A9-1)/12) -> 2100 | D9: ='Deal Inputs'!$B$19 -> 75 | E9: =-C9*'Deal Inputs'!$B$20 -> -126 | F9: =C9+D9+E9 -> 2049 | G9: ='Deal Inputs'!$B$24*(1+'Deal Inputs'!$B$34)^INT((A9-1)/12) -> 240 | H9: ='Deal Inputs'!$B$25*(1+'Deal Inputs'!$B$34)^INT((A9-1)/12) -> 115 | I9: =F9*'Deal Inputs'!$B$26 -> 204.9 | J9: =C9*'Deal Inputs'!$B$27 -> 105 | K9: =C9*'Deal Inputs'!$B$28 -> 105 | L9: ='Deal Inputs'!$B$29 -> 0 | M9: ='Deal Inputs'!$B$30 -> 0 | N9: ='Deal Inputs'!$B$31 -> 0 | O9: =SUM(G9:N9) -> 769.9 | P9: =F9-O9 -> 1279.1 | Q9: ='Deal Inputs'!$B$15 -> 1440.0733 | R9: =P9-Q9 -> -160.97334
A10: 9 | B10: =EDATE('Deal Inputs'!$B$2,A10-1) -> 45901 | C10: ='Deal Inputs'!$B$18*(1+'Deal Inputs'!$B$21)^INT((A10-1)/12) -> 2100 | D10: ='Deal Inputs'!$B$19 -> 75 | E10: =-C10*'Deal Inputs'!$B$20 -> -126 | F10: =C10+D10+E10 -> 2049 | G10: ='Deal Inputs'!$B$24*(1+'Deal Inputs'!$B$34)^INT((A10-1)/12) -> 240 | H10: ='Deal Inputs'!$B$25*(1+'Deal Inputs'!$B$34)^INT((A10-1)/12) -> 115 | I10: =F10*'Deal Inputs'!$B$26 -> 204.9 | J10: =C10*'Deal Inputs'!$B$27 -> 105 | K10: =C10*'Deal Inputs'!$B$28 -> 105 | L10: ='Deal Inputs'!$B$29 -> 0 | M10: ='Deal Inputs'!$B$30 -> 0 | N10: ='Deal Inputs'!$B$31 -> 0 | O10: =SUM(G10:N10) -> 769.9 | P10: =F10-O10 -> 1279.1 | Q10: ='Deal Inputs'!$B$15 -> 1440.0733 | R10: =P10-Q10 -> -160.97334
A11: 10 | B11: =EDATE('Deal Inputs'!$B$2,A11-1) -> 45931 | C11: ='Deal Inputs'!$B$18*(1+'Deal Inputs'!$B$21)^INT((A11-1)/12) -> 2100 | D11: ='Deal Inputs'!$B$19 -> 75 | E11: =-C11*'Deal Inputs'!$B$20 -> -126 | F11: =C11+D11+E11 -> 2049 | G11: ='Deal Inputs'!$B$24*(1+'Deal Inputs'!$B$34)^INT((A11-1)/12) -> 240 | H11: ='Deal Inputs'!$B$25*(1+'Deal Inputs'!$B$34)^INT((A11-1)/12) -> 115 | I11: =F11*'Deal Inputs'!$B$26 -> 204.9 | J11: =C11*'Deal Inputs'!$B$27 -> 105 | K11: =C11*'Deal Inputs'!$B$28 -> 105 | L11: ='Deal Inputs'!$B$29 -> 0 | M11: ='Deal Inputs'!$B$30 -> 0 | N11: ='Deal Inputs'!$B$31 -> 0 | O11: =SUM(G11:N11) -> 769.9 | P11: =F11-O11 -> 1279.1 | Q11: ='Deal Inputs'!$B$15 -> 1440.0733 | R11: =P11-Q11 -> -160.97334
A12: 11 | B12: =EDATE('Deal Inputs'!$B$2,A12-1) -> 45962 | C12: ='Deal Inputs'!$B$18*(1+'Deal Inputs'!$B$21)^INT((A12-1)/12) -> 2100 | D12: ='Deal Inputs'!$B$19 -> 75 | E12: =-C12*'Deal Inputs'!$B$20 -> -126 | F12: =C12+D12+E12 -> 2049 | G12: ='Deal Inputs'!$B$24*(1+'Deal Inputs'!$B$34)^INT((A12-1)/12) -> 240 | H12: ='Deal Inputs'!$B$25*(1+'Deal Inputs'!$B$34)^INT((A12-1)/12) -> 115 | I12: =F12*'Deal Inputs'!$B$26 -> 204.9 | J12: =C12*'Deal Inputs'!$B$27 -> 105 | K12: =C12*'Deal Inputs'!$B$28 -> 105 | L12: ='Deal Inputs'!$B$29 -> 0 | M12: ='Deal Inputs'!$B$30 -> 0 | N12: ='Deal Inputs'!$B$31 -> 0 | O12: =SUM(G12:N12) -> 769.9 | P12: =F12-O12 -> 1279.1 | Q12: ='Deal Inputs'!$B$15 -> 1440.0733 | R12: =P12-Q12 -> -160.97334
A13: 12 | B13: =EDATE('Deal Inputs'!$B$2,A13-1) -> 45992 | C13: ='Deal Inputs'!$B$18*(1+'Deal Inputs'!$B$21)^INT((A13-1)/12) -> 2100 | D13: ='Deal Inputs'!$B$19 -> 75 | E13: =-C13*'Deal Inputs'!$B$20 -> -126 | F13: =C13+D13+E13 -> 2049 | G13: ='Deal Inputs'!$B$24*(1+'Deal Inputs'!$B$34)^INT((A13-1)/12) -> 240 | H13: ='Deal Inputs'!$B$25*(1+'Deal Inputs'!$B$34)^INT((A13-1)/12) -> 115 | I13: =F13*'Deal Inputs'!$B$26 -> 204.9 | J13: =C13*'Deal Inputs'!$B$27 -> 105 | K13: =C13*'Deal Inputs'!$B$28 -> 105 | L13: ='Deal Inputs'!$B$29 -> 0 | M13: ='Deal Inputs'!$B$30 -> 0 | N13: ='Deal Inputs'!$B$31 -> 0 | O13: =SUM(G13:N13) -> 769.9 | P13: =F13-O13 -> 1279.1 | Q13: ='Deal Inputs'!$B$15 -> 1440.0733 | R13: =P13-Q13 -> -160.97334
... A61: 60 | B61: =EDATE('Deal Inputs'!$B$2,A61-1) -> 47453 | C61: ='Deal Inputs'!$B$18*(1+'Deal Inputs'!$B$21)^INT((A61-1)/12) -> 2363.5685 | D61: ='Deal Inputs'!$B$19 -> 75 | E61: =-C61*'Deal Inputs'!$B$20 -> -141.81411 | F61: =C61+D61+E61 -> 2296.7544 | G61: ='Deal Inputs'!$B$24*(1+'Deal Inputs'!$B$34)^INT((A61-1)/12) -> 259.78372 | H61: ='Deal Inputs'!$B$25*(1+'Deal Inputs'!$B$34)^INT((A61-1)/12) -> 124.4797 | I61: =F61*'Deal Inputs'!$B$26 -> 229.67544 | J61: =C61*'Deal Inputs'!$B$27 -> 118.17843 | K61: =C61*'Deal Inputs'!$B$28 -> 118.17843 | L61: ='Deal Inputs'!$B$29 -> 0 | M61: ='Deal Inputs'!$B$30 -> 0 | N61: ='Deal Inputs'!$B$31 -> 0 | O61: =SUM(G61:N61) -> 850.29571 | P61: =F61-O61 -> 1446.4587 | Q61: ='Deal Inputs'!$B$15 -> 1440.0733 | R61: =P61-Q61 -> 6.3853414

Sheet Annual Summary
A1: Year | B1: Gross rental income | C1: Vacancy loss | D1: Effective gross income | E1: Total operating expenses | F1: NOI | G1: Annual debt service | H1: Annual cash flow | I1: Cash-on-cash return | J1: Yield on cost (NOI / purchase) | K1: Cap rate (NOI / est. value) | L1: Est. property value | M1: Est. equity | N1: Gross rent multiplier
A2: 1 | B2: =SUMIFS('Monthly Cash Flow'!$C:$C,'Monthly Cash Flow'!$A:$A,">="&(12*(A2-1)+1),'Monthly Cash Flow'!$A:$A,"<="&(12*A2)) -> 25200 | C2: =SUMIFS('Monthly Cash Flow'!$E:$E,'Monthly Cash Flow'!$A:$A,">="&(12*(A2-1)+1),'Monthly Cash Flow'!$A:$A,"<="&(12*A2)) -> -1512 | D2: =SUMIFS('Monthly Cash Flow'!$F:$F,'Monthly Cash Flow'!$A:$A,">="&(12*(A2-1)+1),'Monthly Cash Flow'!$A:$A,"<="&(12*A2)) -> 24588 | E2: =SUMIFS('Monthly Cash Flow'!$O:$O,'Monthly Cash Flow'!$A:$A,">="&(12*(A2-1)+1),'Monthly Cash Flow'!$A:$A,"<="&(12*A2)) -> 9238.8 | F2: =D2-E2 -> 15349.2 | G2: =12*'Deal Inputs'!$B$15 -> 17280.88 | H2: =F2-G2 -> -1931.6801 | I2: =IF('Deal Inputs'!$B$7=0,"",H2/'Deal Inputs'!$B$7) -> -0.021042267 | J2: =IF('Deal Inputs'!$B$4=0,"",F2/'Deal Inputs'!$B$4) -> 0.053856842 | K2: =IF(L2=0,"",F2/L2) -> 0.052288196 | L2: ='Deal Inputs'!$B$4*(1+'Deal Inputs'!$B$35)^A2 -> 293550 | M2: =L2+FV('Deal Inputs'!$B$13/12,12*A2,'Deal Inputs'!$B$15,-'Deal Inputs'!$B$12) -> 505180.48 | N2: =IF(B2=0,"",L2/B2) -> 11.64881
A3: 2 | B3: =SUMIFS('Monthly Cash Flow'!$C:$C,'Monthly Cash Flow'!$A:$A,">="&(12*(A3-1)+1),'Monthly Cash Flow'!$A:$A,"<="&(12*A3)) -> 25956 | C3: =SUMIFS('Monthly Cash Flow'!$E:$E,'Monthly Cash Flow'!$A:$A,">="&(12*(A3-1)+1),'Monthly Cash Flow'!$A:$A,"<="&(12*A3)) -> -1557.36 | D3: =SUMIFS('Monthly Cash Flow'!$F:$F,'Monthly Cash Flow'!$A:$A,">="&(12*(A3-1)+1),'Monthly Cash Flow'!$A:$A,"<="&(12*A3)) -> 25298.64 | E3: =SUMIFS('Monthly Cash Flow'!$O:$O,'Monthly Cash Flow'!$A:$A,">="&(12*(A3-1)+1),'Monthly Cash Flow'!$A:$A,"<="&(12*A3)) -> 9470.664 | F3: =D3-E3 -> 15827.976 | G3: =12*'Deal Inputs'!$B$15 -> 17280.88 | H3: =F3-G3 -> -1452.9041 | I3: =IF('Deal Inputs'!$B$7=0,"",H3/'Deal Inputs'!$B$7) -> -0.015826842 | J3: =IF('Deal Inputs'!$B$4=0,"",F3/'Deal Inputs'!$B$4) -> 0.055536758 | K3: =IF(L3=0,"",F3/L3) -> 0.052348721 | L3: ='Deal Inputs'!$B$4*(1+'Deal Inputs'!$B$35)^A3 -> 302356.5 | M3: =L3+FV('Deal Inputs'!$B$13/12,12*A3,'Deal Inputs'!$B$15,-'Deal Inputs'!$B$12) -> 511711.41 | N3: =IF(B3=0,"",L3/B3) -> 11.64881
A4: 3 | B4: =SUMIFS('Monthly Cash Flow'!$C:$C,'Monthly Cash Flow'!$A:$A,">="&(12*(A4-1)+1),'Monthly Cash Flow'!$A:$A,"<="&(12*A4)) -> 26734.68 | C4: =SUMIFS('Monthly Cash Flow'!$E:$E,'Monthly Cash Flow'!$A:$A,">="&(12*(A4-1)+1),'Monthly Cash Flow'!$A:$A,"<="&(12*A4)) -> -1604.0808 | D4: =SUMIFS('Monthly Cash Flow'!$F:$F,'Monthly Cash Flow'!$A:$A,">="&(12*(A4-1)+1),'Monthly Cash Flow'!$A:$A,"<="&(12*A4)) -> 26030.599 | E4: =SUMIFS('Monthly Cash Flow'!$O:$O,'Monthly Cash Flow'!$A:$A,">="&(12*(A4-1)+1),'Monthly Cash Flow'!$A:$A,"<="&(12*A4)) -> 9708.6319 | F4: =D4-E4 -> 16321.967 | G4: =12*'Deal Inputs'!$B$15 -> 17280.88 | H4: =F4-G4 -> -958.91284 | I4: =IF('Deal Inputs'!$B$7=0,"",H4/'Deal Inputs'!$B$7) -> -0.010445674 | J4: =IF('Deal Inputs'!$B$4=0,"",F4/'Deal Inputs'!$B$4) -> 0.057270061 | K4: =IF(L4=0,"",F4/L4) -> 0.052410218 | L4: ='Deal Inputs'!$B$4*(1+'Deal Inputs'!$B$35)^A4 -> 311427.2 | M4: =L4+FV('Deal Inputs'!$B$13/12,12*A4,'Deal Inputs'!$B$15,-'Deal Inputs'!$B$12) -> 518339.01 | N4: =IF(B4=0,"",L4/B4) -> 11.64881
A5: 4 | B5: =SUMIFS('Monthly Cash Flow'!$C:$C,'Monthly Cash Flow'!$A:$A,">="&(12*(A5-1)+1),'Monthly Cash Flow'!$A:$A,"<="&(12*A5)) -> 27536.72 | C5: =SUMIFS('Monthly Cash Flow'!$E:$E,'Monthly Cash Flow'!$A:$A,">="&(12*(A5-1)+1),'Monthly Cash Flow'!$A:$A,"<="&(12*A5)) -> -1652.2032 | D5: =SUMIFS('Monthly Cash Flow'!$F:$F,'Monthly Cash Flow'!$A:$A,">="&(12*(A5-1)+1),'Monthly Cash Flow'!$A:$A,"<="&(12*A5)) -> 26784.517 | E5: =SUMIFS('Monthly Cash Flow'!$O:$O,'Monthly Cash Flow'!$A:$A,">="&(12*(A5-1)+1),'Monthly Cash Flow'!$A:$A,"<="&(12*A5)) -> 9952.8698 | F5: =D5-E5 -> 16831.647 | G5: =12*'Deal Inputs'!$B$15 -> 17280.88 | H5: =F5-G5 -> -449.23278 | I5: =IF('Deal Inputs'!$B$7=0,"",H5/'Deal Inputs'!$B$7) -> -0.0048936033 | J5: =IF('Deal Inputs'!$B$4=0,"",F5/'Deal Inputs'!$B$4) -> 0.059058412 | K5: =IF(L5=0,"",F5/L5) -> 0.052472634 | L5: ='Deal Inputs'!$B$4*(1+'Deal Inputs'!$B$35)^A5 -> 320770.01 | M5: =L5+FV('Deal Inputs'!$B$13/12,12*A5,'Deal Inputs'!$B$15,-'Deal Inputs'!$B$12) -> 525058.85 | N5: =IF(B5=0,"",L5/B5) -> 11.64881
A6: 5 | B6: =SUMIFS('Monthly Cash Flow'!$C:$C,'Monthly Cash Flow'!$A:$A,">="&(12*(A6-1)+1),'Monthly Cash Flow'!$A:$A,"<="&(12*A6)) -> 28362.822 | C6: =SUMIFS('Monthly Cash Flow'!$E:$E,'Monthly Cash Flow'!$A:$A,">="&(12*(A6-1)+1),'Monthly Cash Flow'!$A:$A,"<="&(12*A6)) -> -1701.7693 | D6: =SUMIFS('Monthly Cash Flow'!$F:$F,'Monthly Cash Flow'!$A:$A,">="&(12*(A6-1)+1),'Monthly Cash Flow'!$A:$A,"<="&(12*A6)) -> 27561.053 | E6: =SUMIFS('Monthly Cash Flow'!$O:$O,'Monthly Cash Flow'!$A:$A,">="&(12*(A6-1)+1),'Monthly Cash Flow'!$A:$A,"<="&(12*A6)) -> 10203.548 | F6: =D6-E6 -> 17357.504 | G6: =12*'Deal Inputs'!$B$15 -> 17280.88 | H6: =F6-G6 -> 76.624097 | I6: =IF('Deal Inputs'!$B$7=0,"",H6/'Deal Inputs'!$B$7) -> 0.00083468515 | J6: =IF('Deal Inputs'!$B$4=0,"",F6/'Deal Inputs'!$B$4) -> 0.060903524 | K6: =IF(L6=0,"",F6/L6) -> 0.052535914 | L6: ='Deal Inputs'!$B$4*(1+'Deal Inputs'!$B$35)^A6 -> 330393.11 | M6: =L6+FV('Deal Inputs'!$B$13/12,12*A6,'Deal Inputs'!$B$15,-'Deal Inputs'!$B$12) -> 531865.87 | N6: =IF(B6=0,"",L6/B6) -> 11.64881

Sheet Deal Snapshot
A1: Deal Snapshot
A3: Property and equity in
A4: Property address | B4: ='Deal Inputs'!B3 -> 742 Evergreen Terrace
A5: Purchase price | B5: ='Deal Inputs'!B4 -> 285000
A6: Total cash invested | B6: ='Deal Inputs'!B7 -> 91800
A7: Financing
A8: Loan amount | B8: ='Deal Inputs'!B12 -> 213750
A9: Interest rate (annual) | B9: ='Deal Inputs'!B13 -> 0.07125
A10: Loan term (years) | B10: ='Deal Inputs'!B14 -> 30
A11: Monthly P&I | B11: ='Deal Inputs'!B15 -> 1440.0733
A12: Year 1 performance
A13: Effective gross income | B13: ='Annual Summary'!D2 -> 24588
A14: NOI | B14: ='Annual Summary'!F2 -> 15349.2
A15: Annual cash flow (after debt) | B15: ='Annual Summary'!H2 -> -1931.6801
A16: Yield on cost (NOI / purchase) | B16: ='Annual Summary'!J2 -> 0.053856842
A17: Cash-on-cash return | B17: ='Annual Summary'!I2 -> -0.021042267
A18: Exit at end of holding period
A19: Holding period (years) | B19: ='Deal Inputs'!B36 -> 5
A20: Estimated sale price | B20: ='Deal Inputs'!B4*(1+'Deal Inputs'!B35)^'Deal Inputs'!B36 -> 330393.11
A21: Selling costs | B21: =('Deal Inputs'!B4*(1+'Deal Inputs'!B35)^'Deal Inputs'!B36)*'Deal Inputs'!B37 -> 19823.587
A22: Net before loan payoff | B22: =('Deal Inputs'!B4*(1+'Deal Inputs'!B35)^'Deal Inputs'!B36)-(('Deal Inputs'!B4*(1+'Deal Inputs'!B35)^'Deal Inputs'!B36)*'Deal Inputs'!B37) -> 310569.52
A23: Loan payoff (remaining balance) | B23: =-FV('Deal Inputs'!B13/12,12*'Deal Inputs'!B36,'Deal Inputs'!B15,-'Deal Inputs'!B12) -> -201472.76
A24: Net sale proceeds to seller | B24: =(('Deal Inputs'!B4*(1+'Deal Inputs'!B35)^'Deal Inputs'!B36)-(('Deal Inputs'!B4*(1+'Deal Inputs'!B35)^'Deal Inputs'!B36)*'Deal Inputs'!B37))+FV('Deal Inputs'!B13/12,12*'Deal Inputs'!B36,'Deal Inputs'!B15,-'Deal Inputs'!B12) -> 512042.28
A25: Cumulative operating cash (years 1 to hold, after debt) | B25: =SUMIFS('Annual Summary'!$H:$H,'Annual Summary'!$A:$A,"<="&'Deal Inputs'!$B$36) -> -4716.1058
A26: Total profit (ops + exit - initial cash) | B26: =SUMIFS('Annual Summary'!$H:$H,'Annual Summary'!$A:$A,"<="&'Deal Inputs'!$B$36)+((('Deal Inputs'!B4*(1+'Deal Inputs'!B35)^'Deal Inputs'!B36)-(('Deal Inputs'!B4*(1+'Deal Inputs'!B35)^'Deal Inputs'!B36)*'Deal Inputs'!B37))+FV('Deal Inputs'!B13/12,12*'Deal Inputs'!B36,'Deal Inputs'!B15,-'Deal Inputs'!B12))-'Deal Inputs'!B7 -> 415526.17
A27: Simple annualized return on cash | B27: =IF('Deal Inputs'!B7=0,"",IF('Deal Inputs'!B36=0,"",B26/'Deal Inputs'!B7/'Deal Inputs'!B36)) -> 0.90528578
A29: Annualized return = total profit / total cash invested / holding years. Exit sale, selling costs, and loan payoff all use the holding period in Deal Inputs.
