Workbook

Sheet Invoices
A1: KM Digital — Invoice Tracker
A2: 2026
A4: Total Outstanding: | B4: =SUMPRODUCT((Invoices!H14:H30="")*Invoices!E14:E30) -> 9750
A5: Overdue (>30 days): | B5: =SUMPRODUCT((H14:H30="")*(I14:I30>30)*E14:E30) -> 500
A6: Avg Days to Payment: | B6: =IFERROR(AVERAGEIF(H14:H30,"<>"&"",I14:I30),0) -> 26.7
A7: Total Collected YTD: | B7: =SUMPRODUCT((H14:H30<>"")*E14:E30) -> 20550
A8: Problem Clients (>45 days avg): | B8: Riverside Dental, BrightPath Academy
A10: Default Terms: | B10: Net 30 | D10: Late Fee %: | E10: 0.015
A11: Hourly Rate: | B11: 95
A13: Invoice # | B13: Client | C13: Description | D13: Date Sent | E13: Amount | F13: Terms | G13: Due Date | H13: Date Paid | I13: Days Outstanding | J13: Status | K13: Late Fee | L13: Notes
A14: INV-031 | B14: Greenleaf Cafe | C14: Website redesign - homepage + menu page | D14: 46030 | E14: 2850 | F14: Net 30 | G14: =D14+30 -> 46060 | H14: 46055 | I14: =IF(H14<>"",H14-D14,TODAY()-D14) -> 25 | J14: =IF(H14<>"","Paid",IF(TODAY()>G14,"OVERDUE","Open")) -> Paid | K14: =IF(AND(H14="",TODAY()>G14),E14*$E$10*(TODAY()-G14)/30,0) -> 0
A15: INV-032 | B15: Martinez Law Group | C15: Monthly retainer - Jan | D15: 46032 | E15: 1500 | F15: Net 15 | G15: =D15+15 -> 46047 | H15: 46044 | I15: =IF(H15<>"",H15-D15,TODAY()-D15) -> 12 | J15: =IF(H15<>"","Paid",IF(TODAY()>G15,"OVERDUE","Open")) -> Paid | K15: =IF(AND(H15="",TODAY()>G15),E15*$E$10*(TODAY()-G15)/30,0) -> 0 | L15: always pays early
A16: INV-033 | B16: Riverside Dental | C16: New patient form + online booking integration | D16: 46037 | E16: 3400 | F16: Net 30 | G16: =D16+30 -> 46067 | H16: 46093 | I16: =IF(H16<>"",H16-D16,TODAY()-D16) -> 56 | J16: =IF(H16<>"","Paid",IF(TODAY()>G16,"OVERDUE","Open")) -> Paid | K16: =IF(AND(H16="",TODAY()>G16),E16*$E$10*(TODAY()-G16)/30,0) -> 0 | L16: had to chase, 3 emails + phone call
A17: INV-034 | B17: Summit CrossFit | C17: Landing page for spring promo | D17: 46044 | E17: 1200 | F17: Net 30 | G17: =D17+30 -> 46074 | H17: 46071 | I17: =IF(H17<>"",H17-D17,TODAY()-D17) -> 27 | J17: =IF(H17<>"","Paid",IF(TODAY()>G17,"OVERDUE","Open")) -> Paid | K17: =IF(AND(H17="",TODAY()>G17),E17*$E$10*(TODAY()-G17)/30,0) -> 0
A18: INV-036 | B18: Martinez Law Group | C18: Monthly retainer - Feb | D18: 46058 | E18: 1500 | F18: Net 15 | G18: =D18+15 -> 46073 | H18: 46070 | I18: =IF(H18<>"",H18-D18,TODAY()-D18) -> 12 | J18: =IF(H18<>"","Paid",IF(TODAY()>G18,"OVERDUE","Open")) -> Paid | K18: =IF(AND(H18="",TODAY()>G18),E18*$E$10*(TODAY()-G18)/30,0) -> 0
A19: INV-037 | B19: Greenleaf Cafe | C19: Add catering page + photo gallery | D19: 46063 | E19: 1850 | F19: Net 30 | G19: =D19+30 -> 46093 | H19: 46089 | I19: =IF(H19<>"",H19-D19,TODAY()-D19) -> 26 | J19: =IF(H19<>"","Paid",IF(TODAY()>G19,"OVERDUE","Open")) -> Paid | K19: =IF(AND(H19="",TODAY()>G19),E19*$E$10*(TODAY()-G19)/30,0) -> 0
A20: INV-038 | B20: BrightPath Academy | C20: Course catalog rebuild | D20: 46065 | E20: 4200 | F20: Net 30 | G20: =D20+30 -> 46095 | H20: 46114 | I20: =IF(H20<>"",H20-D20,TODAY()-D20) -> 49 | J20: =IF(H20<>"","Paid",IF(TODAY()>G20,"OVERDUE","Open")) -> Paid | K20: =IF(AND(H20="",TODAY()>G20),E20*$E$10*(TODAY()-G20)/30,0) -> 0 | L20: slow payer, nice people but disorganized
A21: INV-039 | B21: TrueNorth HVAC | C21: Google Business setup + basic SEO | D21: 46073 | E21: 950 | F21: Net 30 | G21: =D21+30 -> 46103 | H21: 46096 | I21: =IF(H21<>"",H21-D21,TODAY()-D21) -> 23 | J21: =IF(H21<>"","Paid",IF(TODAY()>G21,"OVERDUE","Open")) -> Paid | K21: =IF(AND(H21="",TODAY()>G21),E21*$E$10*(TODAY()-G21)/30,0) -> 0
A22: INV-040 | B22: Martinez Law Group | C22: Monthly retainer - Mar | D22: 46084 | E22: 1500 | F22: Net 15 | G22: =D22+15 -> 46099 | H22: 46095 | I22: =IF(H22<>"",H22-D22,TODAY()-D22) -> 11 | J22: =IF(H22<>"","Paid",IF(TODAY()>G22,"OVERDUE","Open")) -> Paid | K22: =IF(AND(H22="",TODAY()>G22),E22*$E$10*(TODAY()-G22)/30,0) -> 0
A23: INV-041 | B23: Summit CrossFit | C23: Email signup popup + Mailchimp integration | D23: 46091 | E23: 1600 | F23: Net 30 | G23: =D23+30 -> 46121 | H23: 46117 | I23: =IF(H23<>"",H23-D23,TODAY()-D23) -> 26 | J23: =IF(H23<>"","Paid",IF(TODAY()>G23,"OVERDUE","Open")) -> Paid | K23: =IF(AND(H23="",TODAY()>G23),E23*$E$10*(TODAY()-G23)/30,0) -> 0
A24: INV-042 | B24: Riverside Dental | C24: Blog setup + 4 initial posts | D24: 46096 | E24: 2800 | F24: Net 30 | G24: =D24+30 -> 46126 | I24: =IF(H24<>"",H24-D24,TODAY()-D24) -> 26 | J24: =IF(H24<>"","Paid",IF(TODAY()>G24,"OVERDUE","Open")) -> Open | K24: =IF(AND(H24="",TODAY()>G24),E24*$E$10*(TODAY()-G24)/30,0) -> 0 | L24: emailed 3/28, they said check's in the mail lol
A25: INV-043 | B25: BrightPath Academy | C25: Event registration page | D25: 46099 | E25: 2100 | F25: Net 30 | G25: =D25+30 -> 46129 | I25: =IF(H25<>"",H25-D25,TODAY()-D25) -> 23 | J25: =IF(H25<>"","Paid",IF(TODAY()>G25,"OVERDUE","Open")) -> Open | K25: =IF(AND(H25="",TODAY()>G25),E25*$E$10*(TODAY()-G25)/30,0) -> 0 | L25: sent, no response yet
A26: INV-044 | B26: Greenleaf Cafe | C26: Menu PDF auto-update system | D26: 46106 | E26: 1400 | F26: Net 30 | G26: =D26+30 -> 46136 | I26: =IF(H26<>"",H26-D26,TODAY()-D26) -> 16 | J26: =IF(H26<>"","Paid",IF(TODAY()>G26,"OVERDUE","Open")) -> Open | K26: =IF(AND(H26="",TODAY()>G26),E26*$E$10*(TODAY()-G26)/30,0) -> 0
A27: INV-045 | B27: Martinez Law Group | C27: Monthly retainer - Apr | D27: 46114 | E27: 1500 | F27: Net 15 | G27: =D27+15 -> 46129 | I27: =IF(H27<>"",H27-D27,TODAY()-D27) -> 8 | J27: =IF(H27<>"","Paid",IF(TODAY()>G27,"OVERDUE","Open")) -> Open | K27: =IF(AND(H27="",TODAY()>G27),E27*$E$10*(TODAY()-G27)/30,0) -> 0
A28: INV-046 | B28: TrueNorth HVAC | C28: Seasonal landing page (AC promo) | D28: 46117 | E28: 1100 | F28: Net 30 | G28: =D28+30 -> 46147 | I28: =IF(H28<>"",H28-D28,TODAY()-D28) -> 5 | J28: =IF(H28<>"","Paid",IF(TODAY()>G28,"OVERDUE","Open")) -> Open | K28: =IF(AND(H28="",TODAY()>G28),E28*$E$10*(TODAY()-G28)/30,0) -> 0
A29: INV-047 | B29: Riverside Dental | C29: Monthly hosting + support | D29: 46120 | E29: 350 | F29: Net 15 | G29: =D29+15 -> 46135 | I29: =IF(H29<>"",H29-D29,TODAY()-D29) -> 2 | J29: =IF(H29<>"","Paid",IF(TODAY()>G29,"OVERDUE","Open")) -> Open | K29: =IF(AND(H29="",TODAY()>G29),E29*$E$10*(TODAY()-G29)/30,0) -> 0 | L29: dispute - they say hosting should be included in original deal
B30: Dave (friend's startup) | C30: logo + business cards | D30: 46082 | E30: 500 | F30: verbal | I30: =IF(H30<>"",H30-D30,TODAY()-D30) -> 40 | J30: =IF(H30<>"","Paid","Open") -> Open | K30: 0 | L30: verbal agreement, probably won't pay, lesson learned
A32: ---
A33: INV-035 was a quote for Oak Hill Church, never signed
A34: need to start requiring 50% upfront for new clients
A35: Riverside is becoming a pattern... consider dropping or requiring prepay
A36: last updated 4/10

Sheet Client Summary
A1: Client Summary
A3: Client | B3: Total Invoiced | C3: Total Paid | D3: Outstanding | E3: # Invoices | F3: Avg Days to Pay | G3: Longest Wait | H3: Rating | I3: Notes
A4: Martinez Law Group | B4: =SUMIF(Invoices!B$14:B$30,A4,Invoices!E$14:E$30) -> 6000 | C4: =SUMPRODUCT((Invoices!B$14:B$30=A4)*(Invoices!H$14:H$30<>"")*Invoices!E$14:E$30) -> 4500 | D4: =B4-C4 -> 1500 | E4: =COUNTIF(Invoices!B$14:B$30,A4) -> 4 | F4: =IFERROR(AVERAGEIFS(Invoices!I$14:I$30,Invoices!B$14:B$30,A4,Invoices!H$14:H$30,"<>"),"") -> 11.666667 | G4: =IFERROR(_xludf.MAXIFS(Invoices!I$14:I$30,Invoices!B$14:B$30,A4,Invoices!H$14:H$30,"<>"),"") | H4: great | I4: best client, always on time, retainer is reliable income
A5: Summit CrossFit | B5: =SUMIF(Invoices!B$14:B$30,A5,Invoices!E$14:E$30) -> 2800 | C5: =SUMPRODUCT((Invoices!B$14:B$30=A5)*(Invoices!H$14:H$30<>"")*Invoices!E$14:E$30) -> 2800 | D5: =B5-C5 -> 0 | E5: =COUNTIF(Invoices!B$14:B$30,A5) -> 2 | F5: =IFERROR(AVERAGEIFS(Invoices!I$14:I$30,Invoices!B$14:B$30,A5,Invoices!H$14:H$30,"<>"),"") -> 26.5 | G5: =IFERROR(_xludf.MAXIFS(Invoices!I$14:I$30,Invoices!B$14:B$30,A5,Invoices!H$14:H$30,"<>"),"") | H5: good
A6: Greenleaf Cafe | B6: =SUMIF(Invoices!B$14:B$30,A6,Invoices!E$14:E$30) -> 6100 | C6: =SUMPRODUCT((Invoices!B$14:B$30=A6)*(Invoices!H$14:H$30<>"")*Invoices!E$14:E$30) -> 4700 | D6: =B6-C6 -> 1400 | E6: =COUNTIF(Invoices!B$14:B$30,A6) -> 3 | F6: =IFERROR(AVERAGEIFS(Invoices!I$14:I$30,Invoices!B$14:B$30,A6,Invoices!H$14:H$30,"<>"),"") -> 25.5 | G6: =IFERROR(_xludf.MAXIFS(Invoices!I$14:I$30,Invoices!B$14:B$30,A6,Invoices!H$14:H$30,"<>"),"") | H6: good | I6: growing relationship, good for portfolio
A7: TrueNorth HVAC | B7: =SUMIF(Invoices!B$14:B$30,A7,Invoices!E$14:E$30) -> 2050 | C7: =SUMPRODUCT((Invoices!B$14:B$30=A7)*(Invoices!H$14:H$30<>"")*Invoices!E$14:E$30) -> 950 | D7: =B7-C7 -> 1100 | E7: =COUNTIF(Invoices!B$14:B$30,A7) -> 2 | F7: =IFERROR(AVERAGEIFS(Invoices!I$14:I$30,Invoices!B$14:B$30,A7,Invoices!H$14:H$30,"<>"),"") -> 23 | G7: =IFERROR(_xludf.MAXIFS(Invoices!I$14:I$30,Invoices!B$14:B$30,A7,Invoices!H$14:H$30,"<>"),"") | H7: good | I7: small jobs but quick pay
A8: Riverside Dental | B8: =SUMIF(Invoices!B$14:B$30,A8,Invoices!E$14:E$30) -> 6550 | C8: =SUMPRODUCT((Invoices!B$14:B$30=A8)*(Invoices!H$14:H$30<>"")*Invoices!E$14:E$30) -> 3400 | D8: =B8-C8 -> 3150 | E8: =COUNTIF(Invoices!B$14:B$30,A8) -> 3 | F8: =IFERROR(AVERAGEIFS(Invoices!I$14:I$30,Invoices!B$14:B$30,A8,Invoices!H$14:H$30,"<>"),"") -> 56 | G8: =IFERROR(_xludf.MAXIFS(Invoices!I$14:I$30,Invoices!B$14:B$30,A8,Invoices!H$14:H$30,"<>"),"") | H8: problem | I8: always late, 50+ days twice, consider prepay requirement
A9: BrightPath Academy | B9: =SUMIF(Invoices!B$14:B$30,A9,Invoices!E$14:E$30) -> 6300 | C9: =SUMPRODUCT((Invoices!B$14:B$30=A9)*(Invoices!H$14:H$30<>"")*Invoices!E$14:E$30) -> 4200 | D9: =B9-C9 -> 2100 | E9: =COUNTIF(Invoices!B$14:B$30,A9) -> 2 | F9: =IFERROR(AVERAGEIFS(Invoices!I$14:I$30,Invoices!B$14:B$30,A9,Invoices!H$14:H$30,"<>"),"") -> 49 | G9: =IFERROR(_xludf.MAXIFS(Invoices!I$14:I$30,Invoices!B$14:B$30,A9,Invoices!H$14:H$30,"<>"),"") | H9: slow | I9: nice people but disorganized, net 15 next time?
A10: Dave (friend's startup) | B10: =SUMIF(Invoices!B$14:B$30,A10,Invoices!E$14:E$30) -> 500 | C10: =SUMPRODUCT((Invoices!B$14:B$30=A10)*(Invoices!H$14:H$30<>"")*Invoices!E$14:E$30) -> 0 | D10: =B10-C10 -> 500 | E10: =COUNTIF(Invoices!B$14:B$30,A10) -> 1 | F10: =IFERROR(AVERAGEIFS(Invoices!I$14:I$30,Invoices!B$14:B$30,A10,Invoices!H$14:H$30,"<>"),"") | G10: =IFERROR(_xludf.MAXIFS(Invoices!I$14:I$30,Invoices!B$14:B$30,A10,Invoices!H$14:H$30,"<>"),"") | H10: n/a | I10: never again, don't do work for friends without a contract
A13: clients sorted by total invoiced, roughly

Sheet Rate Card
A1: Rate Card & Pricing
A3: HOURLY RATES
A4: Service Type | B4: Rate/Hr | C4: Notes
A5: Web Design / Development | B5: 95
A6: SEO / Digital Marketing | B6: 85 | C6: lower rate, less demand
A7: Consulting / Strategy | B7: 120 | C7: rarely bill this
A8: Maintenance / Support | B8: 75 | C8: for existing client sites
A10: COMMON PACKAGES
A11: Package | B11: Price | C11: Est. Hours | D11: Effective Rate | E11: Notes
A12: Basic Landing Page | B12: 1200 | C12: 10 | D12: =B12/C12 -> 120
A13: Full Website (5-7 pages) | B13: 3500 | C13: 35 | D13: =B13/C13 -> 100 | E13: includes 1 round revisions
A14: E-commerce Setup (Shopify) | B14: 4500 | C14: 45 | D14: =B14/C14 -> 100 | E14: doesn't include product photography
A15: Monthly Retainer | B15: 1500 | C15: 15 | D15: =B15/C15 -> 100 | E15: Martinez pays this, works well
A16: Monthly Hosting + Support | B16: 350 | C16: 3 | D16: =B16/C16 -> 116.66667 | E16: mostly passive income
A18: PAYMENT TERMS
A19: Default: | B19: Net 30
A20: Retainer clients: | B20: Net 15
A21: Late fee: | B21: 1.5% per 30 days past due
A22: Deposit for new clients: | B22: 50% upfront | C22: (not enforced yet, need to start)
A24: notes
A25: need to raise rates Q3, haven't changed since 2024
A26: e-commerce jobs take longer than estimated, bump to $5k?
A27: updated 4/10
