Workbook

Sheet Position & Inputs
B2: One stock risk check
B4: Concentrated Position | H4: Where it sits
B5: Ticker | C5: NVDA | H5: Current position value | I5: =C9
B6: Shares Owned | C6: 2400 | H6: Current concentration | I6: =C21
B7: Current Price | C7: 112 | H7: Dollars above target | I7: =MAX(0,C9-(C23*C20))
B8: 52-Week High | C8: 140 | H8: Shares above target | I8: =MAX(0,ROUNDUP((C9-(C23*C20))/C7,0))
B9: Current Position Value | C9: =C6*C7 | H9: Net worth if stock drops 35% | I9: =C19+(C9*0.65)
B10: Dividend Yield | C10: 0.002 | H10: Net worth if 25% sold now | I10: =C19+(C9*0.25)+(C9*0.75*0.65)
H12: Not trying to call the stock.
B13: Other Assets | H13: This just shows how concentrated the balance sheet got.
B14: Cash | C14: 85000
B15: Diversified Brokerage | C15: 310000
B16: Retirement Accounts | C16: 540000
B17: Real Estate Equity | C17: 280000
B18: Other Assets | C18: 60000
B19: Total Other Assets | C19: =SUM(C14:C18)
B20: Total Net Worth | C20: =C9+C19
B21: Current Concentration | C21: =IF(C20=0,0,C9/C20)
B22: Risk Goals
B23: Target Max Concentration | C23: 0.25
B24: Monthly Sell Pace (shares) | C24: 200

Sheet Risk Scenarios
B2: Risk Scenarios
B4: Scenario | C4: Price Change | D4: Stock Value | E4: Total Net Worth | F4: Concentration % | G4: Net Worth Change | H4: Position Gain / Loss | J4: Strategy Compare
B5: Up 20% | C5: 0.2 | D5: ='Position & Inputs'!$C$9*(1+C5) | E5: ='Position & Inputs'!$C$19+D5 | F5: =IF(E5=0,0,D5/E5) | G5: =E5-'Position & Inputs'!$C$20 | H5: =D5-'Position & Inputs'!$C$9 | J5: Scenario | K5: Hold | L5: Sell 25% Now | M5: Sell 50% Now
B6: Down 10% | C6: -0.1 | D6: ='Position & Inputs'!$C$9*(1+C6) | E6: ='Position & Inputs'!$C$19+D6 | F6: =IF(E6=0,0,D6/E6) | G6: =E6-'Position & Inputs'!$C$20 | H6: =D6-'Position & Inputs'!$C$9 | J6: Up 20% | K6: ='Position & Inputs'!$C$19+('Position & Inputs'!$C$9*(1+C5)) | L6: ='Position & Inputs'!$C$19+('Position & Inputs'!$C$9*0.25)+('Position & Inputs'!$C$9*0.75*(1+C5)) | M6: ='Position & Inputs'!$C$19+('Position & Inputs'!$C$9*0.5)+('Position & Inputs'!$C$9*0.5*(1+C5))
B7: Down 20% | C7: -0.2 | D7: ='Position & Inputs'!$C$9*(1+C7) | E7: ='Position & Inputs'!$C$19+D7 | F7: =IF(E7=0,0,D7/E7) | G7: =E7-'Position & Inputs'!$C$20 | H7: =D7-'Position & Inputs'!$C$9 | J7: Down 10% | K7: ='Position & Inputs'!$C$19+('Position & Inputs'!$C$9*(1+C6)) | L7: ='Position & Inputs'!$C$19+('Position & Inputs'!$C$9*0.25)+('Position & Inputs'!$C$9*0.75*(1+C6)) | M7: ='Position & Inputs'!$C$19+('Position & Inputs'!$C$9*0.5)+('Position & Inputs'!$C$9*0.5*(1+C6))
B8: Down 35% | C8: -0.35 | D8: ='Position & Inputs'!$C$9*(1+C8) | E8: ='Position & Inputs'!$C$19+D8 | F8: =IF(E8=0,0,D8/E8) | G8: =E8-'Position & Inputs'!$C$20 | H8: =D8-'Position & Inputs'!$C$9 | J8: Down 20% | K8: ='Position & Inputs'!$C$19+('Position & Inputs'!$C$9*(1+C7)) | L8: ='Position & Inputs'!$C$19+('Position & Inputs'!$C$9*0.25)+('Position & Inputs'!$C$9*0.75*(1+C7)) | M8: ='Position & Inputs'!$C$19+('Position & Inputs'!$C$9*0.5)+('Position & Inputs'!$C$9*0.5*(1+C7))
B9: Down 50% | C9: -0.5 | D9: ='Position & Inputs'!$C$9*(1+C9) | E9: ='Position & Inputs'!$C$19+D9 | F9: =IF(E9=0,0,D9/E9) | G9: =E9-'Position & Inputs'!$C$20 | H9: =D9-'Position & Inputs'!$C$9 | J9: Down 35% | K9: ='Position & Inputs'!$C$19+('Position & Inputs'!$C$9*(1+C8)) | L9: ='Position & Inputs'!$C$19+('Position & Inputs'!$C$9*0.25)+('Position & Inputs'!$C$9*0.75*(1+C8)) | M9: ='Position & Inputs'!$C$19+('Position & Inputs'!$C$9*0.5)+('Position & Inputs'!$C$9*0.5*(1+C8))
J10: Down 50% | K10: ='Position & Inputs'!$C$19+('Position & Inputs'!$C$9*(1+C9)) | L10: ='Position & Inputs'!$C$19+('Position & Inputs'!$C$9*0.25)+('Position & Inputs'!$C$9*0.75*(1+C9)) | M10: ='Position & Inputs'!$C$19+('Position & Inputs'!$C$9*0.5)+('Position & Inputs'!$C$9*0.5*(1+C9))

Sheet Sale Plan
B2: Sale Plan
B4: Linked Inputs
B5: Target concentration | C5: ='Position & Inputs'!C23 | D5: Current shares | E5: ='Position & Inputs'!C6
B6: Sell pace | C6: ='Position & Inputs'!C24 | D6: Current price | E6: ='Position & Inputs'!C7
B8: Target Shares | C8: =ROUND(('Position & Inputs'!C23*'Position & Inputs'!C20)/'Position & Inputs'!C7,0)
B10: Step | C10: Trigger | D10: Shares to Sell | E10: Sale Price | F10: Gross Proceeds | G10: Remaining Shares | H10: Remaining Position Value | I10: Estimated Net Worth | J10: Concentration %
B11: 1 | C11: Now | D11: =MIN('Position & Inputs'!$C$24,MAX(0,'Position & Inputs'!$C$6-$C$8)) | E11: ='Position & Inputs'!$C$7*(1+((B11-1)*0.01)) | F11: =D11*E11 | G11: ='Position & Inputs'!$C$6-D11 | H11: =G11*E11 | I11: ='Position & Inputs'!$C$19+SUM($F$11:F11)+H11 | J11: =IF(I11=0,0,H11/I11)
B12: 2 | C12: 1 | D12: =MIN('Position & Inputs'!$C$24,MAX(0,G11-$C$8)) | E12: ='Position & Inputs'!$C$7*(1+((B12-1)*0.01)) | F12: =D12*E12 | G12: =G11-D12 | H12: =G12*E12 | I12: ='Position & Inputs'!$C$19+SUM($F$11:F12)+H12 | J12: =IF(I12=0,0,H12/I12)
B13: 3 | C13: 2 | D13: =MIN('Position & Inputs'!$C$24,MAX(0,G12-$C$8)) | E13: ='Position & Inputs'!$C$7*(1+((B13-1)*0.01)) | F13: =D13*E13 | G13: =G12-D13 | H13: =G13*E13 | I13: ='Position & Inputs'!$C$19+SUM($F$11:F13)+H13 | J13: =IF(I13=0,0,H13/I13)
B14: 4 | C14: 3 | D14: =MIN('Position & Inputs'!$C$24,MAX(0,G13-$C$8)) | E14: ='Position & Inputs'!$C$7*(1+((B14-1)*0.01)) | F14: =D14*E14 | G14: =G13-D14 | H14: =G14*E14 | I14: ='Position & Inputs'!$C$19+SUM($F$11:F14)+H14 | J14: =IF(I14=0,0,H14/I14)
B15: 5 | C15: 4 | D15: =MIN('Position & Inputs'!$C$24,MAX(0,G14-$C$8)) | E15: ='Position & Inputs'!$C$7*(1+((B15-1)*0.01)) | F15: =D15*E15 | G15: =G14-D15 | H15: =G15*E15 | I15: ='Position & Inputs'!$C$19+SUM($F$11:F15)+H15 | J15: =IF(I15=0,0,H15/I15)
B16: 6 | C16: 5 | D16: =MIN('Position & Inputs'!$C$24,MAX(0,G15-$C$8)) | E16: ='Position & Inputs'!$C$7*(1+((B16-1)*0.01)) | F16: =D16*E16 | G16: =G15-D16 | H16: =G16*E16 | I16: ='Position & Inputs'!$C$19+SUM($F$11:F16)+H16 | J16: =IF(I16=0,0,H16/I16)
B17: 7 | C17: 6 | D17: =MIN('Position & Inputs'!$C$24,MAX(0,G16-$C$8)) | E17: ='Position & Inputs'!$C$7*(1+((B17-1)*0.01)) | F17: =D17*E17 | G17: =G16-D17 | H17: =G17*E17 | I17: ='Position & Inputs'!$C$19+SUM($F$11:F17)+H17 | J17: =IF(I17=0,0,H17/I17)
B18: 8 | C18: 7 | D18: =MIN('Position & Inputs'!$C$24,MAX(0,G17-$C$8)) | E18: ='Position & Inputs'!$C$7*(1+((B18-1)*0.01)) | F18: =D18*E18 | G18: =G17-D18 | H18: =G18*E18 | I18: ='Position & Inputs'!$C$19+SUM($F$11:F18)+H18 | J18: =IF(I18=0,0,H18/I18)
B19: 9 | C19: 8 | D19: =MIN('Position & Inputs'!$C$24,MAX(0,G18-$C$8)) | E19: ='Position & Inputs'!$C$7*(1+((B19-1)*0.01)) | F19: =D19*E19 | G19: =G18-D19 | H19: =G19*E19 | I19: ='Position & Inputs'!$C$19+SUM($F$11:F19)+H19 | J19: =IF(I19=0,0,H19/I19)
B20: 10 | C20: 9 | D20: =MIN('Position & Inputs'!$C$24,MAX(0,G19-$C$8)) | E20: ='Position & Inputs'!$C$7*(1+((B20-1)*0.01)) | F20: =D20*E20 | G20: =G19-D20 | H20: =G20*E20 | I20: ='Position & Inputs'!$C$19+SUM($F$11:F20)+H20 | J20: =IF(I20=0,0,H20/I20)
B21: 11 | C21: 10 | D21: =MIN('Position & Inputs'!$C$24,MAX(0,G20-$C$8)) | E21: ='Position & Inputs'!$C$7*(1+((B21-1)*0.01)) | F21: =D21*E21 | G21: =G20-D21 | H21: =G21*E21 | I21: ='Position & Inputs'!$C$19+SUM($F$11:F21)+H21 | J21: =IF(I21=0,0,H21/I21)
B22: 12 | C22: 11 | D22: =MIN('Position & Inputs'!$C$24,MAX(0,G21-$C$8)) | E22: ='Position & Inputs'!$C$7*(1+((B22-1)*0.01)) | F22: =D22*E22 | G22: =G21-D22 | H22: =G22*E22 | I22: ='Position & Inputs'!$C$19+SUM($F$11:F22)+H22 | J22: =IF(I22=0,0,H22/I22)
B24: Total Proceeds | C24: =SUM(F11:F22)
B25: Months to Target | C25: =IFERROR(MINIFS(B11:B22,J11:J22,"<="&'Position & Inputs'!$C$23)-1,"")
B26: Remaining Shares at Target | C26: =IF(C25="","",INDEX(G11:G22,C25+1))

Sheet Hedge Comparison
B2: Hedge Comparison
B4: Hedge Inputs
B5: Put Cost (%) | C5: 0.04
B6: Put Floor (%) | C6: -0.15
B7: Collar Floor (%) | C7: -0.12
B8: Collar Cap (%) | C8: 0.18
B9: Hedge Coverage | C9: 0.5
B11: Scenario | C11: Move | D11: Hold | E11: Sell 25% Now | F11: Sell 50% Now | G11: Protective Put | H11: Zero-Cost Collar
B12: Up 20% | C12: 0.2 | D12: ='Position & Inputs'!$C$19+('Position & Inputs'!$C$9*(1+C12)) | E12: ='Position & Inputs'!$C$19+('Position & Inputs'!$C$9*0.25)+('Position & Inputs'!$C$9*0.75*(1+C12)) | F12: ='Position & Inputs'!$C$19+('Position & Inputs'!$C$9*0.5)+('Position & Inputs'!$C$9*0.5*(1+C12)) | G12: ='Position & Inputs'!$C$19+('Position & Inputs'!$C$9*(1-$C$9)*(1+C12))+('Position & Inputs'!$C$9*$C$9*MAX(1+C12,1+$C$6))-('Position & Inputs'!$C$9*$C$9*$C$5) | H12: ='Position & Inputs'!$C$19+('Position & Inputs'!$C$9*(1-$C$9)*(1+C12))+('Position & Inputs'!$C$9*$C$9*MIN(MAX(1+C12,1+$C$7),1+$C$8))
B13: Up 10% | C13: 0.1 | D13: ='Position & Inputs'!$C$19+('Position & Inputs'!$C$9*(1+C13)) | E13: ='Position & Inputs'!$C$19+('Position & Inputs'!$C$9*0.25)+('Position & Inputs'!$C$9*0.75*(1+C13)) | F13: ='Position & Inputs'!$C$19+('Position & Inputs'!$C$9*0.5)+('Position & Inputs'!$C$9*0.5*(1+C13)) | G13: ='Position & Inputs'!$C$19+('Position & Inputs'!$C$9*(1-$C$9)*(1+C13))+('Position & Inputs'!$C$9*$C$9*MAX(1+C13,1+$C$6))-('Position & Inputs'!$C$9*$C$9*$C$5) | H13: ='Position & Inputs'!$C$19+('Position & Inputs'!$C$9*(1-$C$9)*(1+C13))+('Position & Inputs'!$C$9*$C$9*MIN(MAX(1+C13,1+$C$7),1+$C$8))
B14: Flat | C14: 0 | D14: ='Position & Inputs'!$C$19+('Position & Inputs'!$C$9*(1+C14)) | E14: ='Position & Inputs'!$C$19+('Position & Inputs'!$C$9*0.25)+('Position & Inputs'!$C$9*0.75*(1+C14)) | F14: ='Position & Inputs'!$C$19+('Position & Inputs'!$C$9*0.5)+('Position & Inputs'!$C$9*0.5*(1+C14)) | G14: ='Position & Inputs'!$C$19+('Position & Inputs'!$C$9*(1-$C$9)*(1+C14))+('Position & Inputs'!$C$9*$C$9*MAX(1+C14,1+$C$6))-('Position & Inputs'!$C$9*$C$9*$C$5) | H14: ='Position & Inputs'!$C$19+('Position & Inputs'!$C$9*(1-$C$9)*(1+C14))+('Position & Inputs'!$C$9*$C$9*MIN(MAX(1+C14,1+$C$7),1+$C$8))
B15: Down 10% | C15: -0.1 | D15: ='Position & Inputs'!$C$19+('Position & Inputs'!$C$9*(1+C15)) | E15: ='Position & Inputs'!$C$19+('Position & Inputs'!$C$9*0.25)+('Position & Inputs'!$C$9*0.75*(1+C15)) | F15: ='Position & Inputs'!$C$19+('Position & Inputs'!$C$9*0.5)+('Position & Inputs'!$C$9*0.5*(1+C15)) | G15: ='Position & Inputs'!$C$19+('Position & Inputs'!$C$9*(1-$C$9)*(1+C15))+('Position & Inputs'!$C$9*$C$9*MAX(1+C15,1+$C$6))-('Position & Inputs'!$C$9*$C$9*$C$5) | H15: ='Position & Inputs'!$C$19+('Position & Inputs'!$C$9*(1-$C$9)*(1+C15))+('Position & Inputs'!$C$9*$C$9*MIN(MAX(1+C15,1+$C$7),1+$C$8))
B16: Down 20% | C16: -0.2 | D16: ='Position & Inputs'!$C$19+('Position & Inputs'!$C$9*(1+C16)) | E16: ='Position & Inputs'!$C$19+('Position & Inputs'!$C$9*0.25)+('Position & Inputs'!$C$9*0.75*(1+C16)) | F16: ='Position & Inputs'!$C$19+('Position & Inputs'!$C$9*0.5)+('Position & Inputs'!$C$9*0.5*(1+C16)) | G16: ='Position & Inputs'!$C$19+('Position & Inputs'!$C$9*(1-$C$9)*(1+C16))+('Position & Inputs'!$C$9*$C$9*MAX(1+C16,1+$C$6))-('Position & Inputs'!$C$9*$C$9*$C$5) | H16: ='Position & Inputs'!$C$19+('Position & Inputs'!$C$9*(1-$C$9)*(1+C16))+('Position & Inputs'!$C$9*$C$9*MIN(MAX(1+C16,1+$C$7),1+$C$8))
B17: Down 35% | C17: -0.35 | D17: ='Position & Inputs'!$C$19+('Position & Inputs'!$C$9*(1+C17)) | E17: ='Position & Inputs'!$C$19+('Position & Inputs'!$C$9*0.25)+('Position & Inputs'!$C$9*0.75*(1+C17)) | F17: ='Position & Inputs'!$C$19+('Position & Inputs'!$C$9*0.5)+('Position & Inputs'!$C$9*0.5*(1+C17)) | G17: ='Position & Inputs'!$C$19+('Position & Inputs'!$C$9*(1-$C$9)*(1+C17))+('Position & Inputs'!$C$9*$C$9*MAX(1+C17,1+$C$6))-('Position & Inputs'!$C$9*$C$9*$C$5) | H17: ='Position & Inputs'!$C$19+('Position & Inputs'!$C$9*(1-$C$9)*(1+C17))+('Position & Inputs'!$C$9*$C$9*MIN(MAX(1+C17,1+$C$7),1+$C$8))
B18: Down 50% | C18: -0.5 | D18: ='Position & Inputs'!$C$19+('Position & Inputs'!$C$9*(1+C18)) | E18: ='Position & Inputs'!$C$19+('Position & Inputs'!$C$9*0.25)+('Position & Inputs'!$C$9*0.75*(1+C18)) | F18: ='Position & Inputs'!$C$19+('Position & Inputs'!$C$9*0.5)+('Position & Inputs'!$C$9*0.5*(1+C18)) | G18: ='Position & Inputs'!$C$19+('Position & Inputs'!$C$9*(1-$C$9)*(1+C18))+('Position & Inputs'!$C$9*$C$9*MAX(1+C18,1+$C$6))-('Position & Inputs'!$C$9*$C$9*$C$5) | H18: ='Position & Inputs'!$C$19+('Position & Inputs'!$C$9*(1-$C$9)*(1+C18))+('Position & Inputs'!$C$9*$C$9*MIN(MAX(1+C18,1+$C$7),1+$C$8))

Sheet Snapshot
B2: Snapshot
B4: Now
B5: Ticker | C5: ='Position & Inputs'!C5
B6: Position value | C6: ='Position & Inputs'!C9
B7: Total net worth | C7: ='Position & Inputs'!C20
B8: Current concentration | C8: ='Position & Inputs'!C21
B9: Target concentration | C9: ='Position & Inputs'!C23
B12: Options
B13: Shares to sell now to hit target | C13: =MAX(0,ROUNDUP(('Position & Inputs'!C9-('Position & Inputs'!C23*'Position & Inputs'!C20))/'Position & Inputs'!C7,0))
B14: Dollar amount above target | C14: =MAX(0,'Position & Inputs'!C9-('Position & Inputs'!C23*'Position & Inputs'!C20))
B15: Best simple action from the comparison set | C15: =IF(MAX('Hedge Comparison'!D17:H17)='Hedge Comparison'!D17,"Hold",IF(MAX('Hedge Comparison'!D17:H17)='Hedge Comparison'!E17,"Sell 25% Now",IF(MAX('Hedge Comparison'!D17:H17)='Hedge Comparison'!F17,"Sell 50% Now",IF(MAX('Hedge Comparison'!D17:H17)='Hedge Comparison'!G17,"Protective Put","Zero-Cost Collar"))))
B16: Net worth under a 35% drop if unchanged | C16: ='Risk Scenarios'!E8
B17: Net worth under a 35% drop after a 25% sale | C17: ='Hedge Comparison'!E17
B19: Downside
B20: Hold outcome at +20% | C20: ='Hedge Comparison'!D12
B21: Hold outcome at -35% | C21: ='Hedge Comparison'!D17
B22: Protective put at -35% | C22: ='Hedge Comparison'!G17
B23: Collar at -35% | C23: ='Hedge Comparison'!H17
B24: Sale-plan months to target | C24: ='Sale Plan'!C25
