Workbook

Sheet Center Overview
A2: Maple Plaza rent roll
A4: Property | G4: Back of envelope
A5: Center Name | B5: Maple Plaza | G5: Year 1 NOI before TI / LC | H5: ='5-Year Pro Forma'!B12 -> 123607.04
A6: Address | B6: 910 Maple Ave | G6: Year 1 CF after debt | H6: ='5-Year Pro Forma'!B16 -> -79993.637
A7: Total SqFt | B7: =SUM('Rent Roll'!C5:C10) -> 9200 | G7: Blended occupancy | H7: =B9 -> 0.82608696
A8: Occupied SqFt | B8: =SUMIFS('Rent Roll'!C5:C10,'Rent Roll'!D5:D10,"Occupied")+SUMIFS('Rent Roll'!C5:C10,'Rent Roll'!D5:D10,"MTM") -> 7600 | G8: Total TI / LC in hold | H8: ='Exit & Snapshot'!B13 -> 116616.96
A9: Current Occupancy | B9: =IF(B7=0,0,B8/B7) -> 0.82608696 | G9: Year 5 exit value | H9: ='Exit & Snapshot'!B21 -> 2334598.3
A10: Avg In-Place Rent / SqFt | B10: =IF(B8=0,0,SUM('Rent Roll'!J5:J10)/B8) -> 22.289474 | G10: 5-year equity multiple | H10: ='Exit & Snapshot'!B30 -> -1.5246255
A11: Avg Market Rent / SqFt | B11: =IF(B7=0,0,SUMPRODUCT('Rent Roll'!C5:C10,'Rent Roll'!G5:G10)/B7) -> 24.23913
A13: Acquisition
A14: Purchase Price | B14: 3150000
A15: Closing Costs | B15: 55000
A16: Immediate CapEx | B16: 40000
A17: Total Basis | B17: =B14+B15+B16 -> 3245000
A19: Financing
A20: Down Payment (%) | B20: 0.35
A21: Loan Amount | B21: =B14*(1-B20) -> 2047500
A22: Rate | B22: 0.0665
A23: Amortization (years) | B23: 25
A24: Monthly Debt Service | B24: =PMT(B22/12,B23*12,-B21) -> 14017.39
A25: Annual Debt Service | B25: =B24*12 -> 168208.68
A27: Leasing Assumptions
A28: Market Rent Growth | B28: 0.025
A29: General Credit Loss | B29: 0.02
A30: Default Downtime (months) | B30: 4
A31: Leasing Commission (%) | B31: 0.04
A32: TI Allowance / SqFt | B32: 12
A33: Hold Period (years) | B33: 5
A34: Exit Cap Rate | B34: 0.07
A35: Selling Costs (%) | B35: 0.035
A37: Center Expenses
A38: Property Tax | B38: 32000
A39: Insurance | B39: 9000
A40: Common Area Utilities | B40: 15000
A41: Repairs & Maintenance | B41: 18000
A42: Admin / Marketing | B42: 8000
A43: Nonrecoverable CAM | B43: 12000
A44: Management Fee (%) | B44: 0.04
A45: Annual Expense Growth | B45: 0.025

Sheet Rent Roll
A2: Rent Roll
A4: Suite | B4: Tenant | C4: SqFt | D4: Status | E4: Roll Year | F4: In-Place Rent / SqFt | G4: Market Rent / SqFt | H4: In-Place Escalator | I4: CAM Recovery / SqFt | J4: Current Annual Base Rent | K4: Notes
A5: A | B5: A&J Pizza | C5: 1800 | D5: Occupied | E5: 3 | F5: 24 | G5: 26 | H5: 0.025 | I5: 5.5 | J5: =IF(D5="Vacant",0,C5*F5) -> 43200 | K5: doing fine
A6: B | B6: Nails by Ana | C6: 1200 | D6: Occupied | E6: 1 | F6: 22 | G6: 24 | H6: 0.02 | I6: 5.25 | J6: =IF(D6="Vacant",0,C6*F6) -> 26400 | K6: roll soon
A7: C | B7: Town Wash | C7: 2200 | D7: Occupied | E7: 4 | F7: 18 | G7: 20 | H7: 0.02 | I7: 4.75 | J7: =IF(D7="Vacant",0,C7*F7) -> 39600
A8: D | B8: Metro PCS | C8: 1000 | D8: Occupied | E8: 2 | F8: 28 | G8: 30 | H8: 0.03 | I8: 6 | J8: =IF(D8="Vacant",0,C8*F8) -> 28000
A9: E | B9: Thread Local | C9: 1400 | D9: Occupied | E9: 5 | F9: 23 | G9: 25 | H9: 0.025 | I9: 5.25 | J9: =IF(D9="Vacant",0,C9*F9) -> 32200
A10: F | B10: (Vacant) | C10: 1600 | D10: Vacant | E10: 1 | F10: 0 | G10: 24 | H10: 0 | I10: 5.25 | J10: =IF(D10="Vacant",0,C10*F10) -> 0 | K10: Former salon

Sheet Lease Rollover
A2: Lease Rollover
A4: Base Rent by Suite
A5: Suite | B5: SqFt | C5: Status | D5: Roll Year | E5: In-Place Rent | F5: Market Rent | G5: Escalator | H5: Downtime | I5: Year 1 | J5: Year 2 | K5: Year 3 | L5: Year 4 | M5: Year 5
A6: ='Rent Roll'!A5 -> A | B6: ='Rent Roll'!C5 -> 1800 | C6: ='Rent Roll'!D5 -> Occupied | D6: ='Rent Roll'!E5 -> 3 | E6: ='Rent Roll'!F5 -> 24 | F6: ='Rent Roll'!G5 -> 26 | G6: ='Rent Roll'!H5 -> 0.025 | H6: ='Center Overview'!$B$30 -> 4 | I6: =IF($C6="Vacant",IF(1=1,$B6*$F6*(12-$H6)/12,$B6*$F6*(1+'Center Overview'!$B$28)^(1-1)),IF(1<$D6,$B6*$E6*(1+$G6)^(1-1),IF(1=$D6,$B6*$F6*(1+'Center Overview'!$B$28)^(1-1)*(12-$H6)/12,$B6*$F6*(1+'Center Overview'!$B$28)^(1-1)))) -> 43200 | J6: =IF($C6="Vacant",IF(2=1,$B6*$F6*(12-$H6)/12,$B6*$F6*(1+'Center Overview'!$B$28)^(2-1)),IF(2<$D6,$B6*$E6*(1+$G6)^(2-1),IF(2=$D6,$B6*$F6*(1+'Center Overview'!$B$28)^(2-1)*(12-$H6)/12,$B6*$F6*(1+'Center Overview'!$B$28)^(2-1)))) -> 44280 | K6: =IF($C6="Vacant",IF(3=1,$B6*$F6*(12-$H6)/12,$B6*$F6*(1+'Center Overview'!$B$28)^(3-1)),IF(3<$D6,$B6*$E6*(1+$G6)^(3-1),IF(3=$D6,$B6*$F6*(1+'Center Overview'!$B$28)^(3-1)*(12-$H6)/12,$B6*$F6*(1+'Center Overview'!$B$28)^(3-1)))) -> 32779.5 | L6: =IF($C6="Vacant",IF(4=1,$B6*$F6*(12-$H6)/12,$B6*$F6*(1+'Center Overview'!$B$28)^(4-1)),IF(4<$D6,$B6*$E6*(1+$G6)^(4-1),IF(4=$D6,$B6*$F6*(1+'Center Overview'!$B$28)^(4-1)*(12-$H6)/12,$B6*$F6*(1+'Center Overview'!$B$28)^(4-1)))) -> 50398.481 | M6: =IF($C6="Vacant",IF(5=1,$B6*$F6*(12-$H6)/12,$B6*$F6*(1+'Center Overview'!$B$28)^(5-1)),IF(5<$D6,$B6*$E6*(1+$G6)^(5-1),IF(5=$D6,$B6*$F6*(1+'Center Overview'!$B$28)^(5-1)*(12-$H6)/12,$B6*$F6*(1+'Center Overview'!$B$28)^(5-1)))) -> 51658.443
A7: ='Rent Roll'!A6 -> B | B7: ='Rent Roll'!C6 -> 1200 | C7: ='Rent Roll'!D6 -> Occupied | D7: ='Rent Roll'!E6 -> 1 | E7: ='Rent Roll'!F6 -> 22 | F7: ='Rent Roll'!G6 -> 24 | G7: ='Rent Roll'!H6 -> 0.02 | H7: ='Center Overview'!$B$30 -> 4 | I7: =IF($C7="Vacant",IF(1=1,$B7*$F7*(12-$H7)/12,$B7*$F7*(1+'Center Overview'!$B$28)^(1-1)),IF(1<$D7,$B7*$E7*(1+$G7)^(1-1),IF(1=$D7,$B7*$F7*(1+'Center Overview'!$B$28)^(1-1)*(12-$H7)/12,$B7*$F7*(1+'Center Overview'!$B$28)^(1-1)))) -> 19200 | J7: =IF($C7="Vacant",IF(2=1,$B7*$F7*(12-$H7)/12,$B7*$F7*(1+'Center Overview'!$B$28)^(2-1)),IF(2<$D7,$B7*$E7*(1+$G7)^(2-1),IF(2=$D7,$B7*$F7*(1+'Center Overview'!$B$28)^(2-1)*(12-$H7)/12,$B7*$F7*(1+'Center Overview'!$B$28)^(2-1)))) -> 29520 | K7: =IF($C7="Vacant",IF(3=1,$B7*$F7*(12-$H7)/12,$B7*$F7*(1+'Center Overview'!$B$28)^(3-1)),IF(3<$D7,$B7*$E7*(1+$G7)^(3-1),IF(3=$D7,$B7*$F7*(1+'Center Overview'!$B$28)^(3-1)*(12-$H7)/12,$B7*$F7*(1+'Center Overview'!$B$28)^(3-1)))) -> 30258 | L7: =IF($C7="Vacant",IF(4=1,$B7*$F7*(12-$H7)/12,$B7*$F7*(1+'Center Overview'!$B$28)^(4-1)),IF(4<$D7,$B7*$E7*(1+$G7)^(4-1),IF(4=$D7,$B7*$F7*(1+'Center Overview'!$B$28)^(4-1)*(12-$H7)/12,$B7*$F7*(1+'Center Overview'!$B$28)^(4-1)))) -> 31014.45 | M7: =IF($C7="Vacant",IF(5=1,$B7*$F7*(12-$H7)/12,$B7*$F7*(1+'Center Overview'!$B$28)^(5-1)),IF(5<$D7,$B7*$E7*(1+$G7)^(5-1),IF(5=$D7,$B7*$F7*(1+'Center Overview'!$B$28)^(5-1)*(12-$H7)/12,$B7*$F7*(1+'Center Overview'!$B$28)^(5-1)))) -> 31789.811
A8: ='Rent Roll'!A7 -> C | B8: ='Rent Roll'!C7 -> 2200 | C8: ='Rent Roll'!D7 -> Occupied | D8: ='Rent Roll'!E7 -> 4 | E8: ='Rent Roll'!F7 -> 18 | F8: ='Rent Roll'!G7 -> 20 | G8: ='Rent Roll'!H7 -> 0.02 | H8: ='Center Overview'!$B$30 -> 4 | I8: =IF($C8="Vacant",IF(1=1,$B8*$F8*(12-$H8)/12,$B8*$F8*(1+'Center Overview'!$B$28)^(1-1)),IF(1<$D8,$B8*$E8*(1+$G8)^(1-1),IF(1=$D8,$B8*$F8*(1+'Center Overview'!$B$28)^(1-1)*(12-$H8)/12,$B8*$F8*(1+'Center Overview'!$B$28)^(1-1)))) -> 39600 | J8: =IF($C8="Vacant",IF(2=1,$B8*$F8*(12-$H8)/12,$B8*$F8*(1+'Center Overview'!$B$28)^(2-1)),IF(2<$D8,$B8*$E8*(1+$G8)^(2-1),IF(2=$D8,$B8*$F8*(1+'Center Overview'!$B$28)^(2-1)*(12-$H8)/12,$B8*$F8*(1+'Center Overview'!$B$28)^(2-1)))) -> 40392 | K8: =IF($C8="Vacant",IF(3=1,$B8*$F8*(12-$H8)/12,$B8*$F8*(1+'Center Overview'!$B$28)^(3-1)),IF(3<$D8,$B8*$E8*(1+$G8)^(3-1),IF(3=$D8,$B8*$F8*(1+'Center Overview'!$B$28)^(3-1)*(12-$H8)/12,$B8*$F8*(1+'Center Overview'!$B$28)^(3-1)))) -> 41199.84 | L8: =IF($C8="Vacant",IF(4=1,$B8*$F8*(12-$H8)/12,$B8*$F8*(1+'Center Overview'!$B$28)^(4-1)),IF(4<$D8,$B8*$E8*(1+$G8)^(4-1),IF(4=$D8,$B8*$F8*(1+'Center Overview'!$B$28)^(4-1)*(12-$H8)/12,$B8*$F8*(1+'Center Overview'!$B$28)^(4-1)))) -> 31588.792 | M8: =IF($C8="Vacant",IF(5=1,$B8*$F8*(12-$H8)/12,$B8*$F8*(1+'Center Overview'!$B$28)^(5-1)),IF(5<$D8,$B8*$E8*(1+$G8)^(5-1),IF(5=$D8,$B8*$F8*(1+'Center Overview'!$B$28)^(5-1)*(12-$H8)/12,$B8*$F8*(1+'Center Overview'!$B$28)^(5-1)))) -> 48567.767
A9: ='Rent Roll'!A8 -> D | B9: ='Rent Roll'!C8 -> 1000 | C9: ='Rent Roll'!D8 -> Occupied | D9: ='Rent Roll'!E8 -> 2 | E9: ='Rent Roll'!F8 -> 28 | F9: ='Rent Roll'!G8 -> 30 | G9: ='Rent Roll'!H8 -> 0.03 | H9: ='Center Overview'!$B$30 -> 4 | I9: =IF($C9="Vacant",IF(1=1,$B9*$F9*(12-$H9)/12,$B9*$F9*(1+'Center Overview'!$B$28)^(1-1)),IF(1<$D9,$B9*$E9*(1+$G9)^(1-1),IF(1=$D9,$B9*$F9*(1+'Center Overview'!$B$28)^(1-1)*(12-$H9)/12,$B9*$F9*(1+'Center Overview'!$B$28)^(1-1)))) -> 28000 | J9: =IF($C9="Vacant",IF(2=1,$B9*$F9*(12-$H9)/12,$B9*$F9*(1+'Center Overview'!$B$28)^(2-1)),IF(2<$D9,$B9*$E9*(1+$G9)^(2-1),IF(2=$D9,$B9*$F9*(1+'Center Overview'!$B$28)^(2-1)*(12-$H9)/12,$B9*$F9*(1+'Center Overview'!$B$28)^(2-1)))) -> 20500 | K9: =IF($C9="Vacant",IF(3=1,$B9*$F9*(12-$H9)/12,$B9*$F9*(1+'Center Overview'!$B$28)^(3-1)),IF(3<$D9,$B9*$E9*(1+$G9)^(3-1),IF(3=$D9,$B9*$F9*(1+'Center Overview'!$B$28)^(3-1)*(12-$H9)/12,$B9*$F9*(1+'Center Overview'!$B$28)^(3-1)))) -> 31518.75 | L9: =IF($C9="Vacant",IF(4=1,$B9*$F9*(12-$H9)/12,$B9*$F9*(1+'Center Overview'!$B$28)^(4-1)),IF(4<$D9,$B9*$E9*(1+$G9)^(4-1),IF(4=$D9,$B9*$F9*(1+'Center Overview'!$B$28)^(4-1)*(12-$H9)/12,$B9*$F9*(1+'Center Overview'!$B$28)^(4-1)))) -> 32306.719 | M9: =IF($C9="Vacant",IF(5=1,$B9*$F9*(12-$H9)/12,$B9*$F9*(1+'Center Overview'!$B$28)^(5-1)),IF(5<$D9,$B9*$E9*(1+$G9)^(5-1),IF(5=$D9,$B9*$F9*(1+'Center Overview'!$B$28)^(5-1)*(12-$H9)/12,$B9*$F9*(1+'Center Overview'!$B$28)^(5-1)))) -> 33114.387
A10: ='Rent Roll'!A9 -> E | B10: ='Rent Roll'!C9 -> 1400 | C10: ='Rent Roll'!D9 -> Occupied | D10: ='Rent Roll'!E9 -> 5 | E10: ='Rent Roll'!F9 -> 23 | F10: ='Rent Roll'!G9 -> 25 | G10: ='Rent Roll'!H9 -> 0.025 | H10: ='Center Overview'!$B$30 -> 4 | I10: =IF($C10="Vacant",IF(1=1,$B10*$F10*(12-$H10)/12,$B10*$F10*(1+'Center Overview'!$B$28)^(1-1)),IF(1<$D10,$B10*$E10*(1+$G10)^(1-1),IF(1=$D10,$B10*$F10*(1+'Center Overview'!$B$28)^(1-1)*(12-$H10)/12,$B10*$F10*(1+'Center Overview'!$B$28)^(1-1)))) -> 32200 | J10: =IF($C10="Vacant",IF(2=1,$B10*$F10*(12-$H10)/12,$B10*$F10*(1+'Center Overview'!$B$28)^(2-1)),IF(2<$D10,$B10*$E10*(1+$G10)^(2-1),IF(2=$D10,$B10*$F10*(1+'Center Overview'!$B$28)^(2-1)*(12-$H10)/12,$B10*$F10*(1+'Center Overview'!$B$28)^(2-1)))) -> 33005 | K10: =IF($C10="Vacant",IF(3=1,$B10*$F10*(12-$H10)/12,$B10*$F10*(1+'Center Overview'!$B$28)^(3-1)),IF(3<$D10,$B10*$E10*(1+$G10)^(3-1),IF(3=$D10,$B10*$F10*(1+'Center Overview'!$B$28)^(3-1)*(12-$H10)/12,$B10*$F10*(1+'Center Overview'!$B$28)^(3-1)))) -> 33830.125 | L10: =IF($C10="Vacant",IF(4=1,$B10*$F10*(12-$H10)/12,$B10*$F10*(1+'Center Overview'!$B$28)^(4-1)),IF(4<$D10,$B10*$E10*(1+$G10)^(4-1),IF(4=$D10,$B10*$F10*(1+'Center Overview'!$B$28)^(4-1)*(12-$H10)/12,$B10*$F10*(1+'Center Overview'!$B$28)^(4-1)))) -> 34675.878 | M10: =IF($C10="Vacant",IF(5=1,$B10*$F10*(12-$H10)/12,$B10*$F10*(1+'Center Overview'!$B$28)^(5-1)),IF(5<$D10,$B10*$E10*(1+$G10)^(5-1),IF(5=$D10,$B10*$F10*(1+'Center Overview'!$B$28)^(5-1)*(12-$H10)/12,$B10*$F10*(1+'Center Overview'!$B$28)^(5-1)))) -> 25755.634
A11: ='Rent Roll'!A10 -> F | B11: ='Rent Roll'!C10 -> 1600 | C11: ='Rent Roll'!D10 -> Vacant | D11: ='Rent Roll'!E10 -> 1 | E11: ='Rent Roll'!F10 -> 0 | F11: ='Rent Roll'!G10 -> 24 | G11: ='Rent Roll'!H10 -> 0 | H11: ='Center Overview'!$B$30 -> 4 | I11: =IF($C11="Vacant",IF(1=1,$B11*$F11*(12-$H11)/12,$B11*$F11*(1+'Center Overview'!$B$28)^(1-1)),IF(1<$D11,$B11*$E11*(1+$G11)^(1-1),IF(1=$D11,$B11*$F11*(1+'Center Overview'!$B$28)^(1-1)*(12-$H11)/12,$B11*$F11*(1+'Center Overview'!$B$28)^(1-1)))) -> 25600 | J11: =IF($C11="Vacant",IF(2=1,$B11*$F11*(12-$H11)/12,$B11*$F11*(1+'Center Overview'!$B$28)^(2-1)),IF(2<$D11,$B11*$E11*(1+$G11)^(2-1),IF(2=$D11,$B11*$F11*(1+'Center Overview'!$B$28)^(2-1)*(12-$H11)/12,$B11*$F11*(1+'Center Overview'!$B$28)^(2-1)))) -> 39360 | K11: =IF($C11="Vacant",IF(3=1,$B11*$F11*(12-$H11)/12,$B11*$F11*(1+'Center Overview'!$B$28)^(3-1)),IF(3<$D11,$B11*$E11*(1+$G11)^(3-1),IF(3=$D11,$B11*$F11*(1+'Center Overview'!$B$28)^(3-1)*(12-$H11)/12,$B11*$F11*(1+'Center Overview'!$B$28)^(3-1)))) -> 40344 | L11: =IF($C11="Vacant",IF(4=1,$B11*$F11*(12-$H11)/12,$B11*$F11*(1+'Center Overview'!$B$28)^(4-1)),IF(4<$D11,$B11*$E11*(1+$G11)^(4-1),IF(4=$D11,$B11*$F11*(1+'Center Overview'!$B$28)^(4-1)*(12-$H11)/12,$B11*$F11*(1+'Center Overview'!$B$28)^(4-1)))) -> 41352.6 | M11: =IF($C11="Vacant",IF(5=1,$B11*$F11*(12-$H11)/12,$B11*$F11*(1+'Center Overview'!$B$28)^(5-1)),IF(5<$D11,$B11*$E11*(1+$G11)^(5-1),IF(5=$D11,$B11*$F11*(1+'Center Overview'!$B$28)^(5-1)*(12-$H11)/12,$B11*$F11*(1+'Center Overview'!$B$28)^(5-1)))) -> 42386.415
A12: Total Base Rent | I12: =SUM(I6:I11) -> 187800 | J12: =SUM(J6:J11) -> 207057 | K12: =SUM(K6:K11) -> 209930.21 | L12: =SUM(L6:L11) -> 221336.92 | M12: =SUM(M6:M11) -> 233272.46
A14: CAM Recovery by Suite
A15: Suite | B15: SqFt | C15: Status | D15: Roll Year | E15: CAM / SqFt | F15: Downtime | G15: Year 1 | H15: Year 2 | I15: Year 3 | J15: Year 4 | K15: Year 5
A16: ='Rent Roll'!A5 -> A | B16: ='Rent Roll'!C5 -> 1800 | C16: ='Rent Roll'!D5 -> Occupied | D16: ='Rent Roll'!E5 -> 3 | E16: ='Rent Roll'!I5 -> 5.5 | F16: ='Center Overview'!$B$30 -> 4 | G16: =IF($C16="Vacant",IF(1=1,$B16*$E16*(12-$F16)/12,$B16*$E16*(1+'Center Overview'!$B$45)^(1-1)),IF(1<$D16,$B16*$E16*(1+'Center Overview'!$B$45)^(1-1),IF(1=$D16,$B16*$E16*(1+'Center Overview'!$B$45)^(1-1)*(12-$F16)/12,$B16*$E16*(1+'Center Overview'!$B$45)^(1-1)))) -> 9900 | H16: =IF($C16="Vacant",IF(2=1,$B16*$E16*(12-$F16)/12,$B16*$E16*(1+'Center Overview'!$B$45)^(2-1)),IF(2<$D16,$B16*$E16*(1+'Center Overview'!$B$45)^(2-1),IF(2=$D16,$B16*$E16*(1+'Center Overview'!$B$45)^(2-1)*(12-$F16)/12,$B16*$E16*(1+'Center Overview'!$B$45)^(2-1)))) -> 10147.5 | I16: =IF($C16="Vacant",IF(3=1,$B16*$E16*(12-$F16)/12,$B16*$E16*(1+'Center Overview'!$B$45)^(3-1)),IF(3<$D16,$B16*$E16*(1+'Center Overview'!$B$45)^(3-1),IF(3=$D16,$B16*$E16*(1+'Center Overview'!$B$45)^(3-1)*(12-$F16)/12,$B16*$E16*(1+'Center Overview'!$B$45)^(3-1)))) -> 6934.125 | J16: =IF($C16="Vacant",IF(4=1,$B16*$E16*(12-$F16)/12,$B16*$E16*(1+'Center Overview'!$B$45)^(4-1)),IF(4<$D16,$B16*$E16*(1+'Center Overview'!$B$45)^(4-1),IF(4=$D16,$B16*$E16*(1+'Center Overview'!$B$45)^(4-1)*(12-$F16)/12,$B16*$E16*(1+'Center Overview'!$B$45)^(4-1)))) -> 10661.217 | K16: =IF($C16="Vacant",IF(5=1,$B16*$E16*(12-$F16)/12,$B16*$E16*(1+'Center Overview'!$B$45)^(5-1)),IF(5<$D16,$B16*$E16*(1+'Center Overview'!$B$45)^(5-1),IF(5=$D16,$B16*$E16*(1+'Center Overview'!$B$45)^(5-1)*(12-$F16)/12,$B16*$E16*(1+'Center Overview'!$B$45)^(5-1)))) -> 10927.748
A17: ='Rent Roll'!A6 -> B | B17: ='Rent Roll'!C6 -> 1200 | C17: ='Rent Roll'!D6 -> Occupied | D17: ='Rent Roll'!E6 -> 1 | E17: ='Rent Roll'!I6 -> 5.25 | F17: ='Center Overview'!$B$30 -> 4 | G17: =IF($C17="Vacant",IF(1=1,$B17*$E17*(12-$F17)/12,$B17*$E17*(1+'Center Overview'!$B$45)^(1-1)),IF(1<$D17,$B17*$E17*(1+'Center Overview'!$B$45)^(1-1),IF(1=$D17,$B17*$E17*(1+'Center Overview'!$B$45)^(1-1)*(12-$F17)/12,$B17*$E17*(1+'Center Overview'!$B$45)^(1-1)))) -> 4200 | H17: =IF($C17="Vacant",IF(2=1,$B17*$E17*(12-$F17)/12,$B17*$E17*(1+'Center Overview'!$B$45)^(2-1)),IF(2<$D17,$B17*$E17*(1+'Center Overview'!$B$45)^(2-1),IF(2=$D17,$B17*$E17*(1+'Center Overview'!$B$45)^(2-1)*(12-$F17)/12,$B17*$E17*(1+'Center Overview'!$B$45)^(2-1)))) -> 6457.5 | I17: =IF($C17="Vacant",IF(3=1,$B17*$E17*(12-$F17)/12,$B17*$E17*(1+'Center Overview'!$B$45)^(3-1)),IF(3<$D17,$B17*$E17*(1+'Center Overview'!$B$45)^(3-1),IF(3=$D17,$B17*$E17*(1+'Center Overview'!$B$45)^(3-1)*(12-$F17)/12,$B17*$E17*(1+'Center Overview'!$B$45)^(3-1)))) -> 6618.9375 | J17: =IF($C17="Vacant",IF(4=1,$B17*$E17*(12-$F17)/12,$B17*$E17*(1+'Center Overview'!$B$45)^(4-1)),IF(4<$D17,$B17*$E17*(1+'Center Overview'!$B$45)^(4-1),IF(4=$D17,$B17*$E17*(1+'Center Overview'!$B$45)^(4-1)*(12-$F17)/12,$B17*$E17*(1+'Center Overview'!$B$45)^(4-1)))) -> 6784.4109 | K17: =IF($C17="Vacant",IF(5=1,$B17*$E17*(12-$F17)/12,$B17*$E17*(1+'Center Overview'!$B$45)^(5-1)),IF(5<$D17,$B17*$E17*(1+'Center Overview'!$B$45)^(5-1),IF(5=$D17,$B17*$E17*(1+'Center Overview'!$B$45)^(5-1)*(12-$F17)/12,$B17*$E17*(1+'Center Overview'!$B$45)^(5-1)))) -> 6954.0212
A18: ='Rent Roll'!A7 -> C | B18: ='Rent Roll'!C7 -> 2200 | C18: ='Rent Roll'!D7 -> Occupied | D18: ='Rent Roll'!E7 -> 4 | E18: ='Rent Roll'!I7 -> 4.75 | F18: ='Center Overview'!$B$30 -> 4 | G18: =IF($C18="Vacant",IF(1=1,$B18*$E18*(12-$F18)/12,$B18*$E18*(1+'Center Overview'!$B$45)^(1-1)),IF(1<$D18,$B18*$E18*(1+'Center Overview'!$B$45)^(1-1),IF(1=$D18,$B18*$E18*(1+'Center Overview'!$B$45)^(1-1)*(12-$F18)/12,$B18*$E18*(1+'Center Overview'!$B$45)^(1-1)))) -> 10450 | H18: =IF($C18="Vacant",IF(2=1,$B18*$E18*(12-$F18)/12,$B18*$E18*(1+'Center Overview'!$B$45)^(2-1)),IF(2<$D18,$B18*$E18*(1+'Center Overview'!$B$45)^(2-1),IF(2=$D18,$B18*$E18*(1+'Center Overview'!$B$45)^(2-1)*(12-$F18)/12,$B18*$E18*(1+'Center Overview'!$B$45)^(2-1)))) -> 10711.25 | I18: =IF($C18="Vacant",IF(3=1,$B18*$E18*(12-$F18)/12,$B18*$E18*(1+'Center Overview'!$B$45)^(3-1)),IF(3<$D18,$B18*$E18*(1+'Center Overview'!$B$45)^(3-1),IF(3=$D18,$B18*$E18*(1+'Center Overview'!$B$45)^(3-1)*(12-$F18)/12,$B18*$E18*(1+'Center Overview'!$B$45)^(3-1)))) -> 10979.031 | J18: =IF($C18="Vacant",IF(4=1,$B18*$E18*(12-$F18)/12,$B18*$E18*(1+'Center Overview'!$B$45)^(4-1)),IF(4<$D18,$B18*$E18*(1+'Center Overview'!$B$45)^(4-1),IF(4=$D18,$B18*$E18*(1+'Center Overview'!$B$45)^(4-1)*(12-$F18)/12,$B18*$E18*(1+'Center Overview'!$B$45)^(4-1)))) -> 7502.338 | K18: =IF($C18="Vacant",IF(5=1,$B18*$E18*(12-$F18)/12,$B18*$E18*(1+'Center Overview'!$B$45)^(5-1)),IF(5<$D18,$B18*$E18*(1+'Center Overview'!$B$45)^(5-1),IF(5=$D18,$B18*$E18*(1+'Center Overview'!$B$45)^(5-1)*(12-$F18)/12,$B18*$E18*(1+'Center Overview'!$B$45)^(5-1)))) -> 11534.845
A19: ='Rent Roll'!A8 -> D | B19: ='Rent Roll'!C8 -> 1000 | C19: ='Rent Roll'!D8 -> Occupied | D19: ='Rent Roll'!E8 -> 2 | E19: ='Rent Roll'!I8 -> 6 | F19: ='Center Overview'!$B$30 -> 4 | G19: =IF($C19="Vacant",IF(1=1,$B19*$E19*(12-$F19)/12,$B19*$E19*(1+'Center Overview'!$B$45)^(1-1)),IF(1<$D19,$B19*$E19*(1+'Center Overview'!$B$45)^(1-1),IF(1=$D19,$B19*$E19*(1+'Center Overview'!$B$45)^(1-1)*(12-$F19)/12,$B19*$E19*(1+'Center Overview'!$B$45)^(1-1)))) -> 6000 | H19: =IF($C19="Vacant",IF(2=1,$B19*$E19*(12-$F19)/12,$B19*$E19*(1+'Center Overview'!$B$45)^(2-1)),IF(2<$D19,$B19*$E19*(1+'Center Overview'!$B$45)^(2-1),IF(2=$D19,$B19*$E19*(1+'Center Overview'!$B$45)^(2-1)*(12-$F19)/12,$B19*$E19*(1+'Center Overview'!$B$45)^(2-1)))) -> 4100 | I19: =IF($C19="Vacant",IF(3=1,$B19*$E19*(12-$F19)/12,$B19*$E19*(1+'Center Overview'!$B$45)^(3-1)),IF(3<$D19,$B19*$E19*(1+'Center Overview'!$B$45)^(3-1),IF(3=$D19,$B19*$E19*(1+'Center Overview'!$B$45)^(3-1)*(12-$F19)/12,$B19*$E19*(1+'Center Overview'!$B$45)^(3-1)))) -> 6303.75 | J19: =IF($C19="Vacant",IF(4=1,$B19*$E19*(12-$F19)/12,$B19*$E19*(1+'Center Overview'!$B$45)^(4-1)),IF(4<$D19,$B19*$E19*(1+'Center Overview'!$B$45)^(4-1),IF(4=$D19,$B19*$E19*(1+'Center Overview'!$B$45)^(4-1)*(12-$F19)/12,$B19*$E19*(1+'Center Overview'!$B$45)^(4-1)))) -> 6461.3437 | K19: =IF($C19="Vacant",IF(5=1,$B19*$E19*(12-$F19)/12,$B19*$E19*(1+'Center Overview'!$B$45)^(5-1)),IF(5<$D19,$B19*$E19*(1+'Center Overview'!$B$45)^(5-1),IF(5=$D19,$B19*$E19*(1+'Center Overview'!$B$45)^(5-1)*(12-$F19)/12,$B19*$E19*(1+'Center Overview'!$B$45)^(5-1)))) -> 6622.8773
A20: ='Rent Roll'!A9 -> E | B20: ='Rent Roll'!C9 -> 1400 | C20: ='Rent Roll'!D9 -> Occupied | D20: ='Rent Roll'!E9 -> 5 | E20: ='Rent Roll'!I9 -> 5.25 | F20: ='Center Overview'!$B$30 -> 4 | G20: =IF($C20="Vacant",IF(1=1,$B20*$E20*(12-$F20)/12,$B20*$E20*(1+'Center Overview'!$B$45)^(1-1)),IF(1<$D20,$B20*$E20*(1+'Center Overview'!$B$45)^(1-1),IF(1=$D20,$B20*$E20*(1+'Center Overview'!$B$45)^(1-1)*(12-$F20)/12,$B20*$E20*(1+'Center Overview'!$B$45)^(1-1)))) -> 7350 | H20: =IF($C20="Vacant",IF(2=1,$B20*$E20*(12-$F20)/12,$B20*$E20*(1+'Center Overview'!$B$45)^(2-1)),IF(2<$D20,$B20*$E20*(1+'Center Overview'!$B$45)^(2-1),IF(2=$D20,$B20*$E20*(1+'Center Overview'!$B$45)^(2-1)*(12-$F20)/12,$B20*$E20*(1+'Center Overview'!$B$45)^(2-1)))) -> 7533.75 | I20: =IF($C20="Vacant",IF(3=1,$B20*$E20*(12-$F20)/12,$B20*$E20*(1+'Center Overview'!$B$45)^(3-1)),IF(3<$D20,$B20*$E20*(1+'Center Overview'!$B$45)^(3-1),IF(3=$D20,$B20*$E20*(1+'Center Overview'!$B$45)^(3-1)*(12-$F20)/12,$B20*$E20*(1+'Center Overview'!$B$45)^(3-1)))) -> 7722.0937 | J20: =IF($C20="Vacant",IF(4=1,$B20*$E20*(12-$F20)/12,$B20*$E20*(1+'Center Overview'!$B$45)^(4-1)),IF(4<$D20,$B20*$E20*(1+'Center Overview'!$B$45)^(4-1),IF(4=$D20,$B20*$E20*(1+'Center Overview'!$B$45)^(4-1)*(12-$F20)/12,$B20*$E20*(1+'Center Overview'!$B$45)^(4-1)))) -> 7915.1461 | K20: =IF($C20="Vacant",IF(5=1,$B20*$E20*(12-$F20)/12,$B20*$E20*(1+'Center Overview'!$B$45)^(5-1)),IF(5<$D20,$B20*$E20*(1+'Center Overview'!$B$45)^(5-1),IF(5=$D20,$B20*$E20*(1+'Center Overview'!$B$45)^(5-1)*(12-$F20)/12,$B20*$E20*(1+'Center Overview'!$B$45)^(5-1)))) -> 5408.6832
A21: ='Rent Roll'!A10 -> F | B21: ='Rent Roll'!C10 -> 1600 | C21: ='Rent Roll'!D10 -> Vacant | D21: ='Rent Roll'!E10 -> 1 | E21: ='Rent Roll'!I10 -> 5.25 | F21: ='Center Overview'!$B$30 -> 4 | G21: =IF($C21="Vacant",IF(1=1,$B21*$E21*(12-$F21)/12,$B21*$E21*(1+'Center Overview'!$B$45)^(1-1)),IF(1<$D21,$B21*$E21*(1+'Center Overview'!$B$45)^(1-1),IF(1=$D21,$B21*$E21*(1+'Center Overview'!$B$45)^(1-1)*(12-$F21)/12,$B21*$E21*(1+'Center Overview'!$B$45)^(1-1)))) -> 5600 | H21: =IF($C21="Vacant",IF(2=1,$B21*$E21*(12-$F21)/12,$B21*$E21*(1+'Center Overview'!$B$45)^(2-1)),IF(2<$D21,$B21*$E21*(1+'Center Overview'!$B$45)^(2-1),IF(2=$D21,$B21*$E21*(1+'Center Overview'!$B$45)^(2-1)*(12-$F21)/12,$B21*$E21*(1+'Center Overview'!$B$45)^(2-1)))) -> 8610 | I21: =IF($C21="Vacant",IF(3=1,$B21*$E21*(12-$F21)/12,$B21*$E21*(1+'Center Overview'!$B$45)^(3-1)),IF(3<$D21,$B21*$E21*(1+'Center Overview'!$B$45)^(3-1),IF(3=$D21,$B21*$E21*(1+'Center Overview'!$B$45)^(3-1)*(12-$F21)/12,$B21*$E21*(1+'Center Overview'!$B$45)^(3-1)))) -> 8825.25 | J21: =IF($C21="Vacant",IF(4=1,$B21*$E21*(12-$F21)/12,$B21*$E21*(1+'Center Overview'!$B$45)^(4-1)),IF(4<$D21,$B21*$E21*(1+'Center Overview'!$B$45)^(4-1),IF(4=$D21,$B21*$E21*(1+'Center Overview'!$B$45)^(4-1)*(12-$F21)/12,$B21*$E21*(1+'Center Overview'!$B$45)^(4-1)))) -> 9045.8812 | K21: =IF($C21="Vacant",IF(5=1,$B21*$E21*(12-$F21)/12,$B21*$E21*(1+'Center Overview'!$B$45)^(5-1)),IF(5<$D21,$B21*$E21*(1+'Center Overview'!$B$45)^(5-1),IF(5=$D21,$B21*$E21*(1+'Center Overview'!$B$45)^(5-1)*(12-$F21)/12,$B21*$E21*(1+'Center Overview'!$B$45)^(5-1)))) -> 9272.0283
A22: Total CAM Recovery | G22: =SUM(G16:G21) -> 43500 | H22: =SUM(H16:H21) -> 47560 | I22: =SUM(I16:I21) -> 47383.188 | J22: =SUM(J16:J21) -> 48370.337 | K22: =SUM(K16:K21) -> 50720.202
A24: TI / LC Cost by Suite
A25: Suite | B25: SqFt | C25: Status | D25: Roll Year | E25: TI / SqFt | F25: LC % | G25: Year 1 | H25: Year 2 | I25: Year 3 | J25: Year 4 | K25: Year 5
A26: ='Rent Roll'!A5 -> A | B26: ='Rent Roll'!C5 -> 1800 | C26: ='Rent Roll'!D5 -> Occupied | D26: ='Rent Roll'!E5 -> 3 | E26: ='Center Overview'!$B$32 -> 12 | F26: ='Center Overview'!$B$31 -> 0.04 | G26: =IF(OR(AND($C26="Vacant",1=1),AND($C26<>"Vacant",1=$D26)),-($B26*$E26+(I6*$F26)),0) -> 0 | H26: =IF(OR(AND($C26="Vacant",2=1),AND($C26<>"Vacant",2=$D26)),-($B26*$E26+(J6*$F26)),0) -> 0 | I26: =IF(OR(AND($C26="Vacant",3=1),AND($C26<>"Vacant",3=$D26)),-($B26*$E26+(K6*$F26)),0) -> -22911.18 | J26: =IF(OR(AND($C26="Vacant",4=1),AND($C26<>"Vacant",4=$D26)),-($B26*$E26+(L6*$F26)),0) -> 0 | K26: =IF(OR(AND($C26="Vacant",5=1),AND($C26<>"Vacant",5=$D26)),-($B26*$E26+(M6*$F26)),0) -> 0
A27: ='Rent Roll'!A6 -> B | B27: ='Rent Roll'!C6 -> 1200 | C27: ='Rent Roll'!D6 -> Occupied | D27: ='Rent Roll'!E6 -> 1 | E27: ='Center Overview'!$B$32 -> 12 | F27: ='Center Overview'!$B$31 -> 0.04 | G27: =IF(OR(AND($C27="Vacant",1=1),AND($C27<>"Vacant",1=$D27)),-($B27*$E27+(I7*$F27)),0) -> -15168 | H27: =IF(OR(AND($C27="Vacant",2=1),AND($C27<>"Vacant",2=$D27)),-($B27*$E27+(J7*$F27)),0) -> 0 | I27: =IF(OR(AND($C27="Vacant",3=1),AND($C27<>"Vacant",3=$D27)),-($B27*$E27+(K7*$F27)),0) -> 0 | J27: =IF(OR(AND($C27="Vacant",4=1),AND($C27<>"Vacant",4=$D27)),-($B27*$E27+(L7*$F27)),0) -> 0 | K27: =IF(OR(AND($C27="Vacant",5=1),AND($C27<>"Vacant",5=$D27)),-($B27*$E27+(M7*$F27)),0) -> 0
A28: ='Rent Roll'!A7 -> C | B28: ='Rent Roll'!C7 -> 2200 | C28: ='Rent Roll'!D7 -> Occupied | D28: ='Rent Roll'!E7 -> 4 | E28: ='Center Overview'!$B$32 -> 12 | F28: ='Center Overview'!$B$31 -> 0.04 | G28: =IF(OR(AND($C28="Vacant",1=1),AND($C28<>"Vacant",1=$D28)),-($B28*$E28+(I8*$F28)),0) -> 0 | H28: =IF(OR(AND($C28="Vacant",2=1),AND($C28<>"Vacant",2=$D28)),-($B28*$E28+(J8*$F28)),0) -> 0 | I28: =IF(OR(AND($C28="Vacant",3=1),AND($C28<>"Vacant",3=$D28)),-($B28*$E28+(K8*$F28)),0) -> 0 | J28: =IF(OR(AND($C28="Vacant",4=1),AND($C28<>"Vacant",4=$D28)),-($B28*$E28+(L8*$F28)),0) -> -27663.552 | K28: =IF(OR(AND($C28="Vacant",5=1),AND($C28<>"Vacant",5=$D28)),-($B28*$E28+(M8*$F28)),0) -> 0
A29: ='Rent Roll'!A8 -> D | B29: ='Rent Roll'!C8 -> 1000 | C29: ='Rent Roll'!D8 -> Occupied | D29: ='Rent Roll'!E8 -> 2 | E29: ='Center Overview'!$B$32 -> 12 | F29: ='Center Overview'!$B$31 -> 0.04 | G29: =IF(OR(AND($C29="Vacant",1=1),AND($C29<>"Vacant",1=$D29)),-($B29*$E29+(I9*$F29)),0) -> 0 | H29: =IF(OR(AND($C29="Vacant",2=1),AND($C29<>"Vacant",2=$D29)),-($B29*$E29+(J9*$F29)),0) -> -12820 | I29: =IF(OR(AND($C29="Vacant",3=1),AND($C29<>"Vacant",3=$D29)),-($B29*$E29+(K9*$F29)),0) -> 0 | J29: =IF(OR(AND($C29="Vacant",4=1),AND($C29<>"Vacant",4=$D29)),-($B29*$E29+(L9*$F29)),0) -> 0 | K29: =IF(OR(AND($C29="Vacant",5=1),AND($C29<>"Vacant",5=$D29)),-($B29*$E29+(M9*$F29)),0) -> 0
A30: ='Rent Roll'!A9 -> E | B30: ='Rent Roll'!C9 -> 1400 | C30: ='Rent Roll'!D9 -> Occupied | D30: ='Rent Roll'!E9 -> 5 | E30: ='Center Overview'!$B$32 -> 12 | F30: ='Center Overview'!$B$31 -> 0.04 | G30: =IF(OR(AND($C30="Vacant",1=1),AND($C30<>"Vacant",1=$D30)),-($B30*$E30+(I10*$F30)),0) -> 0 | H30: =IF(OR(AND($C30="Vacant",2=1),AND($C30<>"Vacant",2=$D30)),-($B30*$E30+(J10*$F30)),0) -> 0 | I30: =IF(OR(AND($C30="Vacant",3=1),AND($C30<>"Vacant",3=$D30)),-($B30*$E30+(K10*$F30)),0) -> 0 | J30: =IF(OR(AND($C30="Vacant",4=1),AND($C30<>"Vacant",4=$D30)),-($B30*$E30+(L10*$F30)),0) -> 0 | K30: =IF(OR(AND($C30="Vacant",5=1),AND($C30<>"Vacant",5=$D30)),-($B30*$E30+(M10*$F30)),0) -> -17830.225
A31: ='Rent Roll'!A10 -> F | B31: ='Rent Roll'!C10 -> 1600 | C31: ='Rent Roll'!D10 -> Vacant | D31: ='Rent Roll'!E10 -> 1 | E31: ='Center Overview'!$B$32 -> 12 | F31: ='Center Overview'!$B$31 -> 0.04 | G31: =IF(OR(AND($C31="Vacant",1=1),AND($C31<>"Vacant",1=$D31)),-($B31*$E31+(I11*$F31)),0) -> -20224 | H31: =IF(OR(AND($C31="Vacant",2=1),AND($C31<>"Vacant",2=$D31)),-($B31*$E31+(J11*$F31)),0) -> 0 | I31: =IF(OR(AND($C31="Vacant",3=1),AND($C31<>"Vacant",3=$D31)),-($B31*$E31+(K11*$F31)),0) -> 0 | J31: =IF(OR(AND($C31="Vacant",4=1),AND($C31<>"Vacant",4=$D31)),-($B31*$E31+(L11*$F31)),0) -> 0 | K31: =IF(OR(AND($C31="Vacant",5=1),AND($C31<>"Vacant",5=$D31)),-($B31*$E31+(M11*$F31)),0) -> 0
A32: Total TI / LC | G32: =SUM(G26:G31) -> -35392 | H32: =SUM(H26:H31) -> -12820 | I32: =SUM(I26:I31) -> -22911.18 | J32: =SUM(J26:J31) -> -27663.552 | K32: =SUM(K26:K31) -> -17830.225

Sheet 5-Year Pro Forma
A2: 5-Year Pro Forma
A4: Line Item | B4: Year 1 | C4: Year 2 | D4: Year 3 | E4: Year 4 | F4: Year 5
A5: Base rent | B5: ='Lease Rollover'!I12 -> 187800 | C5: ='Lease Rollover'!J12 -> 207057 | D5: ='Lease Rollover'!K12 -> 209930.21 | E5: ='Lease Rollover'!L12 -> 221336.92 | F5: ='Lease Rollover'!M12 -> 233272.46
A6: CAM recoveries | B6: ='Lease Rollover'!G22 -> 43500 | C6: ='Lease Rollover'!H22 -> 47560 | D6: ='Lease Rollover'!I22 -> 47383.188 | E6: ='Lease Rollover'!J22 -> 48370.337 | F6: ='Lease Rollover'!K22 -> 50720.202
A7: Potential gross income | B7: =B5+B6 -> 231300 | C7: =C5+C6 -> 254617 | D7: =D5+D6 -> 257313.4 | E7: =E5+E6 -> 269707.26 | F7: =F5+F6 -> 283992.66
A8: General credit loss | B8: =B7*'Center Overview'!$B$29*-1 -> -4626 | C8: =C7*'Center Overview'!$B$29*-1 -> -5092.34 | D8: =D7*'Center Overview'!$B$29*-1 -> -5146.268 | E8: =E7*'Center Overview'!$B$29*-1 -> -5394.1451 | F8: =F7*'Center Overview'!$B$29*-1 -> -5679.8532
A9: Effective gross income | B9: =B7+B8 -> 226674 | C9: =C7+C8 -> 249524.66 | D9: =D7+D8 -> 252167.13 | E9: =E7+E8 -> 264313.11 | F9: =F7+F8 -> 278312.81
A10: Fixed operating expenses | B10: =SUM('Center Overview'!$B$38:$B$43) -> 94000 | C10: =B10*(1+'Center Overview'!$B$45) -> 96350 | D10: =C10*(1+'Center Overview'!$B$45) -> 98758.75 | E10: =D10*(1+'Center Overview'!$B$45) -> 101227.72 | F10: =E10*(1+'Center Overview'!$B$45) -> 103758.41
A11: Management fee | B11: =B9*'Center Overview'!$B$44 -> 9066.96 | C11: =C9*'Center Overview'!$B$44 -> 9980.9864 | D11: =D9*'Center Overview'!$B$44 -> 10086.685 | E11: =E9*'Center Overview'!$B$44 -> 10572.524 | F11: =F9*'Center Overview'!$B$44 -> 11132.512
A12: NOI before TI / LC | B12: =B9-B10-B11 -> 123607.04 | C12: =C9-C10-C11 -> 143193.67 | D12: =D9-D10-D11 -> 143321.7 | E12: =E9-E10-E11 -> 152512.87 | F12: =F9-F10-F11 -> 163421.88
A13: TI / LC costs | B13: =ABS('Lease Rollover'!G32) -> 35392 | C13: =ABS('Lease Rollover'!H32) -> 12820 | D13: =ABS('Lease Rollover'!I32) -> 22911.18 | E13: =ABS('Lease Rollover'!J32) -> 27663.552 | F13: =ABS('Lease Rollover'!K32) -> 17830.225
A14: NOI after TI / LC | B14: =B12-B13 -> 88215.04 | C14: =C12-C13 -> 130373.67 | D14: =D12-D13 -> 120410.52 | E14: =E12-E13 -> 124849.32 | F14: =F12-F13 -> 145591.66
A15: Debt service | B15: ='Center Overview'!$B$25 -> 168208.68 | C15: ='Center Overview'!$B$25 -> 168208.68 | D15: ='Center Overview'!$B$25 -> 168208.68 | E15: ='Center Overview'!$B$25 -> 168208.68 | F15: ='Center Overview'!$B$25 -> 168208.68
A16: Cash flow after debt | B16: =B14-B15 -> -79993.637 | C16: =C14-C15 -> -37835.003 | D16: =D14-D15 -> -47798.158 | E16: =E14-E15 -> -43359.36 | F16: =F14-F15 -> -22617.019
A17: DSCR | B17: =IF(B15=0,0,B12/B15) -> 0.73484342 | C17: =IF(C15=0,0,C12/C15) -> 0.85128589 | D17: =IF(D15=0,0,D12/D15) -> 0.852047 | E17: =IF(E15=0,0,E12/E15) -> 0.90668848 | F17: =IF(F15=0,0,F12/F15) -> 0.97154253

Sheet Exit & Snapshot
A2: Exit & Snapshot
A4: Deal | E4: IRR Cash Flow
A5: Purchase price | B5: ='Center Overview'!B14 -> 3150000 | E5: Initial | F5: Year 1 | G5: Year 2 | H5: Year 3 | I5: Year 4 | J5: Year 5 + Sale
A6: Total basis | B6: ='Center Overview'!B17 -> 3245000 | E6: =+B28 -> 1197500 | F6: ='5-Year Pro Forma'!B16 -> -79993.637 | G6: ='5-Year Pro Forma'!C16 -> -37835.003 | H6: ='5-Year Pro Forma'!D16 -> -47798.158 | I6: ='5-Year Pro Forma'!E16 -> -43359.36 | J6: ='5-Year Pro Forma'!F16+B24 -> -1616752.9
A7: Loan amount | B7: ='Center Overview'!B21 -> 2047500
A8: Year 1 NOI before TI / LC | B8: ='5-Year Pro Forma'!B12 -> 123607.04
A9: Year 1 cash flow after debt | B9: ='5-Year Pro Forma'!B16 -> -79993.637
A12: Hold
A13: Total TI / LC over 5 years | B13: =SUM('5-Year Pro Forma'!B13:F13) -> 116616.96
A14: Average annual cash flow | B14: =AVERAGE('5-Year Pro Forma'!B16:F16) -> -46320.635
A15: Current occupancy | B15: ='Center Overview'!B9 -> 0.82608696
A16: Blended market rent / SqFt | B16: ='Center Overview'!B11 -> 24.23913
A19: Sale
A20: Year 5 NOI before TI / LC | B20: ='5-Year Pro Forma'!F12 -> 163421.88
A21: Exit value | B21: =IF('Center Overview'!B34=0,0,B20/'Center Overview'!B34) -> 2334598.3
A22: Selling costs | B22: =B21*'Center Overview'!B35 -> 81710.941
A23: Loan payoff | B23: =-FV('Center Overview'!B22/12,'Center Overview'!B33*12,'Center Overview'!B24,'Center Overview'!B21) -> 3847023.2
A24: Net sale proceeds | B24: =B21-B22-B23 -> -1594135.8
A27: Returns
A28: Initial equity | B28: ='Center Overview'!B17-'Center Overview'!B21 -> 1197500
A29: Total cash back | B29: =SUM('5-Year Pro Forma'!B16:F16)+B24 -> -1825739
A30: 5-year equity multiple | B30: =IF(B28=0,0,B29/B28) -> -1.5246255
A31: Levered IRR | B31: =IRR(E6:J6) -> 0.095135367
