Workbook

Sheet Trade Log
A1: Trade # | B1: Date opened | C1: Date closed | D1: Ticker | E1: Strategy | F1: Strike | G1: Expiration | H1: Contracts | I1: Premium/share | J1: Total premium | K1: Outcome | L1: Close price/share | M1: Net P&L | N1: Days held | O1: Annualized return | P1: Notes
A2: 1 | B2: 45299 | C2: 45338 | D2: AAPL | E2: Cash-Secured Put | F2: 185 | G2: 45338 | H2: 1 | I2: 1.25 | J2: =IF(H2="","",H2*I2*100) -> 125 | K2: Expired Worthless | L2: 0 | M2: =IF(K2="Open","",IF(K2="Bought to Close",J2-L2*H2*100,J2)) -> 125 | N2: =IF(OR(C2="",B2=""),"",C2-B2) -> 39 | O2: =IF(OR(K2="Open",N2="",N2=0),"",IFERROR((M2/IF(E2="Cash-Secured Put",F2*H2*100,IF(SUMPRODUCT((Holdings!$A$2:$A$21=D2)*(Holdings!$M$2:$M$21="Holding"),Holdings!$F$2:$F$21,Holdings!$B$2:$B$21)=0,F2*H2*100,SUMPRODUCT((Holdings!$A$2:$A$21=D2)*(Holdings!$M$2:$M$21="Holding"),Holdings!$F$2:$F$21,Holdings!$B$2:$B$21))))*(365/N2),"")) -> 0.063236313 | P2: CSP rolled once then expired
A3: 2 | B3: 45355 | C3: 45401 | D3: AAPL | E3: Cash-Secured Put | F3: 172.5 | G3: 45401 | H3: 1 | I3: 2.1 | J3: =IF(H3="","",H3*I3*100) -> 210 | K3: Expired Worthless | L3: 0 | M3: =IF(K3="Open","",IF(K3="Bought to Close",J3-L3*H3*100,J3)) -> 210 | N3: =IF(OR(C3="",B3=""),"",C3-B3) -> 46 | O3: =IF(OR(K3="Open",N3="",N3=0),"",IFERROR((M3/IF(E3="Cash-Secured Put",F3*H3*100,IF(SUMPRODUCT((Holdings!$A$2:$A$21=D3)*(Holdings!$M$2:$M$21="Holding"),Holdings!$F$2:$F$21,Holdings!$B$2:$B$21)=0,F3*H3*100,SUMPRODUCT((Holdings!$A$2:$A$21=D3)*(Holdings!$M$2:$M$21="Holding"),Holdings!$F$2:$F$21,Holdings!$B$2:$B$21))))*(365/N3),"")) -> 0.096597353
A4: 3 | B4: 45418 | C4: 45464 | D4: AAPL | E4: Cash-Secured Put | F4: 178 | G4: 45464 | H4: 1 | I4: 1.85 | J4: =IF(H4="","",H4*I4*100) -> 185 | K4: Assigned | L4: 0 | M4: =IF(K4="Open","",IF(K4="Bought to Close",J4-L4*H4*100,J4)) -> 185 | N4: =IF(OR(C4="",B4=""),"",C4-B4) -> 46 | O4: =IF(OR(K4="Open",N4="",N4=0),"",IFERROR((M4/IF(E4="Cash-Secured Put",F4*H4*100,IF(SUMPRODUCT((Holdings!$A$2:$A$21=D4)*(Holdings!$M$2:$M$21="Holding"),Holdings!$F$2:$F$21,Holdings!$B$2:$B$21)=0,F4*H4*100,SUMPRODUCT((Holdings!$A$2:$A$21=D4)*(Holdings!$M$2:$M$21="Holding"),Holdings!$F$2:$F$21,Holdings!$B$2:$B$21))))*(365/N4),"")) -> 0.082468246 | P4: Assigned into shares
A5: 4 | B5: 45467 | C5: 45492 | D5: AAPL | E5: Covered Call | F5: 185 | G5: 45492 | H5: 1 | I5: 1.4 | J5: =IF(H5="","",H5*I5*100) -> 140 | K5: Expired Worthless | L5: 0 | M5: =IF(K5="Open","",IF(K5="Bought to Close",J5-L5*H5*100,J5)) -> 140 | N5: =IF(OR(C5="",B5=""),"",C5-B5) -> 25 | O5: =IF(OR(K5="Open",N5="",N5=0),"",IFERROR((M5/IF(E5="Cash-Secured Put",F5*H5*100,IF(SUMPRODUCT((Holdings!$A$2:$A$21=D5)*(Holdings!$M$2:$M$21="Holding"),Holdings!$F$2:$F$21,Holdings!$B$2:$B$21)=0,F5*H5*100,SUMPRODUCT((Holdings!$A$2:$A$21=D5)*(Holdings!$M$2:$M$21="Holding"),Holdings!$F$2:$F$21,Holdings!$B$2:$B$21))))*(365/N5),"")) -> 0.11603747
A6: 5 | B6: 45495 | C6: 45520 | D6: AAPL | E6: Covered Call | F6: 190 | G6: 45520 | H6: 1 | I6: 1.15 | J6: =IF(H6="","",H6*I6*100) -> 115 | K6: Called Away | L6: 0 | M6: =IF(K6="Open","",IF(K6="Bought to Close",J6-L6*H6*100,J6)) -> 115 | N6: =IF(OR(C6="",B6=""),"",C6-B6) -> 25 | O6: =IF(OR(K6="Open",N6="",N6=0),"",IFERROR((M6/IF(E6="Cash-Secured Put",F6*H6*100,IF(SUMPRODUCT((Holdings!$A$2:$A$21=D6)*(Holdings!$M$2:$M$21="Holding"),Holdings!$F$2:$F$21,Holdings!$B$2:$B$21)=0,F6*H6*100,SUMPRODUCT((Holdings!$A$2:$A$21=D6)*(Holdings!$M$2:$M$21="Holding"),Holdings!$F$2:$F$21,Holdings!$B$2:$B$21))))*(365/N6),"")) -> 0.095316492 | P6: Stock called at 190
A7: 6 | B7: 45323 | C7: 45366 | D7: KO | E7: Cash-Secured Put | F7: 58 | G7: 45366 | H7: 2 | I7: 0.45 | J7: =IF(H7="","",H7*I7*100) -> 90 | K7: Bought to Close | L7: 0.12 | M7: =IF(K7="Open","",IF(K7="Bought to Close",J7-L7*H7*100,J7)) -> 66 | N7: =IF(OR(C7="",B7=""),"",C7-B7) -> 43 | O7: =IF(OR(K7="Open",N7="",N7=0),"",IFERROR((M7/IF(E7="Cash-Secured Put",F7*H7*100,IF(SUMPRODUCT((Holdings!$A$2:$A$21=D7)*(Holdings!$M$2:$M$21="Holding"),Holdings!$F$2:$F$21,Holdings!$B$2:$B$21)=0,F7*H7*100,SUMPRODUCT((Holdings!$A$2:$A$21=D7)*(Holdings!$M$2:$M$21="Holding"),Holdings!$F$2:$F$21,Holdings!$B$2:$B$21))))*(365/N7),"")) -> 0.04829591 | P7: Closed early before ex-div
A8: 7 | B8: 45384 | C8: 45429 | D8: KO | E8: Cash-Secured Put | F8: 59 | G8: 45429 | H8: 2 | I8: 0.52 | J8: =IF(H8="","",H8*I8*100) -> 104 | K8: Expired Worthless | L8: 0 | M8: =IF(K8="Open","",IF(K8="Bought to Close",J8-L8*H8*100,J8)) -> 104 | N8: =IF(OR(C8="",B8=""),"",C8-B8) -> 45 | O8: =IF(OR(K8="Open",N8="",N8=0),"",IFERROR((M8/IF(E8="Cash-Secured Put",F8*H8*100,IF(SUMPRODUCT((Holdings!$A$2:$A$21=D8)*(Holdings!$M$2:$M$21="Holding"),Holdings!$F$2:$F$21,Holdings!$B$2:$B$21)=0,F8*H8*100,SUMPRODUCT((Holdings!$A$2:$A$21=D8)*(Holdings!$M$2:$M$21="Holding"),Holdings!$F$2:$F$21,Holdings!$B$2:$B$21))))*(365/N8),"")) -> 0.071487759
A9: 8 | B9: 45446 | C9: 45492 | D9: KO | E9: Cash-Secured Put | F9: 60 | G9: 45492 | H9: 2 | I9: 0.38 | J9: =IF(H9="","",H9*I9*100) -> 76 | K9: Expired Worthless | L9: 0 | M9: =IF(K9="Open","",IF(K9="Bought to Close",J9-L9*H9*100,J9)) -> 76 | N9: =IF(OR(C9="",B9=""),"",C9-B9) -> 46 | O9: =IF(OR(K9="Open",N9="",N9=0),"",IFERROR((M9/IF(E9="Cash-Secured Put",F9*H9*100,IF(SUMPRODUCT((Holdings!$A$2:$A$21=D9)*(Holdings!$M$2:$M$21="Holding"),Holdings!$F$2:$F$21,Holdings!$B$2:$B$21)=0,F9*H9*100,SUMPRODUCT((Holdings!$A$2:$A$21=D9)*(Holdings!$M$2:$M$21="Holding"),Holdings!$F$2:$F$21,Holdings!$B$2:$B$21))))*(365/N9),"")) -> 0.050253623
A10: 9 | B10: 45313 | C10: 45366 | D10: MSFT | E10: Cash-Secured Put | F10: 380 | G10: 45366 | H10: 1 | I10: 4.5 | J10: =IF(H10="","",H10*I10*100) -> 450 | K10: Expired Worthless | L10: 0 | M10: =IF(K10="Open","",IF(K10="Bought to Close",J10-L10*H10*100,J10)) -> 450 | N10: =IF(OR(C10="",B10=""),"",C10-B10) -> 53 | O10: =IF(OR(K10="Open",N10="",N10=0),"",IFERROR((M10/IF(E10="Cash-Secured Put",F10*H10*100,IF(SUMPRODUCT((Holdings!$A$2:$A$21=D10)*(Holdings!$M$2:$M$21="Holding"),Holdings!$F$2:$F$21,Holdings!$B$2:$B$21)=0,F10*H10*100,SUMPRODUCT((Holdings!$A$2:$A$21=D10)*(Holdings!$M$2:$M$21="Holding"),Holdings!$F$2:$F$21,Holdings!$B$2:$B$21))))*(365/N10),"")) -> 0.081554121
A11: 10 | B11: 45383 | C11: 45429 | D11: MSFT | E11: Cash-Secured Put | F11: 405 | G11: 45429 | H11: 1 | I11: 3.2 | J11: =IF(H11="","",H11*I11*100) -> 320 | K11: Assigned | L11: 0 | M11: =IF(K11="Open","",IF(K11="Bought to Close",J11-L11*H11*100,J11)) -> 320 | N11: =IF(OR(C11="",B11=""),"",C11-B11) -> 46 | O11: =IF(OR(K11="Open",N11="",N11=0),"",IFERROR((M11/IF(E11="Cash-Secured Put",F11*H11*100,IF(SUMPRODUCT((Holdings!$A$2:$A$21=D11)*(Holdings!$M$2:$M$21="Holding"),Holdings!$F$2:$F$21,Holdings!$B$2:$B$21)=0,F11*H11*100,SUMPRODUCT((Holdings!$A$2:$A$21=D11)*(Holdings!$M$2:$M$21="Holding"),Holdings!$F$2:$F$21,Holdings!$B$2:$B$21))))*(365/N11),"")) -> 0.062694579
A12: 11 | B12: 45432 | C12: 45464 | D12: MSFT | E12: Covered Call | F12: 420 | G12: 45464 | H12: 1 | I12: 2.05 | J12: =IF(H12="","",H12*I12*100) -> 205 | K12: Expired Worthless | L12: 0 | M12: =IF(K12="Open","",IF(K12="Bought to Close",J12-L12*H12*100,J12)) -> 205 | N12: =IF(OR(C12="",B12=""),"",C12-B12) -> 32 | O12: =IF(OR(K12="Open",N12="",N12=0),"",IFERROR((M12/IF(E12="Cash-Secured Put",F12*H12*100,IF(SUMPRODUCT((Holdings!$A$2:$A$21=D12)*(Holdings!$M$2:$M$21="Holding"),Holdings!$F$2:$F$21,Holdings!$B$2:$B$21)=0,F12*H12*100,SUMPRODUCT((Holdings!$A$2:$A$21=D12)*(Holdings!$M$2:$M$21="Holding"),Holdings!$F$2:$F$21,Holdings!$B$2:$B$21))))*(365/N12),"")) -> 0.058195153
A13: 12 | B13: 45467 | C13: 45492 | D13: MSFT | E13: Covered Call | F13: 425 | G13: 45492 | H13: 1 | I13: 1.65 | J13: =IF(H13="","",H13*I13*100) -> 165 | K13: Bought to Close | L13: 0.55 | M13: =IF(K13="Open","",IF(K13="Bought to Close",J13-L13*H13*100,J13)) -> 110 | N13: =IF(OR(C13="",B13=""),"",C13-B13) -> 25 | O13: =IF(OR(K13="Open",N13="",N13=0),"",IFERROR((M13/IF(E13="Cash-Secured Put",F13*H13*100,IF(SUMPRODUCT((Holdings!$A$2:$A$21=D13)*(Holdings!$M$2:$M$21="Holding"),Holdings!$F$2:$F$21,Holdings!$B$2:$B$21)=0,F13*H13*100,SUMPRODUCT((Holdings!$A$2:$A$21=D13)*(Holdings!$M$2:$M$21="Holding"),Holdings!$F$2:$F$21,Holdings!$B$2:$B$21))))*(365/N13),"")) -> 0.039970134 | P13: Rolled idea abandoned
A14: 13 | B14: 45495 | D14: MSFT | E14: Covered Call | F14: 430 | G14: 45520 | H14: 1 | I14: 1.3 | J14: =IF(H14="","",H14*I14*100) -> 130 | K14: Open | M14: =IF(K14="Open","",IF(K14="Bought to Close",J14-L14*H14*100,J14)) | N14: =IF(OR(C14="",B14=""),"",C14-B14) | O14: =IF(OR(K14="Open",N14="",N14=0),"",IFERROR((M14/IF(E14="Cash-Secured Put",F14*H14*100,IF(SUMPRODUCT((Holdings!$A$2:$A$21=D14)*(Holdings!$M$2:$M$21="Holding"),Holdings!$F$2:$F$21,Holdings!$B$2:$B$21)=0,F14*H14*100,SUMPRODUCT((Holdings!$A$2:$A$21=D14)*(Holdings!$M$2:$M$21="Holding"),Holdings!$F$2:$F$21,Holdings!$B$2:$B$21))))*(365/N14),"")) | P14: Still open in sample
A15: 14 | B15: 45334 | C15: 45366 | D15: T | E15: Cash-Secured Put | F15: 17.5 | G15: 45366 | H15: 4 | I15: 0.22 | J15: =IF(H15="","",H15*I15*100) -> 88 | K15: Expired Worthless | L15: 0 | M15: =IF(K15="Open","",IF(K15="Bought to Close",J15-L15*H15*100,J15)) -> 88 | N15: =IF(OR(C15="",B15=""),"",C15-B15) -> 32 | O15: =IF(OR(K15="Open",N15="",N15=0),"",IFERROR((M15/IF(E15="Cash-Secured Put",F15*H15*100,IF(SUMPRODUCT((Holdings!$A$2:$A$21=D15)*(Holdings!$M$2:$M$21="Holding"),Holdings!$F$2:$F$21,Holdings!$B$2:$B$21)=0,F15*H15*100,SUMPRODUCT((Holdings!$A$2:$A$21=D15)*(Holdings!$M$2:$M$21="Holding"),Holdings!$F$2:$F$21,Holdings!$B$2:$B$21))))*(365/N15),"")) -> 0.14339286
A16: 15 | B16: 45390 | C16: 45429 | D16: T | E16: Cash-Secured Put | F16: 18 | G16: 45429 | H16: 4 | I16: 0.18 | J16: =IF(H16="","",H16*I16*100) -> 72 | K16: Expired Worthless | L16: 0 | M16: =IF(K16="Open","",IF(K16="Bought to Close",J16-L16*H16*100,J16)) -> 72 | N16: =IF(OR(C16="",B16=""),"",C16-B16) -> 39 | O16: =IF(OR(K16="Open",N16="",N16=0),"",IFERROR((M16/IF(E16="Cash-Secured Put",F16*H16*100,IF(SUMPRODUCT((Holdings!$A$2:$A$21=D16)*(Holdings!$M$2:$M$21="Holding"),Holdings!$F$2:$F$21,Holdings!$B$2:$B$21)=0,F16*H16*100,SUMPRODUCT((Holdings!$A$2:$A$21=D16)*(Holdings!$M$2:$M$21="Holding"),Holdings!$F$2:$F$21,Holdings!$B$2:$B$21))))*(365/N16),"")) -> 0.093589744
A17: 16 | B17: 45453 | C17: 45492 | D17: T | E17: Cash-Secured Put | F17: 18.5 | G17: 45492 | H17: 4 | I17: 0.15 | J17: =IF(H17="","",H17*I17*100) -> 60 | K17: Assigned | L17: 0 | M17: =IF(K17="Open","",IF(K17="Bought to Close",J17-L17*H17*100,J17)) -> 60 | N17: =IF(OR(C17="",B17=""),"",C17-B17) -> 39 | O17: =IF(OR(K17="Open",N17="",N17=0),"",IFERROR((M17/IF(E17="Cash-Secured Put",F17*H17*100,IF(SUMPRODUCT((Holdings!$A$2:$A$21=D17)*(Holdings!$M$2:$M$21="Holding"),Holdings!$F$2:$F$21,Holdings!$B$2:$B$21)=0,F17*H17*100,SUMPRODUCT((Holdings!$A$2:$A$21=D17)*(Holdings!$M$2:$M$21="Holding"),Holdings!$F$2:$F$21,Holdings!$B$2:$B$21))))*(365/N17),"")) -> 0.075883576
A18: 17 | B18: 45495 | C18: 45520 | D18: T | E18: Covered Call | F18: 19 | G18: 45520 | H18: 4 | I18: 0.09 | J18: =IF(H18="","",H18*I18*100) -> 36 | K18: Called Away | L18: 0 | M18: =IF(K18="Open","",IF(K18="Bought to Close",J18-L18*H18*100,J18)) -> 36 | N18: =IF(OR(C18="",B18=""),"",C18-B18) -> 25 | O18: =IF(OR(K18="Open",N18="",N18=0),"",IFERROR((M18/IF(E18="Cash-Secured Put",F18*H18*100,IF(SUMPRODUCT((Holdings!$A$2:$A$21=D18)*(Holdings!$M$2:$M$21="Holding"),Holdings!$F$2:$F$21,Holdings!$B$2:$B$21)=0,F18*H18*100,SUMPRODUCT((Holdings!$A$2:$A$21=D18)*(Holdings!$M$2:$M$21="Holding"),Holdings!$F$2:$F$21,Holdings!$B$2:$B$21))))*(365/N18),"")) -> 0.069157895 | P18: Called at 19
A19: 18 | B19: 45524 | D19: KO | E19: Cash-Secured Put | F19: 61 | G19: 45555 | H19: 2 | I19: 0.41 | J19: =IF(H19="","",H19*I19*100) -> 82 | K19: Open | M19: =IF(K19="Open","",IF(K19="Bought to Close",J19-L19*H19*100,J19)) | N19: =IF(OR(C19="",B19=""),"",C19-B19) | O19: =IF(OR(K19="Open",N19="",N19=0),"",IFERROR((M19/IF(E19="Cash-Secured Put",F19*H19*100,IF(SUMPRODUCT((Holdings!$A$2:$A$21=D19)*(Holdings!$M$2:$M$21="Holding"),Holdings!$F$2:$F$21,Holdings!$B$2:$B$21)=0,F19*H19*100,SUMPRODUCT((Holdings!$A$2:$A$21=D19)*(Holdings!$M$2:$M$21="Holding"),Holdings!$F$2:$F$21,Holdings!$B$2:$B$21))))*(365/N19),"")) | P19: New CSP open
J20: =IF(H20="","",H20*I20*100) | O20: =IF(OR(K20="Open",N20="",N20=0),"",IFERROR((M20/IF(E20="Cash-Secured Put",F20*H20*100,IF(SUMPRODUCT((Holdings!$A$2:$A$21=D20)*(Holdings!$M$2:$M$21="Holding"),Holdings!$F$2:$F$21,Holdings!$B$2:$B$21)=0,F20*H20*100,SUMPRODUCT((Holdings!$A$2:$A$21=D20)*(Holdings!$M$2:$M$21="Holding"),Holdings!$F$2:$F$21,Holdings!$B$2:$B$21))))*(365/N20),""))
J21: =IF(H21="","",H21*I21*100) | O21: =IF(OR(K21="Open",N21="",N21=0),"",IFERROR((M21/IF(E21="Cash-Secured Put",F21*H21*100,IF(SUMPRODUCT((Holdings!$A$2:$A$21=D21)*(Holdings!$M$2:$M$21="Holding"),Holdings!$F$2:$F$21,Holdings!$B$2:$B$21)=0,F21*H21*100,SUMPRODUCT((Holdings!$A$2:$A$21=D21)*(Holdings!$M$2:$M$21="Holding"),Holdings!$F$2:$F$21,Holdings!$B$2:$B$21))))*(365/N21),""))
A22: Report as-of date | B22: 45535 | J22: =IF(H22="","",H22*I22*100) | O22: =IF(OR(K22="Open",N22="",N22=0),"",IFERROR((M22/IF(E22="Cash-Secured Put",F22*H22*100,IF(SUMPRODUCT((Holdings!$A$2:$A$21=D22)*(Holdings!$M$2:$M$21="Holding"),Holdings!$F$2:$F$21,Holdings!$B$2:$B$21)=0,F22*H22*100,SUMPRODUCT((Holdings!$A$2:$A$21=D22)*(Holdings!$M$2:$M$21="Holding"),Holdings!$F$2:$F$21,Holdings!$B$2:$B$21))))*(365/N22),""))
J23: =IF(H23="","",H23*I23*100) | O23: =IF(OR(K23="Open",N23="",N23=0),"",IFERROR((M23/IF(E23="Cash-Secured Put",F23*H23*100,IF(SUMPRODUCT((Holdings!$A$2:$A$21=D23)*(Holdings!$M$2:$M$21="Holding"),Holdings!$F$2:$F$21,Holdings!$B$2:$B$21)=0,F23*H23*100,SUMPRODUCT((Holdings!$A$2:$A$21=D23)*(Holdings!$M$2:$M$21="Holding"),Holdings!$F$2:$F$21,Holdings!$B$2:$B$21))))*(365/N23),""))
J24: =IF(H24="","",H24*I24*100) | O24: =IF(OR(K24="Open",N24="",N24=0),"",IFERROR((M24/IF(E24="Cash-Secured Put",F24*H24*100,IF(SUMPRODUCT((Holdings!$A$2:$A$21=D24)*(Holdings!$M$2:$M$21="Holding"),Holdings!$F$2:$F$21,Holdings!$B$2:$B$21)=0,F24*H24*100,SUMPRODUCT((Holdings!$A$2:$A$21=D24)*(Holdings!$M$2:$M$21="Holding"),Holdings!$F$2:$F$21,Holdings!$B$2:$B$21))))*(365/N24),""))
J25: =IF(H25="","",H25*I25*100) | O25: =IF(OR(K25="Open",N25="",N25=0),"",IFERROR((M25/IF(E25="Cash-Secured Put",F25*H25*100,IF(SUMPRODUCT((Holdings!$A$2:$A$21=D25)*(Holdings!$M$2:$M$21="Holding"),Holdings!$F$2:$F$21,Holdings!$B$2:$B$21)=0,F25*H25*100,SUMPRODUCT((Holdings!$A$2:$A$21=D25)*(Holdings!$M$2:$M$21="Holding"),Holdings!$F$2:$F$21,Holdings!$B$2:$B$21))))*(365/N25),""))
J26: =IF(H26="","",H26*I26*100) | O26: =IF(OR(K26="Open",N26="",N26=0),"",IFERROR((M26/IF(E26="Cash-Secured Put",F26*H26*100,IF(SUMPRODUCT((Holdings!$A$2:$A$21=D26)*(Holdings!$M$2:$M$21="Holding"),Holdings!$F$2:$F$21,Holdings!$B$2:$B$21)=0,F26*H26*100,SUMPRODUCT((Holdings!$A$2:$A$21=D26)*(Holdings!$M$2:$M$21="Holding"),Holdings!$F$2:$F$21,Holdings!$B$2:$B$21))))*(365/N26),""))
J27: =IF(H27="","",H27*I27*100) | O27: =IF(OR(K27="Open",N27="",N27=0),"",IFERROR((M27/IF(E27="Cash-Secured Put",F27*H27*100,IF(SUMPRODUCT((Holdings!$A$2:$A$21=D27)*(Holdings!$M$2:$M$21="Holding"),Holdings!$F$2:$F$21,Holdings!$B$2:$B$21)=0,F27*H27*100,SUMPRODUCT((Holdings!$A$2:$A$21=D27)*(Holdings!$M$2:$M$21="Holding"),Holdings!$F$2:$F$21,Holdings!$B$2:$B$21))))*(365/N27),""))
J28: =IF(H28="","",H28*I28*100) | O28: =IF(OR(K28="Open",N28="",N28=0),"",IFERROR((M28/IF(E28="Cash-Secured Put",F28*H28*100,IF(SUMPRODUCT((Holdings!$A$2:$A$21=D28)*(Holdings!$M$2:$M$21="Holding"),Holdings!$F$2:$F$21,Holdings!$B$2:$B$21)=0,F28*H28*100,SUMPRODUCT((Holdings!$A$2:$A$21=D28)*(Holdings!$M$2:$M$21="Holding"),Holdings!$F$2:$F$21,Holdings!$B$2:$B$21))))*(365/N28),""))
J29: =IF(H29="","",H29*I29*100) | O29: =IF(OR(K29="Open",N29="",N29=0),"",IFERROR((M29/IF(E29="Cash-Secured Put",F29*H29*100,IF(SUMPRODUCT((Holdings!$A$2:$A$21=D29)*(Holdings!$M$2:$M$21="Holding"),Holdings!$F$2:$F$21,Holdings!$B$2:$B$21)=0,F29*H29*100,SUMPRODUCT((Holdings!$A$2:$A$21=D29)*(Holdings!$M$2:$M$21="Holding"),Holdings!$F$2:$F$21,Holdings!$B$2:$B$21))))*(365/N29),""))
J30: =IF(H30="","",H30*I30*100) | O30: =IF(OR(K30="Open",N30="",N30=0),"",IFERROR((M30/IF(E30="Cash-Secured Put",F30*H30*100,IF(SUMPRODUCT((Holdings!$A$2:$A$21=D30)*(Holdings!$M$2:$M$21="Holding"),Holdings!$F$2:$F$21,Holdings!$B$2:$B$21)=0,F30*H30*100,SUMPRODUCT((Holdings!$A$2:$A$21=D30)*(Holdings!$M$2:$M$21="Holding"),Holdings!$F$2:$F$21,Holdings!$B$2:$B$21))))*(365/N30),""))
J31: =IF(H31="","",H31*I31*100) | O31: =IF(OR(K31="Open",N31="",N31=0),"",IFERROR((M31/IF(E31="Cash-Secured Put",F31*H31*100,IF(SUMPRODUCT((Holdings!$A$2:$A$21=D31)*(Holdings!$M$2:$M$21="Holding"),Holdings!$F$2:$F$21,Holdings!$B$2:$B$21)=0,F31*H31*100,SUMPRODUCT((Holdings!$A$2:$A$21=D31)*(Holdings!$M$2:$M$21="Holding"),Holdings!$F$2:$F$21,Holdings!$B$2:$B$21))))*(365/N31),""))
J32: =IF(H32="","",H32*I32*100) | O32: =IF(OR(K32="Open",N32="",N32=0),"",IFERROR((M32/IF(E32="Cash-Secured Put",F32*H32*100,IF(SUMPRODUCT((Holdings!$A$2:$A$21=D32)*(Holdings!$M$2:$M$21="Holding"),Holdings!$F$2:$F$21,Holdings!$B$2:$B$21)=0,F32*H32*100,SUMPRODUCT((Holdings!$A$2:$A$21=D32)*(Holdings!$M$2:$M$21="Holding"),Holdings!$F$2:$F$21,Holdings!$B$2:$B$21))))*(365/N32),""))
J33: =IF(H33="","",H33*I33*100) | O33: =IF(OR(K33="Open",N33="",N33=0),"",IFERROR((M33/IF(E33="Cash-Secured Put",F33*H33*100,IF(SUMPRODUCT((Holdings!$A$2:$A$21=D33)*(Holdings!$M$2:$M$21="Holding"),Holdings!$F$2:$F$21,Holdings!$B$2:$B$21)=0,F33*H33*100,SUMPRODUCT((Holdings!$A$2:$A$21=D33)*(Holdings!$M$2:$M$21="Holding"),Holdings!$F$2:$F$21,Holdings!$B$2:$B$21))))*(365/N33),""))
J34: =IF(H34="","",H34*I34*100) | O34: =IF(OR(K34="Open",N34="",N34=0),"",IFERROR((M34/IF(E34="Cash-Secured Put",F34*H34*100,IF(SUMPRODUCT((Holdings!$A$2:$A$21=D34)*(Holdings!$M$2:$M$21="Holding"),Holdings!$F$2:$F$21,Holdings!$B$2:$B$21)=0,F34*H34*100,SUMPRODUCT((Holdings!$A$2:$A$21=D34)*(Holdings!$M$2:$M$21="Holding"),Holdings!$F$2:$F$21,Holdings!$B$2:$B$21))))*(365/N34),""))
... J41: =IF(H41="","",H41*I41*100) | O41: =IF(OR(K41="Open",N41="",N41=0),"",IFERROR((M41/IF(E41="Cash-Secured Put",F41*H41*100,IF(SUMPRODUCT((Holdings!$A$2:$A$21=D41)*(Holdings!$M$2:$M$21="Holding"),Holdings!$F$2:$F$21,Holdings!$B$2:$B$21)=0,F41*H41*100,SUMPRODUCT((Holdings!$A$2:$A$21=D41)*(Holdings!$M$2:$M$21="Holding"),Holdings!$F$2:$F$21,Holdings!$B$2:$B$21))))*(365/N41),""))

Sheet Holdings
A1: Ticker | B1: Shares | C1: Assignment date | D1: Assignment strike | E1: Put premium (total $) | F1: Adj. cost/share | G1: Current price | H1: Unrealized P/share | I1: Unrealized P&L ($) | J1: CC premium (sum) | K1: Total income | L1: Lot end (CC window) | M1: Status
A2: AAPL | B2: 100 | C2: 45464 | D2: 178 | E2: 185 | F2: =IF(OR(B2="",B2=0),"",D2-E2/B2) -> 176.15 | G2: 212.5 | H2: =IF(B2=0,"",G2-F2) -> 36.35 | I2: =IF(B2=0,"",H2*B2) -> 3635 | J2: =SUMIFS('Trade Log'!$J:$J,'Trade Log'!$D:$D,A2,'Trade Log'!$E:$E,"Covered Call",'Trade Log'!$B:$B,">="&C2,'Trade Log'!$B:$B,"<="&IF(L2="",'Trade Log'!$B$22,L2)) -> 255 | K2: =I2+J2 -> 3890 | M2: Holding
A3: MSFT | B3: 100 | C3: 45429 | D3: 405 | E3: 320 | F3: =IF(OR(B3="",B3=0),"",D3-E3/B3) -> 401.8 | G3: 418 | H3: =IF(B3=0,"",G3-F3) -> 16.2 | I3: =IF(B3=0,"",H3*B3) -> 1620 | J3: =SUMIFS('Trade Log'!$J:$J,'Trade Log'!$D:$D,A3,'Trade Log'!$E:$E,"Covered Call",'Trade Log'!$B:$B,">="&C3,'Trade Log'!$B:$B,"<="&IF(L3="",'Trade Log'!$B$22,L3)) -> 500 | K3: =I3+J3 -> 2120 | M3: Holding
A4: KO | B4: 200 | C4: 45247 | D4: 55 | E4: 180 | F4: =IF(OR(B4="",B4=0),"",D4-E4/B4) -> 54.1 | G4: 54.25 | H4: =IF(B4=0,"",G4-F4) -> 0.15 | I4: =IF(B4=0,"",H4*B4) -> 30 | J4: =SUMIFS('Trade Log'!$J:$J,'Trade Log'!$D:$D,A4,'Trade Log'!$E:$E,"Covered Call",'Trade Log'!$B:$B,">="&C4,'Trade Log'!$B:$B,"<="&IF(L4="",'Trade Log'!$B$22,L4)) -> 0 | K4: =I4+J4 -> 30 | L4: 45429 | M4: Called Away
A5: T | B5: 400 | C5: 45492 | D5: 18.5 | E5: 60 | F5: =IF(OR(B5="",B5=0),"",D5-E5/B5) -> 18.35 | G5: 19.2 | H5: =IF(B5=0,"",G5-F5) -> 0.85 | I5: =IF(B5=0,"",H5*B5) -> 340 | J5: =SUMIFS('Trade Log'!$J:$J,'Trade Log'!$D:$D,A5,'Trade Log'!$E:$E,"Covered Call",'Trade Log'!$B:$B,">="&C5,'Trade Log'!$B:$B,"<="&IF(L5="",'Trade Log'!$B$22,L5)) -> 36 | K5: =I5+J5 -> 376 | L5: 45520 | M5: Sold
F6: =IF(OR(B6="",B6=0),"",D6-E6/B6) | H6: =IF(B6=0,"",G6-F6) | I6: =IF(B6=0,"",H6*B6)
F7: =IF(OR(B7="",B7=0),"",D7-E7/B7) | H7: =IF(B7=0,"",G7-F7) | I7: =IF(B7=0,"",H7*B7)
F8: =IF(OR(B8="",B8=0),"",D8-E8/B8) | H8: =IF(B8=0,"",G8-F8) | I8: =IF(B8=0,"",H8*B8)
F9: =IF(OR(B9="",B9=0),"",D9-E9/B9) | H9: =IF(B9=0,"",G9-F9) | I9: =IF(B9=0,"",H9*B9)
F10: =IF(OR(B10="",B10=0),"",D10-E10/B10) | H10: =IF(B10=0,"",G10-F10) | I10: =IF(B10=0,"",H10*B10)
F11: =IF(OR(B11="",B11=0),"",D11-E11/B11) | H11: =IF(B11=0,"",G11-F11) | I11: =IF(B11=0,"",H11*B11)
F12: =IF(OR(B12="",B12=0),"",D12-E12/B12) | H12: =IF(B12=0,"",G12-F12) | I12: =IF(B12=0,"",H12*B12)
F13: =IF(OR(B13="",B13=0),"",D13-E13/B13) | H13: =IF(B13=0,"",G13-F13) | I13: =IF(B13=0,"",H13*B13)
F14: =IF(OR(B14="",B14=0),"",D14-E14/B14) | H14: =IF(B14=0,"",G14-F14) | I14: =IF(B14=0,"",H14*B14)
F15: =IF(OR(B15="",B15=0),"",D15-E15/B15) | H15: =IF(B15=0,"",G15-F15) | I15: =IF(B15=0,"",H15*B15)
F16: =IF(OR(B16="",B16=0),"",D16-E16/B16) | H16: =IF(B16=0,"",G16-F16) | I16: =IF(B16=0,"",H16*B16)
F17: =IF(OR(B17="",B17=0),"",D17-E17/B17) | H17: =IF(B17=0,"",G17-F17) | I17: =IF(B17=0,"",H17*B17)
... F21: =IF(OR(B21="",B21=0),"",D21-E21/B21) | H21: =IF(B21=0,"",G21-F21) | I21: =IF(B21=0,"",H21*B21)

Sheet Performance Summary
A1: By ticker
A2: Ticker | B2: Total trades | C2: Total premium | D2: Close costs (BTC) | E2: Net premium | F2: Assignments | G2: Called away | H2: Win rate | I2: Avg days held | J2: Avg annualized
A3: AAPL | B3: =COUNTIF('Trade Log'!$D$2:$D$41,A3) -> 5 | C3: =SUMIFS('Trade Log'!$J:$J,'Trade Log'!$D:$D,A3) -> 775 | D3: =SUMPRODUCT(('Trade Log'!$D$2:$D$41=A3)*('Trade Log'!$K$2:$K$41="Bought to Close"),'Trade Log'!$L$2:$L$41,'Trade Log'!$H$2:$H$41)*100 -> 0 | E3: =C3-D3 -> 775 | F3: =COUNTIFS('Trade Log'!$D$2:$D$41,A3,'Trade Log'!$K$2:$K$41,"Assigned") -> 1 | G3: =COUNTIFS('Trade Log'!$D$2:$D$41,A3,'Trade Log'!$K$2:$K$41,"Called Away") -> 1 | H3: =IF(COUNTIFS('Trade Log'!$D$2:$D$41,A3,'Trade Log'!$K$2:$K$41,"<>Open")=0,"",COUNTIFS('Trade Log'!$D$2:$D$41,A3,'Trade Log'!$K$2:$K$41,"<>Open",'Trade Log'!$M$2:$M$41,">0")/COUNTIFS('Trade Log'!$D$2:$D$41,A3,'Trade Log'!$K$2:$K$41,"<>Open")) -> 1 | I3: =AVERAGEIFS('Trade Log'!$N:$N,'Trade Log'!$D:$D,A3,'Trade Log'!$N:$N,"<>") -> 36.2 | J3: =AVERAGEIFS('Trade Log'!$O:$O,'Trade Log'!$D:$D,A3,'Trade Log'!$O:$O,"<>") -> 0.090731175
A4: KO | B4: =COUNTIF('Trade Log'!$D$2:$D$41,A4) -> 4 | C4: =SUMIFS('Trade Log'!$J:$J,'Trade Log'!$D:$D,A4) -> 352 | D4: =SUMPRODUCT(('Trade Log'!$D$2:$D$41=A4)*('Trade Log'!$K$2:$K$41="Bought to Close"),'Trade Log'!$L$2:$L$41,'Trade Log'!$H$2:$H$41)*100 -> 24 | E4: =C4-D4 -> 328 | F4: =COUNTIFS('Trade Log'!$D$2:$D$41,A4,'Trade Log'!$K$2:$K$41,"Assigned") -> 0 | G4: =COUNTIFS('Trade Log'!$D$2:$D$41,A4,'Trade Log'!$K$2:$K$41,"Called Away") -> 0 | H4: =IF(COUNTIFS('Trade Log'!$D$2:$D$41,A4,'Trade Log'!$K$2:$K$41,"<>Open")=0,"",COUNTIFS('Trade Log'!$D$2:$D$41,A4,'Trade Log'!$K$2:$K$41,"<>Open",'Trade Log'!$M$2:$M$41,">0")/COUNTIFS('Trade Log'!$D$2:$D$41,A4,'Trade Log'!$K$2:$K$41,"<>Open")) -> 1 | I4: =AVERAGEIFS('Trade Log'!$N:$N,'Trade Log'!$D:$D,A4,'Trade Log'!$N:$N,"<>") -> 44.666667 | J4: =AVERAGEIFS('Trade Log'!$O:$O,'Trade Log'!$D:$D,A4,'Trade Log'!$O:$O,"<>") -> 0.056679097
A5: MSFT | B5: =COUNTIF('Trade Log'!$D$2:$D$41,A5) -> 5 | C5: =SUMIFS('Trade Log'!$J:$J,'Trade Log'!$D:$D,A5) -> 1270 | D5: =SUMPRODUCT(('Trade Log'!$D$2:$D$41=A5)*('Trade Log'!$K$2:$K$41="Bought to Close"),'Trade Log'!$L$2:$L$41,'Trade Log'!$H$2:$H$41)*100 -> 55 | E5: =C5-D5 -> 1215 | F5: =COUNTIFS('Trade Log'!$D$2:$D$41,A5,'Trade Log'!$K$2:$K$41,"Assigned") -> 1 | G5: =COUNTIFS('Trade Log'!$D$2:$D$41,A5,'Trade Log'!$K$2:$K$41,"Called Away") -> 0 | H5: =IF(COUNTIFS('Trade Log'!$D$2:$D$41,A5,'Trade Log'!$K$2:$K$41,"<>Open")=0,"",COUNTIFS('Trade Log'!$D$2:$D$41,A5,'Trade Log'!$K$2:$K$41,"<>Open",'Trade Log'!$M$2:$M$41,">0")/COUNTIFS('Trade Log'!$D$2:$D$41,A5,'Trade Log'!$K$2:$K$41,"<>Open")) -> 1 | I5: =AVERAGEIFS('Trade Log'!$N:$N,'Trade Log'!$D:$D,A5,'Trade Log'!$N:$N,"<>") -> 39 | J5: =AVERAGEIFS('Trade Log'!$O:$O,'Trade Log'!$D:$D,A5,'Trade Log'!$O:$O,"<>") -> 0.060603497
A6: T | B6: =COUNTIF('Trade Log'!$D$2:$D$41,A6) -> 4 | C6: =SUMIFS('Trade Log'!$J:$J,'Trade Log'!$D:$D,A6) -> 256 | D6: =SUMPRODUCT(('Trade Log'!$D$2:$D$41=A6)*('Trade Log'!$K$2:$K$41="Bought to Close"),'Trade Log'!$L$2:$L$41,'Trade Log'!$H$2:$H$41)*100 -> 0 | E6: =C6-D6 -> 256 | F6: =COUNTIFS('Trade Log'!$D$2:$D$41,A6,'Trade Log'!$K$2:$K$41,"Assigned") -> 1 | G6: =COUNTIFS('Trade Log'!$D$2:$D$41,A6,'Trade Log'!$K$2:$K$41,"Called Away") -> 1 | H6: =IF(COUNTIFS('Trade Log'!$D$2:$D$41,A6,'Trade Log'!$K$2:$K$41,"<>Open")=0,"",COUNTIFS('Trade Log'!$D$2:$D$41,A6,'Trade Log'!$K$2:$K$41,"<>Open",'Trade Log'!$M$2:$M$41,">0")/COUNTIFS('Trade Log'!$D$2:$D$41,A6,'Trade Log'!$K$2:$K$41,"<>Open")) -> 1 | I6: =AVERAGEIFS('Trade Log'!$N:$N,'Trade Log'!$D:$D,A6,'Trade Log'!$N:$N,"<>") -> 33.75 | J6: =AVERAGEIFS('Trade Log'!$O:$O,'Trade Log'!$D:$D,A6,'Trade Log'!$O:$O,"<>") -> 0.095506018
A8: Add rows above if you track more tickers.
A10: Overall portfolio
A11: Total net premium (sum of ticker net) | B11: =SUM(E3:E6) -> 2574
A12: Total trades closed | B12: =COUNTIFS('Trade Log'!$K$2:$K$41,"<>Open") -> 38
A13: Overall win rate (closed) | B13: =IF(COUNTIFS('Trade Log'!$K$2:$K$41,"<>Open")=0,"",COUNTIFS('Trade Log'!$K$2:$K$41,"<>Open",'Trade Log'!$M$2:$M$41,">0")/COUNTIFS('Trade Log'!$K$2:$K$41,"<>Open")) -> 0.42105263
A14: Capital in stock (Holding basis $) | B14: =SUMPRODUCT((Holdings!$M$2:$M$21="Holding")*1,Holdings!$F$2:$F$21,Holdings!$B$2:$B$21) -> 57795
A15: Avg days held (all closed) | B15: =AVERAGEIFS('Trade Log'!$N$2:$N$41,'Trade Log'!$K$2:$K$41,"<>Open",'Trade Log'!$N$2:$N$41,"<>") -> 37.875
A16: Total unrealized P&L (Holding rows) | B16: =SUMIFS(Holdings!$I:$I,Holdings!$M:$M,"Holding") -> 5255

Sheet Wheel Tracker
A1: Cycle # | B1: Ticker | C1: CSP trade # | D1: CSP premium | E1: Assigned? | F1: Assignment strike | G1: CC trade #s | H1: CC total premium | I1: Called away? | J1: Call strike | K1: Shares | L1: Total cycle income | M1: Cycle days | N1: Annualized | O1: Status
A2: 1 | B2: AAPL | C2: 3 | D2: ='Trade Log'!J4 -> 185 | E2: Yes | F2: 178 | G2: 4,5 | H2: ='Trade Log'!J5+'Trade Log'!J6 -> 255 | I2: Yes | J2: 190 | K2: 100 | L2: =D2+H2+IF(AND(I2="Yes",F2<>"",K2<>""),(J2-F2)*K2,0) -> 1640 | M2: =IF('Trade Log'!C6="",'Trade Log'!$B$22-'Trade Log'!B4,'Trade Log'!C6-'Trade Log'!B4) -> 102 | N2: =IF(OR(M2="",M2=0),"",IF(E2="Yes",IF(F2*K2-D2<=0,"",(L2/(F2*K2-D2))*(365/M2)),IF('Trade Log'!F4*'Trade Log'!H4*100=0,"",(L2/('Trade Log'!F4*'Trade Log'!H4*100))*(365/M2)))) -> 0.3331608 | O2: =IF('Trade Log'!C6="","Active","Complete") -> Complete
A3: 2 | B3: KO | C3: 6 | D3: ='Trade Log'!J7 -> 90 | E3: No | H3: 0 | I3: No | L3: =D3+H3+IF(AND(I3="Yes",F3<>"",K3<>""),(J3-F3)*K3,0) -> 90 | M3: =IF('Trade Log'!C7="",'Trade Log'!$B$22-'Trade Log'!B7,'Trade Log'!C7-'Trade Log'!B7) -> 43 | N3: =IF(OR(M3="",M3=0),"",IF(E3="Yes",IF(F3*K3-D3<=0,"",(L3/(F3*K3-D3))*(365/M3)),IF('Trade Log'!F7*'Trade Log'!H7*100=0,"",(L3/('Trade Log'!F7*'Trade Log'!H7*100))*(365/M3)))) -> 0.065858059 | O3: =IF('Trade Log'!C7="","Active","Complete") -> Complete
A4: 3 | B4: MSFT | C4: 10 | D4: ='Trade Log'!J11 -> 320 | E4: Yes | F4: 405 | G4: 11,12,13 | H4: ='Trade Log'!J12+'Trade Log'!J13+'Trade Log'!J14 -> 500 | I4: No | J4: 430 | K4: 100 | L4: =D4+H4+IF(AND(I4="Yes",F4<>"",K4<>""),(J4-F4)*K4,0) -> 820 | M4: =IF('Trade Log'!C14="",'Trade Log'!$B$22-'Trade Log'!B11,'Trade Log'!C14-'Trade Log'!B11) -> 152 | N4: =IF(OR(M4="",M4=0),"",IF(E4="Yes",IF(F4*K4-D4<=0,"",(L4/(F4*K4-D4))*(365/M4)),IF('Trade Log'!F11*'Trade Log'!H11*100=0,"",(L4/('Trade Log'!F11*'Trade Log'!H11*100))*(365/M4)))) -> 0.049006445 | O4: =IF('Trade Log'!C14="","Active","Complete") -> Active
A5: 4 | B5: T | C5: 16 | D5: ='Trade Log'!J17 -> 60 | E5: Yes | F5: 18.5 | G5: 17 | H5: ='Trade Log'!J18 -> 36 | I5: Yes | J5: 19 | K5: 400 | L5: =D5+H5+IF(AND(I5="Yes",F5<>"",K5<>""),(J5-F5)*K5,0) -> 296 | M5: =IF('Trade Log'!C18="",'Trade Log'!$B$22-'Trade Log'!B17,'Trade Log'!C18-'Trade Log'!B17) -> 67 | N5: =IF(OR(M5="",M5=0),"",IF(E5="Yes",IF(F5*K5-D5<=0,"",(L5/(F5*K5-D5))*(365/M5)),IF('Trade Log'!F17*'Trade Log'!H17*100=0,"",(L5/('Trade Log'!F17*'Trade Log'!H17*100))*(365/M5)))) -> 0.21969173 | O5: =IF('Trade Log'!C18="","Active","Complete") -> Complete
A6: 5 | B6: KO | C6: 18 | D6: ='Trade Log'!J19 -> 82 | E6: No | F6: 61 | H6: 0 | I6: No | K6: 200 | L6: =D6+H6+IF(AND(I6="Yes",F6<>"",K6<>""),(J6-F6)*K6,0) -> 82 | M6: =IF('Trade Log'!C19="",'Trade Log'!$B$22-'Trade Log'!B19,'Trade Log'!C19-'Trade Log'!B19) -> 11 | N6: =IF(OR(M6="",M6=0),"",IF(E6="Yes",IF(F6*K6-D6<=0,"",(L6/(F6*K6-D6))*(365/M6)),IF('Trade Log'!F19*'Trade Log'!H19*100=0,"",(L6/('Trade Log'!F19*'Trade Log'!H19*100))*(365/M6)))) -> 0.22302534 | O6: =IF('Trade Log'!C19="","Active","Complete") -> Active
A10: CC trade #s in column G are hints; column H sums premiums from those Trade Log rows. Total cycle income uses a simplified stock leg on call-away: (call strike - assignment strike) x shares, not adjusted cost basis from Holdings.
A11: Annualized return when assigned uses capital approx. (assignment strike x shares) minus CSP premium (col D). Active cycle days use Trade Log B43 when the last trade in the cycle is still open.
