Workbook

Sheet Accounts
B2: Account Registry
B3: Account Name | C3: Institution | D3: Type | E3: Asset/Liability | F3: Opening Balance | G3: Opening Date | I3: Type | J3: Classification
B4: Chase Checking | C4: Chase | D4: Checking | E4: =VLOOKUP(D4,$I$4:$J$18,2,FALSE) | F4: 4200 | G4: 45292 | I4: Checking | J4: Asset
B5: Ally Savings | C5: Ally | D5: Savings | E5: =VLOOKUP(D5,$I$4:$J$18,2,FALSE) | F5: 12500 | G5: 45292 | I5: Savings | J5: Asset
B6: Fidelity Brokerage | C6: Fidelity | D6: Brokerage | E6: =VLOOKUP(D6,$I$4:$J$18,2,FALSE) | F6: 28000 | G6: 45292 | I6: Money Market | J6: Asset
B7: Vanguard 401k | C7: Vanguard | D7: 401k | E7: =VLOOKUP(D7,$I$4:$J$18,2,FALSE) | F7: 68000 | G7: 45292 | I7: Brokerage | J7: Asset
B8: Roth IRA | C8: Vanguard | D8: IRA | E8: =VLOOKUP(D8,$I$4:$J$18,2,FALSE) | F8: 22000 | G8: 45292 | I8: 401k | J8: Asset
B9: HSA Account | C9: Optum | D9: HSA | E9: =VLOOKUP(D9,$I$4:$J$18,2,FALSE) | F9: 4800 | G9: 45292 | I9: IRA | J9: Asset
B10: 529 College | C10: Vanguard | D10: 529 | E10: =VLOOKUP(D10,$I$4:$J$18,2,FALSE) | F10: 3200 | G10: 45292 | I10: HSA | J10: Asset
B11: Home Equity | C11: Zillow Est. | D11: Real Estate | E11: =VLOOKUP(D11,$I$4:$J$18,2,FALSE) | F11: 85000 | G11: 45292 | I11: 529 | J11: Asset
B12: Car Value | C12: KBB Est. | D12: Vehicle | E12: =VLOOKUP(D12,$I$4:$J$18,2,FALSE) | F12: 14000 | G12: 45292 | I12: Real Estate | J12: Asset
B13: Chase Visa | C13: Chase | D13: Credit Card | E13: =VLOOKUP(D13,$I$4:$J$18,2,FALSE) | F13: 2800 | G13: 45292 | I13: Vehicle | J13: Asset
B14: Student Loans | C14: Navient | D14: Student Loan | E14: =VLOOKUP(D14,$I$4:$J$18,2,FALSE) | F14: 24000 | G14: 45292 | I14: Credit Card | J14: Liability
B15: Mortgage | C15: Wells Fargo | D15: Mortgage | E15: =VLOOKUP(D15,$I$4:$J$18,2,FALSE) | F15: 195000 | G15: 45292 | I15: Student Loan | J15: Liability
... B17: Medical Debt | C17: Collection | D17: Other Debt | E17: =VLOOKUP(D17,$I$4:$J$18,2,FALSE) | F17: 1200 | G17: 45292 | I17: Auto Loan | J17: Liability
I18: Other Debt | J18: Liability

Sheet Monthly Balances
B2: Monthly Balances (2025)
B3: Account | C3: Jan | D3: Feb | E3: Mar | F3: Apr | G3: May | H3: Jun | I3: Jul | J3: Aug | K3: Sep | L3: Oct | M3: Nov | N3: Dec
B4: Chase Checking | C4: 4093 | D4: 4107 | E4: 4167 | F4: 4225 | G4: 4242 | H4: 4216 | I4: 4227 | J4: 4218 | K4: 4284 | L4: 4233 | M4: 4225 | N4: 4257
B5: Ally Savings | C5: 12815 | D5: 12987 | E5: 13179 | F5: 13342 | G5: 13256 | H5: 13380 | I5: 13516 | J5: 13585 | K5: 13683 | L5: 13623 | M5: 13762 | N5: 13682
B6: Fidelity Brokerage | C6: 30767 | D6: 31440 | E6: 32149 | F6: 32462 | G6: 32667 | H6: 33400 | I6: 33714 | J6: 34292 | K6: 34137 | L6: 34170 | M6: 34764 | N6: 35091
B7: Vanguard 401k | C7: 75581 | D7: 75603 | E7: 75858 | F7: 77589 | G7: 79276 | H7: 80366 | I7: 80229 | J7: 81884 | K7: 81625 | L7: 81388 | M7: 82735 | N7: 83010
B8: Roth IRA | C8: 22785 | D8: 23011 | E8: 22857 | F8: 22748 | G8: 23159 | H8: 23637 | I8: 23711 | J8: 24162 | K8: 24629 | L8: 24630 | M8: 24503 | N8: 24422
B9: HSA Account | C9: 5171 | D9: 5272 | E9: 5290 | F9: 5299 | G9: 5299 | H9: 5386 | I9: 5417 | J9: 5391 | K9: 5499 | L9: 5469 | M9: 5495 | N9: 5575
B10: 529 College | C10: 3412 | D10: 3391 | E10: 3407 | F10: 3423 | G10: 3421 | H10: 3446 | I10: 3487 | J10: 3552 | K10: 3623 | L10: 3611 | M10: 3652 | N10: 3624
B11: Home Equity | C11: 91535 | D11: 92448 | E11: 91592 | F11: 93074 | G11: 93388 | H11: 93122 | I11: 94668 | J11: 95063 | K11: 94949 | L11: 94120 | M11: 95625 | N11: 96930
B12: Car Value | C12: 13047 | D12: 13051 | E12: 12875 | F12: 12839 | G12: 12604 | H12: 12495 | I12: 12218 | J12: 12254 | K12: 12163 | L12: 12107 | M12: 12141 | N12: 11969
B13: Chase Visa | C13: 1955 | D13: 1902 | E13: 1850 | F13: 1801 | G13: 1745 | H13: 1696 | I13: 1654 | J13: 1598 | K13: 1528 | L13: 1487 | M13: 1428 | N13: 1367
B14: Student Loans | C14: 19602 | D14: 19133 | E14: 19070 | F14: 18791 | G14: 18785 | H14: 18337 | I14: 18181 | J14: 18183 | K14: 17964 | L14: 17716 | M14: 17678 | N14: 17410
B15: Mortgage | C15: 189836 | D15: 186588 | E15: 186726 | F15: 183820 | G15: 181748 | H15: 181988 | I15: 181485 | J15: 182102 | K15: 182997 | L15: 181386 | M15: 181416 | N15: 183121
... B17: Medical Debt | C17: 801 | D17: 781 | E17: 768 | F17: 743 | G17: 722 | H17: 706 | I17: 689 | J17: 665 | K17: 645 | L17: 624 | M17: 604 | N17: 589
B19: Total Assets | C19: =SUMPRODUCT((Accounts!$E$4:$E$17="Asset")*C$4:C$17) | D19: =SUMPRODUCT((Accounts!$E$4:$E$17="Asset")*D$4:D$17) | E19: =SUMPRODUCT((Accounts!$E$4:$E$17="Asset")*E$4:E$17) | F19: =SUMPRODUCT((Accounts!$E$4:$E$17="Asset")*F$4:F$17) | G19: =SUMPRODUCT((Accounts!$E$4:$E$17="Asset")*G$4:G$17) | H19: =SUMPRODUCT((Accounts!$E$4:$E$17="Asset")*H$4:H$17) | I19: =SUMPRODUCT((Accounts!$E$4:$E$17="Asset")*I$4:I$17) | J19: =SUMPRODUCT((Accounts!$E$4:$E$17="Asset")*J$4:J$17) | ... N19: =SUMPRODUCT((Accounts!$E$4:$E$17="Asset")*N$4:N$17)
B20: Total Liabilities | C20: =SUMPRODUCT((Accounts!$E$4:$E$17="Liability")*C$4:C$17) | D20: =SUMPRODUCT((Accounts!$E$4:$E$17="Liability")*D$4:D$17) | E20: =SUMPRODUCT((Accounts!$E$4:$E$17="Liability")*E$4:E$17) | F20: =SUMPRODUCT((Accounts!$E$4:$E$17="Liability")*F$4:F$17) | G20: =SUMPRODUCT((Accounts!$E$4:$E$17="Liability")*G$4:G$17) | H20: =SUMPRODUCT((Accounts!$E$4:$E$17="Liability")*H$4:H$17) | I20: =SUMPRODUCT((Accounts!$E$4:$E$17="Liability")*I$4:I$17) | J20: =SUMPRODUCT((Accounts!$E$4:$E$17="Liability")*J$4:J$17) | ... N20: =SUMPRODUCT((Accounts!$E$4:$E$17="Liability")*N$4:N$17)
B21: Net Worth | C21: =C19-C20 | D21: =D19-D20 | E21: =E19-E20 | F21: =F19-F20 | G21: =G19-G20 | H21: =H19-H20 | I21: =I19-I20 | J21: =J19-J20 | ... N21: =N19-N20
B22: MoM Change ($) | C22: =C21 | D22: =D21-C21 | E22: =E21-D21 | F22: =F21-E21 | G22: =G21-F21 | H22: =H21-G21 | I22: =I21-H21 | J22: =J21-I21 | K22: =K21-J21 | ... N22: =N21-M21
B23: MoM Change (%) | C23: 0 | D23: =IFERROR(D22/C21,0) | E23: =IFERROR(E22/D21,0) | F23: =IFERROR(F22/E21,0) | G23: =IFERROR(G22/F21,0) | H23: =IFERROR(H22/G21,0) | I23: =IFERROR(I22/H21,0) | J23: =IFERROR(J22/I21,0) | K23: =IFERROR(K22/J21,0) | ... N23: =IFERROR(N22/M21,0)

Sheet History
B2: Net Worth History
B3: Month/Year | C3: Total Assets | D3: Total Liabilities | E3: Net Worth | F3: MoM Change ($) | G3: MoM Change (%) | H3: 3-Mo Avg Change | I3: 6-Mo Avg Change | J3: 12-Mo Avg Change
B4: Jan 2024 | C4: 242909 | D4: 230238 | E4: =C4-D4 | F4: 0 | G4: 0 | H4: =IFERROR(AVERAGE(F$4:F4),0) | I4: =IFERROR(AVERAGE(F$4:F4),0) | J4: =IFERROR(AVERAGE(F$4:F4),0)
B5: Feb 2024 | C5: 243439 | D5: 228661 | E5: =C5-D5 | F5: =E5-E4 | G5: =IFERROR(F5/E4,0) | H5: =IFERROR(AVERAGE(F$4:F5),0) | I5: =IFERROR(AVERAGE(F$4:F5),0) | J5: =IFERROR(AVERAGE(F$4:F5),0)
B6: Mar 2024 | C6: 244138 | D6: 229761 | E6: =C6-D6 | F6: =E6-E5 | G6: =IFERROR(F6/E5,0) | H6: =AVERAGE(F4:F6) | I6: =IFERROR(AVERAGE(F$4:F6),0) | J6: =IFERROR(AVERAGE(F$4:F6),0)
B7: Apr 2024 | C7: 244439 | D7: 227618 | E7: =C7-D7 | F7: =E7-E6 | G7: =IFERROR(F7/E6,0) | H7: =AVERAGE(F5:F7) | I7: =IFERROR(AVERAGE(F$4:F7),0) | J7: =IFERROR(AVERAGE(F$4:F7),0)
B8: May 2024 | C8: 245978 | D8: 228299 | E8: =C8-D8 | F8: =E8-E7 | G8: =IFERROR(F8/E7,0) | H8: =AVERAGE(F6:F8) | I8: =IFERROR(AVERAGE(F$4:F8),0) | J8: =IFERROR(AVERAGE(F$4:F8),0)
B9: Jun 2024 | C9: 248183 | D9: 224743 | E9: =C9-D9 | F9: =E9-E8 | G9: =IFERROR(F9/E8,0) | H9: =AVERAGE(F7:F9) | I9: =AVERAGE(F4:F9) | J9: =IFERROR(AVERAGE(F$4:F9),0)
B10: Jul 2024 | C10: 248886 | D10: 224744 | E10: =C10-D10 | F10: =E10-E9 | G10: =IFERROR(F10/E9,0) | H10: =AVERAGE(F8:F10) | I10: =AVERAGE(F5:F10) | J10: =IFERROR(AVERAGE(F$4:F10),0)
B11: Aug 2024 | C11: 250418 | D11: 223606 | E11: =C11-D11 | F11: =E11-E10 | G11: =IFERROR(F11/E10,0) | H11: =AVERAGE(F9:F11) | I11: =AVERAGE(F6:F11) | J11: =IFERROR(AVERAGE(F$4:F11),0)
B12: Sep 2024 | C12: 252378 | D12: 223377 | E12: =C12-D12 | F12: =E12-E11 | G12: =IFERROR(F12/E11,0) | H12: =AVERAGE(F10:F12) | I12: =AVERAGE(F7:F12) | J12: =IFERROR(AVERAGE(F$4:F12),0)
B13: Oct 2024 | C13: 254475 | D13: 220254 | E13: =C13-D13 | F13: =E13-E12 | G13: =IFERROR(F13/E12,0) | H13: =AVERAGE(F11:F13) | I13: =AVERAGE(F8:F13) | J13: =IFERROR(AVERAGE(F$4:F13),0)
B14: Nov 2024 | C14: 256547 | D14: 219365 | E14: =C14-D14 | F14: =E14-E13 | G14: =IFERROR(F14/E13,0) | H14: =AVERAGE(F12:F14) | I14: =AVERAGE(F9:F14) | J14: =IFERROR(AVERAGE(F$4:F14),0)
B15: Dec 2024 | C15: 257938 | D15: 221154 | E15: =C15-D15 | F15: =E15-E14 | G15: =IFERROR(F15/E14,0) | H15: =AVERAGE(F13:F15) | I15: =AVERAGE(F10:F15) | J15: =AVERAGE(F4:F15)
B16: Jan 2025 | C16: 259206 | D16: 219294 | E16: =C16-D16 | F16: =E16-E15 | G16: =IFERROR(F16/E15,0) | H16: =AVERAGE(F14:F16) | I16: =AVERAGE(F11:F16) | J16: =AVERAGE(F5:F16)
B17: Feb 2025 | C17: 261310 | D17: 215438 | E17: =C17-D17 | F17: =E17-E16 | G17: =IFERROR(F17/E16,0) | H17: =AVERAGE(F15:F17) | I17: =AVERAGE(F12:F17) | J17: =AVERAGE(F6:F17)
B18: Mar 2025 | C18: 261374 | D18: 215309 | E18: =C18-D18 | F18: =E18-E17 | G18: =IFERROR(F18/E17,0) | H18: =AVERAGE(F16:F18) | I18: =AVERAGE(F13:F18) | J18: =AVERAGE(F7:F18)
B19: Apr 2025 | C19: 265001 | D19: 212043 | E19: =C19-D19 | F19: =E19-E18 | G19: =IFERROR(F19/E18,0) | H19: =AVERAGE(F17:F19) | I19: =AVERAGE(F14:F19) | J19: =AVERAGE(F8:F19)
B20: May 2025 | C20: 267312 | D20: 209719 | E20: =C20-D20 | F20: =E20-E19 | G20: =IFERROR(F20/E19,0) | H20: =AVERAGE(F18:F20) | I20: =AVERAGE(F15:F20) | J20: =AVERAGE(F9:F20)
B21: Jun 2025 | C21: 269448 | D21: 209368 | E21: =C21-D21 | F21: =E21-E20 | G21: =IFERROR(F21/E20,0) | H21: =AVERAGE(F19:F21) | I21: =AVERAGE(F16:F21) | J21: =AVERAGE(F10:F21)
B22: Jul 2025 | C22: 271187 | D22: 208614 | E22: =C22-D22 | F22: =E22-E21 | G22: =IFERROR(F22/E21,0) | H22: =AVERAGE(F20:F22) | I22: =AVERAGE(F17:F22) | J22: =AVERAGE(F11:F22)
B23: Aug 2025 | C23: 274401 | D23: 208990 | E23: =C23-D23 | F23: =E23-E22 | G23: =IFERROR(F23/E22,0) | H23: =AVERAGE(F21:F23) | I23: =AVERAGE(F18:F23) | J23: =AVERAGE(F12:F23)
B24: Sep 2025 | C24: 274592 | D24: 209426 | E24: =C24-D24 | F24: =E24-E23 | G24: =IFERROR(F24/E23,0) | H24: =AVERAGE(F22:F24) | I24: =AVERAGE(F19:F24) | J24: =AVERAGE(F13:F24)
B25: Oct 2025 | C25: 273351 | D25: 207409 | E25: =C25-D25 | F25: =E25-E24 | G25: =IFERROR(F25/E24,0) | H25: =AVERAGE(F23:F25) | I25: =AVERAGE(F20:F25) | J25: =AVERAGE(F14:F25)
B26: Nov 2025 | C26: 276902 | D26: 207219 | E26: =C26-D26 | F26: =E26-E25 | G26: =IFERROR(F26/E25,0) | H26: =AVERAGE(F24:F26) | I26: =AVERAGE(F21:F26) | J26: =AVERAGE(F15:F26)
B27: Dec 2025 | C27: 278560 | D27: 208591 | E27: =C27-D27 | F27: =E27-E26 | G27: =IFERROR(F27/E26,0) | H27: =AVERAGE(F25:F27) | I27: =AVERAGE(F22:F27) | J27: =AVERAGE(F16:F27)

Sheet Milestones
B2: Net Worth Milestones
B3: Milestone | C3: Target | D3: Current NW | E3: Remaining | F3: Avg Mo Growth | G3: Proj. Months | H3: Proj. Date | I3: Target Date | J3: Status
B4: $50K Net Worth | C4: 50000 | D4: =History!E27 | E4: =MAX(0,C4-D4) | F4: =History!I27 | G4: =IFERROR(IF(E4<=0,0,E4/F4),0) | H4: =IF(G4=0,TODAY(),TODAY()+G4*30.44) | I4: 45809 | J4: =IF(D4>=C4,"Reached",IF(H4<=I4,"On Track","Behind"))
B5: $100K Net Worth | C5: 100000 | D5: =History!E27 | E5: =MAX(0,C5-D5) | F5: =History!I27 | G5: =IFERROR(IF(E5<=0,0,E5/F5),0) | H5: =IF(G5=0,TODAY(),TODAY()+G5*30.44) | I5: 46022 | J5: =IF(D5>=C5,"Reached",IF(H5<=I5,"On Track","Behind"))
B6: $150K Net Worth | C6: 150000 | D6: =History!E27 | E6: =MAX(0,C6-D6) | F6: =History!I27 | G6: =IFERROR(IF(E6<=0,0,E6/F6),0) | H6: =IF(G6=0,TODAY(),TODAY()+G6*30.44) | I6: 46387 | J6: =IF(D6>=C6,"Reached",IF(H6<=I6,"On Track","Behind"))
B7: $250K Net Worth | C7: 250000 | D7: =History!E27 | E7: =MAX(0,C7-D7) | F7: =History!I27 | G7: =IFERROR(IF(E7<=0,0,E7/F7),0) | H7: =IF(G7=0,TODAY(),TODAY()+G7*30.44) | I7: 47118 | J7: =IF(D7>=C7,"Reached",IF(H7<=I7,"On Track","Behind"))
B8: $500K Net Worth | C8: 500000 | D8: =History!E27 | E8: =MAX(0,C8-D8) | F8: =History!I27 | G8: =IFERROR(IF(E8<=0,0,E8/F8),0) | H8: =IF(G8=0,TODAY(),TODAY()+G8*30.44) | I8: 48579 | J8: =IF(D8>=C8,"Reached",IF(H8<=I8,"On Track","Behind"))
B9: $1M Net Worth | C9: 1000000 | D9: =History!E27 | E9: =MAX(0,C9-D9) | F9: =History!I27 | G9: =IFERROR(IF(E9<=0,0,E9/F9),0) | H9: =IF(G9=0,TODAY(),TODAY()+G9*30.44) | I9: 50770 | J9: =IF(D9>=C9,"Reached",IF(H9<=I9,"On Track","Behind"))

Sheet Dashboard
B2: Net Worth Dashboard
B39: Account Type | C39: Current Balance
B40: Checking | C40: =SUMPRODUCT((Accounts!$D$4:$D$17="Checking")*'Monthly Balances'!$N$4:$N$17)
B41: Savings | C41: =SUMPRODUCT((Accounts!$D$4:$D$17="Savings")*'Monthly Balances'!$N$4:$N$17)
B42: Money Market | C42: =SUMPRODUCT((Accounts!$D$4:$D$17="Money Market")*'Monthly Balances'!$N$4:$N$17)
B43: Brokerage | C43: =SUMPRODUCT((Accounts!$D$4:$D$17="Brokerage")*'Monthly Balances'!$N$4:$N$17)
B44: 401k | C44: =SUMPRODUCT((Accounts!$D$4:$D$17="401k")*'Monthly Balances'!$N$4:$N$17)
B45: IRA | C45: =SUMPRODUCT((Accounts!$D$4:$D$17="IRA")*'Monthly Balances'!$N$4:$N$17)
B46: HSA | C46: =SUMPRODUCT((Accounts!$D$4:$D$17="HSA")*'Monthly Balances'!$N$4:$N$17)
B47: 529 | C47: =SUMPRODUCT((Accounts!$D$4:$D$17="529")*'Monthly Balances'!$N$4:$N$17)
B48: Real Estate | C48: =SUMPRODUCT((Accounts!$D$4:$D$17="Real Estate")*'Monthly Balances'!$N$4:$N$17)
B49: Vehicle | C49: =SUMPRODUCT((Accounts!$D$4:$D$17="Vehicle")*'Monthly Balances'!$N$4:$N$17)
B69: Milestone | C69: Target | D69: Current | E69: % Complete
B70: =Milestones!B4 | C70: =Milestones!C4 | D70: =Milestones!D4 | E70: =MIN(1,Milestones!D4/Milestones!C4)
B71: =Milestones!B5 | C71: =Milestones!C5 | D71: =Milestones!D5 | E71: =MIN(1,Milestones!D5/Milestones!C5)
B72: =Milestones!B6 | C72: =Milestones!C6 | D72: =Milestones!D6 | E72: =MIN(1,Milestones!D6/Milestones!C6)
B73: =Milestones!B7 | C73: =Milestones!C7 | D73: =Milestones!D7 | E73: =MIN(1,Milestones!D7/Milestones!C7)
B74: =Milestones!B8 | C74: =Milestones!C8 | D74: =Milestones!D8 | E74: =MIN(1,Milestones!D8/Milestones!C8)
B75: =Milestones!B9 | C75: =Milestones!C9 | D75: =Milestones!D9 | E75: =MIN(1,Milestones!D9/Milestones!C9)

Sheet Readme
C3: Net Worth Tracker
C5: Sample data covers January 2024 through December 2025.
C6: All account names and balances are fictional.
C7: Update the Monthly Balances sheet once a month with current figures.
C8: Copy each year's totals into the History sheet for multi-year tracking.
C9: Milestones project forward using the trailing 6-month average growth.
C10: Do not insert or delete rows inside the account ranges.
C11: This is not financial advice. Talk to a professional about your situation.
