Workbook

Sheet Deal Setup
A1: BRRRR rental scratch
A2: Property & Purchase | H2: What matters
A3: Property Address | B3: 1842 Linden Ave | H3: Total basis | I3: =B9 -> 233800
A4: Property Type | B4: Single Family | H4: Equity created | I4: =B7-B9 -> 21200
A5: Purchase Price | B5: 168000 | H5: Cash out at refi | I5: =B29 -> 1350
A6: Closing Costs | B6: 5800 | H6: Cash left in deal | I6: =B30 -> 50758
A7: After Repair Value (ARV) | B7: 255000 | H7: Post-refi DSCR | I7: ='Refi & 5-Year Hold'!B19 -> 1.035977
A8: Total Rehab Budget | B8: ='Rehab Budget'!B14 -> 60000 | H8: Year 1 cash flow | I8: ='Refi & 5-Year Hold'!B18 -> 563.25437
A9: Total Basis | B9: =B5+B6+B8 -> 233800 | H9: 5-year equity multiple | I9: ='BRRRR Snapshot'!B28 -> -1.8455001
A11: Initial Financing
A12: Purchase Loan LTV | B12: 0.8
A13: Rehab Draw Coverage | B13: 0.85
A14: Purchase Loan Amount | B14: =B5*B12 -> 134400
A15: Rehab Draw Amount | B15: =B8*B13 -> 51000
A16: Total Initial Loan | B16: =B14+B15 -> 185400
A17: Rate (interest only) | B17: 0.105
A18: Points (%) | B18: 0.02
A19: Monthly Interest Payment | B19: =B16*B17/12 -> 1622.25
A20: Cash to Close | B20: =MAX(0,(B5-B14)+(B8-B15)+B6+(B16*B18)) -> 52108
A22: Refinance Assumptions
A23: Refi LTV | B23: 0.75
A24: Refi Loan Amount | B24: =B7*B23 -> 191250
A25: Refi Rate | B25: 0.0725
A26: Refi Term (years) | B26: 30
A27: Refi Closing Costs | B27: 4500
A28: Monthly P&I After Refi | B28: =PMT(B25/12,B26*12,-B24) -> 1304.6621
A29: Cash Out at Refi | B29: =B24-B16-B27 -> 1350
A30: Cash Left in Deal | B30: =B20-B29 -> 50758
A32: Hold / Exit
A33: Hold Period (years) | B33: 5
A34: Annual Rent Growth | B34: 0.03
A35: Annual Expense Growth | B35: 0.025
A36: Exit Cap Rate | B36: 0.0675
A37: Selling Costs (%) | B37: 0.04

Sheet Rehab Budget
A1: Rehab Budget
A2: Line Item | B2: Budget | C2: % of Rehab | D2: Draw Month | E2: Notes | G2: Draw Schedule
A3: Demo / cleanout | B3: 4200 | C3: =IF($B$14=0,0,B3/$B$14) -> 0.07 | D3: 1 | G3: Month 1 | H3: Month 2 | I3: Month 3 | J3: Month 4 | K3: Month 5 | L3: Month 6
A4: Roof | B4: 12000 | C4: =IF($B$14=0,0,B4/$B$14) -> 0.2 | D4: 2 | G4: =SUMIF($D$3:$D$12,1,$B$3:$B$12) -> 4200 | H4: =SUMIF($D$3:$D$12,2,$B$3:$B$12) -> 19000 | I4: =SUMIF($D$3:$D$12,3,$B$3:$B$12) -> 15700 | J4: =SUMIF($D$3:$D$12,4,$B$3:$B$12) -> 9000 | K4: =SUMIF($D$3:$D$12,5,$B$3:$B$12) -> 6100 | L4: =SUMIF($D$3:$D$12,6,$B$3:$B$12) -> 6000
A5: HVAC / mechanical | B5: 7000 | C5: =IF($B$14=0,0,B5/$B$14) -> 0.11666667 | D5: 2 | G5: =SUM(G4:L4) -> 60000
A6: Kitchen | B6: 9500 | C6: =IF($B$14=0,0,B6/$B$14) -> 0.15833333 | D6: 3
A7: Bath | B7: 6200 | C7: =IF($B$14=0,0,B7/$B$14) -> 0.10333333 | D7: 3
A8: Flooring | B8: 5400 | C8: =IF($B$14=0,0,B8/$B$14) -> 0.09 | D8: 4
A9: Paint | B9: 3600 | C9: =IF($B$14=0,0,B9/$B$14) -> 0.06 | D9: 4
A10: Exterior / windows | B10: 4300 | C10: =IF($B$14=0,0,B10/$B$14) -> 0.071666667 | D10: 5
A11: Landscaping | B11: 1800 | C11: =IF($B$14=0,0,B11/$B$14) -> 0.03 | D11: 5
A12: Contingency | B12: 6000 | C12: =IF($B$14=0,0,B12/$B$14) -> 0.1 | D12: 6 | E12: Leave this in
A14: Total Rehab | B14: =SUM(B3:B12) -> 60000
A15: Avg Monthly Draw | B15: =B14/6 -> 10000

Sheet Stabilized Rental
A1: Stabilized Rental
A3: Monthly Rent | B3: 2250
A4: Other Income | B4: 35
A5: Vacancy (%) | B5: 0.05
A6: Management (%) | B6: 0.08
A7: Maintenance Reserve (%) | B7: 0.07
A8: CapEx Reserve (%) | B8: 0.05
A9: Property Tax (monthly) | B9: 210
A10: Insurance (monthly) | B10: 95
A11: HOA | B11: 0
A12: Utilities / lawn / misc | B12: 80
A14: Annual Gross Scheduled Rent | B14: =B3*12 -> 27000
A15: Annual Other Income | B15: =B4*12 -> 420
A16: Gross Income | B16: =B14+B15 -> 27420
A17: Vacancy Loss | B17: =B16*B5*-1 -> -1371
A18: Effective Gross Income | B18: =B16+B17 -> 26049
A19: Management Fee | B19: =B18*B6*-1 -> -2083.92
A20: Maintenance Reserve | B20: =B18*B7*-1 -> -1823.43
A21: CapEx Reserve | B21: =B18*B8*-1 -> -1302.45
A22: Fixed Annual Expenses | B22: =SUM(B9:B12)*12 -> 4620
A23: Total Operating Expenses | B23: =ABS(SUM(B19:B21))+B22 -> 9829.8
A24: Annual NOI | B24: =B18-B23 -> 16219.2
A25: Monthly NOI | B25: =B24/12 -> 1351.6

Sheet Refi & 5-Year Hold
A1: Refi & 5-Year Hold
A2: Refi Math
A3: Refi loan amount | B3: ='Deal Setup'!B24 -> 191250
A4: Hard money payoff | B4: ='Deal Setup'!B16 -> 185400
A5: Refi closing costs | B5: ='Deal Setup'!B27 -> 4500
A6: Cash out at refi | B6: =B3-B4-B5 -> 1350
A7: Cash left in deal | B7: ='Deal Setup'!B20-B6 -> 50758
A8: Post-refi DSCR | B8: =IF('Deal Setup'!B28*12=0,0,'Stabilized Rental'!B24/('Deal Setup'!B28*12)) -> 1.035977
A11: Line Item | B11: Year 1 | C11: Year 2 | D11: Year 3 | E11: Year 4 | F11: Year 5
A12: Gross income | B12: ='Stabilized Rental'!B16 -> 27420 | C12: =B12*(1+'Deal Setup'!$B$34) -> 28242.6 | D12: =C12*(1+'Deal Setup'!$B$34) -> 29089.878 | E12: =D12*(1+'Deal Setup'!$B$34) -> 29962.574 | F12: =E12*(1+'Deal Setup'!$B$34) -> 30861.452
A13: Vacancy loss | B13: ='Stabilized Rental'!B17 -> -1371 | C13: =C12*'Stabilized Rental'!$B$5*-1 -> -1412.13 | D13: =D12*'Stabilized Rental'!$B$5*-1 -> -1454.4939 | E13: =E12*'Stabilized Rental'!$B$5*-1 -> -1498.1287 | F13: =F12*'Stabilized Rental'!$B$5*-1 -> -1543.0726
A14: Effective gross income | B14: ='Stabilized Rental'!B18 -> 26049 | C14: =C12+C13 -> 26830.47 | D14: =D12+D13 -> 27635.384 | E14: =E12+E13 -> 28464.446 | F14: =F12+F13 -> 29318.379
A15: Operating expenses | B15: ='Stabilized Rental'!B23 -> 9829.8 | C15: =B15*(1+'Deal Setup'!$B$35) -> 10075.545 | D15: =C15*(1+'Deal Setup'!$B$35) -> 10327.434 | E15: =D15*(1+'Deal Setup'!$B$35) -> 10585.619 | F15: =E15*(1+'Deal Setup'!$B$35) -> 10850.26
A16: NOI | B16: ='Stabilized Rental'!B24 -> 16219.2 | C16: =C14-C15 -> 16754.925 | D16: =D14-D15 -> 17307.95 | E16: =E14-E15 -> 17878.826 | F16: =F14-F15 -> 18468.119
A17: Debt service | B17: ='Deal Setup'!B28*12 -> 15655.946 | C17: ='Deal Setup'!$B$28*12 -> 15655.946 | D17: ='Deal Setup'!$B$28*12 -> 15655.946 | E17: ='Deal Setup'!$B$28*12 -> 15655.946 | F17: ='Deal Setup'!$B$28*12 -> 15655.946
A18: Cash flow after debt | B18: =B16-B17 -> 563.25437 | C18: =C16-C17 -> 1098.9794 | D18: =D16-D17 -> 1652.0048 | E18: =E16-E17 -> 2222.8805 | F18: =F16-F17 -> 2812.1734
A19: DSCR | B19: =IF(B17=0,0,B16/B17) -> 1.035977 | C19: =IF(C17=0,0,C16/C17) -> 1.0701957 | D19: =IF(D17=0,0,D16/D17) -> 1.1055193 | E19: =IF(E17=0,0,E16/E17) -> 1.1419832 | F19: =IF(F17=0,0,F16/F17) -> 1.1796234

Sheet BRRRR Snapshot
A1: BRRRR Snapshot
A2: Deal
A3: Purchase price | B3: ='Deal Setup'!B5 -> 168000 | D3: IRR Cash Flow
A4: Rehab | B4: ='Deal Setup'!B8 -> 60000 | D4: Initial | E4: Refi | F4: Year 1 | G4: Year 2 | H4: Year 3 | I4: Year 4 | J4: Year 5 + Sale
A5: Total basis | B5: ='Deal Setup'!B9 -> 233800 | D5: =B11 -> 52108 | E5: =B12 -> 1350 | F5: ='Refi & 5-Year Hold'!B18 -> 563.25437 | G5: ='Refi & 5-Year Hold'!C18 -> 1098.9794 | H5: ='Refi & 5-Year Hold'!D18 -> 1652.0048 | I5: ='Refi & 5-Year Hold'!E18 -> 2222.8805 | J5: ='Refi & 5-Year Hold'!F18+B22 -> -103052.44
A6: ARV | B6: ='Deal Setup'!B7 -> 255000
A7: Equity created | B7: =B6-B5 -> 21200
A10: Refi
A11: Initial cash in | B11: ='Deal Setup'!B20 -> 52108
A12: Cash out at refi | B12: ='Refi & 5-Year Hold'!B6 -> 1350
A13: Cash left in deal | B13: ='Refi & 5-Year Hold'!B7 -> 50758
A14: Year 1 cash flow | B14: ='Refi & 5-Year Hold'!B18 -> 563.25437
A15: Cash-on-cash return | B15: =IF(B13<=0,0,B14/B13) -> 0.011096859
A17: Exit
A18: Year 5 NOI | B18: ='Refi & 5-Year Hold'!F16 -> 18468.119
A19: Exit value | B19: =IF('Deal Setup'!B36=0,0,B18/'Deal Setup'!B36) -> 273601.76
A20: Selling costs | B20: =B19*'Deal Setup'!B37 -> 10944.071
A21: Loan payoff | B21: =-FV('Deal Setup'!B25/12,'Deal Setup'!B33*12,'Deal Setup'!B28,'Deal Setup'!B24) -> 368522.3
A22: Net sale proceeds | B22: =B19-B20-B21 -> -105864.61
A25: Return Math
A26: 5-year cash flow total | B26: =SUM('Refi & 5-Year Hold'!B18:F18) -> 8349.2925
A27: Total cash back | B27: =B12+B22+B26 -> -96165.317
A28: 5-year equity multiple | B28: =IF(B11=0,0,B27/B11) -> -1.8455001
A29: Levered IRR | B29: =IRR(D5:J5) -> 0.10345876
