Workbook

Sheet Situation
A1: Traditional IRA / 401k Balance | B1: 420000
A2: Roth IRA Balance (existing) | B2: 35000
A3: Taxable Brokerage | B3: 180000
A4: Cash / Savings | B4: 45000
A7: Current Age | B7: 48
A8: Spouse's Age (if MFJ, else leave blank) | B8: 46
A9: Filing Status | B9: Married Filing Jointly
A10: Other Annual Income (non-conversion) | B10: 32000
A11: State Income Tax Rate (flat approx.) | B11: 0.05
A12: Annual Living Expenses | B12: 65000
A13: Expected Investment Return | B13: 0.06
A14: Planning Horizon (years) | B14: 15
A17: Conversion Start Year | B17: 2025
A18: Conversion Window (years) | B18: 7
A19: Year 1 Conversion Amount | B19: 50000
A20: Year 2 Conversion Amount | B20: 55000
A21: Year 3 Conversion Amount | B21: 60000
A22: Year 4 Conversion Amount | B22: 62000
A23: Year 5 Conversion Amount | B23: 65000
... A28: Expected tax rate in retirement (for compare) | B28: 0.22
A30: Tax Bracket Reference (2025, ordinary income)
A31: Bracket | B31: Single (taxable) | C31: MFJ (taxable) | D31: HoH (taxable)
A32: 10% | B32: 0 – 11,925 | C32: 0 – 23,850 | D32: 0 – 17,025
A33: 12% | B33: 11,926 – 48,475 | C33: 23,851 – 96,950 | D33: 17,026 – 69,250
A34: 22% | B34: 48,476 – 103,350 | C34: 96,951 – 206,700 | D34: 69,251 – 110,150
A35: 24% | B35: 103,351 – 197,300 | C35: 206,701 – 394,600 | D35: 110,151 – 210,300
A36: 32% | B36: 197,301 – 250,525 | C36: 394,601 – 501,050 | D36: 210,301 – 267,450
A37: 35% | B37: 250,526 – 626,350 | C37: 501,051 – 751,600 | D37: 267,451 – 626,350
A38: 37% | B38: 626,351+ | C38: 751,601+ | D38: 626,351+
A41: Bracket Lookup Table (used by Conversion Schedule)
A42: Rate | B42: Single upper | C42: Single cum | D42: MFJ upper | E42: MFJ cum | F42: HoH upper | G42: HoH cum
A43: 0.1 | B43: 11925 | C43: 0 | D43: 23850 | E43: 0 | F43: 17025 | G43: 0
A44: 0.12 | B44: 48475 | C44: 1192.5 | D44: 96950 | E44: 2385 | F44: 69250 | G44: 1702.5
A45: 0.22 | B45: 103350 | C45: 5578.5 | D45: 206700 | E45: 11157 | F45: 110150 | G45: 7975.5
A46: 0.24 | B46: 197300 | C46: 17651 | D46: 394600 | E46: 35302 | F46: 210300 | G46: 18993
A47: 0.32 | B47: 250525 | C47: 40199 | D47: 501050 | E47: 80398 | F47: 267450 | G47: 43029
A48: 0.35 | B48: 626350 | C48: 57231 | D48: 751600 | E48: 114462 | F48: 626350 | G48: 61317
A49: 0.37 | B49: 9999999 | C49: 188769.5 | D49: 9999999 | E49: 201814 | F49: 9999999 | G49: 186867

Sheet Conversion Schedule
A1: Year | B1: Age | C1: Trad IRA Beg | D1: Conversion | E1: Trad IRA End | F1: Roth Beg | G1: Roth Conv | H1: Roth End | I1: Other Income | J1: Total Taxable Inc | K1: Std Deduction | L1: Taxable After Ded | M1: Federal Tax | N1: State Tax | O1: Total Tax | P1: Marginal Bracket | Q1: Tax Paid From | R1: Taxable Acct End | S1: Net Worth (after-tax Trad)
A2: =IF(ROW()-2>=Situation!$B$14,"",Situation!$B$17+(ROW()-2)) -> 2025 | B2: =IF(A2="","",Situation!$B$7+A2-Situation!$B$17) -> 48 | C2: =IF(A2="","",Situation!$B$1) -> 420000 | D2: =IF(A2="",0,IF(A2>=Situation!$B$17+Situation!$B$18,0,INDEX(Situation!$B$19:$B$25,MIN(7,A2-Situation!$B$17+1)))) -> 50000 | E2: =IF(A2="","",(C2-D2)*(1+Situation!$B$13)) -> 392200 | F2: =IF(A2="","",Situation!$B$2) -> 35000 | G2: =IF(A2="","",D2) -> 50000 | H2: =IF(A2="","",(F2+G2)*(1+Situation!$B$13)) -> 90100 | I2: =IF(A2="","",Situation!$B$10) -> 32000 | J2: =IF(A2="","",I2+D2) -> 82000 | K2: =IF(A2="","",IF(Situation!$B$9="Single",15000,IF(Situation!$B$9="Married Filing Jointly",30000,IF(Situation!$B$9="Head of Household",22500,15000)))*(1.02^(A2-Situation!$B$17))) -> 30000 | L2: =IF(A2="","",MAX(0,J2-K2)) -> 52000 | M2: =IF(A2="","",IF(Situation!$B$9="Married Filing Jointly",IF(L2<=0,0,INDEX(Situation!$E$43:$E$49,MATCH(L2,Situation!$D$43:$D$49,1))+(L2-IF(MATCH(L2,Situation!$D$43:$D$49,1)=1,0,INDEX(Situation!$D$43:$D$49,MATCH(L2,Situation!$D$43:$D$49,1)-1)))*INDEX(Situation!$A$43:$A$49,MATCH(L2,Situation!$D$43:$D$49,1))),IF(Situation!$B$9="Head of Household",IF(L2<=0,0,INDEX(Situation!$G$43:$G$49,MATCH(L2,Situation!$F$43:$F$49,1))+(L2-IF(MATCH(L2,Situation!$F$43:$F$49,1)=1,0,INDEX(Situation!$F$43:$F$49,MATCH(L2,Situation!$F$43:$F$49,1)-1)))*INDEX(Situation!$A$43:$A$49,MATCH(L2,Situation!$F$43:$F$49,1))),IF(L2<=0,0,INDEX(Situation!$C$43:$C$49,MATCH(L2,Situation!$B$43:$B$49,1))+(L2-IF(MATCH(L2,Situation!$B$43:$B$49,1)=1,0,INDEX(Situation!$B$43:$B$49,MATCH(L2,Situation!$B$43:$B$49,1)-1)))*INDEX(Situation!$A$43:$A$49,MATCH(L2,Situation!$B$43:$B$49,1)))))) -> 5200 | N2: =IF(A2="","",L2*Situation!$B$11) -> 2600 | O2: =IF(A2="","",M2+N2) -> 7800 | P2: =IF(OR(A2="",L2<=0),"",IF(Situation!$B$9="Married Filing Jointly",INDEX(Situation!$A$43:$A$49,MATCH(L2,Situation!$D$43:$D$49,1)),IF(Situation!$B$9="Head of Household",INDEX(Situation!$A$43:$A$49,MATCH(L2,Situation!$F$43:$F$49,1)),INDEX(Situation!$A$43:$A$49,MATCH(L2,Situation!$B$43:$B$49,1))))) -> 0.1 | Q2: Taxable Account | R2: =IF(A2="","",(Situation!$B$3+Situation!$B$4-O2-MAX(0,Situation!$B$12-Situation!$B$10))*(1+Situation!$B$13)) -> 195252 | S2: =IF(A2="","",E2*(1-Situation!$B$28)+H2+R2) -> 591268
A3: =IF(ROW()-2>=Situation!$B$14,"",Situation!$B$17+(ROW()-2)) -> 2026 | B3: =IF(A3="","",Situation!$B$7+A3-Situation!$B$17) -> 49 | C3: =IF(A3="","",E2) -> 392200 | D3: =IF(A3="",0,IF(A3>=Situation!$B$17+Situation!$B$18,0,INDEX(Situation!$B$19:$B$25,MIN(7,A3-Situation!$B$17+1)))) -> 55000 | E3: =IF(A3="","",(C3-D3)*(1+Situation!$B$13)) -> 357432 | F3: =IF(A3="","",H2) -> 90100 | G3: =IF(A3="","",D3) -> 55000 | H3: =IF(A3="","",(F3+G3)*(1+Situation!$B$13)) -> 153806 | I3: =IF(A3="","",Situation!$B$10) -> 32000 | J3: =IF(A3="","",I3+D3) -> 87000 | K3: =IF(A3="","",IF(Situation!$B$9="Single",15000,IF(Situation!$B$9="Married Filing Jointly",30000,IF(Situation!$B$9="Head of Household",22500,15000)))*(1.02^(A3-Situation!$B$17))) -> 30600 | L3: =IF(A3="","",MAX(0,J3-K3)) -> 56400 | M3: =IF(A3="","",IF(Situation!$B$9="Married Filing Jointly",IF(L3<=0,0,INDEX(Situation!$E$43:$E$49,MATCH(L3,Situation!$D$43:$D$49,1))+(L3-IF(MATCH(L3,Situation!$D$43:$D$49,1)=1,0,INDEX(Situation!$D$43:$D$49,MATCH(L3,Situation!$D$43:$D$49,1)-1)))*INDEX(Situation!$A$43:$A$49,MATCH(L3,Situation!$D$43:$D$49,1))),IF(Situation!$B$9="Head of Household",IF(L3<=0,0,INDEX(Situation!$G$43:$G$49,MATCH(L3,Situation!$F$43:$F$49,1))+(L3-IF(MATCH(L3,Situation!$F$43:$F$49,1)=1,0,INDEX(Situation!$F$43:$F$49,MATCH(L3,Situation!$F$43:$F$49,1)-1)))*INDEX(Situation!$A$43:$A$49,MATCH(L3,Situation!$F$43:$F$49,1))),IF(L3<=0,0,INDEX(Situation!$C$43:$C$49,MATCH(L3,Situation!$B$43:$B$49,1))+(L3-IF(MATCH(L3,Situation!$B$43:$B$49,1)=1,0,INDEX(Situation!$B$43:$B$49,MATCH(L3,Situation!$B$43:$B$49,1)-1)))*INDEX(Situation!$A$43:$A$49,MATCH(L3,Situation!$B$43:$B$49,1)))))) -> 5640 | N3: =IF(A3="","",L3*Situation!$B$11) -> 2820 | O3: =IF(A3="","",M3+N3) -> 8460 | P3: =IF(OR(A3="",L3<=0),"",IF(Situation!$B$9="Married Filing Jointly",INDEX(Situation!$A$43:$A$49,MATCH(L3,Situation!$D$43:$D$49,1)),IF(Situation!$B$9="Head of Household",INDEX(Situation!$A$43:$A$49,MATCH(L3,Situation!$F$43:$F$49,1)),INDEX(Situation!$A$43:$A$49,MATCH(L3,Situation!$B$43:$B$49,1))))) -> 0.1 | Q3: Taxable Account | R3: =IF(A3="","",(R2-O3-MAX(0,Situation!$B$12-Situation!$B$10))*(1+Situation!$B$13)) -> 163019.52 | S3: =IF(A3="","",E3*(1-Situation!$B$28)+H3+R3) -> 595622.48
A4: =IF(ROW()-2>=Situation!$B$14,"",Situation!$B$17+(ROW()-2)) -> 2027 | B4: =IF(A4="","",Situation!$B$7+A4-Situation!$B$17) -> 50 | C4: =IF(A4="","",E3) -> 357432 | D4: =IF(A4="",0,IF(A4>=Situation!$B$17+Situation!$B$18,0,INDEX(Situation!$B$19:$B$25,MIN(7,A4-Situation!$B$17+1)))) -> 60000 | E4: =IF(A4="","",(C4-D4)*(1+Situation!$B$13)) -> 315277.92 | F4: =IF(A4="","",H3) -> 153806 | G4: =IF(A4="","",D4) -> 60000 | H4: =IF(A4="","",(F4+G4)*(1+Situation!$B$13)) -> 226634.36 | I4: =IF(A4="","",Situation!$B$10) -> 32000 | J4: =IF(A4="","",I4+D4) -> 92000 | K4: =IF(A4="","",IF(Situation!$B$9="Single",15000,IF(Situation!$B$9="Married Filing Jointly",30000,IF(Situation!$B$9="Head of Household",22500,15000)))*(1.02^(A4-Situation!$B$17))) -> 31212 | L4: =IF(A4="","",MAX(0,J4-K4)) -> 60788 | M4: =IF(A4="","",IF(Situation!$B$9="Married Filing Jointly",IF(L4<=0,0,INDEX(Situation!$E$43:$E$49,MATCH(L4,Situation!$D$43:$D$49,1))+(L4-IF(MATCH(L4,Situation!$D$43:$D$49,1)=1,0,INDEX(Situation!$D$43:$D$49,MATCH(L4,Situation!$D$43:$D$49,1)-1)))*INDEX(Situation!$A$43:$A$49,MATCH(L4,Situation!$D$43:$D$49,1))),IF(Situation!$B$9="Head of Household",IF(L4<=0,0,INDEX(Situation!$G$43:$G$49,MATCH(L4,Situation!$F$43:$F$49,1))+(L4-IF(MATCH(L4,Situation!$F$43:$F$49,1)=1,0,INDEX(Situation!$F$43:$F$49,MATCH(L4,Situation!$F$43:$F$49,1)-1)))*INDEX(Situation!$A$43:$A$49,MATCH(L4,Situation!$F$43:$F$49,1))),IF(L4<=0,0,INDEX(Situation!$C$43:$C$49,MATCH(L4,Situation!$B$43:$B$49,1))+(L4-IF(MATCH(L4,Situation!$B$43:$B$49,1)=1,0,INDEX(Situation!$B$43:$B$49,MATCH(L4,Situation!$B$43:$B$49,1)-1)))*INDEX(Situation!$A$43:$A$49,MATCH(L4,Situation!$B$43:$B$49,1)))))) -> 6078.8 | N4: =IF(A4="","",L4*Situation!$B$11) -> 3039.4 | O4: =IF(A4="","",M4+N4) -> 9118.2 | P4: =IF(OR(A4="",L4<=0),"",IF(Situation!$B$9="Married Filing Jointly",INDEX(Situation!$A$43:$A$49,MATCH(L4,Situation!$D$43:$D$49,1)),IF(Situation!$B$9="Head of Household",INDEX(Situation!$A$43:$A$49,MATCH(L4,Situation!$F$43:$F$49,1)),INDEX(Situation!$A$43:$A$49,MATCH(L4,Situation!$B$43:$B$49,1))))) -> 0.1 | Q4: Taxable Account | R4: =IF(A4="","",(R3-O4-MAX(0,Situation!$B$12-Situation!$B$10))*(1+Situation!$B$13)) -> 128155.4 | S4: =IF(A4="","",E4*(1-Situation!$B$28)+H4+R4) -> 600706.54
A5: =IF(ROW()-2>=Situation!$B$14,"",Situation!$B$17+(ROW()-2)) -> 2028 | B5: =IF(A5="","",Situation!$B$7+A5-Situation!$B$17) -> 51 | C5: =IF(A5="","",E4) -> 315277.92 | D5: =IF(A5="",0,IF(A5>=Situation!$B$17+Situation!$B$18,0,INDEX(Situation!$B$19:$B$25,MIN(7,A5-Situation!$B$17+1)))) -> 62000 | E5: =IF(A5="","",(C5-D5)*(1+Situation!$B$13)) -> 268474.6 | F5: =IF(A5="","",H4) -> 226634.36 | G5: =IF(A5="","",D5) -> 62000 | H5: =IF(A5="","",(F5+G5)*(1+Situation!$B$13)) -> 305952.42 | I5: =IF(A5="","",Situation!$B$10) -> 32000 | J5: =IF(A5="","",I5+D5) -> 94000 | K5: =IF(A5="","",IF(Situation!$B$9="Single",15000,IF(Situation!$B$9="Married Filing Jointly",30000,IF(Situation!$B$9="Head of Household",22500,15000)))*(1.02^(A5-Situation!$B$17))) -> 31836.24 | L5: =IF(A5="","",MAX(0,J5-K5)) -> 62163.76 | M5: =IF(A5="","",IF(Situation!$B$9="Married Filing Jointly",IF(L5<=0,0,INDEX(Situation!$E$43:$E$49,MATCH(L5,Situation!$D$43:$D$49,1))+(L5-IF(MATCH(L5,Situation!$D$43:$D$49,1)=1,0,INDEX(Situation!$D$43:$D$49,MATCH(L5,Situation!$D$43:$D$49,1)-1)))*INDEX(Situation!$A$43:$A$49,MATCH(L5,Situation!$D$43:$D$49,1))),IF(Situation!$B$9="Head of Household",IF(L5<=0,0,INDEX(Situation!$G$43:$G$49,MATCH(L5,Situation!$F$43:$F$49,1))+(L5-IF(MATCH(L5,Situation!$F$43:$F$49,1)=1,0,INDEX(Situation!$F$43:$F$49,MATCH(L5,Situation!$F$43:$F$49,1)-1)))*INDEX(Situation!$A$43:$A$49,MATCH(L5,Situation!$F$43:$F$49,1))),IF(L5<=0,0,INDEX(Situation!$C$43:$C$49,MATCH(L5,Situation!$B$43:$B$49,1))+(L5-IF(MATCH(L5,Situation!$B$43:$B$49,1)=1,0,INDEX(Situation!$B$43:$B$49,MATCH(L5,Situation!$B$43:$B$49,1)-1)))*INDEX(Situation!$A$43:$A$49,MATCH(L5,Situation!$B$43:$B$49,1)))))) -> 6216.376 | N5: =IF(A5="","",L5*Situation!$B$11) -> 3108.188 | O5: =IF(A5="","",M5+N5) -> 9324.564 | P5: =IF(OR(A5="",L5<=0),"",IF(Situation!$B$9="Married Filing Jointly",INDEX(Situation!$A$43:$A$49,MATCH(L5,Situation!$D$43:$D$49,1)),IF(Situation!$B$9="Head of Household",INDEX(Situation!$A$43:$A$49,MATCH(L5,Situation!$F$43:$F$49,1)),INDEX(Situation!$A$43:$A$49,MATCH(L5,Situation!$B$43:$B$49,1))))) -> 0.1 | Q5: Taxable Account | R5: =IF(A5="","",(R4-O5-MAX(0,Situation!$B$12-Situation!$B$10))*(1+Situation!$B$13)) -> 90980.685 | S5: =IF(A5="","",E5*(1-Situation!$B$28)+H5+R5) -> 606343.29
A6: =IF(ROW()-2>=Situation!$B$14,"",Situation!$B$17+(ROW()-2)) -> 2029 | B6: =IF(A6="","",Situation!$B$7+A6-Situation!$B$17) -> 52 | C6: =IF(A6="","",E5) -> 268474.6 | D6: =IF(A6="",0,IF(A6>=Situation!$B$17+Situation!$B$18,0,INDEX(Situation!$B$19:$B$25,MIN(7,A6-Situation!$B$17+1)))) -> 65000 | E6: =IF(A6="","",(C6-D6)*(1+Situation!$B$13)) -> 215683.07 | F6: =IF(A6="","",H5) -> 305952.42 | G6: =IF(A6="","",D6) -> 65000 | H6: =IF(A6="","",(F6+G6)*(1+Situation!$B$13)) -> 393209.57 | I6: =IF(A6="","",Situation!$B$10) -> 32000 | J6: =IF(A6="","",I6+D6) -> 97000 | K6: =IF(A6="","",IF(Situation!$B$9="Single",15000,IF(Situation!$B$9="Married Filing Jointly",30000,IF(Situation!$B$9="Head of Household",22500,15000)))*(1.02^(A6-Situation!$B$17))) -> 32472.965 | L6: =IF(A6="","",MAX(0,J6-K6)) -> 64527.035 | M6: =IF(A6="","",IF(Situation!$B$9="Married Filing Jointly",IF(L6<=0,0,INDEX(Situation!$E$43:$E$49,MATCH(L6,Situation!$D$43:$D$49,1))+(L6-IF(MATCH(L6,Situation!$D$43:$D$49,1)=1,0,INDEX(Situation!$D$43:$D$49,MATCH(L6,Situation!$D$43:$D$49,1)-1)))*INDEX(Situation!$A$43:$A$49,MATCH(L6,Situation!$D$43:$D$49,1))),IF(Situation!$B$9="Head of Household",IF(L6<=0,0,INDEX(Situation!$G$43:$G$49,MATCH(L6,Situation!$F$43:$F$49,1))+(L6-IF(MATCH(L6,Situation!$F$43:$F$49,1)=1,0,INDEX(Situation!$F$43:$F$49,MATCH(L6,Situation!$F$43:$F$49,1)-1)))*INDEX(Situation!$A$43:$A$49,MATCH(L6,Situation!$F$43:$F$49,1))),IF(L6<=0,0,INDEX(Situation!$C$43:$C$49,MATCH(L6,Situation!$B$43:$B$49,1))+(L6-IF(MATCH(L6,Situation!$B$43:$B$49,1)=1,0,INDEX(Situation!$B$43:$B$49,MATCH(L6,Situation!$B$43:$B$49,1)-1)))*INDEX(Situation!$A$43:$A$49,MATCH(L6,Situation!$B$43:$B$49,1)))))) -> 6452.7035 | N6: =IF(A6="","",L6*Situation!$B$11) -> 3226.3518 | O6: =IF(A6="","",M6+N6) -> 9679.0553 | P6: =IF(OR(A6="",L6<=0),"",IF(Situation!$B$9="Married Filing Jointly",INDEX(Situation!$A$43:$A$49,MATCH(L6,Situation!$D$43:$D$49,1)),IF(Situation!$B$9="Head of Household",INDEX(Situation!$A$43:$A$49,MATCH(L6,Situation!$F$43:$F$49,1)),INDEX(Situation!$A$43:$A$49,MATCH(L6,Situation!$B$43:$B$49,1))))) -> 0.1 | Q6: Taxable Account | R6: =IF(A6="","",(R5-O6-MAX(0,Situation!$B$12-Situation!$B$10))*(1+Situation!$B$13)) -> 51199.728 | S6: =IF(A6="","",E6*(1-Situation!$B$28)+H6+R6) -> 612642.09
A7: =IF(ROW()-2>=Situation!$B$14,"",Situation!$B$17+(ROW()-2)) -> 2030 | B7: =IF(A7="","",Situation!$B$7+A7-Situation!$B$17) -> 53 | C7: =IF(A7="","",E6) -> 215683.07 | D7: =IF(A7="",0,IF(A7>=Situation!$B$17+Situation!$B$18,0,INDEX(Situation!$B$19:$B$25,MIN(7,A7-Situation!$B$17+1)))) -> 68000 | E7: =IF(A7="","",(C7-D7)*(1+Situation!$B$13)) -> 156544.06 | F7: =IF(A7="","",H6) -> 393209.57 | G7: =IF(A7="","",D7) -> 68000 | H7: =IF(A7="","",(F7+G7)*(1+Situation!$B$13)) -> 488882.14 | I7: =IF(A7="","",Situation!$B$10) -> 32000 | J7: =IF(A7="","",I7+D7) -> 100000 | K7: =IF(A7="","",IF(Situation!$B$9="Single",15000,IF(Situation!$B$9="Married Filing Jointly",30000,IF(Situation!$B$9="Head of Household",22500,15000)))*(1.02^(A7-Situation!$B$17))) -> 33122.424 | L7: =IF(A7="","",MAX(0,J7-K7)) -> 66877.576 | M7: =IF(A7="","",IF(Situation!$B$9="Married Filing Jointly",IF(L7<=0,0,INDEX(Situation!$E$43:$E$49,MATCH(L7,Situation!$D$43:$D$49,1))+(L7-IF(MATCH(L7,Situation!$D$43:$D$49,1)=1,0,INDEX(Situation!$D$43:$D$49,MATCH(L7,Situation!$D$43:$D$49,1)-1)))*INDEX(Situation!$A$43:$A$49,MATCH(L7,Situation!$D$43:$D$49,1))),IF(Situation!$B$9="Head of Household",IF(L7<=0,0,INDEX(Situation!$G$43:$G$49,MATCH(L7,Situation!$F$43:$F$49,1))+(L7-IF(MATCH(L7,Situation!$F$43:$F$49,1)=1,0,INDEX(Situation!$F$43:$F$49,MATCH(L7,Situation!$F$43:$F$49,1)-1)))*INDEX(Situation!$A$43:$A$49,MATCH(L7,Situation!$F$43:$F$49,1))),IF(L7<=0,0,INDEX(Situation!$C$43:$C$49,MATCH(L7,Situation!$B$43:$B$49,1))+(L7-IF(MATCH(L7,Situation!$B$43:$B$49,1)=1,0,INDEX(Situation!$B$43:$B$49,MATCH(L7,Situation!$B$43:$B$49,1)-1)))*INDEX(Situation!$A$43:$A$49,MATCH(L7,Situation!$B$43:$B$49,1)))))) -> 6687.7576 | N7: =IF(A7="","",L7*Situation!$B$11) -> 3343.8788 | O7: =IF(A7="","",M7+N7) -> 10031.636 | P7: =IF(OR(A7="",L7<=0),"",IF(Situation!$B$9="Married Filing Jointly",INDEX(Situation!$A$43:$A$49,MATCH(L7,Situation!$D$43:$D$49,1)),IF(Situation!$B$9="Head of Household",INDEX(Situation!$A$43:$A$49,MATCH(L7,Situation!$F$43:$F$49,1)),INDEX(Situation!$A$43:$A$49,MATCH(L7,Situation!$B$43:$B$49,1))))) -> 0.1 | Q7: Taxable Account | R7: =IF(A7="","",(R6-O7-MAX(0,Situation!$B$12-Situation!$B$10))*(1+Situation!$B$13)) -> 8658.1769 | S7: =IF(A7="","",E7*(1-Situation!$B$28)+H7+R7) -> 619644.68
A8: =IF(ROW()-2>=Situation!$B$14,"",Situation!$B$17+(ROW()-2)) -> 2031 | B8: =IF(A8="","",Situation!$B$7+A8-Situation!$B$17) -> 54 | C8: =IF(A8="","",E7) -> 156544.06 | D8: =IF(A8="",0,IF(A8>=Situation!$B$17+Situation!$B$18,0,INDEX(Situation!$B$19:$B$25,MIN(7,A8-Situation!$B$17+1)))) -> 70000 | E8: =IF(A8="","",(C8-D8)*(1+Situation!$B$13)) -> 91736.698 | F8: =IF(A8="","",H7) -> 488882.14 | G8: =IF(A8="","",D8) -> 70000 | H8: =IF(A8="","",(F8+G8)*(1+Situation!$B$13)) -> 592415.07 | I8: =IF(A8="","",Situation!$B$10) -> 32000 | J8: =IF(A8="","",I8+D8) -> 102000 | K8: =IF(A8="","",IF(Situation!$B$9="Single",15000,IF(Situation!$B$9="Married Filing Jointly",30000,IF(Situation!$B$9="Head of Household",22500,15000)))*(1.02^(A8-Situation!$B$17))) -> 33784.873 | L8: =IF(A8="","",MAX(0,J8-K8)) -> 68215.127 | M8: =IF(A8="","",IF(Situation!$B$9="Married Filing Jointly",IF(L8<=0,0,INDEX(Situation!$E$43:$E$49,MATCH(L8,Situation!$D$43:$D$49,1))+(L8-IF(MATCH(L8,Situation!$D$43:$D$49,1)=1,0,INDEX(Situation!$D$43:$D$49,MATCH(L8,Situation!$D$43:$D$49,1)-1)))*INDEX(Situation!$A$43:$A$49,MATCH(L8,Situation!$D$43:$D$49,1))),IF(Situation!$B$9="Head of Household",IF(L8<=0,0,INDEX(Situation!$G$43:$G$49,MATCH(L8,Situation!$F$43:$F$49,1))+(L8-IF(MATCH(L8,Situation!$F$43:$F$49,1)=1,0,INDEX(Situation!$F$43:$F$49,MATCH(L8,Situation!$F$43:$F$49,1)-1)))*INDEX(Situation!$A$43:$A$49,MATCH(L8,Situation!$F$43:$F$49,1))),IF(L8<=0,0,INDEX(Situation!$C$43:$C$49,MATCH(L8,Situation!$B$43:$B$49,1))+(L8-IF(MATCH(L8,Situation!$B$43:$B$49,1)=1,0,INDEX(Situation!$B$43:$B$49,MATCH(L8,Situation!$B$43:$B$49,1)-1)))*INDEX(Situation!$A$43:$A$49,MATCH(L8,Situation!$B$43:$B$49,1)))))) -> 6821.5127 | N8: =IF(A8="","",L8*Situation!$B$11) -> 3410.7564 | O8: =IF(A8="","",M8+N8) -> 10232.269 | P8: =IF(OR(A8="",L8<=0),"",IF(Situation!$B$9="Married Filing Jointly",INDEX(Situation!$A$43:$A$49,MATCH(L8,Situation!$D$43:$D$49,1)),IF(Situation!$B$9="Head of Household",INDEX(Situation!$A$43:$A$49,MATCH(L8,Situation!$F$43:$F$49,1)),INDEX(Situation!$A$43:$A$49,MATCH(L8,Situation!$B$43:$B$49,1))))) -> 0.1 | Q8: Taxable Account | R8: =IF(A8="","",(R7-O8-MAX(0,Situation!$B$12-Situation!$B$10))*(1+Situation!$B$13)) -> -36648.538 | S8: =IF(A8="","",E8*(1-Situation!$B$28)+H8+R8) -> 627321.16
A9: =IF(ROW()-2>=Situation!$B$14,"",Situation!$B$17+(ROW()-2)) -> 2032 | B9: =IF(A9="","",Situation!$B$7+A9-Situation!$B$17) -> 55 | C9: =IF(A9="","",E8) -> 91736.698 | D9: =IF(A9="",0,IF(A9>=Situation!$B$17+Situation!$B$18,0,INDEX(Situation!$B$19:$B$25,MIN(7,A9-Situation!$B$17+1)))) -> 0 | E9: =IF(A9="","",(C9-D9)*(1+Situation!$B$13)) -> 97240.9 | F9: =IF(A9="","",H8) -> 592415.07 | G9: =IF(A9="","",D9) -> 0 | H9: =IF(A9="","",(F9+G9)*(1+Situation!$B$13)) -> 627959.97 | I9: =IF(A9="","",Situation!$B$10) -> 32000 | J9: =IF(A9="","",I9+D9) -> 32000 | K9: =IF(A9="","",IF(Situation!$B$9="Single",15000,IF(Situation!$B$9="Married Filing Jointly",30000,IF(Situation!$B$9="Head of Household",22500,15000)))*(1.02^(A9-Situation!$B$17))) -> 34460.57 | L9: =IF(A9="","",MAX(0,J9-K9)) -> 0 | M9: =IF(A9="","",IF(Situation!$B$9="Married Filing Jointly",IF(L9<=0,0,INDEX(Situation!$E$43:$E$49,MATCH(L9,Situation!$D$43:$D$49,1))+(L9-IF(MATCH(L9,Situation!$D$43:$D$49,1)=1,0,INDEX(Situation!$D$43:$D$49,MATCH(L9,Situation!$D$43:$D$49,1)-1)))*INDEX(Situation!$A$43:$A$49,MATCH(L9,Situation!$D$43:$D$49,1))),IF(Situation!$B$9="Head of Household",IF(L9<=0,0,INDEX(Situation!$G$43:$G$49,MATCH(L9,Situation!$F$43:$F$49,1))+(L9-IF(MATCH(L9,Situation!$F$43:$F$49,1)=1,0,INDEX(Situation!$F$43:$F$49,MATCH(L9,Situation!$F$43:$F$49,1)-1)))*INDEX(Situation!$A$43:$A$49,MATCH(L9,Situation!$F$43:$F$49,1))),IF(L9<=0,0,INDEX(Situation!$C$43:$C$49,MATCH(L9,Situation!$B$43:$B$49,1))+(L9-IF(MATCH(L9,Situation!$B$43:$B$49,1)=1,0,INDEX(Situation!$B$43:$B$49,MATCH(L9,Situation!$B$43:$B$49,1)-1)))*INDEX(Situation!$A$43:$A$49,MATCH(L9,Situation!$B$43:$B$49,1)))))) -> 0 | N9: =IF(A9="","",L9*Situation!$B$11) -> 0 | O9: =IF(A9="","",M9+N9) -> 0 | P9: =IF(OR(A9="",L9<=0),"",IF(Situation!$B$9="Married Filing Jointly",INDEX(Situation!$A$43:$A$49,MATCH(L9,Situation!$D$43:$D$49,1)),IF(Situation!$B$9="Head of Household",INDEX(Situation!$A$43:$A$49,MATCH(L9,Situation!$F$43:$F$49,1)),INDEX(Situation!$A$43:$A$49,MATCH(L9,Situation!$B$43:$B$49,1))))) | Q9: Taxable Account | R9: =IF(A9="","",(R8-O9-MAX(0,Situation!$B$12-Situation!$B$10))*(1+Situation!$B$13)) -> -73827.45 | S9: =IF(A9="","",E9*(1-Situation!$B$28)+H9+R9) -> 629980.43
A10: =IF(ROW()-2>=Situation!$B$14,"",Situation!$B$17+(ROW()-2)) -> 2033 | B10: =IF(A10="","",Situation!$B$7+A10-Situation!$B$17) -> 56 | C10: =IF(A10="","",E9) -> 97240.9 | D10: =IF(A10="",0,IF(A10>=Situation!$B$17+Situation!$B$18,0,INDEX(Situation!$B$19:$B$25,MIN(7,A10-Situation!$B$17+1)))) -> 0 | E10: =IF(A10="","",(C10-D10)*(1+Situation!$B$13)) -> 103075.35 | F10: =IF(A10="","",H9) -> 627959.97 | G10: =IF(A10="","",D10) -> 0 | H10: =IF(A10="","",(F10+G10)*(1+Situation!$B$13)) -> 665637.57 | I10: =IF(A10="","",Situation!$B$10) -> 32000 | J10: =IF(A10="","",I10+D10) -> 32000 | K10: =IF(A10="","",IF(Situation!$B$9="Single",15000,IF(Situation!$B$9="Married Filing Jointly",30000,IF(Situation!$B$9="Head of Household",22500,15000)))*(1.02^(A10-Situation!$B$17))) -> 35149.781 | L10: =IF(A10="","",MAX(0,J10-K10)) -> 0 | M10: =IF(A10="","",IF(Situation!$B$9="Married Filing Jointly",IF(L10<=0,0,INDEX(Situation!$E$43:$E$49,MATCH(L10,Situation!$D$43:$D$49,1))+(L10-IF(MATCH(L10,Situation!$D$43:$D$49,1)=1,0,INDEX(Situation!$D$43:$D$49,MATCH(L10,Situation!$D$43:$D$49,1)-1)))*INDEX(Situation!$A$43:$A$49,MATCH(L10,Situation!$D$43:$D$49,1))),IF(Situation!$B$9="Head of Household",IF(L10<=0,0,INDEX(Situation!$G$43:$G$49,MATCH(L10,Situation!$F$43:$F$49,1))+(L10-IF(MATCH(L10,Situation!$F$43:$F$49,1)=1,0,INDEX(Situation!$F$43:$F$49,MATCH(L10,Situation!$F$43:$F$49,1)-1)))*INDEX(Situation!$A$43:$A$49,MATCH(L10,Situation!$F$43:$F$49,1))),IF(L10<=0,0,INDEX(Situation!$C$43:$C$49,MATCH(L10,Situation!$B$43:$B$49,1))+(L10-IF(MATCH(L10,Situation!$B$43:$B$49,1)=1,0,INDEX(Situation!$B$43:$B$49,MATCH(L10,Situation!$B$43:$B$49,1)-1)))*INDEX(Situation!$A$43:$A$49,MATCH(L10,Situation!$B$43:$B$49,1)))))) -> 0 | N10: =IF(A10="","",L10*Situation!$B$11) -> 0 | O10: =IF(A10="","",M10+N10) -> 0 | P10: =IF(OR(A10="",L10<=0),"",IF(Situation!$B$9="Married Filing Jointly",INDEX(Situation!$A$43:$A$49,MATCH(L10,Situation!$D$43:$D$49,1)),IF(Situation!$B$9="Head of Household",INDEX(Situation!$A$43:$A$49,MATCH(L10,Situation!$F$43:$F$49,1)),INDEX(Situation!$A$43:$A$49,MATCH(L10,Situation!$B$43:$B$49,1))))) | Q10: Taxable Account | R10: =IF(A10="","",(R9-O10-MAX(0,Situation!$B$12-Situation!$B$10))*(1+Situation!$B$13)) -> -113237.1 | S10: =IF(A10="","",E10*(1-Situation!$B$28)+H10+R10) -> 632799.25
A11: =IF(ROW()-2>=Situation!$B$14,"",Situation!$B$17+(ROW()-2)) -> 2034 | B11: =IF(A11="","",Situation!$B$7+A11-Situation!$B$17) -> 57 | C11: =IF(A11="","",E10) -> 103075.35 | D11: =IF(A11="",0,IF(A11>=Situation!$B$17+Situation!$B$18,0,INDEX(Situation!$B$19:$B$25,MIN(7,A11-Situation!$B$17+1)))) -> 0 | E11: =IF(A11="","",(C11-D11)*(1+Situation!$B$13)) -> 109259.88 | F11: =IF(A11="","",H10) -> 665637.57 | G11: =IF(A11="","",D11) -> 0 | H11: =IF(A11="","",(F11+G11)*(1+Situation!$B$13)) -> 705575.83 | I11: =IF(A11="","",Situation!$B$10) -> 32000 | J11: =IF(A11="","",I11+D11) -> 32000 | K11: =IF(A11="","",IF(Situation!$B$9="Single",15000,IF(Situation!$B$9="Married Filing Jointly",30000,IF(Situation!$B$9="Head of Household",22500,15000)))*(1.02^(A11-Situation!$B$17))) -> 35852.777 | L11: =IF(A11="","",MAX(0,J11-K11)) -> 0 | M11: =IF(A11="","",IF(Situation!$B$9="Married Filing Jointly",IF(L11<=0,0,INDEX(Situation!$E$43:$E$49,MATCH(L11,Situation!$D$43:$D$49,1))+(L11-IF(MATCH(L11,Situation!$D$43:$D$49,1)=1,0,INDEX(Situation!$D$43:$D$49,MATCH(L11,Situation!$D$43:$D$49,1)-1)))*INDEX(Situation!$A$43:$A$49,MATCH(L11,Situation!$D$43:$D$49,1))),IF(Situation!$B$9="Head of Household",IF(L11<=0,0,INDEX(Situation!$G$43:$G$49,MATCH(L11,Situation!$F$43:$F$49,1))+(L11-IF(MATCH(L11,Situation!$F$43:$F$49,1)=1,0,INDEX(Situation!$F$43:$F$49,MATCH(L11,Situation!$F$43:$F$49,1)-1)))*INDEX(Situation!$A$43:$A$49,MATCH(L11,Situation!$F$43:$F$49,1))),IF(L11<=0,0,INDEX(Situation!$C$43:$C$49,MATCH(L11,Situation!$B$43:$B$49,1))+(L11-IF(MATCH(L11,Situation!$B$43:$B$49,1)=1,0,INDEX(Situation!$B$43:$B$49,MATCH(L11,Situation!$B$43:$B$49,1)-1)))*INDEX(Situation!$A$43:$A$49,MATCH(L11,Situation!$B$43:$B$49,1)))))) -> 0 | N11: =IF(A11="","",L11*Situation!$B$11) -> 0 | O11: =IF(A11="","",M11+N11) -> 0 | P11: =IF(OR(A11="",L11<=0),"",IF(Situation!$B$9="Married Filing Jointly",INDEX(Situation!$A$43:$A$49,MATCH(L11,Situation!$D$43:$D$49,1)),IF(Situation!$B$9="Head of Household",INDEX(Situation!$A$43:$A$49,MATCH(L11,Situation!$F$43:$F$49,1)),INDEX(Situation!$A$43:$A$49,MATCH(L11,Situation!$B$43:$B$49,1))))) | Q11: Taxable Account | R11: =IF(A11="","",(R10-O11-MAX(0,Situation!$B$12-Situation!$B$10))*(1+Situation!$B$13)) -> -155011.32 | S11: =IF(A11="","",E11*(1-Situation!$B$28)+H11+R11) -> 635787.21
A12: =IF(ROW()-2>=Situation!$B$14,"",Situation!$B$17+(ROW()-2)) -> 2035 | B12: =IF(A12="","",Situation!$B$7+A12-Situation!$B$17) -> 58 | C12: =IF(A12="","",E11) -> 109259.88 | D12: =IF(A12="",0,IF(A12>=Situation!$B$17+Situation!$B$18,0,INDEX(Situation!$B$19:$B$25,MIN(7,A12-Situation!$B$17+1)))) -> 0 | E12: =IF(A12="","",(C12-D12)*(1+Situation!$B$13)) -> 115815.47 | F12: =IF(A12="","",H11) -> 705575.83 | G12: =IF(A12="","",D12) -> 0 | H12: =IF(A12="","",(F12+G12)*(1+Situation!$B$13)) -> 747910.38 | I12: =IF(A12="","",Situation!$B$10) -> 32000 | J12: =IF(A12="","",I12+D12) -> 32000 | K12: =IF(A12="","",IF(Situation!$B$9="Single",15000,IF(Situation!$B$9="Married Filing Jointly",30000,IF(Situation!$B$9="Head of Household",22500,15000)))*(1.02^(A12-Situation!$B$17))) -> 36569.833 | L12: =IF(A12="","",MAX(0,J12-K12)) -> 0 | M12: =IF(A12="","",IF(Situation!$B$9="Married Filing Jointly",IF(L12<=0,0,INDEX(Situation!$E$43:$E$49,MATCH(L12,Situation!$D$43:$D$49,1))+(L12-IF(MATCH(L12,Situation!$D$43:$D$49,1)=1,0,INDEX(Situation!$D$43:$D$49,MATCH(L12,Situation!$D$43:$D$49,1)-1)))*INDEX(Situation!$A$43:$A$49,MATCH(L12,Situation!$D$43:$D$49,1))),IF(Situation!$B$9="Head of Household",IF(L12<=0,0,INDEX(Situation!$G$43:$G$49,MATCH(L12,Situation!$F$43:$F$49,1))+(L12-IF(MATCH(L12,Situation!$F$43:$F$49,1)=1,0,INDEX(Situation!$F$43:$F$49,MATCH(L12,Situation!$F$43:$F$49,1)-1)))*INDEX(Situation!$A$43:$A$49,MATCH(L12,Situation!$F$43:$F$49,1))),IF(L12<=0,0,INDEX(Situation!$C$43:$C$49,MATCH(L12,Situation!$B$43:$B$49,1))+(L12-IF(MATCH(L12,Situation!$B$43:$B$49,1)=1,0,INDEX(Situation!$B$43:$B$49,MATCH(L12,Situation!$B$43:$B$49,1)-1)))*INDEX(Situation!$A$43:$A$49,MATCH(L12,Situation!$B$43:$B$49,1)))))) -> 0 | N12: =IF(A12="","",L12*Situation!$B$11) -> 0 | O12: =IF(A12="","",M12+N12) -> 0 | P12: =IF(OR(A12="",L12<=0),"",IF(Situation!$B$9="Married Filing Jointly",INDEX(Situation!$A$43:$A$49,MATCH(L12,Situation!$D$43:$D$49,1)),IF(Situation!$B$9="Head of Household",INDEX(Situation!$A$43:$A$49,MATCH(L12,Situation!$F$43:$F$49,1)),INDEX(Situation!$A$43:$A$49,MATCH(L12,Situation!$B$43:$B$49,1))))) | Q12: Taxable Account | R12: =IF(A12="","",(R11-O12-MAX(0,Situation!$B$12-Situation!$B$10))*(1+Situation!$B$13)) -> -199292 | S12: =IF(A12="","",E12*(1-Situation!$B$28)+H12+R12) -> 638954.44
A13: =IF(ROW()-2>=Situation!$B$14,"",Situation!$B$17+(ROW()-2)) -> 2036 | B13: =IF(A13="","",Situation!$B$7+A13-Situation!$B$17) -> 59 | C13: =IF(A13="","",E12) -> 115815.47 | D13: =IF(A13="",0,IF(A13>=Situation!$B$17+Situation!$B$18,0,INDEX(Situation!$B$19:$B$25,MIN(7,A13-Situation!$B$17+1)))) -> 0 | E13: =IF(A13="","",(C13-D13)*(1+Situation!$B$13)) -> 122764.4 | F13: =IF(A13="","",H12) -> 747910.38 | G13: =IF(A13="","",D13) -> 0 | H13: =IF(A13="","",(F13+G13)*(1+Situation!$B$13)) -> 792785 | I13: =IF(A13="","",Situation!$B$10) -> 32000 | J13: =IF(A13="","",I13+D13) -> 32000 | K13: =IF(A13="","",IF(Situation!$B$9="Single",15000,IF(Situation!$B$9="Married Filing Jointly",30000,IF(Situation!$B$9="Head of Household",22500,15000)))*(1.02^(A13-Situation!$B$17))) -> 37301.229 | L13: =IF(A13="","",MAX(0,J13-K13)) -> 0 | M13: =IF(A13="","",IF(Situation!$B$9="Married Filing Jointly",IF(L13<=0,0,INDEX(Situation!$E$43:$E$49,MATCH(L13,Situation!$D$43:$D$49,1))+(L13-IF(MATCH(L13,Situation!$D$43:$D$49,1)=1,0,INDEX(Situation!$D$43:$D$49,MATCH(L13,Situation!$D$43:$D$49,1)-1)))*INDEX(Situation!$A$43:$A$49,MATCH(L13,Situation!$D$43:$D$49,1))),IF(Situation!$B$9="Head of Household",IF(L13<=0,0,INDEX(Situation!$G$43:$G$49,MATCH(L13,Situation!$F$43:$F$49,1))+(L13-IF(MATCH(L13,Situation!$F$43:$F$49,1)=1,0,INDEX(Situation!$F$43:$F$49,MATCH(L13,Situation!$F$43:$F$49,1)-1)))*INDEX(Situation!$A$43:$A$49,MATCH(L13,Situation!$F$43:$F$49,1))),IF(L13<=0,0,INDEX(Situation!$C$43:$C$49,MATCH(L13,Situation!$B$43:$B$49,1))+(L13-IF(MATCH(L13,Situation!$B$43:$B$49,1)=1,0,INDEX(Situation!$B$43:$B$49,MATCH(L13,Situation!$B$43:$B$49,1)-1)))*INDEX(Situation!$A$43:$A$49,MATCH(L13,Situation!$B$43:$B$49,1)))))) -> 0 | N13: =IF(A13="","",L13*Situation!$B$11) -> 0 | O13: =IF(A13="","",M13+N13) -> 0 | P13: =IF(OR(A13="",L13<=0),"",IF(Situation!$B$9="Married Filing Jointly",INDEX(Situation!$A$43:$A$49,MATCH(L13,Situation!$D$43:$D$49,1)),IF(Situation!$B$9="Head of Household",INDEX(Situation!$A$43:$A$49,MATCH(L13,Situation!$F$43:$F$49,1)),INDEX(Situation!$A$43:$A$49,MATCH(L13,Situation!$B$43:$B$49,1))))) | Q13: Taxable Account | R13: =IF(A13="","",(R12-O13-MAX(0,Situation!$B$12-Situation!$B$10))*(1+Situation!$B$13)) -> -246229.52 | S13: =IF(A13="","",E13*(1-Situation!$B$28)+H13+R13) -> 642311.71
A14: =IF(ROW()-2>=Situation!$B$14,"",Situation!$B$17+(ROW()-2)) -> 2037 | B14: =IF(A14="","",Situation!$B$7+A14-Situation!$B$17) -> 60 | C14: =IF(A14="","",E13) -> 122764.4 | D14: =IF(A14="",0,IF(A14>=Situation!$B$17+Situation!$B$18,0,INDEX(Situation!$B$19:$B$25,MIN(7,A14-Situation!$B$17+1)))) -> 0 | E14: =IF(A14="","",(C14-D14)*(1+Situation!$B$13)) -> 130130.26 | F14: =IF(A14="","",H13) -> 792785 | G14: =IF(A14="","",D14) -> 0 | H14: =IF(A14="","",(F14+G14)*(1+Situation!$B$13)) -> 840352.1 | I14: =IF(A14="","",Situation!$B$10) -> 32000 | J14: =IF(A14="","",I14+D14) -> 32000 | K14: =IF(A14="","",IF(Situation!$B$9="Single",15000,IF(Situation!$B$9="Married Filing Jointly",30000,IF(Situation!$B$9="Head of Household",22500,15000)))*(1.02^(A14-Situation!$B$17))) -> 38047.254 | L14: =IF(A14="","",MAX(0,J14-K14)) -> 0 | M14: =IF(A14="","",IF(Situation!$B$9="Married Filing Jointly",IF(L14<=0,0,INDEX(Situation!$E$43:$E$49,MATCH(L14,Situation!$D$43:$D$49,1))+(L14-IF(MATCH(L14,Situation!$D$43:$D$49,1)=1,0,INDEX(Situation!$D$43:$D$49,MATCH(L14,Situation!$D$43:$D$49,1)-1)))*INDEX(Situation!$A$43:$A$49,MATCH(L14,Situation!$D$43:$D$49,1))),IF(Situation!$B$9="Head of Household",IF(L14<=0,0,INDEX(Situation!$G$43:$G$49,MATCH(L14,Situation!$F$43:$F$49,1))+(L14-IF(MATCH(L14,Situation!$F$43:$F$49,1)=1,0,INDEX(Situation!$F$43:$F$49,MATCH(L14,Situation!$F$43:$F$49,1)-1)))*INDEX(Situation!$A$43:$A$49,MATCH(L14,Situation!$F$43:$F$49,1))),IF(L14<=0,0,INDEX(Situation!$C$43:$C$49,MATCH(L14,Situation!$B$43:$B$49,1))+(L14-IF(MATCH(L14,Situation!$B$43:$B$49,1)=1,0,INDEX(Situation!$B$43:$B$49,MATCH(L14,Situation!$B$43:$B$49,1)-1)))*INDEX(Situation!$A$43:$A$49,MATCH(L14,Situation!$B$43:$B$49,1)))))) -> 0 | N14: =IF(A14="","",L14*Situation!$B$11) -> 0 | O14: =IF(A14="","",M14+N14) -> 0 | P14: =IF(OR(A14="",L14<=0),"",IF(Situation!$B$9="Married Filing Jointly",INDEX(Situation!$A$43:$A$49,MATCH(L14,Situation!$D$43:$D$49,1)),IF(Situation!$B$9="Head of Household",INDEX(Situation!$A$43:$A$49,MATCH(L14,Situation!$F$43:$F$49,1)),INDEX(Situation!$A$43:$A$49,MATCH(L14,Situation!$B$43:$B$49,1))))) | Q14: Taxable Account | R14: =IF(A14="","",(R13-O14-MAX(0,Situation!$B$12-Situation!$B$10))*(1+Situation!$B$13)) -> -295983.29 | S14: =IF(A14="","",E14*(1-Situation!$B$28)+H14+R14) -> 645870.41
... A16: =IF(ROW()-2>=Situation!$B$14,"",Situation!$B$17+(ROW()-2)) -> 2039 | B16: =IF(A16="","",Situation!$B$7+A16-Situation!$B$17) -> 62 | C16: =IF(A16="","",E15) -> 137938.08 | D16: =IF(A16="",0,IF(A16>=Situation!$B$17+Situation!$B$18,0,INDEX(Situation!$B$19:$B$25,MIN(7,A16-Situation!$B$17+1)))) -> 0 | E16: =IF(A16="","",(C16-D16)*(1+Situation!$B$13)) -> 146214.36 | F16: =IF(A16="","",H15) -> 890773.22 | G16: =IF(A16="","",D16) -> 0 | H16: =IF(A16="","",(F16+G16)*(1+Situation!$B$13)) -> 944219.62 | I16: =IF(A16="","",Situation!$B$10) -> 32000 | J16: =IF(A16="","",I16+D16) -> 32000 | K16: =IF(A16="","",IF(Situation!$B$9="Single",15000,IF(Situation!$B$9="Married Filing Jointly",30000,IF(Situation!$B$9="Head of Household",22500,15000)))*(1.02^(A16-Situation!$B$17))) -> 39584.363 | L16: =IF(A16="","",MAX(0,J16-K16)) -> 0 | M16: =IF(A16="","",IF(Situation!$B$9="Married Filing Jointly",IF(L16<=0,0,INDEX(Situation!$E$43:$E$49,MATCH(L16,Situation!$D$43:$D$49,1))+(L16-IF(MATCH(L16,Situation!$D$43:$D$49,1)=1,0,INDEX(Situation!$D$43:$D$49,MATCH(L16,Situation!$D$43:$D$49,1)-1)))*INDEX(Situation!$A$43:$A$49,MATCH(L16,Situation!$D$43:$D$49,1))),IF(Situation!$B$9="Head of Household",IF(L16<=0,0,INDEX(Situation!$G$43:$G$49,MATCH(L16,Situation!$F$43:$F$49,1))+(L16-IF(MATCH(L16,Situation!$F$43:$F$49,1)=1,0,INDEX(Situation!$F$43:$F$49,MATCH(L16,Situation!$F$43:$F$49,1)-1)))*INDEX(Situation!$A$43:$A$49,MATCH(L16,Situation!$F$43:$F$49,1))),IF(L16<=0,0,INDEX(Situation!$C$43:$C$49,MATCH(L16,Situation!$B$43:$B$49,1))+(L16-IF(MATCH(L16,Situation!$B$43:$B$49,1)=1,0,INDEX(Situation!$B$43:$B$49,MATCH(L16,Situation!$B$43:$B$49,1)-1)))*INDEX(Situation!$A$43:$A$49,MATCH(L16,Situation!$B$43:$B$49,1)))))) -> 0 | N16: =IF(A16="","",L16*Situation!$B$11) -> 0 | O16: =IF(A16="","",M16+N16) -> 0 | P16: =IF(OR(A16="",L16<=0),"",IF(Situation!$B$9="Married Filing Jointly",INDEX(Situation!$A$43:$A$49,MATCH(L16,Situation!$D$43:$D$49,1)),IF(Situation!$B$9="Head of Household",INDEX(Situation!$A$43:$A$49,MATCH(L16,Situation!$F$43:$F$49,1)),INDEX(Situation!$A$43:$A$49,MATCH(L16,Situation!$B$43:$B$49,1))))) | Q16: Taxable Account | R16: =IF(A16="","",(R15-O16-MAX(0,Situation!$B$12-Situation!$B$10))*(1+Situation!$B$13)) -> -404625.63 | S16: =IF(A16="","",E16*(1-Situation!$B$28)+H16+R16) -> 653641.19
P17: =IF(OR(A17="",L17<=0),"",IF(Situation!$B$9="Married Filing Jointly",INDEX(Situation!$A$43:$A$49,MATCH(L17,Situation!$D$43:$D$49,1)),IF(Situation!$B$9="Head of Household",INDEX(Situation!$A$43:$A$49,MATCH(L17,Situation!$F$43:$F$49,1)),INDEX(Situation!$A$43:$A$49,MATCH(L17,Situation!$B$43:$B$49,1)))))
P18: =IF(OR(A18="",L18<=0),"",IF(Situation!$B$9="Married Filing Jointly",INDEX(Situation!$A$43:$A$49,MATCH(L18,Situation!$D$43:$D$49,1)),IF(Situation!$B$9="Head of Household",INDEX(Situation!$A$43:$A$49,MATCH(L18,Situation!$F$43:$F$49,1)),INDEX(Situation!$A$43:$A$49,MATCH(L18,Situation!$B$43:$B$49,1)))))
P19: =IF(OR(A19="",L19<=0),"",IF(Situation!$B$9="Married Filing Jointly",INDEX(Situation!$A$43:$A$49,MATCH(L19,Situation!$D$43:$D$49,1)),IF(Situation!$B$9="Head of Household",INDEX(Situation!$A$43:$A$49,MATCH(L19,Situation!$F$43:$F$49,1)),INDEX(Situation!$A$43:$A$49,MATCH(L19,Situation!$B$43:$B$49,1)))))
P20: =IF(OR(A20="",L20<=0),"",IF(Situation!$B$9="Married Filing Jointly",INDEX(Situation!$A$43:$A$49,MATCH(L20,Situation!$D$43:$D$49,1)),IF(Situation!$B$9="Head of Household",INDEX(Situation!$A$43:$A$49,MATCH(L20,Situation!$F$43:$F$49,1)),INDEX(Situation!$A$43:$A$49,MATCH(L20,Situation!$B$43:$B$49,1)))))
P21: =IF(OR(A21="",L21<=0),"",IF(Situation!$B$9="Married Filing Jointly",INDEX(Situation!$A$43:$A$49,MATCH(L21,Situation!$D$43:$D$49,1)),IF(Situation!$B$9="Head of Household",INDEX(Situation!$A$43:$A$49,MATCH(L21,Situation!$F$43:$F$49,1)),INDEX(Situation!$A$43:$A$49,MATCH(L21,Situation!$B$43:$B$49,1)))))
P22: =IF(OR(A22="",L22<=0),"",IF(Situation!$B$9="Married Filing Jointly",INDEX(Situation!$A$43:$A$49,MATCH(L22,Situation!$D$43:$D$49,1)),IF(Situation!$B$9="Head of Household",INDEX(Situation!$A$43:$A$49,MATCH(L22,Situation!$F$43:$F$49,1)),INDEX(Situation!$A$43:$A$49,MATCH(L22,Situation!$B$43:$B$49,1)))))
P23: =IF(OR(A23="",L23<=0),"",IF(Situation!$B$9="Married Filing Jointly",INDEX(Situation!$A$43:$A$49,MATCH(L23,Situation!$D$43:$D$49,1)),IF(Situation!$B$9="Head of Household",INDEX(Situation!$A$43:$A$49,MATCH(L23,Situation!$F$43:$F$49,1)),INDEX(Situation!$A$43:$A$49,MATCH(L23,Situation!$B$43:$B$49,1)))))
P24: =IF(OR(A24="",L24<=0),"",IF(Situation!$B$9="Married Filing Jointly",INDEX(Situation!$A$43:$A$49,MATCH(L24,Situation!$D$43:$D$49,1)),IF(Situation!$B$9="Head of Household",INDEX(Situation!$A$43:$A$49,MATCH(L24,Situation!$F$43:$F$49,1)),INDEX(Situation!$A$43:$A$49,MATCH(L24,Situation!$B$43:$B$49,1)))))
P25: =IF(OR(A25="",L25<=0),"",IF(Situation!$B$9="Married Filing Jointly",INDEX(Situation!$A$43:$A$49,MATCH(L25,Situation!$D$43:$D$49,1)),IF(Situation!$B$9="Head of Household",INDEX(Situation!$A$43:$A$49,MATCH(L25,Situation!$F$43:$F$49,1)),INDEX(Situation!$A$43:$A$49,MATCH(L25,Situation!$B$43:$B$49,1)))))
P26: =IF(OR(A26="",L26<=0),"",IF(Situation!$B$9="Married Filing Jointly",INDEX(Situation!$A$43:$A$49,MATCH(L26,Situation!$D$43:$D$49,1)),IF(Situation!$B$9="Head of Household",INDEX(Situation!$A$43:$A$49,MATCH(L26,Situation!$F$43:$F$49,1)),INDEX(Situation!$A$43:$A$49,MATCH(L26,Situation!$B$43:$B$49,1)))))
P27: =IF(OR(A27="",L27<=0),"",IF(Situation!$B$9="Married Filing Jointly",INDEX(Situation!$A$43:$A$49,MATCH(L27,Situation!$D$43:$D$49,1)),IF(Situation!$B$9="Head of Household",INDEX(Situation!$A$43:$A$49,MATCH(L27,Situation!$F$43:$F$49,1)),INDEX(Situation!$A$43:$A$49,MATCH(L27,Situation!$B$43:$B$49,1)))))
P28: =IF(OR(A28="",L28<=0),"",IF(Situation!$B$9="Married Filing Jointly",INDEX(Situation!$A$43:$A$49,MATCH(L28,Situation!$D$43:$D$49,1)),IF(Situation!$B$9="Head of Household",INDEX(Situation!$A$43:$A$49,MATCH(L28,Situation!$F$43:$F$49,1)),INDEX(Situation!$A$43:$A$49,MATCH(L28,Situation!$B$43:$B$49,1)))))
... P37: =IF(OR(A37="",L37<=0),"",IF(Situation!$B$9="Married Filing Jointly",INDEX(Situation!$A$43:$A$49,MATCH(L37,Situation!$D$43:$D$49,1)),IF(Situation!$B$9="Head of Household",INDEX(Situation!$A$43:$A$49,MATCH(L37,Situation!$F$43:$F$49,1)),INDEX(Situation!$A$43:$A$49,MATCH(L37,Situation!$B$43:$B$49,1)))))

Sheet 5-Year Rule Tracker
A1: Conversion Year | B1: Amount | C1: Seasoning Start | D1: Penalty-Free Date | E1: Age at PF Date | F1: Penalty-Free? | G1: Avail $ | H1: Cumulative Avail
A2: =IF(0+1>Situation!$B$18,"",Situation!$B$17+0) -> 2025 | B2: =IF(A2="","",INDEX(Situation!$B$19:$B$25,0+1)) -> 50000 | C2: =IF(A2="","",DATE(A2,1,1)) -> 45658 | D2: =IF(A2="","",DATE(A2+5,1,1)) -> 47484 | E2: =IF(A2="","",MAX(Situation!$B$7,IF(ISBLANK(Situation!$B$8),Situation!$B$7,Situation!$B$8))+(A2-Situation!$B$17)+5) -> 53 | F2: =IF(A2="","",IF(TODAY()>=D2,IF(E2>=59.5,"Yes","Yes (check age 59.5)"),"Not Yet")) -> Not Yet | G2: =IF(A2="","",IF(TODAY()>=D2,B2,0)) -> 0 | H2: =IF(A2="","",SUM($G$2:G2)) -> 0
A3: =IF(1+1>Situation!$B$18,"",Situation!$B$17+1) -> 2026 | B3: =IF(A3="","",INDEX(Situation!$B$19:$B$25,1+1)) -> 55000 | C3: =IF(A3="","",DATE(A3,1,1)) -> 46023 | D3: =IF(A3="","",DATE(A3+5,1,1)) -> 47849 | E3: =IF(A3="","",MAX(Situation!$B$7,IF(ISBLANK(Situation!$B$8),Situation!$B$7,Situation!$B$8))+(A3-Situation!$B$17)+5) -> 54 | F3: =IF(A3="","",IF(TODAY()>=D3,IF(E3>=59.5,"Yes","Yes (check age 59.5)"),"Not Yet")) -> Not Yet | G3: =IF(A3="","",IF(TODAY()>=D3,B3,0)) -> 0 | H3: =IF(A3="","",SUM($G$2:G3)) -> 0
A4: =IF(2+1>Situation!$B$18,"",Situation!$B$17+2) -> 2027 | B4: =IF(A4="","",INDEX(Situation!$B$19:$B$25,2+1)) -> 60000 | C4: =IF(A4="","",DATE(A4,1,1)) -> 46388 | D4: =IF(A4="","",DATE(A4+5,1,1)) -> 48214 | E4: =IF(A4="","",MAX(Situation!$B$7,IF(ISBLANK(Situation!$B$8),Situation!$B$7,Situation!$B$8))+(A4-Situation!$B$17)+5) -> 55 | F4: =IF(A4="","",IF(TODAY()>=D4,IF(E4>=59.5,"Yes","Yes (check age 59.5)"),"Not Yet")) -> Not Yet | G4: =IF(A4="","",IF(TODAY()>=D4,B4,0)) -> 0 | H4: =IF(A4="","",SUM($G$2:G4)) -> 0
A5: =IF(3+1>Situation!$B$18,"",Situation!$B$17+3) -> 2028 | B5: =IF(A5="","",INDEX(Situation!$B$19:$B$25,3+1)) -> 62000 | C5: =IF(A5="","",DATE(A5,1,1)) -> 46753 | D5: =IF(A5="","",DATE(A5+5,1,1)) -> 48580 | E5: =IF(A5="","",MAX(Situation!$B$7,IF(ISBLANK(Situation!$B$8),Situation!$B$7,Situation!$B$8))+(A5-Situation!$B$17)+5) -> 56 | F5: =IF(A5="","",IF(TODAY()>=D5,IF(E5>=59.5,"Yes","Yes (check age 59.5)"),"Not Yet")) -> Not Yet | G5: =IF(A5="","",IF(TODAY()>=D5,B5,0)) -> 0 | H5: =IF(A5="","",SUM($G$2:G5)) -> 0
A6: =IF(4+1>Situation!$B$18,"",Situation!$B$17+4) -> 2029 | B6: =IF(A6="","",INDEX(Situation!$B$19:$B$25,4+1)) -> 65000 | C6: =IF(A6="","",DATE(A6,1,1)) -> 47119 | D6: =IF(A6="","",DATE(A6+5,1,1)) -> 48945 | E6: =IF(A6="","",MAX(Situation!$B$7,IF(ISBLANK(Situation!$B$8),Situation!$B$7,Situation!$B$8))+(A6-Situation!$B$17)+5) -> 57 | F6: =IF(A6="","",IF(TODAY()>=D6,IF(E6>=59.5,"Yes","Yes (check age 59.5)"),"Not Yet")) -> Not Yet | G6: =IF(A6="","",IF(TODAY()>=D6,B6,0)) -> 0 | H6: =IF(A6="","",SUM($G$2:G6)) -> 0
A7: =IF(5+1>Situation!$B$18,"",Situation!$B$17+5) -> 2030 | B7: =IF(A7="","",INDEX(Situation!$B$19:$B$25,5+1)) -> 68000 | C7: =IF(A7="","",DATE(A7,1,1)) -> 47484 | D7: =IF(A7="","",DATE(A7+5,1,1)) -> 49310 | E7: =IF(A7="","",MAX(Situation!$B$7,IF(ISBLANK(Situation!$B$8),Situation!$B$7,Situation!$B$8))+(A7-Situation!$B$17)+5) -> 58 | F7: =IF(A7="","",IF(TODAY()>=D7,IF(E7>=59.5,"Yes","Yes (check age 59.5)"),"Not Yet")) -> Not Yet | G7: =IF(A7="","",IF(TODAY()>=D7,B7,0)) -> 0 | H7: =IF(A7="","",SUM($G$2:G7)) -> 0
A8: =IF(6+1>Situation!$B$18,"",Situation!$B$17+6) -> 2031 | B8: =IF(A8="","",INDEX(Situation!$B$19:$B$25,6+1)) -> 70000 | C8: =IF(A8="","",DATE(A8,1,1)) -> 47849 | D8: =IF(A8="","",DATE(A8+5,1,1)) -> 49675 | E8: =IF(A8="","",MAX(Situation!$B$7,IF(ISBLANK(Situation!$B$8),Situation!$B$7,Situation!$B$8))+(A8-Situation!$B$17)+5) -> 59 | F8: =IF(A8="","",IF(TODAY()>=D8,IF(E8>=59.5,"Yes","Yes (check age 59.5)"),"Not Yet")) -> Not Yet | G8: =IF(A8="","",IF(TODAY()>=D8,B8,0)) -> 0 | H8: =IF(A8="","",SUM($G$2:G8)) -> 0

Sheet Convert vs. Don't Convert
A1: Scenario A: Convert (from schedule); NW matches column S (after-tax Trad + Roth + Taxable)
A2: Year | B2: Trad IRA | C2: Roth IRA | D2: Taxable | E2: Taxes Paid YTD | F2: Net Worth | G2: NW vs don't
A3: ='Conversion Schedule'!A2 -> 2025 | B3: ='Conversion Schedule'!E2 -> 392200 | C3: ='Conversion Schedule'!H2 -> 90100 | D3: ='Conversion Schedule'!R2 -> 195252 | E3: =SUM('Conversion Schedule'!$O$2:O2) -> 7800 | F3: ='Conversion Schedule'!S2 -> 591268 | G3: =IF(OR(A3="",OFFSET($A$40,ROW()-3,0)=""),"",F3-OFFSET($F$40,ROW()-3,0)) -> 3392
A4: ='Conversion Schedule'!A3 -> 2026 | B4: ='Conversion Schedule'!E3 -> 357432 | C4: ='Conversion Schedule'!H3 -> 153806 | D4: ='Conversion Schedule'!R3 -> 163019.52 | E4: =SUM('Conversion Schedule'!$O$2:O3) -> 16260 | F4: ='Conversion Schedule'!S3 -> 595622.48 | G4: =IF(OR(A4="",OFFSET($A$40,ROW()-3,0)=""),"",F4-OFFSET($F$40,ROW()-3,0)) -> 7453.92
A5: ='Conversion Schedule'!A4 -> 2027 | B5: ='Conversion Schedule'!E4 -> 315277.92 | C5: ='Conversion Schedule'!H4 -> 226634.36 | D5: ='Conversion Schedule'!R4 -> 128155.4 | E5: =SUM('Conversion Schedule'!$O$2:O4) -> 25378.2 | F5: ='Conversion Schedule'!S4 -> 600706.54 | G5: =IF(OR(A5="",OFFSET($A$40,ROW()-3,0)=""),"",F5-OFFSET($F$40,ROW()-3,0)) -> 12227.863
A6: ='Conversion Schedule'!A5 -> 2028 | B6: ='Conversion Schedule'!E5 -> 268474.6 | C6: ='Conversion Schedule'!H5 -> 305952.42 | D6: ='Conversion Schedule'!R5 -> 90980.685 | E6: =SUM('Conversion Schedule'!$O$2:O5) -> 34702.764 | F6: ='Conversion Schedule'!S5 -> 606343.29 | G6: =IF(OR(A6="",OFFSET($A$40,ROW()-3,0)=""),"",F6-OFFSET($F$40,ROW()-3,0)) -> 17535.897
A7: ='Conversion Schedule'!A6 -> 2029 | B7: ='Conversion Schedule'!E6 -> 215683.07 | C7: ='Conversion Schedule'!H6 -> 393209.57 | D7: ='Conversion Schedule'!R6 -> 51199.728 | E7: =SUM('Conversion Schedule'!$O$2:O6) -> 44381.819 | F7: ='Conversion Schedule'!S6 -> 612642.09 | G7: =IF(OR(A7="",OFFSET($A$40,ROW()-3,0)=""),"",F7-OFFSET($F$40,ROW()-3,0)) -> 23486.252
A8: ='Conversion Schedule'!A7 -> 2030 | B8: ='Conversion Schedule'!E7 -> 156544.06 | C8: ='Conversion Schedule'!H7 -> 488882.14 | D8: ='Conversion Schedule'!R7 -> 8658.1769 | E8: =SUM('Conversion Schedule'!$O$2:O7) -> 54413.456 | F8: ='Conversion Schedule'!S7 -> 619644.68 | G8: =IF(OR(A8="",OFFSET($A$40,ROW()-3,0)=""),"",F8-OFFSET($F$40,ROW()-3,0)) -> 30119.493
A9: ='Conversion Schedule'!A8 -> 2031 | B9: ='Conversion Schedule'!E8 -> 91736.698 | C9: ='Conversion Schedule'!H8 -> 592415.07 | D9: ='Conversion Schedule'!R8 -> -36648.538 | E9: =SUM('Conversion Schedule'!$O$2:O8) -> 64645.725 | F9: ='Conversion Schedule'!S8 -> 627321.16 | G9: =IF(OR(A9="",OFFSET($A$40,ROW()-3,0)=""),"",F9-OFFSET($F$40,ROW()-3,0)) -> 37404.457
A10: ='Conversion Schedule'!A9 -> 2032 | B10: ='Conversion Schedule'!E9 -> 97240.9 | C10: ='Conversion Schedule'!H9 -> 627959.97 | D10: ='Conversion Schedule'!R9 -> -73827.45 | E10: =SUM('Conversion Schedule'!$O$2:O9) -> 64645.725 | F10: ='Conversion Schedule'!S9 -> 629980.43 | G10: =IF(OR(A10="",OFFSET($A$40,ROW()-3,0)=""),"",F10-OFFSET($F$40,ROW()-3,0)) -> 39648.725
A11: ='Conversion Schedule'!A10 -> 2033 | B11: ='Conversion Schedule'!E10 -> 103075.35 | C11: ='Conversion Schedule'!H10 -> 665637.57 | D11: ='Conversion Schedule'!R10 -> -113237.1 | E11: =SUM('Conversion Schedule'!$O$2:O10) -> 64645.725 | F11: ='Conversion Schedule'!S10 -> 632799.25 | G11: =IF(OR(A11="",OFFSET($A$40,ROW()-3,0)=""),"",F11-OFFSET($F$40,ROW()-3,0)) -> 42027.648
A12: ='Conversion Schedule'!A11 -> 2034 | B12: ='Conversion Schedule'!E11 -> 109259.88 | C12: ='Conversion Schedule'!H11 -> 705575.83 | D12: ='Conversion Schedule'!R11 -> -155011.32 | E12: =SUM('Conversion Schedule'!$O$2:O11) -> 64645.725 | F12: ='Conversion Schedule'!S11 -> 635787.21 | G12: =IF(OR(A12="",OFFSET($A$40,ROW()-3,0)=""),"",F12-OFFSET($F$40,ROW()-3,0)) -> 44549.307
A13: ='Conversion Schedule'!A12 -> 2035 | B13: ='Conversion Schedule'!E12 -> 115815.47 | C13: ='Conversion Schedule'!H12 -> 747910.38 | D13: ='Conversion Schedule'!R12 -> -199292 | E13: =SUM('Conversion Schedule'!$O$2:O12) -> 64645.725 | F13: ='Conversion Schedule'!S12 -> 638954.44 | G13: =IF(OR(A13="",OFFSET($A$40,ROW()-3,0)=""),"",F13-OFFSET($F$40,ROW()-3,0)) -> 47222.266
A14: ='Conversion Schedule'!A13 -> 2036 | B14: ='Conversion Schedule'!E13 -> 122764.4 | C14: ='Conversion Schedule'!H13 -> 792785 | D14: ='Conversion Schedule'!R13 -> -246229.52 | E14: =SUM('Conversion Schedule'!$O$2:O13) -> 64645.725 | F14: ='Conversion Schedule'!S13 -> 642311.71 | G14: =IF(OR(A14="",OFFSET($A$40,ROW()-3,0)=""),"",F14-OFFSET($F$40,ROW()-3,0)) -> 50055.601
... A37: ='Conversion Schedule'!A36 -> 0 | B37: ='Conversion Schedule'!E36 -> 0 | C37: ='Conversion Schedule'!H36 -> 0 | D37: ='Conversion Schedule'!R36 -> 0 | E37: =SUM('Conversion Schedule'!$O$2:O36) -> 64645.725 | F37: ='Conversion Schedule'!S36 -> 0 | G37: =IF(OR(A37="",OFFSET($A$40,ROW()-3,0)=""),"",F37-OFFSET($F$40,ROW()-3,0)) -> -618356
A38: Scenario B: Don't convert
A39: Year | B39: Trad IRA | C39: Roth IRA | D39: Taxable | E39: Taxes Paid YTD | F39: Net Worth (after-tax Trad)
A40: ='Conversion Schedule'!A2 -> 2025 | B40: =Situation!$B$1*(1+Situation!$B$13) -> 445200 | C40: =Situation!$B$2*(1+Situation!$B$13) -> 37100 | D40: =(Situation!$B$3+Situation!$B$4-MAX(0,Situation!$B$12-Situation!$B$10))*(1+Situation!$B$13) -> 203520 | E40: 0 | F40: =B40*(1-Situation!$B$28)+C40+D40 -> 587876
A41: ='Conversion Schedule'!A3 -> 2026 | B41: =B40*(1+Situation!$B$13) -> 471912 | C41: =C40*(1+Situation!$B$13) -> 39326 | D41: =(D40-MAX(0,Situation!$B$12-Situation!$B$10))*(1+Situation!$B$13) -> 180751.2 | E41: 0 | F41: =B41*(1-Situation!$B$28)+C41+D41 -> 588168.56
A42: ='Conversion Schedule'!A4 -> 2027 | B42: =B41*(1+Situation!$B$13) -> 500226.72 | C42: =C41*(1+Situation!$B$13) -> 41685.56 | D42: =(D41-MAX(0,Situation!$B$12-Situation!$B$10))*(1+Situation!$B$13) -> 156616.27 | E42: 0 | F42: =B42*(1-Situation!$B$28)+C42+D42 -> 588478.67
A43: ='Conversion Schedule'!A5 -> 2028 | B43: =B42*(1+Situation!$B$13) -> 530240.32 | C43: =C42*(1+Situation!$B$13) -> 44186.694 | D43: =(D42-MAX(0,Situation!$B$12-Situation!$B$10))*(1+Situation!$B$13) -> 131033.25 | E43: 0 | F43: =B43*(1-Situation!$B$28)+C43+D43 -> 588807.39
A44: ='Conversion Schedule'!A6 -> 2029 | B44: =B43*(1+Situation!$B$13) -> 562054.74 | C44: =C43*(1+Situation!$B$13) -> 46837.895 | D44: =(D43-MAX(0,Situation!$B$12-Situation!$B$10))*(1+Situation!$B$13) -> 103915.24 | E44: 0 | F44: =B44*(1-Situation!$B$28)+C44+D44 -> 589155.84
A45: ='Conversion Schedule'!A7 -> 2030 | B45: =B44*(1+Situation!$B$13) -> 595778.03 | C45: =C44*(1+Situation!$B$13) -> 49648.169 | D45: =(D44-MAX(0,Situation!$B$12-Situation!$B$10))*(1+Situation!$B$13) -> 75170.158 | E45: 0 | F45: =B45*(1-Situation!$B$28)+C45+D45 -> 589525.19
A46: ='Conversion Schedule'!A8 -> 2031 | B46: =B45*(1+Situation!$B$13) -> 631524.71 | C46: =C45*(1+Situation!$B$13) -> 52627.059 | D46: =(D45-MAX(0,Situation!$B$12-Situation!$B$10))*(1+Situation!$B$13) -> 44700.367 | E46: 0 | F46: =B46*(1-Situation!$B$28)+C46+D46 -> 589916.7
A47: ='Conversion Schedule'!A9 -> 2032 | B47: =B46*(1+Situation!$B$13) -> 669416.19 | C47: =C46*(1+Situation!$B$13) -> 55784.683 | D47: =(D46-MAX(0,Situation!$B$12-Situation!$B$10))*(1+Situation!$B$13) -> 12402.389 | E47: 0 | F47: =B47*(1-Situation!$B$28)+C47+D47 -> 590331.7
A48: ='Conversion Schedule'!A10 -> 2033 | B48: =B47*(1+Situation!$B$13) -> 709581.16 | C48: =C47*(1+Situation!$B$13) -> 59131.764 | D48: =(D47-MAX(0,Situation!$B$12-Situation!$B$10))*(1+Situation!$B$13) -> -21833.467 | E48: 0 | F48: =B48*(1-Situation!$B$28)+C48+D48 -> 590771.6
A49: ='Conversion Schedule'!A11 -> 2034 | B49: =B48*(1+Situation!$B$13) -> 752156.03 | C49: =C48*(1+Situation!$B$13) -> 62679.669 | D49: =(D48-MAX(0,Situation!$B$12-Situation!$B$10))*(1+Situation!$B$13) -> -58123.475 | E49: 0 | F49: =B49*(1-Situation!$B$28)+C49+D49 -> 591237.9
A50: ='Conversion Schedule'!A12 -> 2035 | B50: =B49*(1+Situation!$B$13) -> 797285.39 | C50: =C49*(1+Situation!$B$13) -> 66440.45 | D50: =(D49-MAX(0,Situation!$B$12-Situation!$B$10))*(1+Situation!$B$13) -> -96590.884 | E50: 0 | F50: =B50*(1-Situation!$B$28)+C50+D50 -> 591732.17
A51: ='Conversion Schedule'!A13 -> 2036 | B51: =B50*(1+Situation!$B$13) -> 845122.52 | C51: =C50*(1+Situation!$B$13) -> 70426.877 | D51: =(D50-MAX(0,Situation!$B$12-Situation!$B$10))*(1+Situation!$B$13) -> -137366.34 | E51: 0 | F51: =B51*(1-Situation!$B$28)+C51+D51 -> 592256.1
A52: ='Conversion Schedule'!A14 -> 2037 | B52: =B51*(1+Situation!$B$13) -> 895829.87 | C52: =C51*(1+Situation!$B$13) -> 74652.489 | D52: =(D51-MAX(0,Situation!$B$12-Situation!$B$10))*(1+Situation!$B$13) -> -180588.32 | E52: 0 | F52: =B52*(1-Situation!$B$28)+C52+D52 -> 592811.47
... A74: ='Conversion Schedule'!A36 -> 0 | B74: =B73*(1+Situation!$B$13) -> 3228156.5 | C74: =C73*(1+Situation!$B$13) -> 269013.04 | D74: =(D73-MAX(0,Situation!$B$12-Situation!$B$10))*(1+Situation!$B$13) -> -2168619.1 | E74: 0 | F74: =B74*(1-Situation!$B$28)+C74+D74 -> 618356
A76: Summary
A77: Total taxes paid (horizon) | B77: =E37 -> 64645.725 | C77: 0
A78: Ending NW (convert) | B78: =F37 -> 0
A79: Ending NW (don't) | B79: =F74 -> 618356
A80: Break-even year (convert NW >= don't) | B80: =IFERROR(_xlfn.SINGLE(_xlfn.MINIFS(A3:A37,A3:A37,">2000",G3:G37,">=0")),"-") -> 2025

Sheet What-If Scenarios
A1: What-If: bracket caps vs your plan
A3: Scenario | B3: Conv / yr | C3: Est total taxes (window) | D3: Ending NW | E3: Break-even year
A4: A: Aggressive (fill 22%) | B4: =MAX(0,IF(Situation!$B$9="Married Filing Jointly",Situation!$D$45,IF(Situation!$B$9="Head of Household",Situation!$F$45,Situation!$B$45))+IF(Situation!$B$9="Married Filing Jointly",30000,IF(Situation!$B$9="Head of Household",22500,15000))-Situation!$B$10) -> 204700 | D4: N/A (mirror B4 into B21:B27) | E4: N/A
A5: B: Moderate (your plan avg) | B5: =SUM(Situation!$B$19:$B$25)/Situation!$B$18 -> 61428.571 | D5: ='Convert vs. Don''t Convert'!F37 -> 0 | E5: ='Convert vs. Don''t Convert'!B80 -> 2025
A6: C: Conservative (fill 12%) | B6: =MAX(0,IF(Situation!$B$9="Married Filing Jointly",Situation!$D$44,IF(Situation!$B$9="Head of Household",Situation!$F$44,Situation!$B$44))+IF(Situation!$B$9="Married Filing Jointly",30000,IF(Situation!$B$9="Head of Household",22500,15000))-Situation!$B$10) -> 94950 | D6: N/A (mirror B6 into B21:B27) | E6: N/A
A7: D: No conversion | B7: 0 | C7: 0 | D7: ='Convert vs. Don''t Convert'!F74 -> 618356 | E7: N/A
