Workbook

Sheet Facility Overview
A1: Storage deal scratch
A2: Property Details | H2: Check first
A3: Facility Name | B3: Northgate Storage | H3: Year 1 NOI | I3: ='5-Year Projection'!B10
A4: Market | B4: Columbus, OH | H4: Year 1 DSCR | I4: ='5-Year Projection'!B13
A5: Property Class | B5: Drive-Up + Climate | H5: Year 1 CF After Debt | I5: ='5-Year Projection'!B12
A6: Total Units | B6: =SUM('Unit Mix & Lease-Up'!C3:C8) | H6: Stabilized Yield on Cost | I6: ='Returns & Snapshot'!B10
A7: Total Rentable SqFt | B7: =SUM('Unit Mix & Lease-Up'!E3:E8) | H7: 5-Year Sale Proceeds | I7: ='Returns & Snapshot'!B18
A8: Current Occupancy | B8: =IF(B6=0,0,SUM('Unit Mix & Lease-Up'!F3:F8)/B6) | H8: Equity Multiple | I8: ='Returns & Snapshot'!B23
A9: Stabilized Occupancy Target | B9: 0.92 | H9: Levered IRR | I9: ='Returns & Snapshot'!B24
A10: Avg Current Rent / Occupied Unit | B10: =IF(SUM('Unit Mix & Lease-Up'!F3:F8)=0,0,SUM('Unit Mix & Lease-Up'!K3:K8)/SUM('Unit Mix & Lease-Up'!F3:F8))
A11: Avg Market Rent / Occupied Unit | B11: =IF(SUM('Unit Mix & Lease-Up'!J3:J8)=0,0,SUM('Unit Mix & Lease-Up'!L3:L8)/SUM('Unit Mix & Lease-Up'!J3:J8)) | H11: Scratch note
H12: Lease-up is the swing here.
A13: Acquisition | H13: Exit cap is just a rough look.
A14: Purchase Price | B14: 2450000
A15: Closing Costs | B15: 42000
A16: Immediate CapEx | B16: 85000
A17: Total Basis | B17: =B14+B15+B16
A18: Going-In Cap Rate | B18: =IF(B14=0,0,'5-Year Projection'!B10/B14)
A20: Financing
A21: Down Payment (%) | B21: 0.3
A22: Down Payment ($) | B22: =B14*B21
A23: Loan Amount | B23: =B14-B22
A24: Interest Rate | B24: 0.0685
A25: Loan Term (years) | B25: 25
A26: Monthly Debt Service | B26: =IF(B23=0,0,PMT(B24/12,B25*12,-B23))
A27: Annual Debt Service | B27: =B26*12
A29: Lease-Up / Revenue Assumptions
A30: Monthly Move-Ins | B30: 7
A31: Monthly Move-Out Rate | B31: 0.015
A32: Annual Rent Growth | B32: 0.03
A33: Ancillary Income / Occupied Unit / Month | B33: 9
A34: Bad Debt / Promo Loss (%) | B34: 0.02
A35: Exit Cap Rate | B35: 0.0675
A36: Selling Costs (%) | B36: 0.03
A37: Hold Period (years) | B37: 5

Sheet Unit Mix & Lease-Up
A1: Unit Mix
A2: Unit Type | B2: Size Label | C2: Units | D2: SqFt / Unit | E2: Total SqFt | F2: Current Occupied Units | G2: Current Occ % | H2: Current Avg Rent / Unit | I2: Market Rent / Unit | J2: Stabilized Occupied Units | K2: Current Monthly Gross | L2: Stabilized Monthly Gross | M2: Rent Lift % | O2: Unit Mix Summary
A3: 5x5 | B3: Small | C3: 40 | D3: 25 | E3: =C3*D3 | F3: 31 | G3: =IF(C3=0,0,F3/C3) | H3: 42 | I3: 48 | J3: =ROUND(C3*'Facility Overview'!$B$9,0) | K3: =F3*H3 | L3: =J3*I3 | M3: =IF(H3=0,0,I3/H3-1) | O3: Current occupied units | P3: =SUM(F3:F8)
A4: 5x10 | B4: Small | C4: 55 | D4: 50 | E4: =C4*D4 | F4: 44 | G4: =IF(C4=0,0,F4/C4) | H4: 62 | I4: 69 | J4: =ROUND(C4*'Facility Overview'!$B$9,0) | K4: =F4*H4 | L4: =J4*I4 | M4: =IF(H4=0,0,I4/H4-1) | O4: Current monthly gross | P4: =SUM(K3:K8)
A5: 10x10 | B5: Medium | C5: 64 | D5: 100 | E5: =C5*D5 | F5: 50 | G5: =IF(C5=0,0,F5/C5) | H5: 88 | I5: 97 | J5: =ROUND(C5*'Facility Overview'!$B$9,0) | K5: =F5*H5 | L5: =J5*I5 | M5: =IF(H5=0,0,I5/H5-1) | O5: Stabilized monthly gross | P5: =SUM(L3:L8)
A6: 10x15 | B6: Large | C6: 28 | D6: 150 | E6: =C6*D6 | F6: 18 | G6: =IF(C6=0,0,F6/C6) | H6: 112 | I6: 126 | J6: =ROUND(C6*'Facility Overview'!$B$9,0) | K6: =F6*H6 | L6: =J6*I6 | M6: =IF(H6=0,0,I6/H6-1) | O6: Lease-up month hit | P6: =IFERROR(MINIFS(A17:A40,F17:F40,">="&'Facility Overview'!$B$9),"")
A7: 10x20 | B7: Large | C7: 18 | D7: 200 | E7: =C7*D7 | F7: 11 | G7: =IF(C7=0,0,F7/C7) | H7: 156 | I7: 176 | J7: =ROUND(C7*'Facility Overview'!$B$9,0) | K7: =F7*H7 | L7: =J7*I7 | M7: =IF(H7=0,0,I7/H7-1) | O7: Avg month 1-12 EGI | P7: =AVERAGE(L17:L28)
A8: Parking / RV | B8: Parking | C8: 14 | D8: 300 | E8: =C8*D8 | F8: 8 | G8: =IF(C8=0,0,F8/C8) | H8: 84 | I8: 95 | J8: =ROUND(C8*'Facility Overview'!$B$9,0) | K8: =F8*H8 | L8: =J8*I8 | M8: =IF(H8=0,0,I8/H8-1)
A15: 24-Month Lease-Up
A16: Month # | B16: Beginning Occupied Units | C16: Move-Ins | D16: Move-Outs | E16: Ending Occupied Units | F16: Occupancy % | G16: Avg Rent / Occupied Unit | H16: Storage Rent Revenue | I16: Ancillary Income | J16: Gross Revenue | K16: Bad Debt / Promo Loss | L16: Effective Gross Revenue
A17: 1 | B17: =SUM(F3:F8) | C17: =MIN('Facility Overview'!$B$30,'Facility Overview'!$B$6-B17) | D17: =ROUND(B17*'Facility Overview'!$B$31,0) | E17: =MAX(0,MIN('Facility Overview'!$B$6,B17+C17-D17)) | F17: =IF('Facility Overview'!$B$6=0,0,E17/'Facility Overview'!$B$6) | G17: =('Facility Overview'!$B$10+(MIN(A17,24)/24)*('Facility Overview'!$B$11-'Facility Overview'!$B$10))*(1+'Facility Overview'!$B$32/12)^(A17-1) | H17: =E17*G17 | I17: =E17*'Facility Overview'!$B$33 | J17: =H17+I17 | K17: =J17*'Facility Overview'!$B$34*-1 | L17: =J17+K17
A18: 2 | B18: =E17 | C18: =MIN('Facility Overview'!$B$30,'Facility Overview'!$B$6-B18) | D18: =ROUND(B18*'Facility Overview'!$B$31,0) | E18: =MAX(0,MIN('Facility Overview'!$B$6,B18+C18-D18)) | F18: =IF('Facility Overview'!$B$6=0,0,E18/'Facility Overview'!$B$6) | G18: =('Facility Overview'!$B$10+(MIN(A18,24)/24)*('Facility Overview'!$B$11-'Facility Overview'!$B$10))*(1+'Facility Overview'!$B$32/12)^(A18-1) | H18: =E18*G18 | I18: =E18*'Facility Overview'!$B$33 | J18: =H18+I18 | K18: =J18*'Facility Overview'!$B$34*-1 | L18: =J18+K18
A19: 3 | B19: =E18 | C19: =MIN('Facility Overview'!$B$30,'Facility Overview'!$B$6-B19) | D19: =ROUND(B19*'Facility Overview'!$B$31,0) | E19: =MAX(0,MIN('Facility Overview'!$B$6,B19+C19-D19)) | F19: =IF('Facility Overview'!$B$6=0,0,E19/'Facility Overview'!$B$6) | G19: =('Facility Overview'!$B$10+(MIN(A19,24)/24)*('Facility Overview'!$B$11-'Facility Overview'!$B$10))*(1+'Facility Overview'!$B$32/12)^(A19-1) | H19: =E19*G19 | I19: =E19*'Facility Overview'!$B$33 | J19: =H19+I19 | K19: =J19*'Facility Overview'!$B$34*-1 | L19: =J19+K19
A20: 4 | B20: =E19 | C20: =MIN('Facility Overview'!$B$30,'Facility Overview'!$B$6-B20) | D20: =ROUND(B20*'Facility Overview'!$B$31,0) | E20: =MAX(0,MIN('Facility Overview'!$B$6,B20+C20-D20)) | F20: =IF('Facility Overview'!$B$6=0,0,E20/'Facility Overview'!$B$6) | G20: =('Facility Overview'!$B$10+(MIN(A20,24)/24)*('Facility Overview'!$B$11-'Facility Overview'!$B$10))*(1+'Facility Overview'!$B$32/12)^(A20-1) | H20: =E20*G20 | I20: =E20*'Facility Overview'!$B$33 | J20: =H20+I20 | K20: =J20*'Facility Overview'!$B$34*-1 | L20: =J20+K20
A21: 5 | B21: =E20 | C21: =MIN('Facility Overview'!$B$30,'Facility Overview'!$B$6-B21) | D21: =ROUND(B21*'Facility Overview'!$B$31,0) | E21: =MAX(0,MIN('Facility Overview'!$B$6,B21+C21-D21)) | F21: =IF('Facility Overview'!$B$6=0,0,E21/'Facility Overview'!$B$6) | G21: =('Facility Overview'!$B$10+(MIN(A21,24)/24)*('Facility Overview'!$B$11-'Facility Overview'!$B$10))*(1+'Facility Overview'!$B$32/12)^(A21-1) | H21: =E21*G21 | I21: =E21*'Facility Overview'!$B$33 | J21: =H21+I21 | K21: =J21*'Facility Overview'!$B$34*-1 | L21: =J21+K21
A22: 6 | B22: =E21 | C22: =MIN('Facility Overview'!$B$30,'Facility Overview'!$B$6-B22) | D22: =ROUND(B22*'Facility Overview'!$B$31,0) | E22: =MAX(0,MIN('Facility Overview'!$B$6,B22+C22-D22)) | F22: =IF('Facility Overview'!$B$6=0,0,E22/'Facility Overview'!$B$6) | G22: =('Facility Overview'!$B$10+(MIN(A22,24)/24)*('Facility Overview'!$B$11-'Facility Overview'!$B$10))*(1+'Facility Overview'!$B$32/12)^(A22-1) | H22: =E22*G22 | I22: =E22*'Facility Overview'!$B$33 | J22: =H22+I22 | K22: =J22*'Facility Overview'!$B$34*-1 | L22: =J22+K22
A23: 7 | B23: =E22 | C23: =MIN('Facility Overview'!$B$30,'Facility Overview'!$B$6-B23) | D23: =ROUND(B23*'Facility Overview'!$B$31,0) | E23: =MAX(0,MIN('Facility Overview'!$B$6,B23+C23-D23)) | F23: =IF('Facility Overview'!$B$6=0,0,E23/'Facility Overview'!$B$6) | G23: =('Facility Overview'!$B$10+(MIN(A23,24)/24)*('Facility Overview'!$B$11-'Facility Overview'!$B$10))*(1+'Facility Overview'!$B$32/12)^(A23-1) | H23: =E23*G23 | I23: =E23*'Facility Overview'!$B$33 | J23: =H23+I23 | K23: =J23*'Facility Overview'!$B$34*-1 | L23: =J23+K23
A24: 8 | B24: =E23 | C24: =MIN('Facility Overview'!$B$30,'Facility Overview'!$B$6-B24) | D24: =ROUND(B24*'Facility Overview'!$B$31,0) | E24: =MAX(0,MIN('Facility Overview'!$B$6,B24+C24-D24)) | F24: =IF('Facility Overview'!$B$6=0,0,E24/'Facility Overview'!$B$6) | G24: =('Facility Overview'!$B$10+(MIN(A24,24)/24)*('Facility Overview'!$B$11-'Facility Overview'!$B$10))*(1+'Facility Overview'!$B$32/12)^(A24-1) | H24: =E24*G24 | I24: =E24*'Facility Overview'!$B$33 | J24: =H24+I24 | K24: =J24*'Facility Overview'!$B$34*-1 | L24: =J24+K24
A25: 9 | B25: =E24 | C25: =MIN('Facility Overview'!$B$30,'Facility Overview'!$B$6-B25) | D25: =ROUND(B25*'Facility Overview'!$B$31,0) | E25: =MAX(0,MIN('Facility Overview'!$B$6,B25+C25-D25)) | F25: =IF('Facility Overview'!$B$6=0,0,E25/'Facility Overview'!$B$6) | G25: =('Facility Overview'!$B$10+(MIN(A25,24)/24)*('Facility Overview'!$B$11-'Facility Overview'!$B$10))*(1+'Facility Overview'!$B$32/12)^(A25-1) | H25: =E25*G25 | I25: =E25*'Facility Overview'!$B$33 | J25: =H25+I25 | K25: =J25*'Facility Overview'!$B$34*-1 | L25: =J25+K25
A26: 10 | B26: =E25 | C26: =MIN('Facility Overview'!$B$30,'Facility Overview'!$B$6-B26) | D26: =ROUND(B26*'Facility Overview'!$B$31,0) | E26: =MAX(0,MIN('Facility Overview'!$B$6,B26+C26-D26)) | F26: =IF('Facility Overview'!$B$6=0,0,E26/'Facility Overview'!$B$6) | G26: =('Facility Overview'!$B$10+(MIN(A26,24)/24)*('Facility Overview'!$B$11-'Facility Overview'!$B$10))*(1+'Facility Overview'!$B$32/12)^(A26-1) | H26: =E26*G26 | I26: =E26*'Facility Overview'!$B$33 | J26: =H26+I26 | K26: =J26*'Facility Overview'!$B$34*-1 | L26: =J26+K26
A27: 11 | B27: =E26 | C27: =MIN('Facility Overview'!$B$30,'Facility Overview'!$B$6-B27) | D27: =ROUND(B27*'Facility Overview'!$B$31,0) | E27: =MAX(0,MIN('Facility Overview'!$B$6,B27+C27-D27)) | F27: =IF('Facility Overview'!$B$6=0,0,E27/'Facility Overview'!$B$6) | G27: =('Facility Overview'!$B$10+(MIN(A27,24)/24)*('Facility Overview'!$B$11-'Facility Overview'!$B$10))*(1+'Facility Overview'!$B$32/12)^(A27-1) | H27: =E27*G27 | I27: =E27*'Facility Overview'!$B$33 | J27: =H27+I27 | K27: =J27*'Facility Overview'!$B$34*-1 | L27: =J27+K27
A28: 12 | B28: =E27 | C28: =MIN('Facility Overview'!$B$30,'Facility Overview'!$B$6-B28) | D28: =ROUND(B28*'Facility Overview'!$B$31,0) | E28: =MAX(0,MIN('Facility Overview'!$B$6,B28+C28-D28)) | F28: =IF('Facility Overview'!$B$6=0,0,E28/'Facility Overview'!$B$6) | G28: =('Facility Overview'!$B$10+(MIN(A28,24)/24)*('Facility Overview'!$B$11-'Facility Overview'!$B$10))*(1+'Facility Overview'!$B$32/12)^(A28-1) | H28: =E28*G28 | I28: =E28*'Facility Overview'!$B$33 | J28: =H28+I28 | K28: =J28*'Facility Overview'!$B$34*-1 | L28: =J28+K28
A29: 13 | B29: =E28 | C29: =MIN('Facility Overview'!$B$30,'Facility Overview'!$B$6-B29) | D29: =ROUND(B29*'Facility Overview'!$B$31,0) | E29: =MAX(0,MIN('Facility Overview'!$B$6,B29+C29-D29)) | F29: =IF('Facility Overview'!$B$6=0,0,E29/'Facility Overview'!$B$6) | G29: =('Facility Overview'!$B$10+(MIN(A29,24)/24)*('Facility Overview'!$B$11-'Facility Overview'!$B$10))*(1+'Facility Overview'!$B$32/12)^(A29-1) | H29: =E29*G29 | I29: =E29*'Facility Overview'!$B$33 | J29: =H29+I29 | K29: =J29*'Facility Overview'!$B$34*-1 | L29: =J29+K29
... A40: 24 | B40: =E39 | C40: =MIN('Facility Overview'!$B$30,'Facility Overview'!$B$6-B40) | D40: =ROUND(B40*'Facility Overview'!$B$31,0) | E40: =MAX(0,MIN('Facility Overview'!$B$6,B40+C40-D40)) | F40: =IF('Facility Overview'!$B$6=0,0,E40/'Facility Overview'!$B$6) | G40: =('Facility Overview'!$B$10+(MIN(A40,24)/24)*('Facility Overview'!$B$11-'Facility Overview'!$B$10))*(1+'Facility Overview'!$B$32/12)^(A40-1) | H40: =E40*G40 | I40: =E40*'Facility Overview'!$B$33 | J40: =H40+I40 | K40: =J40*'Facility Overview'!$B$34*-1 | L40: =J40+K40

Sheet Operating Costs
A1: Operating Costs
A2: Expense Line | B2: Type | C2: Year 1 Basis | D2: Growth Rate | E2: Year 1 Expense | F2: Year 2 Expense | G2: Year 3 Expense | H2: Year 4 Expense | I2: Year 5 Expense | K2: Notes
A3: Payroll / manager | B3: Fixed | C3: 78000 | D3: 0.03 | E3: =IF($B3="% of EGI",'5-Year Projection'!B8*$C3,$C3) | F3: =IF($B3="% of EGI",'5-Year Projection'!C8*$C3,E3*(1+$D3)) | G3: =IF($B3="% of EGI",'5-Year Projection'!D8*$C3,F3*(1+$D3)) | H3: =IF($B3="% of EGI",'5-Year Projection'!E8*$C3,G3*(1+$D3)) | I3: =IF($B3="% of EGI",'5-Year Projection'!F8*$C3,H3*(1+$D3)) | K3: Fixed costs step off the growth rate.
A4: Property tax | B4: Fixed | C4: 26500 | D4: 0.02 | E4: =IF($B4="% of EGI",'5-Year Projection'!B8*$C4,$C4) | F4: =IF($B4="% of EGI",'5-Year Projection'!C8*$C4,E4*(1+$D4)) | G4: =IF($B4="% of EGI",'5-Year Projection'!D8*$C4,F4*(1+$D4)) | H4: =IF($B4="% of EGI",'5-Year Projection'!E8*$C4,G4*(1+$D4)) | I4: =IF($B4="% of EGI",'5-Year Projection'!F8*$C4,H4*(1+$D4)) | K4: Percent lines follow each year's EGI.
A5: Insurance | B5: Fixed | C5: 11800 | D5: 0.03 | E5: =IF($B5="% of EGI",'5-Year Projection'!B8*$C5,$C5) | F5: =IF($B5="% of EGI",'5-Year Projection'!C8*$C5,E5*(1+$D5)) | G5: =IF($B5="% of EGI",'5-Year Projection'!D8*$C5,F5*(1+$D5)) | H5: =IF($B5="% of EGI",'5-Year Projection'!E8*$C5,G5*(1+$D5)) | I5: =IF($B5="% of EGI",'5-Year Projection'!F8*$C5,H5*(1+$D5))
A6: Utilities | B6: Fixed | C6: 14200 | D6: 0.03 | E6: =IF($B6="% of EGI",'5-Year Projection'!B8*$C6,$C6) | F6: =IF($B6="% of EGI",'5-Year Projection'!C8*$C6,E6*(1+$D6)) | G6: =IF($B6="% of EGI",'5-Year Projection'!D8*$C6,F6*(1+$D6)) | H6: =IF($B6="% of EGI",'5-Year Projection'!E8*$C6,G6*(1+$D6)) | I6: =IF($B6="% of EGI",'5-Year Projection'!F8*$C6,H6*(1+$D6))
A7: Repairs & maintenance | B7: Fixed | C7: 21000 | D7: 0.03 | E7: =IF($B7="% of EGI",'5-Year Projection'!B8*$C7,$C7) | F7: =IF($B7="% of EGI",'5-Year Projection'!C8*$C7,E7*(1+$D7)) | G7: =IF($B7="% of EGI",'5-Year Projection'!D8*$C7,F7*(1+$D7)) | H7: =IF($B7="% of EGI",'5-Year Projection'!E8*$C7,G7*(1+$D7)) | I7: =IF($B7="% of EGI",'5-Year Projection'!F8*$C7,H7*(1+$D7))
A8: Marketing | B8: Fixed | C8: 9000 | D8: 0.02 | E8: =IF($B8="% of EGI",'5-Year Projection'!B8*$C8,$C8) | F8: =IF($B8="% of EGI",'5-Year Projection'!C8*$C8,E8*(1+$D8)) | G8: =IF($B8="% of EGI",'5-Year Projection'!D8*$C8,F8*(1+$D8)) | H8: =IF($B8="% of EGI",'5-Year Projection'!E8*$C8,G8*(1+$D8)) | I8: =IF($B8="% of EGI",'5-Year Projection'!F8*$C8,H8*(1+$D8))
A9: Software / admin | B9: Fixed | C9: 6200 | D9: 0.03 | E9: =IF($B9="% of EGI",'5-Year Projection'!B8*$C9,$C9) | F9: =IF($B9="% of EGI",'5-Year Projection'!C8*$C9,E9*(1+$D9)) | G9: =IF($B9="% of EGI",'5-Year Projection'!D8*$C9,F9*(1+$D9)) | H9: =IF($B9="% of EGI",'5-Year Projection'!E8*$C9,G9*(1+$D9)) | I9: =IF($B9="% of EGI",'5-Year Projection'!F8*$C9,H9*(1+$D9))
A10: Security / gate | B10: Fixed | C10: 5400 | D10: 0.03 | E10: =IF($B10="% of EGI",'5-Year Projection'!B8*$C10,$C10) | F10: =IF($B10="% of EGI",'5-Year Projection'!C8*$C10,E10*(1+$D10)) | G10: =IF($B10="% of EGI",'5-Year Projection'!D8*$C10,F10*(1+$D10)) | H10: =IF($B10="% of EGI",'5-Year Projection'!E8*$C10,G10*(1+$D10)) | I10: =IF($B10="% of EGI",'5-Year Projection'!F8*$C10,H10*(1+$D10))
A11: Snow / lawn | B11: Fixed | C11: 4600 | D11: 0.02 | E11: =IF($B11="% of EGI",'5-Year Projection'!B8*$C11,$C11) | F11: =IF($B11="% of EGI",'5-Year Projection'!C8*$C11,E11*(1+$D11)) | G11: =IF($B11="% of EGI",'5-Year Projection'!D8*$C11,F11*(1+$D11)) | H11: =IF($B11="% of EGI",'5-Year Projection'!E8*$C11,G11*(1+$D11)) | I11: =IF($B11="% of EGI",'5-Year Projection'!F8*$C11,H11*(1+$D11))
A12: Management fee | B12: % of EGI | C12: 0.05 | D12: 0 | E12: =IF($B12="% of EGI",'5-Year Projection'!B8*$C12,$C12) | F12: =IF($B12="% of EGI",'5-Year Projection'!C8*$C12,E12*(1+$D12)) | G12: =IF($B12="% of EGI",'5-Year Projection'!D8*$C12,F12*(1+$D12)) | H12: =IF($B12="% of EGI",'5-Year Projection'!E8*$C12,G12*(1+$D12)) | I12: =IF($B12="% of EGI",'5-Year Projection'!F8*$C12,H12*(1+$D12))
A13: Replacement reserve | B13: % of EGI | C13: 0.03 | D13: 0 | E13: =IF($B13="% of EGI",'5-Year Projection'!B8*$C13,$C13) | F13: =IF($B13="% of EGI",'5-Year Projection'!C8*$C13,E13*(1+$D13)) | G13: =IF($B13="% of EGI",'5-Year Projection'!D8*$C13,F13*(1+$D13)) | H13: =IF($B13="% of EGI",'5-Year Projection'!E8*$C13,G13*(1+$D13)) | I13: =IF($B13="% of EGI",'5-Year Projection'!F8*$C13,H13*(1+$D13))
A14: Other | B14: Fixed | C14: 3500 | D14: 0.02 | E14: =IF($B14="% of EGI",'5-Year Projection'!B8*$C14,$C14) | F14: =IF($B14="% of EGI",'5-Year Projection'!C8*$C14,E14*(1+$D14)) | G14: =IF($B14="% of EGI",'5-Year Projection'!D8*$C14,F14*(1+$D14)) | H14: =IF($B14="% of EGI",'5-Year Projection'!E8*$C14,G14*(1+$D14)) | I14: =IF($B14="% of EGI",'5-Year Projection'!F8*$C14,H14*(1+$D14))

Sheet 5-Year Projection
A1: 5-Year Projection
A2: Line Item | B2: Year 1 | C2: Year 2 | D2: Year 3 | E2: Year 4 | F2: Year 5
A3: Occupancy % | B3: =AVERAGE('Unit Mix & Lease-Up'!F17:F28) | C3: =AVERAGE('Unit Mix & Lease-Up'!F29:F40) | D3: ='Facility Overview'!$B$9 | E3: =D3 | F3: =E3
A4: Storage rent | B4: =SUM('Unit Mix & Lease-Up'!H17:H28) | C4: =SUM('Unit Mix & Lease-Up'!H29:H40) | D4: =C4*(1+'Facility Overview'!$B$32) | E4: =D4*(1+'Facility Overview'!$B$32) | F4: =E4*(1+'Facility Overview'!$B$32)
A5: Ancillary income | B5: =SUM('Unit Mix & Lease-Up'!I17:I28) | C5: =SUM('Unit Mix & Lease-Up'!I29:I40) | D5: =C5*(1+'Facility Overview'!$B$32) | E5: =D5*(1+'Facility Overview'!$B$32) | F5: =E5*(1+'Facility Overview'!$B$32)
A6: Gross revenue | B6: =B4+B5 | C6: =C4+C5 | D6: =D4+D5 | E6: =E4+E5 | F6: =F4+F5
A7: Bad debt / promo loss | B7: =B6*'Facility Overview'!$B$34*-1 | C7: =C6*'Facility Overview'!$B$34*-1 | D7: =D6*'Facility Overview'!$B$34*-1 | E7: =E6*'Facility Overview'!$B$34*-1 | F7: =F6*'Facility Overview'!$B$34*-1
A8: Effective gross income | B8: =B6+B7 | C8: =C6+C7 | D8: =D6+D7 | E8: =E6+E7 | F8: =F6+F7
A9: Total operating expenses | B9: =SUM('Operating Costs'!E3:E14) | C9: =SUM('Operating Costs'!F3:F14) | D9: =SUM('Operating Costs'!G3:G14) | E9: =SUM('Operating Costs'!H3:H14) | F9: =SUM('Operating Costs'!I3:I14)
A10: NOI | B10: =B8-B9 | C10: =C8-C9 | D10: =D8-D9 | E10: =E8-E9 | F10: =F8-F9
A11: Debt service | B11: ='Facility Overview'!$B$27 | C11: ='Facility Overview'!$B$27 | D11: ='Facility Overview'!$B$27 | E11: ='Facility Overview'!$B$27 | F11: ='Facility Overview'!$B$27
A12: Cash flow after debt | B12: =B10-B11 | C12: =C10-C11 | D12: =D10-D11 | E12: =E10-E11 | F12: =F10-F11
A13: DSCR | B13: =IF(B11=0,0,B10/B11) | C13: =IF(C11=0,0,C10/C11) | D13: =IF(D11=0,0,D10/D11) | E13: =IF(E11=0,0,E10/E11) | F13: =IF(F11=0,0,F10/F11)

Sheet Returns & Snapshot
A1: Returns & Snapshot
A2: Deal
A3: Purchase price | B3: ='Facility Overview'!B14 | D3: IRR Cash Flow
A4: Total basis | B4: ='Facility Overview'!B17 | D4: Initial | E4: Year 1 | F4: Year 2 | G4: Year 3 | H4: Year 4 | I4: Year 5 + Sale
A5: Loan amount | B5: ='Facility Overview'!B23 | D5: =-B6 | E5: ='5-Year Projection'!B12 | F5: ='5-Year Projection'!C12 | G5: ='5-Year Projection'!D12 | H5: ='5-Year Projection'!E12 | I5: ='5-Year Projection'!F12+B18
A6: Initial equity | B6: ='Facility Overview'!B22+'Facility Overview'!B15+'Facility Overview'!B16
A7: Year 1 NOI | B7: ='5-Year Projection'!B10
A8: Year 1 cap rate | B8: =IF(B3=0,0,B7/B3)
A9: Year 1 cash-on-cash | B9: =IF(B6=0,0,'5-Year Projection'!B12/B6)
A10: Stabilized yield on cost | B10: =IF(B4=0,0,'5-Year Projection'!D10/B4)
A12: Exit
A13: Year 5 NOI | B13: ='5-Year Projection'!F10
A14: Exit cap rate | B14: ='Facility Overview'!B35
A15: Gross sale value | B15: =IF(B14=0,0,B13/B14)
A16: Selling costs | B16: =B15*'Facility Overview'!B36
A17: Loan payoff | B17: =-FV('Facility Overview'!B24/12,'Facility Overview'!B37*12,'Facility Overview'!B26,'Facility Overview'!B23)
A18: Net sale proceeds | B18: =B15-B16-B17
A20: Return Math
A21: 5-year cash flow total | B21: =SUM('5-Year Projection'!B12:F12)
A22: Total cash back | B22: =B21+B18
A23: Equity multiple | B23: =IF(B6=0,0,B22/B6)
A24: Levered IRR | B24: =IRR(D5:I5)
