Workbook

Sheet Job Log
A1: Redd Brothers Construction
A2: Job Profitability Tracker — 2026
B4: Total Jobs: | C4: =COUNTA(B12:B23) -> 12
B5: Completed Jobs: | C5: =COUNTIF(D12:D23,"done") -> 7
B6: Avg Margin: | C6: =AVERAGEIF(D12:D23,"done",M12:M23) -> 0.27095029
B7: Best Job: | C7: =INDEX(B12:B23,MATCH(_xlfn.MAXIFS(M12:M23,D12:D23,"done"),M12:M23,0)) -> Heritage Apartments
B8: Worst Job: | C8: =INDEX(B12:B23,MATCH(_xlfn.MINIFS(M12:M23,D12:D23,"done"),M12:M23,0)) -> Tom Petrosky
B9: Total Profit (completed): | C9: =SUMPRODUCT((D12:D23="done")*L12:L23) -> 25354.05
A11: Job # | B11: Client | C11: Job Description | D11: Status | E11: Quoted Price | F11: Materials | G11: Labor Hrs | H11: Labor Cost | I11: Subcontractor | J11: Other Costs | K11: Total Actual | L11: Profit | M11: Margin % | N11: Notes
A12: JB-2601 | B12: Dave Kowalski | C12: Kitchen remodel - cabinets, countertops, backsplash | D12: done | E12: 28500 | F12: 11247.83 | G12: 142 | H12: =G12*'Rates & Assumptions'!$B$1 -> 6390 | I12: 3800 | J12: 425 | K12: =SUM(F12,H12,I12,J12) -> 21862.83 | L12: =E12-K12 -> 6637.17 | M12: =IF(E12=0,"",L12/E12) -> 0.23288316 | N12: came in under, Dave wants to do bathroom next
A13: JB-2602 | B13: Sarah & Mike Chen | C13: Deck build - 16x20 composite | D13: done | E13: 18000 | F13: 8945 | G13: 96 | H13: =G13*'Rates & Assumptions'!$B$1 -> 4320 | J13: 267 | K13: =SUM(F13,H13,I13,J13) -> 13532 | L13: =E13-K13 -> 4468 | M13: =IF(E13=0,"",L13/E13) -> 0.24822222 | N13: permit took 3 weeks, delayed start
A14: JB-2603 | B14: Meridian Church | C14: Bathroom ADA retrofit x2 | D14: done | E14: 22000 | F14: 7823.4 | G14: 118 | H14: =G14*'Rates & Assumptions'!$B$1 -> 5310 | I14: 2100 | J14: 890 | K14: =SUM(F14,H14,I14,J14) -> 16123.4 | L14: =E14-K14 -> 5876.6 | M14: =IF(E14=0,"",L14/E14) -> 0.26711818 | N14: non-profit, gave them a break on price
A15: JB-2604 | B15: Tom Petrosky | C15: Basement finishing - framing, drywall, LVP, egress window | D15: done | E15: 35000 | F15: 17892.17 | G15: 203 | H15: =G15*'Rates & Assumptions'!$B$1 -> 9135 | I15: 6300 | J15: 2440 | K15: =SUM(F15,H15,I15,J15) -> 35767.17 | L15: =E15-K15 -> -767.17 | M15: =IF(E15=0,"",L15/E15) -> -0.021919143 | N15: client added scope mid-job, should have re-quoted
A16: JB-2605 | B16: Linda Ferraro | C16: Fence - 180 LF cedar privacy 6ft | D16: done | E16: 12500 | F16: 5430 | G16: 54 | H16: =G16*'Rates & Assumptions'!$B$1 -> 2430 | J16: 180 | K16: =SUM(F16,H16,I16,J16) -> 8040 | L16: =E16-K16 -> 4460 | M16: =IF(E16=0,"",L16/E16) -> 0.3568
A17: JB-2606 | B17: Heritage Apartments | C17: Unit turnover - paint, patch, fixtures (unit 4B) | D17: done | E17: 4200 | F17: 823.55 | G17: 28 | H17: =G17*'Rates & Assumptions'!$B$1 -> 1260 | J17: 95 | K17: =SUM(F17,H17,I17,J17) -> 2178.55 | L17: =E17-K17 -> 2021.45 | M17: =IF(E17=0,"",L17/E17) -> 0.48129762 | N17: quick job, they have 3 more units coming
A18: JB-2607 | B18: Dave Kowalski | C18: Master bath - tile, vanity, lighting | D18: active | E18: 19500 | F18: 6100 | G18: 67 | H18: =G18*'Rates & Assumptions'!$B$1 -> 3015 | I18: 2400 | J18: 350 | K18: =SUM(F18,H18,I18,J18) -> 11865 | L18: =E18-K18 -> 7635 | M18: =IF(E18=0,"",L18/E18) -> 0.39153846 | N18: waiting on vanity backorder, ETA 4/22
A19: JB-2608 | B19: First Methodist Daycare | C19: Playground fence + gate install | D19: done | E19: 8000 | F19: 3412 | G19: 38 | H19: =G19*'Rates & Assumptions'!$B$1 -> 1710 | J19: 220 | K19: =SUM(F19,H19,I19,J19) -> 5342 | L19: =E19-K19 -> 2658 | M19: =IF(E19=0,"",L19/E19) -> 0.33225
A20: JB-2609 | B20: Carla Briggs | C20: Garage conversion to home office | D20: active | E20: 24000 | F20: 4890 | G20: 45 | H20: =G20*'Rates & Assumptions'!$B$1 -> 2025 | I20: 1600 | K20: =SUM(F20,H20,I20,J20) -> 8515 | L20: =E20-K20 -> 15485 | M20: =IF(E20=0,"",L20/E20) -> 0.64520833 | N20: just started demo, inspection scheduled 4/18
A21: JB-2610 | B21: Heritage Apartments | C21: Unit turnover - unit 7A, bigger scope than 4B | D21: active | E21: 5800 | F21: 340 | G21: 8 | H21: =G21*'Rates & Assumptions'!$B$1 -> 360 | K21: =SUM(F21,H21,I21,J21) -> 700 | L21: =E21-K21 -> 5100 | M21: =IF(E21=0,"",L21/E21) -> 0.87931034 | N21: just started
A22: JB-2611 | B22: Jim & Pat Deluca | C22: Whole-house interior paint | D22: on hold | E22: 7500 | N22: on hold, they're dealing with insurance claim from water damage
A23: JB-2612 | B23: Dave (referral from Tom) | C23: Shed build - 12x16 with electrical | D23: on hold | E23: 14000 | N23: waiting on HOA approval, might not happen
A25: ---
A26: shop rate is $45/hr, need to bump to $50 in Q3
A27: Heritage wants a bulk deal for remaining units, think about 10% discount
A28: last updated 4/13

Sheet Rates & Assumptions
A1: Shop rate ($/hr) | B1: 45
A2: Target margin | B2: 0.25
A3: Insurance monthly | B3: 485
A4: Truck payment | B4: 487
A6: Material markup % | B6: n/a - we pass through at cost
A8: notes
A9: Tom wants to renegotiate rate for Q3
A10: check workers comp renewal date
