Workbook

Sheet Revenue Log
A1: Date Received | B1: Client / Source | C1: Project / Description | D1: Invoice # | E1: Gross Amount | F1: Platform Fee | G1: Net Received | H1: Quarter | I1: Category | J1: Paid?
A2: 45665 | B2: Acme Corp | C2: Q1 strategy deck | D2: INV-101 | E2: 3200 | F2: 0 | G2: =E2-F2 -> 3200 | H2: =IF(MONTH(A2)<=3,"Q1",IF(MONTH(A2)<=6,"Q2",IF(MONTH(A2)<=9,"Q3","Q4"))) -> Q1 | I2: Consulting | J2: Paid
A3: 45679 | B3: Upwork | C3: React bugfix bundle | D3: UW-2401 | E3: 1800 | F3: 180 | G3: =E3-F3 -> 1620 | H3: =IF(MONTH(A3)<=3,"Q1",IF(MONTH(A3)<=6,"Q2",IF(MONTH(A3)<=9,"Q3","Q4"))) -> Q1 | I3: Development | J3: Paid
A4: 45691 | B4: Bloom LLC | C4: Brand refresh concepts | D4: INV-102 | E4: 4500 | F4: 0 | G4: =E4-F4 -> 4500 | H4: =IF(MONTH(A4)<=3,"Q1",IF(MONTH(A4)<=6,"Q2",IF(MONTH(A4)<=9,"Q3","Q4"))) -> Q1 | I4: Design | J4: Paid
A5: 45702 | B5: Upwork | C5: API integration | D5: UW-2402 | E5: 2400 | F5: 240 | G5: =E5-F5 -> 2160 | H5: =IF(MONTH(A5)<=3,"Q1",IF(MONTH(A5)<=6,"Q2",IF(MONTH(A5)<=9,"Q3","Q4"))) -> Q1 | I5: Development | J5: Invoiced
A6: 45716 | B6: Acme Corp | C6: Workshop afternoon | D6: INV-103 | E6: 950 | F6: 0 | G6: =E6-F6 -> 950 | H6: =IF(MONTH(A6)<=3,"Q1",IF(MONTH(A6)<=6,"Q2",IF(MONTH(A6)<=9,"Q3","Q4"))) -> Q1 | I6: Teaching | J6: Paid
A7: 45721 | B7: Direct | C7: Blog series (3 posts) | D7: INV-104 | E7: 1200 | F7: 0 | G7: =E7-F7 -> 1200 | H7: =IF(MONTH(A7)<=3,"Q1",IF(MONTH(A7)<=6,"Q2",IF(MONTH(A7)<=9,"Q3","Q4"))) -> Q1 | I7: Writing | J7: Paid
A8: 45734 | B8: Upwork | C8: Wireframes v2 | D8: UW-2403 | E8: 1650 | F8: 165 | G8: =E8-F8 -> 1485 | H8: =IF(MONTH(A8)<=3,"Q1",IF(MONTH(A8)<=6,"Q2",IF(MONTH(A8)<=9,"Q3","Q4"))) -> Q1 | I8: Design | J8: Paid
A9: 45749 | B9: Bloom LLC | C9: Landing page copy | D9: INV-105 | E9: 2100 | F9: 0 | G9: =E9-F9 -> 2100 | H9: =IF(MONTH(A9)<=3,"Q1",IF(MONTH(A9)<=6,"Q2",IF(MONTH(A9)<=9,"Q3","Q4"))) -> Q2 | I9: Writing | J9: Paid
A10: 45763 | B10: Acme Corp | C10: Sprint support | D10: INV-106 | E10: 3800 | F10: 0 | G10: =E10-F10 -> 3800 | H10: =IF(MONTH(A10)<=3,"Q1",IF(MONTH(A10)<=6,"Q2",IF(MONTH(A10)<=9,"Q3","Q4"))) -> Q2 | I10: Consulting | J10: Overdue
A11: 45776 | B11: Upwork | C11: SQL report pack | D11: UW-2404 | E11: 1100 | F11: 110 | G11: =E11-F11 -> 990 | H11: =IF(MONTH(A11)<=3,"Q1",IF(MONTH(A11)<=6,"Q2",IF(MONTH(A11)<=9,"Q3","Q4"))) -> Q2 | I11: Development | J11: Paid
A12: 45784 | B12: River Studio | C12: Logo variations | D12: RS-01 | E12: 2750 | F12: 0 | G12: =E12-F12 -> 2750 | H12: =IF(MONTH(A12)<=3,"Q1",IF(MONTH(A12)<=6,"Q2",IF(MONTH(A12)<=9,"Q3","Q4"))) -> Q2 | I12: Design | J12: Paid
A13: 45798 | B13: Direct | C13: Newsletter setup | D13: INV-107 | E13: 800 | F13: 0 | G13: =E13-F13 -> 800 | H13: =IF(MONTH(A13)<=3,"Q1",IF(MONTH(A13)<=6,"Q2",IF(MONTH(A13)<=9,"Q3","Q4"))) -> Q2 | I13: Other | J13: Paid
... A27: 46007 | B27: Upwork | C27: Year-end cleanup | D27: UW-2408 | E27: 1500 | F27: 150 | G27: =E27-F27 -> 1350 | H27: =IF(MONTH(A27)<=3,"Q1",IF(MONTH(A27)<=6,"Q2",IF(MONTH(A27)<=9,"Q3","Q4"))) -> Q4 | I27: Development | J27: Paid

Sheet Expense Log
A1: Date | B1: Vendor / Payee | C1: Description | D1: Amount | E1: Category | F1: Tax Deductible? | G1: Deductible Amount | H1: Quarter | I1: Receipt? | J1: Notes
A2: 45662 | B2: Adobe | C2: Creative Cloud | D2: 59.99 | E2: Software/Subscriptions | F2: =IF(E2="Meals (50%)","Partial",IF(E2="Other","Check","Yes")) -> Yes | G2: =IF(E2="Meals (50%)",D2*0.5,D2) -> 59.99 | H2: =IF(MONTH(A2)<=3,"Q1",IF(MONTH(A2)<=6,"Q2",IF(MONTH(A2)<=9,"Q3","Q4"))) -> Q1 | I2: Digital
A3: 45669 | B3: Apple | C3: MacBook Air (partial biz) | D3: 899 | E3: Equipment | F3: =IF(E3="Meals (50%)","Partial",IF(E3="Other","Check","Yes")) -> Yes | G3: =IF(E3="Meals (50%)",D3*0.5,D3) -> 899 | H3: =IF(MONTH(A3)<=3,"Q1",IF(MONTH(A3)<=6,"Q2",IF(MONTH(A3)<=9,"Q3","Q4"))) -> Q1 | I3: Digital | J3: depreciation note
A4: 45675 | B4: Staples | C4: Printer paper | D4: 42.5 | E4: Office Supplies | F4: =IF(E4="Meals (50%)","Partial",IF(E4="Other","Check","Yes")) -> Yes | G4: =IF(E4="Meals (50%)",D4*0.5,D4) -> 42.5 | H4: =IF(MONTH(A4)<=3,"Q1",IF(MONTH(A4)<=6,"Q2",IF(MONTH(A4)<=9,"Q3","Q4"))) -> Q1 | I4: Yes
A5: 45682 | B5: CPA Review | C5: Q4 consult | D5: 275 | E5: Professional Services | F5: =IF(E5="Meals (50%)","Partial",IF(E5="Other","Check","Yes")) -> Yes | G5: =IF(E5="Meals (50%)",D5*0.5,D5) -> 275 | H5: =IF(MONTH(A5)<=3,"Q1",IF(MONTH(A5)<=6,"Q2",IF(MONTH(A5)<=9,"Q3","Q4"))) -> Q1 | I5: Digital
A6: 45690 | B6: Coursera | C6: Python course | D6: 49 | E6: Education/Training | F6: =IF(E6="Meals (50%)","Partial",IF(E6="Other","Check","Yes")) -> Yes | G6: =IF(E6="Meals (50%)",D6*0.5,D6) -> 49 | H6: =IF(MONTH(A6)<=3,"Q1",IF(MONTH(A6)<=6,"Q2",IF(MONTH(A6)<=9,"Q3","Q4"))) -> Q1 | I6: Digital
A7: 45697 | B7: WeWork | C7: Day pass | D7: 45 | E7: Travel | F7: =IF(E7="Meals (50%)","Partial",IF(E7="Other","Check","Yes")) -> Yes | G7: =IF(E7="Meals (50%)",D7*0.5,D7) -> 45 | H7: =IF(MONTH(A7)<=3,"Q1",IF(MONTH(A7)<=6,"Q2",IF(MONTH(A7)<=9,"Q3","Q4"))) -> Q1 | I7: Digital
A8: 45704 | B8: Cafe Rio | C8: Client lunch | D8: 38.2 | E8: Meals (50%) | F8: =IF(E8="Meals (50%)","Partial",IF(E8="Other","Check","Yes")) -> Partial | G8: =IF(E8="Meals (50%)",D8*0.5,D8) -> 19.1 | H8: =IF(MONTH(A8)<=3,"Q1",IF(MONTH(A8)<=6,"Q2",IF(MONTH(A8)<=9,"Q3","Q4"))) -> Q1 | I8: No
A9: 45711 | B9: Google | C9: Workspace | D9: 12 | E9: Software/Subscriptions | F9: =IF(E9="Meals (50%)","Partial",IF(E9="Other","Check","Yes")) -> Yes | G9: =IF(E9="Meals (50%)",D9*0.5,D9) -> 12 | H9: =IF(MONTH(A9)<=3,"Q1",IF(MONTH(A9)<=6,"Q2",IF(MONTH(A9)<=9,"Q3","Q4"))) -> Q1 | I9: Digital
A10: 45717 | B10: Best Buy | C10: External SSD | D10: 129 | E10: Equipment | F10: =IF(E10="Meals (50%)","Partial",IF(E10="Other","Check","Yes")) -> Yes | G10: =IF(E10="Meals (50%)",D10*0.5,D10) -> 129 | H10: =IF(MONTH(A10)<=3,"Q1",IF(MONTH(A10)<=6,"Q2",IF(MONTH(A10)<=9,"Q3","Q4"))) -> Q1 | I10: Yes
A11: 45731 | B11: Home Office | C11: Simplified method (sample) | D11: 150 | E11: Home Office | F11: =IF(E11="Meals (50%)","Partial",IF(E11="Other","Check","Yes")) -> Yes | G11: =IF(E11="Meals (50%)",D11*0.5,D11) -> 150 | H11: =IF(MONTH(A11)<=3,"Q1",IF(MONTH(A11)<=6,"Q2",IF(MONTH(A11)<=9,"Q3","Q4"))) -> Q1 | I11: Digital
A12: 45738 | B12: Zoom | C12: Pro plan | D12: 15.99 | E12: Software/Subscriptions | F12: =IF(E12="Meals (50%)","Partial",IF(E12="Other","Check","Yes")) -> Yes | G12: =IF(E12="Meals (50%)",D12*0.5,D12) -> 15.99 | H12: =IF(MONTH(A12)<=3,"Q1",IF(MONTH(A12)<=6,"Q2",IF(MONTH(A12)<=9,"Q3","Q4"))) -> Q1 | I12: Digital
A13: 45750 | B13: Delta | C13: Conference flight | D13: 312 | E13: Travel | F13: =IF(E13="Meals (50%)","Partial",IF(E13="Other","Check","Yes")) -> Yes | G13: =IF(E13="Meals (50%)",D13*0.5,D13) -> 312 | H13: =IF(MONTH(A13)<=3,"Q1",IF(MONTH(A13)<=6,"Q2",IF(MONTH(A13)<=9,"Q3","Q4"))) -> Q2 | I13: Digital
A14: 45757 | B14: Hotel Indigo | C14: 1 night stay | D14: 189 | E14: Travel | F14: =IF(E14="Meals (50%)","Partial",IF(E14="Other","Check","Yes")) -> Yes | G14: =IF(E14="Meals (50%)",D14*0.5,D14) -> 189 | H14: =IF(MONTH(A14)<=3,"Q1",IF(MONTH(A14)<=6,"Q2",IF(MONTH(A14)<=9,"Q3","Q4"))) -> Q2 | I14: Digital
A15: 45764 | B15: LinkedIn | C15: Ads test | D15: 50 | E15: Marketing | F15: =IF(E15="Meals (50%)","Partial",IF(E15="Other","Check","Yes")) -> Yes | G15: =IF(E15="Meals (50%)",D15*0.5,D15) -> 50 | H15: =IF(MONTH(A15)<=3,"Q1",IF(MONTH(A15)<=6,"Q2",IF(MONTH(A15)<=9,"Q3","Q4"))) -> Q2 | I15: Digital
... A30: 45870 | B30: ChatGPT Plus | C30: Research | D30: 20 | E30: Software/Subscriptions | F30: =IF(E30="Meals (50%)","Partial",IF(E30="Other","Check","Yes")) -> Yes | G30: =IF(E30="Meals (50%)",D30*0.5,D30) -> 20 | H30: =IF(MONTH(A30)<=3,"Q1",IF(MONTH(A30)<=6,"Q2",IF(MONTH(A30)<=9,"Q3","Q4"))) -> Q3 | I30: Digital
A31: 45877 | B31: Costco | C31: Office snacks | D31: 55 | E31: Other | F31: =IF(E31="Meals (50%)","Partial",IF(E31="Other","Check","Yes")) -> Check | G31: =IF(E31="Meals (50%)",D31*0.5,D31) -> 55 | H31: =IF(MONTH(A31)<=3,"Q1",IF(MONTH(A31)<=6,"Q2",IF(MONTH(A31)<=9,"Q3","Q4"))) -> Q3 | I31: Yes | J31: mixed use
A32: 45884 | B32: Law firm | C32: Contract template | D32: 350 | E32: Professional Services | F32: =IF(E32="Meals (50%)","Partial",IF(E32="Other","Check","Yes")) -> Yes | G32: =IF(E32="Meals (50%)",D32*0.5,D32) -> 350 | H32: =IF(MONTH(A32)<=3,"Q1",IF(MONTH(A32)<=6,"Q2",IF(MONTH(A32)<=9,"Q3","Q4"))) -> Q3 | I32: Digital
A33: 45891 | B33: AT&T | C33: Internet | D33: 80 | E33: Phone/Internet | F33: =IF(E33="Meals (50%)","Partial",IF(E33="Other","Check","Yes")) -> Yes | G33: =IF(E33="Meals (50%)",D33*0.5,D33) -> 80 | H33: =IF(MONTH(A33)<=3,"Q1",IF(MONTH(A33)<=6,"Q2",IF(MONTH(A33)<=9,"Q3","Q4"))) -> Q3 | I33: Digital
A34: 45898 | B34: Miro | C34: Boards | D34: 10 | E34: Software/Subscriptions | F34: =IF(E34="Meals (50%)","Partial",IF(E34="Other","Check","Yes")) -> Yes | G34: =IF(E34="Meals (50%)",D34*0.5,D34) -> 10 | H34: =IF(MONTH(A34)<=3,"Q1",IF(MONTH(A34)<=6,"Q2",IF(MONTH(A34)<=9,"Q3","Q4"))) -> Q3 | I34: Digital
A35: 45905 | B35: Parking | C35: Downtown garage | D35: 22 | E35: Travel | F35: =IF(E35="Meals (50%)","Partial",IF(E35="Other","Check","Yes")) -> Yes | G35: =IF(E35="Meals (50%)",D35*0.5,D35) -> 22 | H35: =IF(MONTH(A35)<=3,"Q1",IF(MONTH(A35)<=6,"Q2",IF(MONTH(A35)<=9,"Q3","Q4"))) -> Q3 | I35: No
A36: 45912 | B36: Home Depot | C36: Desk lamp | D36: 45 | E36: Office Supplies | F36: =IF(E36="Meals (50%)","Partial",IF(E36="Other","Check","Yes")) -> Yes | G36: =IF(E36="Meals (50%)",D36*0.5,D36) -> 45 | H36: =IF(MONTH(A36)<=3,"Q1",IF(MONTH(A36)<=6,"Q2",IF(MONTH(A36)<=9,"Q3","Q4"))) -> Q3 | I36: Yes
A37: 45919 | B37: Conference | C37: Ticket | D37: 299 | E37: Education/Training | F37: =IF(E37="Meals (50%)","Partial",IF(E37="Other","Check","Yes")) -> Yes | G37: =IF(E37="Meals (50%)",D37*0.5,D37) -> 299 | H37: =IF(MONTH(A37)<=3,"Q1",IF(MONTH(A37)<=6,"Q2",IF(MONTH(A37)<=9,"Q3","Q4"))) -> Q3 | I37: Digital
A38: 45926 | B38: Sushi spot | C38: Client dinner | D38: 94 | E38: Meals (50%) | F38: =IF(E38="Meals (50%)","Partial",IF(E38="Other","Check","Yes")) -> Partial | G38: =IF(E38="Meals (50%)",D38*0.5,D38) -> 47 | H38: =IF(MONTH(A38)<=3,"Q1",IF(MONTH(A38)<=6,"Q2",IF(MONTH(A38)<=9,"Q3","Q4"))) -> Q3 | I38: No
A39: 45933 | B39: Slack | C39: Pro | D39: 8.75 | E39: Software/Subscriptions | F39: =IF(E39="Meals (50%)","Partial",IF(E39="Other","Check","Yes")) -> Yes | G39: =IF(E39="Meals (50%)",D39*0.5,D39) -> 8.75 | H39: =IF(MONTH(A39)<=3,"Q1",IF(MONTH(A39)<=6,"Q2",IF(MONTH(A39)<=9,"Q3","Q4"))) -> Q4 | I39: Digital
A40: 45940 | B40: UPS | C40: Ship samples | D40: 27.15 | E40: Office Supplies | F40: =IF(E40="Meals (50%)","Partial",IF(E40="Other","Check","Yes")) -> Yes | G40: =IF(E40="Meals (50%)",D40*0.5,D40) -> 27.15 | H40: =IF(MONTH(A40)<=3,"Q1",IF(MONTH(A40)<=6,"Q2",IF(MONTH(A40)<=9,"Q3","Q4"))) -> Q4 | I40: Yes
A41: 45947 | B41: Canva | C41: Pro | D41: 12.99 | E41: Software/Subscriptions | F41: =IF(E41="Meals (50%)","Partial",IF(E41="Other","Check","Yes")) -> Yes | G41: =IF(E41="Meals (50%)",D41*0.5,D41) -> 12.99 | H41: =IF(MONTH(A41)<=3,"Q1",IF(MONTH(A41)<=6,"Q2",IF(MONTH(A41)<=9,"Q3","Q4"))) -> Q4 | I41: Digital
A42: 45954 | B42: QuickBooks | C42: Self-employed | D42: 30 | E42: Software/Subscriptions | F42: =IF(E42="Meals (50%)","Partial",IF(E42="Other","Check","Yes")) -> Yes | G42: =IF(E42="Meals (50%)",D42*0.5,D42) -> 30 | H42: =IF(MONTH(A42)<=3,"Q1",IF(MONTH(A42)<=6,"Q2",IF(MONTH(A42)<=9,"Q3","Q4"))) -> Q4 | I42: Digital
A43: 45962 | B43: Lumen | C43: Fiber | D43: 75 | E43: Phone/Internet | F43: =IF(E43="Meals (50%)","Partial",IF(E43="Other","Check","Yes")) -> Yes | G43: =IF(E43="Meals (50%)",D43*0.5,D43) -> 75 | H43: =IF(MONTH(A43)<=3,"Q1",IF(MONTH(A43)<=6,"Q2",IF(MONTH(A43)<=9,"Q3","Q4"))) -> Q4 | I43: Digital
... A49: 46004 | B49: Post office | C49: Certified mail | D49: 9.65 | E49: Office Supplies | F49: =IF(E49="Meals (50%)","Partial",IF(E49="Other","Check","Yes")) -> Yes | G49: =IF(E49="Meals (50%)",D49*0.5,D49) -> 9.65 | H49: =IF(MONTH(A49)<=3,"Q1",IF(MONTH(A49)<=6,"Q2",IF(MONTH(A49)<=9,"Q3","Q4"))) -> Q4 | I49: Yes
A50: 46011 | B50: Charity gala ticket | C50: Networking | D50: 125 | E50: Marketing | F50: =IF(E50="Meals (50%)","Partial",IF(E50="Other","Check","Yes")) -> Yes | G50: =IF(E50="Meals (50%)",D50*0.5,D50) -> 125 | H50: =IF(MONTH(A50)<=3,"Q1",IF(MONTH(A50)<=6,"Q2",IF(MONTH(A50)<=9,"Q3","Q4"))) -> Q4 | I50: Digital | J50: ask CPA

Sheet Monthly P&L
A1: Month | B1: Gross Revenue | C1: Platform Fees | D1: Net Revenue | E1: Deductible expenses (tax) | F1: Cash expenses (full) | G1: Net Profit | H1: Profit Margin | I1: Cumulative Revenue (YTD) | J1: Cumulative deductible (YTD) | K1: Cumulative Profit (YTD)
A2: Jan | B2: =SUMPRODUCT((ISNUMBER('Revenue Log'!$A$2:$A$500))*(MONTH('Revenue Log'!$A$2:$A$500)=1)*'Revenue Log'!$E$2:$E$500) -> 5000 | C2: =SUMPRODUCT((ISNUMBER('Revenue Log'!$A$2:$A$500))*(MONTH('Revenue Log'!$A$2:$A$500)=1)*'Revenue Log'!$F$2:$F$500) -> 180 | D2: =B2-C2 -> 4820 | E2: =SUMPRODUCT((ISNUMBER('Expense Log'!$A$2:$A$500))*(MONTH('Expense Log'!$A$2:$A$500)=1)*'Expense Log'!$G$2:$G$500) -> 1276.49 | F2: =SUMPRODUCT((ISNUMBER('Expense Log'!$A$2:$A$500))*(MONTH('Expense Log'!$A$2:$A$500)=1)*'Expense Log'!$D$2:$D$500) -> 1276.49 | G2: =D2-E2 -> 3543.51 | H2: =IF(B2>0,G2/B2,"") -> 0.708702 | I2: =D2 -> 4820 | J2: =E2 -> 1276.49 | K2: =I2-J2 -> 3543.51
A3: Feb | B3: =SUMPRODUCT((ISNUMBER('Revenue Log'!$A$2:$A$500))*(MONTH('Revenue Log'!$A$2:$A$500)=2)*'Revenue Log'!$E$2:$E$500) -> 7850 | C3: =SUMPRODUCT((ISNUMBER('Revenue Log'!$A$2:$A$500))*(MONTH('Revenue Log'!$A$2:$A$500)=2)*'Revenue Log'!$F$2:$F$500) -> 240 | D3: =B3-C3 -> 7610 | E3: =SUMPRODUCT((ISNUMBER('Expense Log'!$A$2:$A$500))*(MONTH('Expense Log'!$A$2:$A$500)=2)*'Expense Log'!$G$2:$G$500) -> 125.1 | F3: =SUMPRODUCT((ISNUMBER('Expense Log'!$A$2:$A$500))*(MONTH('Expense Log'!$A$2:$A$500)=2)*'Expense Log'!$D$2:$D$500) -> 144.2 | G3: =D3-E3 -> 7484.9 | H3: =IF(B3>0,G3/B3,"") -> 0.95349045 | I3: =I2+D3 -> 12430 | J3: =J2+E3 -> 1401.59 | K3: =I3-J3 -> 11028.41
A4: Mar | B4: =SUMPRODUCT((ISNUMBER('Revenue Log'!$A$2:$A$500))*(MONTH('Revenue Log'!$A$2:$A$500)=3)*'Revenue Log'!$E$2:$E$500) -> 2850 | C4: =SUMPRODUCT((ISNUMBER('Revenue Log'!$A$2:$A$500))*(MONTH('Revenue Log'!$A$2:$A$500)=3)*'Revenue Log'!$F$2:$F$500) -> 165 | D4: =B4-C4 -> 2685 | E4: =SUMPRODUCT((ISNUMBER('Expense Log'!$A$2:$A$500))*(MONTH('Expense Log'!$A$2:$A$500)=3)*'Expense Log'!$G$2:$G$500) -> 294.99 | F4: =SUMPRODUCT((ISNUMBER('Expense Log'!$A$2:$A$500))*(MONTH('Expense Log'!$A$2:$A$500)=3)*'Expense Log'!$D$2:$D$500) -> 294.99 | G4: =D4-E4 -> 2390.01 | H4: =IF(B4>0,G4/B4,"") -> 0.8386 | I4: =I3+D4 -> 15115 | J4: =J3+E4 -> 1696.58 | K4: =I4-J4 -> 13418.42
A5: Apr | B5: =SUMPRODUCT((ISNUMBER('Revenue Log'!$A$2:$A$500))*(MONTH('Revenue Log'!$A$2:$A$500)=4)*'Revenue Log'!$E$2:$E$500) -> 7000 | C5: =SUMPRODUCT((ISNUMBER('Revenue Log'!$A$2:$A$500))*(MONTH('Revenue Log'!$A$2:$A$500)=4)*'Revenue Log'!$F$2:$F$500) -> 110 | D5: =B5-C5 -> 6890 | E5: =SUMPRODUCT((ISNUMBER('Expense Log'!$A$2:$A$500))*(MONTH('Expense Log'!$A$2:$A$500)=4)*'Expense Log'!$G$2:$G$500) -> 616 | F5: =SUMPRODUCT((ISNUMBER('Expense Log'!$A$2:$A$500))*(MONTH('Expense Log'!$A$2:$A$500)=4)*'Expense Log'!$D$2:$D$500) -> 616 | G5: =D5-E5 -> 6274 | H5: =IF(B5>0,G5/B5,"") -> 0.89628571 | I5: =I4+D5 -> 22005 | J5: =J4+E5 -> 2312.58 | K5: =I5-J5 -> 19692.42
A6: May | B6: =SUMPRODUCT((ISNUMBER('Revenue Log'!$A$2:$A$500))*(MONTH('Revenue Log'!$A$2:$A$500)=5)*'Revenue Log'!$E$2:$E$500) -> 3550 | C6: =SUMPRODUCT((ISNUMBER('Revenue Log'!$A$2:$A$500))*(MONTH('Revenue Log'!$A$2:$A$500)=5)*'Revenue Log'!$F$2:$F$500) -> 0 | D6: =B6-C6 -> 3550 | E6: =SUMPRODUCT((ISNUMBER('Expense Log'!$A$2:$A$500))*(MONTH('Expense Log'!$A$2:$A$500)=5)*'Expense Log'!$G$2:$G$500) -> 145.24 | F6: =SUMPRODUCT((ISNUMBER('Expense Log'!$A$2:$A$500))*(MONTH('Expense Log'!$A$2:$A$500)=5)*'Expense Log'!$D$2:$D$500) -> 145.24 | G6: =D6-E6 -> 3404.76 | H6: =IF(B6>0,G6/B6,"") -> 0.95908732 | I6: =I5+D6 -> 25555 | J6: =J5+E6 -> 2457.82 | K6: =I6-J6 -> 23097.18
A7: Jun | B7: =SUMPRODUCT((ISNUMBER('Revenue Log'!$A$2:$A$500))*(MONTH('Revenue Log'!$A$2:$A$500)=6)*'Revenue Log'!$E$2:$E$500) -> 5600 | C7: =SUMPRODUCT((ISNUMBER('Revenue Log'!$A$2:$A$500))*(MONTH('Revenue Log'!$A$2:$A$500)=6)*'Revenue Log'!$F$2:$F$500) -> 220 | D7: =B7-C7 -> 5380 | E7: =SUMPRODUCT((ISNUMBER('Expense Log'!$A$2:$A$500))*(MONTH('Expense Log'!$A$2:$A$500)=6)*'Expense Log'!$G$2:$G$500) -> 163.45 | F7: =SUMPRODUCT((ISNUMBER('Expense Log'!$A$2:$A$500))*(MONTH('Expense Log'!$A$2:$A$500)=6)*'Expense Log'!$D$2:$D$500) -> 194.5 | G7: =D7-E7 -> 5216.55 | H7: =IF(B7>0,G7/B7,"") -> 0.93152679 | I7: =I6+D7 -> 30935 | J7: =J6+E7 -> 2621.27 | K7: =I7-J7 -> 28313.73
A8: Jul | B8: =SUMPRODUCT((ISNUMBER('Revenue Log'!$A$2:$A$500))*(MONTH('Revenue Log'!$A$2:$A$500)=7)*'Revenue Log'!$E$2:$E$500) -> 5000 | C8: =SUMPRODUCT((ISNUMBER('Revenue Log'!$A$2:$A$500))*(MONTH('Revenue Log'!$A$2:$A$500)=7)*'Revenue Log'!$F$2:$F$500) -> 0 | D8: =B8-C8 -> 5000 | E8: =SUMPRODUCT((ISNUMBER('Expense Log'!$A$2:$A$500))*(MONTH('Expense Log'!$A$2:$A$500)=7)*'Expense Log'!$G$2:$G$500) -> 535.87 | F8: =SUMPRODUCT((ISNUMBER('Expense Log'!$A$2:$A$500))*(MONTH('Expense Log'!$A$2:$A$500)=7)*'Expense Log'!$D$2:$D$500) -> 535.87 | G8: =D8-E8 -> 4464.13 | H8: =IF(B8>0,G8/B8,"") -> 0.892826 | I8: =I7+D8 -> 35935 | J8: =J7+E8 -> 3157.14 | K8: =I8-J8 -> 32777.86
A9: Aug | B9: =SUMPRODUCT((ISNUMBER('Revenue Log'!$A$2:$A$500))*(MONTH('Revenue Log'!$A$2:$A$500)=8)*'Revenue Log'!$E$2:$E$500) -> 2330 | C9: =SUMPRODUCT((ISNUMBER('Revenue Log'!$A$2:$A$500))*(MONTH('Revenue Log'!$A$2:$A$500)=8)*'Revenue Log'!$F$2:$F$500) -> 98 | D9: =B9-C9 -> 2232 | E9: =SUMPRODUCT((ISNUMBER('Expense Log'!$A$2:$A$500))*(MONTH('Expense Log'!$A$2:$A$500)=8)*'Expense Log'!$G$2:$G$500) -> 515 | F9: =SUMPRODUCT((ISNUMBER('Expense Log'!$A$2:$A$500))*(MONTH('Expense Log'!$A$2:$A$500)=8)*'Expense Log'!$D$2:$D$500) -> 515 | G9: =D9-E9 -> 1717 | H9: =IF(B9>0,G9/B9,"") -> 0.73690987 | I9: =I8+D9 -> 38167 | J9: =J8+E9 -> 3672.14 | K9: =I9-J9 -> 34494.86
A10: Sep | B10: =SUMPRODUCT((ISNUMBER('Revenue Log'!$A$2:$A$500))*(MONTH('Revenue Log'!$A$2:$A$500)=9)*'Revenue Log'!$E$2:$E$500) -> 4350 | C10: =SUMPRODUCT((ISNUMBER('Revenue Log'!$A$2:$A$500))*(MONTH('Revenue Log'!$A$2:$A$500)=9)*'Revenue Log'!$F$2:$F$500) -> 0 | D10: =B10-C10 -> 4350 | E10: =SUMPRODUCT((ISNUMBER('Expense Log'!$A$2:$A$500))*(MONTH('Expense Log'!$A$2:$A$500)=9)*'Expense Log'!$G$2:$G$500) -> 413 | F10: =SUMPRODUCT((ISNUMBER('Expense Log'!$A$2:$A$500))*(MONTH('Expense Log'!$A$2:$A$500)=9)*'Expense Log'!$D$2:$D$500) -> 460 | G10: =D10-E10 -> 3937 | H10: =IF(B10>0,G10/B10,"") -> 0.90505747 | I10: =I9+D10 -> 42517 | J10: =J9+E10 -> 4085.14 | K10: =I10-J10 -> 38431.86
A11: Oct | B11: =SUMPRODUCT((ISNUMBER('Revenue Log'!$A$2:$A$500))*(MONTH('Revenue Log'!$A$2:$A$500)=10)*'Revenue Log'!$E$2:$E$500) -> 2750 | C11: =SUMPRODUCT((ISNUMBER('Revenue Log'!$A$2:$A$500))*(MONTH('Revenue Log'!$A$2:$A$500)=10)*'Revenue Log'!$F$2:$F$500) -> 130 | D11: =B11-C11 -> 2620 | E11: =SUMPRODUCT((ISNUMBER('Expense Log'!$A$2:$A$500))*(MONTH('Expense Log'!$A$2:$A$500)=10)*'Expense Log'!$G$2:$G$500) -> 78.89 | F11: =SUMPRODUCT((ISNUMBER('Expense Log'!$A$2:$A$500))*(MONTH('Expense Log'!$A$2:$A$500)=10)*'Expense Log'!$D$2:$D$500) -> 78.89 | G11: =D11-E11 -> 2541.11 | H11: =IF(B11>0,G11/B11,"") -> 0.92404 | I11: =I10+D11 -> 45137 | J11: =J10+E11 -> 4164.03 | K11: =I11-J11 -> 40972.97
A12: Nov | B12: =SUMPRODUCT((ISNUMBER('Revenue Log'!$A$2:$A$500))*(MONTH('Revenue Log'!$A$2:$A$500)=11)*'Revenue Log'!$E$2:$E$500) -> 6300 | C12: =SUMPRODUCT((ISNUMBER('Revenue Log'!$A$2:$A$500))*(MONTH('Revenue Log'!$A$2:$A$500)=11)*'Revenue Log'!$F$2:$F$500) -> 0 | D12: =B12-C12 -> 6300 | E12: =SUMPRODUCT((ISNUMBER('Expense Log'!$A$2:$A$500))*(MONTH('Expense Log'!$A$2:$A$500)=11)*'Expense Log'!$G$2:$G$500) -> 294.45 | F12: =SUMPRODUCT((ISNUMBER('Expense Log'!$A$2:$A$500))*(MONTH('Expense Log'!$A$2:$A$500)=11)*'Expense Log'!$D$2:$D$500) -> 301.7 | G12: =D12-E12 -> 6005.55 | H12: =IF(B12>0,G12/B12,"") -> 0.9532619 | I12: =I11+D12 -> 51437 | J12: =J11+E12 -> 4458.48 | K12: =I12-J12 -> 46978.52
A13: Dec | B13: =SUMPRODUCT((ISNUMBER('Revenue Log'!$A$2:$A$500))*(MONTH('Revenue Log'!$A$2:$A$500)=12)*'Revenue Log'!$E$2:$E$500) -> 4400 | C13: =SUMPRODUCT((ISNUMBER('Revenue Log'!$A$2:$A$500))*(MONTH('Revenue Log'!$A$2:$A$500)=12)*'Revenue Log'!$F$2:$F$500) -> 150 | D13: =B13-C13 -> 4250 | E13: =SUMPRODUCT((ISNUMBER('Expense Log'!$A$2:$A$500))*(MONTH('Expense Log'!$A$2:$A$500)=12)*'Expense Log'!$G$2:$G$500) -> 182.98 | F13: =SUMPRODUCT((ISNUMBER('Expense Log'!$A$2:$A$500))*(MONTH('Expense Log'!$A$2:$A$500)=12)*'Expense Log'!$D$2:$D$500) -> 182.98 | G13: =D13-E13 -> 4067.02 | H13: =IF(B13>0,G13/B13,"") -> 0.92432273 | I13: =I12+D13 -> 55687 | J13: =J12+E13 -> 4641.46 | K13: =I13-J13 -> 51045.54
A14: Annual | B14: =SUM(B2:B13) -> 56980 | C14: =SUM(C2:C13) -> 1293 | D14: =SUM(D2:D13) -> 55687 | E14: =SUM(E2:E13) -> 4641.46 | F14: =SUM(F2:F13) -> 4745.86 | G14: =SUM(G2:G13) -> 51045.54 | H14: =IF(B14>0,G14/B14,"") -> 0.89585012
A16: By client (gross billed)
A17: Client | B17: Total billed | C17: % of revenue
A18: Acme Corp | B18: =SUMIFS('Revenue Log'!$E$2:$E$500,'Revenue Log'!$B$2:$B$500,$A$18) -> 18050 | C18: =IF($B$14=0,"",B18/$B$14) -> 0.31677782
A19: Upwork | B19: =SUMIFS('Revenue Log'!$E$2:$E$500,'Revenue Log'!$B$2:$B$500,$A$19) -> 12930 | C19: =IF($B$14=0,"",B19/$B$14) -> 0.22692173
A20: Bloom LLC | B20: =SUMIFS('Revenue Log'!$E$2:$E$500,'Revenue Log'!$B$2:$B$500,$A$20) -> 13150 | C20: =IF($B$14=0,"",B20/$B$14) -> 0.23078273
A21: River Studio | B21: =SUMIFS('Revenue Log'!$E$2:$E$500,'Revenue Log'!$B$2:$B$500,$A$21) -> 7300 | C21: =IF($B$14=0,"",B21/$B$14) -> 0.12811513
A22: Direct | B22: =SUMIFS('Revenue Log'!$E$2:$E$500,'Revenue Log'!$B$2:$B$500,$A$22) -> 5550 | C22: =IF($B$14=0,"",B22/$B$14) -> 0.097402597

Sheet Tax Estimator
A1: Tax Estimator
A3: Filing status | B3: Single
A4: W-2 income (day job, gross) | B4: 85000
A5: W-2 federal tax withheld (YTD or annual est.) | B5: 12800
A6: State (reference only) | B6: CA
A7: Side hustle net profit (from Monthly P&L annual) | B7: ='Monthly P&L'!$G$14 -> 51045.54
A9: SS wage base (2025, edit if law changes) | B9: 176100
A10: Net profit (Schedule C) | B10: =B7 -> 51045.54
A11: SE tax base (92.35%) | B11: =B10*0.9235 -> 47140.556
A12: Social Security portion (12.4%) | B12: =MIN(B11,MAX(0,$B$9-B4))*0.124 -> 5845.429
A13: Medicare portion (2.9%) | B13: =B11*0.029 -> 1367.0761
A14: Total self-employment tax | B14: =B12+B13 -> 7212.5051
A15: Deductible half of SE tax | B15: =B14*0.5 -> 3606.2525
A17: Combined gross for income tax estimate | B17: =B4+B7-B15 -> 132439.29
A18: Standard deduction (approx.; 2025-style) | B18: =IF(B3="Single",15000,IF(B3="Married Filing Jointly",30000,IF(B3="Head of Household",22500,15000))) -> 15000
A19: Taxable income (federal, rough) | B19: =MAX(0,B17-B18) -> 117439.29
A20: Federal income tax (approx.; ordinary brackets) | B20: =IF(B3="Married Filing Jointly",IF(B19<=0,0,IF(B19<=23850,B19*0.1,IF(B19<=96950,2385+(B19-23850)*0.12,IF(B19<=206700,11157+(B19-96950)*0.22,IF(B19<=394600,35302+(B19-206700)*0.24,IF(B19<=501050,80398+(B19-394600)*0.32,IF(B19<=1252700,114462+(B19-501050)*0.35,114462+(1252700-501050)*0.35+(B19-1252700)*0.37))))))),IF(B3="Head of Household",IF(B19<=0,0,IF(B19<=17025,B19*0.1,IF(B19<=69250,1702.5+(B19-17025)*0.12,IF(B19<=110150,7975.5+(B19-69250)*0.22,IF(B19<=210300,18993+(B19-110150)*0.24,IF(B19<=267450,43029+(B19-210300)*0.32,IF(B19<=626350,61317+(B19-267450)*0.35,61317+(626350-267450)*0.35+(B19-626350)*0.37))))))),IF(B19<=0,0,IF(B19<=11925,B19*0.1,IF(B19<=48475,1192.5+(B19-11925)*0.12,IF(B19<=103350,5578.5+(B19-48475)*0.22,IF(B19<=197300,17651+(B19-103350)*0.24,IF(B19<=250525,40199+(B19-197300)*0.32,IF(B19<=626350,57231+(B19-250525)*0.35,57231+(626350-250525)*0.35+(B19-626350)*0.37))))))))) -> 21032.429
A21: Tax already withheld (W-2) | B21: =B5 -> 12800
A22: Remaining tax owed (income + SE - withheld) | B22: =B20+B14-B21 -> 15444.934
A23: Quarterly payment target (1/4 of remaining) | B23: =MAX(0,B22/4) -> 3861.2335
A25: Quarterly estimated payments
A26: Quarter | B26: Due date | C26: Amount owed | D26: Amount paid | E26: Remaining
A27: Q1 | B27: Apr 15 | C27: =$B$23 -> 3861.2335 | D27: 0 | E27: =C27-D27 -> 3861.2335
A28: Q2 | B28: Jun 15 | C28: =$B$23 -> 3861.2335 | D28: 0 | E28: =C28-D28 -> 3861.2335
A29: Q3 | B29: Sep 15 | C29: =$B$23 -> 3861.2335 | D29: 0 | E29: =C29-D29 -> 3861.2335
A30: Q4 | B30: Jan 15 (next year) | C30: =$B$23 -> 3861.2335 | D30: 0 | E30: =C30-D30 -> 3861.2335

Sheet Schedule C Preview
A1: Line | B1: Description | C1: Amount | D1: Source / notes
A2: 1 | B2: Gross receipts (after platform fees) | C2: =SUM('Revenue Log'!$E$2:$E$500)-SUM('Revenue Log'!$F$2:$F$500) -> 55687 | D2: Matches Revenue Log E minus F so net ties Monthly P&L
A3: 2 | B3: Returns and allowances | C3: 0
A4: 3 | B4: Net receipts | C4: =C2-C3 -> 55687 | D4: Line 1 minus line 2
A5: 4 | B5: Cost of goods sold | C5: 0 | D5: Most freelancers leave 0
A6: 5 | B6: Gross profit | C6: =C4-C5 -> 55687 | D6: Net receipts (line 3 $) minus COGS (line 4 $)
B7: Expenses
A8: 8 | B8: Advertising / marketing | C8: =SUMIFS('Expense Log'!$D$2:$D$500,'Expense Log'!$E$2:$E$500,"Marketing") -> 211.88 | D8: Expense category Marketing
A9: 10 | B9: Car and truck (not tracked here) | C9: 0
A10: 13 | B10: Depreciation (not tracked here) | C10: 0
A11: 17 | B11: Legal and professional | C11: =SUMIFS('Expense Log'!$D$2:$D$500,'Expense Log'!$E$2:$E$500,"Professional Services") -> 794 | D11: Expense category
A12: 18 | B12: Office expense (supplies + home office) | C12: =SUMIFS('Expense Log'!$D$2:$D$500,'Expense Log'!$E$2:$E$500,"Office Supplies")+SUMIFS('Expense Log'!$D$2:$D$500,'Expense Log'!$E$2:$E$500,"Home Office") -> 441.65 | D12: Two categories summed
A13: 22 | B13: Supplies (equipment purchases) | C13: =SUMIFS('Expense Log'!$D$2:$D$500,'Expense Log'!$E$2:$E$500,"Equipment") -> 1028 | D13: Equipment mapped here
A14: 24a | B14: Travel | C14: =SUMIFS('Expense Log'!$D$2:$D$500,'Expense Log'!$E$2:$E$500,"Travel") -> 1012.5 | D14: Expense category Travel
A15: 24b | B15: Meals (50% deductible portion) | C15: =SUMIFS('Expense Log'!$G$2:$G$500,'Expense Log'!$E$2:$E$500,"Meals (50%)") -> 104.4 | D15: Expense Log column G
A16: 25 | B16: Utilities / phone / internet | C16: =SUMIFS('Expense Log'!$D$2:$D$500,'Expense Log'!$E$2:$E$500,"Phone/Internet") -> 220
A17: 27 | B17: Other (software, education, insurance, misc.) | C17: =SUMIFS('Expense Log'!$D$2:$D$500,'Expense Log'!$E$2:$E$500,"Software/Subscriptions")+SUMIFS('Expense Log'!$D$2:$D$500,'Expense Log'!$E$2:$E$500,"Education/Training")+SUMIFS('Expense Log'!$D$2:$D$500,'Expense Log'!$E$2:$E$500,"Insurance")+SUMIFS('Expense Log'!$D$2:$D$500,'Expense Log'!$E$2:$E$500,"Other") -> 829.03 | D17: Rolled categories
A18: 28 | B18: Total expenses | C18: =SUM(C8:C17) -> 4641.46 | D18: Sum of expense lines above
A19: 31 | B19: Net profit or loss | C19: =C6-C18 -> 51045.54 | D19: Should match Monthly P&L annual net profit
B20: Check (P&L vs Schedule C) | C20: =ABS(C19-'Monthly P&L'!$G$14)<0.01 -> TRUE | D20: TRUE if tie-out within a penny
