Workbook

Sheet This Year
B2: This Year (2025)
C3: Jan | D3: Feb | E3: Mar | F3: Apr | G3: May | H3: Jun | I3: Jul | J3: Aug | K3: Sep | L3: Oct | M3: Nov | N3: Dec | O3: Annual Total | P3: Monthly Avg
B4: Monthly Income | C4: 5200 | D4: 5200 | E4: 5200 | F4: 5200 | G4: 5200 | H4: 5200 | I4: 5200 | J4: 5200 | K4: 5200 | L4: 5200 | M4: 5200 | N4: 5200 | O4: =SUM(C4:N4) | P4: =O4/12
B6: Spending by Category
B7: Category | C7: Jan | D7: Feb | E7: Mar | F7: Apr | G7: May | H7: Jun | I7: Jul | J7: Aug | K7: Sep | L7: Oct | M7: Nov | N7: Dec | O7: Annual Total | P7: Monthly Avg
B8: Rent/Mortgage | C8: 1791 | D8: 1425 | E8: 1566 | F8: 1770 | G8: 1296 | H8: 1512 | I8: 1563 | J8: 1835 | K8: 1149 | L8: 1177 | M8: 1365 | N8: 1744 | O8: =SUM(C8:N8) | P8: =O8/12
B9: Utilities | C9: 227 | D9: 158 | E9: 188 | F9: 157 | G9: 191 | H9: 189 | I9: 154 | J9: 240 | K9: 153 | L9: 128 | M9: 152 | N9: 122 | O9: =SUM(C9:N9) | P9: =O9/12
B10: Groceries | C10: 472 | D10: 429 | E10: 338 | F10: 363 | G10: 421 | H10: 478 | I10: 373 | J10: 337 | K10: 389 | L10: 329 | M10: 385 | N10: 498 | O10: =SUM(C10:N10) | P10: =O10/12
B11: Gas | C11: 109 | D11: 117 | E11: 148 | F11: 111 | G11: 105 | H11: 114 | I11: 137 | J11: 144 | K11: 141 | L11: 102 | M11: 116 | N11: 105 | O11: =SUM(C11:N11) | P11: =O11/12
B12: Auto Insurance | C12: 113 | D12: 103 | E12: 124 | F12: 114 | G12: 115 | H12: 92 | I12: 112 | J12: 86 | K12: 88 | L12: 130 | M12: 92 | N12: 83 | O12: =SUM(C12:N12) | P12: =O12/12
B13: Health Insurance | C13: 222 | D13: 169 | E13: 180 | F13: 207 | G13: 244 | H13: 152 | I13: 215 | J13: 154 | K13: 227 | L13: 187 | M13: 159 | N13: 189 | O13: =SUM(C13:N13) | P13: =O13/12
B14: Phone/Internet | C14: 129 | D14: 98 | E14: 113 | F14: 137 | G14: 139 | H14: 134 | I14: 118 | J14: 132 | K14: 99 | L14: 113 | M14: 109 | N14: 98 | O14: =SUM(C14:N14) | P14: =O14/12
B15: Dining Out | C15: 131 | D15: 132 | E15: 210 | F15: 160 | G15: 155 | H15: 183 | I15: 189 | J15: 204 | K15: 205 | L15: 132 | M15: 149 | N15: 161 | O15: =SUM(C15:N15) | P15: =O15/12
B16: Coffee | C16: 41 | D16: 46 | E16: 39 | F16: 54 | G16: 41 | H16: 54 | I16: 55 | J16: 49 | K16: 40 | L16: 35 | M16: 56 | N16: 55 | O16: =SUM(C16:N16) | P16: =O16/12
B17: Entertainment | C17: 75 | D17: 59 | E17: 85 | F17: 67 | G17: 73 | H17: 93 | I17: 91 | J17: 88 | K17: 59 | L17: 81 | M17: 79 | N17: 83 | O17: =SUM(C17:N17) | P17: =O17/12
B18: Clothing | C18: 49 | D18: 78 | E18: 54 | F18: 49 | G18: 70 | H18: 73 | I18: 72 | J18: 52 | K18: 56 | L18: 66 | M18: 68 | N18: 73 | O18: =SUM(C18:N18) | P18: =O18/12
B19: Subscriptions | C19: 42 | D19: 59 | E19: 47 | F19: 51 | G19: 46 | H19: 55 | I19: 48 | J19: 58 | K19: 49 | L19: 45 | M19: 50 | N19: 49 | O19: =SUM(C19:N19) | P19: =O19/12
... B27: Miscellaneous | C27: 73 | D27: 55 | E27: 56 | F27: 67 | G27: 67 | H27: 54 | I27: 47 | J27: 49 | K27: 53 | L27: 46 | M27: 67 | N27: 57 | O27: =SUM(C27:N27) | P27: =O27/12
B28: Total Spent | C28: =SUM(C8:C27) | D28: =SUM(D8:D27) | E28: =SUM(E8:E27) | F28: =SUM(F8:F27) | G28: =SUM(G8:G27) | H28: =SUM(H8:H27) | I28: =SUM(I8:I27) | J28: =SUM(J8:J27) | ... N28: =SUM(N8:N27) | O28: =SUM(C28:N28)
B29: Savings Rate | C29: =IFERROR((C4-C28)/C4,0) | D29: =IFERROR((D4-D28)/D4,0) | E29: =IFERROR((E4-E28)/E4,0) | F29: =IFERROR((F4-F28)/F4,0) | G29: =IFERROR((G4-G28)/G4,0) | H29: =IFERROR((H4-H28)/H4,0) | I29: =IFERROR((I4-I28)/I4,0) | J29: =IFERROR((J4-J28)/J4,0) | ... O29: =IFERROR((O4-O28)/O4,0)

Sheet Prior Year
B2: Prior Year (2024)
C3: Jan | D3: Feb | E3: Mar | F3: Apr | G3: May | H3: Jun | I3: Jul | J3: Aug | K3: Sep | L3: Oct | M3: Nov | N3: Dec | O3: Annual Total | P3: Monthly Avg
B4: Monthly Income | C4: 5000 | D4: 5000 | E4: 5000 | F4: 5000 | G4: 5000 | H4: 5000 | I4: 5000 | J4: 5000 | K4: 5000 | L4: 5000 | M4: 5000 | N4: 5000 | O4: =SUM(C4:N4) | P4: =O4/12
B6: Spending by Category
B7: Category | C7: Jan | D7: Feb | E7: Mar | F7: Apr | G7: May | H7: Jun | I7: Jul | J7: Aug | K7: Sep | L7: Oct | M7: Nov | N7: Dec | O7: Annual Total | P7: Monthly Avg
B8: Rent/Mortgage | C8: 1199 | D8: 1024 | E8: 1017 | F8: 1281 | G8: 1388 | H8: 1018 | I8: 1443 | J8: 1235 | K8: 1087 | L8: 1413 | M8: 1281 | N8: 1233 | O8: =SUM(C8:N8) | P8: =O8/12
B9: Utilities | C9: 200 | D9: 169 | E9: 122 | F9: 133 | G9: 159 | H9: 108 | I9: 178 | J9: 200 | K9: 141 | L9: 105 | M9: 149 | N9: 132 | O9: =SUM(C9:N9) | P9: =O9/12
B10: Groceries | C10: 304 | D10: 398 | E10: 429 | F10: 403 | G10: 443 | H10: 298 | I10: 451 | J10: 426 | K10: 335 | L10: 368 | M10: 422 | N10: 406 | O10: =SUM(C10:N10) | P10: =O10/12
B11: Gas | C11: 118 | D11: 100 | E11: 118 | F11: 143 | G11: 140 | H11: 103 | I11: 91 | J11: 113 | K11: 124 | L11: 143 | M11: 142 | N11: 121 | O11: =SUM(C11:N11) | P11: =O11/12
B12: Auto Insurance | C12: 90 | D12: 116 | E12: 105 | F12: 81 | G12: 99 | H12: 107 | I12: 98 | J12: 105 | K12: 116 | L12: 123 | M12: 105 | N12: 83 | O12: =SUM(C12:N12) | P12: =O12/12
B13: Health Insurance | C13: 228 | D13: 212 | E13: 182 | F13: 185 | G13: 227 | H13: 143 | I13: 197 | J13: 184 | K13: 229 | L13: 154 | M13: 223 | N13: 155 | O13: =SUM(C13:N13) | P13: =O13/12
B14: Phone/Internet | C14: 98 | D14: 124 | E14: 100 | F14: 90 | G14: 95 | H14: 103 | I14: 85 | J14: 130 | K14: 105 | L14: 97 | M14: 117 | N14: 109 | O14: =SUM(C14:N14) | P14: =O14/12
B15: Dining Out | C15: 139 | D15: 195 | E15: 170 | F15: 144 | G15: 195 | H15: 174 | I15: 135 | J15: 184 | K15: 158 | L15: 137 | M15: 128 | N15: 184 | O15: =SUM(C15:N15) | P15: =O15/12
B16: Coffee | C16: 31 | D16: 42 | E16: 38 | F16: 32 | G16: 38 | H16: 29 | I16: 37 | J16: 29 | K16: 36 | L16: 29 | M16: 44 | N16: 43 | O16: =SUM(C16:N16) | P16: =O16/12
B17: Entertainment | C17: 54 | D17: 82 | E17: 77 | F17: 56 | G17: 66 | H17: 69 | I17: 79 | J17: 55 | K17: 76 | L17: 64 | M17: 52 | N17: 60 | O17: =SUM(C17:N17) | P17: =O17/12
B18: Clothing | C18: 46 | D18: 66 | E18: 65 | F18: 44 | G18: 68 | H18: 62 | I18: 63 | J18: 63 | K18: 64 | L18: 67 | M18: 56 | N18: 67 | O18: =SUM(C18:N18) | P18: =O18/12
B19: Subscriptions | C19: 63 | D19: 61 | E19: 46 | F19: 61 | G19: 52 | H19: 49 | I19: 61 | J19: 42 | K19: 50 | L19: 44 | M19: 61 | N19: 64 | O19: =SUM(C19:N19) | P19: =O19/12
... B27: Miscellaneous | C27: 41 | D27: 36 | E27: 39 | F27: 55 | G27: 44 | H27: 45 | I27: 56 | J27: 41 | K27: 60 | L27: 38 | M27: 37 | N27: 53 | O27: =SUM(C27:N27) | P27: =O27/12
B28: Total Spent | C28: =SUM(C8:C27) | D28: =SUM(D8:D27) | E28: =SUM(E8:E27) | F28: =SUM(F8:F27) | G28: =SUM(G8:G27) | H28: =SUM(H8:H27) | I28: =SUM(I8:I27) | J28: =SUM(J8:J27) | ... N28: =SUM(N8:N27) | O28: =SUM(C28:N28)
B29: Savings Rate | C29: =IFERROR((C4-C28)/C4,0) | D29: =IFERROR((D4-D28)/D4,0) | E29: =IFERROR((E4-E28)/E4,0) | F29: =IFERROR((F4-F28)/F4,0) | G29: =IFERROR((G4-G28)/G4,0) | H29: =IFERROR((H4-H28)/H4,0) | I29: =IFERROR((I4-I28)/I4,0) | J29: =IFERROR((J4-J28)/J4,0) | ... O29: =IFERROR((O4-O28)/O4,0)

Sheet Category Stats
B2: Category Statistics (This Year)
B3: Category | C3: Annual Total | D3: Monthly Avg | E3: Highest Month | F3: Lowest Month | G3: Std Dev | H3: Coeff of Variation
B4: Rent/Mortgage | C4: ='This Year'!O8 | D4: ='This Year'!P8 | E4: =MAX('This Year'!C8:N8) | F4: =MIN('This Year'!C8:N8) | G4: =STDEV('This Year'!C8:N8) | H4: =IFERROR(G4/D4,0)
B5: Utilities | C5: ='This Year'!O9 | D5: ='This Year'!P9 | E5: =MAX('This Year'!C9:N9) | F5: =MIN('This Year'!C9:N9) | G5: =STDEV('This Year'!C9:N9) | H5: =IFERROR(G5/D5,0)
B6: Groceries | C6: ='This Year'!O10 | D6: ='This Year'!P10 | E6: =MAX('This Year'!C10:N10) | F6: =MIN('This Year'!C10:N10) | G6: =STDEV('This Year'!C10:N10) | H6: =IFERROR(G6/D6,0)
B7: Gas | C7: ='This Year'!O11 | D7: ='This Year'!P11 | E7: =MAX('This Year'!C11:N11) | F7: =MIN('This Year'!C11:N11) | G7: =STDEV('This Year'!C11:N11) | H7: =IFERROR(G7/D7,0)
B8: Auto Insurance | C8: ='This Year'!O12 | D8: ='This Year'!P12 | E8: =MAX('This Year'!C12:N12) | F8: =MIN('This Year'!C12:N12) | G8: =STDEV('This Year'!C12:N12) | H8: =IFERROR(G8/D8,0)
B9: Health Insurance | C9: ='This Year'!O13 | D9: ='This Year'!P13 | E9: =MAX('This Year'!C13:N13) | F9: =MIN('This Year'!C13:N13) | G9: =STDEV('This Year'!C13:N13) | H9: =IFERROR(G9/D9,0)
B10: Phone/Internet | C10: ='This Year'!O14 | D10: ='This Year'!P14 | E10: =MAX('This Year'!C14:N14) | F10: =MIN('This Year'!C14:N14) | G10: =STDEV('This Year'!C14:N14) | H10: =IFERROR(G10/D10,0)
B11: Dining Out | C11: ='This Year'!O15 | D11: ='This Year'!P15 | E11: =MAX('This Year'!C15:N15) | F11: =MIN('This Year'!C15:N15) | G11: =STDEV('This Year'!C15:N15) | H11: =IFERROR(G11/D11,0)
B12: Coffee | C12: ='This Year'!O16 | D12: ='This Year'!P16 | E12: =MAX('This Year'!C16:N16) | F12: =MIN('This Year'!C16:N16) | G12: =STDEV('This Year'!C16:N16) | H12: =IFERROR(G12/D12,0)
B13: Entertainment | C13: ='This Year'!O17 | D13: ='This Year'!P17 | E13: =MAX('This Year'!C17:N17) | F13: =MIN('This Year'!C17:N17) | G13: =STDEV('This Year'!C17:N17) | H13: =IFERROR(G13/D13,0)
B14: Clothing | C14: ='This Year'!O18 | D14: ='This Year'!P18 | E14: =MAX('This Year'!C18:N18) | F14: =MIN('This Year'!C18:N18) | G14: =STDEV('This Year'!C18:N18) | H14: =IFERROR(G14/D14,0)
B15: Subscriptions | C15: ='This Year'!O19 | D15: ='This Year'!P19 | E15: =MAX('This Year'!C19:N19) | F15: =MIN('This Year'!C19:N19) | G15: =STDEV('This Year'!C19:N19) | H15: =IFERROR(G15/D15,0)
... B23: Miscellaneous | C23: ='This Year'!O27 | D23: ='This Year'!P27 | E23: =MAX('This Year'!C27:N27) | F23: =MIN('This Year'!C27:N27) | G23: =STDEV('This Year'!C27:N27) | H23: =IFERROR(G23/D23,0)

Sheet YoY Comparison
B2: Year-over-Year Comparison
B3: Category | C3: This Year | D3: Prior Year | E3: $ Change | F3: % Change | G3: Rank (abs)
B4: Rent/Mortgage | C4: ='This Year'!O8 | D4: =IFERROR('Prior Year'!O8,0) | E4: =C4-D4 | F4: =IFERROR(E4/D4,0) | G4: =1+SUMPRODUCT(--(ABS($E$4:$E$23)>ABS(E4)))
B5: Utilities | C5: ='This Year'!O9 | D5: =IFERROR('Prior Year'!O9,0) | E5: =C5-D5 | F5: =IFERROR(E5/D5,0) | G5: =1+SUMPRODUCT(--(ABS($E$4:$E$23)>ABS(E5)))
B6: Groceries | C6: ='This Year'!O10 | D6: =IFERROR('Prior Year'!O10,0) | E6: =C6-D6 | F6: =IFERROR(E6/D6,0) | G6: =1+SUMPRODUCT(--(ABS($E$4:$E$23)>ABS(E6)))
B7: Gas | C7: ='This Year'!O11 | D7: =IFERROR('Prior Year'!O11,0) | E7: =C7-D7 | F7: =IFERROR(E7/D7,0) | G7: =1+SUMPRODUCT(--(ABS($E$4:$E$23)>ABS(E7)))
B8: Auto Insurance | C8: ='This Year'!O12 | D8: =IFERROR('Prior Year'!O12,0) | E8: =C8-D8 | F8: =IFERROR(E8/D8,0) | G8: =1+SUMPRODUCT(--(ABS($E$4:$E$23)>ABS(E8)))
B9: Health Insurance | C9: ='This Year'!O13 | D9: =IFERROR('Prior Year'!O13,0) | E9: =C9-D9 | F9: =IFERROR(E9/D9,0) | G9: =1+SUMPRODUCT(--(ABS($E$4:$E$23)>ABS(E9)))
B10: Phone/Internet | C10: ='This Year'!O14 | D10: =IFERROR('Prior Year'!O14,0) | E10: =C10-D10 | F10: =IFERROR(E10/D10,0) | G10: =1+SUMPRODUCT(--(ABS($E$4:$E$23)>ABS(E10)))
B11: Dining Out | C11: ='This Year'!O15 | D11: =IFERROR('Prior Year'!O15,0) | E11: =C11-D11 | F11: =IFERROR(E11/D11,0) | G11: =1+SUMPRODUCT(--(ABS($E$4:$E$23)>ABS(E11)))
B12: Coffee | C12: ='This Year'!O16 | D12: =IFERROR('Prior Year'!O16,0) | E12: =C12-D12 | F12: =IFERROR(E12/D12,0) | G12: =1+SUMPRODUCT(--(ABS($E$4:$E$23)>ABS(E12)))
B13: Entertainment | C13: ='This Year'!O17 | D13: =IFERROR('Prior Year'!O17,0) | E13: =C13-D13 | F13: =IFERROR(E13/D13,0) | G13: =1+SUMPRODUCT(--(ABS($E$4:$E$23)>ABS(E13)))
B14: Clothing | C14: ='This Year'!O18 | D14: =IFERROR('Prior Year'!O18,0) | E14: =C14-D14 | F14: =IFERROR(E14/D14,0) | G14: =1+SUMPRODUCT(--(ABS($E$4:$E$23)>ABS(E14)))
B15: Subscriptions | C15: ='This Year'!O19 | D15: =IFERROR('Prior Year'!O19,0) | E15: =C15-D15 | F15: =IFERROR(E15/D15,0) | G15: =1+SUMPRODUCT(--(ABS($E$4:$E$23)>ABS(E15)))
... B23: Miscellaneous | C23: ='This Year'!O27 | D23: =IFERROR('Prior Year'!O27,0) | E23: =C23-D23 | F23: =IFERROR(E23/D23,0) | G23: =1+SUMPRODUCT(--(ABS($E$4:$E$23)>ABS(E23)))
B25: Summary
B26: Total This Year | C26: =SUM(C4:C23)
B27: Total Prior Year | C27: =SUM(D4:D23)
B28: Net Change | C28: =C26-C27
B30: Top 3 Increases
B31: =INDEX(B4:B23,MATCH(LARGE(E4:E23,1),E4:E23,0)) | C31: =LARGE(E4:E23,1)
B32: =INDEX(B4:B23,MATCH(LARGE(E4:E23,2),E4:E23,0)) | C32: =LARGE(E4:E23,2)
B33: =INDEX(B4:B23,MATCH(LARGE(E4:E23,3),E4:E23,0)) | C33: =LARGE(E4:E23,3)
B35: Top 3 Decreases
B36: =INDEX(B4:B23,MATCH(SMALL(E4:E23,1),E4:E23,0)) | C36: =SMALL(E4:E23,1)
B37: =INDEX(B4:B23,MATCH(SMALL(E4:E23,2),E4:E23,0)) | C37: =SMALL(E4:E23,2)
B38: =INDEX(B4:B23,MATCH(SMALL(E4:E23,3),E4:E23,0)) | C38: =SMALL(E4:E23,3)

Sheet Forecast
B2: Next Year Forecast
B3: Category | C3: Trailing 6-Mo Avg | D3: Override | E3: Projected Monthly | F3: Projected Annual | G3: vs This Year
B4: Rent/Mortgage | C4: =AVERAGE('This Year'!I8:N8) | E4: =IF(D4<>"",D4,C4) | F4: =E4*12 | G4: =F4-'This Year'!O8
B5: Utilities | C5: =AVERAGE('This Year'!I9:N9) | E5: =IF(D5<>"",D5,C5) | F5: =E5*12 | G5: =F5-'This Year'!O9
B6: Groceries | C6: =AVERAGE('This Year'!I10:N10) | E6: =IF(D6<>"",D6,C6) | F6: =E6*12 | G6: =F6-'This Year'!O10
B7: Gas | C7: =AVERAGE('This Year'!I11:N11) | E7: =IF(D7<>"",D7,C7) | F7: =E7*12 | G7: =F7-'This Year'!O11
B8: Auto Insurance | C8: =AVERAGE('This Year'!I12:N12) | E8: =IF(D8<>"",D8,C8) | F8: =E8*12 | G8: =F8-'This Year'!O12
B9: Health Insurance | C9: =AVERAGE('This Year'!I13:N13) | E9: =IF(D9<>"",D9,C9) | F9: =E9*12 | G9: =F9-'This Year'!O13
B10: Phone/Internet | C10: =AVERAGE('This Year'!I14:N14) | E10: =IF(D10<>"",D10,C10) | F10: =E10*12 | G10: =F10-'This Year'!O14
B11: Dining Out | C11: =AVERAGE('This Year'!I15:N15) | E11: =IF(D11<>"",D11,C11) | F11: =E11*12 | G11: =F11-'This Year'!O15
B12: Coffee | C12: =AVERAGE('This Year'!I16:N16) | E12: =IF(D12<>"",D12,C12) | F12: =E12*12 | G12: =F12-'This Year'!O16
B13: Entertainment | C13: =AVERAGE('This Year'!I17:N17) | E13: =IF(D13<>"",D13,C13) | F13: =E13*12 | G13: =F13-'This Year'!O17
B14: Clothing | C14: =AVERAGE('This Year'!I18:N18) | E14: =IF(D14<>"",D14,C14) | F14: =E14*12 | G14: =F14-'This Year'!O18
B15: Subscriptions | C15: =AVERAGE('This Year'!I19:N19) | E15: =IF(D15<>"",D15,C15) | F15: =E15*12 | G15: =F15-'This Year'!O19
... B23: Miscellaneous | C23: =AVERAGE('This Year'!I27:N27) | E23: =IF(D23<>"",D23,C23) | F23: =E23*12 | G23: =F23-'This Year'!O27
B25: Projected Total | F25: =SUM(F4:F23)
B26: This Year Total | F26: ='This Year'!O28
B27: Projected Change | F27: =F25-F26

Sheet Summary
B2: Annual Summary
B4: KPIs
B5: Total Spent This Year | C5: ='This Year'!O28
B6: Total Spent Prior Year | C6: ='Prior Year'!O28
B7: Savings Rate This Year | C7: ='This Year'!O29
B8: Projected Next Year | C8: =Forecast!F25
B11: Month | C11: This Year | D11: Prior Year
B12: Jan | C12: ='This Year'!C28 | D12: =IFERROR('Prior Year'!C28,0)
B13: Feb | C13: ='This Year'!D28 | D13: =IFERROR('Prior Year'!D28,0)
B14: Mar | C14: ='This Year'!E28 | D14: =IFERROR('Prior Year'!E28,0)
B15: Apr | C15: ='This Year'!F28 | D15: =IFERROR('Prior Year'!F28,0)
B16: May | C16: ='This Year'!G28 | D16: =IFERROR('Prior Year'!G28,0)
B17: Jun | C17: ='This Year'!H28 | D17: =IFERROR('Prior Year'!H28,0)
B18: Jul | C18: ='This Year'!I28 | D18: =IFERROR('Prior Year'!I28,0)
B19: Aug | C19: ='This Year'!J28 | D19: =IFERROR('Prior Year'!J28,0)
B20: Sep | C20: ='This Year'!K28 | D20: =IFERROR('Prior Year'!K28,0)
B21: Oct | C21: ='This Year'!L28 | D21: =IFERROR('Prior Year'!L28,0)
B22: Nov | C22: ='This Year'!M28 | D22: =IFERROR('Prior Year'!M28,0)
B23: Dec | C23: ='This Year'!N28 | D23: =IFERROR('Prior Year'!N28,0)
B26: Category | C26: $ Change
B27: ='YoY Comparison'!B4 | C27: ='YoY Comparison'!E4
B28: ='YoY Comparison'!B5 | C28: ='YoY Comparison'!E5
B29: ='YoY Comparison'!B6 | C29: ='YoY Comparison'!E6
B30: ='YoY Comparison'!B7 | C30: ='YoY Comparison'!E7
B31: ='YoY Comparison'!B8 | C31: ='YoY Comparison'!E8
B32: ='YoY Comparison'!B9 | C32: ='YoY Comparison'!E9
B33: ='YoY Comparison'!B10 | C33: ='YoY Comparison'!E10
B34: ='YoY Comparison'!B11 | C34: ='YoY Comparison'!E11
B35: ='YoY Comparison'!B12 | C35: ='YoY Comparison'!E12
B36: ='YoY Comparison'!B13 | C36: ='YoY Comparison'!E13
B37: ='YoY Comparison'!B14 | C37: ='YoY Comparison'!E14
B38: ='YoY Comparison'!B15 | C38: ='YoY Comparison'!E15
... B46: ='YoY Comparison'!B23 | C46: ='YoY Comparison'!E23

Sheet Readme
C3: Annual Spending Review
C5: This Year uses sample 2025 data. Prior Year uses sample 2024 data.
C6: All amounts are fictional.
C7: Enter or paste your own monthly spending into This Year and Prior Year.
C8: Category Stats and YoY Comparison update automatically.
C9: Use the Override column on the Forecast sheet to adjust projections.
C10: Do not insert or delete rows inside the category ranges.
C11: This is not financial advice. Talk to a professional about your situation.
