Workbook

Sheet Property & Loan
A1: Property Type | B1: Duplex | D1: Overview
A2: Purchase Price | B2: 425000 | D2: Tenant rent offset | E2: ='Monthly Housing Cost'!D2 -> 2555.5
A3: Down Payment (%) | B3: 0.035 | D3: Owner net housing cost | E3: ='Monthly Housing Cost'!L2 -> 1263.7995
A4: Loan Amount | B4: =B2*(1-B3) -> 410125 | D4: Savings vs current rent | E4: ='Monthly Housing Cost'!M2 -> 686.20052
A5: Interest Rate | B5: 0.066 | D5: Break-even occupancy | E5: =IF('Unit Rent Roll'!B8=0,0,('Property & Loan'!B7+'Property & Loan'!B8+'Property & Loan'!B9+'Property & Loan'!B10+'Property & Loan'!B11+'Property & Loan'!B12+'Property & Loan'!B13)/'Unit Rent Roll'!B8) -> 1.4198139
A6: Term (years) | B6: 30
A7: Monthly P&I | B7: =PMT(B5/12,B6*12,-B4) -> 2619.2995
A8: Property Tax (monthly) | B8: 425
A9: Insurance (monthly) | B9: 155
A10: PMI (monthly) | B10: 180
A11: Utilities / Common (monthly) | B11: 140
A12: Maintenance Reserve (monthly) | B12: 175
A13: CapEx Reserve (monthly) | B13: 125
A14: Current Rent Alternative | B14: 1950
A15: Vacancy Assumption | B15: 0.05
A16: Annual Rent Growth | B16: 0.03

Sheet Unit Rent Roll
A1: Unit | B1: Status | C1: Bedrooms | D1: Market Rent | E1: In-Place Rent | F1: Utility Share | G1: Net Rent to Owner
A2: Unit 1 | B2: Owner | C2: 2 | D2: 0 | E2: 0 | F2: 0 | G2: =IF(B2="Owner",0,E2-F2) -> 0
A3: Unit 2 | B3: Rented | C3: 2 | D3: 1450 | E3: 1425 | F3: 35 | G3: =IF(B3="Owner",0,E3-F3) -> 1390
A4: Unit 3 | B4: Rented | C4: 1 | D4: 1350 | E4: 1325 | F4: 25 | G4: =IF(B4="Owner",0,E4-F4) -> 1300
A7: Rent Roll Summary
A8: Gross potential tenant rent | B8: =SUMIF(B2:B4,"Rented",G2:G4) -> 2690
A9: Effective tenant rent after vacancy | B9: =B8*(1-'Property & Loan'!B15) -> 2555.5
A10: Average rentable-unit rent | B10: =IF(COUNTIF(B2:B4,"Rented")=0,0,B8/COUNTIF(B2:B4,"Rented")) -> 1345

Sheet Monthly Housing Cost
A1: Month | B1: Gross Tenant Rent | C1: Vacancy Loss | D1: Effective Tenant Rent | E1: Mortgage P&I | F1: Tax | G1: Insurance | H1: PMI | I1: Utilities / Common | J1: Maintenance | K1: CapEx | L1: Owner Net Housing Cost | M1: Savings vs Current Rent
A2: Jan | B2: ='Unit Rent Roll'!B8 -> 2690 | C2: =B2*'Property & Loan'!$B$15*-1 -> -134.5 | D2: =B2+C2 -> 2555.5 | E2: ='Property & Loan'!$B$7 -> 2619.2995 | F2: ='Property & Loan'!$B$8 -> 425 | G2: ='Property & Loan'!$B$9 -> 155 | H2: ='Property & Loan'!$B$10 -> 180 | I2: ='Property & Loan'!$B$11 -> 140 | J2: ='Property & Loan'!$B$12 -> 175 | K2: ='Property & Loan'!$B$13 -> 125 | L2: =SUM(E2:K2)-D2 -> 1263.7995 | M2: ='Property & Loan'!$B$14-L2 -> 686.20052
A3: Feb | B3: ='Unit Rent Roll'!B8 -> 2690 | C3: =B3*'Property & Loan'!$B$15*-1 -> -134.5 | D3: =B3+C3 -> 2555.5 | E3: ='Property & Loan'!$B$7 -> 2619.2995 | F3: ='Property & Loan'!$B$8 -> 425 | G3: ='Property & Loan'!$B$9 -> 155 | H3: ='Property & Loan'!$B$10 -> 180 | I3: ='Property & Loan'!$B$11 -> 140 | J3: ='Property & Loan'!$B$12 -> 175 | K3: ='Property & Loan'!$B$13 -> 125 | L3: =SUM(E3:K3)-D3 -> 1263.7995 | M3: ='Property & Loan'!$B$14-L3 -> 686.20052
A4: Mar | B4: ='Unit Rent Roll'!B8 -> 2690 | C4: =B4*'Property & Loan'!$B$15*-1 -> -134.5 | D4: =B4+C4 -> 2555.5 | E4: ='Property & Loan'!$B$7 -> 2619.2995 | F4: ='Property & Loan'!$B$8 -> 425 | G4: ='Property & Loan'!$B$9 -> 155 | H4: ='Property & Loan'!$B$10 -> 180 | I4: ='Property & Loan'!$B$11 -> 140 | J4: ='Property & Loan'!$B$12 -> 175 | K4: ='Property & Loan'!$B$13 -> 125 | L4: =SUM(E4:K4)-D4 -> 1263.7995 | M4: ='Property & Loan'!$B$14-L4 -> 686.20052
A5: Apr | B5: ='Unit Rent Roll'!B8 -> 2690 | C5: =B5*'Property & Loan'!$B$15*-1 -> -134.5 | D5: =B5+C5 -> 2555.5 | E5: ='Property & Loan'!$B$7 -> 2619.2995 | F5: ='Property & Loan'!$B$8 -> 425 | G5: ='Property & Loan'!$B$9 -> 155 | H5: ='Property & Loan'!$B$10 -> 180 | I5: ='Property & Loan'!$B$11 -> 140 | J5: ='Property & Loan'!$B$12 -> 175 | K5: ='Property & Loan'!$B$13 -> 125 | L5: =SUM(E5:K5)-D5 -> 1263.7995 | M5: ='Property & Loan'!$B$14-L5 -> 686.20052
A6: May | B6: ='Unit Rent Roll'!B8 -> 2690 | C6: =B6*'Property & Loan'!$B$15*-1 -> -134.5 | D6: =B6+C6 -> 2555.5 | E6: ='Property & Loan'!$B$7 -> 2619.2995 | F6: ='Property & Loan'!$B$8 -> 425 | G6: ='Property & Loan'!$B$9 -> 155 | H6: ='Property & Loan'!$B$10 -> 180 | I6: ='Property & Loan'!$B$11 -> 140 | J6: ='Property & Loan'!$B$12 -> 175 | K6: ='Property & Loan'!$B$13 -> 125 | L6: =SUM(E6:K6)-D6 -> 1263.7995 | M6: ='Property & Loan'!$B$14-L6 -> 686.20052
A7: Jun | B7: ='Unit Rent Roll'!B8 -> 2690 | C7: =B7*'Property & Loan'!$B$15*-1 -> -134.5 | D7: =B7+C7 -> 2555.5 | E7: ='Property & Loan'!$B$7 -> 2619.2995 | F7: ='Property & Loan'!$B$8 -> 425 | G7: ='Property & Loan'!$B$9 -> 155 | H7: ='Property & Loan'!$B$10 -> 180 | I7: ='Property & Loan'!$B$11 -> 140 | J7: ='Property & Loan'!$B$12 -> 175 | K7: ='Property & Loan'!$B$13 -> 125 | L7: =SUM(E7:K7)-D7 -> 1263.7995 | M7: ='Property & Loan'!$B$14-L7 -> 686.20052
A8: Jul | B8: ='Unit Rent Roll'!B8*(1+'Property & Loan'!$B$16) -> 2770.7 | C8: =B8*'Property & Loan'!$B$15*-1 -> -138.535 | D8: =B8+C8 -> 2632.165 | E8: ='Property & Loan'!$B$7 -> 2619.2995 | F8: ='Property & Loan'!$B$8 -> 425 | G8: ='Property & Loan'!$B$9 -> 155 | H8: ='Property & Loan'!$B$10 -> 180 | I8: ='Property & Loan'!$B$11 -> 140 | J8: ='Property & Loan'!$B$12 -> 175 | K8: ='Property & Loan'!$B$13 -> 125 | L8: =SUM(E8:K8)-D8 -> 1187.1345 | M8: ='Property & Loan'!$B$14-L8 -> 762.86552
A9: Aug | B9: ='Unit Rent Roll'!B8*(1+'Property & Loan'!$B$16) -> 2770.7 | C9: =B9*'Property & Loan'!$B$15*-1 -> -138.535 | D9: =B9+C9 -> 2632.165 | E9: ='Property & Loan'!$B$7 -> 2619.2995 | F9: ='Property & Loan'!$B$8 -> 425 | G9: ='Property & Loan'!$B$9 -> 155 | H9: ='Property & Loan'!$B$10 -> 180 | I9: ='Property & Loan'!$B$11 -> 140 | J9: ='Property & Loan'!$B$12 -> 175 | K9: ='Property & Loan'!$B$13 -> 125 | L9: =SUM(E9:K9)-D9 -> 1187.1345 | M9: ='Property & Loan'!$B$14-L9 -> 762.86552
A10: Sep | B10: ='Unit Rent Roll'!B8*(1+'Property & Loan'!$B$16) -> 2770.7 | C10: =B10*'Property & Loan'!$B$15*-1 -> -138.535 | D10: =B10+C10 -> 2632.165 | E10: ='Property & Loan'!$B$7 -> 2619.2995 | F10: ='Property & Loan'!$B$8 -> 425 | G10: ='Property & Loan'!$B$9 -> 155 | H10: ='Property & Loan'!$B$10 -> 180 | I10: ='Property & Loan'!$B$11 -> 140 | J10: ='Property & Loan'!$B$12 -> 175 | K10: ='Property & Loan'!$B$13 -> 125 | L10: =SUM(E10:K10)-D10 -> 1187.1345 | M10: ='Property & Loan'!$B$14-L10 -> 762.86552
A11: Oct | B11: ='Unit Rent Roll'!B8*(1+'Property & Loan'!$B$16) -> 2770.7 | C11: =B11*'Property & Loan'!$B$15*-1 -> -138.535 | D11: =B11+C11 -> 2632.165 | E11: ='Property & Loan'!$B$7 -> 2619.2995 | F11: ='Property & Loan'!$B$8 -> 425 | G11: ='Property & Loan'!$B$9 -> 155 | H11: ='Property & Loan'!$B$10 -> 180 | I11: ='Property & Loan'!$B$11 -> 140 | J11: ='Property & Loan'!$B$12 -> 175 | K11: ='Property & Loan'!$B$13 -> 125 | L11: =SUM(E11:K11)-D11 -> 1187.1345 | M11: ='Property & Loan'!$B$14-L11 -> 762.86552
A12: Nov | B12: ='Unit Rent Roll'!B8*(1+'Property & Loan'!$B$16) -> 2770.7 | C12: =B12*'Property & Loan'!$B$15*-1 -> -138.535 | D12: =B12+C12 -> 2632.165 | E12: ='Property & Loan'!$B$7 -> 2619.2995 | F12: ='Property & Loan'!$B$8 -> 425 | G12: ='Property & Loan'!$B$9 -> 155 | H12: ='Property & Loan'!$B$10 -> 180 | I12: ='Property & Loan'!$B$11 -> 140 | J12: ='Property & Loan'!$B$12 -> 175 | K12: ='Property & Loan'!$B$13 -> 125 | L12: =SUM(E12:K12)-D12 -> 1187.1345 | M12: ='Property & Loan'!$B$14-L12 -> 762.86552
A13: Dec | B13: ='Unit Rent Roll'!B8*(1+'Property & Loan'!$B$16) -> 2770.7 | C13: =B13*'Property & Loan'!$B$15*-1 -> -138.535 | D13: =B13+C13 -> 2632.165 | E13: ='Property & Loan'!$B$7 -> 2619.2995 | F13: ='Property & Loan'!$B$8 -> 425 | G13: ='Property & Loan'!$B$9 -> 155 | H13: ='Property & Loan'!$B$10 -> 180 | I13: ='Property & Loan'!$B$11 -> 140 | J13: ='Property & Loan'!$B$12 -> 175 | K13: ='Property & Loan'!$B$13 -> 125 | L13: =SUM(E13:K13)-D13 -> 1187.1345 | M13: ='Property & Loan'!$B$14-L13 -> 762.86552

Sheet Scenario Grid
A1: Rent / occ grid | I1: Cost pieces
C2: 1150 | D2: 1250 | E2: 1350 | F2: 1450 | G2: 1550 | I2: Tenant Rent Offset | J2: ='Monthly Housing Cost'!D2 -> 2555.5
B3: 0.8 | C3: =('Property & Loan'!$B$7+'Property & Loan'!$B$8+'Property & Loan'!$B$9+'Property & Loan'!$B$10+'Property & Loan'!$B$11+'Property & Loan'!$B$12+'Property & Loan'!$B$13)-((C$2*2)*$B3) -> 1979.2995 | D3: =('Property & Loan'!$B$7+'Property & Loan'!$B$8+'Property & Loan'!$B$9+'Property & Loan'!$B$10+'Property & Loan'!$B$11+'Property & Loan'!$B$12+'Property & Loan'!$B$13)-((D$2*2)*$B3) -> 1819.2995 | E3: =('Property & Loan'!$B$7+'Property & Loan'!$B$8+'Property & Loan'!$B$9+'Property & Loan'!$B$10+'Property & Loan'!$B$11+'Property & Loan'!$B$12+'Property & Loan'!$B$13)-((E$2*2)*$B3) -> 1659.2995 | F3: =('Property & Loan'!$B$7+'Property & Loan'!$B$8+'Property & Loan'!$B$9+'Property & Loan'!$B$10+'Property & Loan'!$B$11+'Property & Loan'!$B$12+'Property & Loan'!$B$13)-((F$2*2)*$B3) -> 1499.2995 | G3: =('Property & Loan'!$B$7+'Property & Loan'!$B$8+'Property & Loan'!$B$9+'Property & Loan'!$B$10+'Property & Loan'!$B$11+'Property & Loan'!$B$12+'Property & Loan'!$B$13)-((G$2*2)*$B3) -> 1339.2995 | I3: Mortgage P&I | J3: ='Property & Loan'!B7*-1 -> -2619.2995
B4: 0.85 | C4: =('Property & Loan'!$B$7+'Property & Loan'!$B$8+'Property & Loan'!$B$9+'Property & Loan'!$B$10+'Property & Loan'!$B$11+'Property & Loan'!$B$12+'Property & Loan'!$B$13)-((C$2*2)*$B4) -> 1864.2995 | D4: =('Property & Loan'!$B$7+'Property & Loan'!$B$8+'Property & Loan'!$B$9+'Property & Loan'!$B$10+'Property & Loan'!$B$11+'Property & Loan'!$B$12+'Property & Loan'!$B$13)-((D$2*2)*$B4) -> 1694.2995 | E4: =('Property & Loan'!$B$7+'Property & Loan'!$B$8+'Property & Loan'!$B$9+'Property & Loan'!$B$10+'Property & Loan'!$B$11+'Property & Loan'!$B$12+'Property & Loan'!$B$13)-((E$2*2)*$B4) -> 1524.2995 | F4: =('Property & Loan'!$B$7+'Property & Loan'!$B$8+'Property & Loan'!$B$9+'Property & Loan'!$B$10+'Property & Loan'!$B$11+'Property & Loan'!$B$12+'Property & Loan'!$B$13)-((F$2*2)*$B4) -> 1354.2995 | G4: =('Property & Loan'!$B$7+'Property & Loan'!$B$8+'Property & Loan'!$B$9+'Property & Loan'!$B$10+'Property & Loan'!$B$11+'Property & Loan'!$B$12+'Property & Loan'!$B$13)-((G$2*2)*$B4) -> 1184.2995 | I4: Tax | J4: ='Property & Loan'!B8*-1 -> -425
B5: 0.9 | C5: =('Property & Loan'!$B$7+'Property & Loan'!$B$8+'Property & Loan'!$B$9+'Property & Loan'!$B$10+'Property & Loan'!$B$11+'Property & Loan'!$B$12+'Property & Loan'!$B$13)-((C$2*2)*$B5) -> 1749.2995 | D5: =('Property & Loan'!$B$7+'Property & Loan'!$B$8+'Property & Loan'!$B$9+'Property & Loan'!$B$10+'Property & Loan'!$B$11+'Property & Loan'!$B$12+'Property & Loan'!$B$13)-((D$2*2)*$B5) -> 1569.2995 | E5: =('Property & Loan'!$B$7+'Property & Loan'!$B$8+'Property & Loan'!$B$9+'Property & Loan'!$B$10+'Property & Loan'!$B$11+'Property & Loan'!$B$12+'Property & Loan'!$B$13)-((E$2*2)*$B5) -> 1389.2995 | F5: =('Property & Loan'!$B$7+'Property & Loan'!$B$8+'Property & Loan'!$B$9+'Property & Loan'!$B$10+'Property & Loan'!$B$11+'Property & Loan'!$B$12+'Property & Loan'!$B$13)-((F$2*2)*$B5) -> 1209.2995 | G5: =('Property & Loan'!$B$7+'Property & Loan'!$B$8+'Property & Loan'!$B$9+'Property & Loan'!$B$10+'Property & Loan'!$B$11+'Property & Loan'!$B$12+'Property & Loan'!$B$13)-((G$2*2)*$B5) -> 1029.2995 | I5: Insurance | J5: ='Property & Loan'!B9*-1 -> -155
B6: 0.95 | C6: =('Property & Loan'!$B$7+'Property & Loan'!$B$8+'Property & Loan'!$B$9+'Property & Loan'!$B$10+'Property & Loan'!$B$11+'Property & Loan'!$B$12+'Property & Loan'!$B$13)-((C$2*2)*$B6) -> 1634.2995 | D6: =('Property & Loan'!$B$7+'Property & Loan'!$B$8+'Property & Loan'!$B$9+'Property & Loan'!$B$10+'Property & Loan'!$B$11+'Property & Loan'!$B$12+'Property & Loan'!$B$13)-((D$2*2)*$B6) -> 1444.2995 | E6: =('Property & Loan'!$B$7+'Property & Loan'!$B$8+'Property & Loan'!$B$9+'Property & Loan'!$B$10+'Property & Loan'!$B$11+'Property & Loan'!$B$12+'Property & Loan'!$B$13)-((E$2*2)*$B6) -> 1254.2995 | F6: =('Property & Loan'!$B$7+'Property & Loan'!$B$8+'Property & Loan'!$B$9+'Property & Loan'!$B$10+'Property & Loan'!$B$11+'Property & Loan'!$B$12+'Property & Loan'!$B$13)-((F$2*2)*$B6) -> 1064.2995 | G6: =('Property & Loan'!$B$7+'Property & Loan'!$B$8+'Property & Loan'!$B$9+'Property & Loan'!$B$10+'Property & Loan'!$B$11+'Property & Loan'!$B$12+'Property & Loan'!$B$13)-((G$2*2)*$B6) -> 874.29948 | I6: PMI | J6: ='Property & Loan'!B10*-1 -> -180
B7: 1 | C7: =('Property & Loan'!$B$7+'Property & Loan'!$B$8+'Property & Loan'!$B$9+'Property & Loan'!$B$10+'Property & Loan'!$B$11+'Property & Loan'!$B$12+'Property & Loan'!$B$13)-((C$2*2)*$B7) -> 1519.2995 | D7: =('Property & Loan'!$B$7+'Property & Loan'!$B$8+'Property & Loan'!$B$9+'Property & Loan'!$B$10+'Property & Loan'!$B$11+'Property & Loan'!$B$12+'Property & Loan'!$B$13)-((D$2*2)*$B7) -> 1319.2995 | E7: =('Property & Loan'!$B$7+'Property & Loan'!$B$8+'Property & Loan'!$B$9+'Property & Loan'!$B$10+'Property & Loan'!$B$11+'Property & Loan'!$B$12+'Property & Loan'!$B$13)-((E$2*2)*$B7) -> 1119.2995 | F7: =('Property & Loan'!$B$7+'Property & Loan'!$B$8+'Property & Loan'!$B$9+'Property & Loan'!$B$10+'Property & Loan'!$B$11+'Property & Loan'!$B$12+'Property & Loan'!$B$13)-((F$2*2)*$B7) -> 919.29948 | G7: =('Property & Loan'!$B$7+'Property & Loan'!$B$8+'Property & Loan'!$B$9+'Property & Loan'!$B$10+'Property & Loan'!$B$11+'Property & Loan'!$B$12+'Property & Loan'!$B$13)-((G$2*2)*$B7) -> 719.29948 | I7: Utilities | J7: ='Property & Loan'!B11*-1 -> -140
I8: Maintenance | J8: ='Property & Loan'!B12*-1 -> -175
I9: CapEx | J9: ='Property & Loan'!B13*-1 -> -125
I13: What moves it
I14: Factor | J14: Monthly Impact
I15: Rate | J15: 210
I16: Tenant Rent | J16: 275
I17: Tax | J17: 64
I18: Maintenance | J18: 35

Sheet Snapshot
A1: Purchase price | B1: ='Property & Loan'!B2 -> 425000
A2: Loan amount | B2: ='Property & Loan'!B4 -> 410125
A3: Total monthly housing cost | B3: =SUM('Property & Loan'!B7:B13) -> 3819.2995
A4: Tenant rent offset | B4: ='Monthly Housing Cost'!D2 -> 2555.5
A5: Owner net housing cost | B5: ='Monthly Housing Cost'!L2 -> 1263.7995
A6: Savings vs current rent | B6: ='Monthly Housing Cost'!M2 -> 686.20052
A7: Year 1 average savings | B7: =AVERAGE('Monthly Housing Cost'!M2:M13) -> 724.53302
A8: Worst-case housing cost | B8: =MAX('Scenario Grid'!C3:G7) -> 1979.2995
